Workbook

Sheet Summary
A2: A2C-5 National First Sentinel Construction Compact
A4: Verdict: RETURN. One eighteen-warrant campaign integrates six sentinels, eighteen stations, 102 lots, eighteen site charters and an N-1 bid pool without a master authority. All implementation and evidence states remain empty.
A6: Decision | B6: Result | C6: Unit | D6: State | E6: Why it matters | F6: Current authority | G6: Held conversion | H6: Parent return
A7: integration architecture | B7: warranted construction campaign | C7: architecture | D7: RETURN | E7: integration by typed artifacts, not hierarchy | F7: constitutional compact | G7: compact to execution | H7: six candidate requirements
A8: serial warrants | B8: 18 | C8: count | D8: FROZEN | E8: one producer and acceptor per transition | F8: state machine | G8: warrant to evidence | H8: form-giving loads
A9: selected roots | B9: 6 | C9: count | D9: HOLD | E9: one falsifiable sentinel per system | F9: inquiry only | G9: selection to promise | H9: candidate articles
A10: station nuclei | B10: 18 | C10: count | D10: FROZEN | E10: three epistemic roles per root | F10: functional configuration | G10: station to site | H10: truth infrastructure
A11: construction lots | B11: 102 | C11: count | D11: CONSTITUTED | E11: complete but severable build objects | F11: lot grammar | G11: lot to award | H11: future source records
A12: site charters | B12: 18 | C12: count | D12: CLASS-CONSTITUTED | E12: one nucleus per causal site | F12: class grammar | G12: class to place | H12: future source records
A13: bid positions | B13: 204 | C13: count | D13: OPEN | E13: whole pool must survive one group removal | F13: position grammar | G13: position to bidder | H13: future source records
A14: construction packets | B14: 510 | C14: count | D14: OPEN | E14: as-built evidence remains separate | F14: packet grammar | G14: packet to event | H14: physical records
A15: event packages | B15: 360 | C15: count | D15: SOURCE EMPTY | E15: causal evidence remains separate | F15: event grammar | G15: event to favorable claim | H15: physical events
A16: combined ceiling | B16: 15.586913 | C16: USD B | D16: UNCHANGED | E16: public and private accounts add once | F16: ceiling | G16: ceiling to payment | H16: accepted stages
A17: through MAKE exposure | B17: 10.793456 | C17: USD B | D17: CEILING | E17: bounds pre-event loss | F17: schedule | G17: ceiling to obligation | H17: accepted stages
A18: all-six kill unreleased | B18: 3.5380369 | C18: USD B | D18: PROTECTED | E18: valid failure returns transfer money | F18: schedule | G18: failure to production | H18: root disposition
A19: current awards | B19: 0 | C19: count | D19: HELD | E19: no bidder or site exists | F19: none | G19: slate to contract | H19: external source records
... A22: rendering authority | B22: 0 | C22: count | D22: HELD | E22: form follows controlled loads | F22: none | G22: envelope to exterior | H22: requirement packages
A25: Terminal test | B25: Observed | C25: State
A26: eligible architecture | B26: =COUNTIF(Alternatives!P7:P12,"SELECT") -> 1 | C26: =IF(ABS(B26-1)<0.000001,"PASS","FAIL") -> PASS
A27: warrants | B27: =COUNTA(Warrants!A7:A24) -> 18 | C27: =IF(ABS(B27-18)<0.000001,"PASS","FAIL") -> PASS
A28: lot crosswalk | B28: =COUNTA('Object Crosswalk'!A7:A108) -> 102 | C28: =IF(ABS(B28-102)<0.000001,"PASS","FAIL") -> PASS
A29: construction packets | B29: =COUNTA('Construction Packets'!A7:A516) -> 510 | C29: =IF(ABS(B29-510)<0.000001,"PASS","FAIL") -> PASS
A30: event packages | B30: =COUNTA('Event Evidence'!A7:A366) -> 360 | C30: =IF(ABS(B30-360)<0.000001,"PASS","FAIL") -> PASS
A31: payment stages | B31: =COUNTA('Payment Ledger'!A7:A414) -> 408 | C31: =IF(ABS(B31-408)<0.000001,"PASS","FAIL") -> PASS
A32: authority ceiling | B32: =Finance!E13 -> 15.586913 | C32: =IF(ABS(B32-15.5869128193206)<0.000001,"PASS","FAIL") -> PASS
A33: audit failures | B33: =COUNTIF(Audit!E7:E93,"FAIL") -> 0 | C33: =IF(ABS(B33-0)<0.000001,"PASS","FAIL") -> PASS
A34: awards | B34: =Controls!B34 -> 0 | C34: =IF(ABS(B34-0)<0.000001,"PASS","FAIL") -> PASS
A35: capability | B35: =Controls!B38 -> 0 | C35: =IF(ABS(B35-0)<0.000001,"PASS","FAIL") -> PASS
A36: rendering | B36: =Controls!B40 -> 0 | C36: =IF(ABS(B36-0)<0.000001,"PASS","FAIL") -> PASS

Sheet Controls
A2: Authoritative A2C-5 controls
A4: Blue controls reconcile inherited objects and deliberate zero states. They are not evidence, award or permission to build.
A6: Control | B6: Value | C6: Unit | D6: Authority | E6: Meaning
A7: public construction reserve | B7: 12 | C7: USD B | D7: A2C-3 | E7: inherited or integrated boundary
A8: private candidate options | B8: 3.5869128 | C8: USD B | D8: A2C-1 | E8: inherited or integrated boundary
A9: mission systems | B9: 6 | C9: count | D9: PFP | E9: inherited or integrated boundary
A10: selected roots | B10: 6 | C10: count | D10: A2C-1 | E10: inherited or integrated boundary
A11: endpoints | B11: 12 | C11: count | D11: A2C-1 | E11: inherited or integrated boundary
A12: station nuclei | B12: 18 | C12: count | D12: A2C-2 | E12: inherited or integrated boundary
A13: initial lanes | B13: 36 | C13: count | D13: A2C-2 | E13: inherited or integrated boundary
A14: receiver-state bays | B14: 72 | C14: count | D14: A2C-2 | E14: inherited or integrated boundary
A15: method realizations | B15: 144 | C15: count | D15: A2C-2 | E15: inherited or integrated boundary
A16: regeneration functions | B16: 72 | C16: count | D16: A2C-2 | E16: inherited or integrated boundary
A17: construction lots | B17: 102 | C17: count | D17: A2C-3 | E17: inherited or integrated boundary
A18: minimum control groups | B18: 48 | C18: count | D18: A2C-3 | E18: inherited or integrated boundary
... A40: rendering authority | B40: 0 | C40: count | D40: A2C-5 | E40: source empty or held

Sheet Alternatives
A2: Construction-integration hard-gate test
A4: Only typed artifact succession can integrate the campaign without creating a super-authority or turning administrative completion into physical truth.
A6: Architecture | B6: object conservation | C6: authority separation | D6: typed succession | E6: site independence | F6: industrial separation | G6: whole-slate award | H6: bounded money | I6: valid failure | J6: local rollback | K6: cold return | L6: no capability inference | M6: parent return | N6: Passes | O6: Eligible | P6: Decision
A7: warranted construction campaign | B7: 1 | C7: 1 | D7: 1 | E7: 1 | F7: 1 | G7: 1 | H7: 1 | I7: 1 | J7: 1 | K7: 1 | L7: 1 | M7: 1 | N7: =SUM(B7:M7) -> 12 | O7: =IF(N7=12,"YES","NO") -> YES | P7: =IF(O7="YES","SELECT","REJECT") -> SELECT
A8: one master program baseline | B8: 1 | C8: 0 | D8: 0 | E8: 1 | F8: 0 | G8: 1 | H8: 1 | I8: 1 | J8: 0 | K8: 1 | L8: 0 | M8: 1 | N8: =SUM(B8:M8) -> 7 | O8: =IF(N8=12,"YES","NO") -> NO | P8: =IF(O8="YES","SELECT","REJECT") -> REJECT
A9: central integration office | B9: 1 | C9: 0 | D9: 0 | E9: 1 | F9: 0 | G9: 1 | H9: 1 | I9: 1 | J9: 0 | K9: 1 | L9: 0 | M9: 1 | N9: =SUM(B9:M9) -> 7 | O9: =IF(N9=12,"YES","NO") -> NO | P9: =IF(O9="YES","SELECT","REJECT") -> REJECT
A10: enterprise digital twin | B10: 1 | C10: 0 | D10: 0 | E10: 0 | F10: 0 | G10: 1 | H10: 1 | I10: 0 | J10: 0 | K10: 0 | L10: 0 | M10: 1 | N10: =SUM(B10:M10) -> 4 | O10: =IF(N10=12,"YES","NO") -> NO | P10: =IF(O10="YES","SELECT","REJECT") -> REJECT
A11: four adjacent constitutions | B11: 0 | C11: 1 | D11: 0 | E11: 1 | F11: 1 | G11: 1 | H11: 1 | I11: 1 | J11: 0 | K11: 1 | L11: 1 | M11: 0 | N11: =SUM(B11:M11) -> 8 | O11: =IF(N11=12,"YES","NO") -> NO | P11: =IF(O11="YES","SELECT","REJECT") -> REJECT
A12: sequential station release | B12: 1 | C12: 1 | D12: 1 | E12: 1 | F12: 1 | G12: 0 | H12: 1 | I12: 1 | J12: 1 | K12: 1 | L12: 0 | M12: 0 | N12: =SUM(B12:M12) -> 9 | O12: =IF(N12=12,"YES","NO") -> NO | P12: =IF(O12="YES","SELECT","REJECT") -> REJECT

Sheet Inherited Objects
A2: Conserved objects across the four-pass A2C branch
A4: Counts describe different ontologies. Similar numbers and shared campaigns do not authorize addition, substitution or state conversion.
A6: Layer | B6: Object | C6: Count | D6: Unit | E6: Authority | F6: State | G6: Cannot infer
A7: candidate inquiry | B7: selected sentinels | C7: 6 | D7: roots | E7: A2C-1 | F7: HELD | G7: production preference
A8: candidate inquiry | B8: balance and keystone endpoints | C8: 12 | D8: endpoints | E8: A2C-1 | F8: FROZEN | G8: physical result
A9: physical truth | B9: station nuclei | C9: 18 | D9: stations | E9: A2C-2 | F9: FROZEN | G9: site identity
A10: physical truth | B10: initial active and regeneration lanes | C10: 36 | D10: lanes | E10: A2C-2 | F10: FROZEN | G10: constructed capacity
A11: physical truth | B11: receiver-state bays | C11: 72 | D11: bays | E11: A2C-2 | F11: FROZEN | G11: accepted receiver
A12: physical truth | B12: method realizations | C12: 144 | D12: paths | E12: A2C-2 | F12: HELD | G12: 144 procurements
A13: physical truth | B13: regeneration functions | C13: 72 | D13: functions | E13: A2C-2 | F13: FROZEN | G13: event credit
A14: construction | B14: severable lots | C14: 102 | D14: lots | E14: A2C-3 | F14: CONSTITUTED | G14: award
A15: construction | B15: minimum beneficial-control groups | C15: 48 | D15: groups | E15: A2C-3 | F15: FROZEN | G15: firm identities
A16: construction | B16: construction packets | C16: 510 | D16: packets | E16: A2C-3 | F16: OPEN | G16: event evidence
A17: construction | B17: construction decisions | C17: 714 | D17: decisions | E17: A2C-3 | F17: OPEN | G17: acceptance
A18: site | B18: site charters | C18: 18 | D18: charters | E18: A2C-4 | F18: CLASS-CONSTITUTED | G18: locations
... A28: integration | B28: serial warrants | C28: 18 | D28: warrants | E28: A2C-5 | F28: FROZEN | G28: implementation

Sheet Contradictions
A2: Twelve apparent contradictions closed by the compact
A4: A closed contradiction receives one authoritative interpretation; later work may overturn it only through the supersession record.
A6: ID | B6: Apparent conflict | C6: Closure | D6: Consequence | E6: State
A7: C01 | B7: six candidates versus eighteen stations | C7: each root requires challenge, control and reconstruction | D7: three epistemic roles; not three candidates | E7: CLOSED
A8: C02 | B8: twelve endpoints versus eighteen stations | C8: each endpoint crosses roles and unlike lineages | D8: endpoint count is not station count | E8: CLOSED
A9: C03 | B9: seventy-two cards versus 144 realizations versus thirty-six method lots | C9: two physical lineages per card are bundled into one lineage lot per station | D9: paths are not contracts | E9: CLOSED
A10: C04 | B10: seventy-two regeneration functions versus eighteen lots | C10: four duties form one complete regeneration lot per station | D10: functions are not awards | E10: CLOSED
A11: C05 | B11: 102 lots versus eighteen sites | C11: only station-bearing work shares eighteen charters; candidate and substrate scopes reference them | D11: lots are not locations | E11: CLOSED
A12: C06 | B12: 204 bid positions versus forty-eight control groups | C12: positions are applications; beneficial control is a separate graph | D12: positions are not firms | E12: CLOSED
A13: C07 | B13: six three-site substrate contracts versus one nucleus/site | C13: contract packaging does not authorize co-location or common technical control | D13: economic bundle is not physical site | E13: CLOSED
A14: C08 | B14: 510 construction packets versus 360 event packages | C14: construction proves as-built state; events prove causal performance | D14: evidence types never substitute | E14: CLOSED
A15: C09 | B15: 714 construction, 216 site and 2,856 bid decisions | C15: each gate family has a distinct object and authority | D15: decisions are not pooled scores | E15: CLOSED
A16: C10 | B16: site admission before award | C16: access fitness creates no construction or commercial preference | D16: site fact is not award | E16: CLOSED
A17: C11 | B17: valid candidate failure with valuable public estate | C17: adverse evidence disposes root while truth train remains reusable | D17: failure is a program product | E17: CLOSED
A18: C12 | B18: USD 12.0B public plus USD 3.59B private | C18: two exclusive accounts sum once to the USD 15.6B ceiling | D18: nested values are not re-added | E18: CLOSED

Sheet Object Crosswalk
A2: One hundred two lot-to-campaign crosswalk records
A4: Every lot maps to one role in the campaign while shared site, packet, bid and payment references retain their own ledgers.
A6: Lot | B6: Class | C6: Funding | D6: System | E6: Root | F6: Role | G6: Station scope | H6: Site scope | I6: Ceiling USD B | J6: Construction packets | K6: Construction gates | L6: Bid positions | M6: Payment stages | N6: Site identity | O6: Firm identity | P6: Award | Q6: Obligation USD B | R6: Payment USD B | S6: Capability | T6: State
A7: SUB-01 | B7: Civil substrate | C7: Public | D7: MULTI | E7: — | F7: ROTATED | G7: 3-SITE PACKAGE | H7: 3 CHARTERS | I7: 0.12 | J7: 5 | K7: 7 | L7: 2 | M7: 4 | N7: SOURCE EMPTY | O7: SOURCE EMPTY | P7: =Controls!B34 -> 0 | Q7: =Controls!B35 -> 0 | R7: =Controls!B36 -> 0 | S7: =Controls!B38 -> 0 | T7: =IF(P7=1,"AWARDED","CONSTITUTED") -> CONSTITUTED
A8: SUB-02 | B8: Civil substrate | C8: Public | D8: MULTI | E8: — | F8: ROTATED | G8: 3-SITE PACKAGE | H8: 3 CHARTERS | I8: 0.12 | J8: 5 | K8: 7 | L8: 2 | M8: 4 | N8: SOURCE EMPTY | O8: SOURCE EMPTY | P8: =Controls!B34 -> 0 | Q8: =Controls!B35 -> 0 | R8: =Controls!B36 -> 0 | S8: =Controls!B38 -> 0 | T8: =IF(P8=1,"AWARDED","CONSTITUTED") -> CONSTITUTED
A9: SUB-03 | B9: Civil substrate | C9: Public | D9: MULTI | E9: — | F9: ROTATED | G9: 3-SITE PACKAGE | H9: 3 CHARTERS | I9: 0.12 | J9: 5 | K9: 7 | L9: 2 | M9: 4 | N9: SOURCE EMPTY | O9: SOURCE EMPTY | P9: =Controls!B34 -> 0 | Q9: =Controls!B35 -> 0 | R9: =Controls!B36 -> 0 | S9: =Controls!B38 -> 0 | T9: =IF(P9=1,"AWARDED","CONSTITUTED") -> CONSTITUTED
A10: SUB-04 | B10: Civil substrate | C10: Public | D10: MULTI | E10: — | F10: ROTATED | G10: 3-SITE PACKAGE | H10: 3 CHARTERS | I10: 0.12 | J10: 5 | K10: 7 | L10: 2 | M10: 4 | N10: SOURCE EMPTY | O10: SOURCE EMPTY | P10: =Controls!B34 -> 0 | Q10: =Controls!B35 -> 0 | R10: =Controls!B36 -> 0 | S10: =Controls!B38 -> 0 | T10: =IF(P10=1,"AWARDED","CONSTITUTED") -> CONSTITUTED
A11: SUB-05 | B11: Civil substrate | C11: Public | D11: MULTI | E11: — | F11: ROTATED | G11: 3-SITE PACKAGE | H11: 3 CHARTERS | I11: 0.12 | J11: 5 | K11: 7 | L11: 2 | M11: 4 | N11: SOURCE EMPTY | O11: SOURCE EMPTY | P11: =Controls!B34 -> 0 | Q11: =Controls!B35 -> 0 | R11: =Controls!B36 -> 0 | S11: =Controls!B38 -> 0 | T11: =IF(P11=1,"AWARDED","CONSTITUTED") -> CONSTITUTED
A12: SUB-06 | B12: Civil substrate | C12: Public | D12: MULTI | E12: — | F12: ROTATED | G12: 3-SITE PACKAGE | H12: 3 CHARTERS | I12: 0.12 | J12: 5 | K12: 7 | L12: 2 | M12: 4 | N12: SOURCE EMPTY | O12: SOURCE EMPTY | P12: =Controls!B34 -> 0 | Q12: =Controls!B35 -> 0 | R12: =Controls!B36 -> 0 | S12: =Controls!B38 -> 0 | T12: =IF(P12=1,"AWARDED","CONSTITUTED") -> CONSTITUTED
A13: RIG-ET-CHA | B13: Root-native rig | C13: Public | D13: MS-ET | E13: ET-A | F13: CHALLENGE | G13: ST-ET-CHA | H13: CHR-ET-CHA | I13: 0.31666667 | J13: 5 | K13: 7 | L13: 2 | M13: 4 | N13: SOURCE EMPTY | O13: SOURCE EMPTY | P13: =Controls!B34 -> 0 | Q13: =Controls!B35 -> 0 | R13: =Controls!B36 -> 0 | S13: =Controls!B38 -> 0 | T13: =IF(P13=1,"AWARDED","CONSTITUTED") -> CONSTITUTED
A14: MTH-ET-CHA-L1 | B14: Method lineage | C14: Public | D14: MS-ET | E14: ET-A | F14: CHALLENGE | G14: ST-ET-CHA | H14: CHR-ET-CHA | I14: 0.09 | J14: 5 | K14: 7 | L14: 2 | M14: 4 | N14: SOURCE EMPTY | O14: SOURCE EMPTY | P14: =Controls!B34 -> 0 | Q14: =Controls!B35 -> 0 | R14: =Controls!B36 -> 0 | S14: =Controls!B38 -> 0 | T14: =IF(P14=1,"AWARDED","CONSTITUTED") -> CONSTITUTED
A15: MTH-ET-CHA-L2 | B15: Method lineage | C15: Public | D15: MS-ET | E15: ET-A | F15: CHALLENGE | G15: ST-ET-CHA | H15: CHR-ET-CHA | I15: 0.09 | J15: 5 | K15: 7 | L15: 2 | M15: 4 | N15: SOURCE EMPTY | O15: SOURCE EMPTY | P15: =Controls!B34 -> 0 | Q15: =Controls!B35 -> 0 | R15: =Controls!B36 -> 0 | S15: =Controls!B38 -> 0 | T15: =IF(P15=1,"AWARDED","CONSTITUTED") -> CONSTITUTED
A16: REG-ET-CHA | B16: Regeneration tool | C16: Public | D16: MS-ET | E16: ET-A | F16: CHALLENGE | G16: ST-ET-CHA | H16: CHR-ET-CHA | I16: 0.066666667 | J16: 5 | K16: 7 | L16: 2 | M16: 4 | N16: SOURCE EMPTY | O16: SOURCE EMPTY | P16: =Controls!B34 -> 0 | Q16: =Controls!B35 -> 0 | R16: =Controls!B36 -> 0 | S16: =Controls!B38 -> 0 | T16: =IF(P16=1,"AWARDED","CONSTITUTED") -> CONSTITUTED
A17: INT-ET-CHA | B17: Station integration | C17: Public | D17: MS-ET | E17: ET-A | F17: CHALLENGE | G17: ST-ET-CHA | H17: CHR-ET-CHA | I17: 0.063333333 | J17: 5 | K17: 7 | L17: 2 | M17: 4 | N17: SOURCE EMPTY | O17: SOURCE EMPTY | P17: =Controls!B34 -> 0 | Q17: =Controls!B35 -> 0 | R17: =Controls!B36 -> 0 | S17: =Controls!B38 -> 0 | T17: =IF(P17=1,"AWARDED","CONSTITUTED") -> CONSTITUTED
A18: RIG-ET-CON | B18: Root-native rig | C18: Public | D18: MS-ET | E18: ET-A | F18: CONTROL | G18: ST-ET-CON | H18: CHR-ET-CON | I18: 0.31666667 | J18: 5 | K18: 7 | L18: 2 | M18: 4 | N18: SOURCE EMPTY | O18: SOURCE EMPTY | P18: =Controls!B34 -> 0 | Q18: =Controls!B35 -> 0 | R18: =Controls!B36 -> 0 | S18: =Controls!B38 -> 0 | T18: =IF(P18=1,"AWARDED","CONSTITUTED") -> CONSTITUTED
A19: MTH-ET-CON-L1 | B19: Method lineage | C19: Public | D19: MS-ET | E19: ET-A | F19: CONTROL | G19: ST-ET-CON | H19: CHR-ET-CON | I19: 0.09 | J19: 5 | K19: 7 | L19: 2 | M19: 4 | N19: SOURCE EMPTY | O19: SOURCE EMPTY | P19: =Controls!B34 -> 0 | Q19: =Controls!B35 -> 0 | R19: =Controls!B36 -> 0 | S19: =Controls!B38 -> 0 | T19: =IF(P19=1,"AWARDED","CONSTITUTED") -> CONSTITUTED
A20: MTH-ET-CON-L2 | B20: Method lineage | C20: Public | D20: MS-ET | E20: ET-A | F20: CONTROL | G20: ST-ET-CON | H20: CHR-ET-CON | I20: 0.09 | J20: 5 | K20: 7 | L20: 2 | M20: 4 | N20: SOURCE EMPTY | O20: SOURCE EMPTY | P20: =Controls!B34 -> 0 | Q20: =Controls!B35 -> 0 | R20: =Controls!B36 -> 0 | S20: =Controls!B38 -> 0 | T20: =IF(P20=1,"AWARDED","CONSTITUTED") -> CONSTITUTED
A21: REG-ET-CON | B21: Regeneration tool | C21: Public | D21: MS-ET | E21: ET-A | F21: CONTROL | G21: ST-ET-CON | H21: CHR-ET-CON | I21: 0.066666667 | J21: 5 | K21: 7 | L21: 2 | M21: 4 | N21: SOURCE EMPTY | O21: SOURCE EMPTY | P21: =Controls!B34 -> 0 | Q21: =Controls!B35 -> 0 | R21: =Controls!B36 -> 0 | S21: =Controls!B38 -> 0 | T21: =IF(P21=1,"AWARDED","CONSTITUTED") -> CONSTITUTED
A22: INT-ET-CON | B22: Station integration | C22: Public | D22: MS-ET | E22: ET-A | F22: CONTROL | G22: ST-ET-CON | H22: CHR-ET-CON | I22: 0.063333333 | J22: 5 | K22: 7 | L22: 2 | M22: 4 | N22: SOURCE EMPTY | O22: SOURCE EMPTY | P22: =Controls!B34 -> 0 | Q22: =Controls!B35 -> 0 | R22: =Controls!B36 -> 0 | S22: =Controls!B38 -> 0 | T22: =IF(P22=1,"AWARDED","CONSTITUTED") -> CONSTITUTED
A23: RIG-ET-REC | B23: Root-native rig | C23: Public | D23: MS-ET | E23: ET-A | F23: RECONSTRUCTION | G23: ST-ET-REC | H23: CHR-ET-REC | I23: 0.31666667 | J23: 5 | K23: 7 | L23: 2 | M23: 4 | N23: SOURCE EMPTY | O23: SOURCE EMPTY | P23: =Controls!B34 -> 0 | Q23: =Controls!B35 -> 0 | R23: =Controls!B36 -> 0 | S23: =Controls!B38 -> 0 | T23: =IF(P23=1,"AWARDED","CONSTITUTED") -> CONSTITUTED
A24: MTH-ET-REC-L1 | B24: Method lineage | C24: Public | D24: MS-ET | E24: ET-A | F24: RECONSTRUCTION | G24: ST-ET-REC | H24: CHR-ET-REC | I24: 0.09 | J24: 5 | K24: 7 | L24: 2 | M24: 4 | N24: SOURCE EMPTY | O24: SOURCE EMPTY | P24: =Controls!B34 -> 0 | Q24: =Controls!B35 -> 0 | R24: =Controls!B36 -> 0 | S24: =Controls!B38 -> 0 | T24: =IF(P24=1,"AWARDED","CONSTITUTED") -> CONSTITUTED
A25: MTH-ET-REC-L2 | B25: Method lineage | C25: Public | D25: MS-ET | E25: ET-A | F25: RECONSTRUCTION | G25: ST-ET-REC | H25: CHR-ET-REC | I25: 0.09 | J25: 5 | K25: 7 | L25: 2 | M25: 4 | N25: SOURCE EMPTY | O25: SOURCE EMPTY | P25: =Controls!B34 -> 0 | Q25: =Controls!B35 -> 0 | R25: =Controls!B36 -> 0 | S25: =Controls!B38 -> 0 | T25: =IF(P25=1,"AWARDED","CONSTITUTED") -> CONSTITUTED
A26: REG-ET-REC | B26: Regeneration tool | C26: Public | D26: MS-ET | E26: ET-A | F26: RECONSTRUCTION | G26: ST-ET-REC | H26: CHR-ET-REC | I26: 0.066666667 | J26: 5 | K26: 7 | L26: 2 | M26: 4 | N26: SOURCE EMPTY | O26: SOURCE EMPTY | P26: =Controls!B34 -> 0 | Q26: =Controls!B35 -> 0 | R26: =Controls!B36 -> 0 | S26: =Controls!B38 -> 0 | T26: =IF(P26=1,"AWARDED","CONSTITUTED") -> CONSTITUTED
A27: INT-ET-REC | B27: Station integration | C27: Public | D27: MS-ET | E27: ET-A | F27: RECONSTRUCTION | G27: ST-ET-REC | H27: CHR-ET-REC | I27: 0.063333333 | J27: 5 | K27: 7 | L27: 2 | M27: 4 | N27: SOURCE EMPTY | O27: SOURCE EMPTY | P27: =Controls!B34 -> 0 | Q27: =Controls!B35 -> 0 | R27: =Controls!B36 -> 0 | S27: =Controls!B38 -> 0 | T27: =IF(P27=1,"AWARDED","CONSTITUTED") -> CONSTITUTED
A28: RIG-CT-CHA | B28: Root-native rig | C28: Public | D28: MS-CT | E28: CT-C | F28: CHALLENGE | G28: ST-CT-CHA | H28: CHR-CT-CHA | I28: 0.31666667 | J28: 5 | K28: 7 | L28: 2 | M28: 4 | N28: SOURCE EMPTY | O28: SOURCE EMPTY | P28: =Controls!B34 -> 0 | Q28: =Controls!B35 -> 0 | R28: =Controls!B36 -> 0 | S28: =Controls!B38 -> 0 | T28: =IF(P28=1,"AWARDED","CONSTITUTED") -> CONSTITUTED
A29: MTH-CT-CHA-L1 | B29: Method lineage | C29: Public | D29: MS-CT | E29: CT-C | F29: CHALLENGE | G29: ST-CT-CHA | H29: CHR-CT-CHA | I29: 0.09 | J29: 5 | K29: 7 | L29: 2 | M29: 4 | N29: SOURCE EMPTY | O29: SOURCE EMPTY | P29: =Controls!B34 -> 0 | Q29: =Controls!B35 -> 0 | R29: =Controls!B36 -> 0 | S29: =Controls!B38 -> 0 | T29: =IF(P29=1,"AWARDED","CONSTITUTED") -> CONSTITUTED
A30: MTH-CT-CHA-L2 | B30: Method lineage | C30: Public | D30: MS-CT | E30: CT-C | F30: CHALLENGE | G30: ST-CT-CHA | H30: CHR-CT-CHA | I30: 0.09 | J30: 5 | K30: 7 | L30: 2 | M30: 4 | N30: SOURCE EMPTY | O30: SOURCE EMPTY | P30: =Controls!B34 -> 0 | Q30: =Controls!B35 -> 0 | R30: =Controls!B36 -> 0 | S30: =Controls!B38 -> 0 | T30: =IF(P30=1,"AWARDED","CONSTITUTED") -> CONSTITUTED
A31: REG-CT-CHA | B31: Regeneration tool | C31: Public | D31: MS-CT | E31: CT-C | F31: CHALLENGE | G31: ST-CT-CHA | H31: CHR-CT-CHA | I31: 0.066666667 | J31: 5 | K31: 7 | L31: 2 | M31: 4 | N31: SOURCE EMPTY | O31: SOURCE EMPTY | P31: =Controls!B34 -> 0 | Q31: =Controls!B35 -> 0 | R31: =Controls!B36 -> 0 | S31: =Controls!B38 -> 0 | T31: =IF(P31=1,"AWARDED","CONSTITUTED") -> CONSTITUTED
A32: INT-CT-CHA | B32: Station integration | C32: Public | D32: MS-CT | E32: CT-C | F32: CHALLENGE | G32: ST-CT-CHA | H32: CHR-CT-CHA | I32: 0.063333333 | J32: 5 | K32: 7 | L32: 2 | M32: 4 | N32: SOURCE EMPTY | O32: SOURCE EMPTY | P32: =Controls!B34 -> 0 | Q32: =Controls!B35 -> 0 | R32: =Controls!B36 -> 0 | S32: =Controls!B38 -> 0 | T32: =IF(P32=1,"AWARDED","CONSTITUTED") -> CONSTITUTED
A33: RIG-CT-CON | B33: Root-native rig | C33: Public | D33: MS-CT | E33: CT-C | F33: CONTROL | G33: ST-CT-CON | H33: CHR-CT-CON | I33: 0.31666667 | J33: 5 | K33: 7 | L33: 2 | M33: 4 | N33: SOURCE EMPTY | O33: SOURCE EMPTY | P33: =Controls!B34 -> 0 | Q33: =Controls!B35 -> 0 | R33: =Controls!B36 -> 0 | S33: =Controls!B38 -> 0 | T33: =IF(P33=1,"AWARDED","CONSTITUTED") -> CONSTITUTED
A34: MTH-CT-CON-L1 | B34: Method lineage | C34: Public | D34: MS-CT | E34: CT-C | F34: CONTROL | G34: ST-CT-CON | H34: CHR-CT-CON | I34: 0.09 | J34: 5 | K34: 7 | L34: 2 | M34: 4 | N34: SOURCE EMPTY | O34: SOURCE EMPTY | P34: =Controls!B34 -> 0 | Q34: =Controls!B35 -> 0 | R34: =Controls!B36 -> 0 | S34: =Controls!B38 -> 0 | T34: =IF(P34=1,"AWARDED","CONSTITUTED") -> CONSTITUTED
A35: MTH-CT-CON-L2 | B35: Method lineage | C35: Public | D35: MS-CT | E35: CT-C | F35: CONTROL | G35: ST-CT-CON | H35: CHR-CT-CON | I35: 0.09 | J35: 5 | K35: 7 | L35: 2 | M35: 4 | N35: SOURCE EMPTY | O35: SOURCE EMPTY | P35: =Controls!B34 -> 0 | Q35: =Controls!B35 -> 0 | R35: =Controls!B36 -> 0 | S35: =Controls!B38 -> 0 | T35: =IF(P35=1,"AWARDED","CONSTITUTED") -> CONSTITUTED
A36: REG-CT-CON | B36: Regeneration tool | C36: Public | D36: MS-CT | E36: CT-C | F36: CONTROL | G36: ST-CT-CON | H36: CHR-CT-CON | I36: 0.066666667 | J36: 5 | K36: 7 | L36: 2 | M36: 4 | N36: SOURCE EMPTY | O36: SOURCE EMPTY | P36: =Controls!B34 -> 0 | Q36: =Controls!B35 -> 0 | R36: =Controls!B36 -> 0 | S36: =Controls!B38 -> 0 | T36: =IF(P36=1,"AWARDED","CONSTITUTED") -> CONSTITUTED
A37: INT-CT-CON | B37: Station integration | C37: Public | D37: MS-CT | E37: CT-C | F37: CONTROL | G37: ST-CT-CON | H37: CHR-CT-CON | I37: 0.063333333 | J37: 5 | K37: 7 | L37: 2 | M37: 4 | N37: SOURCE EMPTY | O37: SOURCE EMPTY | P37: =Controls!B34 -> 0 | Q37: =Controls!B35 -> 0 | R37: =Controls!B36 -> 0 | S37: =Controls!B38 -> 0 | T37: =IF(P37=1,"AWARDED","CONSTITUTED") -> CONSTITUTED
A38: RIG-CT-REC | B38: Root-native rig | C38: Public | D38: MS-CT | E38: CT-C | F38: RECONSTRUCTION | G38: ST-CT-REC | H38: CHR-CT-REC | I38: 0.31666667 | J38: 5 | K38: 7 | L38: 2 | M38: 4 | N38: SOURCE EMPTY | O38: SOURCE EMPTY | P38: =Controls!B34 -> 0 | Q38: =Controls!B35 -> 0 | R38: =Controls!B36 -> 0 | S38: =Controls!B38 -> 0 | T38: =IF(P38=1,"AWARDED","CONSTITUTED") -> CONSTITUTED
A39: MTH-CT-REC-L1 | B39: Method lineage | C39: Public | D39: MS-CT | E39: CT-C | F39: RECONSTRUCTION | G39: ST-CT-REC | H39: CHR-CT-REC | I39: 0.09 | J39: 5 | K39: 7 | L39: 2 | M39: 4 | N39: SOURCE EMPTY | O39: SOURCE EMPTY | P39: =Controls!B34 -> 0 | Q39: =Controls!B35 -> 0 | R39: =Controls!B36 -> 0 | S39: =Controls!B38 -> 0 | T39: =IF(P39=1,"AWARDED","CONSTITUTED") -> CONSTITUTED
A40: MTH-CT-REC-L2 | B40: Method lineage | C40: Public | D40: MS-CT | E40: CT-C | F40: RECONSTRUCTION | G40: ST-CT-REC | H40: CHR-CT-REC | I40: 0.09 | J40: 5 | K40: 7 | L40: 2 | M40: 4 | N40: SOURCE EMPTY | O40: SOURCE EMPTY | P40: =Controls!B34 -> 0 | Q40: =Controls!B35 -> 0 | R40: =Controls!B36 -> 0 | S40: =Controls!B38 -> 0 | T40: =IF(P40=1,"AWARDED","CONSTITUTED") -> CONSTITUTED
A41: REG-CT-REC | B41: Regeneration tool | C41: Public | D41: MS-CT | E41: CT-C | F41: RECONSTRUCTION | G41: ST-CT-REC | H41: CHR-CT-REC | I41: 0.066666667 | J41: 5 | K41: 7 | L41: 2 | M41: 4 | N41: SOURCE EMPTY | O41: SOURCE EMPTY | P41: =Controls!B34 -> 0 | Q41: =Controls!B35 -> 0 | R41: =Controls!B36 -> 0 | S41: =Controls!B38 -> 0 | T41: =IF(P41=1,"AWARDED","CONSTITUTED") -> CONSTITUTED
A42: INT-CT-REC | B42: Station integration | C42: Public | D42: MS-CT | E42: CT-C | F42: RECONSTRUCTION | G42: ST-CT-REC | H42: CHR-CT-REC | I42: 0.063333333 | J42: 5 | K42: 7 | L42: 2 | M42: 4 | N42: SOURCE EMPTY | O42: SOURCE EMPTY | P42: =Controls!B34 -> 0 | Q42: =Controls!B35 -> 0 | R42: =Controls!B36 -> 0 | S42: =Controls!B38 -> 0 | T42: =IF(P42=1,"AWARDED","CONSTITUTED") -> CONSTITUTED
A43: RIG-HC-CHA | B43: Root-native rig | C43: Public | D43: MS-HC | E43: HC-A | F43: CHALLENGE | G43: ST-HC-CHA | H43: CHR-HC-CHA | I43: 0.31666667 | J43: 5 | K43: 7 | L43: 2 | M43: 4 | N43: SOURCE EMPTY | O43: SOURCE EMPTY | P43: =Controls!B34 -> 0 | Q43: =Controls!B35 -> 0 | R43: =Controls!B36 -> 0 | S43: =Controls!B38 -> 0 | T43: =IF(P43=1,"AWARDED","CONSTITUTED") -> CONSTITUTED
A44: MTH-HC-CHA-L1 | B44: Method lineage | C44: Public | D44: MS-HC | E44: HC-A | F44: CHALLENGE | G44: ST-HC-CHA | H44: CHR-HC-CHA | I44: 0.09 | J44: 5 | K44: 7 | L44: 2 | M44: 4 | N44: SOURCE EMPTY | O44: SOURCE EMPTY | P44: =Controls!B34 -> 0 | Q44: =Controls!B35 -> 0 | R44: =Controls!B36 -> 0 | S44: =Controls!B38 -> 0 | T44: =IF(P44=1,"AWARDED","CONSTITUTED") -> CONSTITUTED
A45: MTH-HC-CHA-L2 | B45: Method lineage | C45: Public | D45: MS-HC | E45: HC-A | F45: CHALLENGE | G45: ST-HC-CHA | H45: CHR-HC-CHA | I45: 0.09 | J45: 5 | K45: 7 | L45: 2 | M45: 4 | N45: SOURCE EMPTY | O45: SOURCE EMPTY | P45: =Controls!B34 -> 0 | Q45: =Controls!B35 -> 0 | R45: =Controls!B36 -> 0 | S45: =Controls!B38 -> 0 | T45: =IF(P45=1,"AWARDED","CONSTITUTED") -> CONSTITUTED
A46: REG-HC-CHA | B46: Regeneration tool | C46: Public | D46: MS-HC | E46: HC-A | F46: CHALLENGE | G46: ST-HC-CHA | H46: CHR-HC-CHA | I46: 0.066666667 | J46: 5 | K46: 7 | L46: 2 | M46: 4 | N46: SOURCE EMPTY | O46: SOURCE EMPTY | P46: =Controls!B34 -> 0 | Q46: =Controls!B35 -> 0 | R46: =Controls!B36 -> 0 | S46: =Controls!B38 -> 0 | T46: =IF(P46=1,"AWARDED","CONSTITUTED") -> CONSTITUTED
A47: INT-HC-CHA | B47: Station integration | C47: Public | D47: MS-HC | E47: HC-A | F47: CHALLENGE | G47: ST-HC-CHA | H47: CHR-HC-CHA | I47: 0.063333333 | J47: 5 | K47: 7 | L47: 2 | M47: 4 | N47: SOURCE EMPTY | O47: SOURCE EMPTY | P47: =Controls!B34 -> 0 | Q47: =Controls!B35 -> 0 | R47: =Controls!B36 -> 0 | S47: =Controls!B38 -> 0 | T47: =IF(P47=1,"AWARDED","CONSTITUTED") -> CONSTITUTED
A48: RIG-HC-CON | B48: Root-native rig | C48: Public | D48: MS-HC | E48: HC-A | F48: CONTROL | G48: ST-HC-CON | H48: CHR-HC-CON | I48: 0.31666667 | J48: 5 | K48: 7 | L48: 2 | M48: 4 | N48: SOURCE EMPTY | O48: SOURCE EMPTY | P48: =Controls!B34 -> 0 | Q48: =Controls!B35 -> 0 | R48: =Controls!B36 -> 0 | S48: =Controls!B38 -> 0 | T48: =IF(P48=1,"AWARDED","CONSTITUTED") -> CONSTITUTED
A49: MTH-HC-CON-L1 | B49: Method lineage | C49: Public | D49: MS-HC | E49: HC-A | F49: CONTROL | G49: ST-HC-CON | H49: CHR-HC-CON | I49: 0.09 | J49: 5 | K49: 7 | L49: 2 | M49: 4 | N49: SOURCE EMPTY | O49: SOURCE EMPTY | P49: =Controls!B34 -> 0 | Q49: =Controls!B35 -> 0 | R49: =Controls!B36 -> 0 | S49: =Controls!B38 -> 0 | T49: =IF(P49=1,"AWARDED","CONSTITUTED") -> CONSTITUTED
A50: MTH-HC-CON-L2 | B50: Method lineage | C50: Public | D50: MS-HC | E50: HC-A | F50: CONTROL | G50: ST-HC-CON | H50: CHR-HC-CON | I50: 0.09 | J50: 5 | K50: 7 | L50: 2 | M50: 4 | N50: SOURCE EMPTY | O50: SOURCE EMPTY | P50: =Controls!B34 -> 0 | Q50: =Controls!B35 -> 0 | R50: =Controls!B36 -> 0 | S50: =Controls!B38 -> 0 | T50: =IF(P50=1,"AWARDED","CONSTITUTED") -> CONSTITUTED
A51: REG-HC-CON | B51: Regeneration tool | C51: Public | D51: MS-HC | E51: HC-A | F51: CONTROL | G51: ST-HC-CON | H51: CHR-HC-CON | I51: 0.066666667 | J51: 5 | K51: 7 | L51: 2 | M51: 4 | N51: SOURCE EMPTY | O51: SOURCE EMPTY | P51: =Controls!B34 -> 0 | Q51: =Controls!B35 -> 0 | R51: =Controls!B36 -> 0 | S51: =Controls!B38 -> 0 | T51: =IF(P51=1,"AWARDED","CONSTITUTED") -> CONSTITUTED
A52: INT-HC-CON | B52: Station integration | C52: Public | D52: MS-HC | E52: HC-A | F52: CONTROL | G52: ST-HC-CON | H52: CHR-HC-CON | I52: 0.063333333 | J52: 5 | K52: 7 | L52: 2 | M52: 4 | N52: SOURCE EMPTY | O52: SOURCE EMPTY | P52: =Controls!B34 -> 0 | Q52: =Controls!B35 -> 0 | R52: =Controls!B36 -> 0 | S52: =Controls!B38 -> 0 | T52: =IF(P52=1,"AWARDED","CONSTITUTED") -> CONSTITUTED
A53: RIG-HC-REC | B53: Root-native rig | C53: Public | D53: MS-HC | E53: HC-A | F53: RECONSTRUCTION | G53: ST-HC-REC | H53: CHR-HC-REC | I53: 0.31666667 | J53: 5 | K53: 7 | L53: 2 | M53: 4 | N53: SOURCE EMPTY | O53: SOURCE EMPTY | P53: =Controls!B34 -> 0 | Q53: =Controls!B35 -> 0 | R53: =Controls!B36 -> 0 | S53: =Controls!B38 -> 0 | T53: =IF(P53=1,"AWARDED","CONSTITUTED") -> CONSTITUTED
A54: MTH-HC-REC-L1 | B54: Method lineage | C54: Public | D54: MS-HC | E54: HC-A | F54: RECONSTRUCTION | G54: ST-HC-REC | H54: CHR-HC-REC | I54: 0.09 | J54: 5 | K54: 7 | L54: 2 | M54: 4 | N54: SOURCE EMPTY | O54: SOURCE EMPTY | P54: =Controls!B34 -> 0 | Q54: =Controls!B35 -> 0 | R54: =Controls!B36 -> 0 | S54: =Controls!B38 -> 0 | T54: =IF(P54=1,"AWARDED","CONSTITUTED") -> CONSTITUTED
A55: MTH-HC-REC-L2 | B55: Method lineage | C55: Public | D55: MS-HC | E55: HC-A | F55: RECONSTRUCTION | G55: ST-HC-REC | H55: CHR-HC-REC | I55: 0.09 | J55: 5 | K55: 7 | L55: 2 | M55: 4 | N55: SOURCE EMPTY | O55: SOURCE EMPTY | P55: =Controls!B34 -> 0 | Q55: =Controls!B35 -> 0 | R55: =Controls!B36 -> 0 | S55: =Controls!B38 -> 0 | T55: =IF(P55=1,"AWARDED","CONSTITUTED") -> CONSTITUTED
A56: REG-HC-REC | B56: Regeneration tool | C56: Public | D56: MS-HC | E56: HC-A | F56: RECONSTRUCTION | G56: ST-HC-REC | H56: CHR-HC-REC | I56: 0.066666667 | J56: 5 | K56: 7 | L56: 2 | M56: 4 | N56: SOURCE EMPTY | O56: SOURCE EMPTY | P56: =Controls!B34 -> 0 | Q56: =Controls!B35 -> 0 | R56: =Controls!B36 -> 0 | S56: =Controls!B38 -> 0 | T56: =IF(P56=1,"AWARDED","CONSTITUTED") -> CONSTITUTED
A57: INT-HC-REC | B57: Station integration | C57: Public | D57: MS-HC | E57: HC-A | F57: RECONSTRUCTION | G57: ST-HC-REC | H57: CHR-HC-REC | I57: 0.063333333 | J57: 5 | K57: 7 | L57: 2 | M57: 4 | N57: SOURCE EMPTY | O57: SOURCE EMPTY | P57: =Controls!B34 -> 0 | Q57: =Controls!B35 -> 0 | R57: =Controls!B36 -> 0 | S57: =Controls!B38 -> 0 | T57: =IF(P57=1,"AWARDED","CONSTITUTED") -> CONSTITUTED
A58: RIG-LF-CHA | B58: Root-native rig | C58: Public | D58: MS-LF | E58: LF-B | F58: CHALLENGE | G58: ST-LF-CHA | H58: CHR-LF-CHA | I58: 0.31666667 | J58: 5 | K58: 7 | L58: 2 | M58: 4 | N58: SOURCE EMPTY | O58: SOURCE EMPTY | P58: =Controls!B34 -> 0 | Q58: =Controls!B35 -> 0 | R58: =Controls!B36 -> 0 | S58: =Controls!B38 -> 0 | T58: =IF(P58=1,"AWARDED","CONSTITUTED") -> CONSTITUTED
A59: MTH-LF-CHA-L1 | B59: Method lineage | C59: Public | D59: MS-LF | E59: LF-B | F59: CHALLENGE | G59: ST-LF-CHA | H59: CHR-LF-CHA | I59: 0.09 | J59: 5 | K59: 7 | L59: 2 | M59: 4 | N59: SOURCE EMPTY | O59: SOURCE EMPTY | P59: =Controls!B34 -> 0 | Q59: =Controls!B35 -> 0 | R59: =Controls!B36 -> 0 | S59: =Controls!B38 -> 0 | T59: =IF(P59=1,"AWARDED","CONSTITUTED") -> CONSTITUTED
A60: MTH-LF-CHA-L2 | B60: Method lineage | C60: Public | D60: MS-LF | E60: LF-B | F60: CHALLENGE | G60: ST-LF-CHA | H60: CHR-LF-CHA | I60: 0.09 | J60: 5 | K60: 7 | L60: 2 | M60: 4 | N60: SOURCE EMPTY | O60: SOURCE EMPTY | P60: =Controls!B34 -> 0 | Q60: =Controls!B35 -> 0 | R60: =Controls!B36 -> 0 | S60: =Controls!B38 -> 0 | T60: =IF(P60=1,"AWARDED","CONSTITUTED") -> CONSTITUTED
A61: REG-LF-CHA | B61: Regeneration tool | C61: Public | D61: MS-LF | E61: LF-B | F61: CHALLENGE | G61: ST-LF-CHA | H61: CHR-LF-CHA | I61: 0.066666667 | J61: 5 | K61: 7 | L61: 2 | M61: 4 | N61: SOURCE EMPTY | O61: SOURCE EMPTY | P61: =Controls!B34 -> 0 | Q61: =Controls!B35 -> 0 | R61: =Controls!B36 -> 0 | S61: =Controls!B38 -> 0 | T61: =IF(P61=1,"AWARDED","CONSTITUTED") -> CONSTITUTED
A62: INT-LF-CHA | B62: Station integration | C62: Public | D62: MS-LF | E62: LF-B | F62: CHALLENGE | G62: ST-LF-CHA | H62: CHR-LF-CHA | I62: 0.063333333 | J62: 5 | K62: 7 | L62: 2 | M62: 4 | N62: SOURCE EMPTY | O62: SOURCE EMPTY | P62: =Controls!B34 -> 0 | Q62: =Controls!B35 -> 0 | R62: =Controls!B36 -> 0 | S62: =Controls!B38 -> 0 | T62: =IF(P62=1,"AWARDED","CONSTITUTED") -> CONSTITUTED
A63: RIG-LF-CON | B63: Root-native rig | C63: Public | D63: MS-LF | E63: LF-B | F63: CONTROL | G63: ST-LF-CON | H63: CHR-LF-CON | I63: 0.31666667 | J63: 5 | K63: 7 | L63: 2 | M63: 4 | N63: SOURCE EMPTY | O63: SOURCE EMPTY | P63: =Controls!B34 -> 0 | Q63: =Controls!B35 -> 0 | R63: =Controls!B36 -> 0 | S63: =Controls!B38 -> 0 | T63: =IF(P63=1,"AWARDED","CONSTITUTED") -> CONSTITUTED
A64: MTH-LF-CON-L1 | B64: Method lineage | C64: Public | D64: MS-LF | E64: LF-B | F64: CONTROL | G64: ST-LF-CON | H64: CHR-LF-CON | I64: 0.09 | J64: 5 | K64: 7 | L64: 2 | M64: 4 | N64: SOURCE EMPTY | O64: SOURCE EMPTY | P64: =Controls!B34 -> 0 | Q64: =Controls!B35 -> 0 | R64: =Controls!B36 -> 0 | S64: =Controls!B38 -> 0 | T64: =IF(P64=1,"AWARDED","CONSTITUTED") -> CONSTITUTED
A65: MTH-LF-CON-L2 | B65: Method lineage | C65: Public | D65: MS-LF | E65: LF-B | F65: CONTROL | G65: ST-LF-CON | H65: CHR-LF-CON | I65: 0.09 | J65: 5 | K65: 7 | L65: 2 | M65: 4 | N65: SOURCE EMPTY | O65: SOURCE EMPTY | P65: =Controls!B34 -> 0 | Q65: =Controls!B35 -> 0 | R65: =Controls!B36 -> 0 | S65: =Controls!B38 -> 0 | T65: =IF(P65=1,"AWARDED","CONSTITUTED") -> CONSTITUTED
A66: REG-LF-CON | B66: Regeneration tool | C66: Public | D66: MS-LF | E66: LF-B | F66: CONTROL | G66: ST-LF-CON | H66: CHR-LF-CON | I66: 0.066666667 | J66: 5 | K66: 7 | L66: 2 | M66: 4 | N66: SOURCE EMPTY | O66: SOURCE EMPTY | P66: =Controls!B34 -> 0 | Q66: =Controls!B35 -> 0 | R66: =Controls!B36 -> 0 | S66: =Controls!B38 -> 0 | T66: =IF(P66=1,"AWARDED","CONSTITUTED") -> CONSTITUTED
A67: INT-LF-CON | B67: Station integration | C67: Public | D67: MS-LF | E67: LF-B | F67: CONTROL | G67: ST-LF-CON | H67: CHR-LF-CON | I67: 0.063333333 | J67: 5 | K67: 7 | L67: 2 | M67: 4 | N67: SOURCE EMPTY | O67: SOURCE EMPTY | P67: =Controls!B34 -> 0 | Q67: =Controls!B35 -> 0 | R67: =Controls!B36 -> 0 | S67: =Controls!B38 -> 0 | T67: =IF(P67=1,"AWARDED","CONSTITUTED") -> CONSTITUTED
A68: RIG-LF-REC | B68: Root-native rig | C68: Public | D68: MS-LF | E68: LF-B | F68: RECONSTRUCTION | G68: ST-LF-REC | H68: CHR-LF-REC | I68: 0.31666667 | J68: 5 | K68: 7 | L68: 2 | M68: 4 | N68: SOURCE EMPTY | O68: SOURCE EMPTY | P68: =Controls!B34 -> 0 | Q68: =Controls!B35 -> 0 | R68: =Controls!B36 -> 0 | S68: =Controls!B38 -> 0 | T68: =IF(P68=1,"AWARDED","CONSTITUTED") -> CONSTITUTED
A69: MTH-LF-REC-L1 | B69: Method lineage | C69: Public | D69: MS-LF | E69: LF-B | F69: RECONSTRUCTION | G69: ST-LF-REC | H69: CHR-LF-REC | I69: 0.09 | J69: 5 | K69: 7 | L69: 2 | M69: 4 | N69: SOURCE EMPTY | O69: SOURCE EMPTY | P69: =Controls!B34 -> 0 | Q69: =Controls!B35 -> 0 | R69: =Controls!B36 -> 0 | S69: =Controls!B38 -> 0 | T69: =IF(P69=1,"AWARDED","CONSTITUTED") -> CONSTITUTED
A70: MTH-LF-REC-L2 | B70: Method lineage | C70: Public | D70: MS-LF | E70: LF-B | F70: RECONSTRUCTION | G70: ST-LF-REC | H70: CHR-LF-REC | I70: 0.09 | J70: 5 | K70: 7 | L70: 2 | M70: 4 | N70: SOURCE EMPTY | O70: SOURCE EMPTY | P70: =Controls!B34 -> 0 | Q70: =Controls!B35 -> 0 | R70: =Controls!B36 -> 0 | S70: =Controls!B38 -> 0 | T70: =IF(P70=1,"AWARDED","CONSTITUTED") -> CONSTITUTED
A71: REG-LF-REC | B71: Regeneration tool | C71: Public | D71: MS-LF | E71: LF-B | F71: RECONSTRUCTION | G71: ST-LF-REC | H71: CHR-LF-REC | I71: 0.066666667 | J71: 5 | K71: 7 | L71: 2 | M71: 4 | N71: SOURCE EMPTY | O71: SOURCE EMPTY | P71: =Controls!B34 -> 0 | Q71: =Controls!B35 -> 0 | R71: =Controls!B36 -> 0 | S71: =Controls!B38 -> 0 | T71: =IF(P71=1,"AWARDED","CONSTITUTED") -> CONSTITUTED
A72: INT-LF-REC | B72: Station integration | C72: Public | D72: MS-LF | E72: LF-B | F72: RECONSTRUCTION | G72: ST-LF-REC | H72: CHR-LF-REC | I72: 0.063333333 | J72: 5 | K72: 7 | L72: 2 | M72: 4 | N72: SOURCE EMPTY | O72: SOURCE EMPTY | P72: =Controls!B34 -> 0 | Q72: =Controls!B35 -> 0 | R72: =Controls!B36 -> 0 | S72: =Controls!B38 -> 0 | T72: =IF(P72=1,"AWARDED","CONSTITUTED") -> CONSTITUTED
A73: RIG-HU-CHA | B73: Root-native rig | C73: Public | D73: MS-HU | E73: HU-A | F73: CHALLENGE | G73: ST-HU-CHA | H73: CHR-HU-CHA | I73: 0.31666667 | J73: 5 | K73: 7 | L73: 2 | M73: 4 | N73: SOURCE EMPTY | O73: SOURCE EMPTY | P73: =Controls!B34 -> 0 | Q73: =Controls!B35 -> 0 | R73: =Controls!B36 -> 0 | S73: =Controls!B38 -> 0 | T73: =IF(P73=1,"AWARDED","CONSTITUTED") -> CONSTITUTED
A74: MTH-HU-CHA-L1 | B74: Method lineage | C74: Public | D74: MS-HU | E74: HU-A | F74: CHALLENGE | G74: ST-HU-CHA | H74: CHR-HU-CHA | I74: 0.09 | J74: 5 | K74: 7 | L74: 2 | M74: 4 | N74: SOURCE EMPTY | O74: SOURCE EMPTY | P74: =Controls!B34 -> 0 | Q74: =Controls!B35 -> 0 | R74: =Controls!B36 -> 0 | S74: =Controls!B38 -> 0 | T74: =IF(P74=1,"AWARDED","CONSTITUTED") -> CONSTITUTED
A75: MTH-HU-CHA-L2 | B75: Method lineage | C75: Public | D75: MS-HU | E75: HU-A | F75: CHALLENGE | G75: ST-HU-CHA | H75: CHR-HU-CHA | I75: 0.09 | J75: 5 | K75: 7 | L75: 2 | M75: 4 | N75: SOURCE EMPTY | O75: SOURCE EMPTY | P75: =Controls!B34 -> 0 | Q75: =Controls!B35 -> 0 | R75: =Controls!B36 -> 0 | S75: =Controls!B38 -> 0 | T75: =IF(P75=1,"AWARDED","CONSTITUTED") -> CONSTITUTED
A76: REG-HU-CHA | B76: Regeneration tool | C76: Public | D76: MS-HU | E76: HU-A | F76: CHALLENGE | G76: ST-HU-CHA | H76: CHR-HU-CHA | I76: 0.066666667 | J76: 5 | K76: 7 | L76: 2 | M76: 4 | N76: SOURCE EMPTY | O76: SOURCE EMPTY | P76: =Controls!B34 -> 0 | Q76: =Controls!B35 -> 0 | R76: =Controls!B36 -> 0 | S76: =Controls!B38 -> 0 | T76: =IF(P76=1,"AWARDED","CONSTITUTED") -> CONSTITUTED
A77: INT-HU-CHA | B77: Station integration | C77: Public | D77: MS-HU | E77: HU-A | F77: CHALLENGE | G77: ST-HU-CHA | H77: CHR-HU-CHA | I77: 0.063333333 | J77: 5 | K77: 7 | L77: 2 | M77: 4 | N77: SOURCE EMPTY | O77: SOURCE EMPTY | P77: =Controls!B34 -> 0 | Q77: =Controls!B35 -> 0 | R77: =Controls!B36 -> 0 | S77: =Controls!B38 -> 0 | T77: =IF(P77=1,"AWARDED","CONSTITUTED") -> CONSTITUTED
A78: RIG-HU-CON | B78: Root-native rig | C78: Public | D78: MS-HU | E78: HU-A | F78: CONTROL | G78: ST-HU-CON | H78: CHR-HU-CON | I78: 0.31666667 | J78: 5 | K78: 7 | L78: 2 | M78: 4 | N78: SOURCE EMPTY | O78: SOURCE EMPTY | P78: =Controls!B34 -> 0 | Q78: =Controls!B35 -> 0 | R78: =Controls!B36 -> 0 | S78: =Controls!B38 -> 0 | T78: =IF(P78=1,"AWARDED","CONSTITUTED") -> CONSTITUTED
A79: MTH-HU-CON-L1 | B79: Method lineage | C79: Public | D79: MS-HU | E79: HU-A | F79: CONTROL | G79: ST-HU-CON | H79: CHR-HU-CON | I79: 0.09 | J79: 5 | K79: 7 | L79: 2 | M79: 4 | N79: SOURCE EMPTY | O79: SOURCE EMPTY | P79: =Controls!B34 -> 0 | Q79: =Controls!B35 -> 0 | R79: =Controls!B36 -> 0 | S79: =Controls!B38 -> 0 | T79: =IF(P79=1,"AWARDED","CONSTITUTED") -> CONSTITUTED
A80: MTH-HU-CON-L2 | B80: Method lineage | C80: Public | D80: MS-HU | E80: HU-A | F80: CONTROL | G80: ST-HU-CON | H80: CHR-HU-CON | I80: 0.09 | J80: 5 | K80: 7 | L80: 2 | M80: 4 | N80: SOURCE EMPTY | O80: SOURCE EMPTY | P80: =Controls!B34 -> 0 | Q80: =Controls!B35 -> 0 | R80: =Controls!B36 -> 0 | S80: =Controls!B38 -> 0 | T80: =IF(P80=1,"AWARDED","CONSTITUTED") -> CONSTITUTED
A81: REG-HU-CON | B81: Regeneration tool | C81: Public | D81: MS-HU | E81: HU-A | F81: CONTROL | G81: ST-HU-CON | H81: CHR-HU-CON | I81: 0.066666667 | J81: 5 | K81: 7 | L81: 2 | M81: 4 | N81: SOURCE EMPTY | O81: SOURCE EMPTY | P81: =Controls!B34 -> 0 | Q81: =Controls!B35 -> 0 | R81: =Controls!B36 -> 0 | S81: =Controls!B38 -> 0 | T81: =IF(P81=1,"AWARDED","CONSTITUTED") -> CONSTITUTED
A82: INT-HU-CON | B82: Station integration | C82: Public | D82: MS-HU | E82: HU-A | F82: CONTROL | G82: ST-HU-CON | H82: CHR-HU-CON | I82: 0.063333333 | J82: 5 | K82: 7 | L82: 2 | M82: 4 | N82: SOURCE EMPTY | O82: SOURCE EMPTY | P82: =Controls!B34 -> 0 | Q82: =Controls!B35 -> 0 | R82: =Controls!B36 -> 0 | S82: =Controls!B38 -> 0 | T82: =IF(P82=1,"AWARDED","CONSTITUTED") -> CONSTITUTED
A83: RIG-HU-REC | B83: Root-native rig | C83: Public | D83: MS-HU | E83: HU-A | F83: RECONSTRUCTION | G83: ST-HU-REC | H83: CHR-HU-REC | I83: 0.31666667 | J83: 5 | K83: 7 | L83: 2 | M83: 4 | N83: SOURCE EMPTY | O83: SOURCE EMPTY | P83: =Controls!B34 -> 0 | Q83: =Controls!B35 -> 0 | R83: =Controls!B36 -> 0 | S83: =Controls!B38 -> 0 | T83: =IF(P83=1,"AWARDED","CONSTITUTED") -> CONSTITUTED
A84: MTH-HU-REC-L1 | B84: Method lineage | C84: Public | D84: MS-HU | E84: HU-A | F84: RECONSTRUCTION | G84: ST-HU-REC | H84: CHR-HU-REC | I84: 0.09 | J84: 5 | K84: 7 | L84: 2 | M84: 4 | N84: SOURCE EMPTY | O84: SOURCE EMPTY | P84: =Controls!B34 -> 0 | Q84: =Controls!B35 -> 0 | R84: =Controls!B36 -> 0 | S84: =Controls!B38 -> 0 | T84: =IF(P84=1,"AWARDED","CONSTITUTED") -> CONSTITUTED
A85: MTH-HU-REC-L2 | B85: Method lineage | C85: Public | D85: MS-HU | E85: HU-A | F85: RECONSTRUCTION | G85: ST-HU-REC | H85: CHR-HU-REC | I85: 0.09 | J85: 5 | K85: 7 | L85: 2 | M85: 4 | N85: SOURCE EMPTY | O85: SOURCE EMPTY | P85: =Controls!B34 -> 0 | Q85: =Controls!B35 -> 0 | R85: =Controls!B36 -> 0 | S85: =Controls!B38 -> 0 | T85: =IF(P85=1,"AWARDED","CONSTITUTED") -> CONSTITUTED
A86: REG-HU-REC | B86: Regeneration tool | C86: Public | D86: MS-HU | E86: HU-A | F86: RECONSTRUCTION | G86: ST-HU-REC | H86: CHR-HU-REC | I86: 0.066666667 | J86: 5 | K86: 7 | L86: 2 | M86: 4 | N86: SOURCE EMPTY | O86: SOURCE EMPTY | P86: =Controls!B34 -> 0 | Q86: =Controls!B35 -> 0 | R86: =Controls!B36 -> 0 | S86: =Controls!B38 -> 0 | T86: =IF(P86=1,"AWARDED","CONSTITUTED") -> CONSTITUTED
A87: INT-HU-REC | B87: Station integration | C87: Public | D87: MS-HU | E87: HU-A | F87: RECONSTRUCTION | G87: ST-HU-REC | H87: CHR-HU-REC | I87: 0.063333333 | J87: 5 | K87: 7 | L87: 2 | M87: 4 | N87: SOURCE EMPTY | O87: SOURCE EMPTY | P87: =Controls!B34 -> 0 | Q87: =Controls!B35 -> 0 | R87: =Controls!B36 -> 0 | S87: =Controls!B38 -> 0 | T87: =IF(P87=1,"AWARDED","CONSTITUTED") -> CONSTITUTED
A88: RIG-RT-CHA | B88: Root-native rig | C88: Public | D88: MS-RT | E88: RT-B | F88: CHALLENGE | G88: ST-RT-CHA | H88: CHR-RT-CHA | I88: 0.31666667 | J88: 5 | K88: 7 | L88: 2 | M88: 4 | N88: SOURCE EMPTY | O88: SOURCE EMPTY | P88: =Controls!B34 -> 0 | Q88: =Controls!B35 -> 0 | R88: =Controls!B36 -> 0 | S88: =Controls!B38 -> 0 | T88: =IF(P88=1,"AWARDED","CONSTITUTED") -> CONSTITUTED
A89: MTH-RT-CHA-L1 | B89: Method lineage | C89: Public | D89: MS-RT | E89: RT-B | F89: CHALLENGE | G89: ST-RT-CHA | H89: CHR-RT-CHA | I89: 0.09 | J89: 5 | K89: 7 | L89: 2 | M89: 4 | N89: SOURCE EMPTY | O89: SOURCE EMPTY | P89: =Controls!B34 -> 0 | Q89: =Controls!B35 -> 0 | R89: =Controls!B36 -> 0 | S89: =Controls!B38 -> 0 | T89: =IF(P89=1,"AWARDED","CONSTITUTED") -> CONSTITUTED
A90: MTH-RT-CHA-L2 | B90: Method lineage | C90: Public | D90: MS-RT | E90: RT-B | F90: CHALLENGE | G90: ST-RT-CHA | H90: CHR-RT-CHA | I90: 0.09 | J90: 5 | K90: 7 | L90: 2 | M90: 4 | N90: SOURCE EMPTY | O90: SOURCE EMPTY | P90: =Controls!B34 -> 0 | Q90: =Controls!B35 -> 0 | R90: =Controls!B36 -> 0 | S90: =Controls!B38 -> 0 | T90: =IF(P90=1,"AWARDED","CONSTITUTED") -> CONSTITUTED
A91: REG-RT-CHA | B91: Regeneration tool | C91: Public | D91: MS-RT | E91: RT-B | F91: CHALLENGE | G91: ST-RT-CHA | H91: CHR-RT-CHA | I91: 0.066666667 | J91: 5 | K91: 7 | L91: 2 | M91: 4 | N91: SOURCE EMPTY | O91: SOURCE EMPTY | P91: =Controls!B34 -> 0 | Q91: =Controls!B35 -> 0 | R91: =Controls!B36 -> 0 | S91: =Controls!B38 -> 0 | T91: =IF(P91=1,"AWARDED","CONSTITUTED") -> CONSTITUTED
A92: INT-RT-CHA | B92: Station integration | C92: Public | D92: MS-RT | E92: RT-B | F92: CHALLENGE | G92: ST-RT-CHA | H92: CHR-RT-CHA | I92: 0.063333333 | J92: 5 | K92: 7 | L92: 2 | M92: 4 | N92: SOURCE EMPTY | O92: SOURCE EMPTY | P92: =Controls!B34 -> 0 | Q92: =Controls!B35 -> 0 | R92: =Controls!B36 -> 0 | S92: =Controls!B38 -> 0 | T92: =IF(P92=1,"AWARDED","CONSTITUTED") -> CONSTITUTED
A93: RIG-RT-CON | B93: Root-native rig | C93: Public | D93: MS-RT | E93: RT-B | F93: CONTROL | G93: ST-RT-CON | H93: CHR-RT-CON | I93: 0.31666667 | J93: 5 | K93: 7 | L93: 2 | M93: 4 | N93: SOURCE EMPTY | O93: SOURCE EMPTY | P93: =Controls!B34 -> 0 | Q93: =Controls!B35 -> 0 | R93: =Controls!B36 -> 0 | S93: =Controls!B38 -> 0 | T93: =IF(P93=1,"AWARDED","CONSTITUTED") -> CONSTITUTED
A94: MTH-RT-CON-L1 | B94: Method lineage | C94: Public | D94: MS-RT | E94: RT-B | F94: CONTROL | G94: ST-RT-CON | H94: CHR-RT-CON | I94: 0.09 | J94: 5 | K94: 7 | L94: 2 | M94: 4 | N94: SOURCE EMPTY | O94: SOURCE EMPTY | P94: =Controls!B34 -> 0 | Q94: =Controls!B35 -> 0 | R94: =Controls!B36 -> 0 | S94: =Controls!B38 -> 0 | T94: =IF(P94=1,"AWARDED","CONSTITUTED") -> CONSTITUTED
A95: MTH-RT-CON-L2 | B95: Method lineage | C95: Public | D95: MS-RT | E95: RT-B | F95: CONTROL | G95: ST-RT-CON | H95: CHR-RT-CON | I95: 0.09 | J95: 5 | K95: 7 | L95: 2 | M95: 4 | N95: SOURCE EMPTY | O95: SOURCE EMPTY | P95: =Controls!B34 -> 0 | Q95: =Controls!B35 -> 0 | R95: =Controls!B36 -> 0 | S95: =Controls!B38 -> 0 | T95: =IF(P95=1,"AWARDED","CONSTITUTED") -> CONSTITUTED
A96: REG-RT-CON | B96: Regeneration tool | C96: Public | D96: MS-RT | E96: RT-B | F96: CONTROL | G96: ST-RT-CON | H96: CHR-RT-CON | I96: 0.066666667 | J96: 5 | K96: 7 | L96: 2 | M96: 4 | N96: SOURCE EMPTY | O96: SOURCE EMPTY | P96: =Controls!B34 -> 0 | Q96: =Controls!B35 -> 0 | R96: =Controls!B36 -> 0 | S96: =Controls!B38 -> 0 | T96: =IF(P96=1,"AWARDED","CONSTITUTED") -> CONSTITUTED
A97: INT-RT-CON | B97: Station integration | C97: Public | D97: MS-RT | E97: RT-B | F97: CONTROL | G97: ST-RT-CON | H97: CHR-RT-CON | I97: 0.063333333 | J97: 5 | K97: 7 | L97: 2 | M97: 4 | N97: SOURCE EMPTY | O97: SOURCE EMPTY | P97: =Controls!B34 -> 0 | Q97: =Controls!B35 -> 0 | R97: =Controls!B36 -> 0 | S97: =Controls!B38 -> 0 | T97: =IF(P97=1,"AWARDED","CONSTITUTED") -> CONSTITUTED
A98: RIG-RT-REC | B98: Root-native rig | C98: Public | D98: MS-RT | E98: RT-B | F98: RECONSTRUCTION | G98: ST-RT-REC | H98: CHR-RT-REC | I98: 0.31666667 | J98: 5 | K98: 7 | L98: 2 | M98: 4 | N98: SOURCE EMPTY | O98: SOURCE EMPTY | P98: =Controls!B34 -> 0 | Q98: =Controls!B35 -> 0 | R98: =Controls!B36 -> 0 | S98: =Controls!B38 -> 0 | T98: =IF(P98=1,"AWARDED","CONSTITUTED") -> CONSTITUTED
A99: MTH-RT-REC-L1 | B99: Method lineage | C99: Public | D99: MS-RT | E99: RT-B | F99: RECONSTRUCTION | G99: ST-RT-REC | H99: CHR-RT-REC | I99: 0.09 | J99: 5 | K99: 7 | L99: 2 | M99: 4 | N99: SOURCE EMPTY | O99: SOURCE EMPTY | P99: =Controls!B34 -> 0 | Q99: =Controls!B35 -> 0 | R99: =Controls!B36 -> 0 | S99: =Controls!B38 -> 0 | T99: =IF(P99=1,"AWARDED","CONSTITUTED") -> CONSTITUTED
A100: MTH-RT-REC-L2 | B100: Method lineage | C100: Public | D100: MS-RT | E100: RT-B | F100: RECONSTRUCTION | G100: ST-RT-REC | H100: CHR-RT-REC | I100: 0.09 | J100: 5 | K100: 7 | L100: 2 | M100: 4 | N100: SOURCE EMPTY | O100: SOURCE EMPTY | P100: =Controls!B34 -> 0 | Q100: =Controls!B35 -> 0 | R100: =Controls!B36 -> 0 | S100: =Controls!B38 -> 0 | T100: =IF(P100=1,"AWARDED","CONSTITUTED") -> CONSTITUTED
A101: REG-RT-REC | B101: Regeneration tool | C101: Public | D101: MS-RT | E101: RT-B | F101: RECONSTRUCTION | G101: ST-RT-REC | H101: CHR-RT-REC | I101: 0.066666667 | J101: 5 | K101: 7 | L101: 2 | M101: 4 | N101: SOURCE EMPTY | O101: SOURCE EMPTY | P101: =Controls!B34 -> 0 | Q101: =Controls!B35 -> 0 | R101: =Controls!B36 -> 0 | S101: =Controls!B38 -> 0 | T101: =IF(P101=1,"AWARDED","CONSTITUTED") -> CONSTITUTED
A102: INT-RT-REC | B102: Station integration | C102: Public | D102: MS-RT | E102: RT-B | F102: RECONSTRUCTION | G102: ST-RT-REC | H102: CHR-RT-REC | I102: 0.063333333 | J102: 5 | K102: 7 | L102: 2 | M102: 4 | N102: SOURCE EMPTY | O102: SOURCE EMPTY | P102: =Controls!B34 -> 0 | Q102: =Controls!B35 -> 0 | R102: =Controls!B36 -> 0 | S102: =Controls!B38 -> 0 | T102: =IF(P102=1,"AWARDED","CONSTITUTED") -> CONSTITUTED
A103: CAN-ET-A | B103: Candidate mechanism | C103: Private option | D103: MS-ET | E103: ET-A | F103: SYSTEM | G103: ET TRUTH TRAIN | H103: 3 CHARTERS | I103: 0.50047462 | J103: 5 | K103: 7 | L103: 2 | M103: 4 | N103: SOURCE EMPTY | O103: SOURCE EMPTY | P103: =Controls!B34 -> 0 | Q103: =Controls!B35 -> 0 | R103: =Controls!B36 -> 0 | S103: =Controls!B38 -> 0 | T103: =IF(P103=1,"AWARDED","CONSTITUTED") -> CONSTITUTED
...

Sheet Warrants
A2: Eighteen serial construction warrants
A4: Integration is artifact succession. A receiving authority obtains one bounded record, never the producer's power.
A6: Warrant | B6: State | C6: Artifact | D6: Producer | E6: Acceptor / consumer | F6: Next state | G6: Current value | H6: Expiry or rollback
A7: W01 | B7: NEED | C7: public-service deficit and noncompensatory vector | D7: Civic requirement authority | E7: Root portfolio court | F7: SENTINEL | G7: NEED | H7: same-scope return; no forward inference
A8: W02 | B8: SENTINEL | C8: one deliberately fragile root per system | D8: Root portfolio court | E8: Public method authority | F8: METHOD | G8: ROOT HOLD | H8: same-scope return; no forward inference
A9: W03 | B9: METHOD | C9: receiver states, endpoints and denial grammar | D9: Public method authority | E9: Proving Service | F9: RIG | G9: METHOD FROZEN | H9: same-scope return; no forward inference
A10: W04 | B10: RIG | C10: root-native truth train and station configuration | D10: Proving Service | E10: Industrial constitution | F10: LOT | G10: RIG FROZEN | H10: same-scope return; no forward inference
A11: W05 | B11: LOT | C11: 102 severable construction objects and ceilings | D11: Industrial constitution | E11: Site stewardship authority | F11: SITE CLASS | G11: LOT CONSTITUTED | H11: same-scope return; no forward inference
A12: W06 | B12: SITE CLASS | C12: eighteen source-independent causal envelopes | D12: Site stewardship authority | E12: Physical Site Court | F12: SITE ADMISSION | G12: CLASS CONSTITUTED | H12: same-scope return; no forward inference
A13: W07 | B13: SITE ADMISSION | C13: named rights, conditions and causal independence | D13: Physical Site Court | E13: Technical bid panel | F13: TECHNICAL ADMISSION | G13: SOURCE EMPTY | H13: source absent
A14: W08 | B14: TECHNICAL ADMISSION | C14: pseudonymous complete-lot method | D14: Technical bid panel | E14: Control registrar | F14: CONTROL ADMISSION | G14: SOURCE EMPTY | H14: source absent
A15: W09 | B15: CONTROL ADMISSION | C15: ownership, debt, subtier, tool, key and personnel graph | D15: Control registrar | E15: Optimization custodian | F15: SLATE PROOF | G15: SOURCE EMPTY | H15: source absent
A16: W10 | B16: SLATE PROOF | C16: complete primary slate plus forty-eight N-1 solves | D16: Optimization custodian | E16: Comptroller | F16: PRICE ADMISSION | G16: OPEN | H16: same-scope return; no forward inference
A17: W11 | B17: PRICE ADMISSION | C17: lot-local sealed price within ceiling | D17: Comptroller | E17: Award authority | F17: AWARD | G17: SOURCE EMPTY | H17: source absent
... A24: W18 | B24: TRANSFER RETURN | C24: accepted technical record returned to parent portfolio | D24: Evidence Court | E24: Root portfolio court | F24: FORM-GIVING REQUIREMENT | G24: HELD | H24: same-scope return; no forward inference

Sheet State Machine
A2: Eighteen-state construction campaign
A4: Only NEED through SITE CLASS are presently constituted or frozen. Every identity-, award- and evidence-bearing state remains blocked or source empty.
A6: Order | B6: Warrant | C6: State | D6: Current artifact | E6: Transition state | F6: Required predecessor | G6: Successor | H6: Physical observation? | I6: Capability credit | J6: Nonconversion
A7: 1 | B7: W01 | C7: NEED | D7: NEED | E7: CONSTITUTED | F7: parent need warrant | G7: SENTINEL | H7: NO | I7: 0 | J7: NO FORWARD INFERENCE
A8: 2 | B8: W02 | C8: SENTINEL | D8: ROOT HOLD | E8: BLOCKED | F8: NEED | G8: METHOD | H8: NO | I8: 0 | J8: NO FORWARD INFERENCE
A9: 3 | B9: W03 | C9: METHOD | D9: METHOD FROZEN | E9: BLOCKED | F9: SENTINEL | G9: RIG | H9: NO | I9: 0 | J9: NO FORWARD INFERENCE
A10: 4 | B10: W04 | C10: RIG | D10: RIG FROZEN | E10: BLOCKED | F10: METHOD | G10: LOT | H10: NO | I10: 0 | J10: NO FORWARD INFERENCE
A11: 5 | B11: W05 | C11: LOT | D11: LOT CONSTITUTED | E11: BLOCKED | F11: RIG | G11: SITE CLASS | H11: NO | I11: 0 | J11: NO FORWARD INFERENCE
A12: 6 | B12: W06 | C12: SITE CLASS | D12: CLASS CONSTITUTED | E12: BLOCKED | F12: LOT | G12: SITE ADMISSION | H12: NO | I12: 0 | J12: NO FORWARD INFERENCE
A13: 7 | B13: W07 | C13: SITE ADMISSION | D13: SOURCE EMPTY | E13: BLOCKED | F13: SITE CLASS | G13: TECHNICAL ADMISSION | H13: NO | I13: 0 | J13: NO FORWARD INFERENCE
A14: 8 | B14: W08 | C14: TECHNICAL ADMISSION | D14: SOURCE EMPTY | E14: BLOCKED | F14: SITE ADMISSION | G14: CONTROL ADMISSION | H14: NO | I14: 0 | J14: NO FORWARD INFERENCE
A15: 9 | B15: W09 | C15: CONTROL ADMISSION | D15: SOURCE EMPTY | E15: BLOCKED | F15: TECHNICAL ADMISSION | G15: SLATE PROOF | H15: NO | I15: 0 | J15: NO FORWARD INFERENCE
A16: 10 | B16: W10 | C16: SLATE PROOF | D16: OPEN | E16: BLOCKED | F16: CONTROL ADMISSION | G16: PRICE ADMISSION | H16: NO | I16: 0 | J16: NO FORWARD INFERENCE
A17: 11 | B17: W11 | C17: PRICE ADMISSION | D17: SOURCE EMPTY | E17: BLOCKED | F17: SLATE PROOF | G17: AWARD | H17: NO | I17: 0 | J17: NO FORWARD INFERENCE
A18: 12 | B18: W12 | C18: AWARD | D18: HELD | E18: BLOCKED | F18: PRICE ADMISSION | G18: FRAME | H18: NO | I18: 0 | J18: NO FORWARD INFERENCE
... A24: 18 | B24: W18 | C24: TRANSFER RETURN | D24: HELD | E24: BLOCKED | F24: COLD RETURN | G24: FORM-GIVING REQUIREMENT | H24: NO | I24: 0 | J24: NO FORWARD INFERENCE

Sheet Release Graph
A2: Seventeen typed handoffs between warrants
A4: Every edge is one-way and typed. Return moves to a named predecessor; it does not transfer authority upstream or downstream.
A6: Edge | B6: From | C6: To | D6: Transferred artifact | E6: Receiver may do | F6: Receiver may not do | G6: Rollback target | H6: State
A7: E01 | B7: NEED | C7: SENTINEL | D7: public-service deficit and noncompensatory vector | E7: test or consume only for SENTINEL | F7: rewrite NEED or manufacture METHOD | G7: NEED | H7: FROZEN
A8: E02 | B8: SENTINEL | C8: METHOD | D8: one deliberately fragile root per system | E8: test or consume only for METHOD | F8: rewrite SENTINEL or manufacture RIG | G8: SENTINEL | H8: FROZEN
A9: E03 | B9: METHOD | C9: RIG | D9: receiver states, endpoints and denial grammar | E9: test or consume only for RIG | F9: rewrite METHOD or manufacture LOT | G9: METHOD | H9: FROZEN
A10: E04 | B10: RIG | C10: LOT | D10: root-native truth train and station configuration | E10: test or consume only for LOT | F10: rewrite RIG or manufacture SITE CLASS | G10: RIG | H10: FROZEN
A11: E05 | B11: LOT | C11: SITE CLASS | D11: 102 severable construction objects and ceilings | E11: test or consume only for SITE CLASS | F11: rewrite LOT or manufacture SITE ADMISSION | G11: LOT | H11: FROZEN
A12: E06 | B12: SITE CLASS | C12: SITE ADMISSION | D12: eighteen source-independent causal envelopes | E12: test or consume only for SITE ADMISSION | F12: rewrite SITE CLASS or manufacture TECHNICAL ADMISSION | G12: SITE CLASS | H12: FROZEN
A13: E07 | B13: SITE ADMISSION | C13: TECHNICAL ADMISSION | D13: named rights, conditions and causal independence | E13: test or consume only for TECHNICAL ADMISSION | F13: rewrite SITE ADMISSION or manufacture CONTROL ADMISSION | G13: SITE ADMISSION | H13: HELD
A14: E08 | B14: TECHNICAL ADMISSION | C14: CONTROL ADMISSION | D14: pseudonymous complete-lot method | E14: test or consume only for CONTROL ADMISSION | F14: rewrite TECHNICAL ADMISSION or manufacture SLATE PROOF | G14: TECHNICAL ADMISSION | H14: HELD
A15: E09 | B15: CONTROL ADMISSION | C15: SLATE PROOF | D15: ownership, debt, subtier, tool, key and personnel graph | E15: test or consume only for SLATE PROOF | F15: rewrite CONTROL ADMISSION or manufacture PRICE ADMISSION | G15: CONTROL ADMISSION | H15: HELD
A16: E10 | B16: SLATE PROOF | C16: PRICE ADMISSION | D16: complete primary slate plus forty-eight N-1 solves | E16: test or consume only for PRICE ADMISSION | F16: rewrite SLATE PROOF or manufacture AWARD | G16: SLATE PROOF | H16: HELD
A17: E11 | B17: PRICE ADMISSION | C17: AWARD | D17: lot-local sealed price within ceiling | E17: test or consume only for AWARD | F17: rewrite PRICE ADMISSION or manufacture FRAME | G17: PRICE ADMISSION | H17: HELD
... A23: E17 | B23: COLD RETURN | C23: TRANSFER RETURN | D23: outside-team rebuild, calibration and replay | E23: test or consume only for TRANSFER RETURN | F23: rewrite COLD RETURN or manufacture FORM-GIVING REQUIREMENT | G23: COLD RETURN | H23: HELD

Sheet Authority Matrix
A2: Sixteen authorities across eighteen warrants
A4: CREATE and ACCEPT remain distinct. All other cells are NONE; no authority acquires a universal view or override through integration.
A6: Authority | B6: W01 | C6: W02 | D6: W03 | E6: W04 | F6: W05 | G6: W06 | H6: W07 | I6: W08 | J6: W09 | K6: W10 | L6: W11 | M6: W12 | N6: W13 | O6: W14 | P6: W15 | Q6: W16 | R6: W17 | S6: W18 | T6: Create count
A7: Civic requirement authority | B7: CREATE | C7: NONE | D7: NONE | E7: NONE | F7: NONE | G7: NONE | H7: NONE | I7: NONE | J7: NONE | K7: NONE | L7: NONE | M7: NONE | N7: NONE | O7: NONE | P7: NONE | Q7: NONE | R7: NONE | S7: NONE | T7: =COUNTIF(B7:S7,"CREATE") -> 1
A8: Root portfolio court | B8: ACCEPT | C8: CREATE | D8: NONE | E8: NONE | F8: NONE | G8: NONE | H8: NONE | I8: NONE | J8: NONE | K8: NONE | L8: NONE | M8: NONE | N8: NONE | O8: NONE | P8: NONE | Q8: NONE | R8: NONE | S8: ACCEPT | T8: =COUNTIF(B8:S8,"CREATE") -> 1
A9: Public method authority | B9: NONE | C9: ACCEPT | D9: CREATE | E9: NONE | F9: NONE | G9: NONE | H9: NONE | I9: NONE | J9: NONE | K9: NONE | L9: NONE | M9: NONE | N9: NONE | O9: NONE | P9: NONE | Q9: NONE | R9: NONE | S9: NONE | T9: =COUNTIF(B9:S9,"CREATE") -> 1
A10: Proving Service | B10: NONE | C10: NONE | D10: ACCEPT | E10: CREATE | F10: NONE | G10: NONE | H10: NONE | I10: NONE | J10: NONE | K10: NONE | L10: NONE | M10: NONE | N10: NONE | O10: NONE | P10: NONE | Q10: NONE | R10: NONE | S10: NONE | T10: =COUNTIF(B10:S10,"CREATE") -> 1
A11: Industrial constitution | B11: NONE | C11: NONE | D11: NONE | E11: ACCEPT | F11: CREATE | G11: NONE | H11: NONE | I11: NONE | J11: NONE | K11: NONE | L11: NONE | M11: NONE | N11: NONE | O11: NONE | P11: NONE | Q11: NONE | R11: NONE | S11: NONE | T11: =COUNTIF(B11:S11,"CREATE") -> 1
A12: Site stewardship authority | B12: NONE | C12: NONE | D12: NONE | E12: NONE | F12: ACCEPT | G12: CREATE | H12: NONE | I12: NONE | J12: NONE | K12: NONE | L12: NONE | M12: NONE | N12: NONE | O12: NONE | P12: NONE | Q12: NONE | R12: NONE | S12: NONE | T12: =COUNTIF(B12:S12,"CREATE") -> 1
A13: Physical Site Court | B13: NONE | C13: NONE | D13: NONE | E13: NONE | F13: NONE | G13: ACCEPT | H13: CREATE | I13: NONE | J13: NONE | K13: NONE | L13: NONE | M13: NONE | N13: NONE | O13: NONE | P13: NONE | Q13: NONE | R13: NONE | S13: NONE | T13: =COUNTIF(B13:S13,"CREATE") -> 1
A14: Technical bid panel | B14: NONE | C14: NONE | D14: NONE | E14: NONE | F14: NONE | G14: NONE | H14: ACCEPT | I14: CREATE | J14: NONE | K14: NONE | L14: NONE | M14: NONE | N14: NONE | O14: NONE | P14: NONE | Q14: NONE | R14: NONE | S14: NONE | T14: =COUNTIF(B14:S14,"CREATE") -> 1
A15: Control registrar | B15: NONE | C15: NONE | D15: NONE | E15: NONE | F15: NONE | G15: NONE | H15: NONE | I15: ACCEPT | J15: CREATE | K15: NONE | L15: NONE | M15: NONE | N15: NONE | O15: NONE | P15: NONE | Q15: NONE | R15: NONE | S15: NONE | T15: =COUNTIF(B15:S15,"CREATE") -> 1
A16: Optimization custodian | B16: NONE | C16: NONE | D16: NONE | E16: NONE | F16: NONE | G16: NONE | H16: NONE | I16: NONE | J16: ACCEPT | K16: CREATE | L16: NONE | M16: NONE | N16: NONE | O16: NONE | P16: NONE | Q16: NONE | R16: NONE | S16: NONE | T16: =COUNTIF(B16:S16,"CREATE") -> 1
A17: Comptroller | B17: NONE | C17: NONE | D17: NONE | E17: NONE | F17: NONE | G17: NONE | H17: NONE | I17: NONE | J17: NONE | K17: ACCEPT | L17: CREATE | M17: NONE | N17: NONE | O17: NONE | P17: NONE | Q17: NONE | R17: NONE | S17: NONE | T17: =COUNTIF(B17:S17,"CREATE") -> 1
A18: Award authority | B18: NONE | C18: NONE | D18: NONE | E18: NONE | F18: NONE | G18: NONE | H18: NONE | I18: NONE | J18: NONE | K18: NONE | L18: ACCEPT | M18: CREATE | N18: NONE | O18: NONE | P18: NONE | Q18: NONE | R18: NONE | S18: NONE | T18: =COUNTIF(B18:S18,"CREATE") -> 1
... A22: Cold reconstruction authority | B22: NONE | C22: NONE | D22: NONE | E22: NONE | F22: NONE | G22: NONE | H22: NONE | I22: NONE | J22: NONE | K22: NONE | L22: NONE | M22: NONE | N22: NONE | O22: NONE | P22: NONE | Q22: ACCEPT | R22: CREATE | S22: NONE | T22: =COUNTIF(B22:S22,"CREATE") -> 1

Sheet Nonconversions
A2: Eighteen prohibited state conversions
A4: A nonconversion is an enforceable denial rule, not explanatory prose. Its violation rolls back the claiming state.
A6: ID | B6: False conversion | C6: Why invalid | D6: Required intervening warrant | E6: Violation response | F6: State
A7: N01 | B7: selection → promise | C7: sentinel is chosen for falsifiability, not production merit | D7: ROOT DISPOSITION | E7: hold claim | F7: FROZEN
A8: N02 | B8: method → observation | C8: a protocol contains no physical fact | D8: EVENT VALIDITY | E8: reject claim | F8: FROZEN
A9: N03 | B9: configuration → article | C9: paper geometry has no as-built identity | D9: MAKE | E9: reject claim | F9: FROZEN
A10: N04 | B10: lot → award | C10: a procurement object has no winner | D10: AWARD | E10: reject claim | F10: FROZEN
A11: N05 | B11: site class → place | C11: a causal envelope names no land | D11: SITE ADMISSION | E11: reject claim | F11: FROZEN
A12: N06 | B12: distance → independence | C12: mileage cannot expose shared causal ancestry | D12: SITE ADMISSION | E12: repeat basin proof | F12: FROZEN
A13: N07 | B13: bid position → bidder | C13: a required slot is not a submission | D13: TECHNICAL ADMISSION | E13: reject claim | F13: FROZEN
A14: N08 | B14: two bids → N-1 resilience | C14: slot depth does not prove whole-pool recomposition | D14: SLATE PROOF | E14: repeat solve | F14: FROZEN
A15: N09 | B15: low price → admission | C15: money cannot cure technical or control failure | D15: PRICE ADMISSION | E15: reject bid | F15: FROZEN
A16: N10 | B16: provisional → contract | C16: pre-effect selection creates no entitlement | D16: AWARD | E16: revoke without liability | F16: FROZEN
A17: N11 | B17: obligation → acceptance | C17: fund reservation contains no accepted artifact | D17: FRAME or MAKE | E17: hold payment | F17: FROZEN
... A24: N18 | B24: functional envelope → exterior | C24: form remains unselected until article requirements close | D24: FORM-GIVING REQUIREMENT | E24: hold rendering | F24: FROZEN

Sheet Construction Packets
A2: Five hundred ten construction packet references
A4: Construction packets prove configuration and as-built state. They cannot satisfy event-evidence packages.
A6: Packet | B6: Lot | C6: Class | D6: System | E6: Root | F6: Role | G6: Packet type | H6: Source identity | I6: Accepted | J6: Event substitute? | K6: State
A7: ="PKT-"&B7&"-CONFIGURATION" -> PKT-SUB-01-CONFIGURATION | B7: ='Object Crosswalk'!A7 -> SUB-01 | C7: ='Object Crosswalk'!B7 -> Civil substrate | D7: ='Object Crosswalk'!D7 -> MULTI | E7: ='Object Crosswalk'!E7 -> — | F7: ='Object Crosswalk'!F7 -> ROTATED | G7: CONFIGURATION | H7: SOURCE EMPTY | I7: =0 -> 0 | J7: NO | K7: =IF(I7=1,"ACCEPTED","OPEN") -> OPEN
A8: ="PKT-"&B8&"-CONTROL" -> PKT-SUB-01-CONTROL | B8: ='Object Crosswalk'!A7 -> SUB-01 | C8: ='Object Crosswalk'!B7 -> Civil substrate | D8: ='Object Crosswalk'!D7 -> MULTI | E8: ='Object Crosswalk'!E7 -> — | F8: ='Object Crosswalk'!F7 -> ROTATED | G8: CONTROL | H8: SOURCE EMPTY | I8: =0 -> 0 | J8: NO | K8: =IF(I8=1,"ACCEPTED","OPEN") -> OPEN
A9: ="PKT-"&B9&"-METROLOGY" -> PKT-SUB-01-METROLOGY | B9: ='Object Crosswalk'!A7 -> SUB-01 | C9: ='Object Crosswalk'!B7 -> Civil substrate | D9: ='Object Crosswalk'!D7 -> MULTI | E9: ='Object Crosswalk'!E7 -> — | F9: ='Object Crosswalk'!F7 -> ROTATED | G9: METROLOGY | H9: SOURCE EMPTY | I9: =0 -> 0 | J9: NO | K9: =IF(I9=1,"ACCEPTED","OPEN") -> OPEN
A10: ="PKT-"&B10&"-SAFETY" -> PKT-SUB-01-SAFETY | B10: ='Object Crosswalk'!A7 -> SUB-01 | C10: ='Object Crosswalk'!B7 -> Civil substrate | D10: ='Object Crosswalk'!D7 -> MULTI | E10: ='Object Crosswalk'!E7 -> — | F10: ='Object Crosswalk'!F7 -> ROTATED | G10: SAFETY | H10: SOURCE EMPTY | I10: =0 -> 0 | J10: NO | K10: =IF(I10=1,"ACCEPTED","OPEN") -> OPEN
A11: ="PKT-"&B11&"-RECONSTRUCTION" -> PKT-SUB-01-RECONSTRUCTION | B11: ='Object Crosswalk'!A7 -> SUB-01 | C11: ='Object Crosswalk'!B7 -> Civil substrate | D11: ='Object Crosswalk'!D7 -> MULTI | E11: ='Object Crosswalk'!E7 -> — | F11: ='Object Crosswalk'!F7 -> ROTATED | G11: RECONSTRUCTION | H11: SOURCE EMPTY | I11: =0 -> 0 | J11: NO | K11: =IF(I11=1,"ACCEPTED","OPEN") -> OPEN
A12: ="PKT-"&B12&"-CONFIGURATION" -> PKT-SUB-02-CONFIGURATION | B12: ='Object Crosswalk'!A8 -> SUB-02 | C12: ='Object Crosswalk'!B8 -> Civil substrate | D12: ='Object Crosswalk'!D8 -> MULTI | E12: ='Object Crosswalk'!E8 -> — | F12: ='Object Crosswalk'!F8 -> ROTATED | G12: CONFIGURATION | H12: SOURCE EMPTY | I12: =0 -> 0 | J12: NO | K12: =IF(I12=1,"ACCEPTED","OPEN") -> OPEN
A13: ="PKT-"&B13&"-CONTROL" -> PKT-SUB-02-CONTROL | B13: ='Object Crosswalk'!A8 -> SUB-02 | C13: ='Object Crosswalk'!B8 -> Civil substrate | D13: ='Object Crosswalk'!D8 -> MULTI | E13: ='Object Crosswalk'!E8 -> — | F13: ='Object Crosswalk'!F8 -> ROTATED | G13: CONTROL | H13: SOURCE EMPTY | I13: =0 -> 0 | J13: NO | K13: =IF(I13=1,"ACCEPTED","OPEN") -> OPEN
A14: ="PKT-"&B14&"-METROLOGY" -> PKT-SUB-02-METROLOGY | B14: ='Object Crosswalk'!A8 -> SUB-02 | C14: ='Object Crosswalk'!B8 -> Civil substrate | D14: ='Object Crosswalk'!D8 -> MULTI | E14: ='Object Crosswalk'!E8 -> — | F14: ='Object Crosswalk'!F8 -> ROTATED | G14: METROLOGY | H14: SOURCE EMPTY | I14: =0 -> 0 | J14: NO | K14: =IF(I14=1,"ACCEPTED","OPEN") -> OPEN
A15: ="PKT-"&B15&"-SAFETY" -> PKT-SUB-02-SAFETY | B15: ='Object Crosswalk'!A8 -> SUB-02 | C15: ='Object Crosswalk'!B8 -> Civil substrate | D15: ='Object Crosswalk'!D8 -> MULTI | E15: ='Object Crosswalk'!E8 -> — | F15: ='Object Crosswalk'!F8 -> ROTATED | G15: SAFETY | H15: SOURCE EMPTY | I15: =0 -> 0 | J15: NO | K15: =IF(I15=1,"ACCEPTED","OPEN") -> OPEN
A16: ="PKT-"&B16&"-RECONSTRUCTION" -> PKT-SUB-02-RECONSTRUCTION | B16: ='Object Crosswalk'!A8 -> SUB-02 | C16: ='Object Crosswalk'!B8 -> Civil substrate | D16: ='Object Crosswalk'!D8 -> MULTI | E16: ='Object Crosswalk'!E8 -> — | F16: ='Object Crosswalk'!F8 -> ROTATED | G16: RECONSTRUCTION | H16: SOURCE EMPTY | I16: =0 -> 0 | J16: NO | K16: =IF(I16=1,"ACCEPTED","OPEN") -> OPEN
A17: ="PKT-"&B17&"-CONFIGURATION" -> PKT-SUB-03-CONFIGURATION | B17: ='Object Crosswalk'!A9 -> SUB-03 | C17: ='Object Crosswalk'!B9 -> Civil substrate | D17: ='Object Crosswalk'!D9 -> MULTI | E17: ='Object Crosswalk'!E9 -> — | F17: ='Object Crosswalk'!F9 -> ROTATED | G17: CONFIGURATION | H17: SOURCE EMPTY | I17: =0 -> 0 | J17: NO | K17: =IF(I17=1,"ACCEPTED","OPEN") -> OPEN
A18: ="PKT-"&B18&"-CONTROL" -> PKT-SUB-03-CONTROL | B18: ='Object Crosswalk'!A9 -> SUB-03 | C18: ='Object Crosswalk'!B9 -> Civil substrate | D18: ='Object Crosswalk'!D9 -> MULTI | E18: ='Object Crosswalk'!E9 -> — | F18: ='Object Crosswalk'!F9 -> ROTATED | G18: CONTROL | H18: SOURCE EMPTY | I18: =0 -> 0 | J18: NO | K18: =IF(I18=1,"ACCEPTED","OPEN") -> OPEN
A19: ="PKT-"&B19&"-METROLOGY" -> PKT-SUB-03-METROLOGY | B19: ='Object Crosswalk'!A9 -> SUB-03 | C19: ='Object Crosswalk'!B9 -> Civil substrate | D19: ='Object Crosswalk'!D9 -> MULTI | E19: ='Object Crosswalk'!E9 -> — | F19: ='Object Crosswalk'!F9 -> ROTATED | G19: METROLOGY | H19: SOURCE EMPTY | I19: =0 -> 0 | J19: NO | K19: =IF(I19=1,"ACCEPTED","OPEN") -> OPEN
A20: ="PKT-"&B20&"-SAFETY" -> PKT-SUB-03-SAFETY | B20: ='Object Crosswalk'!A9 -> SUB-03 | C20: ='Object Crosswalk'!B9 -> Civil substrate | D20: ='Object Crosswalk'!D9 -> MULTI | E20: ='Object Crosswalk'!E9 -> — | F20: ='Object Crosswalk'!F9 -> ROTATED | G20: SAFETY | H20: SOURCE EMPTY | I20: =0 -> 0 | J20: NO | K20: =IF(I20=1,"ACCEPTED","OPEN") -> OPEN
A21: ="PKT-"&B21&"-RECONSTRUCTION" -> PKT-SUB-03-RECONSTRUCTION | B21: ='Object Crosswalk'!A9 -> SUB-03 | C21: ='Object Crosswalk'!B9 -> Civil substrate | D21: ='Object Crosswalk'!D9 -> MULTI | E21: ='Object Crosswalk'!E9 -> — | F21: ='Object Crosswalk'!F9 -> ROTATED | G21: RECONSTRUCTION | H21: SOURCE EMPTY | I21: =0 -> 0 | J21: NO | K21: =IF(I21=1,"ACCEPTED","OPEN") -> OPEN
A22: ="PKT-"&B22&"-CONFIGURATION" -> PKT-SUB-04-CONFIGURATION | B22: ='Object Crosswalk'!A10 -> SUB-04 | C22: ='Object Crosswalk'!B10 -> Civil substrate | D22: ='Object Crosswalk'!D10 -> MULTI | E22: ='Object Crosswalk'!E10 -> — | F22: ='Object Crosswalk'!F10 -> ROTATED | G22: CONFIGURATION | H22: SOURCE EMPTY | I22: =0 -> 0 | J22: NO | K22: =IF(I22=1,"ACCEPTED","OPEN") -> OPEN
A23: ="PKT-"&B23&"-CONTROL" -> PKT-SUB-04-CONTROL | B23: ='Object Crosswalk'!A10 -> SUB-04 | C23: ='Object Crosswalk'!B10 -> Civil substrate | D23: ='Object Crosswalk'!D10 -> MULTI | E23: ='Object Crosswalk'!E10 -> — | F23: ='Object Crosswalk'!F10 -> ROTATED | G23: CONTROL | H23: SOURCE EMPTY | I23: =0 -> 0 | J23: NO | K23: =IF(I23=1,"ACCEPTED","OPEN") -> OPEN
A24: ="PKT-"&B24&"-METROLOGY" -> PKT-SUB-04-METROLOGY | B24: ='Object Crosswalk'!A10 -> SUB-04 | C24: ='Object Crosswalk'!B10 -> Civil substrate | D24: ='Object Crosswalk'!D10 -> MULTI | E24: ='Object Crosswalk'!E10 -> — | F24: ='Object Crosswalk'!F10 -> ROTATED | G24: METROLOGY | H24: SOURCE EMPTY | I24: =0 -> 0 | J24: NO | K24: =IF(I24=1,"ACCEPTED","OPEN") -> OPEN
A25: ="PKT-"&B25&"-SAFETY" -> PKT-SUB-04-SAFETY | B25: ='Object Crosswalk'!A10 -> SUB-04 | C25: ='Object Crosswalk'!B10 -> Civil substrate | D25: ='Object Crosswalk'!D10 -> MULTI | E25: ='Object Crosswalk'!E10 -> — | F25: ='Object Crosswalk'!F10 -> ROTATED | G25: SAFETY | H25: SOURCE EMPTY | I25: =0 -> 0 | J25: NO | K25: =IF(I25=1,"ACCEPTED","OPEN") -> OPEN
A26: ="PKT-"&B26&"-RECONSTRUCTION" -> PKT-SUB-04-RECONSTRUCTION | B26: ='Object Crosswalk'!A10 -> SUB-04 | C26: ='Object Crosswalk'!B10 -> Civil substrate | D26: ='Object Crosswalk'!D10 -> MULTI | E26: ='Object Crosswalk'!E10 -> — | F26: ='Object Crosswalk'!F10 -> ROTATED | G26: RECONSTRUCTION | H26: SOURCE EMPTY | I26: =0 -> 0 | J26: NO | K26: =IF(I26=1,"ACCEPTED","OPEN") -> OPEN
A27: ="PKT-"&B27&"-CONFIGURATION" -> PKT-SUB-05-CONFIGURATION | B27: ='Object Crosswalk'!A11 -> SUB-05 | C27: ='Object Crosswalk'!B11 -> Civil substrate | D27: ='Object Crosswalk'!D11 -> MULTI | E27: ='Object Crosswalk'!E11 -> — | F27: ='Object Crosswalk'!F11 -> ROTATED | G27: CONFIGURATION | H27: SOURCE EMPTY | I27: =0 -> 0 | J27: NO | K27: =IF(I27=1,"ACCEPTED","OPEN") -> OPEN
A28: ="PKT-"&B28&"-CONTROL" -> PKT-SUB-05-CONTROL | B28: ='Object Crosswalk'!A11 -> SUB-05 | C28: ='Object Crosswalk'!B11 -> Civil substrate | D28: ='Object Crosswalk'!D11 -> MULTI | E28: ='Object Crosswalk'!E11 -> — | F28: ='Object Crosswalk'!F11 -> ROTATED | G28: CONTROL | H28: SOURCE EMPTY | I28: =0 -> 0 | J28: NO | K28: =IF(I28=1,"ACCEPTED","OPEN") -> OPEN
A29: ="PKT-"&B29&"-METROLOGY" -> PKT-SUB-05-METROLOGY | B29: ='Object Crosswalk'!A11 -> SUB-05 | C29: ='Object Crosswalk'!B11 -> Civil substrate | D29: ='Object Crosswalk'!D11 -> MULTI | E29: ='Object Crosswalk'!E11 -> — | F29: ='Object Crosswalk'!F11 -> ROTATED | G29: METROLOGY | H29: SOURCE EMPTY | I29: =0 -> 0 | J29: NO | K29: =IF(I29=1,"ACCEPTED","OPEN") -> OPEN
A30: ="PKT-"&B30&"-SAFETY" -> PKT-SUB-05-SAFETY | B30: ='Object Crosswalk'!A11 -> SUB-05 | C30: ='Object Crosswalk'!B11 -> Civil substrate | D30: ='Object Crosswalk'!D11 -> MULTI | E30: ='Object Crosswalk'!E11 -> — | F30: ='Object Crosswalk'!F11 -> ROTATED | G30: SAFETY | H30: SOURCE EMPTY | I30: =0 -> 0 | J30: NO | K30: =IF(I30=1,"ACCEPTED","OPEN") -> OPEN
A31: ="PKT-"&B31&"-RECONSTRUCTION" -> PKT-SUB-05-RECONSTRUCTION | B31: ='Object Crosswalk'!A11 -> SUB-05 | C31: ='Object Crosswalk'!B11 -> Civil substrate | D31: ='Object Crosswalk'!D11 -> MULTI | E31: ='Object Crosswalk'!E11 -> — | F31: ='Object Crosswalk'!F11 -> ROTATED | G31: RECONSTRUCTION | H31: SOURCE EMPTY | I31: =0 -> 0 | J31: NO | K31: =IF(I31=1,"ACCEPTED","OPEN") -> OPEN
A32: ="PKT-"&B32&"-CONFIGURATION" -> PKT-SUB-06-CONFIGURATION | B32: ='Object Crosswalk'!A12 -> SUB-06 | C32: ='Object Crosswalk'!B12 -> Civil substrate | D32: ='Object Crosswalk'!D12 -> MULTI | E32: ='Object Crosswalk'!E12 -> — | F32: ='Object Crosswalk'!F12 -> ROTATED | G32: CONFIGURATION | H32: SOURCE EMPTY | I32: =0 -> 0 | J32: NO | K32: =IF(I32=1,"ACCEPTED","OPEN") -> OPEN
A33: ="PKT-"&B33&"-CONTROL" -> PKT-SUB-06-CONTROL | B33: ='Object Crosswalk'!A12 -> SUB-06 | C33: ='Object Crosswalk'!B12 -> Civil substrate | D33: ='Object Crosswalk'!D12 -> MULTI | E33: ='Object Crosswalk'!E12 -> — | F33: ='Object Crosswalk'!F12 -> ROTATED | G33: CONTROL | H33: SOURCE EMPTY | I33: =0 -> 0 | J33: NO | K33: =IF(I33=1,"ACCEPTED","OPEN") -> OPEN
A34: ="PKT-"&B34&"-METROLOGY" -> PKT-SUB-06-METROLOGY | B34: ='Object Crosswalk'!A12 -> SUB-06 | C34: ='Object Crosswalk'!B12 -> Civil substrate | D34: ='Object Crosswalk'!D12 -> MULTI | E34: ='Object Crosswalk'!E12 -> — | F34: ='Object Crosswalk'!F12 -> ROTATED | G34: METROLOGY | H34: SOURCE EMPTY | I34: =0 -> 0 | J34: NO | K34: =IF(I34=1,"ACCEPTED","OPEN") -> OPEN
A35: ="PKT-"&B35&"-SAFETY" -> PKT-SUB-06-SAFETY | B35: ='Object Crosswalk'!A12 -> SUB-06 | C35: ='Object Crosswalk'!B12 -> Civil substrate | D35: ='Object Crosswalk'!D12 -> MULTI | E35: ='Object Crosswalk'!E12 -> — | F35: ='Object Crosswalk'!F12 -> ROTATED | G35: SAFETY | H35: SOURCE EMPTY | I35: =0 -> 0 | J35: NO | K35: =IF(I35=1,"ACCEPTED","OPEN") -> OPEN
A36: ="PKT-"&B36&"-RECONSTRUCTION" -> PKT-SUB-06-RECONSTRUCTION | B36: ='Object Crosswalk'!A12 -> SUB-06 | C36: ='Object Crosswalk'!B12 -> Civil substrate | D36: ='Object Crosswalk'!D12 -> MULTI | E36: ='Object Crosswalk'!E12 -> — | F36: ='Object Crosswalk'!F12 -> ROTATED | G36: RECONSTRUCTION | H36: SOURCE EMPTY | I36: =0 -> 0 | J36: NO | K36: =IF(I36=1,"ACCEPTED","OPEN") -> OPEN
A37: ="PKT-"&B37&"-CONFIGURATION" -> PKT-RIG-ET-CHA-CONFIGURATION | B37: ='Object Crosswalk'!A13 -> RIG-ET-CHA | C37: ='Object Crosswalk'!B13 -> Root-native rig | D37: ='Object Crosswalk'!D13 -> MS-ET | E37: ='Object Crosswalk'!E13 -> ET-A | F37: ='Object Crosswalk'!F13 -> CHALLENGE | G37: CONFIGURATION | H37: SOURCE EMPTY | I37: =0 -> 0 | J37: NO | K37: =IF(I37=1,"ACCEPTED","OPEN") -> OPEN
A38: ="PKT-"&B38&"-CONTROL" -> PKT-RIG-ET-CHA-CONTROL | B38: ='Object Crosswalk'!A13 -> RIG-ET-CHA | C38: ='Object Crosswalk'!B13 -> Root-native rig | D38: ='Object Crosswalk'!D13 -> MS-ET | E38: ='Object Crosswalk'!E13 -> ET-A | F38: ='Object Crosswalk'!F13 -> CHALLENGE | G38: CONTROL | H38: SOURCE EMPTY | I38: =0 -> 0 | J38: NO | K38: =IF(I38=1,"ACCEPTED","OPEN") -> OPEN
A39: ="PKT-"&B39&"-METROLOGY" -> PKT-RIG-ET-CHA-METROLOGY | B39: ='Object Crosswalk'!A13 -> RIG-ET-CHA | C39: ='Object Crosswalk'!B13 -> Root-native rig | D39: ='Object Crosswalk'!D13 -> MS-ET | E39: ='Object Crosswalk'!E13 -> ET-A | F39: ='Object Crosswalk'!F13 -> CHALLENGE | G39: METROLOGY | H39: SOURCE EMPTY | I39: =0 -> 0 | J39: NO | K39: =IF(I39=1,"ACCEPTED","OPEN") -> OPEN
A40: ="PKT-"&B40&"-SAFETY" -> PKT-RIG-ET-CHA-SAFETY | B40: ='Object Crosswalk'!A13 -> RIG-ET-CHA | C40: ='Object Crosswalk'!B13 -> Root-native rig | D40: ='Object Crosswalk'!D13 -> MS-ET | E40: ='Object Crosswalk'!E13 -> ET-A | F40: ='Object Crosswalk'!F13 -> CHALLENGE | G40: SAFETY | H40: SOURCE EMPTY | I40: =0 -> 0 | J40: NO | K40: =IF(I40=1,"ACCEPTED","OPEN") -> OPEN
A41: ="PKT-"&B41&"-RECONSTRUCTION" -> PKT-RIG-ET-CHA-RECONSTRUCTION | B41: ='Object Crosswalk'!A13 -> RIG-ET-CHA | C41: ='Object Crosswalk'!B13 -> Root-native rig | D41: ='Object Crosswalk'!D13 -> MS-ET | E41: ='Object Crosswalk'!E13 -> ET-A | F41: ='Object Crosswalk'!F13 -> CHALLENGE | G41: RECONSTRUCTION | H41: SOURCE EMPTY | I41: =0 -> 0 | J41: NO | K41: =IF(I41=1,"ACCEPTED","OPEN") -> OPEN
A42: ="PKT-"&B42&"-CONFIGURATION" -> PKT-MTH-ET-CHA-L1-CONFIGURATION | B42: ='Object Crosswalk'!A14 -> MTH-ET-CHA-L1 | C42: ='Object Crosswalk'!B14 -> Method lineage | D42: ='Object Crosswalk'!D14 -> MS-ET | E42: ='Object Crosswalk'!E14 -> ET-A | F42: ='Object Crosswalk'!F14 -> CHALLENGE | G42: CONFIGURATION | H42: SOURCE EMPTY | I42: =0 -> 0 | J42: NO | K42: =IF(I42=1,"ACCEPTED","OPEN") -> OPEN
A43: ="PKT-"&B43&"-CONTROL" -> PKT-MTH-ET-CHA-L1-CONTROL | B43: ='Object Crosswalk'!A14 -> MTH-ET-CHA-L1 | C43: ='Object Crosswalk'!B14 -> Method lineage | D43: ='Object Crosswalk'!D14 -> MS-ET | E43: ='Object Crosswalk'!E14 -> ET-A | F43: ='Object Crosswalk'!F14 -> CHALLENGE | G43: CONTROL | H43: SOURCE EMPTY | I43: =0 -> 0 | J43: NO | K43: =IF(I43=1,"ACCEPTED","OPEN") -> OPEN
A44: ="PKT-"&B44&"-METROLOGY" -> PKT-MTH-ET-CHA-L1-METROLOGY | B44: ='Object Crosswalk'!A14 -> MTH-ET-CHA-L1 | C44: ='Object Crosswalk'!B14 -> Method lineage | D44: ='Object Crosswalk'!D14 -> MS-ET | E44: ='Object Crosswalk'!E14 -> ET-A | F44: ='Object Crosswalk'!F14 -> CHALLENGE | G44: METROLOGY | H44: SOURCE EMPTY | I44: =0 -> 0 | J44: NO | K44: =IF(I44=1,"ACCEPTED","OPEN") -> OPEN
A45: ="PKT-"&B45&"-SAFETY" -> PKT-MTH-ET-CHA-L1-SAFETY | B45: ='Object Crosswalk'!A14 -> MTH-ET-CHA-L1 | C45: ='Object Crosswalk'!B14 -> Method lineage | D45: ='Object Crosswalk'!D14 -> MS-ET | E45: ='Object Crosswalk'!E14 -> ET-A | F45: ='Object Crosswalk'!F14 -> CHALLENGE | G45: SAFETY | H45: SOURCE EMPTY | I45: =0 -> 0 | J45: NO | K45: =IF(I45=1,"ACCEPTED","OPEN") -> OPEN
A46: ="PKT-"&B46&"-RECONSTRUCTION" -> PKT-MTH-ET-CHA-L1-RECONSTRUCTION | B46: ='Object Crosswalk'!A14 -> MTH-ET-CHA-L1 | C46: ='Object Crosswalk'!B14 -> Method lineage | D46: ='Object Crosswalk'!D14 -> MS-ET | E46: ='Object Crosswalk'!E14 -> ET-A | F46: ='Object Crosswalk'!F14 -> CHALLENGE | G46: RECONSTRUCTION | H46: SOURCE EMPTY | I46: =0 -> 0 | J46: NO | K46: =IF(I46=1,"ACCEPTED","OPEN") -> OPEN
A47: ="PKT-"&B47&"-CONFIGURATION" -> PKT-MTH-ET-CHA-L2-CONFIGURATION | B47: ='Object Crosswalk'!A15 -> MTH-ET-CHA-L2 | C47: ='Object Crosswalk'!B15 -> Method lineage | D47: ='Object Crosswalk'!D15 -> MS-ET | E47: ='Object Crosswalk'!E15 -> ET-A | F47: ='Object Crosswalk'!F15 -> CHALLENGE | G47: CONFIGURATION | H47: SOURCE EMPTY | I47: =0 -> 0 | J47: NO | K47: =IF(I47=1,"ACCEPTED","OPEN") -> OPEN
A48: ="PKT-"&B48&"-CONTROL" -> PKT-MTH-ET-CHA-L2-CONTROL | B48: ='Object Crosswalk'!A15 -> MTH-ET-CHA-L2 | C48: ='Object Crosswalk'!B15 -> Method lineage | D48: ='Object Crosswalk'!D15 -> MS-ET | E48: ='Object Crosswalk'!E15 -> ET-A | F48: ='Object Crosswalk'!F15 -> CHALLENGE | G48: CONTROL | H48: SOURCE EMPTY | I48: =0 -> 0 | J48: NO | K48: =IF(I48=1,"ACCEPTED","OPEN") -> OPEN
A49: ="PKT-"&B49&"-METROLOGY" -> PKT-MTH-ET-CHA-L2-METROLOGY | B49: ='Object Crosswalk'!A15 -> MTH-ET-CHA-L2 | C49: ='Object Crosswalk'!B15 -> Method lineage | D49: ='Object Crosswalk'!D15 -> MS-ET | E49: ='Object Crosswalk'!E15 -> ET-A | F49: ='Object Crosswalk'!F15 -> CHALLENGE | G49: METROLOGY | H49: SOURCE EMPTY | I49: =0 -> 0 | J49: NO | K49: =IF(I49=1,"ACCEPTED","OPEN") -> OPEN
A50: ="PKT-"&B50&"-SAFETY" -> PKT-MTH-ET-CHA-L2-SAFETY | B50: ='Object Crosswalk'!A15 -> MTH-ET-CHA-L2 | C50: ='Object Crosswalk'!B15 -> Method lineage | D50: ='Object Crosswalk'!D15 -> MS-ET | E50: ='Object Crosswalk'!E15 -> ET-A | F50: ='Object Crosswalk'!F15 -> CHALLENGE | G50: SAFETY | H50: SOURCE EMPTY | I50: =0 -> 0 | J50: NO | K50: =IF(I50=1,"ACCEPTED","OPEN") -> OPEN
A51: ="PKT-"&B51&"-RECONSTRUCTION" -> PKT-MTH-ET-CHA-L2-RECONSTRUCTION | B51: ='Object Crosswalk'!A15 -> MTH-ET-CHA-L2 | C51: ='Object Crosswalk'!B15 -> Method lineage | D51: ='Object Crosswalk'!D15 -> MS-ET | E51: ='Object Crosswalk'!E15 -> ET-A | F51: ='Object Crosswalk'!F15 -> CHALLENGE | G51: RECONSTRUCTION | H51: SOURCE EMPTY | I51: =0 -> 0 | J51: NO | K51: =IF(I51=1,"ACCEPTED","OPEN") -> OPEN
A52: ="PKT-"&B52&"-CONFIGURATION" -> PKT-REG-ET-CHA-CONFIGURATION | B52: ='Object Crosswalk'!A16 -> REG-ET-CHA | C52: ='Object Crosswalk'!B16 -> Regeneration tool | D52: ='Object Crosswalk'!D16 -> MS-ET | E52: ='Object Crosswalk'!E16 -> ET-A | F52: ='Object Crosswalk'!F16 -> CHALLENGE | G52: CONFIGURATION | H52: SOURCE EMPTY | I52: =0 -> 0 | J52: NO | K52: =IF(I52=1,"ACCEPTED","OPEN") -> OPEN
A53: ="PKT-"&B53&"-CONTROL" -> PKT-REG-ET-CHA-CONTROL | B53: ='Object Crosswalk'!A16 -> REG-ET-CHA | C53: ='Object Crosswalk'!B16 -> Regeneration tool | D53: ='Object Crosswalk'!D16 -> MS-ET | E53: ='Object Crosswalk'!E16 -> ET-A | F53: ='Object Crosswalk'!F16 -> CHALLENGE | G53: CONTROL | H53: SOURCE EMPTY | I53: =0 -> 0 | J53: NO | K53: =IF(I53=1,"ACCEPTED","OPEN") -> OPEN
A54: ="PKT-"&B54&"-METROLOGY" -> PKT-REG-ET-CHA-METROLOGY | B54: ='Object Crosswalk'!A16 -> REG-ET-CHA | C54: ='Object Crosswalk'!B16 -> Regeneration tool | D54: ='Object Crosswalk'!D16 -> MS-ET | E54: ='Object Crosswalk'!E16 -> ET-A | F54: ='Object Crosswalk'!F16 -> CHALLENGE | G54: METROLOGY | H54: SOURCE EMPTY | I54: =0 -> 0 | J54: NO | K54: =IF(I54=1,"ACCEPTED","OPEN") -> OPEN
A55: ="PKT-"&B55&"-SAFETY" -> PKT-REG-ET-CHA-SAFETY | B55: ='Object Crosswalk'!A16 -> REG-ET-CHA | C55: ='Object Crosswalk'!B16 -> Regeneration tool | D55: ='Object Crosswalk'!D16 -> MS-ET | E55: ='Object Crosswalk'!E16 -> ET-A | F55: ='Object Crosswalk'!F16 -> CHALLENGE | G55: SAFETY | H55: SOURCE EMPTY | I55: =0 -> 0 | J55: NO | K55: =IF(I55=1,"ACCEPTED","OPEN") -> OPEN
A56: ="PKT-"&B56&"-RECONSTRUCTION" -> PKT-REG-ET-CHA-RECONSTRUCTION | B56: ='Object Crosswalk'!A16 -> REG-ET-CHA | C56: ='Object Crosswalk'!B16 -> Regeneration tool | D56: ='Object Crosswalk'!D16 -> MS-ET | E56: ='Object Crosswalk'!E16 -> ET-A | F56: ='Object Crosswalk'!F16 -> CHALLENGE | G56: RECONSTRUCTION | H56: SOURCE EMPTY | I56: =0 -> 0 | J56: NO | K56: =IF(I56=1,"ACCEPTED","OPEN") -> OPEN
A57: ="PKT-"&B57&"-CONFIGURATION" -> PKT-INT-ET-CHA-CONFIGURATION | B57: ='Object Crosswalk'!A17 -> INT-ET-CHA | C57: ='Object Crosswalk'!B17 -> Station integration | D57: ='Object Crosswalk'!D17 -> MS-ET | E57: ='Object Crosswalk'!E17 -> ET-A | F57: ='Object Crosswalk'!F17 -> CHALLENGE | G57: CONFIGURATION | H57: SOURCE EMPTY | I57: =0 -> 0 | J57: NO | K57: =IF(I57=1,"ACCEPTED","OPEN") -> OPEN
A58: ="PKT-"&B58&"-CONTROL" -> PKT-INT-ET-CHA-CONTROL | B58: ='Object Crosswalk'!A17 -> INT-ET-CHA | C58: ='Object Crosswalk'!B17 -> Station integration | D58: ='Object Crosswalk'!D17 -> MS-ET | E58: ='Object Crosswalk'!E17 -> ET-A | F58: ='Object Crosswalk'!F17 -> CHALLENGE | G58: CONTROL | H58: SOURCE EMPTY | I58: =0 -> 0 | J58: NO | K58: =IF(I58=1,"ACCEPTED","OPEN") -> OPEN
A59: ="PKT-"&B59&"-METROLOGY" -> PKT-INT-ET-CHA-METROLOGY | B59: ='Object Crosswalk'!A17 -> INT-ET-CHA | C59: ='Object Crosswalk'!B17 -> Station integration | D59: ='Object Crosswalk'!D17 -> MS-ET | E59: ='Object Crosswalk'!E17 -> ET-A | F59: ='Object Crosswalk'!F17 -> CHALLENGE | G59: METROLOGY | H59: SOURCE EMPTY | I59: =0 -> 0 | J59: NO | K59: =IF(I59=1,"ACCEPTED","OPEN") -> OPEN
A60: ="PKT-"&B60&"-SAFETY" -> PKT-INT-ET-CHA-SAFETY | B60: ='Object Crosswalk'!A17 -> INT-ET-CHA | C60: ='Object Crosswalk'!B17 -> Station integration | D60: ='Object Crosswalk'!D17 -> MS-ET | E60: ='Object Crosswalk'!E17 -> ET-A | F60: ='Object Crosswalk'!F17 -> CHALLENGE | G60: SAFETY | H60: SOURCE EMPTY | I60: =0 -> 0 | J60: NO | K60: =IF(I60=1,"ACCEPTED","OPEN") -> OPEN
A61: ="PKT-"&B61&"-RECONSTRUCTION" -> PKT-INT-ET-CHA-RECONSTRUCTION | B61: ='Object Crosswalk'!A17 -> INT-ET-CHA | C61: ='Object Crosswalk'!B17 -> Station integration | D61: ='Object Crosswalk'!D17 -> MS-ET | E61: ='Object Crosswalk'!E17 -> ET-A | F61: ='Object Crosswalk'!F17 -> CHALLENGE | G61: RECONSTRUCTION | H61: SOURCE EMPTY | I61: =0 -> 0 | J61: NO | K61: =IF(I61=1,"ACCEPTED","OPEN") -> OPEN
A62: ="PKT-"&B62&"-CONFIGURATION" -> PKT-RIG-ET-CON-CONFIGURATION | B62: ='Object Crosswalk'!A18 -> RIG-ET-CON | C62: ='Object Crosswalk'!B18 -> Root-native rig | D62: ='Object Crosswalk'!D18 -> MS-ET | E62: ='Object Crosswalk'!E18 -> ET-A | F62: ='Object Crosswalk'!F18 -> CONTROL | G62: CONFIGURATION | H62: SOURCE EMPTY | I62: =0 -> 0 | J62: NO | K62: =IF(I62=1,"ACCEPTED","OPEN") -> OPEN
A63: ="PKT-"&B63&"-CONTROL" -> PKT-RIG-ET-CON-CONTROL | B63: ='Object Crosswalk'!A18 -> RIG-ET-CON | C63: ='Object Crosswalk'!B18 -> Root-native rig | D63: ='Object Crosswalk'!D18 -> MS-ET | E63: ='Object Crosswalk'!E18 -> ET-A | F63: ='Object Crosswalk'!F18 -> CONTROL | G63: CONTROL | H63: SOURCE EMPTY | I63: =0 -> 0 | J63: NO | K63: =IF(I63=1,"ACCEPTED","OPEN") -> OPEN
A64: ="PKT-"&B64&"-METROLOGY" -> PKT-RIG-ET-CON-METROLOGY | B64: ='Object Crosswalk'!A18 -> RIG-ET-CON | C64: ='Object Crosswalk'!B18 -> Root-native rig | D64: ='Object Crosswalk'!D18 -> MS-ET | E64: ='Object Crosswalk'!E18 -> ET-A | F64: ='Object Crosswalk'!F18 -> CONTROL | G64: METROLOGY | H64: SOURCE EMPTY | I64: =0 -> 0 | J64: NO | K64: =IF(I64=1,"ACCEPTED","OPEN") -> OPEN
A65: ="PKT-"&B65&"-SAFETY" -> PKT-RIG-ET-CON-SAFETY | B65: ='Object Crosswalk'!A18 -> RIG-ET-CON | C65: ='Object Crosswalk'!B18 -> Root-native rig | D65: ='Object Crosswalk'!D18 -> MS-ET | E65: ='Object Crosswalk'!E18 -> ET-A | F65: ='Object Crosswalk'!F18 -> CONTROL | G65: SAFETY | H65: SOURCE EMPTY | I65: =0 -> 0 | J65: NO | K65: =IF(I65=1,"ACCEPTED","OPEN") -> OPEN
A66: ="PKT-"&B66&"-RECONSTRUCTION" -> PKT-RIG-ET-CON-RECONSTRUCTION | B66: ='Object Crosswalk'!A18 -> RIG-ET-CON | C66: ='Object Crosswalk'!B18 -> Root-native rig | D66: ='Object Crosswalk'!D18 -> MS-ET | E66: ='Object Crosswalk'!E18 -> ET-A | F66: ='Object Crosswalk'!F18 -> CONTROL | G66: RECONSTRUCTION | H66: SOURCE EMPTY | I66: =0 -> 0 | J66: NO | K66: =IF(I66=1,"ACCEPTED","OPEN") -> OPEN
A67: ="PKT-"&B67&"-CONFIGURATION" -> PKT-MTH-ET-CON-L1-CONFIGURATION | B67: ='Object Crosswalk'!A19 -> MTH-ET-CON-L1 | C67: ='Object Crosswalk'!B19 -> Method lineage | D67: ='Object Crosswalk'!D19 -> MS-ET | E67: ='Object Crosswalk'!E19 -> ET-A | F67: ='Object Crosswalk'!F19 -> CONTROL | G67: CONFIGURATION | H67: SOURCE EMPTY | I67: =0 -> 0 | J67: NO | K67: =IF(I67=1,"ACCEPTED","OPEN") -> OPEN
A68: ="PKT-"&B68&"-CONTROL" -> PKT-MTH-ET-CON-L1-CONTROL | B68: ='Object Crosswalk'!A19 -> MTH-ET-CON-L1 | C68: ='Object Crosswalk'!B19 -> Method lineage | D68: ='Object Crosswalk'!D19 -> MS-ET | E68: ='Object Crosswalk'!E19 -> ET-A | F68: ='Object Crosswalk'!F19 -> CONTROL | G68: CONTROL | H68: SOURCE EMPTY | I68: =0 -> 0 | J68: NO | K68: =IF(I68=1,"ACCEPTED","OPEN") -> OPEN
A69: ="PKT-"&B69&"-METROLOGY" -> PKT-MTH-ET-CON-L1-METROLOGY | B69: ='Object Crosswalk'!A19 -> MTH-ET-CON-L1 | C69: ='Object Crosswalk'!B19 -> Method lineage | D69: ='Object Crosswalk'!D19 -> MS-ET | E69: ='Object Crosswalk'!E19 -> ET-A | F69: ='Object Crosswalk'!F19 -> CONTROL | G69: METROLOGY | H69: SOURCE EMPTY | I69: =0 -> 0 | J69: NO | K69: =IF(I69=1,"ACCEPTED","OPEN") -> OPEN
A70: ="PKT-"&B70&"-SAFETY" -> PKT-MTH-ET-CON-L1-SAFETY | B70: ='Object Crosswalk'!A19 -> MTH-ET-CON-L1 | C70: ='Object Crosswalk'!B19 -> Method lineage | D70: ='Object Crosswalk'!D19 -> MS-ET | E70: ='Object Crosswalk'!E19 -> ET-A | F70: ='Object Crosswalk'!F19 -> CONTROL | G70: SAFETY | H70: SOURCE EMPTY | I70: =0 -> 0 | J70: NO | K70: =IF(I70=1,"ACCEPTED","OPEN") -> OPEN
A71: ="PKT-"&B71&"-RECONSTRUCTION" -> PKT-MTH-ET-CON-L1-RECONSTRUCTION | B71: ='Object Crosswalk'!A19 -> MTH-ET-CON-L1 | C71: ='Object Crosswalk'!B19 -> Method lineage | D71: ='Object Crosswalk'!D19 -> MS-ET | E71: ='Object Crosswalk'!E19 -> ET-A | F71: ='Object Crosswalk'!F19 -> CONTROL | G71: RECONSTRUCTION | H71: SOURCE EMPTY | I71: =0 -> 0 | J71: NO | K71: =IF(I71=1,"ACCEPTED","OPEN") -> OPEN
A72: ="PKT-"&B72&"-CONFIGURATION" -> PKT-MTH-ET-CON-L2-CONFIGURATION | B72: ='Object Crosswalk'!A20 -> MTH-ET-CON-L2 | C72: ='Object Crosswalk'!B20 -> Method lineage | D72: ='Object Crosswalk'!D20 -> MS-ET | E72: ='Object Crosswalk'!E20 -> ET-A | F72: ='Object Crosswalk'!F20 -> CONTROL | G72: CONFIGURATION | H72: SOURCE EMPTY | I72: =0 -> 0 | J72: NO | K72: =IF(I72=1,"ACCEPTED","OPEN") -> OPEN
A73: ="PKT-"&B73&"-CONTROL" -> PKT-MTH-ET-CON-L2-CONTROL | B73: ='Object Crosswalk'!A20 -> MTH-ET-CON-L2 | C73: ='Object Crosswalk'!B20 -> Method lineage | D73: ='Object Crosswalk'!D20 -> MS-ET | E73: ='Object Crosswalk'!E20 -> ET-A | F73: ='Object Crosswalk'!F20 -> CONTROL | G73: CONTROL | H73: SOURCE EMPTY | I73: =0 -> 0 | J73: NO | K73: =IF(I73=1,"ACCEPTED","OPEN") -> OPEN
A74: ="PKT-"&B74&"-METROLOGY" -> PKT-MTH-ET-CON-L2-METROLOGY | B74: ='Object Crosswalk'!A20 -> MTH-ET-CON-L2 | C74: ='Object Crosswalk'!B20 -> Method lineage | D74: ='Object Crosswalk'!D20 -> MS-ET | E74: ='Object Crosswalk'!E20 -> ET-A | F74: ='Object Crosswalk'!F20 -> CONTROL | G74: METROLOGY | H74: SOURCE EMPTY | I74: =0 -> 0 | J74: NO | K74: =IF(I74=1,"ACCEPTED","OPEN") -> OPEN
A75: ="PKT-"&B75&"-SAFETY" -> PKT-MTH-ET-CON-L2-SAFETY | B75: ='Object Crosswalk'!A20 -> MTH-ET-CON-L2 | C75: ='Object Crosswalk'!B20 -> Method lineage | D75: ='Object Crosswalk'!D20 -> MS-ET | E75: ='Object Crosswalk'!E20 -> ET-A | F75: ='Object Crosswalk'!F20 -> CONTROL | G75: SAFETY | H75: SOURCE EMPTY | I75: =0 -> 0 | J75: NO | K75: =IF(I75=1,"ACCEPTED","OPEN") -> OPEN
A76: ="PKT-"&B76&"-RECONSTRUCTION" -> PKT-MTH-ET-CON-L2-RECONSTRUCTION | B76: ='Object Crosswalk'!A20 -> MTH-ET-CON-L2 | C76: ='Object Crosswalk'!B20 -> Method lineage | D76: ='Object Crosswalk'!D20 -> MS-ET | E76: ='Object Crosswalk'!E20 -> ET-A | F76: ='Object Crosswalk'!F20 -> CONTROL | G76: RECONSTRUCTION | H76: SOURCE EMPTY | I76: =0 -> 0 | J76: NO | K76: =IF(I76=1,"ACCEPTED","OPEN") -> OPEN
A77: ="PKT-"&B77&"-CONFIGURATION" -> PKT-REG-ET-CON-CONFIGURATION | B77: ='Object Crosswalk'!A21 -> REG-ET-CON | C77: ='Object Crosswalk'!B21 -> Regeneration tool | D77: ='Object Crosswalk'!D21 -> MS-ET | E77: ='Object Crosswalk'!E21 -> ET-A | F77: ='Object Crosswalk'!F21 -> CONTROL | G77: CONFIGURATION | H77: SOURCE EMPTY | I77: =0 -> 0 | J77: NO | K77: =IF(I77=1,"ACCEPTED","OPEN") -> OPEN
A78: ="PKT-"&B78&"-CONTROL" -> PKT-REG-ET-CON-CONTROL | B78: ='Object Crosswalk'!A21 -> REG-ET-CON | C78: ='Object Crosswalk'!B21 -> Regeneration tool | D78: ='Object Crosswalk'!D21 -> MS-ET | E78: ='Object Crosswalk'!E21 -> ET-A | F78: ='Object Crosswalk'!F21 -> CONTROL | G78: CONTROL | H78: SOURCE EMPTY | I78: =0 -> 0 | J78: NO | K78: =IF(I78=1,"ACCEPTED","OPEN") -> OPEN
A79: ="PKT-"&B79&"-METROLOGY" -> PKT-REG-ET-CON-METROLOGY | B79: ='Object Crosswalk'!A21 -> REG-ET-CON | C79: ='Object Crosswalk'!B21 -> Regeneration tool | D79: ='Object Crosswalk'!D21 -> MS-ET | E79: ='Object Crosswalk'!E21 -> ET-A | F79: ='Object Crosswalk'!F21 -> CONTROL | G79: METROLOGY | H79: SOURCE EMPTY | I79: =0 -> 0 | J79: NO | K79: =IF(I79=1,"ACCEPTED","OPEN") -> OPEN
A80: ="PKT-"&B80&"-SAFETY" -> PKT-REG-ET-CON-SAFETY | B80: ='Object Crosswalk'!A21 -> REG-ET-CON | C80: ='Object Crosswalk'!B21 -> Regeneration tool | D80: ='Object Crosswalk'!D21 -> MS-ET | E80: ='Object Crosswalk'!E21 -> ET-A | F80: ='Object Crosswalk'!F21 -> CONTROL | G80: SAFETY | H80: SOURCE EMPTY | I80: =0 -> 0 | J80: NO | K80: =IF(I80=1,"ACCEPTED","OPEN") -> OPEN
A81: ="PKT-"&B81&"-RECONSTRUCTION" -> PKT-REG-ET-CON-RECONSTRUCTION | B81: ='Object Crosswalk'!A21 -> REG-ET-CON | C81: ='Object Crosswalk'!B21 -> Regeneration tool | D81: ='Object Crosswalk'!D21 -> MS-ET | E81: ='Object Crosswalk'!E21 -> ET-A | F81: ='Object Crosswalk'!F21 -> CONTROL | G81: RECONSTRUCTION | H81: SOURCE EMPTY | I81: =0 -> 0 | J81: NO | K81: =IF(I81=1,"ACCEPTED","OPEN") -> OPEN
A82: ="PKT-"&B82&"-CONFIGURATION" -> PKT-INT-ET-CON-CONFIGURATION | B82: ='Object Crosswalk'!A22 -> INT-ET-CON | C82: ='Object Crosswalk'!B22 -> Station integration | D82: ='Object Crosswalk'!D22 -> MS-ET | E82: ='Object Crosswalk'!E22 -> ET-A | F82: ='Object Crosswalk'!F22 -> CONTROL | G82: CONFIGURATION | H82: SOURCE EMPTY | I82: =0 -> 0 | J82: NO | K82: =IF(I82=1,"ACCEPTED","OPEN") -> OPEN
A83: ="PKT-"&B83&"-CONTROL" -> PKT-INT-ET-CON-CONTROL | B83: ='Object Crosswalk'!A22 -> INT-ET-CON | C83: ='Object Crosswalk'!B22 -> Station integration | D83: ='Object Crosswalk'!D22 -> MS-ET | E83: ='Object Crosswalk'!E22 -> ET-A | F83: ='Object Crosswalk'!F22 -> CONTROL | G83: CONTROL | H83: SOURCE EMPTY | I83: =0 -> 0 | J83: NO | K83: =IF(I83=1,"ACCEPTED","OPEN") -> OPEN
A84: ="PKT-"&B84&"-METROLOGY" -> PKT-INT-ET-CON-METROLOGY | B84: ='Object Crosswalk'!A22 -> INT-ET-CON | C84: ='Object Crosswalk'!B22 -> Station integration | D84: ='Object Crosswalk'!D22 -> MS-ET | E84: ='Object Crosswalk'!E22 -> ET-A | F84: ='Object Crosswalk'!F22 -> CONTROL | G84: METROLOGY | H84: SOURCE EMPTY | I84: =0 -> 0 | J84: NO | K84: =IF(I84=1,"ACCEPTED","OPEN") -> OPEN
A85: ="PKT-"&B85&"-SAFETY" -> PKT-INT-ET-CON-SAFETY | B85: ='Object Crosswalk'!A22 -> INT-ET-CON | C85: ='Object Crosswalk'!B22 -> Station integration | D85: ='Object Crosswalk'!D22 -> MS-ET | E85: ='Object Crosswalk'!E22 -> ET-A | F85: ='Object Crosswalk'!F22 -> CONTROL | G85: SAFETY | H85: SOURCE EMPTY | I85: =0 -> 0 | J85: NO | K85: =IF(I85=1,"ACCEPTED","OPEN") -> OPEN
A86: ="PKT-"&B86&"-RECONSTRUCTION" -> PKT-INT-ET-CON-RECONSTRUCTION | B86: ='Object Crosswalk'!A22 -> INT-ET-CON | C86: ='Object Crosswalk'!B22 -> Station integration | D86: ='Object Crosswalk'!D22 -> MS-ET | E86: ='Object Crosswalk'!E22 -> ET-A | F86: ='Object Crosswalk'!F22 -> CONTROL | G86: RECONSTRUCTION | H86: SOURCE EMPTY | I86: =0 -> 0 | J86: NO | K86: =IF(I86=1,"ACCEPTED","OPEN") -> OPEN
A87: ="PKT-"&B87&"-CONFIGURATION" -> PKT-RIG-ET-REC-CONFIGURATION | B87: ='Object Crosswalk'!A23 -> RIG-ET-REC | C87: ='Object Crosswalk'!B23 -> Root-native rig | D87: ='Object Crosswalk'!D23 -> MS-ET | E87: ='Object Crosswalk'!E23 -> ET-A | F87: ='Object Crosswalk'!F23 -> RECONSTRUCTION | G87: CONFIGURATION | H87: SOURCE EMPTY | I87: =0 -> 0 | J87: NO | K87: =IF(I87=1,"ACCEPTED","OPEN") -> OPEN
A88: ="PKT-"&B88&"-CONTROL" -> PKT-RIG-ET-REC-CONTROL | B88: ='Object Crosswalk'!A23 -> RIG-ET-REC | C88: ='Object Crosswalk'!B23 -> Root-native rig | D88: ='Object Crosswalk'!D23 -> MS-ET | E88: ='Object Crosswalk'!E23 -> ET-A | F88: ='Object Crosswalk'!F23 -> RECONSTRUCTION | G88: CONTROL | H88: SOURCE EMPTY | I88: =0 -> 0 | J88: NO | K88: =IF(I88=1,"ACCEPTED","OPEN") -> OPEN
A89: ="PKT-"&B89&"-METROLOGY" -> PKT-RIG-ET-REC-METROLOGY | B89: ='Object Crosswalk'!A23 -> RIG-ET-REC | C89: ='Object Crosswalk'!B23 -> Root-native rig | D89: ='Object Crosswalk'!D23 -> MS-ET | E89: ='Object Crosswalk'!E23 -> ET-A | F89: ='Object Crosswalk'!F23 -> RECONSTRUCTION | G89: METROLOGY | H89: SOURCE EMPTY | I89: =0 -> 0 | J89: NO | K89: =IF(I89=1,"ACCEPTED","OPEN") -> OPEN
A90: ="PKT-"&B90&"-SAFETY" -> PKT-RIG-ET-REC-SAFETY | B90: ='Object Crosswalk'!A23 -> RIG-ET-REC | C90: ='Object Crosswalk'!B23 -> Root-native rig | D90: ='Object Crosswalk'!D23 -> MS-ET | E90: ='Object Crosswalk'!E23 -> ET-A | F90: ='Object Crosswalk'!F23 -> RECONSTRUCTION | G90: SAFETY | H90: SOURCE EMPTY | I90: =0 -> 0 | J90: NO | K90: =IF(I90=1,"ACCEPTED","OPEN") -> OPEN
A91: ="PKT-"&B91&"-RECONSTRUCTION" -> PKT-RIG-ET-REC-RECONSTRUCTION | B91: ='Object Crosswalk'!A23 -> RIG-ET-REC | C91: ='Object Crosswalk'!B23 -> Root-native rig | D91: ='Object Crosswalk'!D23 -> MS-ET | E91: ='Object Crosswalk'!E23 -> ET-A | F91: ='Object Crosswalk'!F23 -> RECONSTRUCTION | G91: RECONSTRUCTION | H91: SOURCE EMPTY | I91: =0 -> 0 | J91: NO | K91: =IF(I91=1,"ACCEPTED","OPEN") -> OPEN
A92: ="PKT-"&B92&"-CONFIGURATION" -> PKT-MTH-ET-REC-L1-CONFIGURATION | B92: ='Object Crosswalk'!A24 -> MTH-ET-REC-L1 | C92: ='Object Crosswalk'!B24 -> Method lineage | D92: ='Object Crosswalk'!D24 -> MS-ET | E92: ='Object Crosswalk'!E24 -> ET-A | F92: ='Object Crosswalk'!F24 -> RECONSTRUCTION | G92: CONFIGURATION | H92: SOURCE EMPTY | I92: =0 -> 0 | J92: NO | K92: =IF(I92=1,"ACCEPTED","OPEN") -> OPEN
A93: ="PKT-"&B93&"-CONTROL" -> PKT-MTH-ET-REC-L1-CONTROL | B93: ='Object Crosswalk'!A24 -> MTH-ET-REC-L1 | C93: ='Object Crosswalk'!B24 -> Method lineage | D93: ='Object Crosswalk'!D24 -> MS-ET | E93: ='Object Crosswalk'!E24 -> ET-A | F93: ='Object Crosswalk'!F24 -> RECONSTRUCTION | G93: CONTROL | H93: SOURCE EMPTY | I93: =0 -> 0 | J93: NO | K93: =IF(I93=1,"ACCEPTED","OPEN") -> OPEN
A94: ="PKT-"&B94&"-METROLOGY" -> PKT-MTH-ET-REC-L1-METROLOGY | B94: ='Object Crosswalk'!A24 -> MTH-ET-REC-L1 | C94: ='Object Crosswalk'!B24 -> Method lineage | D94: ='Object Crosswalk'!D24 -> MS-ET | E94: ='Object Crosswalk'!E24 -> ET-A | F94: ='Object Crosswalk'!F24 -> RECONSTRUCTION | G94: METROLOGY | H94: SOURCE EMPTY | I94: =0 -> 0 | J94: NO | K94: =IF(I94=1,"ACCEPTED","OPEN") -> OPEN
A95: ="PKT-"&B95&"-SAFETY" -> PKT-MTH-ET-REC-L1-SAFETY | B95: ='Object Crosswalk'!A24 -> MTH-ET-REC-L1 | C95: ='Object Crosswalk'!B24 -> Method lineage | D95: ='Object Crosswalk'!D24 -> MS-ET | E95: ='Object Crosswalk'!E24 -> ET-A | F95: ='Object Crosswalk'!F24 -> RECONSTRUCTION | G95: SAFETY | H95: SOURCE EMPTY | I95: =0 -> 0 | J95: NO | K95: =IF(I95=1,"ACCEPTED","OPEN") -> OPEN
A96: ="PKT-"&B96&"-RECONSTRUCTION" -> PKT-MTH-ET-REC-L1-RECONSTRUCTION | B96: ='Object Crosswalk'!A24 -> MTH-ET-REC-L1 | C96: ='Object Crosswalk'!B24 -> Method lineage | D96: ='Object Crosswalk'!D24 -> MS-ET | E96: ='Object Crosswalk'!E24 -> ET-A | F96: ='Object Crosswalk'!F24 -> RECONSTRUCTION | G96: RECONSTRUCTION | H96: SOURCE EMPTY | I96: =0 -> 0 | J96: NO | K96: =IF(I96=1,"ACCEPTED","OPEN") -> OPEN
A97: ="PKT-"&B97&"-CONFIGURATION" -> PKT-MTH-ET-REC-L2-CONFIGURATION | B97: ='Object Crosswalk'!A25 -> MTH-ET-REC-L2 | C97: ='Object Crosswalk'!B25 -> Method lineage | D97: ='Object Crosswalk'!D25 -> MS-ET | E97: ='Object Crosswalk'!E25 -> ET-A | F97: ='Object Crosswalk'!F25 -> RECONSTRUCTION | G97: CONFIGURATION | H97: SOURCE EMPTY | I97: =0 -> 0 | J97: NO | K97: =IF(I97=1,"ACCEPTED","OPEN") -> OPEN
A98: ="PKT-"&B98&"-CONTROL" -> PKT-MTH-ET-REC-L2-CONTROL | B98: ='Object Crosswalk'!A25 -> MTH-ET-REC-L2 | C98: ='Object Crosswalk'!B25 -> Method lineage | D98: ='Object Crosswalk'!D25 -> MS-ET | E98: ='Object Crosswalk'!E25 -> ET-A | F98: ='Object Crosswalk'!F25 -> RECONSTRUCTION | G98: CONTROL | H98: SOURCE EMPTY | I98: =0 -> 0 | J98: NO | K98: =IF(I98=1,"ACCEPTED","OPEN") -> OPEN
A99: ="PKT-"&B99&"-METROLOGY" -> PKT-MTH-ET-REC-L2-METROLOGY | B99: ='Object Crosswalk'!A25 -> MTH-ET-REC-L2 | C99: ='Object Crosswalk'!B25 -> Method lineage | D99: ='Object Crosswalk'!D25 -> MS-ET | E99: ='Object Crosswalk'!E25 -> ET-A | F99: ='Object Crosswalk'!F25 -> RECONSTRUCTION | G99: METROLOGY | H99: SOURCE EMPTY | I99: =0 -> 0 | J99: NO | K99: =IF(I99=1,"ACCEPTED","OPEN") -> OPEN
A100: ="PKT-"&B100&"-SAFETY" -> PKT-MTH-ET-REC-L2-SAFETY | B100: ='Object Crosswalk'!A25 -> MTH-ET-REC-L2 | C100: ='Object Crosswalk'!B25 -> Method lineage | D100: ='Object Crosswalk'!D25 -> MS-ET | E100: ='Object Crosswalk'!E25 -> ET-A | F100: ='Object Crosswalk'!F25 -> RECONSTRUCTION | G100: SAFETY | H100: SOURCE EMPTY | I100: =0 -> 0 | J100: NO | K100: =IF(I100=1,"ACCEPTED","OPEN") -> OPEN
A101: ="PKT-"&B101&"-RECONSTRUCTION" -> PKT-MTH-ET-REC-L2-RECONSTRUCTION | B101: ='Object Crosswalk'!A25 -> MTH-ET-REC-L2 | C101: ='Object Crosswalk'!B25 -> Method lineage | D101: ='Object Crosswalk'!D25 -> MS-ET | E101: ='Object Crosswalk'!E25 -> ET-A | F101: ='Object Crosswalk'!F25 -> RECONSTRUCTION | G101: RECONSTRUCTION | H101: SOURCE EMPTY | I101: =0 -> 0 | J101: NO | K101: =IF(I101=1,"ACCEPTED","OPEN") -> OPEN
A102: ="PKT-"&B102&"-CONFIGURATION" -> PKT-REG-ET-REC-CONFIGURATION | B102: ='Object Crosswalk'!A26 -> REG-ET-REC | C102: ='Object Crosswalk'!B26 -> Regeneration tool | D102: ='Object Crosswalk'!D26 -> MS-ET | E102: ='Object Crosswalk'!E26 -> ET-A | F102: ='Object Crosswalk'!F26 -> RECONSTRUCTION | G102: CONFIGURATION | H102: SOURCE EMPTY | I102: =0 -> 0 | J102: NO | K102: =IF(I102=1,"ACCEPTED","OPEN") -> OPEN
A103: ="PKT-"&B103&"-CONTROL" -> PKT-REG-ET-REC-CONTROL | B103: ='Object Crosswalk'!A26 -> REG-ET-REC | C103: ='Object Crosswalk'!B26 -> Regeneration tool | D103: ='Object Crosswalk'!D26 -> MS-ET | E103: ='Object Crosswalk'!E26 -> ET-A | F103: ='Object Crosswalk'!F26 -> RECONSTRUCTION | G103: CONTROL | H103: SOURCE EMPTY | I103: =0 -> 0 | J103: NO | K103: =IF(I103=1,"ACCEPTED","OPEN") -> OPEN
...

Sheet Event Evidence
A2: Three hundred sixty event-evidence package references
A4: Five evidence packages accompany each of seventy-two valid-event positions. All observations, validity and outcomes remain source empty.
A6: Package | B6: Event | C6: System | D6: Root | E6: Endpoint | F6: Role | G6: Lineage | H6: Evidence plane | I6: Observation identity | J6: Validity | K6: Outcome | L6: State
A7: EVD-EV-ET-BAL-CHA-L1-EVENT | B7: EV-ET-BAL-CHA-L1 | C7: MS-ET | D7: ET-A | E7: BALANCE | F7: CHALLENGE | G7: L1 | H7: EVENT INTEGRITY | I7: SOURCE EMPTY | J7: SOURCE EMPTY | K7: SOURCE EMPTY | L7: =IF(J7="VALID","ADJUDICATE","OPEN") -> OPEN
A8: EVD-EV-ET-BAL-CHA-L1-MECHANISM | B8: EV-ET-BAL-CHA-L1 | C8: MS-ET | D8: ET-A | E8: BALANCE | F8: CHALLENGE | G8: L1 | H8: MECHANISM | I8: SOURCE EMPTY | J8: SOURCE EMPTY | K8: SOURCE EMPTY | L8: =IF(J8="VALID","ADJUDICATE","OPEN") -> OPEN
A9: EVD-EV-ET-BAL-CHA-L1-PUBLIC | B9: EV-ET-BAL-CHA-L1 | C9: MS-ET | D9: ET-A | E9: BALANCE | F9: CHALLENGE | G9: L1 | H9: PUBLIC EFFECT | I9: SOURCE EMPTY | J9: SOURCE EMPTY | K9: SOURCE EMPTY | L9: =IF(J9="VALID","ADJUDICATE","OPEN") -> OPEN
A10: EVD-EV-ET-BAL-CHA-L1-RIGHTS | B10: EV-ET-BAL-CHA-L1 | C10: MS-ET | D10: ET-A | E10: BALANCE | F10: CHALLENGE | G10: L1 | H10: RIGHTS / RESIDUAL | I10: SOURCE EMPTY | J10: SOURCE EMPTY | K10: SOURCE EMPTY | L10: =IF(J10="VALID","ADJUDICATE","OPEN") -> OPEN
A11: EVD-EV-ET-BAL-CHA-L1-CUSTODY | B11: EV-ET-BAL-CHA-L1 | C11: MS-ET | D11: ET-A | E11: BALANCE | F11: CHALLENGE | G11: L1 | H11: CUSTODY / REPLAY | I11: SOURCE EMPTY | J11: SOURCE EMPTY | K11: SOURCE EMPTY | L11: =IF(J11="VALID","ADJUDICATE","OPEN") -> OPEN
A12: EVD-EV-ET-BAL-CHA-L2-EVENT | B12: EV-ET-BAL-CHA-L2 | C12: MS-ET | D12: ET-A | E12: BALANCE | F12: CHALLENGE | G12: L2 | H12: EVENT INTEGRITY | I12: SOURCE EMPTY | J12: SOURCE EMPTY | K12: SOURCE EMPTY | L12: =IF(J12="VALID","ADJUDICATE","OPEN") -> OPEN
A13: EVD-EV-ET-BAL-CHA-L2-MECHANISM | B13: EV-ET-BAL-CHA-L2 | C13: MS-ET | D13: ET-A | E13: BALANCE | F13: CHALLENGE | G13: L2 | H13: MECHANISM | I13: SOURCE EMPTY | J13: SOURCE EMPTY | K13: SOURCE EMPTY | L13: =IF(J13="VALID","ADJUDICATE","OPEN") -> OPEN
A14: EVD-EV-ET-BAL-CHA-L2-PUBLIC | B14: EV-ET-BAL-CHA-L2 | C14: MS-ET | D14: ET-A | E14: BALANCE | F14: CHALLENGE | G14: L2 | H14: PUBLIC EFFECT | I14: SOURCE EMPTY | J14: SOURCE EMPTY | K14: SOURCE EMPTY | L14: =IF(J14="VALID","ADJUDICATE","OPEN") -> OPEN
A15: EVD-EV-ET-BAL-CHA-L2-RIGHTS | B15: EV-ET-BAL-CHA-L2 | C15: MS-ET | D15: ET-A | E15: BALANCE | F15: CHALLENGE | G15: L2 | H15: RIGHTS / RESIDUAL | I15: SOURCE EMPTY | J15: SOURCE EMPTY | K15: SOURCE EMPTY | L15: =IF(J15="VALID","ADJUDICATE","OPEN") -> OPEN
A16: EVD-EV-ET-BAL-CHA-L2-CUSTODY | B16: EV-ET-BAL-CHA-L2 | C16: MS-ET | D16: ET-A | E16: BALANCE | F16: CHALLENGE | G16: L2 | H16: CUSTODY / REPLAY | I16: SOURCE EMPTY | J16: SOURCE EMPTY | K16: SOURCE EMPTY | L16: =IF(J16="VALID","ADJUDICATE","OPEN") -> OPEN
A17: EVD-EV-ET-BAL-CON-L1-EVENT | B17: EV-ET-BAL-CON-L1 | C17: MS-ET | D17: ET-A | E17: BALANCE | F17: CONTROL | G17: L1 | H17: EVENT INTEGRITY | I17: SOURCE EMPTY | J17: SOURCE EMPTY | K17: SOURCE EMPTY | L17: =IF(J17="VALID","ADJUDICATE","OPEN") -> OPEN
A18: EVD-EV-ET-BAL-CON-L1-MECHANISM | B18: EV-ET-BAL-CON-L1 | C18: MS-ET | D18: ET-A | E18: BALANCE | F18: CONTROL | G18: L1 | H18: MECHANISM | I18: SOURCE EMPTY | J18: SOURCE EMPTY | K18: SOURCE EMPTY | L18: =IF(J18="VALID","ADJUDICATE","OPEN") -> OPEN
... A366: EVD-EV-RT-KEY-REC-L2-CUSTODY | B366: EV-RT-KEY-REC-L2 | C366: MS-RT | D366: RT-B | E366: KEYSTONE | F366: RECONSTRUCTION | G366: L2 | H366: CUSTODY / REPLAY | I366: SOURCE EMPTY | J366: SOURCE EMPTY | K366: SOURCE EMPTY | L366: =IF(J366="VALID","ADJUDICATE","OPEN") -> OPEN

Sheet Finance
A2: Conserved USD 15.6B authority and stage exposure
A4: Public and private accounts are exclusive and add once. No nested reserve, site or test value is added again.
A6: Code | B6: Class | C6: Funding | D6: Lots | E6: Authority USD B | F6: FRAME % | G6: MAKE % | H6: BREAK % | I6: TRANSFER % | J6: Through MAKE USD B | K6: Through BREAK USD B | L6: Unreleased after BREAK
A7: SUB | B7: Civil substrate | C7: Public | D7: 6 | E7: 0.72 | F7: 0.25 | G7: 0.5 | H7: 0 | I7: 0.25 | J7: =E7*(F7+G7) -> 0.54 | K7: =E7*(F7+G7+H7) -> 0.54 | L7: =E7-K7 -> 0.18
A8: RIG | B8: Root-native rig | C8: Public | D8: 18 | E8: 5.7 | F8: 0.25 | G8: 0.5 | H8: 0 | I8: 0.25 | J8: =E8*(F8+G8) -> 4.275 | K8: =E8*(F8+G8+H8) -> 4.275 | L8: =E8-K8 -> 1.425
A9: MTH | B9: Method lineage | C9: Public | D9: 36 | E9: 3.24 | F9: 0.25 | G9: 0.5 | H9: 0 | I9: 0.25 | J9: =E9*(F9+G9) -> 2.43 | K9: =E9*(F9+G9+H9) -> 2.43 | L9: =E9-K9 -> 0.81
A10: REG | B10: Regeneration tool | C10: Public | D10: 18 | E10: 1.2 | F10: 0.25 | G10: 0.5 | H10: 0 | I10: 0.25 | J10: =E10*(F10+G10) -> 0.9 | K10: =E10*(F10+G10+H10) -> 0.9 | L10: =E10-K10 -> 0.3
A11: INT | B11: Station integration | C11: Public | D11: 18 | E11: 1.14 | F11: 0.25 | G11: 0.5 | H11: 0 | I11: 0.25 | J11: =E11*(F11+G11) -> 0.855 | K11: =E11*(F11+G11+H11) -> 0.855 | L11: =E11-K11 -> 0.285
A12: CAN | B12: Candidate mechanism | C12: Private option | D12: 6 | E12: 3.5869128 | F12: 0.15 | G12: 0.35 | H12: 0.35 | I12: 0.15 | J12: =E12*(F12+G12) -> 1.7934564 | K12: =E12*(F12+G12+H12) -> 3.0488759 | L12: =E12-K12 -> 0.53803692
A13: TOTAL | B13: six classes | C13: mixed | D13: =SUM(D7:D12) -> 102 | E13: =SUM(E7:E12) -> 15.586913 | J13: =SUM(J7:J12) -> 10.793456 | K13: =SUM(K7:K12) -> 12.048876 | L13: =SUM(L7:L12) -> 3.5380369

Sheet Payment Ledger
A2: Four hundred eight lot-stage payment records
A4: A stage ceiling is payable only against its own accepted artifact. Zero obligations and payments are deliberate current states.
A6: Record | B6: Lot | C6: Class | D6: Funding | E6: System | F6: Root | G6: Stage | H6: Stage % | I6: Lot ceiling USD B | J6: Stage ceiling USD B | K6: Accepted | L6: Obligation USD B | M6: Payment USD B | N6: State
A7: ="PAY-"&B7&"-FRAME" -> PAY-SUB-01-FRAME | B7: ='Object Crosswalk'!A7 -> SUB-01 | C7: ='Object Crosswalk'!B7 -> Civil substrate | D7: ='Object Crosswalk'!C7 -> Public | E7: ='Object Crosswalk'!D7 -> MULTI | F7: ='Object Crosswalk'!E7 -> — | G7: FRAME | H7: 0.25 | I7: ='Object Crosswalk'!I7 -> 0.12 | J7: =H7*I7 -> 0.03 | K7: =0 -> 0 | L7: =Controls!B35 -> 0 | M7: =Controls!B36 -> 0 | N7: =IF(M7>0,"PAID","HELD") -> HELD
A8: ="PAY-"&B8&"-MAKE" -> PAY-SUB-01-MAKE | B8: ='Object Crosswalk'!A7 -> SUB-01 | C8: ='Object Crosswalk'!B7 -> Civil substrate | D8: ='Object Crosswalk'!C7 -> Public | E8: ='Object Crosswalk'!D7 -> MULTI | F8: ='Object Crosswalk'!E7 -> — | G8: MAKE | H8: 0.5 | I8: ='Object Crosswalk'!I7 -> 0.12 | J8: =H8*I8 -> 0.06 | K8: =0 -> 0 | L8: =Controls!B35 -> 0 | M8: =Controls!B36 -> 0 | N8: =IF(M8>0,"PAID","HELD") -> HELD
A9: ="PAY-"&B9&"-BREAK" -> PAY-SUB-01-BREAK | B9: ='Object Crosswalk'!A7 -> SUB-01 | C9: ='Object Crosswalk'!B7 -> Civil substrate | D9: ='Object Crosswalk'!C7 -> Public | E9: ='Object Crosswalk'!D7 -> MULTI | F9: ='Object Crosswalk'!E7 -> — | G9: BREAK | H9: 0 | I9: ='Object Crosswalk'!I7 -> 0.12 | J9: =H9*I9 -> 0 | K9: =0 -> 0 | L9: =Controls!B35 -> 0 | M9: =Controls!B36 -> 0 | N9: =IF(M9>0,"PAID","HELD") -> HELD
A10: ="PAY-"&B10&"-TRANSFER" -> PAY-SUB-01-TRANSFER | B10: ='Object Crosswalk'!A7 -> SUB-01 | C10: ='Object Crosswalk'!B7 -> Civil substrate | D10: ='Object Crosswalk'!C7 -> Public | E10: ='Object Crosswalk'!D7 -> MULTI | F10: ='Object Crosswalk'!E7 -> — | G10: TRANSFER | H10: 0.25 | I10: ='Object Crosswalk'!I7 -> 0.12 | J10: =H10*I10 -> 0.03 | K10: =0 -> 0 | L10: =Controls!B35 -> 0 | M10: =Controls!B36 -> 0 | N10: =IF(M10>0,"PAID","HELD") -> HELD
A11: ="PAY-"&B11&"-FRAME" -> PAY-SUB-02-FRAME | B11: ='Object Crosswalk'!A8 -> SUB-02 | C11: ='Object Crosswalk'!B8 -> Civil substrate | D11: ='Object Crosswalk'!C8 -> Public | E11: ='Object Crosswalk'!D8 -> MULTI | F11: ='Object Crosswalk'!E8 -> — | G11: FRAME | H11: 0.25 | I11: ='Object Crosswalk'!I8 -> 0.12 | J11: =H11*I11 -> 0.03 | K11: =0 -> 0 | L11: =Controls!B35 -> 0 | M11: =Controls!B36 -> 0 | N11: =IF(M11>0,"PAID","HELD") -> HELD
A12: ="PAY-"&B12&"-MAKE" -> PAY-SUB-02-MAKE | B12: ='Object Crosswalk'!A8 -> SUB-02 | C12: ='Object Crosswalk'!B8 -> Civil substrate | D12: ='Object Crosswalk'!C8 -> Public | E12: ='Object Crosswalk'!D8 -> MULTI | F12: ='Object Crosswalk'!E8 -> — | G12: MAKE | H12: 0.5 | I12: ='Object Crosswalk'!I8 -> 0.12 | J12: =H12*I12 -> 0.06 | K12: =0 -> 0 | L12: =Controls!B35 -> 0 | M12: =Controls!B36 -> 0 | N12: =IF(M12>0,"PAID","HELD") -> HELD
A13: ="PAY-"&B13&"-BREAK" -> PAY-SUB-02-BREAK | B13: ='Object Crosswalk'!A8 -> SUB-02 | C13: ='Object Crosswalk'!B8 -> Civil substrate | D13: ='Object Crosswalk'!C8 -> Public | E13: ='Object Crosswalk'!D8 -> MULTI | F13: ='Object Crosswalk'!E8 -> — | G13: BREAK | H13: 0 | I13: ='Object Crosswalk'!I8 -> 0.12 | J13: =H13*I13 -> 0 | K13: =0 -> 0 | L13: =Controls!B35 -> 0 | M13: =Controls!B36 -> 0 | N13: =IF(M13>0,"PAID","HELD") -> HELD
A14: ="PAY-"&B14&"-TRANSFER" -> PAY-SUB-02-TRANSFER | B14: ='Object Crosswalk'!A8 -> SUB-02 | C14: ='Object Crosswalk'!B8 -> Civil substrate | D14: ='Object Crosswalk'!C8 -> Public | E14: ='Object Crosswalk'!D8 -> MULTI | F14: ='Object Crosswalk'!E8 -> — | G14: TRANSFER | H14: 0.25 | I14: ='Object Crosswalk'!I8 -> 0.12 | J14: =H14*I14 -> 0.03 | K14: =0 -> 0 | L14: =Controls!B35 -> 0 | M14: =Controls!B36 -> 0 | N14: =IF(M14>0,"PAID","HELD") -> HELD
A15: ="PAY-"&B15&"-FRAME" -> PAY-SUB-03-FRAME | B15: ='Object Crosswalk'!A9 -> SUB-03 | C15: ='Object Crosswalk'!B9 -> Civil substrate | D15: ='Object Crosswalk'!C9 -> Public | E15: ='Object Crosswalk'!D9 -> MULTI | F15: ='Object Crosswalk'!E9 -> — | G15: FRAME | H15: 0.25 | I15: ='Object Crosswalk'!I9 -> 0.12 | J15: =H15*I15 -> 0.03 | K15: =0 -> 0 | L15: =Controls!B35 -> 0 | M15: =Controls!B36 -> 0 | N15: =IF(M15>0,"PAID","HELD") -> HELD
A16: ="PAY-"&B16&"-MAKE" -> PAY-SUB-03-MAKE | B16: ='Object Crosswalk'!A9 -> SUB-03 | C16: ='Object Crosswalk'!B9 -> Civil substrate | D16: ='Object Crosswalk'!C9 -> Public | E16: ='Object Crosswalk'!D9 -> MULTI | F16: ='Object Crosswalk'!E9 -> — | G16: MAKE | H16: 0.5 | I16: ='Object Crosswalk'!I9 -> 0.12 | J16: =H16*I16 -> 0.06 | K16: =0 -> 0 | L16: =Controls!B35 -> 0 | M16: =Controls!B36 -> 0 | N16: =IF(M16>0,"PAID","HELD") -> HELD
A17: ="PAY-"&B17&"-BREAK" -> PAY-SUB-03-BREAK | B17: ='Object Crosswalk'!A9 -> SUB-03 | C17: ='Object Crosswalk'!B9 -> Civil substrate | D17: ='Object Crosswalk'!C9 -> Public | E17: ='Object Crosswalk'!D9 -> MULTI | F17: ='Object Crosswalk'!E9 -> — | G17: BREAK | H17: 0 | I17: ='Object Crosswalk'!I9 -> 0.12 | J17: =H17*I17 -> 0 | K17: =0 -> 0 | L17: =Controls!B35 -> 0 | M17: =Controls!B36 -> 0 | N17: =IF(M17>0,"PAID","HELD") -> HELD
A18: ="PAY-"&B18&"-TRANSFER" -> PAY-SUB-03-TRANSFER | B18: ='Object Crosswalk'!A9 -> SUB-03 | C18: ='Object Crosswalk'!B9 -> Civil substrate | D18: ='Object Crosswalk'!C9 -> Public | E18: ='Object Crosswalk'!D9 -> MULTI | F18: ='Object Crosswalk'!E9 -> — | G18: TRANSFER | H18: 0.25 | I18: ='Object Crosswalk'!I9 -> 0.12 | J18: =H18*I18 -> 0.03 | K18: =0 -> 0 | L18: =Controls!B35 -> 0 | M18: =Controls!B36 -> 0 | N18: =IF(M18>0,"PAID","HELD") -> HELD
A19: ="PAY-"&B19&"-FRAME" -> PAY-SUB-04-FRAME | B19: ='Object Crosswalk'!A10 -> SUB-04 | C19: ='Object Crosswalk'!B10 -> Civil substrate | D19: ='Object Crosswalk'!C10 -> Public | E19: ='Object Crosswalk'!D10 -> MULTI | F19: ='Object Crosswalk'!E10 -> — | G19: FRAME | H19: 0.25 | I19: ='Object Crosswalk'!I10 -> 0.12 | J19: =H19*I19 -> 0.03 | K19: =0 -> 0 | L19: =Controls!B35 -> 0 | M19: =Controls!B36 -> 0 | N19: =IF(M19>0,"PAID","HELD") -> HELD
A20: ="PAY-"&B20&"-MAKE" -> PAY-SUB-04-MAKE | B20: ='Object Crosswalk'!A10 -> SUB-04 | C20: ='Object Crosswalk'!B10 -> Civil substrate | D20: ='Object Crosswalk'!C10 -> Public | E20: ='Object Crosswalk'!D10 -> MULTI | F20: ='Object Crosswalk'!E10 -> — | G20: MAKE | H20: 0.5 | I20: ='Object Crosswalk'!I10 -> 0.12 | J20: =H20*I20 -> 0.06 | K20: =0 -> 0 | L20: =Controls!B35 -> 0 | M20: =Controls!B36 -> 0 | N20: =IF(M20>0,"PAID","HELD") -> HELD
A21: ="PAY-"&B21&"-BREAK" -> PAY-SUB-04-BREAK | B21: ='Object Crosswalk'!A10 -> SUB-04 | C21: ='Object Crosswalk'!B10 -> Civil substrate | D21: ='Object Crosswalk'!C10 -> Public | E21: ='Object Crosswalk'!D10 -> MULTI | F21: ='Object Crosswalk'!E10 -> — | G21: BREAK | H21: 0 | I21: ='Object Crosswalk'!I10 -> 0.12 | J21: =H21*I21 -> 0 | K21: =0 -> 0 | L21: =Controls!B35 -> 0 | M21: =Controls!B36 -> 0 | N21: =IF(M21>0,"PAID","HELD") -> HELD
A22: ="PAY-"&B22&"-TRANSFER" -> PAY-SUB-04-TRANSFER | B22: ='Object Crosswalk'!A10 -> SUB-04 | C22: ='Object Crosswalk'!B10 -> Civil substrate | D22: ='Object Crosswalk'!C10 -> Public | E22: ='Object Crosswalk'!D10 -> MULTI | F22: ='Object Crosswalk'!E10 -> — | G22: TRANSFER | H22: 0.25 | I22: ='Object Crosswalk'!I10 -> 0.12 | J22: =H22*I22 -> 0.03 | K22: =0 -> 0 | L22: =Controls!B35 -> 0 | M22: =Controls!B36 -> 0 | N22: =IF(M22>0,"PAID","HELD") -> HELD
A23: ="PAY-"&B23&"-FRAME" -> PAY-SUB-05-FRAME | B23: ='Object Crosswalk'!A11 -> SUB-05 | C23: ='Object Crosswalk'!B11 -> Civil substrate | D23: ='Object Crosswalk'!C11 -> Public | E23: ='Object Crosswalk'!D11 -> MULTI | F23: ='Object Crosswalk'!E11 -> — | G23: FRAME | H23: 0.25 | I23: ='Object Crosswalk'!I11 -> 0.12 | J23: =H23*I23 -> 0.03 | K23: =0 -> 0 | L23: =Controls!B35 -> 0 | M23: =Controls!B36 -> 0 | N23: =IF(M23>0,"PAID","HELD") -> HELD
A24: ="PAY-"&B24&"-MAKE" -> PAY-SUB-05-MAKE | B24: ='Object Crosswalk'!A11 -> SUB-05 | C24: ='Object Crosswalk'!B11 -> Civil substrate | D24: ='Object Crosswalk'!C11 -> Public | E24: ='Object Crosswalk'!D11 -> MULTI | F24: ='Object Crosswalk'!E11 -> — | G24: MAKE | H24: 0.5 | I24: ='Object Crosswalk'!I11 -> 0.12 | J24: =H24*I24 -> 0.06 | K24: =0 -> 0 | L24: =Controls!B35 -> 0 | M24: =Controls!B36 -> 0 | N24: =IF(M24>0,"PAID","HELD") -> HELD
A25: ="PAY-"&B25&"-BREAK" -> PAY-SUB-05-BREAK | B25: ='Object Crosswalk'!A11 -> SUB-05 | C25: ='Object Crosswalk'!B11 -> Civil substrate | D25: ='Object Crosswalk'!C11 -> Public | E25: ='Object Crosswalk'!D11 -> MULTI | F25: ='Object Crosswalk'!E11 -> — | G25: BREAK | H25: 0 | I25: ='Object Crosswalk'!I11 -> 0.12 | J25: =H25*I25 -> 0 | K25: =0 -> 0 | L25: =Controls!B35 -> 0 | M25: =Controls!B36 -> 0 | N25: =IF(M25>0,"PAID","HELD") -> HELD
A26: ="PAY-"&B26&"-TRANSFER" -> PAY-SUB-05-TRANSFER | B26: ='Object Crosswalk'!A11 -> SUB-05 | C26: ='Object Crosswalk'!B11 -> Civil substrate | D26: ='Object Crosswalk'!C11 -> Public | E26: ='Object Crosswalk'!D11 -> MULTI | F26: ='Object Crosswalk'!E11 -> — | G26: TRANSFER | H26: 0.25 | I26: ='Object Crosswalk'!I11 -> 0.12 | J26: =H26*I26 -> 0.03 | K26: =0 -> 0 | L26: =Controls!B35 -> 0 | M26: =Controls!B36 -> 0 | N26: =IF(M26>0,"PAID","HELD") -> HELD
A27: ="PAY-"&B27&"-FRAME" -> PAY-SUB-06-FRAME | B27: ='Object Crosswalk'!A12 -> SUB-06 | C27: ='Object Crosswalk'!B12 -> Civil substrate | D27: ='Object Crosswalk'!C12 -> Public | E27: ='Object Crosswalk'!D12 -> MULTI | F27: ='Object Crosswalk'!E12 -> — | G27: FRAME | H27: 0.25 | I27: ='Object Crosswalk'!I12 -> 0.12 | J27: =H27*I27 -> 0.03 | K27: =0 -> 0 | L27: =Controls!B35 -> 0 | M27: =Controls!B36 -> 0 | N27: =IF(M27>0,"PAID","HELD") -> HELD
A28: ="PAY-"&B28&"-MAKE" -> PAY-SUB-06-MAKE | B28: ='Object Crosswalk'!A12 -> SUB-06 | C28: ='Object Crosswalk'!B12 -> Civil substrate | D28: ='Object Crosswalk'!C12 -> Public | E28: ='Object Crosswalk'!D12 -> MULTI | F28: ='Object Crosswalk'!E12 -> — | G28: MAKE | H28: 0.5 | I28: ='Object Crosswalk'!I12 -> 0.12 | J28: =H28*I28 -> 0.06 | K28: =0 -> 0 | L28: =Controls!B35 -> 0 | M28: =Controls!B36 -> 0 | N28: =IF(M28>0,"PAID","HELD") -> HELD
A29: ="PAY-"&B29&"-BREAK" -> PAY-SUB-06-BREAK | B29: ='Object Crosswalk'!A12 -> SUB-06 | C29: ='Object Crosswalk'!B12 -> Civil substrate | D29: ='Object Crosswalk'!C12 -> Public | E29: ='Object Crosswalk'!D12 -> MULTI | F29: ='Object Crosswalk'!E12 -> — | G29: BREAK | H29: 0 | I29: ='Object Crosswalk'!I12 -> 0.12 | J29: =H29*I29 -> 0 | K29: =0 -> 0 | L29: =Controls!B35 -> 0 | M29: =Controls!B36 -> 0 | N29: =IF(M29>0,"PAID","HELD") -> HELD
A30: ="PAY-"&B30&"-TRANSFER" -> PAY-SUB-06-TRANSFER | B30: ='Object Crosswalk'!A12 -> SUB-06 | C30: ='Object Crosswalk'!B12 -> Civil substrate | D30: ='Object Crosswalk'!C12 -> Public | E30: ='Object Crosswalk'!D12 -> MULTI | F30: ='Object Crosswalk'!E12 -> — | G30: TRANSFER | H30: 0.25 | I30: ='Object Crosswalk'!I12 -> 0.12 | J30: =H30*I30 -> 0.03 | K30: =0 -> 0 | L30: =Controls!B35 -> 0 | M30: =Controls!B36 -> 0 | N30: =IF(M30>0,"PAID","HELD") -> HELD
A31: ="PAY-"&B31&"-FRAME" -> PAY-RIG-ET-CHA-FRAME | B31: ='Object Crosswalk'!A13 -> RIG-ET-CHA | C31: ='Object Crosswalk'!B13 -> Root-native rig | D31: ='Object Crosswalk'!C13 -> Public | E31: ='Object Crosswalk'!D13 -> MS-ET | F31: ='Object Crosswalk'!E13 -> ET-A | G31: FRAME | H31: 0.25 | I31: ='Object Crosswalk'!I13 -> 0.31666667 | J31: =H31*I31 -> 0.079166667 | K31: =0 -> 0 | L31: =Controls!B35 -> 0 | M31: =Controls!B36 -> 0 | N31: =IF(M31>0,"PAID","HELD") -> HELD
A32: ="PAY-"&B32&"-MAKE" -> PAY-RIG-ET-CHA-MAKE | B32: ='Object Crosswalk'!A13 -> RIG-ET-CHA | C32: ='Object Crosswalk'!B13 -> Root-native rig | D32: ='Object Crosswalk'!C13 -> Public | E32: ='Object Crosswalk'!D13 -> MS-ET | F32: ='Object Crosswalk'!E13 -> ET-A | G32: MAKE | H32: 0.5 | I32: ='Object Crosswalk'!I13 -> 0.31666667 | J32: =H32*I32 -> 0.15833333 | K32: =0 -> 0 | L32: =Controls!B35 -> 0 | M32: =Controls!B36 -> 0 | N32: =IF(M32>0,"PAID","HELD") -> HELD
A33: ="PAY-"&B33&"-BREAK" -> PAY-RIG-ET-CHA-BREAK | B33: ='Object Crosswalk'!A13 -> RIG-ET-CHA | C33: ='Object Crosswalk'!B13 -> Root-native rig | D33: ='Object Crosswalk'!C13 -> Public | E33: ='Object Crosswalk'!D13 -> MS-ET | F33: ='Object Crosswalk'!E13 -> ET-A | G33: BREAK | H33: 0 | I33: ='Object Crosswalk'!I13 -> 0.31666667 | J33: =H33*I33 -> 0 | K33: =0 -> 0 | L33: =Controls!B35 -> 0 | M33: =Controls!B36 -> 0 | N33: =IF(M33>0,"PAID","HELD") -> HELD
A34: ="PAY-"&B34&"-TRANSFER" -> PAY-RIG-ET-CHA-TRANSFER | B34: ='Object Crosswalk'!A13 -> RIG-ET-CHA | C34: ='Object Crosswalk'!B13 -> Root-native rig | D34: ='Object Crosswalk'!C13 -> Public | E34: ='Object Crosswalk'!D13 -> MS-ET | F34: ='Object Crosswalk'!E13 -> ET-A | G34: TRANSFER | H34: 0.25 | I34: ='Object Crosswalk'!I13 -> 0.31666667 | J34: =H34*I34 -> 0.079166667 | K34: =0 -> 0 | L34: =Controls!B35 -> 0 | M34: =Controls!B36 -> 0 | N34: =IF(M34>0,"PAID","HELD") -> HELD
A35: ="PAY-"&B35&"-FRAME" -> PAY-MTH-ET-CHA-L1-FRAME | B35: ='Object Crosswalk'!A14 -> MTH-ET-CHA-L1 | C35: ='Object Crosswalk'!B14 -> Method lineage | D35: ='Object Crosswalk'!C14 -> Public | E35: ='Object Crosswalk'!D14 -> MS-ET | F35: ='Object Crosswalk'!E14 -> ET-A | G35: FRAME | H35: 0.25 | I35: ='Object Crosswalk'!I14 -> 0.09 | J35: =H35*I35 -> 0.0225 | K35: =0 -> 0 | L35: =Controls!B35 -> 0 | M35: =Controls!B36 -> 0 | N35: =IF(M35>0,"PAID","HELD") -> HELD
A36: ="PAY-"&B36&"-MAKE" -> PAY-MTH-ET-CHA-L1-MAKE | B36: ='Object Crosswalk'!A14 -> MTH-ET-CHA-L1 | C36: ='Object Crosswalk'!B14 -> Method lineage | D36: ='Object Crosswalk'!C14 -> Public | E36: ='Object Crosswalk'!D14 -> MS-ET | F36: ='Object Crosswalk'!E14 -> ET-A | G36: MAKE | H36: 0.5 | I36: ='Object Crosswalk'!I14 -> 0.09 | J36: =H36*I36 -> 0.045 | K36: =0 -> 0 | L36: =Controls!B35 -> 0 | M36: =Controls!B36 -> 0 | N36: =IF(M36>0,"PAID","HELD") -> HELD
A37: ="PAY-"&B37&"-BREAK" -> PAY-MTH-ET-CHA-L1-BREAK | B37: ='Object Crosswalk'!A14 -> MTH-ET-CHA-L1 | C37: ='Object Crosswalk'!B14 -> Method lineage | D37: ='Object Crosswalk'!C14 -> Public | E37: ='Object Crosswalk'!D14 -> MS-ET | F37: ='Object Crosswalk'!E14 -> ET-A | G37: BREAK | H37: 0 | I37: ='Object Crosswalk'!I14 -> 0.09 | J37: =H37*I37 -> 0 | K37: =0 -> 0 | L37: =Controls!B35 -> 0 | M37: =Controls!B36 -> 0 | N37: =IF(M37>0,"PAID","HELD") -> HELD
A38: ="PAY-"&B38&"-TRANSFER" -> PAY-MTH-ET-CHA-L1-TRANSFER | B38: ='Object Crosswalk'!A14 -> MTH-ET-CHA-L1 | C38: ='Object Crosswalk'!B14 -> Method lineage | D38: ='Object Crosswalk'!C14 -> Public | E38: ='Object Crosswalk'!D14 -> MS-ET | F38: ='Object Crosswalk'!E14 -> ET-A | G38: TRANSFER | H38: 0.25 | I38: ='Object Crosswalk'!I14 -> 0.09 | J38: =H38*I38 -> 0.0225 | K38: =0 -> 0 | L38: =Controls!B35 -> 0 | M38: =Controls!B36 -> 0 | N38: =IF(M38>0,"PAID","HELD") -> HELD
A39: ="PAY-"&B39&"-FRAME" -> PAY-MTH-ET-CHA-L2-FRAME | B39: ='Object Crosswalk'!A15 -> MTH-ET-CHA-L2 | C39: ='Object Crosswalk'!B15 -> Method lineage | D39: ='Object Crosswalk'!C15 -> Public | E39: ='Object Crosswalk'!D15 -> MS-ET | F39: ='Object Crosswalk'!E15 -> ET-A | G39: FRAME | H39: 0.25 | I39: ='Object Crosswalk'!I15 -> 0.09 | J39: =H39*I39 -> 0.0225 | K39: =0 -> 0 | L39: =Controls!B35 -> 0 | M39: =Controls!B36 -> 0 | N39: =IF(M39>0,"PAID","HELD") -> HELD
A40: ="PAY-"&B40&"-MAKE" -> PAY-MTH-ET-CHA-L2-MAKE | B40: ='Object Crosswalk'!A15 -> MTH-ET-CHA-L2 | C40: ='Object Crosswalk'!B15 -> Method lineage | D40: ='Object Crosswalk'!C15 -> Public | E40: ='Object Crosswalk'!D15 -> MS-ET | F40: ='Object Crosswalk'!E15 -> ET-A | G40: MAKE | H40: 0.5 | I40: ='Object Crosswalk'!I15 -> 0.09 | J40: =H40*I40 -> 0.045 | K40: =0 -> 0 | L40: =Controls!B35 -> 0 | M40: =Controls!B36 -> 0 | N40: =IF(M40>0,"PAID","HELD") -> HELD
A41: ="PAY-"&B41&"-BREAK" -> PAY-MTH-ET-CHA-L2-BREAK | B41: ='Object Crosswalk'!A15 -> MTH-ET-CHA-L2 | C41: ='Object Crosswalk'!B15 -> Method lineage | D41: ='Object Crosswalk'!C15 -> Public | E41: ='Object Crosswalk'!D15 -> MS-ET | F41: ='Object Crosswalk'!E15 -> ET-A | G41: BREAK | H41: 0 | I41: ='Object Crosswalk'!I15 -> 0.09 | J41: =H41*I41 -> 0 | K41: =0 -> 0 | L41: =Controls!B35 -> 0 | M41: =Controls!B36 -> 0 | N41: =IF(M41>0,"PAID","HELD") -> HELD
A42: ="PAY-"&B42&"-TRANSFER" -> PAY-MTH-ET-CHA-L2-TRANSFER | B42: ='Object Crosswalk'!A15 -> MTH-ET-CHA-L2 | C42: ='Object Crosswalk'!B15 -> Method lineage | D42: ='Object Crosswalk'!C15 -> Public | E42: ='Object Crosswalk'!D15 -> MS-ET | F42: ='Object Crosswalk'!E15 -> ET-A | G42: TRANSFER | H42: 0.25 | I42: ='Object Crosswalk'!I15 -> 0.09 | J42: =H42*I42 -> 0.0225 | K42: =0 -> 0 | L42: =Controls!B35 -> 0 | M42: =Controls!B36 -> 0 | N42: =IF(M42>0,"PAID","HELD") -> HELD
A43: ="PAY-"&B43&"-FRAME" -> PAY-REG-ET-CHA-FRAME | B43: ='Object Crosswalk'!A16 -> REG-ET-CHA | C43: ='Object Crosswalk'!B16 -> Regeneration tool | D43: ='Object Crosswalk'!C16 -> Public | E43: ='Object Crosswalk'!D16 -> MS-ET | F43: ='Object Crosswalk'!E16 -> ET-A | G43: FRAME | H43: 0.25 | I43: ='Object Crosswalk'!I16 -> 0.066666667 | J43: =H43*I43 -> 0.016666667 | K43: =0 -> 0 | L43: =Controls!B35 -> 0 | M43: =Controls!B36 -> 0 | N43: =IF(M43>0,"PAID","HELD") -> HELD
A44: ="PAY-"&B44&"-MAKE" -> PAY-REG-ET-CHA-MAKE | B44: ='Object Crosswalk'!A16 -> REG-ET-CHA | C44: ='Object Crosswalk'!B16 -> Regeneration tool | D44: ='Object Crosswalk'!C16 -> Public | E44: ='Object Crosswalk'!D16 -> MS-ET | F44: ='Object Crosswalk'!E16 -> ET-A | G44: MAKE | H44: 0.5 | I44: ='Object Crosswalk'!I16 -> 0.066666667 | J44: =H44*I44 -> 0.033333333 | K44: =0 -> 0 | L44: =Controls!B35 -> 0 | M44: =Controls!B36 -> 0 | N44: =IF(M44>0,"PAID","HELD") -> HELD
A45: ="PAY-"&B45&"-BREAK" -> PAY-REG-ET-CHA-BREAK | B45: ='Object Crosswalk'!A16 -> REG-ET-CHA | C45: ='Object Crosswalk'!B16 -> Regeneration tool | D45: ='Object Crosswalk'!C16 -> Public | E45: ='Object Crosswalk'!D16 -> MS-ET | F45: ='Object Crosswalk'!E16 -> ET-A | G45: BREAK | H45: 0 | I45: ='Object Crosswalk'!I16 -> 0.066666667 | J45: =H45*I45 -> 0 | K45: =0 -> 0 | L45: =Controls!B35 -> 0 | M45: =Controls!B36 -> 0 | N45: =IF(M45>0,"PAID","HELD") -> HELD
A46: ="PAY-"&B46&"-TRANSFER" -> PAY-REG-ET-CHA-TRANSFER | B46: ='Object Crosswalk'!A16 -> REG-ET-CHA | C46: ='Object Crosswalk'!B16 -> Regeneration tool | D46: ='Object Crosswalk'!C16 -> Public | E46: ='Object Crosswalk'!D16 -> MS-ET | F46: ='Object Crosswalk'!E16 -> ET-A | G46: TRANSFER | H46: 0.25 | I46: ='Object Crosswalk'!I16 -> 0.066666667 | J46: =H46*I46 -> 0.016666667 | K46: =0 -> 0 | L46: =Controls!B35 -> 0 | M46: =Controls!B36 -> 0 | N46: =IF(M46>0,"PAID","HELD") -> HELD
A47: ="PAY-"&B47&"-FRAME" -> PAY-INT-ET-CHA-FRAME | B47: ='Object Crosswalk'!A17 -> INT-ET-CHA | C47: ='Object Crosswalk'!B17 -> Station integration | D47: ='Object Crosswalk'!C17 -> Public | E47: ='Object Crosswalk'!D17 -> MS-ET | F47: ='Object Crosswalk'!E17 -> ET-A | G47: FRAME | H47: 0.25 | I47: ='Object Crosswalk'!I17 -> 0.063333333 | J47: =H47*I47 -> 0.015833333 | K47: =0 -> 0 | L47: =Controls!B35 -> 0 | M47: =Controls!B36 -> 0 | N47: =IF(M47>0,"PAID","HELD") -> HELD
A48: ="PAY-"&B48&"-MAKE" -> PAY-INT-ET-CHA-MAKE | B48: ='Object Crosswalk'!A17 -> INT-ET-CHA | C48: ='Object Crosswalk'!B17 -> Station integration | D48: ='Object Crosswalk'!C17 -> Public | E48: ='Object Crosswalk'!D17 -> MS-ET | F48: ='Object Crosswalk'!E17 -> ET-A | G48: MAKE | H48: 0.5 | I48: ='Object Crosswalk'!I17 -> 0.063333333 | J48: =H48*I48 -> 0.031666667 | K48: =0 -> 0 | L48: =Controls!B35 -> 0 | M48: =Controls!B36 -> 0 | N48: =IF(M48>0,"PAID","HELD") -> HELD
A49: ="PAY-"&B49&"-BREAK" -> PAY-INT-ET-CHA-BREAK | B49: ='Object Crosswalk'!A17 -> INT-ET-CHA | C49: ='Object Crosswalk'!B17 -> Station integration | D49: ='Object Crosswalk'!C17 -> Public | E49: ='Object Crosswalk'!D17 -> MS-ET | F49: ='Object Crosswalk'!E17 -> ET-A | G49: BREAK | H49: 0 | I49: ='Object Crosswalk'!I17 -> 0.063333333 | J49: =H49*I49 -> 0 | K49: =0 -> 0 | L49: =Controls!B35 -> 0 | M49: =Controls!B36 -> 0 | N49: =IF(M49>0,"PAID","HELD") -> HELD
A50: ="PAY-"&B50&"-TRANSFER" -> PAY-INT-ET-CHA-TRANSFER | B50: ='Object Crosswalk'!A17 -> INT-ET-CHA | C50: ='Object Crosswalk'!B17 -> Station integration | D50: ='Object Crosswalk'!C17 -> Public | E50: ='Object Crosswalk'!D17 -> MS-ET | F50: ='Object Crosswalk'!E17 -> ET-A | G50: TRANSFER | H50: 0.25 | I50: ='Object Crosswalk'!I17 -> 0.063333333 | J50: =H50*I50 -> 0.015833333 | K50: =0 -> 0 | L50: =Controls!B35 -> 0 | M50: =Controls!B36 -> 0 | N50: =IF(M50>0,"PAID","HELD") -> HELD
A51: ="PAY-"&B51&"-FRAME" -> PAY-RIG-ET-CON-FRAME | B51: ='Object Crosswalk'!A18 -> RIG-ET-CON | C51: ='Object Crosswalk'!B18 -> Root-native rig | D51: ='Object Crosswalk'!C18 -> Public | E51: ='Object Crosswalk'!D18 -> MS-ET | F51: ='Object Crosswalk'!E18 -> ET-A | G51: FRAME | H51: 0.25 | I51: ='Object Crosswalk'!I18 -> 0.31666667 | J51: =H51*I51 -> 0.079166667 | K51: =0 -> 0 | L51: =Controls!B35 -> 0 | M51: =Controls!B36 -> 0 | N51: =IF(M51>0,"PAID","HELD") -> HELD
A52: ="PAY-"&B52&"-MAKE" -> PAY-RIG-ET-CON-MAKE | B52: ='Object Crosswalk'!A18 -> RIG-ET-CON | C52: ='Object Crosswalk'!B18 -> Root-native rig | D52: ='Object Crosswalk'!C18 -> Public | E52: ='Object Crosswalk'!D18 -> MS-ET | F52: ='Object Crosswalk'!E18 -> ET-A | G52: MAKE | H52: 0.5 | I52: ='Object Crosswalk'!I18 -> 0.31666667 | J52: =H52*I52 -> 0.15833333 | K52: =0 -> 0 | L52: =Controls!B35 -> 0 | M52: =Controls!B36 -> 0 | N52: =IF(M52>0,"PAID","HELD") -> HELD
A53: ="PAY-"&B53&"-BREAK" -> PAY-RIG-ET-CON-BREAK | B53: ='Object Crosswalk'!A18 -> RIG-ET-CON | C53: ='Object Crosswalk'!B18 -> Root-native rig | D53: ='Object Crosswalk'!C18 -> Public | E53: ='Object Crosswalk'!D18 -> MS-ET | F53: ='Object Crosswalk'!E18 -> ET-A | G53: BREAK | H53: 0 | I53: ='Object Crosswalk'!I18 -> 0.31666667 | J53: =H53*I53 -> 0 | K53: =0 -> 0 | L53: =Controls!B35 -> 0 | M53: =Controls!B36 -> 0 | N53: =IF(M53>0,"PAID","HELD") -> HELD
A54: ="PAY-"&B54&"-TRANSFER" -> PAY-RIG-ET-CON-TRANSFER | B54: ='Object Crosswalk'!A18 -> RIG-ET-CON | C54: ='Object Crosswalk'!B18 -> Root-native rig | D54: ='Object Crosswalk'!C18 -> Public | E54: ='Object Crosswalk'!D18 -> MS-ET | F54: ='Object Crosswalk'!E18 -> ET-A | G54: TRANSFER | H54: 0.25 | I54: ='Object Crosswalk'!I18 -> 0.31666667 | J54: =H54*I54 -> 0.079166667 | K54: =0 -> 0 | L54: =Controls!B35 -> 0 | M54: =Controls!B36 -> 0 | N54: =IF(M54>0,"PAID","HELD") -> HELD
A55: ="PAY-"&B55&"-FRAME" -> PAY-MTH-ET-CON-L1-FRAME | B55: ='Object Crosswalk'!A19 -> MTH-ET-CON-L1 | C55: ='Object Crosswalk'!B19 -> Method lineage | D55: ='Object Crosswalk'!C19 -> Public | E55: ='Object Crosswalk'!D19 -> MS-ET | F55: ='Object Crosswalk'!E19 -> ET-A | G55: FRAME | H55: 0.25 | I55: ='Object Crosswalk'!I19 -> 0.09 | J55: =H55*I55 -> 0.0225 | K55: =0 -> 0 | L55: =Controls!B35 -> 0 | M55: =Controls!B36 -> 0 | N55: =IF(M55>0,"PAID","HELD") -> HELD
A56: ="PAY-"&B56&"-MAKE" -> PAY-MTH-ET-CON-L1-MAKE | B56: ='Object Crosswalk'!A19 -> MTH-ET-CON-L1 | C56: ='Object Crosswalk'!B19 -> Method lineage | D56: ='Object Crosswalk'!C19 -> Public | E56: ='Object Crosswalk'!D19 -> MS-ET | F56: ='Object Crosswalk'!E19 -> ET-A | G56: MAKE | H56: 0.5 | I56: ='Object Crosswalk'!I19 -> 0.09 | J56: =H56*I56 -> 0.045 | K56: =0 -> 0 | L56: =Controls!B35 -> 0 | M56: =Controls!B36 -> 0 | N56: =IF(M56>0,"PAID","HELD") -> HELD
A57: ="PAY-"&B57&"-BREAK" -> PAY-MTH-ET-CON-L1-BREAK | B57: ='Object Crosswalk'!A19 -> MTH-ET-CON-L1 | C57: ='Object Crosswalk'!B19 -> Method lineage | D57: ='Object Crosswalk'!C19 -> Public | E57: ='Object Crosswalk'!D19 -> MS-ET | F57: ='Object Crosswalk'!E19 -> ET-A | G57: BREAK | H57: 0 | I57: ='Object Crosswalk'!I19 -> 0.09 | J57: =H57*I57 -> 0 | K57: =0 -> 0 | L57: =Controls!B35 -> 0 | M57: =Controls!B36 -> 0 | N57: =IF(M57>0,"PAID","HELD") -> HELD
A58: ="PAY-"&B58&"-TRANSFER" -> PAY-MTH-ET-CON-L1-TRANSFER | B58: ='Object Crosswalk'!A19 -> MTH-ET-CON-L1 | C58: ='Object Crosswalk'!B19 -> Method lineage | D58: ='Object Crosswalk'!C19 -> Public | E58: ='Object Crosswalk'!D19 -> MS-ET | F58: ='Object Crosswalk'!E19 -> ET-A | G58: TRANSFER | H58: 0.25 | I58: ='Object Crosswalk'!I19 -> 0.09 | J58: =H58*I58 -> 0.0225 | K58: =0 -> 0 | L58: =Controls!B35 -> 0 | M58: =Controls!B36 -> 0 | N58: =IF(M58>0,"PAID","HELD") -> HELD
A59: ="PAY-"&B59&"-FRAME" -> PAY-MTH-ET-CON-L2-FRAME | B59: ='Object Crosswalk'!A20 -> MTH-ET-CON-L2 | C59: ='Object Crosswalk'!B20 -> Method lineage | D59: ='Object Crosswalk'!C20 -> Public | E59: ='Object Crosswalk'!D20 -> MS-ET | F59: ='Object Crosswalk'!E20 -> ET-A | G59: FRAME | H59: 0.25 | I59: ='Object Crosswalk'!I20 -> 0.09 | J59: =H59*I59 -> 0.0225 | K59: =0 -> 0 | L59: =Controls!B35 -> 0 | M59: =Controls!B36 -> 0 | N59: =IF(M59>0,"PAID","HELD") -> HELD
A60: ="PAY-"&B60&"-MAKE" -> PAY-MTH-ET-CON-L2-MAKE | B60: ='Object Crosswalk'!A20 -> MTH-ET-CON-L2 | C60: ='Object Crosswalk'!B20 -> Method lineage | D60: ='Object Crosswalk'!C20 -> Public | E60: ='Object Crosswalk'!D20 -> MS-ET | F60: ='Object Crosswalk'!E20 -> ET-A | G60: MAKE | H60: 0.5 | I60: ='Object Crosswalk'!I20 -> 0.09 | J60: =H60*I60 -> 0.045 | K60: =0 -> 0 | L60: =Controls!B35 -> 0 | M60: =Controls!B36 -> 0 | N60: =IF(M60>0,"PAID","HELD") -> HELD
A61: ="PAY-"&B61&"-BREAK" -> PAY-MTH-ET-CON-L2-BREAK | B61: ='Object Crosswalk'!A20 -> MTH-ET-CON-L2 | C61: ='Object Crosswalk'!B20 -> Method lineage | D61: ='Object Crosswalk'!C20 -> Public | E61: ='Object Crosswalk'!D20 -> MS-ET | F61: ='Object Crosswalk'!E20 -> ET-A | G61: BREAK | H61: 0 | I61: ='Object Crosswalk'!I20 -> 0.09 | J61: =H61*I61 -> 0 | K61: =0 -> 0 | L61: =Controls!B35 -> 0 | M61: =Controls!B36 -> 0 | N61: =IF(M61>0,"PAID","HELD") -> HELD
A62: ="PAY-"&B62&"-TRANSFER" -> PAY-MTH-ET-CON-L2-TRANSFER | B62: ='Object Crosswalk'!A20 -> MTH-ET-CON-L2 | C62: ='Object Crosswalk'!B20 -> Method lineage | D62: ='Object Crosswalk'!C20 -> Public | E62: ='Object Crosswalk'!D20 -> MS-ET | F62: ='Object Crosswalk'!E20 -> ET-A | G62: TRANSFER | H62: 0.25 | I62: ='Object Crosswalk'!I20 -> 0.09 | J62: =H62*I62 -> 0.0225 | K62: =0 -> 0 | L62: =Controls!B35 -> 0 | M62: =Controls!B36 -> 0 | N62: =IF(M62>0,"PAID","HELD") -> HELD
A63: ="PAY-"&B63&"-FRAME" -> PAY-REG-ET-CON-FRAME | B63: ='Object Crosswalk'!A21 -> REG-ET-CON | C63: ='Object Crosswalk'!B21 -> Regeneration tool | D63: ='Object Crosswalk'!C21 -> Public | E63: ='Object Crosswalk'!D21 -> MS-ET | F63: ='Object Crosswalk'!E21 -> ET-A | G63: FRAME | H63: 0.25 | I63: ='Object Crosswalk'!I21 -> 0.066666667 | J63: =H63*I63 -> 0.016666667 | K63: =0 -> 0 | L63: =Controls!B35 -> 0 | M63: =Controls!B36 -> 0 | N63: =IF(M63>0,"PAID","HELD") -> HELD
A64: ="PAY-"&B64&"-MAKE" -> PAY-REG-ET-CON-MAKE | B64: ='Object Crosswalk'!A21 -> REG-ET-CON | C64: ='Object Crosswalk'!B21 -> Regeneration tool | D64: ='Object Crosswalk'!C21 -> Public | E64: ='Object Crosswalk'!D21 -> MS-ET | F64: ='Object Crosswalk'!E21 -> ET-A | G64: MAKE | H64: 0.5 | I64: ='Object Crosswalk'!I21 -> 0.066666667 | J64: =H64*I64 -> 0.033333333 | K64: =0 -> 0 | L64: =Controls!B35 -> 0 | M64: =Controls!B36 -> 0 | N64: =IF(M64>0,"PAID","HELD") -> HELD
A65: ="PAY-"&B65&"-BREAK" -> PAY-REG-ET-CON-BREAK | B65: ='Object Crosswalk'!A21 -> REG-ET-CON | C65: ='Object Crosswalk'!B21 -> Regeneration tool | D65: ='Object Crosswalk'!C21 -> Public | E65: ='Object Crosswalk'!D21 -> MS-ET | F65: ='Object Crosswalk'!E21 -> ET-A | G65: BREAK | H65: 0 | I65: ='Object Crosswalk'!I21 -> 0.066666667 | J65: =H65*I65 -> 0 | K65: =0 -> 0 | L65: =Controls!B35 -> 0 | M65: =Controls!B36 -> 0 | N65: =IF(M65>0,"PAID","HELD") -> HELD
A66: ="PAY-"&B66&"-TRANSFER" -> PAY-REG-ET-CON-TRANSFER | B66: ='Object Crosswalk'!A21 -> REG-ET-CON | C66: ='Object Crosswalk'!B21 -> Regeneration tool | D66: ='Object Crosswalk'!C21 -> Public | E66: ='Object Crosswalk'!D21 -> MS-ET | F66: ='Object Crosswalk'!E21 -> ET-A | G66: TRANSFER | H66: 0.25 | I66: ='Object Crosswalk'!I21 -> 0.066666667 | J66: =H66*I66 -> 0.016666667 | K66: =0 -> 0 | L66: =Controls!B35 -> 0 | M66: =Controls!B36 -> 0 | N66: =IF(M66>0,"PAID","HELD") -> HELD
A67: ="PAY-"&B67&"-FRAME" -> PAY-INT-ET-CON-FRAME | B67: ='Object Crosswalk'!A22 -> INT-ET-CON | C67: ='Object Crosswalk'!B22 -> Station integration | D67: ='Object Crosswalk'!C22 -> Public | E67: ='Object Crosswalk'!D22 -> MS-ET | F67: ='Object Crosswalk'!E22 -> ET-A | G67: FRAME | H67: 0.25 | I67: ='Object Crosswalk'!I22 -> 0.063333333 | J67: =H67*I67 -> 0.015833333 | K67: =0 -> 0 | L67: =Controls!B35 -> 0 | M67: =Controls!B36 -> 0 | N67: =IF(M67>0,"PAID","HELD") -> HELD
A68: ="PAY-"&B68&"-MAKE" -> PAY-INT-ET-CON-MAKE | B68: ='Object Crosswalk'!A22 -> INT-ET-CON | C68: ='Object Crosswalk'!B22 -> Station integration | D68: ='Object Crosswalk'!C22 -> Public | E68: ='Object Crosswalk'!D22 -> MS-ET | F68: ='Object Crosswalk'!E22 -> ET-A | G68: MAKE | H68: 0.5 | I68: ='Object Crosswalk'!I22 -> 0.063333333 | J68: =H68*I68 -> 0.031666667 | K68: =0 -> 0 | L68: =Controls!B35 -> 0 | M68: =Controls!B36 -> 0 | N68: =IF(M68>0,"PAID","HELD") -> HELD
A69: ="PAY-"&B69&"-BREAK" -> PAY-INT-ET-CON-BREAK | B69: ='Object Crosswalk'!A22 -> INT-ET-CON | C69: ='Object Crosswalk'!B22 -> Station integration | D69: ='Object Crosswalk'!C22 -> Public | E69: ='Object Crosswalk'!D22 -> MS-ET | F69: ='Object Crosswalk'!E22 -> ET-A | G69: BREAK | H69: 0 | I69: ='Object Crosswalk'!I22 -> 0.063333333 | J69: =H69*I69 -> 0 | K69: =0 -> 0 | L69: =Controls!B35 -> 0 | M69: =Controls!B36 -> 0 | N69: =IF(M69>0,"PAID","HELD") -> HELD
A70: ="PAY-"&B70&"-TRANSFER" -> PAY-INT-ET-CON-TRANSFER | B70: ='Object Crosswalk'!A22 -> INT-ET-CON | C70: ='Object Crosswalk'!B22 -> Station integration | D70: ='Object Crosswalk'!C22 -> Public | E70: ='Object Crosswalk'!D22 -> MS-ET | F70: ='Object Crosswalk'!E22 -> ET-A | G70: TRANSFER | H70: 0.25 | I70: ='Object Crosswalk'!I22 -> 0.063333333 | J70: =H70*I70 -> 0.015833333 | K70: =0 -> 0 | L70: =Controls!B35 -> 0 | M70: =Controls!B36 -> 0 | N70: =IF(M70>0,"PAID","HELD") -> HELD
A71: ="PAY-"&B71&"-FRAME" -> PAY-RIG-ET-REC-FRAME | B71: ='Object Crosswalk'!A23 -> RIG-ET-REC | C71: ='Object Crosswalk'!B23 -> Root-native rig | D71: ='Object Crosswalk'!C23 -> Public | E71: ='Object Crosswalk'!D23 -> MS-ET | F71: ='Object Crosswalk'!E23 -> ET-A | G71: FRAME | H71: 0.25 | I71: ='Object Crosswalk'!I23 -> 0.31666667 | J71: =H71*I71 -> 0.079166667 | K71: =0 -> 0 | L71: =Controls!B35 -> 0 | M71: =Controls!B36 -> 0 | N71: =IF(M71>0,"PAID","HELD") -> HELD
A72: ="PAY-"&B72&"-MAKE" -> PAY-RIG-ET-REC-MAKE | B72: ='Object Crosswalk'!A23 -> RIG-ET-REC | C72: ='Object Crosswalk'!B23 -> Root-native rig | D72: ='Object Crosswalk'!C23 -> Public | E72: ='Object Crosswalk'!D23 -> MS-ET | F72: ='Object Crosswalk'!E23 -> ET-A | G72: MAKE | H72: 0.5 | I72: ='Object Crosswalk'!I23 -> 0.31666667 | J72: =H72*I72 -> 0.15833333 | K72: =0 -> 0 | L72: =Controls!B35 -> 0 | M72: =Controls!B36 -> 0 | N72: =IF(M72>0,"PAID","HELD") -> HELD
A73: ="PAY-"&B73&"-BREAK" -> PAY-RIG-ET-REC-BREAK | B73: ='Object Crosswalk'!A23 -> RIG-ET-REC | C73: ='Object Crosswalk'!B23 -> Root-native rig | D73: ='Object Crosswalk'!C23 -> Public | E73: ='Object Crosswalk'!D23 -> MS-ET | F73: ='Object Crosswalk'!E23 -> ET-A | G73: BREAK | H73: 0 | I73: ='Object Crosswalk'!I23 -> 0.31666667 | J73: =H73*I73 -> 0 | K73: =0 -> 0 | L73: =Controls!B35 -> 0 | M73: =Controls!B36 -> 0 | N73: =IF(M73>0,"PAID","HELD") -> HELD
A74: ="PAY-"&B74&"-TRANSFER" -> PAY-RIG-ET-REC-TRANSFER | B74: ='Object Crosswalk'!A23 -> RIG-ET-REC | C74: ='Object Crosswalk'!B23 -> Root-native rig | D74: ='Object Crosswalk'!C23 -> Public | E74: ='Object Crosswalk'!D23 -> MS-ET | F74: ='Object Crosswalk'!E23 -> ET-A | G74: TRANSFER | H74: 0.25 | I74: ='Object Crosswalk'!I23 -> 0.31666667 | J74: =H74*I74 -> 0.079166667 | K74: =0 -> 0 | L74: =Controls!B35 -> 0 | M74: =Controls!B36 -> 0 | N74: =IF(M74>0,"PAID","HELD") -> HELD
A75: ="PAY-"&B75&"-FRAME" -> PAY-MTH-ET-REC-L1-FRAME | B75: ='Object Crosswalk'!A24 -> MTH-ET-REC-L1 | C75: ='Object Crosswalk'!B24 -> Method lineage | D75: ='Object Crosswalk'!C24 -> Public | E75: ='Object Crosswalk'!D24 -> MS-ET | F75: ='Object Crosswalk'!E24 -> ET-A | G75: FRAME | H75: 0.25 | I75: ='Object Crosswalk'!I24 -> 0.09 | J75: =H75*I75 -> 0.0225 | K75: =0 -> 0 | L75: =Controls!B35 -> 0 | M75: =Controls!B36 -> 0 | N75: =IF(M75>0,"PAID","HELD") -> HELD
A76: ="PAY-"&B76&"-MAKE" -> PAY-MTH-ET-REC-L1-MAKE | B76: ='Object Crosswalk'!A24 -> MTH-ET-REC-L1 | C76: ='Object Crosswalk'!B24 -> Method lineage | D76: ='Object Crosswalk'!C24 -> Public | E76: ='Object Crosswalk'!D24 -> MS-ET | F76: ='Object Crosswalk'!E24 -> ET-A | G76: MAKE | H76: 0.5 | I76: ='Object Crosswalk'!I24 -> 0.09 | J76: =H76*I76 -> 0.045 | K76: =0 -> 0 | L76: =Controls!B35 -> 0 | M76: =Controls!B36 -> 0 | N76: =IF(M76>0,"PAID","HELD") -> HELD
A77: ="PAY-"&B77&"-BREAK" -> PAY-MTH-ET-REC-L1-BREAK | B77: ='Object Crosswalk'!A24 -> MTH-ET-REC-L1 | C77: ='Object Crosswalk'!B24 -> Method lineage | D77: ='Object Crosswalk'!C24 -> Public | E77: ='Object Crosswalk'!D24 -> MS-ET | F77: ='Object Crosswalk'!E24 -> ET-A | G77: BREAK | H77: 0 | I77: ='Object Crosswalk'!I24 -> 0.09 | J77: =H77*I77 -> 0 | K77: =0 -> 0 | L77: =Controls!B35 -> 0 | M77: =Controls!B36 -> 0 | N77: =IF(M77>0,"PAID","HELD") -> HELD
A78: ="PAY-"&B78&"-TRANSFER" -> PAY-MTH-ET-REC-L1-TRANSFER | B78: ='Object Crosswalk'!A24 -> MTH-ET-REC-L1 | C78: ='Object Crosswalk'!B24 -> Method lineage | D78: ='Object Crosswalk'!C24 -> Public | E78: ='Object Crosswalk'!D24 -> MS-ET | F78: ='Object Crosswalk'!E24 -> ET-A | G78: TRANSFER | H78: 0.25 | I78: ='Object Crosswalk'!I24 -> 0.09 | J78: =H78*I78 -> 0.0225 | K78: =0 -> 0 | L78: =Controls!B35 -> 0 | M78: =Controls!B36 -> 0 | N78: =IF(M78>0,"PAID","HELD") -> HELD
A79: ="PAY-"&B79&"-FRAME" -> PAY-MTH-ET-REC-L2-FRAME | B79: ='Object Crosswalk'!A25 -> MTH-ET-REC-L2 | C79: ='Object Crosswalk'!B25 -> Method lineage | D79: ='Object Crosswalk'!C25 -> Public | E79: ='Object Crosswalk'!D25 -> MS-ET | F79: ='Object Crosswalk'!E25 -> ET-A | G79: FRAME | H79: 0.25 | I79: ='Object Crosswalk'!I25 -> 0.09 | J79: =H79*I79 -> 0.0225 | K79: =0 -> 0 | L79: =Controls!B35 -> 0 | M79: =Controls!B36 -> 0 | N79: =IF(M79>0,"PAID","HELD") -> HELD
A80: ="PAY-"&B80&"-MAKE" -> PAY-MTH-ET-REC-L2-MAKE | B80: ='Object Crosswalk'!A25 -> MTH-ET-REC-L2 | C80: ='Object Crosswalk'!B25 -> Method lineage | D80: ='Object Crosswalk'!C25 -> Public | E80: ='Object Crosswalk'!D25 -> MS-ET | F80: ='Object Crosswalk'!E25 -> ET-A | G80: MAKE | H80: 0.5 | I80: ='Object Crosswalk'!I25 -> 0.09 | J80: =H80*I80 -> 0.045 | K80: =0 -> 0 | L80: =Controls!B35 -> 0 | M80: =Controls!B36 -> 0 | N80: =IF(M80>0,"PAID","HELD") -> HELD
A81: ="PAY-"&B81&"-BREAK" -> PAY-MTH-ET-REC-L2-BREAK | B81: ='Object Crosswalk'!A25 -> MTH-ET-REC-L2 | C81: ='Object Crosswalk'!B25 -> Method lineage | D81: ='Object Crosswalk'!C25 -> Public | E81: ='Object Crosswalk'!D25 -> MS-ET | F81: ='Object Crosswalk'!E25 -> ET-A | G81: BREAK | H81: 0 | I81: ='Object Crosswalk'!I25 -> 0.09 | J81: =H81*I81 -> 0 | K81: =0 -> 0 | L81: =Controls!B35 -> 0 | M81: =Controls!B36 -> 0 | N81: =IF(M81>0,"PAID","HELD") -> HELD
A82: ="PAY-"&B82&"-TRANSFER" -> PAY-MTH-ET-REC-L2-TRANSFER | B82: ='Object Crosswalk'!A25 -> MTH-ET-REC-L2 | C82: ='Object Crosswalk'!B25 -> Method lineage | D82: ='Object Crosswalk'!C25 -> Public | E82: ='Object Crosswalk'!D25 -> MS-ET | F82: ='Object Crosswalk'!E25 -> ET-A | G82: TRANSFER | H82: 0.25 | I82: ='Object Crosswalk'!I25 -> 0.09 | J82: =H82*I82 -> 0.0225 | K82: =0 -> 0 | L82: =Controls!B35 -> 0 | M82: =Controls!B36 -> 0 | N82: =IF(M82>0,"PAID","HELD") -> HELD
A83: ="PAY-"&B83&"-FRAME" -> PAY-REG-ET-REC-FRAME | B83: ='Object Crosswalk'!A26 -> REG-ET-REC | C83: ='Object Crosswalk'!B26 -> Regeneration tool | D83: ='Object Crosswalk'!C26 -> Public | E83: ='Object Crosswalk'!D26 -> MS-ET | F83: ='Object Crosswalk'!E26 -> ET-A | G83: FRAME | H83: 0.25 | I83: ='Object Crosswalk'!I26 -> 0.066666667 | J83: =H83*I83 -> 0.016666667 | K83: =0 -> 0 | L83: =Controls!B35 -> 0 | M83: =Controls!B36 -> 0 | N83: =IF(M83>0,"PAID","HELD") -> HELD
A84: ="PAY-"&B84&"-MAKE" -> PAY-REG-ET-REC-MAKE | B84: ='Object Crosswalk'!A26 -> REG-ET-REC | C84: ='Object Crosswalk'!B26 -> Regeneration tool | D84: ='Object Crosswalk'!C26 -> Public | E84: ='Object Crosswalk'!D26 -> MS-ET | F84: ='Object Crosswalk'!E26 -> ET-A | G84: MAKE | H84: 0.5 | I84: ='Object Crosswalk'!I26 -> 0.066666667 | J84: =H84*I84 -> 0.033333333 | K84: =0 -> 0 | L84: =Controls!B35 -> 0 | M84: =Controls!B36 -> 0 | N84: =IF(M84>0,"PAID","HELD") -> HELD
A85: ="PAY-"&B85&"-BREAK" -> PAY-REG-ET-REC-BREAK | B85: ='Object Crosswalk'!A26 -> REG-ET-REC | C85: ='Object Crosswalk'!B26 -> Regeneration tool | D85: ='Object Crosswalk'!C26 -> Public | E85: ='Object Crosswalk'!D26 -> MS-ET | F85: ='Object Crosswalk'!E26 -> ET-A | G85: BREAK | H85: 0 | I85: ='Object Crosswalk'!I26 -> 0.066666667 | J85: =H85*I85 -> 0 | K85: =0 -> 0 | L85: =Controls!B35 -> 0 | M85: =Controls!B36 -> 0 | N85: =IF(M85>0,"PAID","HELD") -> HELD
A86: ="PAY-"&B86&"-TRANSFER" -> PAY-REG-ET-REC-TRANSFER | B86: ='Object Crosswalk'!A26 -> REG-ET-REC | C86: ='Object Crosswalk'!B26 -> Regeneration tool | D86: ='Object Crosswalk'!C26 -> Public | E86: ='Object Crosswalk'!D26 -> MS-ET | F86: ='Object Crosswalk'!E26 -> ET-A | G86: TRANSFER | H86: 0.25 | I86: ='Object Crosswalk'!I26 -> 0.066666667 | J86: =H86*I86 -> 0.016666667 | K86: =0 -> 0 | L86: =Controls!B35 -> 0 | M86: =Controls!B36 -> 0 | N86: =IF(M86>0,"PAID","HELD") -> HELD
A87: ="PAY-"&B87&"-FRAME" -> PAY-INT-ET-REC-FRAME | B87: ='Object Crosswalk'!A27 -> INT-ET-REC | C87: ='Object Crosswalk'!B27 -> Station integration | D87: ='Object Crosswalk'!C27 -> Public | E87: ='Object Crosswalk'!D27 -> MS-ET | F87: ='Object Crosswalk'!E27 -> ET-A | G87: FRAME | H87: 0.25 | I87: ='Object Crosswalk'!I27 -> 0.063333333 | J87: =H87*I87 -> 0.015833333 | K87: =0 -> 0 | L87: =Controls!B35 -> 0 | M87: =Controls!B36 -> 0 | N87: =IF(M87>0,"PAID","HELD") -> HELD
A88: ="PAY-"&B88&"-MAKE" -> PAY-INT-ET-REC-MAKE | B88: ='Object Crosswalk'!A27 -> INT-ET-REC | C88: ='Object Crosswalk'!B27 -> Station integration | D88: ='Object Crosswalk'!C27 -> Public | E88: ='Object Crosswalk'!D27 -> MS-ET | F88: ='Object Crosswalk'!E27 -> ET-A | G88: MAKE | H88: 0.5 | I88: ='Object Crosswalk'!I27 -> 0.063333333 | J88: =H88*I88 -> 0.031666667 | K88: =0 -> 0 | L88: =Controls!B35 -> 0 | M88: =Controls!B36 -> 0 | N88: =IF(M88>0,"PAID","HELD") -> HELD
A89: ="PAY-"&B89&"-BREAK" -> PAY-INT-ET-REC-BREAK | B89: ='Object Crosswalk'!A27 -> INT-ET-REC | C89: ='Object Crosswalk'!B27 -> Station integration | D89: ='Object Crosswalk'!C27 -> Public | E89: ='Object Crosswalk'!D27 -> MS-ET | F89: ='Object Crosswalk'!E27 -> ET-A | G89: BREAK | H89: 0 | I89: ='Object Crosswalk'!I27 -> 0.063333333 | J89: =H89*I89 -> 0 | K89: =0 -> 0 | L89: =Controls!B35 -> 0 | M89: =Controls!B36 -> 0 | N89: =IF(M89>0,"PAID","HELD") -> HELD
A90: ="PAY-"&B90&"-TRANSFER" -> PAY-INT-ET-REC-TRANSFER | B90: ='Object Crosswalk'!A27 -> INT-ET-REC | C90: ='Object Crosswalk'!B27 -> Station integration | D90: ='Object Crosswalk'!C27 -> Public | E90: ='Object Crosswalk'!D27 -> MS-ET | F90: ='Object Crosswalk'!E27 -> ET-A | G90: TRANSFER | H90: 0.25 | I90: ='Object Crosswalk'!I27 -> 0.063333333 | J90: =H90*I90 -> 0.015833333 | K90: =0 -> 0 | L90: =Controls!B35 -> 0 | M90: =Controls!B36 -> 0 | N90: =IF(M90>0,"PAID","HELD") -> HELD
A91: ="PAY-"&B91&"-FRAME" -> PAY-RIG-CT-CHA-FRAME | B91: ='Object Crosswalk'!A28 -> RIG-CT-CHA | C91: ='Object Crosswalk'!B28 -> Root-native rig | D91: ='Object Crosswalk'!C28 -> Public | E91: ='Object Crosswalk'!D28 -> MS-CT | F91: ='Object Crosswalk'!E28 -> CT-C | G91: FRAME | H91: 0.25 | I91: ='Object Crosswalk'!I28 -> 0.31666667 | J91: =H91*I91 -> 0.079166667 | K91: =0 -> 0 | L91: =Controls!B35 -> 0 | M91: =Controls!B36 -> 0 | N91: =IF(M91>0,"PAID","HELD") -> HELD
A92: ="PAY-"&B92&"-MAKE" -> PAY-RIG-CT-CHA-MAKE | B92: ='Object Crosswalk'!A28 -> RIG-CT-CHA | C92: ='Object Crosswalk'!B28 -> Root-native rig | D92: ='Object Crosswalk'!C28 -> Public | E92: ='Object Crosswalk'!D28 -> MS-CT | F92: ='Object Crosswalk'!E28 -> CT-C | G92: MAKE | H92: 0.5 | I92: ='Object Crosswalk'!I28 -> 0.31666667 | J92: =H92*I92 -> 0.15833333 | K92: =0 -> 0 | L92: =Controls!B35 -> 0 | M92: =Controls!B36 -> 0 | N92: =IF(M92>0,"PAID","HELD") -> HELD
A93: ="PAY-"&B93&"-BREAK" -> PAY-RIG-CT-CHA-BREAK | B93: ='Object Crosswalk'!A28 -> RIG-CT-CHA | C93: ='Object Crosswalk'!B28 -> Root-native rig | D93: ='Object Crosswalk'!C28 -> Public | E93: ='Object Crosswalk'!D28 -> MS-CT | F93: ='Object Crosswalk'!E28 -> CT-C | G93: BREAK | H93: 0 | I93: ='Object Crosswalk'!I28 -> 0.31666667 | J93: =H93*I93 -> 0 | K93: =0 -> 0 | L93: =Controls!B35 -> 0 | M93: =Controls!B36 -> 0 | N93: =IF(M93>0,"PAID","HELD") -> HELD
A94: ="PAY-"&B94&"-TRANSFER" -> PAY-RIG-CT-CHA-TRANSFER | B94: ='Object Crosswalk'!A28 -> RIG-CT-CHA | C94: ='Object Crosswalk'!B28 -> Root-native rig | D94: ='Object Crosswalk'!C28 -> Public | E94: ='Object Crosswalk'!D28 -> MS-CT | F94: ='Object Crosswalk'!E28 -> CT-C | G94: TRANSFER | H94: 0.25 | I94: ='Object Crosswalk'!I28 -> 0.31666667 | J94: =H94*I94 -> 0.079166667 | K94: =0 -> 0 | L94: =Controls!B35 -> 0 | M94: =Controls!B36 -> 0 | N94: =IF(M94>0,"PAID","HELD") -> HELD
A95: ="PAY-"&B95&"-FRAME" -> PAY-MTH-CT-CHA-L1-FRAME | B95: ='Object Crosswalk'!A29 -> MTH-CT-CHA-L1 | C95: ='Object Crosswalk'!B29 -> Method lineage | D95: ='Object Crosswalk'!C29 -> Public | E95: ='Object Crosswalk'!D29 -> MS-CT | F95: ='Object Crosswalk'!E29 -> CT-C | G95: FRAME | H95: 0.25 | I95: ='Object Crosswalk'!I29 -> 0.09 | J95: =H95*I95 -> 0.0225 | K95: =0 -> 0 | L95: =Controls!B35 -> 0 | M95: =Controls!B36 -> 0 | N95: =IF(M95>0,"PAID","HELD") -> HELD
A96: ="PAY-"&B96&"-MAKE" -> PAY-MTH-CT-CHA-L1-MAKE | B96: ='Object Crosswalk'!A29 -> MTH-CT-CHA-L1 | C96: ='Object Crosswalk'!B29 -> Method lineage | D96: ='Object Crosswalk'!C29 -> Public | E96: ='Object Crosswalk'!D29 -> MS-CT | F96: ='Object Crosswalk'!E29 -> CT-C | G96: MAKE | H96: 0.5 | I96: ='Object Crosswalk'!I29 -> 0.09 | J96: =H96*I96 -> 0.045 | K96: =0 -> 0 | L96: =Controls!B35 -> 0 | M96: =Controls!B36 -> 0 | N96: =IF(M96>0,"PAID","HELD") -> HELD
A97: ="PAY-"&B97&"-BREAK" -> PAY-MTH-CT-CHA-L1-BREAK | B97: ='Object Crosswalk'!A29 -> MTH-CT-CHA-L1 | C97: ='Object Crosswalk'!B29 -> Method lineage | D97: ='Object Crosswalk'!C29 -> Public | E97: ='Object Crosswalk'!D29 -> MS-CT | F97: ='Object Crosswalk'!E29 -> CT-C | G97: BREAK | H97: 0 | I97: ='Object Crosswalk'!I29 -> 0.09 | J97: =H97*I97 -> 0 | K97: =0 -> 0 | L97: =Controls!B35 -> 0 | M97: =Controls!B36 -> 0 | N97: =IF(M97>0,"PAID","HELD") -> HELD
A98: ="PAY-"&B98&"-TRANSFER" -> PAY-MTH-CT-CHA-L1-TRANSFER | B98: ='Object Crosswalk'!A29 -> MTH-CT-CHA-L1 | C98: ='Object Crosswalk'!B29 -> Method lineage | D98: ='Object Crosswalk'!C29 -> Public | E98: ='Object Crosswalk'!D29 -> MS-CT | F98: ='Object Crosswalk'!E29 -> CT-C | G98: TRANSFER | H98: 0.25 | I98: ='Object Crosswalk'!I29 -> 0.09 | J98: =H98*I98 -> 0.0225 | K98: =0 -> 0 | L98: =Controls!B35 -> 0 | M98: =Controls!B36 -> 0 | N98: =IF(M98>0,"PAID","HELD") -> HELD
A99: ="PAY-"&B99&"-FRAME" -> PAY-MTH-CT-CHA-L2-FRAME | B99: ='Object Crosswalk'!A30 -> MTH-CT-CHA-L2 | C99: ='Object Crosswalk'!B30 -> Method lineage | D99: ='Object Crosswalk'!C30 -> Public | E99: ='Object Crosswalk'!D30 -> MS-CT | F99: ='Object Crosswalk'!E30 -> CT-C | G99: FRAME | H99: 0.25 | I99: ='Object Crosswalk'!I30 -> 0.09 | J99: =H99*I99 -> 0.0225 | K99: =0 -> 0 | L99: =Controls!B35 -> 0 | M99: =Controls!B36 -> 0 | N99: =IF(M99>0,"PAID","HELD") -> HELD
A100: ="PAY-"&B100&"-MAKE" -> PAY-MTH-CT-CHA-L2-MAKE | B100: ='Object Crosswalk'!A30 -> MTH-CT-CHA-L2 | C100: ='Object Crosswalk'!B30 -> Method lineage | D100: ='Object Crosswalk'!C30 -> Public | E100: ='Object Crosswalk'!D30 -> MS-CT | F100: ='Object Crosswalk'!E30 -> CT-C | G100: MAKE | H100: 0.5 | I100: ='Object Crosswalk'!I30 -> 0.09 | J100: =H100*I100 -> 0.045 | K100: =0 -> 0 | L100: =Controls!B35 -> 0 | M100: =Controls!B36 -> 0 | N100: =IF(M100>0,"PAID","HELD") -> HELD
A101: ="PAY-"&B101&"-BREAK" -> PAY-MTH-CT-CHA-L2-BREAK | B101: ='Object Crosswalk'!A30 -> MTH-CT-CHA-L2 | C101: ='Object Crosswalk'!B30 -> Method lineage | D101: ='Object Crosswalk'!C30 -> Public | E101: ='Object Crosswalk'!D30 -> MS-CT | F101: ='Object Crosswalk'!E30 -> CT-C | G101: BREAK | H101: 0 | I101: ='Object Crosswalk'!I30 -> 0.09 | J101: =H101*I101 -> 0 | K101: =0 -> 0 | L101: =Controls!B35 -> 0 | M101: =Controls!B36 -> 0 | N101: =IF(M101>0,"PAID","HELD") -> HELD
A102: ="PAY-"&B102&"-TRANSFER" -> PAY-MTH-CT-CHA-L2-TRANSFER | B102: ='Object Crosswalk'!A30 -> MTH-CT-CHA-L2 | C102: ='Object Crosswalk'!B30 -> Method lineage | D102: ='Object Crosswalk'!C30 -> Public | E102: ='Object Crosswalk'!D30 -> MS-CT | F102: ='Object Crosswalk'!E30 -> CT-C | G102: TRANSFER | H102: 0.25 | I102: ='Object Crosswalk'!I30 -> 0.09 | J102: =H102*I102 -> 0.0225 | K102: =0 -> 0 | L102: =Controls!B35 -> 0 | M102: =Controls!B36 -> 0 | N102: =IF(M102>0,"PAID","HELD") -> HELD
A103: ="PAY-"&B103&"-FRAME" -> PAY-REG-CT-CHA-FRAME | B103: ='Object Crosswalk'!A31 -> REG-CT-CHA | C103: ='Object Crosswalk'!B31 -> Regeneration tool | D103: ='Object Crosswalk'!C31 -> Public | E103: ='Object Crosswalk'!D31 -> MS-CT | F103: ='Object Crosswalk'!E31 -> CT-C | G103: FRAME | H103: 0.25 | I103: ='Object Crosswalk'!I31 -> 0.066666667 | J103: =H103*I103 -> 0.016666667 | K103: =0 -> 0 | L103: =Controls!B35 -> 0 | M103: =Controls!B36 -> 0 | N103: =IF(M103>0,"PAID","HELD") -> HELD
...

Sheet Rollback
A2: Twelve governed failure and return paths
A4: Rollback stays local unless shared causal ancestry or slate independence is implicated. No authority may waive a missing predecessor.
A6: ID | B6: Trigger | C6: Current state | D6: Return target | E6: Scope | F6: Money consequence | G6: Technical consequence | H6: State
A7: R01 | B7: site identity or rights fail | C7: SITE ADMISSION | D7: SITE CLASS | E7: all eighteen charters | F7: no award | G7: no change to root or method | H7: FROZEN
A8: R02 | B8: site causal basin collides | C8: SITE ADMISSION | D8: SITE CLASS | E8: affected truth train plus national charter slate | F8: no award | G8: no independence claim | H8: FROZEN
A9: R03 | B9: technical bid fails | C9: TECHNICAL ADMISSION | D9: bid pool | E9: one position | F9: no award | G9: method record retained | H9: FROZEN
A10: R04 | B10: control graph collides | C10: CONTROL ADMISSION | D10: bid pool | E10: complete national pool | F10: no award | G10: no technical downgrade | H10: FROZEN
A11: R05 | B11: N-1 solve fails | C11: SLATE PROOF | D11: bid admission | E11: complete national pool | F11: no award | G11: expand pool | H11: FROZEN
A12: R06 | B12: provisional winner withdraws | C12: AWARD | D12: SLATE PROOF | E12: complete slate | F12: no termination liability | G12: re-solve | H12: FROZEN
A13: R07 | B13: post-award control changes | C13: FRAME or MAKE | D13: SLATE PROOF | E13: affected work plus national collision check | F13: suspend payment | G13: no silent novation | H13: FROZEN
A14: R08 | B14: construction defect is local | C14: MAKE | D14: FRAME | E14: affected lot | F14: hold affected stage | G14: repair or re-compete | H14: FROZEN
A15: R09 | B15: construction defect reveals common ancestry | C15: MAKE | D15: CONTROL ADMISSION | E15: all affected lots | F15: hold affected stages | G15: reopen control graph | H15: FROZEN
A16: R10 | B16: event is invalid | C16: EVENT VALIDITY | D16: MAKE | E16: exact event | F16: bounded repeat only | G16: no evidence disposition | H16: FROZEN
A17: R11 | B17: event is valid and adverse | C17: ROOT DISPOSITION | D17: no repeat | E17: root lineage | F17: pay earned candidate BREAK | G17: KILL or RESIZE | H17: FROZEN
A18: R12 | B18: cold reconstruction fails | C18: COLD RETURN | D18: MAKE | E18: affected station | F18: hold TRANSFER | G18: regenerate and rebuild | H18: FROZEN

Sheet Root Dispositions
A2: Six sentinel root-disposition records
A4: A valid adverse event is an output, not contractor failure. A killed sentinel returns its system to three held sibling roots.
A6: System | B6: Root | C6: Endpoints | D6: Valid events | E6: Evidence packages | F6: Maximum attempts | G6: Private option USD B | H6: Evidence identity | I6: Current disposition | J6: Permitted dispositions | K6: If killed | L6: Production credit
A7: MS-ET | B7: ET-A | C7: 2 | D7: 12 | E7: 60 | F7: 14 | G7: 0.50047462 | H7: SOURCE EMPTY | I7: HOLD | J7: KILL · RESIZE · ADVANCE | K7: held sibling roots | L7: NO
A8: MS-CT | B8: CT-C | C8: 2 | D8: 12 | E8: 60 | F8: 14 | G8: 0.51649348 | H8: SOURCE EMPTY | I8: HOLD | J8: KILL · RESIZE · ADVANCE | K8: held sibling roots | L8: NO
A9: MS-HC | B9: HC-A | C9: 2 | D9: 12 | E9: 60 | F9: 14 | G9: 0.30722165 | H9: SOURCE EMPTY | I9: HOLD | J9: KILL · RESIZE · ADVANCE | K9: held sibling roots | L9: NO
A10: MS-LF | B10: LF-B | C10: 2 | D10: 12 | E10: 60 | F10: 14 | G10: 0.89941282 | H10: SOURCE EMPTY | I10: HOLD | J10: KILL · RESIZE · ADVANCE | K10: held sibling roots | L10: NO
A11: MS-HU | B11: HU-A | C11: 2 | D11: 12 | E11: 60 | F11: 14 | G11: 0.86071245 | H11: SOURCE EMPTY | I11: HOLD | J11: KILL · RESIZE · ADVANCE | K11: held sibling roots | L11: NO
A12: MS-RT | B12: RT-B | C12: 2 | D12: 12 | E12: 60 | F12: 14 | G12: 0.50259779 | H12: SOURCE EMPTY | I12: HOLD | J12: KILL · RESIZE · ADVANCE | K12: held sibling roots | L12: NO

Sheet Technology Return
A2: Six form-giving candidate requirement packages now due
A4: The A2C branch returns to technology. Exterior form may follow only after these loads, interfaces and denial cases close as controlled requirements.
A6: System | B6: Root | C6: Next article object | D6: Form-giving loads and interfaces | E6: Must preserve | F6: Rendering state | G6: Parent action
A7: MS-ET | B7: ET-A | C7: pelagic exchange candidate article | D7: moving-interface loads, no-pier custody, connector loss and wet-to-dry handoff | E7: public-service vector, unlike roots, denial, cold reconstruction and complete residual return | F7: HELD | G7: derive controlled requirement package
A8: MS-CT | B8: CT-C | C8: occupied-building utility-spine article | D8: damaged-structure attachment, vertical access, utility isolation and egress | E8: public-service vector, unlike roots, denial, cold reconstruction and complete residual return | F8: HELD | G8: derive controlled requirement package
A9: MS-HC | B9: HC-A | C9: atmospheric-flux intervention article | D9: one-kilometre heat, plume, turbulence, deposition and duty-cycle loads | E9: public-service vector, unlike roots, denial, cold reconstruction and complete residual return | F9: HELD | G9: derive controlled requirement package
A10: MS-LF | B10: LF-B | C10: rapid subsurface heat-water article | D10: uncertain geology, rapid bore, firm 40 MW, 25,000 m3/day and residual return | E10: public-service vector, unlike roots, denial, cold reconstruction and complete residual return | F10: HELD | G10: derive controlled requirement package
A11: MS-HU | B11: HU-A | C11: complete clinical-island article | D11: ten care-line interfaces, full utility metabolism, staff denial and discharge | E11: public-service vector, unlike roots, denial, cold reconstruction and complete residual return | F11: HELD | G11: derive controlled requirement package
A12: MS-RT | B12: RT-B | C12: disconnected microfactory article | D12: dirty return, 99 positions in 168 hours and portable certification | E12: public-service vector, unlike roots, denial, cold reconstruction and complete residual return | F12: HELD | G12: derive controlled requirement package

Sheet Stress Tests
A2: Integrated construction-compact stress cases
A4: The compact must preserve useful failure, local rollback and all-six continuity without a super-authority.
A6: ID | B6: Disturbance | C6: Required response | D6: Forbidden conversion | E6: Disposition | F6: State
A7: S01 | B7: one office demands a master baseline | C7: retain typed artifact succession | D7: coordination to authority | E7: REJECT | F7: PASS
A8: S02 | B8: 144 method paths are scoped as 144 contracts | C8: restore thirty-six lineage lots | D8: path to lot | E8: RECONCILE | F8: PASS
A9: S03 | B9: construction packet is offered as event evidence | C9: require separate physical package | D9: as-built to causality | E9: REJECT | F9: PASS
A10: S04 | B10: three substrate sites are co-located | C10: enforce one nucleus per site and causal separation | D10: contract bundle to campus | E10: REJECT | F10: PASS
A11: S05 | B11: two bidders exist but N-1 fails | C11: expand admitted pool | D11: slot count to resilience | E11: HOLD | F11: PASS
A12: S06 | B12: price opens before control admission | C12: reseal and repeat affected judgments | D12: price to admissibility | E12: INVALID | F12: PASS
A13: S07 | B13: one award is made early | C13: revoke without liability | D13: provisional to contract | E13: REVOKE | F13: PASS
A14: S08 | B14: post-award ownership silently novates | C14: suspend and re-solve national collision graph | D14: commercial continuity to independence | E14: RE-SOLVE | F14: PASS
A15: S09 | B15: one local lot defect has no shared ancestry | C15: return affected lot only | D15: local failure to national restart | E15: LOCAL RETURN | F15: PASS
A16: S10 | B16: one defect reveals common toolchain | C16: reopen every affected lot and control admission | D16: nominal prime to independence | E16: CONTROL RETURN | F16: PASS
A17: S11 | B17: invalid event is repeated | C17: consume one bounded repeat token | D17: invalidity to adverse evidence | E17: REPEAT | F17: PASS
... A22: S16 | B22: vehicle rendering requested | C22: complete six form-giving requirement packages first | D22: functional envelope to exterior | E22: HELD | F22: PASS

Sheet Mutations
A2: Live mutation and restoration log
A4: Each mutation changes one authoritative control, trips one or more terminal audits and restores the passing baseline before export.
A6: ID | B6: Control cell | C6: Baseline | D6: Mutated | E6: Audit failures | F6: Mutation detected | G6: Baseline restored
A7: M01 | B7: Controls!B7 | C7: 12 | D7: 13 | E7: 2 | F7: YES | G7: YES
A8: M02 | B8: Controls!B8 | C8: 3.5869128 | D8: 4 | E8: 2 | F8: YES | G8: YES
A9: M03 | B9: Controls!B9 | C9: 6 | D9: 5 | E9: 2 | F9: YES | G9: YES
A10: M04 | B10: Controls!B10 | C10: 6 | D10: 5 | E10: 1 | F10: YES | G10: YES
A11: M05 | B11: Controls!B11 | C11: 12 | D11: 11 | E11: 1 | F11: YES | G11: YES
A12: M06 | B12: Controls!B12 | C12: 18 | D12: 17 | E12: 1 | F12: YES | G12: YES
A13: M07 | B13: Controls!B14 | C13: 72 | D13: 71 | E13: 1 | F13: YES | G13: YES
A14: M08 | B14: Controls!B15 | C14: 144 | D14: 143 | E14: 1 | F14: YES | G14: YES
A15: M09 | B15: Controls!B17 | C15: 102 | D15: 101 | E15: 1 | F15: YES | G15: YES
A16: M10 | B16: Controls!B18 | C16: 48 | D16: 47 | E16: 1 | F16: YES | G16: YES
A17: M11 | B17: Controls!B19 | C17: 510 | D17: 509 | E17: 1 | F17: YES | G17: YES
A18: M12 | B18: Controls!B20 | C18: 714 | D18: 713 | E18: 1 | F18: YES | G18: YES
... A30: M24 | B30: Controls!B40 | C30: 0 | D30: 1 | E30: 1 | F30: YES | G30: YES

Sheet Audit
A2: Terminal branch-integration audit
A4: The audit proves internal conservation and separation. It creates no site, firm, award, evidence, capability, production or rendering authority.
A6: Audit | B6: Observed | C6: Expected | D6: Difference | E6: State
A7: public reserve | B7: =Controls!B7 -> 12 | C7: 12 | D7: =B7-C7 -> 0 | E7: =IF(ABS(D7)<0.000001,"PASS","FAIL") -> PASS
A8: private options | B8: =Controls!B8 -> 3.5869128 | C8: 3.5869128 | D8: =B8-C8 -> 0 | E8: =IF(ABS(D8)<0.000001,"PASS","FAIL") -> PASS
A9: combined ceiling | B9: =Controls!B7+Controls!B8 -> 15.586913 | C9: 15.586913 | D9: =B9-C9 -> 0 | E9: =IF(ABS(D9)<0.000001,"PASS","FAIL") -> PASS
A10: systems | B10: =Controls!B9 -> 6 | C10: 6 | D10: =B10-C10 -> 0 | E10: =IF(ABS(D10)<0.000001,"PASS","FAIL") -> PASS
A11: selected roots | B11: =Controls!B10 -> 6 | C11: 6 | D11: =B11-C11 -> 0 | E11: =IF(ABS(D11)<0.000001,"PASS","FAIL") -> PASS
A12: endpoints | B12: =Controls!B11 -> 12 | C12: 12 | D12: =B12-C12 -> 0 | E12: =IF(ABS(D12)<0.000001,"PASS","FAIL") -> PASS
A13: stations | B13: =Controls!B12 -> 18 | C13: 18 | D13: =B13-C13 -> 0 | E13: =IF(ABS(D13)<0.000001,"PASS","FAIL") -> PASS
A14: lanes | B14: =Controls!B13 -> 36 | C14: 36 | D14: =B14-C14 -> 0 | E14: =IF(ABS(D14)<0.000001,"PASS","FAIL") -> PASS
A15: state bays | B15: =Controls!B14 -> 72 | C15: 72 | D15: =B15-C15 -> 0 | E15: =IF(ABS(D15)<0.000001,"PASS","FAIL") -> PASS
A16: method realizations | B16: =Controls!B15 -> 144 | C16: 144 | D16: =B16-C16 -> 0 | E16: =IF(ABS(D16)<0.000001,"PASS","FAIL") -> PASS
A17: regeneration functions | B17: =Controls!B16 -> 72 | C17: 72 | D17: =B17-C17 -> 0 | E17: =IF(ABS(D17)<0.000001,"PASS","FAIL") -> PASS
A18: lots | B18: =Controls!B17 -> 102 | C18: 102 | D18: =B18-C18 -> 0 | E18: =IF(ABS(D18)<0.000001,"PASS","FAIL") -> PASS
A19: crosswalk rows | B19: =COUNTA('Object Crosswalk'!A7:A108) -> 102 | C19: 102 | D19: =B19-C19 -> 0 | E19: =IF(ABS(D19)<0.000001,"PASS","FAIL") -> PASS
A20: crosswalk public | B20: =COUNTIF('Object Crosswalk'!C7:C108,"Public") -> 96 | C20: 96 | D20: =B20-C20 -> 0 | E20: =IF(ABS(D20)<0.000001,"PASS","FAIL") -> PASS
A21: crosswalk private | B21: =COUNTIF('Object Crosswalk'!C7:C108,"Private option") -> 6 | C21: 6 | D21: =B21-C21 -> 0 | E21: =IF(ABS(D21)<0.000001,"PASS","FAIL") -> PASS
A22: crosswalk authority | B22: =SUM('Object Crosswalk'!I7:I108) -> 15.586913 | C22: 15.586913 | D22: =B22-C22 -> -1.2434498e-14 | E22: =IF(ABS(D22)<0.000001,"PASS","FAIL") -> PASS
A23: crosswalk packet refs | B23: =SUM('Object Crosswalk'!J7:J108) -> 510 | C23: 510 | D23: =B23-C23 -> 0 | E23: =IF(ABS(D23)<0.000001,"PASS","FAIL") -> PASS
A24: crosswalk gate refs | B24: =SUM('Object Crosswalk'!K7:K108) -> 714 | C24: 714 | D24: =B24-C24 -> 0 | E24: =IF(ABS(D24)<0.000001,"PASS","FAIL") -> PASS
A25: crosswalk bid refs | B25: =SUM('Object Crosswalk'!L7:L108) -> 204 | C25: 204 | D25: =B25-C25 -> 0 | E25: =IF(ABS(D25)<0.000001,"PASS","FAIL") -> PASS
A26: crosswalk payment refs | B26: =SUM('Object Crosswalk'!M7:M108) -> 408 | C26: 408 | D26: =B26-C26 -> 0 | E26: =IF(ABS(D26)<0.000001,"PASS","FAIL") -> PASS
A27: control groups | B27: =Controls!B18 -> 48 | C27: 48 | D27: =B27-C27 -> 0 | E27: =IF(ABS(D27)<0.000001,"PASS","FAIL") -> PASS
A28: construction packet control | B28: =Controls!B19 -> 510 | C28: 510 | D28: =B28-C28 -> 0 | E28: =IF(ABS(D28)<0.000001,"PASS","FAIL") -> PASS
A29: construction packet rows | B29: =COUNTA('Construction Packets'!A7:A516) -> 510 | C29: 510 | D29: =B29-C29 -> 0 | E29: =IF(ABS(D29)<0.000001,"PASS","FAIL") -> PASS
A30: construction packet sources empty | B30: =COUNTIF('Construction Packets'!H7:H516,"SOURCE EMPTY") -> 510 | C30: 510 | D30: =B30-C30 -> 0 | E30: =IF(ABS(D30)<0.000001,"PASS","FAIL") -> PASS
A31: construction packet accepted zero | B31: =SUM('Construction Packets'!I7:I516) -> 0 | C31: 0 | D31: =B31-C31 -> 0 | E31: =IF(ABS(D31)<0.000001,"PASS","FAIL") -> PASS
A32: construction packets not event substitute | B32: =COUNTIF('Construction Packets'!J7:J516,"NO") -> 510 | C32: 510 | D32: =B32-C32 -> 0 | E32: =IF(ABS(D32)<0.000001,"PASS","FAIL") -> PASS
A33: construction decisions | B33: =Controls!B20 -> 714 | C33: 714 | D33: =B33-C33 -> 0 | E33: =IF(ABS(D33)<0.000001,"PASS","FAIL") -> PASS
A34: site charters | B34: =Controls!B21 -> 18 | C34: 18 | D34: =B34-C34 -> 0 | E34: =IF(ABS(D34)<0.000001,"PASS","FAIL") -> PASS
A35: site dimensions | B35: =Controls!B22 -> 180 | C35: 180 | D35: =B35-C35 -> 0 | E35: =IF(ABS(D35)<0.000001,"PASS","FAIL") -> PASS
A36: failure basins | B36: =Controls!B23 -> 144 | C36: 144 | D36: =B36-C36 -> 0 | E36: =IF(ABS(D36)<0.000001,"PASS","FAIL") -> PASS
A37: site decisions | B37: =Controls!B24 -> 216 | C37: 216 | D37: =B37-C37 -> 0 | E37: =IF(ABS(D37)<0.000001,"PASS","FAIL") -> PASS
A38: bid positions | B38: =Controls!B25 -> 204 | C38: 204 | D38: =B38-C38 -> 0 | E38: =IF(ABS(D38)<0.000001,"PASS","FAIL") -> PASS
A39: bid decisions | B39: =Controls!B26 -> 2856 | C39: 2856 | D39: =B39-C39 -> 0 | E39: =IF(ABS(D39)<0.000001,"PASS","FAIL") -> PASS
A40: N-1 tests | B40: =Controls!B27 -> 48 | C40: 48 | D40: =B40-C40 -> 0 | E40: =IF(ABS(D40)<0.000001,"PASS","FAIL") -> PASS
A41: valid event control | B41: =Controls!B28 -> 72 | C41: 72 | D41: =B41-C41 -> 0 | E41: =IF(ABS(D41)<0.000001,"PASS","FAIL") -> PASS
A42: event arithmetic | B42: =Controls!B9*2*3*2 -> 72 | C42: 72 | D42: =B42-C42 -> 0 | E42: =IF(ABS(D42)<0.000001,"PASS","FAIL") -> PASS
A43: event unique positions | B43: =COUNTA('Event Evidence'!A7:A366)/5 -> 72 | C43: 72 | D43: =B43-C43 -> 0 | E43: =IF(ABS(D43)<0.000001,"PASS","FAIL") -> PASS
A44: event evidence control | B44: =Controls!B29 -> 360 | C44: 360 | D44: =B44-C44 -> 0 | E44: =IF(ABS(D44)<0.000001,"PASS","FAIL") -> PASS
A45: event evidence rows | B45: =COUNTA('Event Evidence'!A7:A366) -> 360 | C45: 360 | D45: =B45-C45 -> 0 | E45: =IF(ABS(D45)<0.000001,"PASS","FAIL") -> PASS
A46: event observations empty | B46: =COUNTIF('Event Evidence'!I7:I366,"SOURCE EMPTY") -> 360 | C46: 360 | D46: =B46-C46 -> 0 | E46: =IF(ABS(D46)<0.000001,"PASS","FAIL") -> PASS
A47: event validity empty | B47: =COUNTIF('Event Evidence'!J7:J366,"SOURCE EMPTY") -> 360 | C47: 360 | D47: =B47-C47 -> 0 | E47: =IF(ABS(D47)<0.000001,"PASS","FAIL") -> PASS
A48: event outcome empty | B48: =COUNTIF('Event Evidence'!K7:K366,"SOURCE EMPTY") -> 360 | C48: 360 | D48: =B48-C48 -> 0 | E48: =IF(ABS(D48)<0.000001,"PASS","FAIL") -> PASS
A49: maximum attempts | B49: =Controls!B30 -> 84 | C49: 84 | D49: =B49-C49 -> 0 | E49: =IF(ABS(D49)<0.000001,"PASS","FAIL") -> PASS
A50: warrant control | B50: =Controls!B31 -> 18 | C50: 18 | D50: =B50-C50 -> 0 | E50: =IF(ABS(D50)<0.000001,"PASS","FAIL") -> PASS
A51: warrant rows | B51: =COUNTA(Warrants!A7:A24) -> 18 | C51: 18 | D51: =B51-C51 -> 0 | E51: =IF(ABS(D51)<0.000001,"PASS","FAIL") -> PASS
A52: state rows | B52: =COUNTA('State Machine'!A7:A24) -> 18 | C52: 18 | D52: =B52-C52 -> 0 | E52: =IF(ABS(D52)<0.000001,"PASS","FAIL") -> PASS
A53: release edges | B53: =COUNTA('Release Graph'!A7:A23) -> 17 | C53: 17 | D53: =B53-C53 -> 0 | E53: =IF(ABS(D53)<0.000001,"PASS","FAIL") -> PASS
A54: authority rows | B54: =COUNTA('Authority Matrix'!A7:A22) -> 16 | C54: 16 | D54: =B54-C54 -> 0 | E54: =IF(ABS(D54)<0.000001,"PASS","FAIL") -> PASS
A55: authority create total | B55: =SUM('Authority Matrix'!T7:T22) -> 18 | C55: 18 | D55: =B55-C55 -> 0 | E55: =IF(ABS(D55)<0.000001,"PASS","FAIL") -> PASS
A56: nonconversions | B56: =COUNTA(Nonconversions!A7:A24) -> 18 | C56: 18 | D56: =B56-C56 -> 0 | E56: =IF(ABS(D56)<0.000001,"PASS","FAIL") -> PASS
A57: contradictions | B57: =COUNTA(Contradictions!A7:A18) -> 12 | C57: 12 | D57: =B57-C57 -> 0 | E57: =IF(ABS(D57)<0.000001,"PASS","FAIL") -> PASS
A58: contradictions closed | B58: =COUNTIF(Contradictions!E7:E18,"CLOSED") -> 12 | C58: 12 | D58: =B58-C58 -> 0 | E58: =IF(ABS(D58)<0.000001,"PASS","FAIL") -> PASS
A59: finance lots | B59: =Finance!D13 -> 102 | C59: 102 | D59: =B59-C59 -> 0 | E59: =IF(ABS(D59)<0.000001,"PASS","FAIL") -> PASS
A60: finance authority | B60: =Finance!E13 -> 15.586913 | C60: 15.586913 | D60: =B60-C60 -> 0 | E60: =IF(ABS(D60)<0.000001,"PASS","FAIL") -> PASS
A61: through MAKE | B61: =Finance!J13 -> 10.793456 | C61: 10.793456 | D61: =B61-C61 -> 1.7763568e-15 | E61: =IF(ABS(D61)<0.000001,"PASS","FAIL") -> PASS
A62: through BREAK | B62: =Finance!K13 -> 12.048876 | C62: 12.048876 | D62: =B62-C62 -> 1.7763568e-15 | E62: =IF(ABS(D62)<0.000001,"PASS","FAIL") -> PASS
A63: unreleased BREAK | B63: =Finance!L13 -> 3.5380369 | C63: 3.5380369 | D63: =B63-C63 -> 0 | E63: =IF(ABS(D63)<0.000001,"PASS","FAIL") -> PASS
A64: payment ledger rows | B64: =COUNTA('Payment Ledger'!A7:A414) -> 408 | C64: 408 | D64: =B64-C64 -> 0 | E64: =IF(ABS(D64)<0.000001,"PASS","FAIL") -> PASS
A65: payment stage ceiling | B65: =SUM('Payment Ledger'!J7:J414) -> 15.586913 | C65: 15.586913 | D65: =B65-C65 -> 2.3092639e-14 | E65: =IF(ABS(D65)<0.000001,"PASS","FAIL") -> PASS
A66: payment accepted zero | B66: =SUM('Payment Ledger'!K7:K414) -> 0 | C66: 0 | D66: =B66-C66 -> 0 | E66: =IF(ABS(D66)<0.000001,"PASS","FAIL") -> PASS
A67: payment obligations zero | B67: =SUM('Payment Ledger'!L7:L414) -> 0 | C67: 0 | D67: =B67-C67 -> 0 | E67: =IF(ABS(D67)<0.000001,"PASS","FAIL") -> PASS
A68: payment paid zero | B68: =SUM('Payment Ledger'!M7:M414) -> 0 | C68: 0 | D68: =B68-C68 -> 0 | E68: =IF(ABS(D68)<0.000001,"PASS","FAIL") -> PASS
A69: rollback paths | B69: =COUNTA(Rollback!A7:A18) -> 12 | C69: 12 | D69: =B69-C69 -> 0 | E69: =IF(ABS(D69)<0.000001,"PASS","FAIL") -> PASS
A70: root disposition rows | B70: =COUNTA('Root Dispositions'!A7:A12) -> 6 | C70: 6 | D70: =B70-C70 -> 0 | E70: =IF(ABS(D70)<0.000001,"PASS","FAIL") -> PASS
A71: root endpoints | B71: =SUM('Root Dispositions'!C7:C12) -> 12 | C71: 12 | D71: =B71-C71 -> 0 | E71: =IF(ABS(D71)<0.000001,"PASS","FAIL") -> PASS
A72: root events | B72: =SUM('Root Dispositions'!D7:D12) -> 72 | C72: 72 | D72: =B72-C72 -> 0 | E72: =IF(ABS(D72)<0.000001,"PASS","FAIL") -> PASS
A73: root packages | B73: =SUM('Root Dispositions'!E7:E12) -> 360 | C73: 360 | D73: =B73-C73 -> 0 | E73: =IF(ABS(D73)<0.000001,"PASS","FAIL") -> PASS
A74: root attempts | B74: =SUM('Root Dispositions'!F7:F12) -> 84 | C74: 84 | D74: =B74-C74 -> 0 | E74: =IF(ABS(D74)<0.000001,"PASS","FAIL") -> PASS
A75: root private options | B75: =SUM('Root Dispositions'!G7:G12) -> 3.5869128 | C75: 3.5869128 | D75: =B75-C75 -> 0 | E75: =IF(ABS(D75)<0.000001,"PASS","FAIL") -> PASS
A76: root evidence empty | B76: =COUNTIF('Root Dispositions'!H7:H12,"SOURCE EMPTY") -> 6 | C76: 6 | D76: =B76-C76 -> 0 | E76: =IF(ABS(D76)<0.000001,"PASS","FAIL") -> PASS
A77: root dispositions hold | B77: =COUNTIF('Root Dispositions'!I7:I12,"HOLD") -> 6 | C77: 6 | D77: =B77-C77 -> 0 | E77: =IF(ABS(D77)<0.000001,"PASS","FAIL") -> PASS
A78: technology return rows | B78: =COUNTA('Technology Return'!A7:A12) -> 6 | C78: 6 | D78: =B78-C78 -> 0 | E78: =IF(ABS(D78)<0.000001,"PASS","FAIL") -> PASS
A79: technology rendering held | B79: =COUNTIF('Technology Return'!F7:F12,"HELD") -> 6 | C79: 6 | D79: =B79-C79 -> 0 | E79: =IF(ABS(D79)<0.000001,"PASS","FAIL") -> PASS
A80: selected architecture | B80: =COUNTIF(Alternatives!P7:P12,"SELECT") -> 1 | C80: 1 | D80: =B80-C80 -> 0 | E80: =IF(ABS(D80)<0.000001,"PASS","FAIL") -> PASS
A81: selected gates | B81: =Alternatives!N7 -> 12 | C81: 12 | D81: =B81-C81 -> 0 | E81: =IF(ABS(D81)<0.000001,"PASS","FAIL") -> PASS
A82: rejected architectures | B82: =COUNTIF(Alternatives!P7:P12,"REJECT") -> 5 | C82: 5 | D82: =B82-C82 -> 0 | E82: =IF(ABS(D82)<0.000001,"PASS","FAIL") -> PASS
A83: stress tests | B83: =COUNTA('Stress Tests'!A7:A22) -> 16 | C83: 16 | D83: =B83-C83 -> 0 | E83: =IF(ABS(D83)<0.000001,"PASS","FAIL") -> PASS
A84: stress passes | B84: =COUNTIF('Stress Tests'!F7:F22,"PASS") -> 16 | C84: 16 | D84: =B84-C84 -> 0 | E84: =IF(ABS(D84)<0.000001,"PASS","FAIL") -> PASS
A85: sites zero | B85: =Controls!B32 -> 0 | C85: 0 | D85: =B85-C85 -> 0 | E85: =IF(ABS(D85)<0.000001,"PASS","FAIL") -> PASS
A86: firms zero | B86: =Controls!B33 -> 0 | C86: 0 | D86: =B86-C86 -> 0 | E86: =IF(ABS(D86)<0.000001,"PASS","FAIL") -> PASS
A87: awards zero | B87: =Controls!B34 -> 0 | C87: 0 | D87: =B87-C87 -> 0 | E87: =IF(ABS(D87)<0.000001,"PASS","FAIL") -> PASS
A88: obligations zero | B88: =Controls!B35 -> 0 | C88: 0 | D88: =B88-C88 -> 0 | E88: =IF(ABS(D88)<0.000001,"PASS","FAIL") -> PASS
A89: payments zero | B89: =Controls!B36 -> 0 | C89: 0 | D89: =B89-C89 -> 0 | E89: =IF(ABS(D89)<0.000001,"PASS","FAIL") -> PASS
A90: observations zero | B90: =Controls!B37 -> 0 | C90: 0 | D90: =B90-C90 -> 0 | E90: =IF(ABS(D90)<0.000001,"PASS","FAIL") -> PASS
A91: capability zero | B91: =Controls!B38 -> 0 | C91: 0 | D91: =B91-C91 -> 0 | E91: =IF(ABS(D91)<0.000001,"PASS","FAIL") -> PASS
A92: production zero | B92: =Controls!B39 -> 0 | C92: 0 | D92: =B92-C92 -> 0 | E92: =IF(ABS(D92)<0.000001,"PASS","FAIL") -> PASS
A93: rendering zero | B93: =Controls!B40 -> 0 | C93: 0 | D93: =B93-C93 -> 0 | E93: =IF(ABS(D93)<0.000001,"PASS","FAIL") -> PASS

Sheet Sources & Limits
A2: Internal authorities and model limits
A4: This model integrates four internal constitutions. It makes no empirical claim about unbuilt candidates, unselected sites or nonexistent bids.
A6: Source | B6: Repository artifact | C6: Role | D6: Access | E6: Limitation
A7: A2C-1 | B7: six-root sentinel wave and cancellation constitution | C7: roots, endpoints, events, packages, attempts and candidate options | D7: internal repository | E7: no physical observation
A8: A2C-2 | B8: federated physical-truth station and rig constitution | C8: truth trains, nuclei, bays, realizations and regeneration | D8: internal repository | E8: no constructed facility
A9: A2C-3 | B9: severable construction-lot and industrial-firewall constitution | C9: lots, control groups, packets, gates and public finance | D9: internal repository | E9: no firm or award
A10: A2C-4 | B10: site-class, bid-admission and N-1 award-slate constitution | C10: site charters, bid pool and whole-slate admission | D10: internal repository | E10: no location or bid
A11: PFP-5 | B11: National First Physical Launch Compact | C11: parent portfolio, issue and evidence boundary | D11: internal repository | E11: no production inference
A12: Model boundary | B12: this workbook | C12: integration, formula, mutation and rendering checks | D12: internal repository | E12: no external sites used
A13: Evidence boundary | B13: all implementation and physical records | C13: deliberate source-empty and zero states | D13: not available | E13: constitution does not imply execution
A14: Rendering boundary | B14: candidate exterior form | C14: returned to form-giving requirement research | D14: not applicable | E14: no rendering in this pass
