Workbook

Sheet Decision
A1: Department of Resilience constitutional compact
A2: Pass 205 | DCA-5 | Fifth and final constitutional-architecture pass | Verdict: RETURN
A4: Selected constitutional form
A5: A warranted constitutional compact: five coequal houses exchange seventeen typed public-service warrants. Cross-cutting compacts refine those warrants but never become sovereign organizations. The Secretary directs priority and fiscal proposals but cannot manufacture technical fact, readiness, consent, service acceptance or effect.
A9: Control | B9: Count | C9: Meaning | E9: Mature reference | F9: Value | G9: Unit
A10: Houses | B10: 5 | C10: Co-equal authority domains | E10: Affiliated establishment | F10: 13.0307 | G10: million positions
A11: Institution classes | B11: 17 | C11: Existing constitutional actors | E11: Owned formations | F11: 5251 | G11: formations
A12: Top-level warrants | B12: 17 | C12: Exclusive state transitions | E12: Ready formations | F12: 3667 | G12: formations
A13: Domestic warrants | B13: 13 | C13: Duty and activation predicates | E13: Committed formations | F13: 2420 | G13: formations
A14: Personnel warrants | B14: 11 | C14: Affiliation-to-release predicates | E14: Technology account | F14: 1000 | G14: USD billions
A15: Knowledge warrants | B15: 12 | C15: Observation-to-destruction predicates | E15: Capital account | F15: 17400 | G15: USD billions
A16: Nonconversion laws | B16: 18 | C16: Department-wide firebreaks | E16: Ramped operations | F16: 50000 | G16: USD billions
A17: Implementation authority | B17: 0 | C17: No commissioned identity or evidence | E17: Public outlay | F17: 68400 | G17: USD billions
A19: Architecture | B19: Purpose | C19: Direction | D19: Facts | E19: Readiness | F19: Consent | G19: Effect | H19: Failure mode | I19: Result | J19: Reason
A20: Warranted compact | B20: Joined | C20: Secretary | D20: Separated | E20: JCA | F20: Receiver | G20: Trustees | H20: Return to exact warrant | I20: SELECT | J20: Complete integration without ownership merger
A21: Unified department | B21: Joined | C21: Secretary | D21: Secretary chain | E21: Secretary chain | F21: Overridable | G21: Self-scored | H21: Direction manufactures state | I21: FAIL | J21: Concentrates incompatible powers
A22: House council | B22: Negotiated | C22: Consensus | D22: Separated | E22: Separated | F22: Veto-prone | G22: Separated | H22: Silence becomes bargaining | I22: FAIL | J22: No executable default or clock
A23: Automated compiler | B23: Encoded | C23: Rules engine | D23: Model output | E23: Computed | F23: Tokenized | G23: Computed | H23: Software manufactures authority | I23: FAIL | J23: Representation is not law
A24: Emergency command | B24: Exceptional | C24: Incident commander | D24: Waivable | E24: Waivable | F24: Waivable | G24: Deferred | H24: Exception becomes constitution | I24: FAIL | J24: Erases rights and adverse truth

Sheet Five Houses
A1: Five Houses
A2: No house may validate the state it owns. Houses are authority domains, not vertical departments.
A4: House | B4: Constitutional object | C4: Institution classes | D4: Positive authority | E4: Cannot own | F4: Public output | G4: Failure default | H4: Successor
A5: Civic Covenant | B5: Duty and lawful scarcity | C5: Secretary and Staff; Civil Resilience Authority; Effect Trustees; Capital Board | D5: Guarantee, deficit, effect and fiscal option | E5: Technical proof, readiness, consent | F5: Bounded public obligation | G5: HOLD exact warrant | H5: Capability Commonwealth
A6: Capability Commonwealth | B6: Reproducible capability | C6: Mission System Commands; Generating Services; Root Houses; Industrial Mobilization Administration | D6: Baseline, root, technical release and availability | E6: Own evidence, self-readiness, employment | F6: Produced supportable option | G6: Return to failed predicate | H6: Evidence Court
A7: Evidence Court | B7: Adverse truth and remedy | C7: Resilience Proving Service; Rights and Scarcity Tribunal; Public Allocation Ledger | D7: Evidence disposition, rights stop and public reason | E7: Budget, production, force custody | F7: Replayable disposition | G7: Preserve evidence and stop | H7: Force Estate
A8: Force Estate | B8: Conserved readiness | C8: Strategic Sustainment; Joint Capacity Authority; NMAC; seven Readiness Districts | D8: Formation, readiness and allocation | E8: Activation, effect, partner custody | F8: Executable collision-free force state | G8: No silent substitution | H8: Employment Federation
A9: Employment Federation | B9: Use, acceptance and exit | C9: Operational Campaign Commands; Sovereign Compact and Custody Chamber | D9: Activation, service, acceptance, transfer and termination | E9: Self-measured effect, permanent custody | F9: Complete service and lawful exit | G9: Expire or terminate | H9: Regeneration

Sheet Warrant Machine
A1: Seventeen-warrant public-service machine
A2: Each transition has one issuer, one receiver, a negative authority, clock and rollback.
A4: # | B4: Warrant | C4: Issuer | D4: Receiver | E4: Positive artifact | F4: Negative authority | G4: Expiry / clock | H4: Rollback | I4: State
A5: 1 | B5: Enacted guarantee | C5: Congress / statute | D5: Civil Resilience Authority | E5: Public-service floor | F5: Rights Tribunal | G5: Statutory review | H5: Legislative amendment | I5: =IF(AND(C5<>"",D5<>"",E5<>"",F5<>"",G5<>"",H5<>""),"CONSTITUTED","HOLD") -> CONSTITUTED
A6: 2 | B6: Service-deficit order | C6: Civilian Effect Trustee | D6: Mission System Command | E6: Bounded unmet effect | F6: Receiver challenge | G6: Condition / clock | H6: Reobserve deficit | I6: =IF(AND(C6<>"",D6<>"",E6<>"",F6<>"",G6<>"",H6<>""),"CONSTITUTED","HOLD") -> CONSTITUTED
A7: 3 | B7: Effect contract | C7: Civil Resilience Authority | D7: Mission System Command | E7: Complete service obligation | F7: Effect Trustee | G7: Contract term | H7: Reconstitute scope | I7: =IF(AND(C7<>"",D7<>"",E7<>"",F7<>"",G7<>"",H7<>""),"CONSTITUTED","HOLD") -> CONSTITUTED
A8: 4 | B8: Fiscal option | C8: Capital Board | D8: Mission System Command | E8: Staged appropriation option | F8: Congress / audit | G8: Tranche clock | H8: Cancel tranche | I8: =IF(AND(C8<>"",D8<>"",E8<>"",F8<>"",G8<>"",H8<>""),"CONSTITUTED","HOLD") -> CONSTITUTED
A9: 5 | B9: Mission baseline | C9: Mission System Command | D9: Root Houses | E9: Complete configuration baseline | F9: Generating Service | G9: Version expiry | H9: Reopen competition | I9: =IF(AND(C9<>"",D9<>"",E9<>"",F9<>"",G9<>"",H9<>""),"CONSTITUTED","HOLD") -> CONSTITUTED
A10: 6 | B10: Controlled root | C10: Root House | D10: Resilience Proving Service | E10: Reproducible root claim | F10: Industrial administration | G10: Evidence clock | H10: Quarantine root | I10: =IF(AND(C10<>"",D10<>"",E10<>"",F10<>"",G10<>"",H10<>""),"CONSTITUTED","HOLD") -> CONSTITUTED
A11: 7 | B11: Technical release | C11: Generating Service | D11: Industrial administration | E11: Professionally released design | F11: Proving Service | G11: Configuration change | H11: Return to evidence | I11: =IF(AND(C11<>"",D11<>"",E11<>"",F11<>"",G11<>"",H11<>""),"CONSTITUTED","HOLD") -> CONSTITUTED
A12: 8 | B12: Evidence disposition | C12: Resilience Proving Service | D12: Capital Board and Service | E12: Adverse replayable disposition | F12: Rights Tribunal | G12: Evidence validity | H12: Repeat or terminate | I12: =IF(AND(C12<>"",D12<>"",E12<>"",F12<>"",G12<>"",H12<>""),"CONSTITUTED","HOLD") -> CONSTITUTED
A13: 9 | B13: Production availability | C13: Industrial administration | D13: Generating Service | E13: Qualified production lot | F13: Root House / audit | G13: Lot clock | H13: Stop and segregate | I13: =IF(AND(C13<>"",D13<>"",E13<>"",F13<>"",G13<>"",H13<>""),"CONSTITUTED","HOLD") -> CONSTITUTED
A14: 10 | B14: Formation warrant | C14: Generating Service | D14: Joint Capacity Authority | E14: Articles, crew, stocks, mobility and receiver | F14: Strategic Sustainment | G14: Configuration clock | H14: Disassemble claim | I14: =IF(AND(C14<>"",D14<>"",E14<>"",F14<>"",G14<>"",H14<>""),"CONSTITUTED","HOLD") -> CONSTITUTED
A15: 11 | B15: Readiness state | C15: Joint Capacity Authority | D15: NMAC | E15: Family-specific ready serial | F15: Readiness District | G15: Decay clock | H15: Requalify | I15: =IF(AND(C15<>"",D15<>"",E15<>"",F15<>"",G15<>"",H15<>""),"CONSTITUTED","HOLD") -> CONSTITUTED
A16: 12 | B16: Allocation order | C16: NMAC | D16: Campaign Command | E16: Collision-free family-complete schedule | F16: Public Allocation Ledger | G16: Event clock | H16: Recompile | I16: =IF(AND(C16<>"",D16<>"",E16<>"",F16<>"",G16<>"",H16<>""),"CONSTITUTED","HOLD") -> CONSTITUTED
... A21: 17 | B21: Regenerated serial | C21: Strategic Sustainment | D21: Joint Capacity Authority | E21: Rebuilt exact serial | F21: Generating Service | G21: Readiness decay | H21: Return to regeneration | I21: =IF(AND(C21<>"",D21<>"",E21<>"",F21<>"",G21<>"",H21<>""),"CONSTITUTED","HOLD") -> CONSTITUTED

Sheet Compact Registry
A1: Compact Registry
A2: Cross-cutting compacts add predicates and subordinate warrants, not sovereign institution classes.
A4: Compact | B4: Inherited decision | C4: Refines warrants | D4: Subordinate warrants | E4: New body? | F4: Key stop rule | G4: Fiscal treatment | H4: Status
A5: Domestic public-service covenant | B5: Objective breach opens bounded easement | C5: 1–3 and 13–16 | D5: 13 | E5: No | F5: Receiver method and custody survive | G5: Nested view | H5: CLOSED
A6: Civil Service Commonwealth | B6: Paid voluntary service citizenship | C6: 7 and 9–14 | D6: 11 | E6: No | F6: Membership, payroll and license are not readiness | G6: People account | H6: CLOSED
A7: Public Reality Commons | B7: Distributed physical truth and protected custody | C7: 2, 5, 7–8, 13 and 16 | D7: 12 | E7: No | F7: Forecast and warning are not command | G7: Nested view | H7: CLOSED
A8: Force-generation compact | B8: Five circuits through regenerated serial | C8: 4–12 and 17 | D8: 10 | E8: No | F8: Factory, article, formation, readiness and campaign differ | G8: Accounts plus market views | H8: RETURNED
A9: Strategic Power Compact | B9: Four sovereign employment modes | C9: 1 and 4–17 | D9: 7 | E9: No | F9: Invitation, access, output and prestige are not authority | G9: Nested view | H9: RETURNED

Sheet Authority Matrix
A1: Authority Matrix
A2: The Secretary directs. Exclusive validation remains distributed and survives incapacitation without power migration.
A4: Actor | B4: House | C4: May issue | D4: May stop | E4: May not infer | F4: Public reason | G4: Statutory alternate | H4: Incapacitation result
A5: Secretary and Staff | B5: Civic Covenant | C5: Priority, proposal, convening | D5: Unsafe employment | E5: Direction → fact or effect | F5: Portfolio conflict | G5: Same-scope deputy | H5: Power does not migrate
A6: Civil Resilience Authority | B6: Civic Covenant | C6: Effect contract | D6: Incomplete scope | E6: Need → readiness | F6: Duty and scarcity | G6: Named civil alternate | H6: Exact warrant continues
A7: Civilian Effect Trustees | B7: Civic Covenant | C7: Deficit and effect disposition | D7: Unproven effect | E7: Output → effect | F7: Adverse finding | G7: Unlike trustee panel | H7: Unknown stays unknown
A8: Capital Board | B8: Civic Covenant | C8: Fiscal option | D8: Unearned tranche | E8: Appropriation → capability | F8: Option / cancellation | G8: Independent fiscal panel | H8: No automatic funding
A9: Mission System Commands | B9: Capability Commonwealth | C9: Mission baseline | D9: Incomplete chain | E9: Mission → release | F9: Service baseline | G9: Alternate mission office | H9: Competition reopens
A10: Generating Services | B10: Capability Commonwealth | C10: Technical and formation warrants | D10: Unsafe configuration | E10: Article → formation | F10: Professional release | G10: Unlike service authority | H10: Release held
A11: Root Houses | B11: Capability Commonwealth | C11: Controlled root claim | D11: Nonreproducible root | E11: Industry → availability | F11: Root genealogy | G11: Unlike root | H11: Claim quarantined
A12: Industrial Mobilization Administration | B12: Capability Commonwealth | C12: Production availability | D12: Unqualified lot | E12: Factory → formation | F12: Lot and capacity | G12: Public production cell | H12: Lot segregated
A13: Resilience Proving Service | B13: Evidence Court | C13: Evidence disposition | D13: Unreproducible evidence | E13: Favorable result → authority | F13: Method and adversity | G13: Unlike proving root | H13: Evidence open
A14: Rights and Scarcity Tribunal | B14: Evidence Court | C14: Rights remedy | D14: Unlawful use | E14: Emergency → waiver | F14: Rights decision | G14: Emergency civil judge | H14: Action holds
A15: Public Allocation Ledger | B15: Evidence Court | C15: Public reason receipt | D15: Unsealed allocation | E15: Schedule → legitimacy | F15: Allocation ancestry | G15: Independent recorder | H15: No concealed schedule
... A21: Sovereign Compact and Custody Chamber | B21: Employment Federation | C21: Activation and custody | D21: Receiver / host stop | E21: Access → command | F21: Consent and exit | G21: Named sovereign alternate | H21: No presumed consent

Sheet Domestic Covenant
A1: Domestic Covenant
A2: Equal person-bound floor, receiver-governed method, objective-breach path, bounded easement and extinction.
A4: Element | B4: Design | C4: Count / time | D4: Unit | E4: Authority owner | F4: Stop | G4: No conversion | H4: Department warrant
A5: District–campaign–effect deficits | B5: Registered service deficits | C5: 504 | D5: cells | E5: Effect Trustees | F5: Unverified condition | G5: Missing data ≠ low need | H5: Service-deficit order
A6: Primary and alternate receivers | B6: Differently caused routes | C6: 1008 | D6: routes | E6: Sovereign Chamber | F6: Receiver rights | G6: Request ≠ command | H6: Lawful activation
A7: Family–district interfaces | B7: Typed receiver seams | C7: 336 | D7: interfaces | E7: Services and receiver | F7: Incompatibility | G7: Interface ≠ capacity | H7: Campaign service
A8: Objective-breach ceiling | B8: Condition-to-path clock | C8: 12 | D8: hours | E8: Civil Resilience Authority | F8: Contested evidence | G8: Forecast ≠ breach | H8: Service-deficit order
A9: National arrival gap | B9: Preparation and transit | C9: 5.5 | D9: days | E9: NMAC | F9: Missing family | G9: Speed ≠ complete service | H9: Allocation order
A10: Local continuity bridge | B10: Receiver survival obligation | C10: 6 | D10: days | E10: Sovereign receiver | F10: Rights / feasibility | G10: Bridge ≠ federal custody | H10: Effect contract
A11: Initial easement expiry | B11: Fresh authority required | C11: 30 | D11: days | E11: Sovereign Chamber | F11: Automatic expiry | G11: Presence ≠ title | H11: Lawful activation
A12: Legislative review | B12: Fresh authorization | C12: 180 | D12: days | E12: Congress | F12: No review | G12: History ≠ authority | H12: Enacted guarantee

Sheet Civil Service
A1: Civil Service Commonwealth
A2: Voluntary paid public profession at national scale. Membership and labor status remain distinct from release and command.
A4: Component | B4: Positions | C4: Million | D4: Share | E4: Employment character | F4: Readiness treatment
A5: National career | B5: 5570000 | C5: 5.57 | D5: =B5/$B$10 -> 0.42745209 | E5: Federal civil profession | F5: Separate formation warrant
A6: Ready reserve | B6: 2940000 | C6: 2.94 | D6: =B6/$B$10 -> 0.22562103 | E6: Paid bounded reserve duty | F6: Availability is not readiness
A7: Sovereign covenant | B7: 2430000 | C7: 2.43 | D7: =B7/$B$10 -> 0.18648269 | E7: State, tribal and territorial covenant | F7: No federal title conversion
A8: Productive service | B8: 2070000 | C8: 2.07 | D8: =B8/$B$10 -> 0.15885563 | E8: Public and qualified private production | F8: Employment is not formation
A9: Partner fellows | B9: 20700 | C9: 0.0207 | D9: =B9/$B$10 -> 0.0015885563 | E9: Partner professional exchange | F9: No U.S. readiness credit
A10: Total affiliated establishment | B10: =SUM(B5:B9) -> 13030700 | C10: =SUM(C5:C9) -> 13.0307 | D10: =SUM(D5:D9) -> 1
A12: State | B12: Affiliation | C12: Pay | D12: License | E12: Availability | F12: Formation | G12: Readiness | H12: Release
A13: Member | B13: Yes | C13: May be | D13: May be | E13: No | F13: No | G13: No | H13: No
A14: Qualified professional | B14: Yes | C14: Yes | D14: Yes | E14: May be | F14: No | G14: No | H14: No
A15: Assigned crew | B15: Yes | C15: Yes | D15: Current | E15: Yes | F15: Yes | G15: No | H15: No
A16: Ready formation | B16: Yes | C16: Yes | D16: Current | E16: Yes | F16: Yes | G16: Yes | H16: No
A17: Released to campaign | B17: Yes | C17: Yes | D17: Current | E17: Yes | F17: Yes | G17: Yes | H17: Yes

Sheet Reality Commons
A1: Reality Commons
A2: Distributed civil measurement and forecast utility. Products inform action but never supply authority.
A4: Plane | B4: Contains | C4: Custodian | D4: May release | E4: Cannot become | F4: Expiry | G4: Remedy | H4: Scale
A5: Open physical reality | B5: Environment, infrastructure, capacity and effects | C5: Public observatories | D5: Physics-first observations | E5: Identified dossier | F5: Published validity | G5: Correction / challenge | H5: 504 cells / 1,512 paths
A6: Protected civil state | B6: Person, health, property and community records | C6: Originating sovereign or authorized trust | D6: Bounded query result | E6: National population lake | F6: Purpose limit | G6: Human review / deletion | H6: 1,008 query routes
A7: Ephemeral service state | B7: Minimum incident token | C7: One incident easement | D7: Find, admit, serve or transfer | E7: Permanent credential | F7: Purpose extinction | G7: Deletion with receipt | H7: 5,251 disconnected nodes
A8: Sealed evidence | B8: Methods, warrants, versions and minimized proof | C8: Evidence Court | D8: Independent replay | E8: Operational search file | F8: Legal retention | G8: Adverse reproduction | H8: 336 family–district seams
A11: Nested account | B11: Amount | C11: Unit | D11: Treatment
A12: Technology | B12: 175 | C12: USD billions | D12: Inside technology account
A13: Capital | B13: 680 | C13: USD billions | D13: Inside capital account
A14: Mature operations | B14: 280 | C14: USD billions / year | D14: Inside operations
A15: 25-year base jurisdiction | B15: =B12+B13+B14*'Fiscal Accounts'!$B$11 -> 6189 | C15: USD billions | D15: Cross-classified; never added

Sheet Force State
A1: Mature force-state conservation
A2: Formation accounts are exclusive. Aggregates cannot close a missing family or manufacture another campaign.
A4: Formation state | B4: Count | C4: Share | D4: Authority meaning | E4: Forbidden inference
A5: Committed | B5: 2420 | C5: =B5/$B$11 -> 0.4608646 | D5: Ten admitted campaigns | E5: Commitment is not effect
A6: Protected reserve | B6: 502 | C6: =B6/$B$11 -> 0.095600838 | D6: Family-specific demand | E6: Reserve total is not another campaign
A7: Geographic buffer | B7: 745 | C7: =B7/$B$11 -> 0.14187774 | D7: Spatial assurance | E7: Buffer is not general reserve
A8: Requalification | B8: 514 | C8: =B8/$B$11 -> 0.097886117 | D8: Evidence renewal | E8: Past readiness is not current
A9: Maintenance | B9: 527 | C9: =B9/$B$11 -> 0.10036184 | D9: Unavailable | E9: Repair is not availability
A10: Deep overhaul | B10: 543 | C10: =B10/$B$11 -> 0.10340887 | D10: Unavailable | E10: Regeneration is not formation
A11: Owned formations | B11: =SUM(B5:B10) -> 5251 | C11: =SUM(C5:C10) -> 1 | D11: Conserved total | E11: Must equal 5,251
A13: Mode | B13: Formations | C13: Billets (million) | D13: Capital (USD B) | E13: Claim | F13: Nonconversion
A14: Guaranteed domestic continuity | B14: 1745 | C14: 3.7 | D14: 2930 | E14: Eight campaigns | F14: Urgency cannot recall invited serials
A15: Invited stabilization | B15: 675 | C15: 1.45 | D15: 1250 | E15: Two campaigns | F15: Invitation is not activation
A16: Forward partnership | B16: 0 | C16: 0 | D16: 0 | E16: Partner reproduction | F16: Partner capacity is not U.S. readiness
A17: Productive statecraft | B17: 0 | C17: 0 | D17: 0 | E17: Useful output | F17: Revenue is not appropriation

Sheet Fiscal Accounts
A1: Public fiscal constitution
A2: Only three public accounts add to the headline. Program jurisdictions and markets are non-additive views.
A4: Public account | B4: USD billions | C4: Period | D4: Additive? | E4: Owner | F4: Control
A5: Technology | B5: 1000 | C5: 25-year program | D5: Yes | E5: Capital Board | F5: Finite option pool
A6: Capital | B6: 17400 | C6: Estate build | D6: Yes | E6: Capital Board | F6: Exclusive title and reservation
A7: Operations | B7: 50000 | C7: Ramped 25-year path | D7: Yes | E7: Appropriation ledgers | F7: No revenue netting
A8: Total public outlay | B8: =SUM(B5:B7) -> 68400 | C8: 25 years | D8: Yes | E8: Congress | F8: Headline control
A10: Operating ramp control | B10: Value
A11: 25-year mature-year equivalents | B11: 19.05
A12: Implied mature operations (USD B/year) | B12: =B7/B11 -> 2624.6719
A13: Rounded mature statement (USD T/year) | B13: 2.63
A14: Rounded public outlay (USD T) | B14: 68.4
A16: Nested view | B16: Technology / capital (USD B) | C16: Mature operations (USD B/year) | D16: 25-year view (USD B) | E16: Overlap | F16: Rule
A17: Public Reality Commons | B17: 855 | C17: 280 | D17: =B17+C17*$B$11 -> 6189 | E17: People, sensors, networks and proof | F17: Cross-classify only
A18: Domestic covenant | B18: 160 | C18: 22.7 | D18: =B18+C18*$B$11 -> 592.435 | E18: Receiver, continuity and activation | F18: Cross-classify only
A19: Sovereign receiver commons | B19: 1280 | C19: 102 | D19: =B19+C19*$B$11 -> 3223.1 | E19: Capital, bridge, corridors and operations | F19: Cross-classify only
A20: Strategic activation and evidence | B20: 67.5 | C20: 12.2 | D20: =B20+C20*$B$11 -> 299.91 | E20: Inside receiver commons | F20: Never add to parent

Sheet 25-Year Path
A1: Twenty-five-year public outlay path
A2: USD billions. Illustrative timing normalized to inherited account controls; not an appropriation request.
A4: Year | B4: Technology weight | C4: Technology | D4: Capital weight | E4: Capital | F4: Operating ramp | G4: Operations | H4: Annual outlay | I4: Cumulative outlay
A5: 1 | B5: 0.14 | C5: =B5/SUM($B$5:$B$29)*'Fiscal Accounts'!$B$5 -> 140 | D5: 2 | E5: =D5/SUM($D$5:$D$29)*'Fiscal Accounts'!$B$6 -> 343.87352 | F5: 0.03 | G5: =F5/SUM($F$5:$F$29)*'Fiscal Accounts'!$B$7 -> 78.740157 | H5: =SUM(C5,E5,G5) -> 562.61368 | I5: =H5 -> 562.61368
A6: 2 | B6: 0.15 | C6: =B6/SUM($B$5:$B$29)*'Fiscal Accounts'!$B$5 -> 150 | D6: 4 | E6: =D6/SUM($D$5:$D$29)*'Fiscal Accounts'!$B$6 -> 687.74704 | F6: 0.07 | G6: =F6/SUM($F$5:$F$29)*'Fiscal Accounts'!$B$7 -> 183.72703 | H6: =SUM(C6,E6,G6) -> 1021.4741 | I6: =I5+H6 -> 1584.0877
A7: 3 | B7: 0.14 | C7: =B7/SUM($B$5:$B$29)*'Fiscal Accounts'!$B$5 -> 140 | D7: 7 | E7: =D7/SUM($D$5:$D$29)*'Fiscal Accounts'!$B$6 -> 1203.5573 | F7: 0.13 | G7: =F7/SUM($F$5:$F$29)*'Fiscal Accounts'!$B$7 -> 341.20735 | H7: =SUM(C7,E7,G7) -> 1684.7647 | I7: =I6+H7 -> 3268.8524
A8: 4 | B8: 0.12 | C8: =B8/SUM($B$5:$B$29)*'Fiscal Accounts'!$B$5 -> 120 | D8: 9 | E8: =D8/SUM($D$5:$D$29)*'Fiscal Accounts'!$B$6 -> 1547.4308 | F8: 0.22 | G8: =F8/SUM($F$5:$F$29)*'Fiscal Accounts'!$B$7 -> 577.42782 | H8: =SUM(C8,E8,G8) -> 2244.8587 | I8: =I7+H8 -> 5513.7111
A9: 5 | B9: 0.1 | C9: =B9/SUM($B$5:$B$29)*'Fiscal Accounts'!$B$5 -> 100 | D9: 11 | E9: =D9/SUM($D$5:$D$29)*'Fiscal Accounts'!$B$6 -> 1891.3043 | F9: 0.32 | G9: =F9/SUM($F$5:$F$29)*'Fiscal Accounts'!$B$7 -> 839.89501 | H9: =SUM(C9,E9,G9) -> 2831.1994 | I9: =I8+H9 -> 8344.9104
A10: 6 | B10: 0.08 | C10: =B10/SUM($B$5:$B$29)*'Fiscal Accounts'!$B$5 -> 80 | D10: 13 | E10: =D10/SUM($D$5:$D$29)*'Fiscal Accounts'!$B$6 -> 2235.1779 | F10: 0.42 | G10: =F10/SUM($F$5:$F$29)*'Fiscal Accounts'!$B$7 -> 1102.3622 | H10: =SUM(C10,E10,G10) -> 3417.5401 | I10: =I9+H10 -> 11762.45
A11: 7 | B11: 0.07 | C11: =B11/SUM($B$5:$B$29)*'Fiscal Accounts'!$B$5 -> 70 | D11: 12 | E11: =D11/SUM($D$5:$D$29)*'Fiscal Accounts'!$B$6 -> 2063.2411 | F11: 0.52 | G11: =F11/SUM($F$5:$F$29)*'Fiscal Accounts'!$B$7 -> 1364.8294 | H11: =SUM(C11,E11,G11) -> 3498.0705 | I11: =I10+H11 -> 15260.521
A12: 8 | B12: 0.06 | C12: =B12/SUM($B$5:$B$29)*'Fiscal Accounts'!$B$5 -> 60 | D12: 11 | E12: =D12/SUM($D$5:$D$29)*'Fiscal Accounts'!$B$6 -> 1891.3043 | F12: 0.62 | G12: =F12/SUM($F$5:$F$29)*'Fiscal Accounts'!$B$7 -> 1627.2966 | H12: =SUM(C12,E12,G12) -> 3578.6009 | I12: =I11+H12 -> 18839.122
A13: 9 | B13: 0.04 | C13: =B13/SUM($B$5:$B$29)*'Fiscal Accounts'!$B$5 -> 40 | D13: 9 | E13: =D13/SUM($D$5:$D$29)*'Fiscal Accounts'!$B$6 -> 1547.4308 | F13: 0.77 | G13: =F13/SUM($F$5:$F$29)*'Fiscal Accounts'!$B$7 -> 2020.9974 | H13: =SUM(C13,E13,G13) -> 3608.4282 | I13: =I12+H13 -> 22447.55
A14: 10 | B14: 0.03 | C14: =B14/SUM($B$5:$B$29)*'Fiscal Accounts'!$B$5 -> 30 | D14: 7 | E14: =D14/SUM($D$5:$D$29)*'Fiscal Accounts'!$B$6 -> 1203.5573 | F14: 0.95 | G14: =F14/SUM($F$5:$F$29)*'Fiscal Accounts'!$B$7 -> 2493.4383 | H14: =SUM(C14,E14,G14) -> 3726.9956 | I14: =I13+H14 -> 26174.546
A15: 11 | B15: 0.02 | C15: =B15/SUM($B$5:$B$29)*'Fiscal Accounts'!$B$5 -> 20 | D15: 5 | E15: =D15/SUM($D$5:$D$29)*'Fiscal Accounts'!$B$6 -> 859.68379 | F15: 1 | G15: =F15/SUM($F$5:$F$29)*'Fiscal Accounts'!$B$7 -> 2624.6719 | H15: =SUM(C15,E15,G15) -> 3504.3557 | I15: =I14+H15 -> 29678.901
A16: 12 | B16: 0.015 | C16: =B16/SUM($B$5:$B$29)*'Fiscal Accounts'!$B$5 -> 15 | D16: 3 | E16: =D16/SUM($D$5:$D$29)*'Fiscal Accounts'!$B$6 -> 515.81028 | F16: 1 | G16: =F16/SUM($F$5:$F$29)*'Fiscal Accounts'!$B$7 -> 2624.6719 | H16: =SUM(C16,E16,G16) -> 3155.4822 | I16: =I15+H16 -> 32834.384
A17: 13 | B17: 0.01 | C17: =B17/SUM($B$5:$B$29)*'Fiscal Accounts'!$B$5 -> 10 | D17: 2 | E17: =D17/SUM($D$5:$D$29)*'Fiscal Accounts'!$B$6 -> 343.87352 | F17: 1 | G17: =F17/SUM($F$5:$F$29)*'Fiscal Accounts'!$B$7 -> 2624.6719 | H17: =SUM(C17,E17,G17) -> 2978.5454 | I17: =I16+H17 -> 35812.929
... A29: 25 | B29: 0 | C29: =B29/SUM($B$5:$B$29)*'Fiscal Accounts'!$B$5 -> 0 | D29: 0.05 | E29: =D29/SUM($D$5:$D$29)*'Fiscal Accounts'!$B$6 -> 8.5968379 | F29: 1 | G29: =F29/SUM($F$5:$F$29)*'Fiscal Accounts'!$B$7 -> 2624.6719 | H29: =SUM(C29,E29,G29) -> 2633.2688 | I29: =I28+H29 -> 68400
A30: Total / control | B30: =SUM(B5:B29) -> 1 | C30: =SUM(C5:C29) -> 1000 | D30: =SUM(D5:D29) -> 101.2 | E30: =SUM(E5:E29) -> 17400 | F30: =SUM(F5:F29) -> 19.05 | G30: =SUM(G5:G29) -> 50000 | H30: =SUM(H5:H29) -> 68400 | I30: =I29 -> 68400

Sheet Stress Tests
A1: Stress Tests
A2: Service must continue without allowing direction, software, emergency, spending or success to manufacture authority.
A4: # | B4: Stress world | C4: Required response | D4: Exact warrant | E4: Default | F4: Alternate | G4: Forbidden shortcut | H4: Outcome | I4: Reason
A5: 1 | B5: Secretary orders unproved platform | C5: Suspend and demand evidence | D5: Evidence disposition | E5: HOLD | F5: Independent proving root | G5: Direction → fact | H5: PASS | I5: No release
A6: 2 | B6: Governor silent during verified breach | C6: Open objective-breach path | D6: Lawful activation | E6: HOLD | F6: Named sovereign alternate | G6: Silence → veto | H6: PASS | I6: Guarantee survives
A7: 3 | B7: Tribal government invokes direct path | C7: Use direct receiver route | D7: Lawful activation | E7: HOLD | F7: Compact chamber | G7: State intermediation | H7: PASS | I7: Direct sovereignty
A8: 4 | B8: Forecast roots disagree | C8: Preserve dissent | D8: Service-deficit order | E8: HOLD | F8: Unlike model root | G8: Average → certainty | H8: PASS | I8: Uncertainty retained
A9: 5 | B9: NMAC lacks six families | C9: Recompile or publish risk warrant | D9: Allocation order | E9: HOLD | F9: Certified cell | G9: Aggregate reserve → campaign | H9: PASS | I9: No substitution
A10: 6 | B10: Invited host withdraws consent | C10: Stop, transfer or exit | D10: Lawful activation | E10: STOP | F10: Custody alternate | G10: Access → command | H10: PASS | I10: Host stop controls
A11: 7 | B11: Invited serial sought domestically | C11: Require bilateral release | D11: Allocation order | E11: HOLD | F11: Other domestic capacity | G11: Urgency → recall | H11: PASS | I11: Commitment real
A12: 8 | B12: Rights tribunal incapacitated | C12: Use same-scope alternate | D12: Protected query / activation | E12: HOLD | F12: Emergency civil judge | G12: Emergency → waiver | H12: PASS | I12: No migration
A13: 9 | B13: Commercial cloud unavailable | C13: Use sovereign offline nodes | D13: Operational use | E13: HOLD | F13: Disconnected district node | G13: Vendor → continuity | H13: PASS | I13: Duty persists
A14: 10 | B14: Producer reports strong sales | C14: Keep ledgers separate | D14: Production availability | E14: HOLD | F14: Public production cell | G14: Revenue → readiness | H14: PASS | I14: Market separate
A15: 11 | B15: Outputs delivered; effect unknown | C15: Record UNKNOWN | D15: Effect disposition | E15: UNKNOWN | F15: Unlike effect trustee | G15: Output → effect | H15: PASS | I15: No credit
A16: 12 | B16: Warrant expires in emergency | C16: Renew exact warrant or fallback | D16: Expired warrant | E16: HOLD | F16: Same-scope alternate | G16: Emergency → permanence | H16: PASS | I16: Expiry operates

Sheet Mutations
A1: Mutations
A2: Each deliberately invalid mutation must fail before restoration.
A4: # | B4: Mutation | C4: Broken predicate | D4: Expected | E4: Observed | F4: Restoration | G4: Restored | H4: Credit
A5: 1 | B5: Secretary self-certifies release | C5: Separate validation | D5: FAIL | E5: FAIL | F5: Return release to service and proof | G5: YES | H5: 0
A6: 2 | B6: Forecast activates force | C6: Forecast is not command | D6: FAIL | E6: FAIL | F6: Restore activation warrant | G6: YES | H6: 0
A7: 3 | B7: Reserve member counted ready | C7: Personnel is not readiness | D7: FAIL | E7: FAIL | F7: Require formation evidence | G7: YES | H7: 0
A8: 4 | B8: Aggregate reserve closes family gap | C8: Family completeness | D8: FAIL | E8: FAIL | F8: Recompile exact schedule | G8: YES | H8: 0
A9: 5 | B9: Host access treated as command | C9: Sovereign consent | D9: FAIL | E9: FAIL | F9: Restore bilateral custody | G9: YES | H9: 0
A10: 6 | B10: Knowledge view added to total | C10: Fiscal exclusivity | D10: FAIL | E10: FAIL | F10: Cross-classify only | G10: YES | H10: 0
A11: 7 | B11: Missing effect recorded zero | C11: Unknown is not zero | D11: FAIL | E11: FAIL | F11: Restore UNKNOWN | G11: YES | H11: 0
A12: 8 | B12: Expired warrant stays active | C12: Expiry removes authority | D12: FAIL | E12: FAIL | F12: Renew or same-scope alternate | G12: YES | H12: 0

Sheet Audit
A1: Terminal audit
A2: Checks observe the model and never feed an assumption, state, authority or output.
A4: # | B4: Audit | C4: Actual | D4: Required | E4: Status | F4: Interpretation
A5: 1 | B5: House count | C5: =Decision!B10 -> 5 | D5: 5 | E5: =IF(ABS(C5-D5)<0.01,"PASS","FAIL") -> PASS | F5: Five houses
A6: 2 | B6: Institution classes | C6: =Decision!B11 -> 17 | D6: 17 | E6: =IF(ABS(C6-D6)<0.01,"PASS","FAIL") -> PASS | F6: No new sovereign class
A7: 3 | B7: Warrant count | C7: =COUNTA('Warrant Machine'!A5:A21) -> 17 | D7: 17 | E7: =IF(ABS(C7-D7)<0.01,"PASS","FAIL") -> PASS | F7: Complete chain
A8: 4 | B8: Constituted warrants | C8: =COUNTIFS('Warrant Machine'!I5:I21,"CONSTITUTED") -> 17 | D8: 17 | E8: =IF(ABS(C8-D8)<0.01,"PASS","FAIL") -> PASS | F8: Required fields present
A9: 5 | B9: Compact count | C9: =COUNTA('Compact Registry'!A5:A9) -> 5 | D9: 5 | E9: =IF(ABS(C9-D9)<0.01,"PASS","FAIL") -> PASS | F9: Inherited compacts integrated
A10: 6 | B10: New compact bodies | C10: =COUNTIFS('Compact Registry'!E5:E9,"Yes") -> 0 | D10: 0 | E10: =IF(ABS(C10-D10)<0.01,"PASS","FAIL") -> PASS | F10: No hidden Department
A11: 7 | B11: Authority actors | C11: =COUNTA('Authority Matrix'!A5:A21) -> 17 | D11: 17 | E11: =IF(ABS(C11-D11)<0.01,"PASS","FAIL") -> PASS | F11: All classes represented
A12: 8 | B12: Workforce | C12: ='Civil Service'!B10 -> 13030700 | D12: 13030700 | E12: =IF(ABS(C12-D12)<0.01,"PASS","FAIL") -> PASS | F12: Affiliation conserved
A13: 9 | B13: Formation total | C13: ='Force State'!B11 -> 5251 | D13: 5251 | E13: =IF(ABS(C13-D13)<0.01,"PASS","FAIL") -> PASS | F13: Force conserved
A14: 10 | B14: Ready accounts | C14: =SUM('Force State'!B5:B7) -> 3667 | D14: 3667 | E14: =IF(ABS(C14-D14)<0.01,"PASS","FAIL") -> PASS | F14: Ready identity
A15: 11 | B15: Regeneration accounts | C15: =SUM('Force State'!B8:B10) -> 1584 | D15: 1584 | E15: =IF(ABS(C15-D15)<0.01,"PASS","FAIL") -> PASS | F15: Nonready identity
A16: 12 | B16: Committed modes | C16: =SUM('Force State'!B14:B15) -> 2420 | D16: 2420 | E16: =IF(ABS(C16-D16)<0.01,"PASS","FAIL") -> PASS | F16: Domestic + invited
A17: 13 | B17: Technology account | C17: ='Fiscal Accounts'!B5 -> 1000 | D17: 1000 | E17: =IF(ABS(C17-D17)<0.01,"PASS","FAIL") -> PASS | F17: Technology control
A18: 14 | B18: Capital account | C18: ='Fiscal Accounts'!B6 -> 17400 | D18: 17400 | E18: =IF(ABS(C18-D18)<0.01,"PASS","FAIL") -> PASS | F18: Capital control
A19: 15 | B19: Operations account | C19: ='Fiscal Accounts'!B7 -> 50000 | D19: 50000 | E19: =IF(ABS(C19-D19)<0.01,"PASS","FAIL") -> PASS | F19: Operations control
A20: 16 | B20: Public outlay | C20: ='Fiscal Accounts'!B8 -> 68400 | D20: 68400 | E20: =IF(ABS(C20-D20)<0.01,"PASS","FAIL") -> PASS | F20: Three accounts
A21: 17 | B21: Technology schedule | C21: ='25-Year Path'!C30 -> 1000 | D21: 1000 | E21: =IF(ABS(C21-D21)<0.01,"PASS","FAIL") -> PASS | F21: Path closes
A22: 18 | B22: Capital schedule | C22: ='25-Year Path'!E30 -> 17400 | D22: 17400 | E22: =IF(ABS(C22-D22)<0.01,"PASS","FAIL") -> PASS | F22: Path closes
A23: 19 | B23: Operations schedule | C23: ='25-Year Path'!G30 -> 50000 | D23: 50000 | E23: =IF(ABS(C23-D23)<0.01,"PASS","FAIL") -> PASS | F23: Path closes
A24: 20 | B24: Total schedule | C24: ='25-Year Path'!H30 -> 68400 | D24: 68400 | E24: =IF(ABS(C24-D24)<0.01,"PASS","FAIL") -> PASS | F24: Path closes
A25: 21 | B25: Cumulative close | C25: ='25-Year Path'!I30 -> 68400 | D25: 68400 | E25: =IF(ABS(C25-D25)<0.01,"PASS","FAIL") -> PASS | F25: Roll-forward closes
A26: 22 | B26: Ramp total | C26: ='25-Year Path'!F30 -> 19.05 | D26: 19.05 | E26: =IF(ABS(C26-D26)<0.01,"PASS","FAIL") -> PASS | F26: Inherited ramp
A27: 23 | B27: Knowledge nested base | C27: ='Reality Commons'!B15 -> 6189 | D27: 6189 | E27: =IF(ABS(C27-D27)<0.01,"PASS","FAIL") -> PASS | F27: Cross-classified
A28: 24 | B28: Stress tests | C28: =COUNTIFS('Stress Tests'!H5:H16,"PASS") -> 12 | D28: 12 | E28: =IF(ABS(C28-D28)<0.01,"PASS","FAIL") -> PASS | F28: All pass
A29: 25 | B29: Invalid mutations | C29: =COUNTIFS(Mutations!E5:E12,"FAIL") -> 8 | D29: 8 | E29: =IF(ABS(C29-D29)<0.01,"PASS","FAIL") -> PASS | F29: All detected
A30: 26 | B30: Restored mutations | C30: =COUNTIFS(Mutations!G5:G12,"YES") -> 8 | D30: 8 | E30: =IF(ABS(C30-D30)<0.01,"PASS","FAIL") -> PASS | F30: Baseline restored
A31: 27 | B31: Implementation authority | C31: =Decision!B17 -> 0 | D31: 0 | E31: =IF(ABS(C31-D31)<0.01,"PASS","FAIL") -> PASS | F31: Source-empty
A32: 28 | B32: Released effect credit | C32: =SUM(Mutations!H5:H12) -> 0 | D32: 0 | E32: =IF(ABS(C32-D32)<0.01,"PASS","FAIL") -> PASS | F32: No synthetic success
A34: Audit summary | B34: Pass count
A35: Terminal passes | B35: =COUNTIFS(E5:E32,"PASS") -> 28

Sheet Sources & Limits
A1: Sources & Limits
A2: Repository-internal research only. No external evidence, identity, site, exterior or rendering is authorized.
A4: Source / limit | B4: Role | C4: Inherited control | D4: Treatment
A5: Pass 201 — constitutional order | B5: Parent architecture | C5: Five houses, 17 classes, 17 warrants | D5: Authoritative
A6: Pass 202 — domestic covenant | B6: Domestic duty | C6: 13 warrants, six-day bridge and expiry | D6: Authoritative
A7: Pass 203 — Civil Service Commonwealth | B7: People and economy | C7: 13.0307M positions; USD 68.4T | D7: Authoritative
A8: Pass 204 — Public Reality Commons | B8: Knowledge and privacy | C8: Four planes; USD 6.19T nested base | D8: Authoritative
A9: Pass 195 — force-generation return | B9: Formation machinery | C9: 5,251 formations; five circuits | D9: Integrated
A10: Pass 200 — Strategic Power return | B10: Employment | C10: Four modes; sovereign invited use | D10: Integrated
A11: Source status | B11: All identities and evidence | C11: Source-empty | D11: Zero authority
A12: Fiscal precision | B12: Inherited planning controls | C12: Timing normalized to totals | D12: Illustrative
A13: Nested overlap | B13: People, technology, capital and operations | C13: Do not add program views | D13: Cross-classify
A14: Technology maturity | B14: Novel capabilities require unlike roots and proof | C14: No prototype credit | D14: Held
A15: Physical design | B15: No site, serial, exterior or rendering | C15: Research-first constraint | D15: Held
A16: Next decision | B16: First physical build tranche | C16: Complete service systems and evidence sequencing | D16: Frontier
