Workbook

Sheet Summary
A2: Commissioning and non-displacement warrant
A4: Pass 234 decision model. Capacity closure is architectural; every real identity, drill and commissioning act remains open.
A6: Decision: adopt CNW-1 as the only path from FAE-1 topology to an available technical estate | B6: Decision: adopt CNW-1 as the only path from FAE-1 topology to an available technical estate | C6: Decision: adopt CNW-1 as the only path from FAE-1 topology to an available technical estate | D6: Decision: adopt CNW-1 as the only path from FAE-1 topology to an available technical estate | E6: Decision: adopt CNW-1 as the only path from FAE-1 topology to an available technical estate | F6: Decision: adopt CNW-1 as the only path from FAE-1 topology to an available technical estate | G6: Decision: adopt CNW-1 as the only path from FAE-1 topology to an available technical estate
A8: Site dockets | B8: Role appointments | C8: Key records | D8: Vendor lots | E8: Capacity worlds passed | F8: Recovery trials passed | G8: Estate activation
A9: =COUNTA('Site Dockets'!A7:A24) -> 18 | B9: =COUNTA('Role Appointments'!A7:A102) -> 96 | C9: =COUNTA('Key Custody'!A7:A84) -> 78 | D9: =COUNTA('Vendor Lots'!A7:A78) -> 72 | E9: =COUNTIFS('Failure Worlds'!J7:J36,"PASS") -> 30 | F9: =COUNTIFS('Recovery Clocks'!J7:J186,"PASS") -> 0 | G9: =Inputs!B37 -> 0
A13: Commissioning law | B13: Commissioning law | C13: Commissioning law | D13: Commissioning law | E13: Commissioning law | F13: Commissioning law | G13: Commissioning law
A15: 1 | B15: All eighteen site dockets and six root estates activate together; no root gains an artifact-validity timing advantage.
A16: 2 | B16: Every resource carries an exclusive truth-train reservation, a separate artifact partition and unassigned headroom.
A17: 3 | B17: Vendors build bounded lots but never operate enclaves, hold court authority, release escrow or conduct recovery.
A18: 4 | B18: Every site and region loss runs at full truth reservation while artifact failover remains inside its own partition.
A19: 5 | B19: Recovery trials use synthetic availability loads. They contain no package content and create zero AVW credit.
A20: 6 | B20: Common control, lineage leakage or truth-capacity displacement terminates the cell instead of centralizing it.
A24: Capacity and implementation boundary | B24: Capacity and implementation boundary | C24: Capacity and implementation boundary | D24: Capacity and implementation boundary | E24: Capacity and implementation boundary | F24: Capacity and implementation boundary | G24: Capacity and implementation boundary
A26: Normalized host capacity | B26: 100 | I26: World class | J26: Minimum headroom
A27: Truth-train reservation | B27: 75 | I27: Site loss | J27: 5
A28: Artifact partition | B28: 20 | I28: Region loss | J28: 5
A29: Minimum simultaneous headroom | B29: 5 | I29: Vendor exit | J29: 15
A30: Stress records passing | B30: 3024 | I30: Role compromise | J30: 5
A31: Architecture gates passing | B31: 90 | I31: Court or custody | J31: 15
A32: Implementation gates open | B32: 270
A33: Recovery trials open | B33: 180
A34: Capital added (USD M) | B34: 0
A38: Current authority boundary | B38: Current authority boundary | C38: Current authority boundary | D38: Current authority boundary | E38: Current authority boundary | F38: Current authority boundary | G38: Current authority boundary
A40: Named sites and stewards | B40: 0 / 0
A41: Issued keys and vendor awards | B41: 0 / 0
A42: Commissioned builds and completed drills | B42: 0 / 0
A43: Non-displacement warrants | B43: 0 of 18
A44: Root availability and estate activation | B44: 0 / 0
A45: AVW, payments and observations | B45: 0 / 0 / 0
A46: Selection, MAKE and REP-4 | B46: 0 / 0 / 0
A47: Capital status | B47: CO-USE / NO NEW APPROPRIATION

Sheet Warrant Stack
A2: Commissioning warrant stack
A4: The stack may populate a site and activate the estate. It cannot validate a design package, create evidence or release payment.
A6: Instrument | B6: Scope | C6: Issuer | D6: Required input | E6: Authorized act | F6: Forbidden conversion | G6: Required records | H6: Current issued
A7: Site Commissioning Docket | B7: 18 sites | C7: Physical Site Court | D7: named place and control graph | E7: admit one site docket | F7: site class to site fact | G7: 18 | H7: =Inputs!B26 -> 0
A8: Role Appointment Record | B8: 96 appointments | C8: Role registrar | D8: identity and control clearance | E8: appoint one bounded role | F8: appointment to independence | G8: 96 | H8: =Inputs!B29 -> 0
A9: Key and Share Commission | B9: 78 records | C9: Key authority | D9: ceremony and custody chain | E9: issue one scoped key | F9: key to artifact validity | G9: 78 | H9: =Inputs!B30 -> 0
A10: Vendor Admission Record | B10: 72 lots | C10: Control registrar | D10: primary plus N-1 alternate | E10: admit a lot position | F10: award to operating authority | G10: 72 | H10: =Inputs!B31 -> 0
A11: Capacity Reservation Record | B11: 108 resources | C11: Site capacity steward | D11: truth and artifact partitions | E11: reserve bounded capacity | F11: reservation to measurement | G11: 108 | H11: 0
A12: Recovery Trial Record | B12: 180 trials | C12: Independent drill authority | D12: synthetic load and observer | E12: record a recovery clock | F12: drill to AVW | G12: 180 | H12: =Inputs!B34 -> 0
A13: Non-Displacement Warrant | B13: 18 sites | C13: Truth Capacity Court | D13: all stress worlds and schedule | E13: seal co-use boundary | F13: co-use to new appropriation | G13: 18 | H13: =Inputs!B35 -> 0
A14: Root Availability Warrant | B14: 6 roots | C14: Root Artifact Court | D14: three commissioned dockets | E14: make root estate available | F14: availability to package validity | G14: 6 | H14: =Inputs!B36 -> 0
A15: Estate Activation Warrant | B15: 1 cohort | C15: Cohort activation registrar | D15: six simultaneous root warrants | E15: activate technical estate | F15: activation to payment | G15: 1 | H15: =Inputs!B37 -> 0
A16: Artifact Validity Warrant | B16: 30 packages | C16: Root Artifact Court | D16: DRG-1 reconstruction | E16: accept one design artifact | F16: acceptance to observation | G16: 30 | H16: =Inputs!B38 -> 0
A17: Finance Disbursement Warrant | B17: 180 claims | C17: Finance authority | D17: valid artifact and milestone | E17: release bounded payment | F17: payment to evidence | G17: 180 | H17: =Inputs!B39 -> 0
A18: Termination Order | B18: one affected cell | C18: Constitutional custodian | D18: common control, leakage or displacement | E18: seal and return authority | F18: failure to central takeover | G18: 1 | H18: 0

Sheet Site Dockets
A2: Eighteen site commissioning dockets
A4: A docket provides fields for real identities. Every implementation field remains empty until an independent issuer supplies a source record.
A6: Docket | B6: Site slot | C6: Root | D6: Form | E6: Failure domain | F6: Position | G6: Primary role | H6: Standby role | I6: Exchange host | J6: Named site | K6: Charter record | L6: Public steward | M6: Steward control | N6: Site admitted | O6: Failure basin revalidated | P6: Capacity attested | Q6: Enclave build commissioned | R6: Gates passed | S6: State
A7: D-S01 | B7: S01 | C7: ET-A | D7: ET-A-A | E7: FD-A | F7: 1 | G7: Native | H7: Divergence | I7: 1 | N7: 0 | O7: 0 | P7: 0 | Q7: 0 | R7: =COUNTIFS('Commission Gates'!$B$7:$B$366,$B7,'Commission Gates'!$G$7:$G$366,"PASS") -> 5 | S7: =IF(R7=Inputs!$B$18,"READY","OPEN") -> OPEN
A8: D-S02 | B8: S02 | C8: ET-A | D8: ET-A-A | E8: FD-C | F8: 2 | G8: Clean | H8: Native | I8: 0 | N8: 0 | O8: 0 | P8: 0 | Q8: 0 | R8: =COUNTIFS('Commission Gates'!$B$7:$B$366,$B8,'Commission Gates'!$G$7:$G$366,"PASS") -> 5 | S8: =IF(R8=Inputs!$B$18,"READY","OPEN") -> OPEN
A9: D-S03 | B9: S03 | C9: ET-A | D9: ET-A-A | E9: FD-E | F9: 3 | G9: Divergence | H9: Clean | I9: 0 | N9: 0 | O9: 0 | P9: 0 | Q9: 0 | R9: =COUNTIFS('Commission Gates'!$B$7:$B$366,$B9,'Commission Gates'!$G$7:$G$366,"PASS") -> 5 | S9: =IF(R9=Inputs!$B$18,"READY","OPEN") -> OPEN
A10: D-S04 | B10: S04 | C10: CT-C | D10: CT-C-B | E10: FD-B | F10: 1 | G10: Native | H10: Divergence | I10: 1 | N10: 0 | O10: 0 | P10: 0 | Q10: 0 | R10: =COUNTIFS('Commission Gates'!$B$7:$B$366,$B10,'Commission Gates'!$G$7:$G$366,"PASS") -> 5 | S10: =IF(R10=Inputs!$B$18,"READY","OPEN") -> OPEN
A11: D-S05 | B11: S05 | C11: CT-C | D11: CT-C-B | E11: FD-D | F11: 2 | G11: Clean | H11: Native | I11: 0 | N11: 0 | O11: 0 | P11: 0 | Q11: 0 | R11: =COUNTIFS('Commission Gates'!$B$7:$B$366,$B11,'Commission Gates'!$G$7:$G$366,"PASS") -> 5 | S11: =IF(R11=Inputs!$B$18,"READY","OPEN") -> OPEN
A12: D-S06 | B12: S06 | C12: CT-C | D12: CT-C-B | E12: FD-F | F12: 3 | G12: Divergence | H12: Clean | I12: 0 | N12: 0 | O12: 0 | P12: 0 | Q12: 0 | R12: =COUNTIFS('Commission Gates'!$B$7:$B$366,$B12,'Commission Gates'!$G$7:$G$366,"PASS") -> 5 | S12: =IF(R12=Inputs!$B$18,"READY","OPEN") -> OPEN
A13: D-S07 | B13: S07 | C13: HC-A | D13: HC-A-C | E13: FD-A | F13: 1 | G13: Native | H13: Divergence | I13: 0 | N13: 0 | O13: 0 | P13: 0 | Q13: 0 | R13: =COUNTIFS('Commission Gates'!$B$7:$B$366,$B13,'Commission Gates'!$G$7:$G$366,"PASS") -> 5 | S13: =IF(R13=Inputs!$B$18,"READY","OPEN") -> OPEN
A14: D-S08 | B14: S08 | C14: HC-A | D14: HC-A-C | E14: FD-D | F14: 2 | G14: Clean | H14: Native | I14: 0 | N14: 0 | O14: 0 | P14: 0 | Q14: 0 | R14: =COUNTIFS('Commission Gates'!$B$7:$B$366,$B14,'Commission Gates'!$G$7:$G$366,"PASS") -> 5 | S14: =IF(R14=Inputs!$B$18,"READY","OPEN") -> OPEN
A15: D-S09 | B15: S09 | C15: HC-A | D15: HC-A-C | E15: FD-E | F15: 3 | G15: Divergence | H15: Clean | I15: 1 | N15: 0 | O15: 0 | P15: 0 | Q15: 0 | R15: =COUNTIFS('Commission Gates'!$B$7:$B$366,$B15,'Commission Gates'!$G$7:$G$366,"PASS") -> 5 | S15: =IF(R15=Inputs!$B$18,"READY","OPEN") -> OPEN
A16: D-S10 | B16: S10 | C16: LF-B | D16: LF-B-A | E16: FD-B | F16: 1 | G16: Native | H16: Divergence | I16: 0 | N16: 0 | O16: 0 | P16: 0 | Q16: 0 | R16: =COUNTIFS('Commission Gates'!$B$7:$B$366,$B16,'Commission Gates'!$G$7:$G$366,"PASS") -> 5 | S16: =IF(R16=Inputs!$B$18,"READY","OPEN") -> OPEN
A17: D-S11 | B17: S11 | C17: LF-B | D17: LF-B-A | E17: FD-C | F17: 2 | G17: Clean | H17: Native | I17: 1 | N17: 0 | O17: 0 | P17: 0 | Q17: 0 | R17: =COUNTIFS('Commission Gates'!$B$7:$B$366,$B17,'Commission Gates'!$G$7:$G$366,"PASS") -> 5 | S17: =IF(R17=Inputs!$B$18,"READY","OPEN") -> OPEN
A18: D-S12 | B18: S12 | C18: LF-B | D18: LF-B-A | E18: FD-F | F18: 3 | G18: Divergence | H18: Clean | I18: 0 | N18: 0 | O18: 0 | P18: 0 | Q18: 0 | R18: =COUNTIFS('Commission Gates'!$B$7:$B$366,$B18,'Commission Gates'!$G$7:$G$366,"PASS") -> 5 | S18: =IF(R18=Inputs!$B$18,"READY","OPEN") -> OPEN
... A24: D-S18 | B24: S18 | C24: RT-B | D24: RT-B-C | E24: FD-E | F24: 3 | G24: Divergence | H24: Clean | I24: 1 | N24: 0 | O24: 0 | P24: 0 | Q24: 0 | R24: =COUNTIFS('Commission Gates'!$B$7:$B$366,$B24,'Commission Gates'!$G$7:$G$366,"PASS") -> 5 | S24: =IF(R24=Inputs!$B$18,"READY","OPEN") -> OPEN

Sheet Commission Gates
A2: Site commissioning gates
A4: Five architecture gates are constituted at each site. Fifteen implementation gates remain open and noncompensatory.
A6: Gate record | B6: Site | C6: Root | D6: Gate | E6: Required | F6: Current | G6: State | H6: Failure disposition
A7: CG001 | B7: S01 | C7: ET-A | D7: Site slot fixed | E7: 1 | F7: =1 -> 1 | G7: =IF(F7=E7,"PASS","OPEN") -> PASS | H7: RETURN DOCKET
A8: CG002 | B8: S01 | C8: ET-A | D8: Failure domain fixed | E8: 1 | F8: =1 -> 1 | G8: =IF(F8=E8,"PASS","OPEN") -> PASS | H8: RETURN DOCKET
A9: CG003 | B9: S01 | C9: ET-A | D9: Named site record | E9: 1 | F9: =IF('Site Dockets'!J7<>"",1,0) -> 0 | G9: =IF(F9=E9,"PASS","OPEN") -> OPEN | H9: RETURN DOCKET
A10: CG004 | B10: S01 | C10: ET-A | D10: Site charter admitted | E10: 1 | F10: ='Site Dockets'!N7 -> 0 | G10: =IF(F10=E10,"PASS","OPEN") -> OPEN | H10: RETURN DOCKET
A11: CG005 | B11: S01 | C11: ET-A | D11: Failure basin revalidated | E11: 1 | F11: ='Site Dockets'!O7 -> 0 | G11: =IF(F11=E11,"PASS","OPEN") -> OPEN | H11: RETURN DOCKET
A12: CG006 | B12: S01 | C12: ET-A | D12: Public steward named | E12: 1 | F12: =IF('Site Dockets'!L7<>"",1,0) -> 0 | G12: =IF(F12=E12,"PASS","OPEN") -> OPEN | H12: RETURN DOCKET
A13: CG007 | B13: S01 | C13: ET-A | D13: Steward control registered | E13: 1 | F13: =IF('Site Dockets'!M7<>"",1,0) -> 0 | G13: =IF(F13=E13,"PASS","OPEN") -> OPEN | H13: RETURN DOCKET
A14: CG008 | B14: S01 | C14: ET-A | D14: Appointment roster complete | E14: 1 | F14: =IF(COUNTIFS('Role Appointments'!$B$7:$B$102,B14,'Role Appointments'!$J$7:$J$102,"READY")=COUNTIFS('Role Appointments'!$B$7:$B$102,B14),1,0) -> 0 | G14: =IF(F14=E14,"PASS","OPEN") -> OPEN | H14: RETURN DOCKET
A15: CG009 | B15: S01 | C15: ET-A | D15: Key set complete | E15: 1 | F15: =IF(COUNTIFS('Key Custody'!$B$7:$B$84,B15,'Key Custody'!$J$7:$J$84,"READY")=COUNTIFS('Key Custody'!$B$7:$B$84,B15),1,0) -> 0 | G15: =IF(F15=E15,"PASS","OPEN") -> OPEN | H15: RETURN DOCKET
A16: CG010 | B16: S01 | C16: ET-A | D16: Primary vendor slate | E16: 1 | F16: =IF(AND('Vendor Lots'!G7<>"",'Vendor Lots'!G8<>"",'Vendor Lots'!G9<>"",'Vendor Lots'!G10<>""),1,0) -> 0 | G16: =IF(F16=E16,"PASS","OPEN") -> OPEN | H16: RETURN DOCKET
A17: CG011 | B17: S01 | C17: ET-A | D17: N-1 alternate slate | E17: 1 | F17: =IF(AND('Vendor Lots'!I7<>"",'Vendor Lots'!I8<>"",'Vendor Lots'!I9<>"",'Vendor Lots'!I10<>""),1,0) -> 0 | G17: =IF(F17=E17,"PASS","OPEN") -> OPEN | H17: RETURN DOCKET
A18: CG012 | B18: S01 | C18: ET-A | D18: No vendor operating dependency | E18: 1 | F18: =IF(AND('Vendor Lots'!G7<>"",'Vendor Lots'!G8<>"",'Vendor Lots'!G9<>"",'Vendor Lots'!G10<>"",SUM('Vendor Lots'!K7:K10)=0),1,0) -> 0 | G18: =IF(F18=E18,"PASS","OPEN") -> OPEN | H18: TERMINATE CELL
A19: CG013 | B19: S01 | C19: ET-A | D19: Enclave build commissioned | E19: 1 | F19: ='Site Dockets'!Q7 -> 0 | G19: =IF(F19=E19,"PASS","OPEN") -> OPEN | H19: RETURN DOCKET
A20: CG014 | B20: S01 | C20: ET-A | D20: Capacity partition constituted | E20: 1 | F20: =1 -> 1 | G20: =IF(F20=E20,"PASS","OPEN") -> PASS | H20: RETURN DOCKET
A21: CG015 | B21: S01 | C21: ET-A | D21: All capacity worlds pass | E21: 1 | F21: =IF(COUNTIFS('Failure Worlds'!$J$7:$J$36,"PASS")=Inputs!$B$16,1,0) -> 1 | G21: =IF(F21=E21,"PASS","OPEN") -> PASS | H21: HOLD ESTATE
A22: CG016 | B22: S01 | C22: ET-A | D22: Recovery suite executed | E22: 1 | F22: =IF(COUNTIFS('Recovery Clocks'!$J$7:$J$186,"PASS")=180,1,0) -> 0 | G22: =IF(F22=E22,"PASS","OPEN") -> OPEN | H22: RETURN DOCKET
A23: CG017 | B23: S01 | C23: ET-A | D23: Non-displacement warrant | E23: 1 | F23: =IF(Inputs!$B$35=18,1,0) -> 0 | G23: =IF(F23=E23,"PASS","OPEN") -> OPEN | H23: RETURN DOCKET
A24: CG018 | B24: S01 | C24: ET-A | D24: Expiry record | E24: 1 | F24: =0 -> 0 | G24: =IF(F24=E24,"PASS","OPEN") -> OPEN | H24: RETURN DOCKET
A25: CG019 | B25: S01 | C25: ET-A | D25: Rollback route | E25: 1 | F25: =1 -> 1 | G25: =IF(F25=E25,"PASS","OPEN") -> PASS | H25: RETURN DOCKET
A26: CG020 | B26: S01 | C26: ET-A | D26: Cohort activation token | E26: 1 | F26: =Inputs!$B$37 -> 0 | G26: =IF(F26=E26,"PASS","OPEN") -> OPEN | H26: RETURN DOCKET
A27: CG021 | B27: S02 | C27: ET-A | D27: Site slot fixed | E27: 1 | F27: =1 -> 1 | G27: =IF(F27=E27,"PASS","OPEN") -> PASS | H27: RETURN DOCKET
A28: CG022 | B28: S02 | C28: ET-A | D28: Failure domain fixed | E28: 1 | F28: =1 -> 1 | G28: =IF(F28=E28,"PASS","OPEN") -> PASS | H28: RETURN DOCKET
A29: CG023 | B29: S02 | C29: ET-A | D29: Named site record | E29: 1 | F29: =IF('Site Dockets'!J8<>"",1,0) -> 0 | G29: =IF(F29=E29,"PASS","OPEN") -> OPEN | H29: RETURN DOCKET
A30: CG024 | B30: S02 | C30: ET-A | D30: Site charter admitted | E30: 1 | F30: ='Site Dockets'!N8 -> 0 | G30: =IF(F30=E30,"PASS","OPEN") -> OPEN | H30: RETURN DOCKET
A31: CG025 | B31: S02 | C31: ET-A | D31: Failure basin revalidated | E31: 1 | F31: ='Site Dockets'!O8 -> 0 | G31: =IF(F31=E31,"PASS","OPEN") -> OPEN | H31: RETURN DOCKET
A32: CG026 | B32: S02 | C32: ET-A | D32: Public steward named | E32: 1 | F32: =IF('Site Dockets'!L8<>"",1,0) -> 0 | G32: =IF(F32=E32,"PASS","OPEN") -> OPEN | H32: RETURN DOCKET
A33: CG027 | B33: S02 | C33: ET-A | D33: Steward control registered | E33: 1 | F33: =IF('Site Dockets'!M8<>"",1,0) -> 0 | G33: =IF(F33=E33,"PASS","OPEN") -> OPEN | H33: RETURN DOCKET
A34: CG028 | B34: S02 | C34: ET-A | D34: Appointment roster complete | E34: 1 | F34: =IF(COUNTIFS('Role Appointments'!$B$7:$B$102,B34,'Role Appointments'!$J$7:$J$102,"READY")=COUNTIFS('Role Appointments'!$B$7:$B$102,B34),1,0) -> 0 | G34: =IF(F34=E34,"PASS","OPEN") -> OPEN | H34: RETURN DOCKET
A35: CG029 | B35: S02 | C35: ET-A | D35: Key set complete | E35: 1 | F35: =IF(COUNTIFS('Key Custody'!$B$7:$B$84,B35,'Key Custody'!$J$7:$J$84,"READY")=COUNTIFS('Key Custody'!$B$7:$B$84,B35),1,0) -> 0 | G35: =IF(F35=E35,"PASS","OPEN") -> OPEN | H35: RETURN DOCKET
A36: CG030 | B36: S02 | C36: ET-A | D36: Primary vendor slate | E36: 1 | F36: =IF(AND('Vendor Lots'!G11<>"",'Vendor Lots'!G12<>"",'Vendor Lots'!G13<>"",'Vendor Lots'!G14<>""),1,0) -> 0 | G36: =IF(F36=E36,"PASS","OPEN") -> OPEN | H36: RETURN DOCKET
A37: CG031 | B37: S02 | C37: ET-A | D37: N-1 alternate slate | E37: 1 | F37: =IF(AND('Vendor Lots'!I11<>"",'Vendor Lots'!I12<>"",'Vendor Lots'!I13<>"",'Vendor Lots'!I14<>""),1,0) -> 0 | G37: =IF(F37=E37,"PASS","OPEN") -> OPEN | H37: RETURN DOCKET
A38: CG032 | B38: S02 | C38: ET-A | D38: No vendor operating dependency | E38: 1 | F38: =IF(AND('Vendor Lots'!G11<>"",'Vendor Lots'!G12<>"",'Vendor Lots'!G13<>"",'Vendor Lots'!G14<>"",SUM('Vendor Lots'!K11:K14)=0),1,0) -> 0 | G38: =IF(F38=E38,"PASS","OPEN") -> OPEN | H38: TERMINATE CELL
A39: CG033 | B39: S02 | C39: ET-A | D39: Enclave build commissioned | E39: 1 | F39: ='Site Dockets'!Q8 -> 0 | G39: =IF(F39=E39,"PASS","OPEN") -> OPEN | H39: RETURN DOCKET
A40: CG034 | B40: S02 | C40: ET-A | D40: Capacity partition constituted | E40: 1 | F40: =1 -> 1 | G40: =IF(F40=E40,"PASS","OPEN") -> PASS | H40: RETURN DOCKET
A41: CG035 | B41: S02 | C41: ET-A | D41: All capacity worlds pass | E41: 1 | F41: =IF(COUNTIFS('Failure Worlds'!$J$7:$J$36,"PASS")=Inputs!$B$16,1,0) -> 1 | G41: =IF(F41=E41,"PASS","OPEN") -> PASS | H41: HOLD ESTATE
A42: CG036 | B42: S02 | C42: ET-A | D42: Recovery suite executed | E42: 1 | F42: =IF(COUNTIFS('Recovery Clocks'!$J$7:$J$186,"PASS")=180,1,0) -> 0 | G42: =IF(F42=E42,"PASS","OPEN") -> OPEN | H42: RETURN DOCKET
A43: CG037 | B43: S02 | C43: ET-A | D43: Non-displacement warrant | E43: 1 | F43: =IF(Inputs!$B$35=18,1,0) -> 0 | G43: =IF(F43=E43,"PASS","OPEN") -> OPEN | H43: RETURN DOCKET
A44: CG038 | B44: S02 | C44: ET-A | D44: Expiry record | E44: 1 | F44: =0 -> 0 | G44: =IF(F44=E44,"PASS","OPEN") -> OPEN | H44: RETURN DOCKET
A45: CG039 | B45: S02 | C45: ET-A | D45: Rollback route | E45: 1 | F45: =1 -> 1 | G45: =IF(F45=E45,"PASS","OPEN") -> PASS | H45: RETURN DOCKET
A46: CG040 | B46: S02 | C46: ET-A | D46: Cohort activation token | E46: 1 | F46: =Inputs!$B$37 -> 0 | G46: =IF(F46=E46,"PASS","OPEN") -> OPEN | H46: RETURN DOCKET
A47: CG041 | B47: S03 | C47: ET-A | D47: Site slot fixed | E47: 1 | F47: =1 -> 1 | G47: =IF(F47=E47,"PASS","OPEN") -> PASS | H47: RETURN DOCKET
A48: CG042 | B48: S03 | C48: ET-A | D48: Failure domain fixed | E48: 1 | F48: =1 -> 1 | G48: =IF(F48=E48,"PASS","OPEN") -> PASS | H48: RETURN DOCKET
A49: CG043 | B49: S03 | C49: ET-A | D49: Named site record | E49: 1 | F49: =IF('Site Dockets'!J9<>"",1,0) -> 0 | G49: =IF(F49=E49,"PASS","OPEN") -> OPEN | H49: RETURN DOCKET
A50: CG044 | B50: S03 | C50: ET-A | D50: Site charter admitted | E50: 1 | F50: ='Site Dockets'!N9 -> 0 | G50: =IF(F50=E50,"PASS","OPEN") -> OPEN | H50: RETURN DOCKET
A51: CG045 | B51: S03 | C51: ET-A | D51: Failure basin revalidated | E51: 1 | F51: ='Site Dockets'!O9 -> 0 | G51: =IF(F51=E51,"PASS","OPEN") -> OPEN | H51: RETURN DOCKET
A52: CG046 | B52: S03 | C52: ET-A | D52: Public steward named | E52: 1 | F52: =IF('Site Dockets'!L9<>"",1,0) -> 0 | G52: =IF(F52=E52,"PASS","OPEN") -> OPEN | H52: RETURN DOCKET
A53: CG047 | B53: S03 | C53: ET-A | D53: Steward control registered | E53: 1 | F53: =IF('Site Dockets'!M9<>"",1,0) -> 0 | G53: =IF(F53=E53,"PASS","OPEN") -> OPEN | H53: RETURN DOCKET
A54: CG048 | B54: S03 | C54: ET-A | D54: Appointment roster complete | E54: 1 | F54: =IF(COUNTIFS('Role Appointments'!$B$7:$B$102,B54,'Role Appointments'!$J$7:$J$102,"READY")=COUNTIFS('Role Appointments'!$B$7:$B$102,B54),1,0) -> 0 | G54: =IF(F54=E54,"PASS","OPEN") -> OPEN | H54: RETURN DOCKET
A55: CG049 | B55: S03 | C55: ET-A | D55: Key set complete | E55: 1 | F55: =IF(COUNTIFS('Key Custody'!$B$7:$B$84,B55,'Key Custody'!$J$7:$J$84,"READY")=COUNTIFS('Key Custody'!$B$7:$B$84,B55),1,0) -> 0 | G55: =IF(F55=E55,"PASS","OPEN") -> OPEN | H55: RETURN DOCKET
A56: CG050 | B56: S03 | C56: ET-A | D56: Primary vendor slate | E56: 1 | F56: =IF(AND('Vendor Lots'!G15<>"",'Vendor Lots'!G16<>"",'Vendor Lots'!G17<>"",'Vendor Lots'!G18<>""),1,0) -> 0 | G56: =IF(F56=E56,"PASS","OPEN") -> OPEN | H56: RETURN DOCKET
A57: CG051 | B57: S03 | C57: ET-A | D57: N-1 alternate slate | E57: 1 | F57: =IF(AND('Vendor Lots'!I15<>"",'Vendor Lots'!I16<>"",'Vendor Lots'!I17<>"",'Vendor Lots'!I18<>""),1,0) -> 0 | G57: =IF(F57=E57,"PASS","OPEN") -> OPEN | H57: RETURN DOCKET
A58: CG052 | B58: S03 | C58: ET-A | D58: No vendor operating dependency | E58: 1 | F58: =IF(AND('Vendor Lots'!G15<>"",'Vendor Lots'!G16<>"",'Vendor Lots'!G17<>"",'Vendor Lots'!G18<>"",SUM('Vendor Lots'!K15:K18)=0),1,0) -> 0 | G58: =IF(F58=E58,"PASS","OPEN") -> OPEN | H58: TERMINATE CELL
A59: CG053 | B59: S03 | C59: ET-A | D59: Enclave build commissioned | E59: 1 | F59: ='Site Dockets'!Q9 -> 0 | G59: =IF(F59=E59,"PASS","OPEN") -> OPEN | H59: RETURN DOCKET
A60: CG054 | B60: S03 | C60: ET-A | D60: Capacity partition constituted | E60: 1 | F60: =1 -> 1 | G60: =IF(F60=E60,"PASS","OPEN") -> PASS | H60: RETURN DOCKET
A61: CG055 | B61: S03 | C61: ET-A | D61: All capacity worlds pass | E61: 1 | F61: =IF(COUNTIFS('Failure Worlds'!$J$7:$J$36,"PASS")=Inputs!$B$16,1,0) -> 1 | G61: =IF(F61=E61,"PASS","OPEN") -> PASS | H61: HOLD ESTATE
A62: CG056 | B62: S03 | C62: ET-A | D62: Recovery suite executed | E62: 1 | F62: =IF(COUNTIFS('Recovery Clocks'!$J$7:$J$186,"PASS")=180,1,0) -> 0 | G62: =IF(F62=E62,"PASS","OPEN") -> OPEN | H62: RETURN DOCKET
A63: CG057 | B63: S03 | C63: ET-A | D63: Non-displacement warrant | E63: 1 | F63: =IF(Inputs!$B$35=18,1,0) -> 0 | G63: =IF(F63=E63,"PASS","OPEN") -> OPEN | H63: RETURN DOCKET
A64: CG058 | B64: S03 | C64: ET-A | D64: Expiry record | E64: 1 | F64: =0 -> 0 | G64: =IF(F64=E64,"PASS","OPEN") -> OPEN | H64: RETURN DOCKET
A65: CG059 | B65: S03 | C65: ET-A | D65: Rollback route | E65: 1 | F65: =1 -> 1 | G65: =IF(F65=E65,"PASS","OPEN") -> PASS | H65: RETURN DOCKET
A66: CG060 | B66: S03 | C66: ET-A | D66: Cohort activation token | E66: 1 | F66: =Inputs!$B$37 -> 0 | G66: =IF(F66=E66,"PASS","OPEN") -> OPEN | H66: RETURN DOCKET
A67: CG061 | B67: S04 | C67: CT-C | D67: Site slot fixed | E67: 1 | F67: =1 -> 1 | G67: =IF(F67=E67,"PASS","OPEN") -> PASS | H67: RETURN DOCKET
A68: CG062 | B68: S04 | C68: CT-C | D68: Failure domain fixed | E68: 1 | F68: =1 -> 1 | G68: =IF(F68=E68,"PASS","OPEN") -> PASS | H68: RETURN DOCKET
A69: CG063 | B69: S04 | C69: CT-C | D69: Named site record | E69: 1 | F69: =IF('Site Dockets'!J10<>"",1,0) -> 0 | G69: =IF(F69=E69,"PASS","OPEN") -> OPEN | H69: RETURN DOCKET
A70: CG064 | B70: S04 | C70: CT-C | D70: Site charter admitted | E70: 1 | F70: ='Site Dockets'!N10 -> 0 | G70: =IF(F70=E70,"PASS","OPEN") -> OPEN | H70: RETURN DOCKET
A71: CG065 | B71: S04 | C71: CT-C | D71: Failure basin revalidated | E71: 1 | F71: ='Site Dockets'!O10 -> 0 | G71: =IF(F71=E71,"PASS","OPEN") -> OPEN | H71: RETURN DOCKET
A72: CG066 | B72: S04 | C72: CT-C | D72: Public steward named | E72: 1 | F72: =IF('Site Dockets'!L10<>"",1,0) -> 0 | G72: =IF(F72=E72,"PASS","OPEN") -> OPEN | H72: RETURN DOCKET
A73: CG067 | B73: S04 | C73: CT-C | D73: Steward control registered | E73: 1 | F73: =IF('Site Dockets'!M10<>"",1,0) -> 0 | G73: =IF(F73=E73,"PASS","OPEN") -> OPEN | H73: RETURN DOCKET
A74: CG068 | B74: S04 | C74: CT-C | D74: Appointment roster complete | E74: 1 | F74: =IF(COUNTIFS('Role Appointments'!$B$7:$B$102,B74,'Role Appointments'!$J$7:$J$102,"READY")=COUNTIFS('Role Appointments'!$B$7:$B$102,B74),1,0) -> 0 | G74: =IF(F74=E74,"PASS","OPEN") -> OPEN | H74: RETURN DOCKET
A75: CG069 | B75: S04 | C75: CT-C | D75: Key set complete | E75: 1 | F75: =IF(COUNTIFS('Key Custody'!$B$7:$B$84,B75,'Key Custody'!$J$7:$J$84,"READY")=COUNTIFS('Key Custody'!$B$7:$B$84,B75),1,0) -> 0 | G75: =IF(F75=E75,"PASS","OPEN") -> OPEN | H75: RETURN DOCKET
A76: CG070 | B76: S04 | C76: CT-C | D76: Primary vendor slate | E76: 1 | F76: =IF(AND('Vendor Lots'!G19<>"",'Vendor Lots'!G20<>"",'Vendor Lots'!G21<>"",'Vendor Lots'!G22<>""),1,0) -> 0 | G76: =IF(F76=E76,"PASS","OPEN") -> OPEN | H76: RETURN DOCKET
A77: CG071 | B77: S04 | C77: CT-C | D77: N-1 alternate slate | E77: 1 | F77: =IF(AND('Vendor Lots'!I19<>"",'Vendor Lots'!I20<>"",'Vendor Lots'!I21<>"",'Vendor Lots'!I22<>""),1,0) -> 0 | G77: =IF(F77=E77,"PASS","OPEN") -> OPEN | H77: RETURN DOCKET
A78: CG072 | B78: S04 | C78: CT-C | D78: No vendor operating dependency | E78: 1 | F78: =IF(AND('Vendor Lots'!G19<>"",'Vendor Lots'!G20<>"",'Vendor Lots'!G21<>"",'Vendor Lots'!G22<>"",SUM('Vendor Lots'!K19:K22)=0),1,0) -> 0 | G78: =IF(F78=E78,"PASS","OPEN") -> OPEN | H78: TERMINATE CELL
A79: CG073 | B79: S04 | C79: CT-C | D79: Enclave build commissioned | E79: 1 | F79: ='Site Dockets'!Q10 -> 0 | G79: =IF(F79=E79,"PASS","OPEN") -> OPEN | H79: RETURN DOCKET
A80: CG074 | B80: S04 | C80: CT-C | D80: Capacity partition constituted | E80: 1 | F80: =1 -> 1 | G80: =IF(F80=E80,"PASS","OPEN") -> PASS | H80: RETURN DOCKET
A81: CG075 | B81: S04 | C81: CT-C | D81: All capacity worlds pass | E81: 1 | F81: =IF(COUNTIFS('Failure Worlds'!$J$7:$J$36,"PASS")=Inputs!$B$16,1,0) -> 1 | G81: =IF(F81=E81,"PASS","OPEN") -> PASS | H81: HOLD ESTATE
A82: CG076 | B82: S04 | C82: CT-C | D82: Recovery suite executed | E82: 1 | F82: =IF(COUNTIFS('Recovery Clocks'!$J$7:$J$186,"PASS")=180,1,0) -> 0 | G82: =IF(F82=E82,"PASS","OPEN") -> OPEN | H82: RETURN DOCKET
A83: CG077 | B83: S04 | C83: CT-C | D83: Non-displacement warrant | E83: 1 | F83: =IF(Inputs!$B$35=18,1,0) -> 0 | G83: =IF(F83=E83,"PASS","OPEN") -> OPEN | H83: RETURN DOCKET
A84: CG078 | B84: S04 | C84: CT-C | D84: Expiry record | E84: 1 | F84: =0 -> 0 | G84: =IF(F84=E84,"PASS","OPEN") -> OPEN | H84: RETURN DOCKET
A85: CG079 | B85: S04 | C85: CT-C | D85: Rollback route | E85: 1 | F85: =1 -> 1 | G85: =IF(F85=E85,"PASS","OPEN") -> PASS | H85: RETURN DOCKET
A86: CG080 | B86: S04 | C86: CT-C | D86: Cohort activation token | E86: 1 | F86: =Inputs!$B$37 -> 0 | G86: =IF(F86=E86,"PASS","OPEN") -> OPEN | H86: RETURN DOCKET
A87: CG081 | B87: S05 | C87: CT-C | D87: Site slot fixed | E87: 1 | F87: =1 -> 1 | G87: =IF(F87=E87,"PASS","OPEN") -> PASS | H87: RETURN DOCKET
A88: CG082 | B88: S05 | C88: CT-C | D88: Failure domain fixed | E88: 1 | F88: =1 -> 1 | G88: =IF(F88=E88,"PASS","OPEN") -> PASS | H88: RETURN DOCKET
A89: CG083 | B89: S05 | C89: CT-C | D89: Named site record | E89: 1 | F89: =IF('Site Dockets'!J11<>"",1,0) -> 0 | G89: =IF(F89=E89,"PASS","OPEN") -> OPEN | H89: RETURN DOCKET
A90: CG084 | B90: S05 | C90: CT-C | D90: Site charter admitted | E90: 1 | F90: ='Site Dockets'!N11 -> 0 | G90: =IF(F90=E90,"PASS","OPEN") -> OPEN | H90: RETURN DOCKET
A91: CG085 | B91: S05 | C91: CT-C | D91: Failure basin revalidated | E91: 1 | F91: ='Site Dockets'!O11 -> 0 | G91: =IF(F91=E91,"PASS","OPEN") -> OPEN | H91: RETURN DOCKET
A92: CG086 | B92: S05 | C92: CT-C | D92: Public steward named | E92: 1 | F92: =IF('Site Dockets'!L11<>"",1,0) -> 0 | G92: =IF(F92=E92,"PASS","OPEN") -> OPEN | H92: RETURN DOCKET
A93: CG087 | B93: S05 | C93: CT-C | D93: Steward control registered | E93: 1 | F93: =IF('Site Dockets'!M11<>"",1,0) -> 0 | G93: =IF(F93=E93,"PASS","OPEN") -> OPEN | H93: RETURN DOCKET
A94: CG088 | B94: S05 | C94: CT-C | D94: Appointment roster complete | E94: 1 | F94: =IF(COUNTIFS('Role Appointments'!$B$7:$B$102,B94,'Role Appointments'!$J$7:$J$102,"READY")=COUNTIFS('Role Appointments'!$B$7:$B$102,B94),1,0) -> 0 | G94: =IF(F94=E94,"PASS","OPEN") -> OPEN | H94: RETURN DOCKET
A95: CG089 | B95: S05 | C95: CT-C | D95: Key set complete | E95: 1 | F95: =IF(COUNTIFS('Key Custody'!$B$7:$B$84,B95,'Key Custody'!$J$7:$J$84,"READY")=COUNTIFS('Key Custody'!$B$7:$B$84,B95),1,0) -> 0 | G95: =IF(F95=E95,"PASS","OPEN") -> OPEN | H95: RETURN DOCKET
A96: CG090 | B96: S05 | C96: CT-C | D96: Primary vendor slate | E96: 1 | F96: =IF(AND('Vendor Lots'!G23<>"",'Vendor Lots'!G24<>"",'Vendor Lots'!G25<>"",'Vendor Lots'!G26<>""),1,0) -> 0 | G96: =IF(F96=E96,"PASS","OPEN") -> OPEN | H96: RETURN DOCKET
A97: CG091 | B97: S05 | C97: CT-C | D97: N-1 alternate slate | E97: 1 | F97: =IF(AND('Vendor Lots'!I23<>"",'Vendor Lots'!I24<>"",'Vendor Lots'!I25<>"",'Vendor Lots'!I26<>""),1,0) -> 0 | G97: =IF(F97=E97,"PASS","OPEN") -> OPEN | H97: RETURN DOCKET
A98: CG092 | B98: S05 | C98: CT-C | D98: No vendor operating dependency | E98: 1 | F98: =IF(AND('Vendor Lots'!G23<>"",'Vendor Lots'!G24<>"",'Vendor Lots'!G25<>"",'Vendor Lots'!G26<>"",SUM('Vendor Lots'!K23:K26)=0),1,0) -> 0 | G98: =IF(F98=E98,"PASS","OPEN") -> OPEN | H98: TERMINATE CELL
A99: CG093 | B99: S05 | C99: CT-C | D99: Enclave build commissioned | E99: 1 | F99: ='Site Dockets'!Q11 -> 0 | G99: =IF(F99=E99,"PASS","OPEN") -> OPEN | H99: RETURN DOCKET
A100: CG094 | B100: S05 | C100: CT-C | D100: Capacity partition constituted | E100: 1 | F100: =1 -> 1 | G100: =IF(F100=E100,"PASS","OPEN") -> PASS | H100: RETURN DOCKET
A101: CG095 | B101: S05 | C101: CT-C | D101: All capacity worlds pass | E101: 1 | F101: =IF(COUNTIFS('Failure Worlds'!$J$7:$J$36,"PASS")=Inputs!$B$16,1,0) -> 1 | G101: =IF(F101=E101,"PASS","OPEN") -> PASS | H101: HOLD ESTATE
A102: CG096 | B102: S05 | C102: CT-C | D102: Recovery suite executed | E102: 1 | F102: =IF(COUNTIFS('Recovery Clocks'!$J$7:$J$186,"PASS")=180,1,0) -> 0 | G102: =IF(F102=E102,"PASS","OPEN") -> OPEN | H102: RETURN DOCKET
A103: CG097 | B103: S05 | C103: CT-C | D103: Non-displacement warrant | E103: 1 | F103: =IF(Inputs!$B$35=18,1,0) -> 0 | G103: =IF(F103=E103,"PASS","OPEN") -> OPEN | H103: RETURN DOCKET
...

Sheet Role Appointments
A2: Separated role appointments
A4: No person, employer or beneficial-control group may occupy incompatible producer, reconstruction, court, custody and finance roles.
A6: Appointment | B6: Site | C6: Root | D6: Failure domain | E6: Role | F6: Named appointee | G6: Control group | H6: Conflict count | I6: Appointment admitted | J6: State
A7: RA001 | B7: S01 | C7: ET-A | D7: FD-A | E7: Site steward | H7: 0 | I7: 0 | J7: =IF(AND(F7<>"",G7<>"",H7=0,I7=1),"READY","OPEN") -> OPEN
A8: RA002 | B8: S01 | C8: ET-A | D8: FD-A | E8: Native operator | H8: 0 | I8: 0 | J8: =IF(AND(F8<>"",G8<>"",H8=0,I8=1),"READY","OPEN") -> OPEN
A9: RA003 | B9: S01 | C9: ET-A | D9: FD-A | E9: Clean constructor | H9: 0 | I9: 0 | J9: =IF(AND(F9<>"",G9<>"",H9=0,I9=1),"READY","OPEN") -> OPEN
A10: RA004 | B10: S01 | C10: ET-A | D10: FD-A | E10: Divergence challenger | H10: 0 | I10: 0 | J10: =IF(AND(F10<>"",G10<>"",H10=0,I10=1),"READY","OPEN") -> OPEN
A11: RA005 | B11: S01 | C11: ET-A | D11: FD-A | E11: Court adjudicator | H11: 0 | I11: 0 | J11: =IF(AND(F11<>"",G11<>"",H11=0,I11=1),"READY","OPEN") -> OPEN
A12: RA006 | B12: S01 | C12: ET-A | D12: FD-A | E12: Exchange custodian | H12: 0 | I12: 0 | J12: =IF(AND(F12<>"",G12<>"",H12=0,I12=1),"READY","OPEN") -> OPEN
A13: RA007 | B13: S02 | C13: ET-A | D13: FD-C | E13: Site steward | H13: 0 | I13: 0 | J13: =IF(AND(F13<>"",G13<>"",H13=0,I13=1),"READY","OPEN") -> OPEN
A14: RA008 | B14: S02 | C14: ET-A | D14: FD-C | E14: Native operator | H14: 0 | I14: 0 | J14: =IF(AND(F14<>"",G14<>"",H14=0,I14=1),"READY","OPEN") -> OPEN
A15: RA009 | B15: S02 | C15: ET-A | D15: FD-C | E15: Clean constructor | H15: 0 | I15: 0 | J15: =IF(AND(F15<>"",G15<>"",H15=0,I15=1),"READY","OPEN") -> OPEN
A16: RA010 | B16: S02 | C16: ET-A | D16: FD-C | E16: Divergence challenger | H16: 0 | I16: 0 | J16: =IF(AND(F16<>"",G16<>"",H16=0,I16=1),"READY","OPEN") -> OPEN
A17: RA011 | B17: S02 | C17: ET-A | D17: FD-C | E17: Court adjudicator | H17: 0 | I17: 0 | J17: =IF(AND(F17<>"",G17<>"",H17=0,I17=1),"READY","OPEN") -> OPEN
A18: RA012 | B18: S03 | C18: ET-A | D18: FD-E | E18: Site steward | H18: 0 | I18: 0 | J18: =IF(AND(F18<>"",G18<>"",H18=0,I18=1),"READY","OPEN") -> OPEN
... A102: RA096 | B102: S18 | C102: RT-B | D102: FD-E | E102: Exchange custodian | H102: 0 | I102: 0 | J102: =IF(AND(F102<>"",G102<>"",H102=0,I102=1),"READY","OPEN") -> OPEN

Sheet Key Custody
A2: Key and threshold-share custody
A4: Keys are purpose-bound. Enclave, court and Exchange credentials may not be re-used across roles or roots.
A6: Record | B6: Site | C6: Root | D6: Failure domain | E6: Key class | F6: Named custodian | G6: Key identifier | H6: Ceremony complete | I6: Offline copy | J6: State
A7: K001 | B7: S01 | C7: ET-A | D7: FD-A | E7: Native enclave | H7: 0 | I7: 0 | J7: =IF(AND(F7<>"",G7<>"",H7=1,I7=1),"READY","OPEN") -> OPEN
A8: K002 | B8: S01 | C8: ET-A | D8: FD-A | E8: Clean enclave | H8: 0 | I8: 0 | J8: =IF(AND(F8<>"",G8<>"",H8=1,I8=1),"READY","OPEN") -> OPEN
A9: K003 | B9: S01 | C9: ET-A | D9: FD-A | E9: Divergence enclave | H9: 0 | I9: 0 | J9: =IF(AND(F9<>"",G9<>"",H9=1,I9=1),"READY","OPEN") -> OPEN
A10: K004 | B10: S01 | C10: ET-A | D10: FD-A | E10: Court share | H10: 0 | I10: 0 | J10: =IF(AND(F10<>"",G10<>"",H10=1,I10=1),"READY","OPEN") -> OPEN
A11: K005 | B11: S01 | C11: ET-A | D11: FD-A | E11: Exchange share | H11: 0 | I11: 0 | J11: =IF(AND(F11<>"",G11<>"",H11=1,I11=1),"READY","OPEN") -> OPEN
A12: K006 | B12: S02 | C12: ET-A | D12: FD-C | E12: Native enclave | H12: 0 | I12: 0 | J12: =IF(AND(F12<>"",G12<>"",H12=1,I12=1),"READY","OPEN") -> OPEN
A13: K007 | B13: S02 | C13: ET-A | D13: FD-C | E13: Clean enclave | H13: 0 | I13: 0 | J13: =IF(AND(F13<>"",G13<>"",H13=1,I13=1),"READY","OPEN") -> OPEN
A14: K008 | B14: S02 | C14: ET-A | D14: FD-C | E14: Divergence enclave | H14: 0 | I14: 0 | J14: =IF(AND(F14<>"",G14<>"",H14=1,I14=1),"READY","OPEN") -> OPEN
A15: K009 | B15: S02 | C15: ET-A | D15: FD-C | E15: Court share | H15: 0 | I15: 0 | J15: =IF(AND(F15<>"",G15<>"",H15=1,I15=1),"READY","OPEN") -> OPEN
A16: K010 | B16: S03 | C16: ET-A | D16: FD-E | E16: Native enclave | H16: 0 | I16: 0 | J16: =IF(AND(F16<>"",G16<>"",H16=1,I16=1),"READY","OPEN") -> OPEN
A17: K011 | B17: S03 | C17: ET-A | D17: FD-E | E17: Clean enclave | H17: 0 | I17: 0 | J17: =IF(AND(F17<>"",G17<>"",H17=1,I17=1),"READY","OPEN") -> OPEN
A18: K012 | B18: S03 | C18: ET-A | D18: FD-E | E18: Divergence enclave | H18: 0 | I18: 0 | J18: =IF(AND(F18<>"",G18<>"",H18=1,I18=1),"READY","OPEN") -> OPEN
... A84: K078 | B84: S18 | C84: RT-B | D84: FD-E | E84: Exchange share | H84: 0 | I84: 0 | J84: =IF(AND(F84<>"",G84<>"",H84=1,I84=1),"READY","OPEN") -> OPEN

Sheet Vendor Lots
A2: Vendor lot and exit register
A4: A vendor may build or support an enclave but cannot become its operator, custodian, court or recovery authority.
A6: Lot | B6: Site | C6: Root | D6: Failure domain | E6: Class | F6: Capital ceiling (USD M) | G6: Primary vendor | H6: Primary control | I6: N-1 alternate | J6: Alternate control | K6: Operating dependency | L6: Control collision | M6: State
A7: VL001 | B7: S01 | C7: ET-A | D7: FD-A | E7: Host hardening | F7: 10.5 | K7: 0 | L7: 0 | M7: =IF(AND(G7<>"",H7<>"",I7<>"",J7<>"",H7<>J7,K7=0,L7=0),"READY","OPEN") -> OPEN
A8: VL002 | B8: S01 | C8: ET-A | D8: FD-A | E8: Enclave compute | F8: 7.5 | K8: 0 | L8: 0 | M8: =IF(AND(G8<>"",H8<>"",I8<>"",J8<>"",H8<>J8,K8=0,L8=0),"READY","OPEN") -> OPEN
A9: VL003 | B9: S01 | C9: ET-A | D9: FD-A | E9: Cross-region network | F9: 3 | K9: 0 | L9: 0 | M9: =IF(AND(G9<>"",H9<>"",I9<>"",J9<>"",H9<>J9,K9=0,L9=0),"READY","OPEN") -> OPEN
A10: VL004 | B10: S01 | C10: ET-A | D10: FD-A | E10: Operations support | F10: 0 | K10: 0 | L10: 0 | M10: =IF(AND(G10<>"",H10<>"",I10<>"",J10<>"",H10<>J10,K10=0,L10=0),"READY","OPEN") -> OPEN
A11: VL005 | B11: S02 | C11: ET-A | D11: FD-C | E11: Host hardening | F11: 10.5 | K11: 0 | L11: 0 | M11: =IF(AND(G11<>"",H11<>"",I11<>"",J11<>"",H11<>J11,K11=0,L11=0),"READY","OPEN") -> OPEN
A12: VL006 | B12: S02 | C12: ET-A | D12: FD-C | E12: Enclave compute | F12: 7.5 | K12: 0 | L12: 0 | M12: =IF(AND(G12<>"",H12<>"",I12<>"",J12<>"",H12<>J12,K12=0,L12=0),"READY","OPEN") -> OPEN
A13: VL007 | B13: S02 | C13: ET-A | D13: FD-C | E13: Cross-region network | F13: 3 | K13: 0 | L13: 0 | M13: =IF(AND(G13<>"",H13<>"",I13<>"",J13<>"",H13<>J13,K13=0,L13=0),"READY","OPEN") -> OPEN
A14: VL008 | B14: S02 | C14: ET-A | D14: FD-C | E14: Operations support | F14: 0 | K14: 0 | L14: 0 | M14: =IF(AND(G14<>"",H14<>"",I14<>"",J14<>"",H14<>J14,K14=0,L14=0),"READY","OPEN") -> OPEN
A15: VL009 | B15: S03 | C15: ET-A | D15: FD-E | E15: Host hardening | F15: 10.5 | K15: 0 | L15: 0 | M15: =IF(AND(G15<>"",H15<>"",I15<>"",J15<>"",H15<>J15,K15=0,L15=0),"READY","OPEN") -> OPEN
A16: VL010 | B16: S03 | C16: ET-A | D16: FD-E | E16: Enclave compute | F16: 7.5 | K16: 0 | L16: 0 | M16: =IF(AND(G16<>"",H16<>"",I16<>"",J16<>"",H16<>J16,K16=0,L16=0),"READY","OPEN") -> OPEN
A17: VL011 | B17: S03 | C17: ET-A | D17: FD-E | E17: Cross-region network | F17: 3 | K17: 0 | L17: 0 | M17: =IF(AND(G17<>"",H17<>"",I17<>"",J17<>"",H17<>J17,K17=0,L17=0),"READY","OPEN") -> OPEN
A18: VL012 | B18: S03 | C18: ET-A | D18: FD-E | E18: Operations support | F18: 0 | K18: 0 | L18: 0 | M18: =IF(AND(G18<>"",H18<>"",I18<>"",J18<>"",H18<>J18,K18=0,L18=0),"READY","OPEN") -> OPEN
... A78: VL072 | B78: S18 | C78: RT-B | D78: FD-E | E78: Operations support | F78: 0 | K78: 0 | L78: 0 | M78: =IF(AND(G78<>"",H78<>"",I78<>"",J78<>"",H78<>J78,K78=0,L78=0),"READY","OPEN") -> OPEN

Sheet Capacity Basis
A2: Site-resource capacity partitions
A4: Each normalized host resource reserves seventy-five units for the physical truth train, twenty for the artifact estate and five as unassigned headroom.
A6: Record | B6: Site | C6: Root | D6: Failure domain | E6: Resource | F6: Host units | G6: Truth reservation | H6: Artifact partition | I6: Unassigned headroom | J6: Partition sum | K6: State
A7: CB001 | B7: S01 | C7: ET-A | D7: FD-A | E7: Secure compute | F7: =Inputs!$B$11 -> 100 | G7: =Inputs!$B$12 -> 75 | H7: =Inputs!$B$13 -> 20 | I7: =F7-G7-H7 -> 5 | J7: =SUM(G7:I7) -> 100 | K7: =IF(AND(I7>=Inputs!$B$15,J7=F7),"PASS","FAIL") -> PASS
A8: CB002 | B8: S01 | C8: ET-A | D8: FD-A | E8: Protected storage | F8: =Inputs!$B$11 -> 100 | G8: =Inputs!$B$12 -> 75 | H8: =Inputs!$B$13 -> 20 | I8: =F8-G8-H8 -> 5 | J8: =SUM(G8:I8) -> 100 | K8: =IF(AND(I8>=Inputs!$B$15,J8=F8),"PASS","FAIL") -> PASS
A9: CB003 | B9: S01 | C9: ET-A | D9: FD-A | E9: Cross-region network | F9: =Inputs!$B$11 -> 100 | G9: =Inputs!$B$12 -> 75 | H9: =Inputs!$B$13 -> 20 | I9: =F9-G9-H9 -> 5 | J9: =SUM(G9:I9) -> 100 | K9: =IF(AND(I9>=Inputs!$B$15,J9=F9),"PASS","FAIL") -> PASS
A10: CB004 | B10: S01 | C10: ET-A | D10: FD-A | E10: Power and cooling | F10: =Inputs!$B$11 -> 100 | G10: =Inputs!$B$12 -> 75 | H10: =Inputs!$B$13 -> 20 | I10: =F10-G10-H10 -> 5 | J10: =SUM(G10:I10) -> 100 | K10: =IF(AND(I10>=Inputs!$B$15,J10=F10),"PASS","FAIL") -> PASS
A11: CB005 | B11: S01 | C11: ET-A | D11: FD-A | E11: Controlled workspace | F11: =Inputs!$B$11 -> 100 | G11: =Inputs!$B$12 -> 75 | H11: =Inputs!$B$13 -> 20 | I11: =F11-G11-H11 -> 5 | J11: =SUM(G11:I11) -> 100 | K11: =IF(AND(I11>=Inputs!$B$15,J11=F11),"PASS","FAIL") -> PASS
A12: CB006 | B12: S01 | C12: ET-A | D12: FD-A | E12: Specialist labor | F12: =Inputs!$B$11 -> 100 | G12: =Inputs!$B$12 -> 75 | H12: =Inputs!$B$13 -> 20 | I12: =F12-G12-H12 -> 5 | J12: =SUM(G12:I12) -> 100 | K12: =IF(AND(I12>=Inputs!$B$15,J12=F12),"PASS","FAIL") -> PASS
A13: CB007 | B13: S02 | C13: ET-A | D13: FD-C | E13: Secure compute | F13: =Inputs!$B$11 -> 100 | G13: =Inputs!$B$12 -> 75 | H13: =Inputs!$B$13 -> 20 | I13: =F13-G13-H13 -> 5 | J13: =SUM(G13:I13) -> 100 | K13: =IF(AND(I13>=Inputs!$B$15,J13=F13),"PASS","FAIL") -> PASS
A14: CB008 | B14: S02 | C14: ET-A | D14: FD-C | E14: Protected storage | F14: =Inputs!$B$11 -> 100 | G14: =Inputs!$B$12 -> 75 | H14: =Inputs!$B$13 -> 20 | I14: =F14-G14-H14 -> 5 | J14: =SUM(G14:I14) -> 100 | K14: =IF(AND(I14>=Inputs!$B$15,J14=F14),"PASS","FAIL") -> PASS
A15: CB009 | B15: S02 | C15: ET-A | D15: FD-C | E15: Cross-region network | F15: =Inputs!$B$11 -> 100 | G15: =Inputs!$B$12 -> 75 | H15: =Inputs!$B$13 -> 20 | I15: =F15-G15-H15 -> 5 | J15: =SUM(G15:I15) -> 100 | K15: =IF(AND(I15>=Inputs!$B$15,J15=F15),"PASS","FAIL") -> PASS
A16: CB010 | B16: S02 | C16: ET-A | D16: FD-C | E16: Power and cooling | F16: =Inputs!$B$11 -> 100 | G16: =Inputs!$B$12 -> 75 | H16: =Inputs!$B$13 -> 20 | I16: =F16-G16-H16 -> 5 | J16: =SUM(G16:I16) -> 100 | K16: =IF(AND(I16>=Inputs!$B$15,J16=F16),"PASS","FAIL") -> PASS
A17: CB011 | B17: S02 | C17: ET-A | D17: FD-C | E17: Controlled workspace | F17: =Inputs!$B$11 -> 100 | G17: =Inputs!$B$12 -> 75 | H17: =Inputs!$B$13 -> 20 | I17: =F17-G17-H17 -> 5 | J17: =SUM(G17:I17) -> 100 | K17: =IF(AND(I17>=Inputs!$B$15,J17=F17),"PASS","FAIL") -> PASS
A18: CB012 | B18: S02 | C18: ET-A | D18: FD-C | E18: Specialist labor | F18: =Inputs!$B$11 -> 100 | G18: =Inputs!$B$12 -> 75 | H18: =Inputs!$B$13 -> 20 | I18: =F18-G18-H18 -> 5 | J18: =SUM(G18:I18) -> 100 | K18: =IF(AND(I18>=Inputs!$B$15,J18=F18),"PASS","FAIL") -> PASS
... A114: CB108 | B114: S18 | C114: RT-B | D114: FD-E | E114: Specialist labor | F114: =Inputs!$B$11 -> 100 | G114: =Inputs!$B$12 -> 75 | H114: =Inputs!$B$13 -> 20 | I114: =F114-G114-H114 -> 5 | J114: =SUM(G114:I114) -> 100 | K114: =IF(AND(I114>=Inputs!$B$15,J114=F114),"PASS","FAIL") -> PASS

Sheet Capacity Stress
A2: Simultaneous truth and artifact capacity stress
A4: Every active site-resource row carries the full truth reservation while artifact failover remains inside its separate partition.
A6: World | B6: Type | C6: Subject | D6: Site | E6: Site region | F6: Root | G6: Position | H6: Standby role | I6: Resource | J6: Site offline | K6: Affected root | L6: Host capacity | M6: Truth demand | N6: Artifact demand | O6: Artifact cap | P6: Total demand | Q6: Headroom | R6: Truth protected | S6: Artifact isolated | T6: State
A7: W01 | B7: SITE LOSS | C7: S01 | D7: S01 | E7: FD-A | F7: ET-A | G7: 1 | H7: Divergence | I7: Secure compute | J7: =IF(B7="SITE LOSS",IF(D7=C7,1,0),IF(B7="REGION LOSS",IF(E7=C7,1,0),0)) -> 1 | K7: =IF(B7="SITE LOSS",IF(COUNTIFS('Site Dockets'!$B$7:$B$24,C7,'Site Dockets'!$C$7:$C$24,F7)>0,1,0),IF(B7="REGION LOSS",IF(COUNTIFS('Site Dockets'!$E$7:$E$24,C7,'Site Dockets'!$C$7:$C$24,F7)>0,1,0),0)) -> 1 | L7: =IF(J7=1,0,Inputs!$B$11) -> 0 | M7: =IF(J7=1,0,Inputs!$B$12) -> 0 | N7: =IF(J7=1,0,IF(OR(AND(OR(B7="SITE LOSS",B7="REGION LOSS"),K7=1),AND(B7="ROLE COMPROMISE",H7=C7)),Inputs!$B$13,Inputs!$B$14)) -> 0 | O7: =IF(J7=1,0,Inputs!$B$13) -> 0 | P7: =SUM(M7:N7) -> 0 | Q7: =IF(J7=1,"",L7-P7) | R7: =IF(OR(J7=1,M7<=Inputs!$B$12),1,0) -> 1 | S7: =IF(OR(J7=1,N7<=O7),1,0) -> 1 | T7: =IF(J7=1,"OFFLINE",IF(AND(Q7>=Inputs!$B$15,R7=1,S7=1,P7<=L7),"PASS","FAIL")) -> OFFLINE
A8: W01 | B8: SITE LOSS | C8: S01 | D8: S01 | E8: FD-A | F8: ET-A | G8: 1 | H8: Divergence | I8: Protected storage | J8: =IF(B8="SITE LOSS",IF(D8=C8,1,0),IF(B8="REGION LOSS",IF(E8=C8,1,0),0)) -> 1 | K8: =IF(B8="SITE LOSS",IF(COUNTIFS('Site Dockets'!$B$7:$B$24,C8,'Site Dockets'!$C$7:$C$24,F8)>0,1,0),IF(B8="REGION LOSS",IF(COUNTIFS('Site Dockets'!$E$7:$E$24,C8,'Site Dockets'!$C$7:$C$24,F8)>0,1,0),0)) -> 1 | L8: =IF(J8=1,0,Inputs!$B$11) -> 0 | M8: =IF(J8=1,0,Inputs!$B$12) -> 0 | N8: =IF(J8=1,0,IF(OR(AND(OR(B8="SITE LOSS",B8="REGION LOSS"),K8=1),AND(B8="ROLE COMPROMISE",H8=C8)),Inputs!$B$13,Inputs!$B$14)) -> 0 | O8: =IF(J8=1,0,Inputs!$B$13) -> 0 | P8: =SUM(M8:N8) -> 0 | Q8: =IF(J8=1,"",L8-P8) | R8: =IF(OR(J8=1,M8<=Inputs!$B$12),1,0) -> 1 | S8: =IF(OR(J8=1,N8<=O8),1,0) -> 1 | T8: =IF(J8=1,"OFFLINE",IF(AND(Q8>=Inputs!$B$15,R8=1,S8=1,P8<=L8),"PASS","FAIL")) -> OFFLINE
A9: W01 | B9: SITE LOSS | C9: S01 | D9: S01 | E9: FD-A | F9: ET-A | G9: 1 | H9: Divergence | I9: Cross-region network | J9: =IF(B9="SITE LOSS",IF(D9=C9,1,0),IF(B9="REGION LOSS",IF(E9=C9,1,0),0)) -> 1 | K9: =IF(B9="SITE LOSS",IF(COUNTIFS('Site Dockets'!$B$7:$B$24,C9,'Site Dockets'!$C$7:$C$24,F9)>0,1,0),IF(B9="REGION LOSS",IF(COUNTIFS('Site Dockets'!$E$7:$E$24,C9,'Site Dockets'!$C$7:$C$24,F9)>0,1,0),0)) -> 1 | L9: =IF(J9=1,0,Inputs!$B$11) -> 0 | M9: =IF(J9=1,0,Inputs!$B$12) -> 0 | N9: =IF(J9=1,0,IF(OR(AND(OR(B9="SITE LOSS",B9="REGION LOSS"),K9=1),AND(B9="ROLE COMPROMISE",H9=C9)),Inputs!$B$13,Inputs!$B$14)) -> 0 | O9: =IF(J9=1,0,Inputs!$B$13) -> 0 | P9: =SUM(M9:N9) -> 0 | Q9: =IF(J9=1,"",L9-P9) | R9: =IF(OR(J9=1,M9<=Inputs!$B$12),1,0) -> 1 | S9: =IF(OR(J9=1,N9<=O9),1,0) -> 1 | T9: =IF(J9=1,"OFFLINE",IF(AND(Q9>=Inputs!$B$15,R9=1,S9=1,P9<=L9),"PASS","FAIL")) -> OFFLINE
A10: W01 | B10: SITE LOSS | C10: S01 | D10: S01 | E10: FD-A | F10: ET-A | G10: 1 | H10: Divergence | I10: Power and cooling | J10: =IF(B10="SITE LOSS",IF(D10=C10,1,0),IF(B10="REGION LOSS",IF(E10=C10,1,0),0)) -> 1 | K10: =IF(B10="SITE LOSS",IF(COUNTIFS('Site Dockets'!$B$7:$B$24,C10,'Site Dockets'!$C$7:$C$24,F10)>0,1,0),IF(B10="REGION LOSS",IF(COUNTIFS('Site Dockets'!$E$7:$E$24,C10,'Site Dockets'!$C$7:$C$24,F10)>0,1,0),0)) -> 1 | L10: =IF(J10=1,0,Inputs!$B$11) -> 0 | M10: =IF(J10=1,0,Inputs!$B$12) -> 0 | N10: =IF(J10=1,0,IF(OR(AND(OR(B10="SITE LOSS",B10="REGION LOSS"),K10=1),AND(B10="ROLE COMPROMISE",H10=C10)),Inputs!$B$13,Inputs!$B$14)) -> 0 | O10: =IF(J10=1,0,Inputs!$B$13) -> 0 | P10: =SUM(M10:N10) -> 0 | Q10: =IF(J10=1,"",L10-P10) | R10: =IF(OR(J10=1,M10<=Inputs!$B$12),1,0) -> 1 | S10: =IF(OR(J10=1,N10<=O10),1,0) -> 1 | T10: =IF(J10=1,"OFFLINE",IF(AND(Q10>=Inputs!$B$15,R10=1,S10=1,P10<=L10),"PASS","FAIL")) -> OFFLINE
A11: W01 | B11: SITE LOSS | C11: S01 | D11: S01 | E11: FD-A | F11: ET-A | G11: 1 | H11: Divergence | I11: Controlled workspace | J11: =IF(B11="SITE LOSS",IF(D11=C11,1,0),IF(B11="REGION LOSS",IF(E11=C11,1,0),0)) -> 1 | K11: =IF(B11="SITE LOSS",IF(COUNTIFS('Site Dockets'!$B$7:$B$24,C11,'Site Dockets'!$C$7:$C$24,F11)>0,1,0),IF(B11="REGION LOSS",IF(COUNTIFS('Site Dockets'!$E$7:$E$24,C11,'Site Dockets'!$C$7:$C$24,F11)>0,1,0),0)) -> 1 | L11: =IF(J11=1,0,Inputs!$B$11) -> 0 | M11: =IF(J11=1,0,Inputs!$B$12) -> 0 | N11: =IF(J11=1,0,IF(OR(AND(OR(B11="SITE LOSS",B11="REGION LOSS"),K11=1),AND(B11="ROLE COMPROMISE",H11=C11)),Inputs!$B$13,Inputs!$B$14)) -> 0 | O11: =IF(J11=1,0,Inputs!$B$13) -> 0 | P11: =SUM(M11:N11) -> 0 | Q11: =IF(J11=1,"",L11-P11) | R11: =IF(OR(J11=1,M11<=Inputs!$B$12),1,0) -> 1 | S11: =IF(OR(J11=1,N11<=O11),1,0) -> 1 | T11: =IF(J11=1,"OFFLINE",IF(AND(Q11>=Inputs!$B$15,R11=1,S11=1,P11<=L11),"PASS","FAIL")) -> OFFLINE
A12: W01 | B12: SITE LOSS | C12: S01 | D12: S01 | E12: FD-A | F12: ET-A | G12: 1 | H12: Divergence | I12: Specialist labor | J12: =IF(B12="SITE LOSS",IF(D12=C12,1,0),IF(B12="REGION LOSS",IF(E12=C12,1,0),0)) -> 1 | K12: =IF(B12="SITE LOSS",IF(COUNTIFS('Site Dockets'!$B$7:$B$24,C12,'Site Dockets'!$C$7:$C$24,F12)>0,1,0),IF(B12="REGION LOSS",IF(COUNTIFS('Site Dockets'!$E$7:$E$24,C12,'Site Dockets'!$C$7:$C$24,F12)>0,1,0),0)) -> 1 | L12: =IF(J12=1,0,Inputs!$B$11) -> 0 | M12: =IF(J12=1,0,Inputs!$B$12) -> 0 | N12: =IF(J12=1,0,IF(OR(AND(OR(B12="SITE LOSS",B12="REGION LOSS"),K12=1),AND(B12="ROLE COMPROMISE",H12=C12)),Inputs!$B$13,Inputs!$B$14)) -> 0 | O12: =IF(J12=1,0,Inputs!$B$13) -> 0 | P12: =SUM(M12:N12) -> 0 | Q12: =IF(J12=1,"",L12-P12) | R12: =IF(OR(J12=1,M12<=Inputs!$B$12),1,0) -> 1 | S12: =IF(OR(J12=1,N12<=O12),1,0) -> 1 | T12: =IF(J12=1,"OFFLINE",IF(AND(Q12>=Inputs!$B$15,R12=1,S12=1,P12<=L12),"PASS","FAIL")) -> OFFLINE
A13: W01 | B13: SITE LOSS | C13: S01 | D13: S02 | E13: FD-C | F13: ET-A | G13: 2 | H13: Native | I13: Secure compute | J13: =IF(B13="SITE LOSS",IF(D13=C13,1,0),IF(B13="REGION LOSS",IF(E13=C13,1,0),0)) -> 0 | K13: =IF(B13="SITE LOSS",IF(COUNTIFS('Site Dockets'!$B$7:$B$24,C13,'Site Dockets'!$C$7:$C$24,F13)>0,1,0),IF(B13="REGION LOSS",IF(COUNTIFS('Site Dockets'!$E$7:$E$24,C13,'Site Dockets'!$C$7:$C$24,F13)>0,1,0),0)) -> 1 | L13: =IF(J13=1,0,Inputs!$B$11) -> 100 | M13: =IF(J13=1,0,Inputs!$B$12) -> 75 | N13: =IF(J13=1,0,IF(OR(AND(OR(B13="SITE LOSS",B13="REGION LOSS"),K13=1),AND(B13="ROLE COMPROMISE",H13=C13)),Inputs!$B$13,Inputs!$B$14)) -> 20 | O13: =IF(J13=1,0,Inputs!$B$13) -> 20 | P13: =SUM(M13:N13) -> 95 | Q13: =IF(J13=1,"",L13-P13) -> 5 | R13: =IF(OR(J13=1,M13<=Inputs!$B$12),1,0) -> 1 | S13: =IF(OR(J13=1,N13<=O13),1,0) -> 1 | T13: =IF(J13=1,"OFFLINE",IF(AND(Q13>=Inputs!$B$15,R13=1,S13=1,P13<=L13),"PASS","FAIL")) -> PASS
A14: W01 | B14: SITE LOSS | C14: S01 | D14: S02 | E14: FD-C | F14: ET-A | G14: 2 | H14: Native | I14: Protected storage | J14: =IF(B14="SITE LOSS",IF(D14=C14,1,0),IF(B14="REGION LOSS",IF(E14=C14,1,0),0)) -> 0 | K14: =IF(B14="SITE LOSS",IF(COUNTIFS('Site Dockets'!$B$7:$B$24,C14,'Site Dockets'!$C$7:$C$24,F14)>0,1,0),IF(B14="REGION LOSS",IF(COUNTIFS('Site Dockets'!$E$7:$E$24,C14,'Site Dockets'!$C$7:$C$24,F14)>0,1,0),0)) -> 1 | L14: =IF(J14=1,0,Inputs!$B$11) -> 100 | M14: =IF(J14=1,0,Inputs!$B$12) -> 75 | N14: =IF(J14=1,0,IF(OR(AND(OR(B14="SITE LOSS",B14="REGION LOSS"),K14=1),AND(B14="ROLE COMPROMISE",H14=C14)),Inputs!$B$13,Inputs!$B$14)) -> 20 | O14: =IF(J14=1,0,Inputs!$B$13) -> 20 | P14: =SUM(M14:N14) -> 95 | Q14: =IF(J14=1,"",L14-P14) -> 5 | R14: =IF(OR(J14=1,M14<=Inputs!$B$12),1,0) -> 1 | S14: =IF(OR(J14=1,N14<=O14),1,0) -> 1 | T14: =IF(J14=1,"OFFLINE",IF(AND(Q14>=Inputs!$B$15,R14=1,S14=1,P14<=L14),"PASS","FAIL")) -> PASS
A15: W01 | B15: SITE LOSS | C15: S01 | D15: S02 | E15: FD-C | F15: ET-A | G15: 2 | H15: Native | I15: Cross-region network | J15: =IF(B15="SITE LOSS",IF(D15=C15,1,0),IF(B15="REGION LOSS",IF(E15=C15,1,0),0)) -> 0 | K15: =IF(B15="SITE LOSS",IF(COUNTIFS('Site Dockets'!$B$7:$B$24,C15,'Site Dockets'!$C$7:$C$24,F15)>0,1,0),IF(B15="REGION LOSS",IF(COUNTIFS('Site Dockets'!$E$7:$E$24,C15,'Site Dockets'!$C$7:$C$24,F15)>0,1,0),0)) -> 1 | L15: =IF(J15=1,0,Inputs!$B$11) -> 100 | M15: =IF(J15=1,0,Inputs!$B$12) -> 75 | N15: =IF(J15=1,0,IF(OR(AND(OR(B15="SITE LOSS",B15="REGION LOSS"),K15=1),AND(B15="ROLE COMPROMISE",H15=C15)),Inputs!$B$13,Inputs!$B$14)) -> 20 | O15: =IF(J15=1,0,Inputs!$B$13) -> 20 | P15: =SUM(M15:N15) -> 95 | Q15: =IF(J15=1,"",L15-P15) -> 5 | R15: =IF(OR(J15=1,M15<=Inputs!$B$12),1,0) -> 1 | S15: =IF(OR(J15=1,N15<=O15),1,0) -> 1 | T15: =IF(J15=1,"OFFLINE",IF(AND(Q15>=Inputs!$B$15,R15=1,S15=1,P15<=L15),"PASS","FAIL")) -> PASS
A16: W01 | B16: SITE LOSS | C16: S01 | D16: S02 | E16: FD-C | F16: ET-A | G16: 2 | H16: Native | I16: Power and cooling | J16: =IF(B16="SITE LOSS",IF(D16=C16,1,0),IF(B16="REGION LOSS",IF(E16=C16,1,0),0)) -> 0 | K16: =IF(B16="SITE LOSS",IF(COUNTIFS('Site Dockets'!$B$7:$B$24,C16,'Site Dockets'!$C$7:$C$24,F16)>0,1,0),IF(B16="REGION LOSS",IF(COUNTIFS('Site Dockets'!$E$7:$E$24,C16,'Site Dockets'!$C$7:$C$24,F16)>0,1,0),0)) -> 1 | L16: =IF(J16=1,0,Inputs!$B$11) -> 100 | M16: =IF(J16=1,0,Inputs!$B$12) -> 75 | N16: =IF(J16=1,0,IF(OR(AND(OR(B16="SITE LOSS",B16="REGION LOSS"),K16=1),AND(B16="ROLE COMPROMISE",H16=C16)),Inputs!$B$13,Inputs!$B$14)) -> 20 | O16: =IF(J16=1,0,Inputs!$B$13) -> 20 | P16: =SUM(M16:N16) -> 95 | Q16: =IF(J16=1,"",L16-P16) -> 5 | R16: =IF(OR(J16=1,M16<=Inputs!$B$12),1,0) -> 1 | S16: =IF(OR(J16=1,N16<=O16),1,0) -> 1 | T16: =IF(J16=1,"OFFLINE",IF(AND(Q16>=Inputs!$B$15,R16=1,S16=1,P16<=L16),"PASS","FAIL")) -> PASS
A17: W01 | B17: SITE LOSS | C17: S01 | D17: S02 | E17: FD-C | F17: ET-A | G17: 2 | H17: Native | I17: Controlled workspace | J17: =IF(B17="SITE LOSS",IF(D17=C17,1,0),IF(B17="REGION LOSS",IF(E17=C17,1,0),0)) -> 0 | K17: =IF(B17="SITE LOSS",IF(COUNTIFS('Site Dockets'!$B$7:$B$24,C17,'Site Dockets'!$C$7:$C$24,F17)>0,1,0),IF(B17="REGION LOSS",IF(COUNTIFS('Site Dockets'!$E$7:$E$24,C17,'Site Dockets'!$C$7:$C$24,F17)>0,1,0),0)) -> 1 | L17: =IF(J17=1,0,Inputs!$B$11) -> 100 | M17: =IF(J17=1,0,Inputs!$B$12) -> 75 | N17: =IF(J17=1,0,IF(OR(AND(OR(B17="SITE LOSS",B17="REGION LOSS"),K17=1),AND(B17="ROLE COMPROMISE",H17=C17)),Inputs!$B$13,Inputs!$B$14)) -> 20 | O17: =IF(J17=1,0,Inputs!$B$13) -> 20 | P17: =SUM(M17:N17) -> 95 | Q17: =IF(J17=1,"",L17-P17) -> 5 | R17: =IF(OR(J17=1,M17<=Inputs!$B$12),1,0) -> 1 | S17: =IF(OR(J17=1,N17<=O17),1,0) -> 1 | T17: =IF(J17=1,"OFFLINE",IF(AND(Q17>=Inputs!$B$15,R17=1,S17=1,P17<=L17),"PASS","FAIL")) -> PASS
A18: W01 | B18: SITE LOSS | C18: S01 | D18: S02 | E18: FD-C | F18: ET-A | G18: 2 | H18: Native | I18: Specialist labor | J18: =IF(B18="SITE LOSS",IF(D18=C18,1,0),IF(B18="REGION LOSS",IF(E18=C18,1,0),0)) -> 0 | K18: =IF(B18="SITE LOSS",IF(COUNTIFS('Site Dockets'!$B$7:$B$24,C18,'Site Dockets'!$C$7:$C$24,F18)>0,1,0),IF(B18="REGION LOSS",IF(COUNTIFS('Site Dockets'!$E$7:$E$24,C18,'Site Dockets'!$C$7:$C$24,F18)>0,1,0),0)) -> 1 | L18: =IF(J18=1,0,Inputs!$B$11) -> 100 | M18: =IF(J18=1,0,Inputs!$B$12) -> 75 | N18: =IF(J18=1,0,IF(OR(AND(OR(B18="SITE LOSS",B18="REGION LOSS"),K18=1),AND(B18="ROLE COMPROMISE",H18=C18)),Inputs!$B$13,Inputs!$B$14)) -> 20 | O18: =IF(J18=1,0,Inputs!$B$13) -> 20 | P18: =SUM(M18:N18) -> 95 | Q18: =IF(J18=1,"",L18-P18) -> 5 | R18: =IF(OR(J18=1,M18<=Inputs!$B$12),1,0) -> 1 | S18: =IF(OR(J18=1,N18<=O18),1,0) -> 1 | T18: =IF(J18=1,"OFFLINE",IF(AND(Q18>=Inputs!$B$15,R18=1,S18=1,P18<=L18),"PASS","FAIL")) -> PASS
... A3246: W30 | B3246: EXCHANGE SHARE LOSS | C3246: ONE REGION | D3246: S18 | E3246: FD-E | F3246: RT-B | G3246: 3 | H3246: Clean | I3246: Specialist labor | J3246: =IF(B3246="SITE LOSS",IF(D3246=C3246,1,0),IF(B3246="REGION LOSS",IF(E3246=C3246,1,0),0)) -> 0 | K3246: =IF(B3246="SITE LOSS",IF(COUNTIFS('Site Dockets'!$B$7:$B$24,C3246,'Site Dockets'!$C$7:$C$24,F3246)>0,1,0),IF(B3246="REGION LOSS",IF(COUNTIFS('Site Dockets'!$E$7:$E$24,C3246,'Site Dockets'!$C$7:$C$24,F3246)>0,1,0),0)) -> 0 | L3246: =IF(J3246=1,0,Inputs!$B$11) -> 100 | M3246: =IF(J3246=1,0,Inputs!$B$12) -> 75 | N3246: =IF(J3246=1,0,IF(OR(AND(OR(B3246="SITE LOSS",B3246="REGION LOSS"),K3246=1),AND(B3246="ROLE COMPROMISE",H3246=C3246)),Inputs!$B$13,Inputs!$B$14)) -> 10 | O3246: =IF(J3246=1,0,Inputs!$B$13) -> 20 | P3246: =SUM(M3246:N3246) -> 85 | Q3246: =IF(J3246=1,"",L3246-P3246) -> 15 | R3246: =IF(OR(J3246=1,M3246<=Inputs!$B$12),1,0) -> 1 | S3246: =IF(OR(J3246=1,N3246<=O3246),1,0) -> 1 | T3246: =IF(J3246=1,"OFFLINE",IF(AND(Q3246>=Inputs!$B$15,R3246=1,S3246=1,P3246<=L3246),"PASS","FAIL")) -> PASS

Sheet Failure Worlds
A2: Commissioning failure worlds
A4: Capacity may pass before commissioning. A world remains open until all six measured recovery trials pass.
A6: World | B6: Type | C6: Subject | D6: Expected offline records | E6: Observed offline | F6: Expected active passes | G6: Observed active passes | H6: Minimum headroom | I6: Required headroom | J6: Capacity state | K6: Trials required | L6: Trials passed | M6: Commissioning state
A7: W01 | B7: SITE LOSS | C7: S01 | D7: =IF(B7="SITE LOSS",6,IF(B7="REGION LOSS",18,0)) -> 6 | E7: =COUNTIFS('Capacity Stress'!$A$7:$A$3246,A7,'Capacity Stress'!$T$7:$T$3246,"OFFLINE") -> 6 | F7: =108-D7 -> 102 | G7: =COUNTIFS('Capacity Stress'!$A$7:$A$3246,A7,'Capacity Stress'!$T$7:$T$3246,"PASS") -> 102 | H7: =MIN('Capacity Stress'!Q7:Q114) -> 5 | I7: =Inputs!$B$15 -> 5 | J7: =IF(AND(D7=E7,F7=G7,H7>=I7),"PASS","FAIL") -> PASS | K7: =Inputs!$B$17 -> 6 | L7: =COUNTIFS('Recovery Clocks'!$B$7:$B$186,A7,'Recovery Clocks'!$J$7:$J$186,"PASS") -> 0 | M7: =IF(AND(J7="PASS",K7=L7),"READY","OPEN") -> OPEN
A8: W02 | B8: SITE LOSS | C8: S02 | D8: =IF(B8="SITE LOSS",6,IF(B8="REGION LOSS",18,0)) -> 6 | E8: =COUNTIFS('Capacity Stress'!$A$7:$A$3246,A8,'Capacity Stress'!$T$7:$T$3246,"OFFLINE") -> 6 | F8: =108-D8 -> 102 | G8: =COUNTIFS('Capacity Stress'!$A$7:$A$3246,A8,'Capacity Stress'!$T$7:$T$3246,"PASS") -> 102 | H8: =MIN('Capacity Stress'!Q115:Q222) -> 5 | I8: =Inputs!$B$15 -> 5 | J8: =IF(AND(D8=E8,F8=G8,H8>=I8),"PASS","FAIL") -> PASS | K8: =Inputs!$B$17 -> 6 | L8: =COUNTIFS('Recovery Clocks'!$B$7:$B$186,A8,'Recovery Clocks'!$J$7:$J$186,"PASS") -> 0 | M8: =IF(AND(J8="PASS",K8=L8),"READY","OPEN") -> OPEN
A9: W03 | B9: SITE LOSS | C9: S03 | D9: =IF(B9="SITE LOSS",6,IF(B9="REGION LOSS",18,0)) -> 6 | E9: =COUNTIFS('Capacity Stress'!$A$7:$A$3246,A9,'Capacity Stress'!$T$7:$T$3246,"OFFLINE") -> 6 | F9: =108-D9 -> 102 | G9: =COUNTIFS('Capacity Stress'!$A$7:$A$3246,A9,'Capacity Stress'!$T$7:$T$3246,"PASS") -> 102 | H9: =MIN('Capacity Stress'!Q223:Q330) -> 5 | I9: =Inputs!$B$15 -> 5 | J9: =IF(AND(D9=E9,F9=G9,H9>=I9),"PASS","FAIL") -> PASS | K9: =Inputs!$B$17 -> 6 | L9: =COUNTIFS('Recovery Clocks'!$B$7:$B$186,A9,'Recovery Clocks'!$J$7:$J$186,"PASS") -> 0 | M9: =IF(AND(J9="PASS",K9=L9),"READY","OPEN") -> OPEN
A10: W04 | B10: SITE LOSS | C10: S04 | D10: =IF(B10="SITE LOSS",6,IF(B10="REGION LOSS",18,0)) -> 6 | E10: =COUNTIFS('Capacity Stress'!$A$7:$A$3246,A10,'Capacity Stress'!$T$7:$T$3246,"OFFLINE") -> 6 | F10: =108-D10 -> 102 | G10: =COUNTIFS('Capacity Stress'!$A$7:$A$3246,A10,'Capacity Stress'!$T$7:$T$3246,"PASS") -> 102 | H10: =MIN('Capacity Stress'!Q331:Q438) -> 5 | I10: =Inputs!$B$15 -> 5 | J10: =IF(AND(D10=E10,F10=G10,H10>=I10),"PASS","FAIL") -> PASS | K10: =Inputs!$B$17 -> 6 | L10: =COUNTIFS('Recovery Clocks'!$B$7:$B$186,A10,'Recovery Clocks'!$J$7:$J$186,"PASS") -> 0 | M10: =IF(AND(J10="PASS",K10=L10),"READY","OPEN") -> OPEN
A11: W05 | B11: SITE LOSS | C11: S05 | D11: =IF(B11="SITE LOSS",6,IF(B11="REGION LOSS",18,0)) -> 6 | E11: =COUNTIFS('Capacity Stress'!$A$7:$A$3246,A11,'Capacity Stress'!$T$7:$T$3246,"OFFLINE") -> 6 | F11: =108-D11 -> 102 | G11: =COUNTIFS('Capacity Stress'!$A$7:$A$3246,A11,'Capacity Stress'!$T$7:$T$3246,"PASS") -> 102 | H11: =MIN('Capacity Stress'!Q439:Q546) -> 5 | I11: =Inputs!$B$15 -> 5 | J11: =IF(AND(D11=E11,F11=G11,H11>=I11),"PASS","FAIL") -> PASS | K11: =Inputs!$B$17 -> 6 | L11: =COUNTIFS('Recovery Clocks'!$B$7:$B$186,A11,'Recovery Clocks'!$J$7:$J$186,"PASS") -> 0 | M11: =IF(AND(J11="PASS",K11=L11),"READY","OPEN") -> OPEN
A12: W06 | B12: SITE LOSS | C12: S06 | D12: =IF(B12="SITE LOSS",6,IF(B12="REGION LOSS",18,0)) -> 6 | E12: =COUNTIFS('Capacity Stress'!$A$7:$A$3246,A12,'Capacity Stress'!$T$7:$T$3246,"OFFLINE") -> 6 | F12: =108-D12 -> 102 | G12: =COUNTIFS('Capacity Stress'!$A$7:$A$3246,A12,'Capacity Stress'!$T$7:$T$3246,"PASS") -> 102 | H12: =MIN('Capacity Stress'!Q547:Q654) -> 5 | I12: =Inputs!$B$15 -> 5 | J12: =IF(AND(D12=E12,F12=G12,H12>=I12),"PASS","FAIL") -> PASS | K12: =Inputs!$B$17 -> 6 | L12: =COUNTIFS('Recovery Clocks'!$B$7:$B$186,A12,'Recovery Clocks'!$J$7:$J$186,"PASS") -> 0 | M12: =IF(AND(J12="PASS",K12=L12),"READY","OPEN") -> OPEN
A13: W07 | B13: SITE LOSS | C13: S07 | D13: =IF(B13="SITE LOSS",6,IF(B13="REGION LOSS",18,0)) -> 6 | E13: =COUNTIFS('Capacity Stress'!$A$7:$A$3246,A13,'Capacity Stress'!$T$7:$T$3246,"OFFLINE") -> 6 | F13: =108-D13 -> 102 | G13: =COUNTIFS('Capacity Stress'!$A$7:$A$3246,A13,'Capacity Stress'!$T$7:$T$3246,"PASS") -> 102 | H13: =MIN('Capacity Stress'!Q655:Q762) -> 5 | I13: =Inputs!$B$15 -> 5 | J13: =IF(AND(D13=E13,F13=G13,H13>=I13),"PASS","FAIL") -> PASS | K13: =Inputs!$B$17 -> 6 | L13: =COUNTIFS('Recovery Clocks'!$B$7:$B$186,A13,'Recovery Clocks'!$J$7:$J$186,"PASS") -> 0 | M13: =IF(AND(J13="PASS",K13=L13),"READY","OPEN") -> OPEN
A14: W08 | B14: SITE LOSS | C14: S08 | D14: =IF(B14="SITE LOSS",6,IF(B14="REGION LOSS",18,0)) -> 6 | E14: =COUNTIFS('Capacity Stress'!$A$7:$A$3246,A14,'Capacity Stress'!$T$7:$T$3246,"OFFLINE") -> 6 | F14: =108-D14 -> 102 | G14: =COUNTIFS('Capacity Stress'!$A$7:$A$3246,A14,'Capacity Stress'!$T$7:$T$3246,"PASS") -> 102 | H14: =MIN('Capacity Stress'!Q763:Q870) -> 5 | I14: =Inputs!$B$15 -> 5 | J14: =IF(AND(D14=E14,F14=G14,H14>=I14),"PASS","FAIL") -> PASS | K14: =Inputs!$B$17 -> 6 | L14: =COUNTIFS('Recovery Clocks'!$B$7:$B$186,A14,'Recovery Clocks'!$J$7:$J$186,"PASS") -> 0 | M14: =IF(AND(J14="PASS",K14=L14),"READY","OPEN") -> OPEN
A15: W09 | B15: SITE LOSS | C15: S09 | D15: =IF(B15="SITE LOSS",6,IF(B15="REGION LOSS",18,0)) -> 6 | E15: =COUNTIFS('Capacity Stress'!$A$7:$A$3246,A15,'Capacity Stress'!$T$7:$T$3246,"OFFLINE") -> 6 | F15: =108-D15 -> 102 | G15: =COUNTIFS('Capacity Stress'!$A$7:$A$3246,A15,'Capacity Stress'!$T$7:$T$3246,"PASS") -> 102 | H15: =MIN('Capacity Stress'!Q871:Q978) -> 5 | I15: =Inputs!$B$15 -> 5 | J15: =IF(AND(D15=E15,F15=G15,H15>=I15),"PASS","FAIL") -> PASS | K15: =Inputs!$B$17 -> 6 | L15: =COUNTIFS('Recovery Clocks'!$B$7:$B$186,A15,'Recovery Clocks'!$J$7:$J$186,"PASS") -> 0 | M15: =IF(AND(J15="PASS",K15=L15),"READY","OPEN") -> OPEN
A16: W10 | B16: SITE LOSS | C16: S10 | D16: =IF(B16="SITE LOSS",6,IF(B16="REGION LOSS",18,0)) -> 6 | E16: =COUNTIFS('Capacity Stress'!$A$7:$A$3246,A16,'Capacity Stress'!$T$7:$T$3246,"OFFLINE") -> 6 | F16: =108-D16 -> 102 | G16: =COUNTIFS('Capacity Stress'!$A$7:$A$3246,A16,'Capacity Stress'!$T$7:$T$3246,"PASS") -> 102 | H16: =MIN('Capacity Stress'!Q979:Q1086) -> 5 | I16: =Inputs!$B$15 -> 5 | J16: =IF(AND(D16=E16,F16=G16,H16>=I16),"PASS","FAIL") -> PASS | K16: =Inputs!$B$17 -> 6 | L16: =COUNTIFS('Recovery Clocks'!$B$7:$B$186,A16,'Recovery Clocks'!$J$7:$J$186,"PASS") -> 0 | M16: =IF(AND(J16="PASS",K16=L16),"READY","OPEN") -> OPEN
A17: W11 | B17: SITE LOSS | C17: S11 | D17: =IF(B17="SITE LOSS",6,IF(B17="REGION LOSS",18,0)) -> 6 | E17: =COUNTIFS('Capacity Stress'!$A$7:$A$3246,A17,'Capacity Stress'!$T$7:$T$3246,"OFFLINE") -> 6 | F17: =108-D17 -> 102 | G17: =COUNTIFS('Capacity Stress'!$A$7:$A$3246,A17,'Capacity Stress'!$T$7:$T$3246,"PASS") -> 102 | H17: =MIN('Capacity Stress'!Q1087:Q1194) -> 5 | I17: =Inputs!$B$15 -> 5 | J17: =IF(AND(D17=E17,F17=G17,H17>=I17),"PASS","FAIL") -> PASS | K17: =Inputs!$B$17 -> 6 | L17: =COUNTIFS('Recovery Clocks'!$B$7:$B$186,A17,'Recovery Clocks'!$J$7:$J$186,"PASS") -> 0 | M17: =IF(AND(J17="PASS",K17=L17),"READY","OPEN") -> OPEN
A18: W12 | B18: SITE LOSS | C18: S12 | D18: =IF(B18="SITE LOSS",6,IF(B18="REGION LOSS",18,0)) -> 6 | E18: =COUNTIFS('Capacity Stress'!$A$7:$A$3246,A18,'Capacity Stress'!$T$7:$T$3246,"OFFLINE") -> 6 | F18: =108-D18 -> 102 | G18: =COUNTIFS('Capacity Stress'!$A$7:$A$3246,A18,'Capacity Stress'!$T$7:$T$3246,"PASS") -> 102 | H18: =MIN('Capacity Stress'!Q1195:Q1302) -> 5 | I18: =Inputs!$B$15 -> 5 | J18: =IF(AND(D18=E18,F18=G18,H18>=I18),"PASS","FAIL") -> PASS | K18: =Inputs!$B$17 -> 6 | L18: =COUNTIFS('Recovery Clocks'!$B$7:$B$186,A18,'Recovery Clocks'!$J$7:$J$186,"PASS") -> 0 | M18: =IF(AND(J18="PASS",K18=L18),"READY","OPEN") -> OPEN
A19: W13 | B19: SITE LOSS | C19: S13 | D19: =IF(B19="SITE LOSS",6,IF(B19="REGION LOSS",18,0)) -> 6 | E19: =COUNTIFS('Capacity Stress'!$A$7:$A$3246,A19,'Capacity Stress'!$T$7:$T$3246,"OFFLINE") -> 6 | F19: =108-D19 -> 102 | G19: =COUNTIFS('Capacity Stress'!$A$7:$A$3246,A19,'Capacity Stress'!$T$7:$T$3246,"PASS") -> 102 | H19: =MIN('Capacity Stress'!Q1303:Q1410) -> 5 | I19: =Inputs!$B$15 -> 5 | J19: =IF(AND(D19=E19,F19=G19,H19>=I19),"PASS","FAIL") -> PASS | K19: =Inputs!$B$17 -> 6 | L19: =COUNTIFS('Recovery Clocks'!$B$7:$B$186,A19,'Recovery Clocks'!$J$7:$J$186,"PASS") -> 0 | M19: =IF(AND(J19="PASS",K19=L19),"READY","OPEN") -> OPEN
A20: W14 | B20: SITE LOSS | C20: S14 | D20: =IF(B20="SITE LOSS",6,IF(B20="REGION LOSS",18,0)) -> 6 | E20: =COUNTIFS('Capacity Stress'!$A$7:$A$3246,A20,'Capacity Stress'!$T$7:$T$3246,"OFFLINE") -> 6 | F20: =108-D20 -> 102 | G20: =COUNTIFS('Capacity Stress'!$A$7:$A$3246,A20,'Capacity Stress'!$T$7:$T$3246,"PASS") -> 102 | H20: =MIN('Capacity Stress'!Q1411:Q1518) -> 5 | I20: =Inputs!$B$15 -> 5 | J20: =IF(AND(D20=E20,F20=G20,H20>=I20),"PASS","FAIL") -> PASS | K20: =Inputs!$B$17 -> 6 | L20: =COUNTIFS('Recovery Clocks'!$B$7:$B$186,A20,'Recovery Clocks'!$J$7:$J$186,"PASS") -> 0 | M20: =IF(AND(J20="PASS",K20=L20),"READY","OPEN") -> OPEN
A21: W15 | B21: SITE LOSS | C21: S15 | D21: =IF(B21="SITE LOSS",6,IF(B21="REGION LOSS",18,0)) -> 6 | E21: =COUNTIFS('Capacity Stress'!$A$7:$A$3246,A21,'Capacity Stress'!$T$7:$T$3246,"OFFLINE") -> 6 | F21: =108-D21 -> 102 | G21: =COUNTIFS('Capacity Stress'!$A$7:$A$3246,A21,'Capacity Stress'!$T$7:$T$3246,"PASS") -> 102 | H21: =MIN('Capacity Stress'!Q1519:Q1626) -> 5 | I21: =Inputs!$B$15 -> 5 | J21: =IF(AND(D21=E21,F21=G21,H21>=I21),"PASS","FAIL") -> PASS | K21: =Inputs!$B$17 -> 6 | L21: =COUNTIFS('Recovery Clocks'!$B$7:$B$186,A21,'Recovery Clocks'!$J$7:$J$186,"PASS") -> 0 | M21: =IF(AND(J21="PASS",K21=L21),"READY","OPEN") -> OPEN
A22: W16 | B22: SITE LOSS | C22: S16 | D22: =IF(B22="SITE LOSS",6,IF(B22="REGION LOSS",18,0)) -> 6 | E22: =COUNTIFS('Capacity Stress'!$A$7:$A$3246,A22,'Capacity Stress'!$T$7:$T$3246,"OFFLINE") -> 6 | F22: =108-D22 -> 102 | G22: =COUNTIFS('Capacity Stress'!$A$7:$A$3246,A22,'Capacity Stress'!$T$7:$T$3246,"PASS") -> 102 | H22: =MIN('Capacity Stress'!Q1627:Q1734) -> 5 | I22: =Inputs!$B$15 -> 5 | J22: =IF(AND(D22=E22,F22=G22,H22>=I22),"PASS","FAIL") -> PASS | K22: =Inputs!$B$17 -> 6 | L22: =COUNTIFS('Recovery Clocks'!$B$7:$B$186,A22,'Recovery Clocks'!$J$7:$J$186,"PASS") -> 0 | M22: =IF(AND(J22="PASS",K22=L22),"READY","OPEN") -> OPEN
A23: W17 | B23: SITE LOSS | C23: S17 | D23: =IF(B23="SITE LOSS",6,IF(B23="REGION LOSS",18,0)) -> 6 | E23: =COUNTIFS('Capacity Stress'!$A$7:$A$3246,A23,'Capacity Stress'!$T$7:$T$3246,"OFFLINE") -> 6 | F23: =108-D23 -> 102 | G23: =COUNTIFS('Capacity Stress'!$A$7:$A$3246,A23,'Capacity Stress'!$T$7:$T$3246,"PASS") -> 102 | H23: =MIN('Capacity Stress'!Q1735:Q1842) -> 5 | I23: =Inputs!$B$15 -> 5 | J23: =IF(AND(D23=E23,F23=G23,H23>=I23),"PASS","FAIL") -> PASS | K23: =Inputs!$B$17 -> 6 | L23: =COUNTIFS('Recovery Clocks'!$B$7:$B$186,A23,'Recovery Clocks'!$J$7:$J$186,"PASS") -> 0 | M23: =IF(AND(J23="PASS",K23=L23),"READY","OPEN") -> OPEN
A24: W18 | B24: SITE LOSS | C24: S18 | D24: =IF(B24="SITE LOSS",6,IF(B24="REGION LOSS",18,0)) -> 6 | E24: =COUNTIFS('Capacity Stress'!$A$7:$A$3246,A24,'Capacity Stress'!$T$7:$T$3246,"OFFLINE") -> 6 | F24: =108-D24 -> 102 | G24: =COUNTIFS('Capacity Stress'!$A$7:$A$3246,A24,'Capacity Stress'!$T$7:$T$3246,"PASS") -> 102 | H24: =MIN('Capacity Stress'!Q1843:Q1950) -> 5 | I24: =Inputs!$B$15 -> 5 | J24: =IF(AND(D24=E24,F24=G24,H24>=I24),"PASS","FAIL") -> PASS | K24: =Inputs!$B$17 -> 6 | L24: =COUNTIFS('Recovery Clocks'!$B$7:$B$186,A24,'Recovery Clocks'!$J$7:$J$186,"PASS") -> 0 | M24: =IF(AND(J24="PASS",K24=L24),"READY","OPEN") -> OPEN
A25: W19 | B25: REGION LOSS | C25: FD-A | D25: =IF(B25="SITE LOSS",6,IF(B25="REGION LOSS",18,0)) -> 18 | E25: =COUNTIFS('Capacity Stress'!$A$7:$A$3246,A25,'Capacity Stress'!$T$7:$T$3246,"OFFLINE") -> 18 | F25: =108-D25 -> 90 | G25: =COUNTIFS('Capacity Stress'!$A$7:$A$3246,A25,'Capacity Stress'!$T$7:$T$3246,"PASS") -> 90 | H25: =MIN('Capacity Stress'!Q1951:Q2058) -> 5 | I25: =Inputs!$B$15 -> 5 | J25: =IF(AND(D25=E25,F25=G25,H25>=I25),"PASS","FAIL") -> PASS | K25: =Inputs!$B$17 -> 6 | L25: =COUNTIFS('Recovery Clocks'!$B$7:$B$186,A25,'Recovery Clocks'!$J$7:$J$186,"PASS") -> 0 | M25: =IF(AND(J25="PASS",K25=L25),"READY","OPEN") -> OPEN
A26: W20 | B26: REGION LOSS | C26: FD-B | D26: =IF(B26="SITE LOSS",6,IF(B26="REGION LOSS",18,0)) -> 18 | E26: =COUNTIFS('Capacity Stress'!$A$7:$A$3246,A26,'Capacity Stress'!$T$7:$T$3246,"OFFLINE") -> 18 | F26: =108-D26 -> 90 | G26: =COUNTIFS('Capacity Stress'!$A$7:$A$3246,A26,'Capacity Stress'!$T$7:$T$3246,"PASS") -> 90 | H26: =MIN('Capacity Stress'!Q2059:Q2166) -> 5 | I26: =Inputs!$B$15 -> 5 | J26: =IF(AND(D26=E26,F26=G26,H26>=I26),"PASS","FAIL") -> PASS | K26: =Inputs!$B$17 -> 6 | L26: =COUNTIFS('Recovery Clocks'!$B$7:$B$186,A26,'Recovery Clocks'!$J$7:$J$186,"PASS") -> 0 | M26: =IF(AND(J26="PASS",K26=L26),"READY","OPEN") -> OPEN
A27: W21 | B27: REGION LOSS | C27: FD-C | D27: =IF(B27="SITE LOSS",6,IF(B27="REGION LOSS",18,0)) -> 18 | E27: =COUNTIFS('Capacity Stress'!$A$7:$A$3246,A27,'Capacity Stress'!$T$7:$T$3246,"OFFLINE") -> 18 | F27: =108-D27 -> 90 | G27: =COUNTIFS('Capacity Stress'!$A$7:$A$3246,A27,'Capacity Stress'!$T$7:$T$3246,"PASS") -> 90 | H27: =MIN('Capacity Stress'!Q2167:Q2274) -> 5 | I27: =Inputs!$B$15 -> 5 | J27: =IF(AND(D27=E27,F27=G27,H27>=I27),"PASS","FAIL") -> PASS | K27: =Inputs!$B$17 -> 6 | L27: =COUNTIFS('Recovery Clocks'!$B$7:$B$186,A27,'Recovery Clocks'!$J$7:$J$186,"PASS") -> 0 | M27: =IF(AND(J27="PASS",K27=L27),"READY","OPEN") -> OPEN
A28: W22 | B28: REGION LOSS | C28: FD-D | D28: =IF(B28="SITE LOSS",6,IF(B28="REGION LOSS",18,0)) -> 18 | E28: =COUNTIFS('Capacity Stress'!$A$7:$A$3246,A28,'Capacity Stress'!$T$7:$T$3246,"OFFLINE") -> 18 | F28: =108-D28 -> 90 | G28: =COUNTIFS('Capacity Stress'!$A$7:$A$3246,A28,'Capacity Stress'!$T$7:$T$3246,"PASS") -> 90 | H28: =MIN('Capacity Stress'!Q2275:Q2382) -> 5 | I28: =Inputs!$B$15 -> 5 | J28: =IF(AND(D28=E28,F28=G28,H28>=I28),"PASS","FAIL") -> PASS | K28: =Inputs!$B$17 -> 6 | L28: =COUNTIFS('Recovery Clocks'!$B$7:$B$186,A28,'Recovery Clocks'!$J$7:$J$186,"PASS") -> 0 | M28: =IF(AND(J28="PASS",K28=L28),"READY","OPEN") -> OPEN
A29: W23 | B29: REGION LOSS | C29: FD-E | D29: =IF(B29="SITE LOSS",6,IF(B29="REGION LOSS",18,0)) -> 18 | E29: =COUNTIFS('Capacity Stress'!$A$7:$A$3246,A29,'Capacity Stress'!$T$7:$T$3246,"OFFLINE") -> 18 | F29: =108-D29 -> 90 | G29: =COUNTIFS('Capacity Stress'!$A$7:$A$3246,A29,'Capacity Stress'!$T$7:$T$3246,"PASS") -> 90 | H29: =MIN('Capacity Stress'!Q2383:Q2490) -> 5 | I29: =Inputs!$B$15 -> 5 | J29: =IF(AND(D29=E29,F29=G29,H29>=I29),"PASS","FAIL") -> PASS | K29: =Inputs!$B$17 -> 6 | L29: =COUNTIFS('Recovery Clocks'!$B$7:$B$186,A29,'Recovery Clocks'!$J$7:$J$186,"PASS") -> 0 | M29: =IF(AND(J29="PASS",K29=L29),"READY","OPEN") -> OPEN
A30: W24 | B30: REGION LOSS | C30: FD-F | D30: =IF(B30="SITE LOSS",6,IF(B30="REGION LOSS",18,0)) -> 18 | E30: =COUNTIFS('Capacity Stress'!$A$7:$A$3246,A30,'Capacity Stress'!$T$7:$T$3246,"OFFLINE") -> 18 | F30: =108-D30 -> 90 | G30: =COUNTIFS('Capacity Stress'!$A$7:$A$3246,A30,'Capacity Stress'!$T$7:$T$3246,"PASS") -> 90 | H30: =MIN('Capacity Stress'!Q2491:Q2598) -> 5 | I30: =Inputs!$B$15 -> 5 | J30: =IF(AND(D30=E30,F30=G30,H30>=I30),"PASS","FAIL") -> PASS | K30: =Inputs!$B$17 -> 6 | L30: =COUNTIFS('Recovery Clocks'!$B$7:$B$186,A30,'Recovery Clocks'!$J$7:$J$186,"PASS") -> 0 | M30: =IF(AND(J30="PASS",K30=L30),"READY","OPEN") -> OPEN
A31: W25 | B31: VENDOR EXIT | C31: ALL | D31: =IF(B31="SITE LOSS",6,IF(B31="REGION LOSS",18,0)) -> 0 | E31: =COUNTIFS('Capacity Stress'!$A$7:$A$3246,A31,'Capacity Stress'!$T$7:$T$3246,"OFFLINE") -> 0 | F31: =108-D31 -> 108 | G31: =COUNTIFS('Capacity Stress'!$A$7:$A$3246,A31,'Capacity Stress'!$T$7:$T$3246,"PASS") -> 108 | H31: =MIN('Capacity Stress'!Q2599:Q2706) -> 15 | I31: =Inputs!$B$15 -> 5 | J31: =IF(AND(D31=E31,F31=G31,H31>=I31),"PASS","FAIL") -> PASS | K31: =Inputs!$B$17 -> 6 | L31: =COUNTIFS('Recovery Clocks'!$B$7:$B$186,A31,'Recovery Clocks'!$J$7:$J$186,"PASS") -> 0 | M31: =IF(AND(J31="PASS",K31=L31),"READY","OPEN") -> OPEN
A32: W26 | B32: ROLE COMPROMISE | C32: Native | D32: =IF(B32="SITE LOSS",6,IF(B32="REGION LOSS",18,0)) -> 0 | E32: =COUNTIFS('Capacity Stress'!$A$7:$A$3246,A32,'Capacity Stress'!$T$7:$T$3246,"OFFLINE") -> 0 | F32: =108-D32 -> 108 | G32: =COUNTIFS('Capacity Stress'!$A$7:$A$3246,A32,'Capacity Stress'!$T$7:$T$3246,"PASS") -> 108 | H32: =MIN('Capacity Stress'!Q2707:Q2814) -> 5 | I32: =Inputs!$B$15 -> 5 | J32: =IF(AND(D32=E32,F32=G32,H32>=I32),"PASS","FAIL") -> PASS | K32: =Inputs!$B$17 -> 6 | L32: =COUNTIFS('Recovery Clocks'!$B$7:$B$186,A32,'Recovery Clocks'!$J$7:$J$186,"PASS") -> 0 | M32: =IF(AND(J32="PASS",K32=L32),"READY","OPEN") -> OPEN
A33: W27 | B33: ROLE COMPROMISE | C33: Clean | D33: =IF(B33="SITE LOSS",6,IF(B33="REGION LOSS",18,0)) -> 0 | E33: =COUNTIFS('Capacity Stress'!$A$7:$A$3246,A33,'Capacity Stress'!$T$7:$T$3246,"OFFLINE") -> 0 | F33: =108-D33 -> 108 | G33: =COUNTIFS('Capacity Stress'!$A$7:$A$3246,A33,'Capacity Stress'!$T$7:$T$3246,"PASS") -> 108 | H33: =MIN('Capacity Stress'!Q2815:Q2922) -> 5 | I33: =Inputs!$B$15 -> 5 | J33: =IF(AND(D33=E33,F33=G33,H33>=I33),"PASS","FAIL") -> PASS | K33: =Inputs!$B$17 -> 6 | L33: =COUNTIFS('Recovery Clocks'!$B$7:$B$186,A33,'Recovery Clocks'!$J$7:$J$186,"PASS") -> 0 | M33: =IF(AND(J33="PASS",K33=L33),"READY","OPEN") -> OPEN
A34: W28 | B34: ROLE COMPROMISE | C34: Divergence | D34: =IF(B34="SITE LOSS",6,IF(B34="REGION LOSS",18,0)) -> 0 | E34: =COUNTIFS('Capacity Stress'!$A$7:$A$3246,A34,'Capacity Stress'!$T$7:$T$3246,"OFFLINE") -> 0 | F34: =108-D34 -> 108 | G34: =COUNTIFS('Capacity Stress'!$A$7:$A$3246,A34,'Capacity Stress'!$T$7:$T$3246,"PASS") -> 108 | H34: =MIN('Capacity Stress'!Q2923:Q3030) -> 5 | I34: =Inputs!$B$15 -> 5 | J34: =IF(AND(D34=E34,F34=G34,H34>=I34),"PASS","FAIL") -> PASS | K34: =Inputs!$B$17 -> 6 | L34: =COUNTIFS('Recovery Clocks'!$B$7:$B$186,A34,'Recovery Clocks'!$J$7:$J$186,"PASS") -> 0 | M34: =IF(AND(J34="PASS",K34=L34),"READY","OPEN") -> OPEN
A35: W29 | B35: COURT KEY LOSS | C35: ONE PER ROOT | D35: =IF(B35="SITE LOSS",6,IF(B35="REGION LOSS",18,0)) -> 0 | E35: =COUNTIFS('Capacity Stress'!$A$7:$A$3246,A35,'Capacity Stress'!$T$7:$T$3246,"OFFLINE") -> 0 | F35: =108-D35 -> 108 | G35: =COUNTIFS('Capacity Stress'!$A$7:$A$3246,A35,'Capacity Stress'!$T$7:$T$3246,"PASS") -> 108 | H35: =MIN('Capacity Stress'!Q3031:Q3138) -> 15 | I35: =Inputs!$B$15 -> 5 | J35: =IF(AND(D35=E35,F35=G35,H35>=I35),"PASS","FAIL") -> PASS | K35: =Inputs!$B$17 -> 6 | L35: =COUNTIFS('Recovery Clocks'!$B$7:$B$186,A35,'Recovery Clocks'!$J$7:$J$186,"PASS") -> 0 | M35: =IF(AND(J35="PASS",K35=L35),"READY","OPEN") -> OPEN
A36: W30 | B36: EXCHANGE SHARE LOSS | C36: ONE REGION | D36: =IF(B36="SITE LOSS",6,IF(B36="REGION LOSS",18,0)) -> 0 | E36: =COUNTIFS('Capacity Stress'!$A$7:$A$3246,A36,'Capacity Stress'!$T$7:$T$3246,"OFFLINE") -> 0 | F36: =108-D36 -> 108 | G36: =COUNTIFS('Capacity Stress'!$A$7:$A$3246,A36,'Capacity Stress'!$T$7:$T$3246,"PASS") -> 108 | H36: =MIN('Capacity Stress'!Q3139:Q3246) -> 15 | I36: =Inputs!$B$15 -> 5 | J36: =IF(AND(D36=E36,F36=G36,H36>=I36),"PASS","FAIL") -> PASS | K36: =Inputs!$B$17 -> 6 | L36: =COUNTIFS('Recovery Clocks'!$B$7:$B$186,A36,'Recovery Clocks'!$J$7:$J$186,"PASS") -> 0 | M36: =IF(AND(J36="PASS",K36=L36),"READY","OPEN") -> OPEN

Sheet Recovery Clocks
A2: Recovery trial register
A4: Trials use synthetic load and availability records only. Package content, predicted performance and artifact validity are prohibited.
A6: Trial | B6: World | C6: Type | D6: Recovery function | E6: Target minutes | F6: Measured minutes | G6: Integrity log | H6: Independent observer | I6: Trial complete | J6: Clock state | K6: AVW credit
A7: RT001 | B7: W01 | C7: SITE LOSS | D7: Public mirror route | E7: 5 | I7: 0 | J7: =IF(AND(ISNUMBER(F7),G7<>"",H7<>"",I7=1),IF(F7<=E7,"PASS","FAIL"),"OPEN") -> OPEN | K7: =0 -> 0
A8: RT002 | B8: W01 | C8: SITE LOSS | D8: Custody-share isolation | E8: 15 | I8: 0 | J8: =IF(AND(ISNUMBER(F8),G8<>"",H8<>"",I8=1),IF(F8<=E8,"PASS","FAIL"),"OPEN") -> OPEN | K8: =0 -> 0
A9: RT003 | B9: W01 | C9: SITE LOSS | D9: Court re-quorum | E9: 60 | I9: 0 | J9: =IF(AND(ISNUMBER(F9),G9<>"",H9<>"",I9=1),IF(F9<=E9,"PASS","FAIL"),"OPEN") -> OPEN | K9: =0 -> 0
A10: RT004 | B10: W01 | C10: SITE LOSS | D10: Native failover | E10: 120 | I10: 0 | J10: =IF(AND(ISNUMBER(F10),G10<>"",H10<>"",I10=1),IF(F10<=E10,"PASS","FAIL"),"OPEN") -> OPEN | K10: =0 -> 0
A11: RT005 | B11: W01 | C11: SITE LOSS | D11: Clean failover | E11: 240 | I11: 0 | J11: =IF(AND(ISNUMBER(F11),G11<>"",H11<>"",I11=1),IF(F11<=E11,"PASS","FAIL"),"OPEN") -> OPEN | K11: =0 -> 0
A12: RT006 | B12: W01 | C12: SITE LOSS | D12: Divergence failover | E12: 240 | I12: 0 | J12: =IF(AND(ISNUMBER(F12),G12<>"",H12<>"",I12=1),IF(F12<=E12,"PASS","FAIL"),"OPEN") -> OPEN | K12: =0 -> 0
A13: RT007 | B13: W02 | C13: SITE LOSS | D13: Public mirror route | E13: 5 | I13: 0 | J13: =IF(AND(ISNUMBER(F13),G13<>"",H13<>"",I13=1),IF(F13<=E13,"PASS","FAIL"),"OPEN") -> OPEN | K13: =0 -> 0
A14: RT008 | B14: W02 | C14: SITE LOSS | D14: Custody-share isolation | E14: 15 | I14: 0 | J14: =IF(AND(ISNUMBER(F14),G14<>"",H14<>"",I14=1),IF(F14<=E14,"PASS","FAIL"),"OPEN") -> OPEN | K14: =0 -> 0
A15: RT009 | B15: W02 | C15: SITE LOSS | D15: Court re-quorum | E15: 60 | I15: 0 | J15: =IF(AND(ISNUMBER(F15),G15<>"",H15<>"",I15=1),IF(F15<=E15,"PASS","FAIL"),"OPEN") -> OPEN | K15: =0 -> 0
A16: RT010 | B16: W02 | C16: SITE LOSS | D16: Native failover | E16: 120 | I16: 0 | J16: =IF(AND(ISNUMBER(F16),G16<>"",H16<>"",I16=1),IF(F16<=E16,"PASS","FAIL"),"OPEN") -> OPEN | K16: =0 -> 0
A17: RT011 | B17: W02 | C17: SITE LOSS | D17: Clean failover | E17: 240 | I17: 0 | J17: =IF(AND(ISNUMBER(F17),G17<>"",H17<>"",I17=1),IF(F17<=E17,"PASS","FAIL"),"OPEN") -> OPEN | K17: =0 -> 0
A18: RT012 | B18: W02 | C18: SITE LOSS | D18: Divergence failover | E18: 240 | I18: 0 | J18: =IF(AND(ISNUMBER(F18),G18<>"",H18<>"",I18=1),IF(F18<=E18,"PASS","FAIL"),"OPEN") -> OPEN | K18: =0 -> 0
... A186: RT180 | B186: W30 | C186: EXCHANGE SHARE LOSS | D186: Divergence failover | E186: 240 | I186: 0 | J186: =IF(AND(ISNUMBER(F186),G186<>"",H186<>"",I186=1),IF(F186<=E186,"PASS","FAIL"),"OPEN") -> OPEN | K186: =0 -> 0

Sheet Capital and Ops
A2: Conserved commissioning economics
A4: Capital is a co-use ceiling inside the public-method reserve. Operating amounts remain inside the cohort artifact-validity allocation.
A6: Capital co-use ceiling (USD millions) | B6: Capital co-use ceiling (USD millions) | C6: Capital co-use ceiling (USD millions) | D6: Capital co-use ceiling (USD millions)
A8: Function | B8: Allocation | C8: Vendor-delivered | D8: Publicly retained
A9: =Inputs!A49 -> Host and failure-domain hardening | B9: =Inputs!B49 -> 189 | C9: =B9*Inputs!D49 -> 189 | D9: =B9-C9 -> 0
A10: =Inputs!A50 -> Role-separated enclave compute | B10: =Inputs!B50 -> 135 | C10: =B10*Inputs!D50 -> 135 | D10: =B10-C10 -> 0
A11: =Inputs!A51 -> Offline custody and threshold escrow | B11: =Inputs!B51 -> 81 | C11: =B11*Inputs!D51 -> 0 | D11: =B11-C11 -> 81
A12: =Inputs!A52 -> Court seats and key ceremony | B12: =Inputs!B52 -> 54 | C12: =B12*Inputs!D52 -> 0 | D12: =B12-C12 -> 54
A13: =Inputs!A53 -> Cross-region network and restoration | B13: =Inputs!B53 -> 54 | C13: =B13*Inputs!D53 -> 54 | D13: =B13-C13 -> 0
A14: =Inputs!A54 -> Uncommitted recovery reserve | B14: =Inputs!B54 -> 27 | C14: =B14*Inputs!D54 -> 0 | D14: =B14-C14 -> 27
A15: ="Total" -> Total | B15: =SUM(B9:B14) -> 540 | C15: =SUM(C9:C14) -> 378 | D15: =SUM(D9:D14) -> 162
A19: Cohort operating ceiling (USD millions) | B19: Cohort operating ceiling (USD millions) | C19: Cohort operating ceiling (USD millions) | D19: Cohort operating ceiling (USD millions)
A21: Function | B21: Parent ceiling | C21: Share | D21: Function ceiling
A22: Clean-room rebuild cells | B22: =Inputs!B58 -> 26.905 | C22: 0.55 | D22: =B22*C22 -> 14.79775
A23: Root-native instruments and qualification | B23: =Inputs!B58 -> 26.905 | C23: 0.25 | D23: =B23*C23 -> 6.72625
A24: Divergence reserve | B24: =Inputs!B58 -> 26.905 | C24: 0.2 | D24: =B24*C24 -> 5.381
A25: Public Artifact Exchange | B25: =Inputs!B59 -> 14.349333 | C25: 0.45 | D25: =B25*C25 -> 6.4571999
A26: Disconnected archive | B26: =Inputs!B59 -> 14.349333 | C26: 0.3 | D26: =B26*C26 -> 4.3047999
A27: Cryptographic lineage | B27: =Inputs!B59 -> 14.349333 | C27: 0.15 | D27: =B27*C27 -> 2.1523999
A28: Semantic kernel stewardship | B28: =Inputs!B59 -> 14.349333 | C28: 0.1 | D28: =B28*C28 -> 1.4349333
A29: ="Total" -> Total | B29: =SUM(Inputs!B58:B59) -> 41.254333 | C29: ="n.a." -> n.a. | D29: =SUM(D22:D28) -> 41.254333
A33: Non-displacement accounting | B33: Non-displacement accounting | C33: Non-displacement accounting | D33: Non-displacement accounting
A35: Truth-train reservation per site-resource | B35: 75
A36: Artifact-estate maximum per site-resource | B36: 20
A37: Minimum simultaneous headroom | B37: 5
A38: Capital ceiling added | B38: 0
A39: Operating ceiling added | B39: 0
A40: Authority created by budget | B40: 0

Sheet State Law
A2: Commissioning state and nonconversion law
A4: Commissioning establishes availability. It does not establish package validity, observation, selection or production authority.
A6: State | B6: Entry | C6: Permitted act | D6: Forbidden conversion | E6: Loss response | F6: Exit | G6: Authority
A7: PLANNED | B7: FAE-1 selected | C7: register dockets | D7: topology to site fact | E7: none | F7: IDENTIFIED | G7: Research compact
A8: IDENTIFIED | B8: site and actors named | C8: test control graphs | D8: identity to independence | E8: revoke identity | F8: SEPARATED | G8: Control registrar
A9: SEPARATED | B9: all conflicts clear | C9: issue scoped keys | D9: separation to key validity | E9: rekey | F9: KEYED | G9: Key authority
A10: KEYED | B10: ceremonies complete | C10: commission enclave builds | D10: key to artifact validity | E10: destroy affected key | F10: BUILT | G10: Commissioning authority
A11: BUILT | B11: installation accepted | C11: reserve capacity | D11: build acceptance to NDW | E11: repair or replace | F11: RESERVED | G11: Capacity steward
A12: RESERVED | B12: partitions sealed | C12: run synthetic recovery trials | D12: reservation to measured recovery | E12: hold docket | F12: DRILLED | G12: Drill authority
A13: DRILLED | B13: all clocks measured | C13: issue non-displacement warrant | D13: drill to AVW | E13: repeat invalid drill | F13: WARRANTED | G13: Truth Capacity Court
A14: WARRANTED | B14: 18 NDWs and six roots | C14: activate estate simultaneously | D14: activation to payment | E14: hold all activation | F14: AVAILABLE | G14: Activation registrar
A15: AVAILABLE | B15: cohort token live | C15: accept DRG-1 package | D15: availability to AVW | E15: degrade affected root | F15: DEGRADED | G15: Root Artifact Court
A16: DEGRADED | B16: one path or share lost | C16: operate lawful survivor | D16: degradation to normal state | E16: recover before expiry | F16: AVAILABLE | G16: Continuity authority
A17: HELD | B17: quorum, capacity or lineage absent | C17: preserve custody | D17: custody to acceptance | E17: no new AVW | F17: WARRANTED | G17: Artifact Court
A18: TERMINATED | B18: common control, leakage or displacement | C18: seal outputs and return authority | D18: failure to central takeover | E18: archive epoch | F18: PLANNED | G18: Constitution
A21: Sixteen nonconversions | B21: Sixteen nonconversions | C21: Sixteen nonconversions | D21: Sixteen nonconversions | E21: Sixteen nonconversions
A22: Rule | B22: Source | C22: Forbidden result | D22: Required act | E22: Disposition
A23: N01 | B23: Site class | C23: Named place | D23: Physical Site Court admission | E23: OPEN
A24: N02 | B24: Co-location | C24: Common control | D24: separate people, keys and ancestry | E24: TERMINATE
A25: N03 | B25: Appointment | C25: Independence | D25: control-graph clearance | E25: OPEN
A26: N04 | B26: Key ceremony | C26: Artifact validity | D26: DRG-1 reconstruction | E26: ZERO CREDIT
A27: N05 | B27: Vendor award | C27: Operating authority | D27: public appointment | E27: TERMINATE
A28: N06 | B28: Installed capacity | C28: Reserved capacity | D28: capacity attestation | E28: HOLD
A29: N07 | B29: Reservation | C29: Measured recovery | D29: executed trial | E29: HOLD
A30: N08 | B30: Scheduled drill | C30: Completed drill | D30: integrity log and observer | E30: OPEN
A31: N09 | B31: Completed drill | C31: AVW | D31: package-specific reconstruction | E31: ZERO CREDIT
A32: N10 | B32: Capacity pass | C32: Non-displacement warrant | D32: Truth Capacity Court signature | E32: HOLD
... A38: N16 | B38: One-site survival | C38: Two-site survival | D38: stop and reconstitute | E38: HOLD

Sheet Inputs
A2: Commissioning controls and inherited ceilings
A4: Editable controls are blue. Capacity units are normalized commissioning reservations, not physical measurements.
A6: Constitutional controls | B6: Constitutional controls
A7: Root count | B7: 6
A8: Site count | B8: 18
A9: Failure domains | B9: 6
A10: Resource classes | B10: 6
A11: Host capacity units per resource | B11: 100
A12: Truth-train reservation units | B12: 75
A13: Artifact-estate partition units | B13: 20
A14: Artifact baseline demand units | B14: 10
A15: Minimum headroom units | B15: 5
A16: Failure worlds | B16: 30
A17: Recovery functions | B17: 6
A18: Commission gates per site | B18: 20
... A23: Tolerance | B23: 1e-06
A25: Current implementation and authority | B25: Current implementation and authority
A26: Named sites | B26: 0
A27: Admitted site charters | B27: 0
A28: Named site stewards | B28: 0
A29: Admitted role appointments | B29: 0
A30: Issued keys and shares | B30: 0
A31: Primary vendor awards | B31: 0
A32: Alternate vendor awards | B32: 0
A33: Commissioned enclave builds | B33: 0
A34: Completed recovery trials | B34: 0
A35: Non-displacement warrants | B35: 0
A36: Root availability warrants | B36: 0
A37: Estate activation warrants | B37: 0
... A45: Common-control conflicts | B45: 0
A48: Capital co-use ceiling (USD millions) | B48: Capital co-use ceiling (USD millions) | C48: Capital co-use ceiling (USD millions) | D48: Capital co-use ceiling (USD millions) | E48: Capital co-use ceiling (USD millions)
A49: Host and failure-domain hardening | B49: 189 | C49: Vendor lots | D49: 1 | E49: Pass 233
A50: Role-separated enclave compute | B50: 135 | C50: Vendor lots | D50: 1 | E50: Pass 233
A51: Offline custody and threshold escrow | B51: 81 | C51: Public custody | D51: 0 | E51: Pass 233
A52: Court seats and key ceremony | B52: 54 | C52: Public adjudication | D52: 0 | E52: Pass 233
A53: Cross-region network and restoration | B53: 54 | C53: Vendor lots | D53: 1 | E53: Pass 233
A54: Uncommitted recovery reserve | B54: 27 | C54: Public reserve | D54: 0 | E54: Pass 233
A57: Inherited cohort operating ceilings (USD millions) | B57: Inherited cohort operating ceilings (USD millions) | C57: Inherited cohort operating ceilings (USD millions) | D57: Inherited cohort operating ceilings (USD millions) | E57: Inherited cohort operating ceilings (USD millions)
A58: Independent reconstruction | B58: 26.905
A59: Public source escrow | B59: 14.349333
A62: Recovery clock targets | B62: Recovery clock targets | C62: Recovery clock targets | D62: Recovery clock targets
A63: RC1 | B63: Public mirror route | C63: 5 | D63: Planning maximum; measurement required
A64: RC2 | B64: Custody-share isolation | C64: 15 | D64: Planning maximum; measurement required
A65: RC3 | B65: Court re-quorum | C65: 60 | D65: Planning maximum; measurement required
A66: RC4 | B66: Native failover | C66: 120 | D66: Planning maximum; measurement required
A67: RC5 | B67: Clean failover | C67: 240 | D67: Planning maximum; measurement required
A68: RC6 | B68: Divergence failover | C68: 240 | D68: Planning maximum; measurement required
A71: Candidate | B71: Architecture | C71: Sites | D71: Role separation | E71: Single-loss survival | F71: Common control | G71: Decision
A72: C1 | B72: Single national commissioning campus | C72: 1 | D72: 0 | E72: 0 | F72: 1 | G72: REJECT
A73: C2 | B73: Six complete root commissioning estates | C73: 6 | D73: 1 | E73: 1 | F73: 0 | G73: REJECT—DUPLICATIVE
A74: C3 | B74: Thirty-six dedicated function sites | C74: 36 | D74: 1 | E74: 1 | F74: 0 | G74: REJECT—ADDITIVE
A75: C4 | B75: Eighteen-site triadic commissioning lattice | C75: 18 | D75: 1 | E75: 1 | F75: 0 | G75: SELECT
A76: C5 | B76: Vendor cloud with public backup | C76: 2 | D76: 0 | E76: 0 | F76: 1 | G76: REJECT

Sheet Mutations
A2: Controlled mutation register
A4: Each corruption is applied to the live model, detected by a named terminal audit and restored before export.
A6: Mutation | B6: Target | C6: Baseline | D6: Mutated | E6: Expected audit | F6: Detected | G6: Restored
A7: M01 Root-count erosion | B7: Inputs!B7 | C7: 6 | D7: 5 | E7: A01 | F7: YES | G7: YES
A8: M02 Site-count erosion | B8: Inputs!B8 | C8: 18 | D8: 17 | E8: A02 | F8: YES | G8: YES
A9: M03 Resource-count erosion | B9: Inputs!B10 | C9: 6 | D9: 5 | E9: A03 | F9: YES | G9: YES
A10: M04 Host-capacity erosion | B10: Inputs!B11 | C10: 100 | D10: 90 | E10: A22 | F10: YES | G10: YES
A11: M05 Truth-reserve inflation | B11: Inputs!B12 | C11: 75 | D11: 85 | E11: A22 | F11: YES | G11: YES
A12: M06 Artifact-cap erosion | B12: Inputs!B13 | C12: 20 | D12: 5 | E12: A22 | F12: YES | G12: YES
A13: M07 Baseline-demand inflation | B13: Inputs!B14 | C13: 10 | D13: 20 | E13: A61 | F13: YES | G13: YES
A14: M08 Headroom inflation | B14: Inputs!B15 | C14: 5 | D14: 10 | E14: A22 | F14: YES | G14: YES
A15: M09 World-count erosion | B15: Inputs!B16 | C15: 30 | D15: 29 | E15: A12 | F15: YES | G15: YES
A16: M10 Clock-count erosion | B16: Inputs!B17 | C16: 6 | D16: 5 | E16: A62 | F16: YES | G16: YES
A17: M11 Gate-count erosion | B17: Inputs!B18 | C17: 20 | D17: 19 | E17: A63 | F17: YES | G17: YES
A18: M12 Premature site claim | B18: Inputs!B26 | C18: 0 | D18: 1 | E18: A33 | F18: YES | G18: YES
... A26: M20 Role control conflict | B26: Role Appointments!H7 | C26: 0 | D26: 1 | E26: A50 | F26: YES | G26: YES

Sheet Audit
A2: Terminal audit
A4: Audit observes but never feeds commissioning, capacity, finance, validity, payment or evidence state.
A6: Audit | B6: Test | C6: Observed | D6: Expected | E6: Status
A7: A01 | B7: Root-count control | C7: =Inputs!B7 -> 6 | D7: 6 | E7: =IF(ABS(C7-D7)<=Inputs!$B$23,"PASS","FAIL") -> PASS
A8: A02 | B8: Site-count control | C8: =Inputs!B8 -> 18 | D8: 18 | E8: =IF(ABS(C8-D8)<=Inputs!$B$23,"PASS","FAIL") -> PASS
A9: A03 | B9: Resource-count control | C9: =Inputs!B10 -> 6 | D9: 6 | E9: =IF(ABS(C9-D9)<=Inputs!$B$23,"PASS","FAIL") -> PASS
A10: A04 | B10: Six failure domains | C10: =Inputs!B9 -> 6 | D10: 6 | E10: =IF(ABS(C10-D10)<=Inputs!$B$23,"PASS","FAIL") -> PASS
A11: A05 | B11: Eighteen dockets | C11: =COUNTA('Site Dockets'!A7:A24) -> 18 | D11: 18 | E11: =IF(ABS(C11-D11)<=Inputs!$B$23,"PASS","FAIL") -> PASS
A12: A06 | B12: Ninety-six appointments | C12: =COUNTA('Role Appointments'!A7:A102) -> 96 | D12: 96 | E12: =IF(ABS(C12-D12)<=Inputs!$B$23,"PASS","FAIL") -> PASS
A13: A07 | B13: Seventy-eight key records | C13: =COUNTA('Key Custody'!A7:A84) -> 78 | D13: 78 | E13: =IF(ABS(C13-D13)<=Inputs!$B$23,"PASS","FAIL") -> PASS
A14: A08 | B14: Seventy-two vendor lots | C14: =COUNTA('Vendor Lots'!A7:A78) -> 72 | D14: 72 | E14: =IF(ABS(C14-D14)<=Inputs!$B$23,"PASS","FAIL") -> PASS
A15: A09 | B15: Three hundred sixty gates | C15: =COUNTA('Commission Gates'!A7:A366) -> 360 | D15: 360 | E15: =IF(ABS(C15-D15)<=Inputs!$B$23,"PASS","FAIL") -> PASS
A16: A10 | B16: One hundred eighty recovery trials | C16: =COUNTA('Recovery Clocks'!A7:A186) -> 180 | D16: 180 | E16: =IF(ABS(C16-D16)<=Inputs!$B$23,"PASS","FAIL") -> PASS
A17: A11 | B17: Three thousand two hundred forty stress records | C17: =COUNTA('Capacity Stress'!A7:A3246) -> 3240 | D17: 3240 | E17: =IF(ABS(C17-D17)<=Inputs!$B$23,"PASS","FAIL") -> PASS
A18: A12 | B18: World-count control | C18: =Inputs!B16 -> 30 | D18: 30 | E18: =IF(ABS(C18-D18)<=Inputs!$B$23,"PASS","FAIL") -> PASS
A19: A13 | B19: Thirty world records | C19: =COUNTA('Failure Worlds'!A7:A36) -> 30 | D19: 30 | E19: =IF(ABS(C19-D19)<=Inputs!$B$23,"PASS","FAIL") -> PASS
A20: A14 | B20: Eighteen site-loss worlds | C20: =COUNTIFS('Failure Worlds'!B7:B36,"SITE LOSS") -> 18 | D20: 18 | E20: =IF(ABS(C20-D20)<=Inputs!$B$23,"PASS","FAIL") -> PASS
A21: A15 | B21: Six region-loss worlds | C21: =COUNTIFS('Failure Worlds'!B7:B36,"REGION LOSS") -> 6 | D21: 6 | E21: =IF(ABS(C21-D21)<=Inputs!$B$23,"PASS","FAIL") -> PASS
A22: A16 | B22: Three role-compromise worlds | C22: =COUNTIFS('Failure Worlds'!B7:B36,"ROLE COMPROMISE") -> 3 | D22: 3 | E22: =IF(ABS(C22-D22)<=Inputs!$B$23,"PASS","FAIL") -> PASS
A23: A17 | B23: Six Exchange hosts | C23: =SUM('Site Dockets'!I7:I24) -> 6 | D23: 6 | E23: =IF(ABS(C23-D23)<=Inputs!$B$23,"PASS","FAIL") -> PASS
A24: A18 | B24: Three ET-A sites | C24: =COUNTIFS('Site Dockets'!C7:C24,"ET-A") -> 3 | D24: 3 | E24: =IF(ABS(C24-D24)<=Inputs!$B$23,"PASS","FAIL") -> PASS
A25: A19 | B25: Three roots in FD-A | C25: =COUNTIFS('Site Dockets'!E7:E24,"FD-A") -> 3 | D25: 3 | E25: =IF(ABS(C25-D25)<=Inputs!$B$23,"PASS","FAIL") -> PASS
A26: A20 | B26: One selected architecture | C26: =COUNTIFS(Inputs!G72:G76,"SELECT") -> 1 | D26: 1 | E26: =IF(ABS(C26-D26)<=Inputs!$B$23,"PASS","FAIL") -> PASS
A27: A21 | B27: Selected architecture has eighteen sites | C27: =SUMIFS(Inputs!C72:C76,Inputs!G72:G76,"SELECT") -> 18 | D27: 18 | E27: =IF(ABS(C27-D27)<=Inputs!$B$23,"PASS","FAIL") -> PASS
A28: A22 | B28: All capacity worlds pass | C28: =COUNTIFS('Failure Worlds'!J7:J36,"PASS") -> 30 | D28: 30 | E28: =IF(ABS(C28-D28)<=Inputs!$B$23,"PASS","FAIL") -> PASS
A29: A23 | B29: Minimum active headroom | C29: =MIN('Failure Worlds'!H7:H36) -> 5 | D29: 5 | E29: =IF(ABS(C29-D29)<=Inputs!$B$23,"PASS","FAIL") -> PASS
A30: A24 | B30: Offline stress records | C30: =COUNTIFS('Capacity Stress'!T7:T3246,"OFFLINE") -> 216 | D30: 216 | E30: =IF(ABS(C30-D30)<=Inputs!$B$23,"PASS","FAIL") -> PASS
A31: A25 | B31: Active stress passes | C31: =COUNTIFS('Capacity Stress'!T7:T3246,"PASS") -> 3024 | D31: 3024 | E31: =IF(ABS(C31-D31)<=Inputs!$B$23,"PASS","FAIL") -> PASS
A32: A26 | B32: Open commissioning gates | C32: =COUNTIFS('Commission Gates'!G7:G366,"OPEN") -> 270 | D32: 270 | E32: =IF(ABS(C32-D32)<=Inputs!$B$23,"PASS","FAIL") -> PASS
A33: A27 | B33: Passing architecture gates | C33: =COUNTIFS('Commission Gates'!G7:G366,"PASS") -> 90 | D33: 90 | E33: =IF(ABS(C33-D33)<=Inputs!$B$23,"PASS","FAIL") -> PASS
A34: A28 | B34: Open dockets | C34: =COUNTIFS('Site Dockets'!S7:S24,"OPEN") -> 18 | D34: 18 | E34: =IF(ABS(C34-D34)<=Inputs!$B$23,"PASS","FAIL") -> PASS
A35: A29 | B35: Open appointments | C35: =COUNTIFS('Role Appointments'!J7:J102,"OPEN") -> 96 | D35: 96 | E35: =IF(ABS(C35-D35)<=Inputs!$B$23,"PASS","FAIL") -> PASS
A36: A30 | B36: Open keys | C36: =COUNTIFS('Key Custody'!J7:J84,"OPEN") -> 78 | D36: 78 | E36: =IF(ABS(C36-D36)<=Inputs!$B$23,"PASS","FAIL") -> PASS
A37: A31 | B37: Open vendor lots | C37: =COUNTIFS('Vendor Lots'!M7:M78,"OPEN") -> 72 | D37: 72 | E37: =IF(ABS(C37-D37)<=Inputs!$B$23,"PASS","FAIL") -> PASS
A38: A32 | B38: Open recovery trials | C38: =COUNTIFS('Recovery Clocks'!J7:J186,"OPEN") -> 180 | D38: 180 | E38: =IF(ABS(C38-D38)<=Inputs!$B$23,"PASS","FAIL") -> PASS
A39: A33 | B39: Named site claims zero | C39: =Inputs!B26 -> 0 | D39: 0 | E39: =IF(ABS(C39-D39)<=Inputs!$B$23,"PASS","FAIL") -> PASS
A40: A34 | B40: Site admissions zero | C40: =Inputs!B27 -> 0 | D40: 0 | E40: =IF(ABS(C40-D40)<=Inputs!$B$23,"PASS","FAIL") -> PASS
A41: A35 | B41: Named steward claims zero | C41: =Inputs!B28 -> 0 | D41: 0 | E41: =IF(ABS(C41-D41)<=Inputs!$B$23,"PASS","FAIL") -> PASS
A42: A36 | B42: Issued key claims zero | C42: =Inputs!B30 -> 0 | D42: 0 | E42: =IF(ABS(C42-D42)<=Inputs!$B$23,"PASS","FAIL") -> PASS
A43: A37 | B43: Vendor award claims zero | C43: =Inputs!B31 -> 0 | D43: 0 | E43: =IF(ABS(C43-D43)<=Inputs!$B$23,"PASS","FAIL") -> PASS
A44: A38 | B44: Commissioned build claims zero | C44: =Inputs!B33 -> 0 | D44: 0 | E44: =IF(ABS(C44-D44)<=Inputs!$B$23,"PASS","FAIL") -> PASS
A45: A39 | B45: Completed drill claims zero | C45: =Inputs!B34 -> 0 | D45: 0 | E45: =IF(ABS(C45-D45)<=Inputs!$B$23,"PASS","FAIL") -> PASS
A46: A40 | B46: NDW claims zero | C46: =Inputs!B35 -> 0 | D46: 0 | E46: =IF(ABS(C46-D46)<=Inputs!$B$23,"PASS","FAIL") -> PASS
A47: A41 | B47: Root availability claims zero | C47: =Inputs!B36 -> 0 | D47: 0 | E47: =IF(ABS(C47-D47)<=Inputs!$B$23,"PASS","FAIL") -> PASS
A48: A42 | B48: Estate activation claims zero | C48: =Inputs!B37 -> 0 | D48: 0 | E48: =IF(ABS(C48-D48)<=Inputs!$B$23,"PASS","FAIL") -> PASS
A49: A43 | B49: AVW claims zero | C49: =Inputs!B38 -> 0 | D49: 0 | E49: =IF(ABS(C49-D49)<=Inputs!$B$23,"PASS","FAIL") -> PASS
A50: A44 | B50: Payment claims zero | C50: =Inputs!B39 -> 0 | D50: 0 | E50: =IF(ABS(C50-D50)<=Inputs!$B$23,"PASS","FAIL") -> PASS
A51: A45 | B51: Observation claims zero | C51: =Inputs!B40 -> 0 | D51: 0 | E51: =IF(ABS(C51-D51)<=Inputs!$B$23,"PASS","FAIL") -> PASS
A52: A46 | B52: Selection claims zero | C52: =Inputs!B41 -> 0 | D52: 0 | E52: =IF(ABS(C52-D52)<=Inputs!$B$23,"PASS","FAIL") -> PASS
A53: A47 | B53: MAKE claims zero | C53: =Inputs!B42 -> 0 | D53: 0 | E53: =IF(ABS(C53-D53)<=Inputs!$B$23,"PASS","FAIL") -> PASS
A54: A48 | B54: REP-4 claims zero | C54: =Inputs!B43 -> 0 | D54: 0 | E54: =IF(ABS(C54-D54)<=Inputs!$B$23,"PASS","FAIL") -> PASS
A55: A49 | B55: No vendor operating dependencies | C55: =SUM('Vendor Lots'!K7:K78) -> 0 | D55: 0 | E55: =IF(ABS(C55-D55)<=Inputs!$B$23,"PASS","FAIL") -> PASS
A56: A50 | B56: No role control conflicts | C56: =SUM('Role Appointments'!H7:H102) -> 0 | D56: 0 | E56: =IF(ABS(C56-D56)<=Inputs!$B$23,"PASS","FAIL") -> PASS
A57: A51 | B57: Capital ceiling conserved | C57: =SUM(Inputs!B49:B54) -> 540 | D57: 540 | E57: =IF(ABS(C57-D57)<=Inputs!$B$23,"PASS","FAIL") -> PASS
A58: A52 | B58: Vendor-eligible capital | C58: =SUMPRODUCT(Inputs!B49:B54,Inputs!D49:D54) -> 378 | D58: 378 | E58: =IF(ABS(C58-D58)<=Inputs!$B$23,"PASS","FAIL") -> PASS
A59: A53 | B59: Publicly retained capital | C59: =SUM(Inputs!B49:B54)-SUMPRODUCT(Inputs!B49:B54,Inputs!D49:D54) -> 162 | D59: 162 | E59: =IF(ABS(C59-D59)<=Inputs!$B$23,"PASS","FAIL") -> PASS
A60: A54 | B60: Operating ceiling conserved | C60: =SUM(Inputs!B58:B59) -> 41.254333 | D60: 41.254333 | E60: =IF(ABS(C60-D60)<=Inputs!$B$23,"PASS","FAIL") -> PASS
A61: A55 | B61: Twelve state rows | C61: =COUNTA('State Law'!A7:A18) -> 12 | D61: 12 | E61: =IF(ABS(C61-D61)<=Inputs!$B$23,"PASS","FAIL") -> PASS
A62: A56 | B62: Sixteen nonconversion rows | C62: =COUNTA('State Law'!A23:A38) -> 16 | D62: 16 | E62: =IF(ABS(C62-D62)<=Inputs!$B$23,"PASS","FAIL") -> PASS
A63: A57 | B63: Twelve warrant instruments | C63: =COUNTA('Warrant Stack'!A7:A18) -> 12 | D63: 12 | E63: =IF(ABS(C63-D63)<=Inputs!$B$23,"PASS","FAIL") -> PASS
A64: A58 | B64: Current issued warrant count | C64: =SUM('Warrant Stack'!H7:H18) -> 0 | D64: 0 | E64: =IF(ABS(C64-D64)<=Inputs!$B$23,"PASS","FAIL") -> PASS
A65: A59 | B65: Eighteen court shares | C65: =COUNTIFS('Key Custody'!E7:E84,"Court share") -> 18 | D65: 18 | E65: =IF(ABS(C65-D65)<=Inputs!$B$23,"PASS","FAIL") -> PASS
A66: A60 | B66: Six Exchange shares | C66: =COUNTIFS('Key Custody'!E7:E84,"Exchange share") -> 6 | D66: 6 | E66: =IF(ABS(C66-D66)<=Inputs!$B$23,"PASS","FAIL") -> PASS
A67: A61 | B67: Artifact baseline demand control | C67: =Inputs!B14 -> 10 | D67: 10 | E67: =IF(ABS(C67-D67)<=Inputs!$B$23,"PASS","FAIL") -> PASS
A68: A62 | B68: Recovery-function control | C68: =Inputs!B17 -> 6 | D68: 6 | E68: =IF(ABS(C68-D68)<=Inputs!$B$23,"PASS","FAIL") -> PASS
A69: A63 | B69: Commission-gate control | C69: =Inputs!B18 -> 20 | D69: 20 | E69: =IF(ABS(C69-D69)<=Inputs!$B$23,"PASS","FAIL") -> PASS
A70: A64 | B70: Recovery passes remain zero | C70: =COUNTIFS('Recovery Clocks'!J7:J186,"PASS") -> 0 | D70: 0 | E70: =IF(ABS(C70-D70)<=Inputs!$B$23,"PASS","FAIL") -> PASS
A71: A65 | B71: Recovery AVW credit remains zero | C71: =SUM('Recovery Clocks'!K7:K186) -> 0 | D71: 0 | E71: =IF(ABS(C71-D71)<=Inputs!$B$23,"PASS","FAIL") -> PASS

Sheet ReadMe
A2: Model notes and limits
A4: This workbook specifies a commissioning warrant. It does not name a place, appoint a person, award a vendor or complete a recovery trial.
A6: Purpose | B6: Purpose | C6: Purpose | D6: Purpose | E6: Purpose | F6: Purpose
A8: CNW-1 is the sole path from the FAE-1 topology to an available public technical estate.
A9: Eighteen site dockets carry identity, control, capacity, build and rollback fields. Ninety-six appointments, seventy-eight keys and seventy-two vendor lots remain separately governed.
A10: The capacity model tests 3,240 site-resource records across thirty loss worlds while the full truth reservation remains active.
A11: Five architecture gates per site pass. Fifteen implementation gates per site remain open until real records and measured trials exist.
A12: No commissioning act creates artifact validity, evidence, payment, selection, MAKE or REP-4 authority.
A15: Capacity interpretation | B15: Capacity interpretation | C15: Capacity interpretation | D15: Capacity interpretation | E15: Capacity interpretation | F15: Capacity interpretation
A17: Capacity units are normalized shares for commissioning control, not claims about computing, electrical, storage or labor quantities.
A18: Every resource reserves seventy-five units for truth work, twenty for the artifact estate and five as unassigned headroom.
A19: Site and region loss worlds activate artifact failover up to twenty units while truth demand remains seventy-five.
A20: A pass means the artifact load did not enter the truth reservation in the modeled architecture. It is not measured non-displacement.
A21: A later Truth Capacity Court warrant requires real schedules, instrumentation, observers and recovery clocks.
A24: Sources and limits | B24: Sources and limits | C24: Sources and limits | D24: Sources and limits | E24: Sources and limits | F24: Sources and limits
A26: Repository sources: Passes 212, 214, 215, 231, 232 and 233. No external sources were used.
A27: All site, person, key, vendor, build, drill, warrant and authority identities remain empty or zero.
A28: The USD540M capital figure is a maximum co-use ceiling inside the existing USD12.0B public-method reserve.
A29: The USD41.3M operating figure remains inside the inherited cohort-one artifact-validity allocation.
A30: Vehicle and facility renderings remain deferred.
