Workbook

Sheet Summary
A2: A2C-3 Severable Construction Lattice
A4: Verdict: CLOSE. Buy eighteen station nuclei and six truth trains as 102 severable lots behind a forty-eight-control-group floor. No site, firm, award, payment, acceptance, capability or exterior form exists.
A6: Decision | B6: Result | C6: Unit | D6: State | E6: Why it matters | F6: Current authority | G6: Held conversion | H6: Next object
A7: selected architecture | B7: severable construction lattice | C7: architecture | D7: CLOSE | E7: keeps complete liability without common causal control | F7: lot constitution | G7: lot to winner | H7: bid admission
A8: construction lots | B8: 102 | C8: count | D8: CONSTITUTED | E8: six complete object classes | F8: records only | G8: record to award | H8: collision-free slate
A9: public decisive lots | B9: 72 | C9: count | D9: CONSTITUTED | E9: rigs, methods and regeneration remain separate | F9: records only | G9: lot to as-built | H9: construction packets
A10: public boundary lots | B10: 24 | C10: count | D10: CONSTITUTED | E10: substrate and integration cannot become technical roots | F10: records only | G10: boundary to control | H10: site classes
A11: candidate lots | B11: 6 | C11: count | D11: GATED | E11: one option per selected Root House | F11: option ceilings | G11: option to award | H11: bid admission
A12: minimum control groups | B12: 48 | C12: count | D12: FROZEN | E12: control follows ownership, debt, tools, keys and people | F12: firewall | G12: slot to firm | H12: ownership proof
A13: acceptance packets | B13: 510 | C13: count | D13: OPEN | E13: five complete construction records per lot | F13: grammar only | G13: packet to acceptance | H13: physical records
A14: acceptance decisions | B14: 714 | C14: count | D14: OPEN | E14: seven noncompensatory gates per lot | F14: grammar only | G14: gate to pass | H14: physical decisions
A15: public reserve | B15: 12 | C15: USD B | D15: RESERVED | E15: existing authority only | F15: ceiling | G15: reserve to obligation | H15: award warrant
A16: private options | B16: 3.5869128 | C16: USD B | D16: GATED | E16: root-specific option ceilings | F16: ceiling | G16: option to payment | H16: accepted artifact
A17: combined wave | B17: 15.586913 | C17: USD B | D17: CONSTITUTED | E17: no added authority | F17: ceiling | G17: authority to spend | H17: release sequence
A18: through MAKE exposure | B18: 10.793456 | C18: USD B | D18: CEILING | E18: limits pre-destruction loss | F18: schedule | G18: ceiling to payment | H18: accepted stages
A19: all-six kill unreleased | B19: 3.5380369 | C19: USD B | D19: PROTECTED | E19: valid failure returns transfer money | F19: schedule | G19: failure to production | H19: root disposition
... A22: rendering authority | B22: 0 | C22: count | D22: HELD | E22: form follows stabilized requirements | F22: none | G22: envelope to exterior | H22: later design
A25: Terminal test | B25: Observed | C25: State
A26: eligible architecture | B26: =COUNTIF(Alternatives!P7:P11,"SELECT") -> 1 | C26: =IF(ABS(B26-1)<0.000001,"PASS","FAIL") -> PASS
A27: lot count | B27: ='Lot Classes'!D13 -> 102 | C27: =IF(ABS(B27-102)<0.000001,"PASS","FAIL") -> PASS
A28: control groups | B28: =COUNTA('Control Groups'!A7:A54) -> 48 | C28: =IF(ABS(B28-48)<0.000001,"PASS","FAIL") -> PASS
A29: packet records | B29: =COUNTA('Acceptance Packets'!A7:A516) -> 510 | C29: =IF(ABS(B29-510)<0.000001,"PASS","FAIL") -> PASS
A30: gate decisions | B30: =COUNTA('Acceptance Gates'!A7:A720) -> 714 | C30: =IF(ABS(B30-714)<0.000001,"PASS","FAIL") -> PASS
A31: public authority | B31: =SUM('Lot Classes'!E7:E11) -> 12 | C31: =IF(ABS(B31-12)<0.000001,"PASS","FAIL") -> PASS
A32: combined ceiling | B32: ='Lot Classes'!E13 -> 15.586913 | C32: =IF(ABS(B32-15.5869128193206)<0.000001,"PASS","FAIL") -> PASS
A33: audit failures | B33: =COUNTIF(Audit!E7:E86,"FAIL") -> 0 | C33: =IF(ABS(B33-0)<0.000001,"PASS","FAIL") -> PASS
A34: awards | B34: =Controls!B22 -> 0 | C34: =IF(ABS(B34-0)<0.000001,"PASS","FAIL") -> PASS
A35: rendering authority | B35: =Controls!B28 -> 0 | C35: =IF(ABS(B35-0)<0.000001,"PASS","FAIL") -> PASS

Sheet Controls
A2: Authoritative A2C-3 controls
A4: Blue cells are the only mutable controls used by the audit. A zero is a held state, not missing work silently treated as complete.
A6: Control | B6: Value | C6: Unit | D6: Authority | E6: Meaning
A7: public construction reserve | B7: 12 | C7: USD B | D7: A2C-2 | E7: nested in enabling authority
A8: selected candidate options | B8: 3.5869128 | C8: USD B | D8: A2C-1 | E8: six root-specific ceilings
A9: mission systems | B9: 6 | C9: count | D9: A2C-2 | E9: all six remain live
A10: roles per system | B10: 3 | C10: count | D10: A2C-2 | E10: challenge, control, reconstruction
A11: civil substrate lots | B11: 6 | C11: count | D11: A2C-3 | E11: one balanced three-station package each
A12: root-native rig lots | B12: 18 | C12: count | D12: A2C-3 | E12: one per station
A13: method-lineage lots | B13: 36 | C13: count | D13: A2C-3 | E13: two unlike lineages per station
A14: regeneration-tool lots | B14: 18 | C14: count | D14: A2C-3 | E14: one per station
A15: station-integration lots | B15: 18 | C15: count | D15: A2C-3 | E15: one nondecisive interface lot per station
A16: candidate-mechanism lots | B16: 6 | C16: count | D16: A2C-3 | E16: one per selected Root House
A17: minimum control groups | B17: 48 | C17: count | D17: A2C-3 | E17: six candidate, thirty-six decisive, six boundary
A18: packet families per lot | B18: 5 | C18: count | D18: A2C-3 | E18: all required
... A28: rendering authority | B28: 0 | C28: count | D28: A2C-3 | E28: exterior form held

Sheet Alternatives
A2: Construction architecture hard-gate test
A4: All twelve gates are conjunctive. A large contractor roster cannot compensate for unified causal control or orphaned system responsibility.
A6: Architecture | B6: complete liability | C6: candidate separation | D6: role separation | E6: method plurality | F6: regen separation | G6: control transparency | H6: tooling separation | I6: acceptance separation | J6: failure severability | K6: public interfaces | L6: bounded integration | M6: cold return | N6: Passes | O6: Eligible | P6: Decision
A7: 102-lot severable lattice | B7: 1 | C7: 1 | D7: 1 | E7: 1 | F7: 1 | G7: 1 | H7: 1 | I7: 1 | J7: 1 | K7: 1 | L7: 1 | M7: 1 | N7: =SUM(B7:M7) -> 12 | O7: =IF(N7=12,"YES","NO") -> YES | P7: =IF(O7="YES","SELECT","REJECT") -> SELECT
A8: one national EPC prime | B8: 1 | C8: 0 | D8: 0 | E8: 0 | F8: 0 | G8: 0 | H8: 0 | I8: 0 | J8: 0 | K8: 1 | L8: 0 | M8: 0 | N8: =SUM(B8:M8) -> 2 | O8: =IF(N8=12,"YES","NO") -> NO | P8: =IF(O8="YES","SELECT","REJECT") -> REJECT
A9: six system primes | B9: 1 | C9: 0 | D9: 0 | E9: 0 | F9: 0 | G9: 1 | H9: 0 | I9: 0 | J9: 0 | K9: 1 | L9: 0 | M9: 0 | N9: =SUM(B9:M9) -> 3 | O9: =IF(N9=12,"YES","NO") -> NO | P9: =IF(O9="YES","SELECT","REJECT") -> REJECT
A10: eighteen station primes | B10: 1 | C10: 1 | D10: 1 | E10: 0 | F10: 0 | G10: 1 | H10: 0 | I10: 0 | J10: 1 | K10: 1 | L10: 0 | M10: 0 | N10: =SUM(B10:M10) -> 6 | O10: =IF(N10=12,"YES","NO") -> NO | P10: =IF(O10="YES","SELECT","REJECT") -> REJECT
A11: component atomization | B11: 0 | C11: 1 | D11: 1 | E11: 1 | F11: 1 | G11: 1 | H11: 1 | I11: 1 | J11: 1 | K11: 1 | L11: 1 | M11: 1 | N11: =SUM(B11:M11) -> 11 | O11: =IF(N11=12,"YES","NO") -> NO | P11: =IF(O11="YES","SELECT","REJECT") -> REJECT

Sheet Lot Classes
A2: Six severable construction-lot classes
A4: Public classes exhaust the USD 12.0B reservation. Candidate options remain private and root-specific.
A6: Code | B6: Class | C6: Funding | D6: Lots | E6: Authority USD B | F6: Nature | G6: Release | H6: Complete liability | I6: Per-lot USD B | J6: Share of wave
A7: SUB | B7: Civil substrate | C7: Public | D7: 6 | E7: 0.72 | F7: nondecisive | G7: R2 | H7: public boundary control | I7: =E7/D7 -> 0.12 | J7: =E7/$E$13 -> 0.046192598
A8: RIG | B8: Root-native rig | C8: Public | D8: 18 | E8: 5.7 | F8: decisive | G8: R3 | H8: native physical control | I8: =E8/D8 -> 0.31666667 | J8: =E8/$E$13 -> 0.3656914
A9: MTH | B9: Method lineage | C9: Public | D9: 36 | E9: 3.24 | F9: decisive | G9: R3 | H9: unlike realization | I9: =E9/D9 -> 0.09 | J9: =E9/$E$13 -> 0.20786669
A10: REG | B10: Regeneration tool | C10: Public | D10: 18 | E10: 1.2 | F10: decisive | G10: R3 | H10: outside recovery | I10: =E10/D10 -> 0.066666667 | J10: =E10/$E$13 -> 0.076987664
A11: INT | B11: Station integration | C11: Public | D11: 18 | E11: 1.14 | F11: nondecisive | G11: R4 | H11: public-interface assembly only | I11: =E11/D11 -> 0.063333333 | J11: =E11/$E$13 -> 0.07313828
A12: CAN | B12: Candidate mechanism | C12: Private option | D12: 6 | E12: 3.5869128 | F12: decisive | G12: R3 | H12: selected Root House mechanism | I12: =E12/D12 -> 0.5978188 | J12: =E12/$E$13 -> 0.23012336
A13: TOTAL | B13: six classes | C13: mixed | D13: =SUM(D7:D12) -> 102 | E13: =SUM(E7:E12) -> 15.586913 | F13: — | G13: — | H13: 102 separately severable objects | I13: =E13/D13 -> 0.15281287 | J13: =SUM(J7:J12) -> 1

Sheet Lot Register
A2: One hundred two separately severable construction lots
A4: Identity, supplier, award, obligation, payment, acceptance and capability remain source-empty or zero. A constituted lot is not a contract.
A6: Lot ID | B6: Class | C6: Funding | D6: System | E6: Root | F6: Role | G6: Station/package | H6: Lineage | I6: Release | J6: Control group | K6: Authority USD B | L6: Controller ID | M6: Supplier ID | N6: Award | O6: Obligation USD B | P6: Payment USD B | Q6: Packets passed | R6: Gates passed | S6: Capability credit | T6: State
A7: SUB-01 | B7: Civil substrate | C7: Public | D7: MULTI | E7: — | F7: ROTATED | G7: ST-ET-CHA · ST-HC-REC · ST-HU-CON | H7: BOUNDARY | I7: R2 | J7: CG-BND-01 | K7: 0.12 | L7: SOURCE EMPTY | M7: SOURCE EMPTY | N7: 0 | O7: =N7*K7 -> 0 | P7: =Controls!B24 -> 0 | Q7: =Controls!B25 -> 0 | R7: =Controls!B26 -> 0 | S7: =Controls!B27 -> 0 | T7: =IF(N7=0,"CONSTITUTED","AWARDED") -> CONSTITUTED
A8: SUB-02 | B8: Civil substrate | C8: Public | D8: MULTI | E8: — | F8: ROTATED | G8: ST-CT-CHA · ST-LF-REC · ST-RT-CON | H8: BOUNDARY | I8: R2 | J8: CG-BND-02 | K8: 0.12 | L8: SOURCE EMPTY | M8: SOURCE EMPTY | N8: 0 | O8: =N8*K8 -> 0 | P8: =Controls!B24 -> 0 | Q8: =Controls!B25 -> 0 | R8: =Controls!B26 -> 0 | S8: =Controls!B27 -> 0 | T8: =IF(N8=0,"CONSTITUTED","AWARDED") -> CONSTITUTED
A9: SUB-03 | B9: Civil substrate | C9: Public | D9: MULTI | E9: — | F9: ROTATED | G9: ST-ET-CON · ST-HC-CHA · ST-HU-REC | H9: BOUNDARY | I9: R2 | J9: CG-BND-03 | K9: 0.12 | L9: SOURCE EMPTY | M9: SOURCE EMPTY | N9: 0 | O9: =N9*K9 -> 0 | P9: =Controls!B24 -> 0 | Q9: =Controls!B25 -> 0 | R9: =Controls!B26 -> 0 | S9: =Controls!B27 -> 0 | T9: =IF(N9=0,"CONSTITUTED","AWARDED") -> CONSTITUTED
A10: SUB-04 | B10: Civil substrate | C10: Public | D10: MULTI | E10: — | F10: ROTATED | G10: ST-CT-CON · ST-LF-CHA · ST-RT-REC | H10: BOUNDARY | I10: R2 | J10: CG-BND-04 | K10: 0.12 | L10: SOURCE EMPTY | M10: SOURCE EMPTY | N10: 0 | O10: =N10*K10 -> 0 | P10: =Controls!B24 -> 0 | Q10: =Controls!B25 -> 0 | R10: =Controls!B26 -> 0 | S10: =Controls!B27 -> 0 | T10: =IF(N10=0,"CONSTITUTED","AWARDED") -> CONSTITUTED
A11: SUB-05 | B11: Civil substrate | C11: Public | D11: MULTI | E11: — | F11: ROTATED | G11: ST-ET-REC · ST-HC-CON · ST-HU-CHA | H11: BOUNDARY | I11: R2 | J11: CG-BND-05 | K11: 0.12 | L11: SOURCE EMPTY | M11: SOURCE EMPTY | N11: 0 | O11: =N11*K11 -> 0 | P11: =Controls!B24 -> 0 | Q11: =Controls!B25 -> 0 | R11: =Controls!B26 -> 0 | S11: =Controls!B27 -> 0 | T11: =IF(N11=0,"CONSTITUTED","AWARDED") -> CONSTITUTED
A12: SUB-06 | B12: Civil substrate | C12: Public | D12: MULTI | E12: — | F12: ROTATED | G12: ST-CT-REC · ST-LF-CON · ST-RT-CHA | H12: BOUNDARY | I12: R2 | J12: CG-BND-06 | K12: 0.12 | L12: SOURCE EMPTY | M12: SOURCE EMPTY | N12: 0 | O12: =N12*K12 -> 0 | P12: =Controls!B24 -> 0 | Q12: =Controls!B25 -> 0 | R12: =Controls!B26 -> 0 | S12: =Controls!B27 -> 0 | T12: =IF(N12=0,"CONSTITUTED","AWARDED") -> CONSTITUTED
A13: RIG-ET-CHA | B13: Root-native rig | C13: Public | D13: MS-ET | E13: ET-A | F13: CHALLENGE | G13: ST-ET-CHA | H13: RIG | I13: R3 | J13: CG-DEC-RIG-CHA-01 | K13: 0.31666667 | L13: SOURCE EMPTY | M13: SOURCE EMPTY | N13: 0 | O13: =N13*K13 -> 0 | P13: =Controls!B24 -> 0 | Q13: =Controls!B25 -> 0 | R13: =Controls!B26 -> 0 | S13: =Controls!B27 -> 0 | T13: =IF(N13=0,"CONSTITUTED","AWARDED") -> CONSTITUTED
A14: MTH-ET-CHA-L1 | B14: Method lineage | C14: Public | D14: MS-ET | E14: ET-A | F14: CHALLENGE | G14: ST-ET-CHA | H14: L1 | I14: R3 | J14: CG-DEC-M1-CHA-01 | K14: 0.09 | L14: SOURCE EMPTY | M14: SOURCE EMPTY | N14: 0 | O14: =N14*K14 -> 0 | P14: =Controls!B24 -> 0 | Q14: =Controls!B25 -> 0 | R14: =Controls!B26 -> 0 | S14: =Controls!B27 -> 0 | T14: =IF(N14=0,"CONSTITUTED","AWARDED") -> CONSTITUTED
A15: MTH-ET-CHA-L2 | B15: Method lineage | C15: Public | D15: MS-ET | E15: ET-A | F15: CHALLENGE | G15: ST-ET-CHA | H15: L2 | I15: R3 | J15: CG-DEC-M2-CHA-01 | K15: 0.09 | L15: SOURCE EMPTY | M15: SOURCE EMPTY | N15: 0 | O15: =N15*K15 -> 0 | P15: =Controls!B24 -> 0 | Q15: =Controls!B25 -> 0 | R15: =Controls!B26 -> 0 | S15: =Controls!B27 -> 0 | T15: =IF(N15=0,"CONSTITUTED","AWARDED") -> CONSTITUTED
A16: REG-ET-CHA | B16: Regeneration tool | C16: Public | D16: MS-ET | E16: ET-A | F16: CHALLENGE | G16: ST-ET-CHA | H16: REGEN | I16: R3 | J16: CG-DEC-REG-CHA-01 | K16: 0.066666667 | L16: SOURCE EMPTY | M16: SOURCE EMPTY | N16: 0 | O16: =N16*K16 -> 0 | P16: =Controls!B24 -> 0 | Q16: =Controls!B25 -> 0 | R16: =Controls!B26 -> 0 | S16: =Controls!B27 -> 0 | T16: =IF(N16=0,"CONSTITUTED","AWARDED") -> CONSTITUTED
A17: INT-ET-CHA | B17: Station integration | C17: Public | D17: MS-ET | E17: ET-A | F17: CHALLENGE | G17: ST-ET-CHA | H17: BOUNDARY | I17: R4 | J17: CG-BND-02 | K17: 0.063333333 | L17: SOURCE EMPTY | M17: SOURCE EMPTY | N17: 0 | O17: =N17*K17 -> 0 | P17: =Controls!B24 -> 0 | Q17: =Controls!B25 -> 0 | R17: =Controls!B26 -> 0 | S17: =Controls!B27 -> 0 | T17: =IF(N17=0,"CONSTITUTED","AWARDED") -> CONSTITUTED
A18: RIG-ET-CON | B18: Root-native rig | C18: Public | D18: MS-ET | E18: ET-A | F18: CONTROL | G18: ST-ET-CON | H18: RIG | I18: R3 | J18: CG-DEC-RIG-CON-01 | K18: 0.31666667 | L18: SOURCE EMPTY | M18: SOURCE EMPTY | N18: 0 | O18: =N18*K18 -> 0 | P18: =Controls!B24 -> 0 | Q18: =Controls!B25 -> 0 | R18: =Controls!B26 -> 0 | S18: =Controls!B27 -> 0 | T18: =IF(N18=0,"CONSTITUTED","AWARDED") -> CONSTITUTED
A19: MTH-ET-CON-L1 | B19: Method lineage | C19: Public | D19: MS-ET | E19: ET-A | F19: CONTROL | G19: ST-ET-CON | H19: L1 | I19: R3 | J19: CG-DEC-M1-CON-01 | K19: 0.09 | L19: SOURCE EMPTY | M19: SOURCE EMPTY | N19: 0 | O19: =N19*K19 -> 0 | P19: =Controls!B24 -> 0 | Q19: =Controls!B25 -> 0 | R19: =Controls!B26 -> 0 | S19: =Controls!B27 -> 0 | T19: =IF(N19=0,"CONSTITUTED","AWARDED") -> CONSTITUTED
A20: MTH-ET-CON-L2 | B20: Method lineage | C20: Public | D20: MS-ET | E20: ET-A | F20: CONTROL | G20: ST-ET-CON | H20: L2 | I20: R3 | J20: CG-DEC-M2-CON-01 | K20: 0.09 | L20: SOURCE EMPTY | M20: SOURCE EMPTY | N20: 0 | O20: =N20*K20 -> 0 | P20: =Controls!B24 -> 0 | Q20: =Controls!B25 -> 0 | R20: =Controls!B26 -> 0 | S20: =Controls!B27 -> 0 | T20: =IF(N20=0,"CONSTITUTED","AWARDED") -> CONSTITUTED
A21: REG-ET-CON | B21: Regeneration tool | C21: Public | D21: MS-ET | E21: ET-A | F21: CONTROL | G21: ST-ET-CON | H21: REGEN | I21: R3 | J21: CG-DEC-REG-CON-01 | K21: 0.066666667 | L21: SOURCE EMPTY | M21: SOURCE EMPTY | N21: 0 | O21: =N21*K21 -> 0 | P21: =Controls!B24 -> 0 | Q21: =Controls!B25 -> 0 | R21: =Controls!B26 -> 0 | S21: =Controls!B27 -> 0 | T21: =IF(N21=0,"CONSTITUTED","AWARDED") -> CONSTITUTED
A22: INT-ET-CON | B22: Station integration | C22: Public | D22: MS-ET | E22: ET-A | F22: CONTROL | G22: ST-ET-CON | H22: BOUNDARY | I22: R4 | J22: CG-BND-04 | K22: 0.063333333 | L22: SOURCE EMPTY | M22: SOURCE EMPTY | N22: 0 | O22: =N22*K22 -> 0 | P22: =Controls!B24 -> 0 | Q22: =Controls!B25 -> 0 | R22: =Controls!B26 -> 0 | S22: =Controls!B27 -> 0 | T22: =IF(N22=0,"CONSTITUTED","AWARDED") -> CONSTITUTED
A23: RIG-ET-REC | B23: Root-native rig | C23: Public | D23: MS-ET | E23: ET-A | F23: RECONSTRUCTION | G23: ST-ET-REC | H23: RIG | I23: R3 | J23: CG-DEC-RIG-REC-01 | K23: 0.31666667 | L23: SOURCE EMPTY | M23: SOURCE EMPTY | N23: 0 | O23: =N23*K23 -> 0 | P23: =Controls!B24 -> 0 | Q23: =Controls!B25 -> 0 | R23: =Controls!B26 -> 0 | S23: =Controls!B27 -> 0 | T23: =IF(N23=0,"CONSTITUTED","AWARDED") -> CONSTITUTED
A24: MTH-ET-REC-L1 | B24: Method lineage | C24: Public | D24: MS-ET | E24: ET-A | F24: RECONSTRUCTION | G24: ST-ET-REC | H24: L1 | I24: R3 | J24: CG-DEC-M1-REC-01 | K24: 0.09 | L24: SOURCE EMPTY | M24: SOURCE EMPTY | N24: 0 | O24: =N24*K24 -> 0 | P24: =Controls!B24 -> 0 | Q24: =Controls!B25 -> 0 | R24: =Controls!B26 -> 0 | S24: =Controls!B27 -> 0 | T24: =IF(N24=0,"CONSTITUTED","AWARDED") -> CONSTITUTED
A25: MTH-ET-REC-L2 | B25: Method lineage | C25: Public | D25: MS-ET | E25: ET-A | F25: RECONSTRUCTION | G25: ST-ET-REC | H25: L2 | I25: R3 | J25: CG-DEC-M2-REC-01 | K25: 0.09 | L25: SOURCE EMPTY | M25: SOURCE EMPTY | N25: 0 | O25: =N25*K25 -> 0 | P25: =Controls!B24 -> 0 | Q25: =Controls!B25 -> 0 | R25: =Controls!B26 -> 0 | S25: =Controls!B27 -> 0 | T25: =IF(N25=0,"CONSTITUTED","AWARDED") -> CONSTITUTED
A26: REG-ET-REC | B26: Regeneration tool | C26: Public | D26: MS-ET | E26: ET-A | F26: RECONSTRUCTION | G26: ST-ET-REC | H26: REGEN | I26: R3 | J26: CG-DEC-REG-REC-01 | K26: 0.066666667 | L26: SOURCE EMPTY | M26: SOURCE EMPTY | N26: 0 | O26: =N26*K26 -> 0 | P26: =Controls!B24 -> 0 | Q26: =Controls!B25 -> 0 | R26: =Controls!B26 -> 0 | S26: =Controls!B27 -> 0 | T26: =IF(N26=0,"CONSTITUTED","AWARDED") -> CONSTITUTED
A27: INT-ET-REC | B27: Station integration | C27: Public | D27: MS-ET | E27: ET-A | F27: RECONSTRUCTION | G27: ST-ET-REC | H27: BOUNDARY | I27: R4 | J27: CG-BND-06 | K27: 0.063333333 | L27: SOURCE EMPTY | M27: SOURCE EMPTY | N27: 0 | O27: =N27*K27 -> 0 | P27: =Controls!B24 -> 0 | Q27: =Controls!B25 -> 0 | R27: =Controls!B26 -> 0 | S27: =Controls!B27 -> 0 | T27: =IF(N27=0,"CONSTITUTED","AWARDED") -> CONSTITUTED
A28: RIG-CT-CHA | B28: Root-native rig | C28: Public | D28: MS-CT | E28: CT-C | F28: CHALLENGE | G28: ST-CT-CHA | H28: RIG | I28: R3 | J28: CG-DEC-RIG-CHA-02 | K28: 0.31666667 | L28: SOURCE EMPTY | M28: SOURCE EMPTY | N28: 0 | O28: =N28*K28 -> 0 | P28: =Controls!B24 -> 0 | Q28: =Controls!B25 -> 0 | R28: =Controls!B26 -> 0 | S28: =Controls!B27 -> 0 | T28: =IF(N28=0,"CONSTITUTED","AWARDED") -> CONSTITUTED
A29: MTH-CT-CHA-L1 | B29: Method lineage | C29: Public | D29: MS-CT | E29: CT-C | F29: CHALLENGE | G29: ST-CT-CHA | H29: L1 | I29: R3 | J29: CG-DEC-M1-CHA-02 | K29: 0.09 | L29: SOURCE EMPTY | M29: SOURCE EMPTY | N29: 0 | O29: =N29*K29 -> 0 | P29: =Controls!B24 -> 0 | Q29: =Controls!B25 -> 0 | R29: =Controls!B26 -> 0 | S29: =Controls!B27 -> 0 | T29: =IF(N29=0,"CONSTITUTED","AWARDED") -> CONSTITUTED
A30: MTH-CT-CHA-L2 | B30: Method lineage | C30: Public | D30: MS-CT | E30: CT-C | F30: CHALLENGE | G30: ST-CT-CHA | H30: L2 | I30: R3 | J30: CG-DEC-M2-CHA-02 | K30: 0.09 | L30: SOURCE EMPTY | M30: SOURCE EMPTY | N30: 0 | O30: =N30*K30 -> 0 | P30: =Controls!B24 -> 0 | Q30: =Controls!B25 -> 0 | R30: =Controls!B26 -> 0 | S30: =Controls!B27 -> 0 | T30: =IF(N30=0,"CONSTITUTED","AWARDED") -> CONSTITUTED
A31: REG-CT-CHA | B31: Regeneration tool | C31: Public | D31: MS-CT | E31: CT-C | F31: CHALLENGE | G31: ST-CT-CHA | H31: REGEN | I31: R3 | J31: CG-DEC-REG-CHA-02 | K31: 0.066666667 | L31: SOURCE EMPTY | M31: SOURCE EMPTY | N31: 0 | O31: =N31*K31 -> 0 | P31: =Controls!B24 -> 0 | Q31: =Controls!B25 -> 0 | R31: =Controls!B26 -> 0 | S31: =Controls!B27 -> 0 | T31: =IF(N31=0,"CONSTITUTED","AWARDED") -> CONSTITUTED
A32: INT-CT-CHA | B32: Station integration | C32: Public | D32: MS-CT | E32: CT-C | F32: CHALLENGE | G32: ST-CT-CHA | H32: BOUNDARY | I32: R4 | J32: CG-BND-03 | K32: 0.063333333 | L32: SOURCE EMPTY | M32: SOURCE EMPTY | N32: 0 | O32: =N32*K32 -> 0 | P32: =Controls!B24 -> 0 | Q32: =Controls!B25 -> 0 | R32: =Controls!B26 -> 0 | S32: =Controls!B27 -> 0 | T32: =IF(N32=0,"CONSTITUTED","AWARDED") -> CONSTITUTED
A33: RIG-CT-CON | B33: Root-native rig | C33: Public | D33: MS-CT | E33: CT-C | F33: CONTROL | G33: ST-CT-CON | H33: RIG | I33: R3 | J33: CG-DEC-RIG-CON-02 | K33: 0.31666667 | L33: SOURCE EMPTY | M33: SOURCE EMPTY | N33: 0 | O33: =N33*K33 -> 0 | P33: =Controls!B24 -> 0 | Q33: =Controls!B25 -> 0 | R33: =Controls!B26 -> 0 | S33: =Controls!B27 -> 0 | T33: =IF(N33=0,"CONSTITUTED","AWARDED") -> CONSTITUTED
A34: MTH-CT-CON-L1 | B34: Method lineage | C34: Public | D34: MS-CT | E34: CT-C | F34: CONTROL | G34: ST-CT-CON | H34: L1 | I34: R3 | J34: CG-DEC-M1-CON-02 | K34: 0.09 | L34: SOURCE EMPTY | M34: SOURCE EMPTY | N34: 0 | O34: =N34*K34 -> 0 | P34: =Controls!B24 -> 0 | Q34: =Controls!B25 -> 0 | R34: =Controls!B26 -> 0 | S34: =Controls!B27 -> 0 | T34: =IF(N34=0,"CONSTITUTED","AWARDED") -> CONSTITUTED
A35: MTH-CT-CON-L2 | B35: Method lineage | C35: Public | D35: MS-CT | E35: CT-C | F35: CONTROL | G35: ST-CT-CON | H35: L2 | I35: R3 | J35: CG-DEC-M2-CON-02 | K35: 0.09 | L35: SOURCE EMPTY | M35: SOURCE EMPTY | N35: 0 | O35: =N35*K35 -> 0 | P35: =Controls!B24 -> 0 | Q35: =Controls!B25 -> 0 | R35: =Controls!B26 -> 0 | S35: =Controls!B27 -> 0 | T35: =IF(N35=0,"CONSTITUTED","AWARDED") -> CONSTITUTED
A36: REG-CT-CON | B36: Regeneration tool | C36: Public | D36: MS-CT | E36: CT-C | F36: CONTROL | G36: ST-CT-CON | H36: REGEN | I36: R3 | J36: CG-DEC-REG-CON-02 | K36: 0.066666667 | L36: SOURCE EMPTY | M36: SOURCE EMPTY | N36: 0 | O36: =N36*K36 -> 0 | P36: =Controls!B24 -> 0 | Q36: =Controls!B25 -> 0 | R36: =Controls!B26 -> 0 | S36: =Controls!B27 -> 0 | T36: =IF(N36=0,"CONSTITUTED","AWARDED") -> CONSTITUTED
A37: INT-CT-CON | B37: Station integration | C37: Public | D37: MS-CT | E37: CT-C | F37: CONTROL | G37: ST-CT-CON | H37: BOUNDARY | I37: R4 | J37: CG-BND-05 | K37: 0.063333333 | L37: SOURCE EMPTY | M37: SOURCE EMPTY | N37: 0 | O37: =N37*K37 -> 0 | P37: =Controls!B24 -> 0 | Q37: =Controls!B25 -> 0 | R37: =Controls!B26 -> 0 | S37: =Controls!B27 -> 0 | T37: =IF(N37=0,"CONSTITUTED","AWARDED") -> CONSTITUTED
A38: RIG-CT-REC | B38: Root-native rig | C38: Public | D38: MS-CT | E38: CT-C | F38: RECONSTRUCTION | G38: ST-CT-REC | H38: RIG | I38: R3 | J38: CG-DEC-RIG-REC-02 | K38: 0.31666667 | L38: SOURCE EMPTY | M38: SOURCE EMPTY | N38: 0 | O38: =N38*K38 -> 0 | P38: =Controls!B24 -> 0 | Q38: =Controls!B25 -> 0 | R38: =Controls!B26 -> 0 | S38: =Controls!B27 -> 0 | T38: =IF(N38=0,"CONSTITUTED","AWARDED") -> CONSTITUTED
A39: MTH-CT-REC-L1 | B39: Method lineage | C39: Public | D39: MS-CT | E39: CT-C | F39: RECONSTRUCTION | G39: ST-CT-REC | H39: L1 | I39: R3 | J39: CG-DEC-M1-REC-02 | K39: 0.09 | L39: SOURCE EMPTY | M39: SOURCE EMPTY | N39: 0 | O39: =N39*K39 -> 0 | P39: =Controls!B24 -> 0 | Q39: =Controls!B25 -> 0 | R39: =Controls!B26 -> 0 | S39: =Controls!B27 -> 0 | T39: =IF(N39=0,"CONSTITUTED","AWARDED") -> CONSTITUTED
A40: MTH-CT-REC-L2 | B40: Method lineage | C40: Public | D40: MS-CT | E40: CT-C | F40: RECONSTRUCTION | G40: ST-CT-REC | H40: L2 | I40: R3 | J40: CG-DEC-M2-REC-02 | K40: 0.09 | L40: SOURCE EMPTY | M40: SOURCE EMPTY | N40: 0 | O40: =N40*K40 -> 0 | P40: =Controls!B24 -> 0 | Q40: =Controls!B25 -> 0 | R40: =Controls!B26 -> 0 | S40: =Controls!B27 -> 0 | T40: =IF(N40=0,"CONSTITUTED","AWARDED") -> CONSTITUTED
A41: REG-CT-REC | B41: Regeneration tool | C41: Public | D41: MS-CT | E41: CT-C | F41: RECONSTRUCTION | G41: ST-CT-REC | H41: REGEN | I41: R3 | J41: CG-DEC-REG-REC-02 | K41: 0.066666667 | L41: SOURCE EMPTY | M41: SOURCE EMPTY | N41: 0 | O41: =N41*K41 -> 0 | P41: =Controls!B24 -> 0 | Q41: =Controls!B25 -> 0 | R41: =Controls!B26 -> 0 | S41: =Controls!B27 -> 0 | T41: =IF(N41=0,"CONSTITUTED","AWARDED") -> CONSTITUTED
A42: INT-CT-REC | B42: Station integration | C42: Public | D42: MS-CT | E42: CT-C | F42: RECONSTRUCTION | G42: ST-CT-REC | H42: BOUNDARY | I42: R4 | J42: CG-BND-01 | K42: 0.063333333 | L42: SOURCE EMPTY | M42: SOURCE EMPTY | N42: 0 | O42: =N42*K42 -> 0 | P42: =Controls!B24 -> 0 | Q42: =Controls!B25 -> 0 | R42: =Controls!B26 -> 0 | S42: =Controls!B27 -> 0 | T42: =IF(N42=0,"CONSTITUTED","AWARDED") -> CONSTITUTED
A43: RIG-HC-CHA | B43: Root-native rig | C43: Public | D43: MS-HC | E43: HC-A | F43: CHALLENGE | G43: ST-HC-CHA | H43: RIG | I43: R3 | J43: CG-DEC-RIG-CHA-03 | K43: 0.31666667 | L43: SOURCE EMPTY | M43: SOURCE EMPTY | N43: 0 | O43: =N43*K43 -> 0 | P43: =Controls!B24 -> 0 | Q43: =Controls!B25 -> 0 | R43: =Controls!B26 -> 0 | S43: =Controls!B27 -> 0 | T43: =IF(N43=0,"CONSTITUTED","AWARDED") -> CONSTITUTED
A44: MTH-HC-CHA-L1 | B44: Method lineage | C44: Public | D44: MS-HC | E44: HC-A | F44: CHALLENGE | G44: ST-HC-CHA | H44: L1 | I44: R3 | J44: CG-DEC-M1-CHA-03 | K44: 0.09 | L44: SOURCE EMPTY | M44: SOURCE EMPTY | N44: 0 | O44: =N44*K44 -> 0 | P44: =Controls!B24 -> 0 | Q44: =Controls!B25 -> 0 | R44: =Controls!B26 -> 0 | S44: =Controls!B27 -> 0 | T44: =IF(N44=0,"CONSTITUTED","AWARDED") -> CONSTITUTED
A45: MTH-HC-CHA-L2 | B45: Method lineage | C45: Public | D45: MS-HC | E45: HC-A | F45: CHALLENGE | G45: ST-HC-CHA | H45: L2 | I45: R3 | J45: CG-DEC-M2-CHA-03 | K45: 0.09 | L45: SOURCE EMPTY | M45: SOURCE EMPTY | N45: 0 | O45: =N45*K45 -> 0 | P45: =Controls!B24 -> 0 | Q45: =Controls!B25 -> 0 | R45: =Controls!B26 -> 0 | S45: =Controls!B27 -> 0 | T45: =IF(N45=0,"CONSTITUTED","AWARDED") -> CONSTITUTED
A46: REG-HC-CHA | B46: Regeneration tool | C46: Public | D46: MS-HC | E46: HC-A | F46: CHALLENGE | G46: ST-HC-CHA | H46: REGEN | I46: R3 | J46: CG-DEC-REG-CHA-03 | K46: 0.066666667 | L46: SOURCE EMPTY | M46: SOURCE EMPTY | N46: 0 | O46: =N46*K46 -> 0 | P46: =Controls!B24 -> 0 | Q46: =Controls!B25 -> 0 | R46: =Controls!B26 -> 0 | S46: =Controls!B27 -> 0 | T46: =IF(N46=0,"CONSTITUTED","AWARDED") -> CONSTITUTED
A47: INT-HC-CHA | B47: Station integration | C47: Public | D47: MS-HC | E47: HC-A | F47: CHALLENGE | G47: ST-HC-CHA | H47: BOUNDARY | I47: R4 | J47: CG-BND-04 | K47: 0.063333333 | L47: SOURCE EMPTY | M47: SOURCE EMPTY | N47: 0 | O47: =N47*K47 -> 0 | P47: =Controls!B24 -> 0 | Q47: =Controls!B25 -> 0 | R47: =Controls!B26 -> 0 | S47: =Controls!B27 -> 0 | T47: =IF(N47=0,"CONSTITUTED","AWARDED") -> CONSTITUTED
A48: RIG-HC-CON | B48: Root-native rig | C48: Public | D48: MS-HC | E48: HC-A | F48: CONTROL | G48: ST-HC-CON | H48: RIG | I48: R3 | J48: CG-DEC-RIG-CON-03 | K48: 0.31666667 | L48: SOURCE EMPTY | M48: SOURCE EMPTY | N48: 0 | O48: =N48*K48 -> 0 | P48: =Controls!B24 -> 0 | Q48: =Controls!B25 -> 0 | R48: =Controls!B26 -> 0 | S48: =Controls!B27 -> 0 | T48: =IF(N48=0,"CONSTITUTED","AWARDED") -> CONSTITUTED
A49: MTH-HC-CON-L1 | B49: Method lineage | C49: Public | D49: MS-HC | E49: HC-A | F49: CONTROL | G49: ST-HC-CON | H49: L1 | I49: R3 | J49: CG-DEC-M1-CON-03 | K49: 0.09 | L49: SOURCE EMPTY | M49: SOURCE EMPTY | N49: 0 | O49: =N49*K49 -> 0 | P49: =Controls!B24 -> 0 | Q49: =Controls!B25 -> 0 | R49: =Controls!B26 -> 0 | S49: =Controls!B27 -> 0 | T49: =IF(N49=0,"CONSTITUTED","AWARDED") -> CONSTITUTED
A50: MTH-HC-CON-L2 | B50: Method lineage | C50: Public | D50: MS-HC | E50: HC-A | F50: CONTROL | G50: ST-HC-CON | H50: L2 | I50: R3 | J50: CG-DEC-M2-CON-03 | K50: 0.09 | L50: SOURCE EMPTY | M50: SOURCE EMPTY | N50: 0 | O50: =N50*K50 -> 0 | P50: =Controls!B24 -> 0 | Q50: =Controls!B25 -> 0 | R50: =Controls!B26 -> 0 | S50: =Controls!B27 -> 0 | T50: =IF(N50=0,"CONSTITUTED","AWARDED") -> CONSTITUTED
A51: REG-HC-CON | B51: Regeneration tool | C51: Public | D51: MS-HC | E51: HC-A | F51: CONTROL | G51: ST-HC-CON | H51: REGEN | I51: R3 | J51: CG-DEC-REG-CON-03 | K51: 0.066666667 | L51: SOURCE EMPTY | M51: SOURCE EMPTY | N51: 0 | O51: =N51*K51 -> 0 | P51: =Controls!B24 -> 0 | Q51: =Controls!B25 -> 0 | R51: =Controls!B26 -> 0 | S51: =Controls!B27 -> 0 | T51: =IF(N51=0,"CONSTITUTED","AWARDED") -> CONSTITUTED
A52: INT-HC-CON | B52: Station integration | C52: Public | D52: MS-HC | E52: HC-A | F52: CONTROL | G52: ST-HC-CON | H52: BOUNDARY | I52: R4 | J52: CG-BND-06 | K52: 0.063333333 | L52: SOURCE EMPTY | M52: SOURCE EMPTY | N52: 0 | O52: =N52*K52 -> 0 | P52: =Controls!B24 -> 0 | Q52: =Controls!B25 -> 0 | R52: =Controls!B26 -> 0 | S52: =Controls!B27 -> 0 | T52: =IF(N52=0,"CONSTITUTED","AWARDED") -> CONSTITUTED
A53: RIG-HC-REC | B53: Root-native rig | C53: Public | D53: MS-HC | E53: HC-A | F53: RECONSTRUCTION | G53: ST-HC-REC | H53: RIG | I53: R3 | J53: CG-DEC-RIG-REC-03 | K53: 0.31666667 | L53: SOURCE EMPTY | M53: SOURCE EMPTY | N53: 0 | O53: =N53*K53 -> 0 | P53: =Controls!B24 -> 0 | Q53: =Controls!B25 -> 0 | R53: =Controls!B26 -> 0 | S53: =Controls!B27 -> 0 | T53: =IF(N53=0,"CONSTITUTED","AWARDED") -> CONSTITUTED
A54: MTH-HC-REC-L1 | B54: Method lineage | C54: Public | D54: MS-HC | E54: HC-A | F54: RECONSTRUCTION | G54: ST-HC-REC | H54: L1 | I54: R3 | J54: CG-DEC-M1-REC-03 | K54: 0.09 | L54: SOURCE EMPTY | M54: SOURCE EMPTY | N54: 0 | O54: =N54*K54 -> 0 | P54: =Controls!B24 -> 0 | Q54: =Controls!B25 -> 0 | R54: =Controls!B26 -> 0 | S54: =Controls!B27 -> 0 | T54: =IF(N54=0,"CONSTITUTED","AWARDED") -> CONSTITUTED
A55: MTH-HC-REC-L2 | B55: Method lineage | C55: Public | D55: MS-HC | E55: HC-A | F55: RECONSTRUCTION | G55: ST-HC-REC | H55: L2 | I55: R3 | J55: CG-DEC-M2-REC-03 | K55: 0.09 | L55: SOURCE EMPTY | M55: SOURCE EMPTY | N55: 0 | O55: =N55*K55 -> 0 | P55: =Controls!B24 -> 0 | Q55: =Controls!B25 -> 0 | R55: =Controls!B26 -> 0 | S55: =Controls!B27 -> 0 | T55: =IF(N55=0,"CONSTITUTED","AWARDED") -> CONSTITUTED
A56: REG-HC-REC | B56: Regeneration tool | C56: Public | D56: MS-HC | E56: HC-A | F56: RECONSTRUCTION | G56: ST-HC-REC | H56: REGEN | I56: R3 | J56: CG-DEC-REG-REC-03 | K56: 0.066666667 | L56: SOURCE EMPTY | M56: SOURCE EMPTY | N56: 0 | O56: =N56*K56 -> 0 | P56: =Controls!B24 -> 0 | Q56: =Controls!B25 -> 0 | R56: =Controls!B26 -> 0 | S56: =Controls!B27 -> 0 | T56: =IF(N56=0,"CONSTITUTED","AWARDED") -> CONSTITUTED
A57: INT-HC-REC | B57: Station integration | C57: Public | D57: MS-HC | E57: HC-A | F57: RECONSTRUCTION | G57: ST-HC-REC | H57: BOUNDARY | I57: R4 | J57: CG-BND-02 | K57: 0.063333333 | L57: SOURCE EMPTY | M57: SOURCE EMPTY | N57: 0 | O57: =N57*K57 -> 0 | P57: =Controls!B24 -> 0 | Q57: =Controls!B25 -> 0 | R57: =Controls!B26 -> 0 | S57: =Controls!B27 -> 0 | T57: =IF(N57=0,"CONSTITUTED","AWARDED") -> CONSTITUTED
A58: RIG-LF-CHA | B58: Root-native rig | C58: Public | D58: MS-LF | E58: LF-B | F58: CHALLENGE | G58: ST-LF-CHA | H58: RIG | I58: R3 | J58: CG-DEC-RIG-CHA-01 | K58: 0.31666667 | L58: SOURCE EMPTY | M58: SOURCE EMPTY | N58: 0 | O58: =N58*K58 -> 0 | P58: =Controls!B24 -> 0 | Q58: =Controls!B25 -> 0 | R58: =Controls!B26 -> 0 | S58: =Controls!B27 -> 0 | T58: =IF(N58=0,"CONSTITUTED","AWARDED") -> CONSTITUTED
A59: MTH-LF-CHA-L1 | B59: Method lineage | C59: Public | D59: MS-LF | E59: LF-B | F59: CHALLENGE | G59: ST-LF-CHA | H59: L1 | I59: R3 | J59: CG-DEC-M1-CHA-01 | K59: 0.09 | L59: SOURCE EMPTY | M59: SOURCE EMPTY | N59: 0 | O59: =N59*K59 -> 0 | P59: =Controls!B24 -> 0 | Q59: =Controls!B25 -> 0 | R59: =Controls!B26 -> 0 | S59: =Controls!B27 -> 0 | T59: =IF(N59=0,"CONSTITUTED","AWARDED") -> CONSTITUTED
A60: MTH-LF-CHA-L2 | B60: Method lineage | C60: Public | D60: MS-LF | E60: LF-B | F60: CHALLENGE | G60: ST-LF-CHA | H60: L2 | I60: R3 | J60: CG-DEC-M2-CHA-01 | K60: 0.09 | L60: SOURCE EMPTY | M60: SOURCE EMPTY | N60: 0 | O60: =N60*K60 -> 0 | P60: =Controls!B24 -> 0 | Q60: =Controls!B25 -> 0 | R60: =Controls!B26 -> 0 | S60: =Controls!B27 -> 0 | T60: =IF(N60=0,"CONSTITUTED","AWARDED") -> CONSTITUTED
A61: REG-LF-CHA | B61: Regeneration tool | C61: Public | D61: MS-LF | E61: LF-B | F61: CHALLENGE | G61: ST-LF-CHA | H61: REGEN | I61: R3 | J61: CG-DEC-REG-CHA-01 | K61: 0.066666667 | L61: SOURCE EMPTY | M61: SOURCE EMPTY | N61: 0 | O61: =N61*K61 -> 0 | P61: =Controls!B24 -> 0 | Q61: =Controls!B25 -> 0 | R61: =Controls!B26 -> 0 | S61: =Controls!B27 -> 0 | T61: =IF(N61=0,"CONSTITUTED","AWARDED") -> CONSTITUTED
A62: INT-LF-CHA | B62: Station integration | C62: Public | D62: MS-LF | E62: LF-B | F62: CHALLENGE | G62: ST-LF-CHA | H62: BOUNDARY | I62: R4 | J62: CG-BND-05 | K62: 0.063333333 | L62: SOURCE EMPTY | M62: SOURCE EMPTY | N62: 0 | O62: =N62*K62 -> 0 | P62: =Controls!B24 -> 0 | Q62: =Controls!B25 -> 0 | R62: =Controls!B26 -> 0 | S62: =Controls!B27 -> 0 | T62: =IF(N62=0,"CONSTITUTED","AWARDED") -> CONSTITUTED
A63: RIG-LF-CON | B63: Root-native rig | C63: Public | D63: MS-LF | E63: LF-B | F63: CONTROL | G63: ST-LF-CON | H63: RIG | I63: R3 | J63: CG-DEC-RIG-CON-01 | K63: 0.31666667 | L63: SOURCE EMPTY | M63: SOURCE EMPTY | N63: 0 | O63: =N63*K63 -> 0 | P63: =Controls!B24 -> 0 | Q63: =Controls!B25 -> 0 | R63: =Controls!B26 -> 0 | S63: =Controls!B27 -> 0 | T63: =IF(N63=0,"CONSTITUTED","AWARDED") -> CONSTITUTED
A64: MTH-LF-CON-L1 | B64: Method lineage | C64: Public | D64: MS-LF | E64: LF-B | F64: CONTROL | G64: ST-LF-CON | H64: L1 | I64: R3 | J64: CG-DEC-M1-CON-01 | K64: 0.09 | L64: SOURCE EMPTY | M64: SOURCE EMPTY | N64: 0 | O64: =N64*K64 -> 0 | P64: =Controls!B24 -> 0 | Q64: =Controls!B25 -> 0 | R64: =Controls!B26 -> 0 | S64: =Controls!B27 -> 0 | T64: =IF(N64=0,"CONSTITUTED","AWARDED") -> CONSTITUTED
A65: MTH-LF-CON-L2 | B65: Method lineage | C65: Public | D65: MS-LF | E65: LF-B | F65: CONTROL | G65: ST-LF-CON | H65: L2 | I65: R3 | J65: CG-DEC-M2-CON-01 | K65: 0.09 | L65: SOURCE EMPTY | M65: SOURCE EMPTY | N65: 0 | O65: =N65*K65 -> 0 | P65: =Controls!B24 -> 0 | Q65: =Controls!B25 -> 0 | R65: =Controls!B26 -> 0 | S65: =Controls!B27 -> 0 | T65: =IF(N65=0,"CONSTITUTED","AWARDED") -> CONSTITUTED
A66: REG-LF-CON | B66: Regeneration tool | C66: Public | D66: MS-LF | E66: LF-B | F66: CONTROL | G66: ST-LF-CON | H66: REGEN | I66: R3 | J66: CG-DEC-REG-CON-01 | K66: 0.066666667 | L66: SOURCE EMPTY | M66: SOURCE EMPTY | N66: 0 | O66: =N66*K66 -> 0 | P66: =Controls!B24 -> 0 | Q66: =Controls!B25 -> 0 | R66: =Controls!B26 -> 0 | S66: =Controls!B27 -> 0 | T66: =IF(N66=0,"CONSTITUTED","AWARDED") -> CONSTITUTED
A67: INT-LF-CON | B67: Station integration | C67: Public | D67: MS-LF | E67: LF-B | F67: CONTROL | G67: ST-LF-CON | H67: BOUNDARY | I67: R4 | J67: CG-BND-01 | K67: 0.063333333 | L67: SOURCE EMPTY | M67: SOURCE EMPTY | N67: 0 | O67: =N67*K67 -> 0 | P67: =Controls!B24 -> 0 | Q67: =Controls!B25 -> 0 | R67: =Controls!B26 -> 0 | S67: =Controls!B27 -> 0 | T67: =IF(N67=0,"CONSTITUTED","AWARDED") -> CONSTITUTED
A68: RIG-LF-REC | B68: Root-native rig | C68: Public | D68: MS-LF | E68: LF-B | F68: RECONSTRUCTION | G68: ST-LF-REC | H68: RIG | I68: R3 | J68: CG-DEC-RIG-REC-01 | K68: 0.31666667 | L68: SOURCE EMPTY | M68: SOURCE EMPTY | N68: 0 | O68: =N68*K68 -> 0 | P68: =Controls!B24 -> 0 | Q68: =Controls!B25 -> 0 | R68: =Controls!B26 -> 0 | S68: =Controls!B27 -> 0 | T68: =IF(N68=0,"CONSTITUTED","AWARDED") -> CONSTITUTED
A69: MTH-LF-REC-L1 | B69: Method lineage | C69: Public | D69: MS-LF | E69: LF-B | F69: RECONSTRUCTION | G69: ST-LF-REC | H69: L1 | I69: R3 | J69: CG-DEC-M1-REC-01 | K69: 0.09 | L69: SOURCE EMPTY | M69: SOURCE EMPTY | N69: 0 | O69: =N69*K69 -> 0 | P69: =Controls!B24 -> 0 | Q69: =Controls!B25 -> 0 | R69: =Controls!B26 -> 0 | S69: =Controls!B27 -> 0 | T69: =IF(N69=0,"CONSTITUTED","AWARDED") -> CONSTITUTED
A70: MTH-LF-REC-L2 | B70: Method lineage | C70: Public | D70: MS-LF | E70: LF-B | F70: RECONSTRUCTION | G70: ST-LF-REC | H70: L2 | I70: R3 | J70: CG-DEC-M2-REC-01 | K70: 0.09 | L70: SOURCE EMPTY | M70: SOURCE EMPTY | N70: 0 | O70: =N70*K70 -> 0 | P70: =Controls!B24 -> 0 | Q70: =Controls!B25 -> 0 | R70: =Controls!B26 -> 0 | S70: =Controls!B27 -> 0 | T70: =IF(N70=0,"CONSTITUTED","AWARDED") -> CONSTITUTED
A71: REG-LF-REC | B71: Regeneration tool | C71: Public | D71: MS-LF | E71: LF-B | F71: RECONSTRUCTION | G71: ST-LF-REC | H71: REGEN | I71: R3 | J71: CG-DEC-REG-REC-01 | K71: 0.066666667 | L71: SOURCE EMPTY | M71: SOURCE EMPTY | N71: 0 | O71: =N71*K71 -> 0 | P71: =Controls!B24 -> 0 | Q71: =Controls!B25 -> 0 | R71: =Controls!B26 -> 0 | S71: =Controls!B27 -> 0 | T71: =IF(N71=0,"CONSTITUTED","AWARDED") -> CONSTITUTED
A72: INT-LF-REC | B72: Station integration | C72: Public | D72: MS-LF | E72: LF-B | F72: RECONSTRUCTION | G72: ST-LF-REC | H72: BOUNDARY | I72: R4 | J72: CG-BND-03 | K72: 0.063333333 | L72: SOURCE EMPTY | M72: SOURCE EMPTY | N72: 0 | O72: =N72*K72 -> 0 | P72: =Controls!B24 -> 0 | Q72: =Controls!B25 -> 0 | R72: =Controls!B26 -> 0 | S72: =Controls!B27 -> 0 | T72: =IF(N72=0,"CONSTITUTED","AWARDED") -> CONSTITUTED
A73: RIG-HU-CHA | B73: Root-native rig | C73: Public | D73: MS-HU | E73: HU-A | F73: CHALLENGE | G73: ST-HU-CHA | H73: RIG | I73: R3 | J73: CG-DEC-RIG-CHA-02 | K73: 0.31666667 | L73: SOURCE EMPTY | M73: SOURCE EMPTY | N73: 0 | O73: =N73*K73 -> 0 | P73: =Controls!B24 -> 0 | Q73: =Controls!B25 -> 0 | R73: =Controls!B26 -> 0 | S73: =Controls!B27 -> 0 | T73: =IF(N73=0,"CONSTITUTED","AWARDED") -> CONSTITUTED
A74: MTH-HU-CHA-L1 | B74: Method lineage | C74: Public | D74: MS-HU | E74: HU-A | F74: CHALLENGE | G74: ST-HU-CHA | H74: L1 | I74: R3 | J74: CG-DEC-M1-CHA-02 | K74: 0.09 | L74: SOURCE EMPTY | M74: SOURCE EMPTY | N74: 0 | O74: =N74*K74 -> 0 | P74: =Controls!B24 -> 0 | Q74: =Controls!B25 -> 0 | R74: =Controls!B26 -> 0 | S74: =Controls!B27 -> 0 | T74: =IF(N74=0,"CONSTITUTED","AWARDED") -> CONSTITUTED
A75: MTH-HU-CHA-L2 | B75: Method lineage | C75: Public | D75: MS-HU | E75: HU-A | F75: CHALLENGE | G75: ST-HU-CHA | H75: L2 | I75: R3 | J75: CG-DEC-M2-CHA-02 | K75: 0.09 | L75: SOURCE EMPTY | M75: SOURCE EMPTY | N75: 0 | O75: =N75*K75 -> 0 | P75: =Controls!B24 -> 0 | Q75: =Controls!B25 -> 0 | R75: =Controls!B26 -> 0 | S75: =Controls!B27 -> 0 | T75: =IF(N75=0,"CONSTITUTED","AWARDED") -> CONSTITUTED
A76: REG-HU-CHA | B76: Regeneration tool | C76: Public | D76: MS-HU | E76: HU-A | F76: CHALLENGE | G76: ST-HU-CHA | H76: REGEN | I76: R3 | J76: CG-DEC-REG-CHA-02 | K76: 0.066666667 | L76: SOURCE EMPTY | M76: SOURCE EMPTY | N76: 0 | O76: =N76*K76 -> 0 | P76: =Controls!B24 -> 0 | Q76: =Controls!B25 -> 0 | R76: =Controls!B26 -> 0 | S76: =Controls!B27 -> 0 | T76: =IF(N76=0,"CONSTITUTED","AWARDED") -> CONSTITUTED
A77: INT-HU-CHA | B77: Station integration | C77: Public | D77: MS-HU | E77: HU-A | F77: CHALLENGE | G77: ST-HU-CHA | H77: BOUNDARY | I77: R4 | J77: CG-BND-06 | K77: 0.063333333 | L77: SOURCE EMPTY | M77: SOURCE EMPTY | N77: 0 | O77: =N77*K77 -> 0 | P77: =Controls!B24 -> 0 | Q77: =Controls!B25 -> 0 | R77: =Controls!B26 -> 0 | S77: =Controls!B27 -> 0 | T77: =IF(N77=0,"CONSTITUTED","AWARDED") -> CONSTITUTED
A78: RIG-HU-CON | B78: Root-native rig | C78: Public | D78: MS-HU | E78: HU-A | F78: CONTROL | G78: ST-HU-CON | H78: RIG | I78: R3 | J78: CG-DEC-RIG-CON-02 | K78: 0.31666667 | L78: SOURCE EMPTY | M78: SOURCE EMPTY | N78: 0 | O78: =N78*K78 -> 0 | P78: =Controls!B24 -> 0 | Q78: =Controls!B25 -> 0 | R78: =Controls!B26 -> 0 | S78: =Controls!B27 -> 0 | T78: =IF(N78=0,"CONSTITUTED","AWARDED") -> CONSTITUTED
A79: MTH-HU-CON-L1 | B79: Method lineage | C79: Public | D79: MS-HU | E79: HU-A | F79: CONTROL | G79: ST-HU-CON | H79: L1 | I79: R3 | J79: CG-DEC-M1-CON-02 | K79: 0.09 | L79: SOURCE EMPTY | M79: SOURCE EMPTY | N79: 0 | O79: =N79*K79 -> 0 | P79: =Controls!B24 -> 0 | Q79: =Controls!B25 -> 0 | R79: =Controls!B26 -> 0 | S79: =Controls!B27 -> 0 | T79: =IF(N79=0,"CONSTITUTED","AWARDED") -> CONSTITUTED
A80: MTH-HU-CON-L2 | B80: Method lineage | C80: Public | D80: MS-HU | E80: HU-A | F80: CONTROL | G80: ST-HU-CON | H80: L2 | I80: R3 | J80: CG-DEC-M2-CON-02 | K80: 0.09 | L80: SOURCE EMPTY | M80: SOURCE EMPTY | N80: 0 | O80: =N80*K80 -> 0 | P80: =Controls!B24 -> 0 | Q80: =Controls!B25 -> 0 | R80: =Controls!B26 -> 0 | S80: =Controls!B27 -> 0 | T80: =IF(N80=0,"CONSTITUTED","AWARDED") -> CONSTITUTED
A81: REG-HU-CON | B81: Regeneration tool | C81: Public | D81: MS-HU | E81: HU-A | F81: CONTROL | G81: ST-HU-CON | H81: REGEN | I81: R3 | J81: CG-DEC-REG-CON-02 | K81: 0.066666667 | L81: SOURCE EMPTY | M81: SOURCE EMPTY | N81: 0 | O81: =N81*K81 -> 0 | P81: =Controls!B24 -> 0 | Q81: =Controls!B25 -> 0 | R81: =Controls!B26 -> 0 | S81: =Controls!B27 -> 0 | T81: =IF(N81=0,"CONSTITUTED","AWARDED") -> CONSTITUTED
A82: INT-HU-CON | B82: Station integration | C82: Public | D82: MS-HU | E82: HU-A | F82: CONTROL | G82: ST-HU-CON | H82: BOUNDARY | I82: R4 | J82: CG-BND-02 | K82: 0.063333333 | L82: SOURCE EMPTY | M82: SOURCE EMPTY | N82: 0 | O82: =N82*K82 -> 0 | P82: =Controls!B24 -> 0 | Q82: =Controls!B25 -> 0 | R82: =Controls!B26 -> 0 | S82: =Controls!B27 -> 0 | T82: =IF(N82=0,"CONSTITUTED","AWARDED") -> CONSTITUTED
A83: RIG-HU-REC | B83: Root-native rig | C83: Public | D83: MS-HU | E83: HU-A | F83: RECONSTRUCTION | G83: ST-HU-REC | H83: RIG | I83: R3 | J83: CG-DEC-RIG-REC-02 | K83: 0.31666667 | L83: SOURCE EMPTY | M83: SOURCE EMPTY | N83: 0 | O83: =N83*K83 -> 0 | P83: =Controls!B24 -> 0 | Q83: =Controls!B25 -> 0 | R83: =Controls!B26 -> 0 | S83: =Controls!B27 -> 0 | T83: =IF(N83=0,"CONSTITUTED","AWARDED") -> CONSTITUTED
A84: MTH-HU-REC-L1 | B84: Method lineage | C84: Public | D84: MS-HU | E84: HU-A | F84: RECONSTRUCTION | G84: ST-HU-REC | H84: L1 | I84: R3 | J84: CG-DEC-M1-REC-02 | K84: 0.09 | L84: SOURCE EMPTY | M84: SOURCE EMPTY | N84: 0 | O84: =N84*K84 -> 0 | P84: =Controls!B24 -> 0 | Q84: =Controls!B25 -> 0 | R84: =Controls!B26 -> 0 | S84: =Controls!B27 -> 0 | T84: =IF(N84=0,"CONSTITUTED","AWARDED") -> CONSTITUTED
A85: MTH-HU-REC-L2 | B85: Method lineage | C85: Public | D85: MS-HU | E85: HU-A | F85: RECONSTRUCTION | G85: ST-HU-REC | H85: L2 | I85: R3 | J85: CG-DEC-M2-REC-02 | K85: 0.09 | L85: SOURCE EMPTY | M85: SOURCE EMPTY | N85: 0 | O85: =N85*K85 -> 0 | P85: =Controls!B24 -> 0 | Q85: =Controls!B25 -> 0 | R85: =Controls!B26 -> 0 | S85: =Controls!B27 -> 0 | T85: =IF(N85=0,"CONSTITUTED","AWARDED") -> CONSTITUTED
A86: REG-HU-REC | B86: Regeneration tool | C86: Public | D86: MS-HU | E86: HU-A | F86: RECONSTRUCTION | G86: ST-HU-REC | H86: REGEN | I86: R3 | J86: CG-DEC-REG-REC-02 | K86: 0.066666667 | L86: SOURCE EMPTY | M86: SOURCE EMPTY | N86: 0 | O86: =N86*K86 -> 0 | P86: =Controls!B24 -> 0 | Q86: =Controls!B25 -> 0 | R86: =Controls!B26 -> 0 | S86: =Controls!B27 -> 0 | T86: =IF(N86=0,"CONSTITUTED","AWARDED") -> CONSTITUTED
A87: INT-HU-REC | B87: Station integration | C87: Public | D87: MS-HU | E87: HU-A | F87: RECONSTRUCTION | G87: ST-HU-REC | H87: BOUNDARY | I87: R4 | J87: CG-BND-04 | K87: 0.063333333 | L87: SOURCE EMPTY | M87: SOURCE EMPTY | N87: 0 | O87: =N87*K87 -> 0 | P87: =Controls!B24 -> 0 | Q87: =Controls!B25 -> 0 | R87: =Controls!B26 -> 0 | S87: =Controls!B27 -> 0 | T87: =IF(N87=0,"CONSTITUTED","AWARDED") -> CONSTITUTED
A88: RIG-RT-CHA | B88: Root-native rig | C88: Public | D88: MS-RT | E88: RT-B | F88: CHALLENGE | G88: ST-RT-CHA | H88: RIG | I88: R3 | J88: CG-DEC-RIG-CHA-03 | K88: 0.31666667 | L88: SOURCE EMPTY | M88: SOURCE EMPTY | N88: 0 | O88: =N88*K88 -> 0 | P88: =Controls!B24 -> 0 | Q88: =Controls!B25 -> 0 | R88: =Controls!B26 -> 0 | S88: =Controls!B27 -> 0 | T88: =IF(N88=0,"CONSTITUTED","AWARDED") -> CONSTITUTED
A89: MTH-RT-CHA-L1 | B89: Method lineage | C89: Public | D89: MS-RT | E89: RT-B | F89: CHALLENGE | G89: ST-RT-CHA | H89: L1 | I89: R3 | J89: CG-DEC-M1-CHA-03 | K89: 0.09 | L89: SOURCE EMPTY | M89: SOURCE EMPTY | N89: 0 | O89: =N89*K89 -> 0 | P89: =Controls!B24 -> 0 | Q89: =Controls!B25 -> 0 | R89: =Controls!B26 -> 0 | S89: =Controls!B27 -> 0 | T89: =IF(N89=0,"CONSTITUTED","AWARDED") -> CONSTITUTED
A90: MTH-RT-CHA-L2 | B90: Method lineage | C90: Public | D90: MS-RT | E90: RT-B | F90: CHALLENGE | G90: ST-RT-CHA | H90: L2 | I90: R3 | J90: CG-DEC-M2-CHA-03 | K90: 0.09 | L90: SOURCE EMPTY | M90: SOURCE EMPTY | N90: 0 | O90: =N90*K90 -> 0 | P90: =Controls!B24 -> 0 | Q90: =Controls!B25 -> 0 | R90: =Controls!B26 -> 0 | S90: =Controls!B27 -> 0 | T90: =IF(N90=0,"CONSTITUTED","AWARDED") -> CONSTITUTED
A91: REG-RT-CHA | B91: Regeneration tool | C91: Public | D91: MS-RT | E91: RT-B | F91: CHALLENGE | G91: ST-RT-CHA | H91: REGEN | I91: R3 | J91: CG-DEC-REG-CHA-03 | K91: 0.066666667 | L91: SOURCE EMPTY | M91: SOURCE EMPTY | N91: 0 | O91: =N91*K91 -> 0 | P91: =Controls!B24 -> 0 | Q91: =Controls!B25 -> 0 | R91: =Controls!B26 -> 0 | S91: =Controls!B27 -> 0 | T91: =IF(N91=0,"CONSTITUTED","AWARDED") -> CONSTITUTED
A92: INT-RT-CHA | B92: Station integration | C92: Public | D92: MS-RT | E92: RT-B | F92: CHALLENGE | G92: ST-RT-CHA | H92: BOUNDARY | I92: R4 | J92: CG-BND-01 | K92: 0.063333333 | L92: SOURCE EMPTY | M92: SOURCE EMPTY | N92: 0 | O92: =N92*K92 -> 0 | P92: =Controls!B24 -> 0 | Q92: =Controls!B25 -> 0 | R92: =Controls!B26 -> 0 | S92: =Controls!B27 -> 0 | T92: =IF(N92=0,"CONSTITUTED","AWARDED") -> CONSTITUTED
A93: RIG-RT-CON | B93: Root-native rig | C93: Public | D93: MS-RT | E93: RT-B | F93: CONTROL | G93: ST-RT-CON | H93: RIG | I93: R3 | J93: CG-DEC-RIG-CON-03 | K93: 0.31666667 | L93: SOURCE EMPTY | M93: SOURCE EMPTY | N93: 0 | O93: =N93*K93 -> 0 | P93: =Controls!B24 -> 0 | Q93: =Controls!B25 -> 0 | R93: =Controls!B26 -> 0 | S93: =Controls!B27 -> 0 | T93: =IF(N93=0,"CONSTITUTED","AWARDED") -> CONSTITUTED
A94: MTH-RT-CON-L1 | B94: Method lineage | C94: Public | D94: MS-RT | E94: RT-B | F94: CONTROL | G94: ST-RT-CON | H94: L1 | I94: R3 | J94: CG-DEC-M1-CON-03 | K94: 0.09 | L94: SOURCE EMPTY | M94: SOURCE EMPTY | N94: 0 | O94: =N94*K94 -> 0 | P94: =Controls!B24 -> 0 | Q94: =Controls!B25 -> 0 | R94: =Controls!B26 -> 0 | S94: =Controls!B27 -> 0 | T94: =IF(N94=0,"CONSTITUTED","AWARDED") -> CONSTITUTED
A95: MTH-RT-CON-L2 | B95: Method lineage | C95: Public | D95: MS-RT | E95: RT-B | F95: CONTROL | G95: ST-RT-CON | H95: L2 | I95: R3 | J95: CG-DEC-M2-CON-03 | K95: 0.09 | L95: SOURCE EMPTY | M95: SOURCE EMPTY | N95: 0 | O95: =N95*K95 -> 0 | P95: =Controls!B24 -> 0 | Q95: =Controls!B25 -> 0 | R95: =Controls!B26 -> 0 | S95: =Controls!B27 -> 0 | T95: =IF(N95=0,"CONSTITUTED","AWARDED") -> CONSTITUTED
A96: REG-RT-CON | B96: Regeneration tool | C96: Public | D96: MS-RT | E96: RT-B | F96: CONTROL | G96: ST-RT-CON | H96: REGEN | I96: R3 | J96: CG-DEC-REG-CON-03 | K96: 0.066666667 | L96: SOURCE EMPTY | M96: SOURCE EMPTY | N96: 0 | O96: =N96*K96 -> 0 | P96: =Controls!B24 -> 0 | Q96: =Controls!B25 -> 0 | R96: =Controls!B26 -> 0 | S96: =Controls!B27 -> 0 | T96: =IF(N96=0,"CONSTITUTED","AWARDED") -> CONSTITUTED
A97: INT-RT-CON | B97: Station integration | C97: Public | D97: MS-RT | E97: RT-B | F97: CONTROL | G97: ST-RT-CON | H97: BOUNDARY | I97: R4 | J97: CG-BND-03 | K97: 0.063333333 | L97: SOURCE EMPTY | M97: SOURCE EMPTY | N97: 0 | O97: =N97*K97 -> 0 | P97: =Controls!B24 -> 0 | Q97: =Controls!B25 -> 0 | R97: =Controls!B26 -> 0 | S97: =Controls!B27 -> 0 | T97: =IF(N97=0,"CONSTITUTED","AWARDED") -> CONSTITUTED
A98: RIG-RT-REC | B98: Root-native rig | C98: Public | D98: MS-RT | E98: RT-B | F98: RECONSTRUCTION | G98: ST-RT-REC | H98: RIG | I98: R3 | J98: CG-DEC-RIG-REC-03 | K98: 0.31666667 | L98: SOURCE EMPTY | M98: SOURCE EMPTY | N98: 0 | O98: =N98*K98 -> 0 | P98: =Controls!B24 -> 0 | Q98: =Controls!B25 -> 0 | R98: =Controls!B26 -> 0 | S98: =Controls!B27 -> 0 | T98: =IF(N98=0,"CONSTITUTED","AWARDED") -> CONSTITUTED
A99: MTH-RT-REC-L1 | B99: Method lineage | C99: Public | D99: MS-RT | E99: RT-B | F99: RECONSTRUCTION | G99: ST-RT-REC | H99: L1 | I99: R3 | J99: CG-DEC-M1-REC-03 | K99: 0.09 | L99: SOURCE EMPTY | M99: SOURCE EMPTY | N99: 0 | O99: =N99*K99 -> 0 | P99: =Controls!B24 -> 0 | Q99: =Controls!B25 -> 0 | R99: =Controls!B26 -> 0 | S99: =Controls!B27 -> 0 | T99: =IF(N99=0,"CONSTITUTED","AWARDED") -> CONSTITUTED
A100: MTH-RT-REC-L2 | B100: Method lineage | C100: Public | D100: MS-RT | E100: RT-B | F100: RECONSTRUCTION | G100: ST-RT-REC | H100: L2 | I100: R3 | J100: CG-DEC-M2-REC-03 | K100: 0.09 | L100: SOURCE EMPTY | M100: SOURCE EMPTY | N100: 0 | O100: =N100*K100 -> 0 | P100: =Controls!B24 -> 0 | Q100: =Controls!B25 -> 0 | R100: =Controls!B26 -> 0 | S100: =Controls!B27 -> 0 | T100: =IF(N100=0,"CONSTITUTED","AWARDED") -> CONSTITUTED
A101: REG-RT-REC | B101: Regeneration tool | C101: Public | D101: MS-RT | E101: RT-B | F101: RECONSTRUCTION | G101: ST-RT-REC | H101: REGEN | I101: R3 | J101: CG-DEC-REG-REC-03 | K101: 0.066666667 | L101: SOURCE EMPTY | M101: SOURCE EMPTY | N101: 0 | O101: =N101*K101 -> 0 | P101: =Controls!B24 -> 0 | Q101: =Controls!B25 -> 0 | R101: =Controls!B26 -> 0 | S101: =Controls!B27 -> 0 | T101: =IF(N101=0,"CONSTITUTED","AWARDED") -> CONSTITUTED
A102: INT-RT-REC | B102: Station integration | C102: Public | D102: MS-RT | E102: RT-B | F102: RECONSTRUCTION | G102: ST-RT-REC | H102: BOUNDARY | I102: R4 | J102: CG-BND-05 | K102: 0.063333333 | L102: SOURCE EMPTY | M102: SOURCE EMPTY | N102: 0 | O102: =N102*K102 -> 0 | P102: =Controls!B24 -> 0 | Q102: =Controls!B25 -> 0 | R102: =Controls!B26 -> 0 | S102: =Controls!B27 -> 0 | T102: =IF(N102=0,"CONSTITUTED","AWARDED") -> CONSTITUTED
A103: CAN-ET-A | B103: Candidate mechanism | C103: Private option | D103: MS-ET | E103: ET-A | F103: SYSTEM | G103: ET TRUTH TRAIN | H103: CANDIDATE | I103: R3 | J103: CG-CAN-ET | K103: 0.50047462 | L103: SOURCE EMPTY | M103: SOURCE EMPTY | N103: 0 | O103: =N103*K103 -> 0 | P103: =Controls!B24 -> 0 | Q103: =Controls!B25 -> 0 | R103: =Controls!B26 -> 0 | S103: =Controls!B27 -> 0 | T103: =IF(N103=0,"CONSTITUTED","AWARDED") -> CONSTITUTED
...

Sheet Substrate Rotation
A2: Six balanced civil-substrate packages
A4: Each substrate lineage touches three distinct systems and one station in each role; no system-role cell repeats.
A6: Lot | B6: Control group | C6: Stations | D6: Systems | E6: Roles | F6: Station count | G6: Distinct systems | H6: Distinct roles | I6: Authority USD B | J6: State
A7: SUB-01 | B7: CG-BND-01 | C7: ST-ET-CHA · ST-HC-REC · ST-HU-CON | D7: MS-ET · MS-HC · MS-HU | E7: CHALLENGE · RECONSTRUCTION · CONTROL | F7: 3 | G7: 3 | H7: 3 | I7: 0.12 | J7: CONSTITUTED
A8: SUB-02 | B8: CG-BND-02 | C8: ST-CT-CHA · ST-LF-REC · ST-RT-CON | D8: MS-CT · MS-LF · MS-RT | E8: CHALLENGE · RECONSTRUCTION · CONTROL | F8: 3 | G8: 3 | H8: 3 | I8: 0.12 | J8: CONSTITUTED
A9: SUB-03 | B9: CG-BND-03 | C9: ST-ET-CON · ST-HC-CHA · ST-HU-REC | D9: MS-ET · MS-HC · MS-HU | E9: CONTROL · CHALLENGE · RECONSTRUCTION | F9: 3 | G9: 3 | H9: 3 | I9: 0.12 | J9: CONSTITUTED
A10: SUB-04 | B10: CG-BND-04 | C10: ST-CT-CON · ST-LF-CHA · ST-RT-REC | D10: MS-CT · MS-LF · MS-RT | E10: CONTROL · CHALLENGE · RECONSTRUCTION | F10: 3 | G10: 3 | H10: 3 | I10: 0.12 | J10: CONSTITUTED
A11: SUB-05 | B11: CG-BND-05 | C11: ST-ET-REC · ST-HC-CON · ST-HU-CHA | D11: MS-ET · MS-HC · MS-HU | E11: RECONSTRUCTION · CONTROL · CHALLENGE | F11: 3 | G11: 3 | H11: 3 | I11: 0.12 | J11: CONSTITUTED
A12: SUB-06 | B12: CG-BND-06 | C12: ST-CT-REC · ST-LF-CON · ST-RT-CHA | D12: MS-CT · MS-LF · MS-RT | E12: RECONSTRUCTION · CONTROL · CHALLENGE | F12: 3 | G12: 3 | H12: 3 | I12: 0.12 | J12: CONSTITUTED

Sheet Station Crosswalk
A2: Eighteen station nuclei and their five local lots
A4: The candidate option is system-level; each station receives five public construction objects and one rotated substrate package.
A6: Station | B6: System | C6: Root | D6: Role | E6: Substrate | F6: Rig | G6: Method L1 | H6: Method L2 | I6: Regeneration | J6: Integration | K6: Boundary group | L6: Site | M6: State
A7: ST-ET-CHA | B7: MS-ET | C7: ET-A | D7: CHALLENGE | E7: SUB-01 | F7: RIG-ET-CHA | G7: MTH-ET-CHA-L1 | H7: MTH-ET-CHA-L2 | I7: REG-ET-CHA | J7: INT-ET-CHA | K7: CG-BND-02 | L7: SOURCE EMPTY | M7: CONSTITUTED
A8: ST-ET-CON | B8: MS-ET | C8: ET-A | D8: CONTROL | E8: SUB-03 | F8: RIG-ET-CON | G8: MTH-ET-CON-L1 | H8: MTH-ET-CON-L2 | I8: REG-ET-CON | J8: INT-ET-CON | K8: CG-BND-04 | L8: SOURCE EMPTY | M8: CONSTITUTED
A9: ST-ET-REC | B9: MS-ET | C9: ET-A | D9: RECONSTRUCTION | E9: SUB-05 | F9: RIG-ET-REC | G9: MTH-ET-REC-L1 | H9: MTH-ET-REC-L2 | I9: REG-ET-REC | J9: INT-ET-REC | K9: CG-BND-06 | L9: SOURCE EMPTY | M9: CONSTITUTED
A10: ST-CT-CHA | B10: MS-CT | C10: CT-C | D10: CHALLENGE | E10: SUB-02 | F10: RIG-CT-CHA | G10: MTH-CT-CHA-L1 | H10: MTH-CT-CHA-L2 | I10: REG-CT-CHA | J10: INT-CT-CHA | K10: CG-BND-03 | L10: SOURCE EMPTY | M10: CONSTITUTED
A11: ST-CT-CON | B11: MS-CT | C11: CT-C | D11: CONTROL | E11: SUB-04 | F11: RIG-CT-CON | G11: MTH-CT-CON-L1 | H11: MTH-CT-CON-L2 | I11: REG-CT-CON | J11: INT-CT-CON | K11: CG-BND-05 | L11: SOURCE EMPTY | M11: CONSTITUTED
A12: ST-CT-REC | B12: MS-CT | C12: CT-C | D12: RECONSTRUCTION | E12: SUB-06 | F12: RIG-CT-REC | G12: MTH-CT-REC-L1 | H12: MTH-CT-REC-L2 | I12: REG-CT-REC | J12: INT-CT-REC | K12: CG-BND-01 | L12: SOURCE EMPTY | M12: CONSTITUTED
A13: ST-HC-CHA | B13: MS-HC | C13: HC-A | D13: CHALLENGE | E13: SUB-03 | F13: RIG-HC-CHA | G13: MTH-HC-CHA-L1 | H13: MTH-HC-CHA-L2 | I13: REG-HC-CHA | J13: INT-HC-CHA | K13: CG-BND-04 | L13: SOURCE EMPTY | M13: CONSTITUTED
A14: ST-HC-CON | B14: MS-HC | C14: HC-A | D14: CONTROL | E14: SUB-05 | F14: RIG-HC-CON | G14: MTH-HC-CON-L1 | H14: MTH-HC-CON-L2 | I14: REG-HC-CON | J14: INT-HC-CON | K14: CG-BND-06 | L14: SOURCE EMPTY | M14: CONSTITUTED
A15: ST-HC-REC | B15: MS-HC | C15: HC-A | D15: RECONSTRUCTION | E15: SUB-01 | F15: RIG-HC-REC | G15: MTH-HC-REC-L1 | H15: MTH-HC-REC-L2 | I15: REG-HC-REC | J15: INT-HC-REC | K15: CG-BND-02 | L15: SOURCE EMPTY | M15: CONSTITUTED
A16: ST-LF-CHA | B16: MS-LF | C16: LF-B | D16: CHALLENGE | E16: SUB-04 | F16: RIG-LF-CHA | G16: MTH-LF-CHA-L1 | H16: MTH-LF-CHA-L2 | I16: REG-LF-CHA | J16: INT-LF-CHA | K16: CG-BND-05 | L16: SOURCE EMPTY | M16: CONSTITUTED
A17: ST-LF-CON | B17: MS-LF | C17: LF-B | D17: CONTROL | E17: SUB-06 | F17: RIG-LF-CON | G17: MTH-LF-CON-L1 | H17: MTH-LF-CON-L2 | I17: REG-LF-CON | J17: INT-LF-CON | K17: CG-BND-01 | L17: SOURCE EMPTY | M17: CONSTITUTED
... A24: ST-RT-REC | B24: MS-RT | C24: RT-B | D24: RECONSTRUCTION | E24: SUB-04 | F24: RIG-RT-REC | G24: MTH-RT-REC-L1 | H24: MTH-RT-REC-L2 | I24: REG-RT-REC | J24: INT-RT-REC | K24: CG-BND-05 | L24: SOURCE EMPTY | M24: CONSTITUTED

Sheet Control Groups
A2: Forty-eight beneficial-control groups
A4: Control is tested through beneficial ownership, debt, decisive subcontractors, tooling, keys, calibration and accepting personnel—not prime names.
A6: Group | B6: Control class | C6: Permitted work | D6: Lot cap | E6: Assigned lots | F6: Headroom | G6: Cap state | H6: Controller identity | I6: Cross-class control | J6: Rule
A7: CG-CAN-ET | B7: Candidate | C7: private mechanism | D7: 1 | E7: 1 | F7: =D7-E7 -> 0 | G7: =IF(F7>=0,"PASS","FAIL") -> PASS | H7: SOURCE EMPTY | I7: NO | J7: one Root House; no public lot in system
A8: CG-CAN-CT | B8: Candidate | C8: private mechanism | D8: 1 | E8: 1 | F8: =D8-E8 -> 0 | G8: =IF(F8>=0,"PASS","FAIL") -> PASS | H8: SOURCE EMPTY | I8: NO | J8: one Root House; no public lot in system
A9: CG-CAN-HC | B9: Candidate | C9: private mechanism | D9: 1 | E9: 1 | F9: =D9-E9 -> 0 | G9: =IF(F9>=0,"PASS","FAIL") -> PASS | H9: SOURCE EMPTY | I9: NO | J9: one Root House; no public lot in system
A10: CG-CAN-LF | B10: Candidate | C10: private mechanism | D10: 1 | E10: 1 | F10: =D10-E10 -> 0 | G10: =IF(F10>=0,"PASS","FAIL") -> PASS | H10: SOURCE EMPTY | I10: NO | J10: one Root House; no public lot in system
A11: CG-CAN-HU | B11: Candidate | C11: private mechanism | D11: 1 | E11: 1 | F11: =D11-E11 -> 0 | G11: =IF(F11>=0,"PASS","FAIL") -> PASS | H11: SOURCE EMPTY | I11: NO | J11: one Root House; no public lot in system
A12: CG-CAN-RT | B12: Candidate | C12: private mechanism | D12: 1 | E12: 1 | F12: =D12-E12 -> 0 | G12: =IF(F12>=0,"PASS","FAIL") -> PASS | H12: SOURCE EMPTY | I12: NO | J12: one Root House; no public lot in system
A13: CG-DEC-RIG-CHA-01 | B13: Public decisive | C13: RIG | D13: 2 | E13: 2 | F13: =D13-E13 -> 0 | G13: =IF(F13>=0,"PASS","FAIL") -> PASS | H13: SOURCE EMPTY | I13: NO | J13: different systems; one class and role
A14: CG-DEC-RIG-CHA-02 | B14: Public decisive | C14: RIG | D14: 2 | E14: 2 | F14: =D14-E14 -> 0 | G14: =IF(F14>=0,"PASS","FAIL") -> PASS | H14: SOURCE EMPTY | I14: NO | J14: different systems; one class and role
A15: CG-DEC-RIG-CHA-03 | B15: Public decisive | C15: RIG | D15: 2 | E15: 2 | F15: =D15-E15 -> 0 | G15: =IF(F15>=0,"PASS","FAIL") -> PASS | H15: SOURCE EMPTY | I15: NO | J15: different systems; one class and role
A16: CG-DEC-RIG-CON-01 | B16: Public decisive | C16: RIG | D16: 2 | E16: 2 | F16: =D16-E16 -> 0 | G16: =IF(F16>=0,"PASS","FAIL") -> PASS | H16: SOURCE EMPTY | I16: NO | J16: different systems; one class and role
A17: CG-DEC-RIG-CON-02 | B17: Public decisive | C17: RIG | D17: 2 | E17: 2 | F17: =D17-E17 -> 0 | G17: =IF(F17>=0,"PASS","FAIL") -> PASS | H17: SOURCE EMPTY | I17: NO | J17: different systems; one class and role
A18: CG-DEC-RIG-CON-03 | B18: Public decisive | C18: RIG | D18: 2 | E18: 2 | F18: =D18-E18 -> 0 | G18: =IF(F18>=0,"PASS","FAIL") -> PASS | H18: SOURCE EMPTY | I18: NO | J18: different systems; one class and role
... A54: CG-BND-06 | B54: Public boundary | C54: substrate + integration | D54: 4 | E54: 4 | F54: =D54-E54 -> 0 | G54: =IF(F54>=0,"PASS","FAIL") -> PASS | H54: SOURCE EMPTY | I54: NO | J54: no same-station substrate and integration

Sheet Collision Rules
A2: Industrial firewalls that survive nominal subcontracting
A4: The national slate must pass every rule before any partial award; later corporate transactions reopen the complete slate.
A6: ID | B6: Scope | C6: Rule | D6: Test object | E6: Violation action | F6: May waiver fix it? | G6: State
A7: C01 | B7: candidate | C7: one beneficial-control group per selected Root House | D7: owner, debt, keys, tooling | E7: reject slate | F7: NO | G7: FROZEN
A8: C02 | B8: candidate/public | C8: candidate controller holds no public lot in its system | D8: all controlled affiliates | E8: reject slate | F8: NO | G8: FROZEN
A9: C03 | B9: decisive public | C9: maximum two lots nationally | D9: beneficial-control group | E9: reject excess lots | F9: NO | G9: FROZEN
A10: C04 | B10: decisive public | C10: no two controlled lots in one system | D10: system ancestry | E10: reject slate | F10: NO | G10: FROZEN
A11: C05 | B11: method | C11: one controller may not hold both L1 and L2 | D11: method lineage | E11: reject slate | F11: NO | G11: FROZEN
A12: C06 | B12: station | C12: rig and regeneration may not share control | D12: station ancestry | E12: reject slate | F12: NO | G12: FROZEN
A13: C07 | B13: boundary | C13: substrate and integration at one station may not share control | D13: station boundary | E13: reject slate | F13: NO | G13: FROZEN
A14: C08 | B14: cross-class | C14: candidate, public decisive and public boundary classes do not cross-control | D14: complete group map | E14: reject slate | F14: NO | G14: FROZEN
A15: C09 | B15: subtier | C15: decisive subcontractor obeys the prime cap | D15: subtier control graph | E15: replace dependency | F15: NO | G15: FROZEN
A16: C10 | B16: toolchain | C16: executable compiler, calibration or key that changes outcome is decisive | D16: artifact ancestry | E16: split implementation | F16: NO | G16: FROZEN
A17: C11 | B17: commodity | C17: common item is allowed only when incapable of changing outcome | D17: failure and tuning envelope | E17: reclassify or split | F17: NO | G17: FROZEN
A18: C12 | B18: acceptance | C18: builder and integrator sign no acceptance decision on their own lot | D18: signer graph | E18: invalidate acceptance | F18: NO | G18: FROZEN

Sheet Method Lots
A2: Thirty-six unlike physical method-lineage lots
A4: Each lineage realizes all four receiver-state bays at one station. L1 and L2 never share beneficial control, decisive tooling or accepting personnel.
A6: Lot | B6: Station | C6: System | D6: Root | E6: Role | F6: Lineage | G6: Receiver-state bays | H6: Control group | I6: Authority USD B | J6: Realization identity | K6: Accepted bays | L6: State
A7: MTH-ET-CHA-L1 | B7: ST-ET-CHA | C7: MS-ET | D7: ET-A | E7: CHALLENGE | F7: L1 | G7: 4 | H7: CG-DEC-M1-CHA-01 | I7: 0.09 | J7: SOURCE EMPTY | K7: 0 | L7: HELD
A8: MTH-ET-CHA-L2 | B8: ST-ET-CHA | C8: MS-ET | D8: ET-A | E8: CHALLENGE | F8: L2 | G8: 4 | H8: CG-DEC-M2-CHA-01 | I8: 0.09 | J8: SOURCE EMPTY | K8: 0 | L8: HELD
A9: MTH-ET-CON-L1 | B9: ST-ET-CON | C9: MS-ET | D9: ET-A | E9: CONTROL | F9: L1 | G9: 4 | H9: CG-DEC-M1-CON-01 | I9: 0.09 | J9: SOURCE EMPTY | K9: 0 | L9: HELD
A10: MTH-ET-CON-L2 | B10: ST-ET-CON | C10: MS-ET | D10: ET-A | E10: CONTROL | F10: L2 | G10: 4 | H10: CG-DEC-M2-CON-01 | I10: 0.09 | J10: SOURCE EMPTY | K10: 0 | L10: HELD
A11: MTH-ET-REC-L1 | B11: ST-ET-REC | C11: MS-ET | D11: ET-A | E11: RECONSTRUCTION | F11: L1 | G11: 4 | H11: CG-DEC-M1-REC-01 | I11: 0.09 | J11: SOURCE EMPTY | K11: 0 | L11: HELD
A12: MTH-ET-REC-L2 | B12: ST-ET-REC | C12: MS-ET | D12: ET-A | E12: RECONSTRUCTION | F12: L2 | G12: 4 | H12: CG-DEC-M2-REC-01 | I12: 0.09 | J12: SOURCE EMPTY | K12: 0 | L12: HELD
A13: MTH-CT-CHA-L1 | B13: ST-CT-CHA | C13: MS-CT | D13: CT-C | E13: CHALLENGE | F13: L1 | G13: 4 | H13: CG-DEC-M1-CHA-02 | I13: 0.09 | J13: SOURCE EMPTY | K13: 0 | L13: HELD
A14: MTH-CT-CHA-L2 | B14: ST-CT-CHA | C14: MS-CT | D14: CT-C | E14: CHALLENGE | F14: L2 | G14: 4 | H14: CG-DEC-M2-CHA-02 | I14: 0.09 | J14: SOURCE EMPTY | K14: 0 | L14: HELD
A15: MTH-CT-CON-L1 | B15: ST-CT-CON | C15: MS-CT | D15: CT-C | E15: CONTROL | F15: L1 | G15: 4 | H15: CG-DEC-M1-CON-02 | I15: 0.09 | J15: SOURCE EMPTY | K15: 0 | L15: HELD
A16: MTH-CT-CON-L2 | B16: ST-CT-CON | C16: MS-CT | D16: CT-C | E16: CONTROL | F16: L2 | G16: 4 | H16: CG-DEC-M2-CON-02 | I16: 0.09 | J16: SOURCE EMPTY | K16: 0 | L16: HELD
A17: MTH-CT-REC-L1 | B17: ST-CT-REC | C17: MS-CT | D17: CT-C | E17: RECONSTRUCTION | F17: L1 | G17: 4 | H17: CG-DEC-M1-REC-02 | I17: 0.09 | J17: SOURCE EMPTY | K17: 0 | L17: HELD
A18: MTH-CT-REC-L2 | B18: ST-CT-REC | C18: MS-CT | D18: CT-C | E18: RECONSTRUCTION | F18: L2 | G18: 4 | H18: CG-DEC-M2-REC-02 | I18: 0.09 | J18: SOURCE EMPTY | K18: 0 | L18: HELD
... A42: MTH-RT-REC-L2 | B42: ST-RT-REC | C42: MS-RT | D42: RT-B | E42: RECONSTRUCTION | F42: L2 | G42: 4 | H42: CG-DEC-M2-REC-03 | I42: 0.09 | J42: SOURCE EMPTY | K42: 0 | L42: HELD

Sheet Acceptance Packets
A2: Five hundred ten construction-acceptance packet records
A4: Every lot owes all five packet families. Source identity and acceptance remain empty or zero until a separately warranted physical record exists.
A6: Packet ID | B6: Lot ID | C6: Lot class | D6: System | E6: Station/package | F6: Packet family | G6: Required evidence | H6: Accepting authority | I6: Source identity | J6: Accepted | K6: State
A7: ="PKT-"&B7&"-CONFIGURATION" -> PKT-SUB-01-CONFIGURATION | B7: ='Lot Register'!A7 -> SUB-01 | C7: ='Lot Register'!B7 -> Civil substrate | D7: ='Lot Register'!D7 -> MULTI | E7: ='Lot Register'!G7 -> ST-ET-CHA · ST-HC-REC · ST-HU-CON | F7: CONFIGURATION | G7: frozen requirement, materials, interfaces and as-built record | H7: Requirement issuer | I7: SOURCE EMPTY | J7: =Controls!B25 -> 0 | K7: =IF(J7=1,"ACCEPTED","OPEN") -> OPEN
A8: ="PKT-"&B8&"-CONTROL" -> PKT-SUB-01-CONTROL | B8: ='Lot Register'!A7 -> SUB-01 | C8: ='Lot Register'!B7 -> Civil substrate | D8: ='Lot Register'!D7 -> MULTI | E8: ='Lot Register'!G7 -> ST-ET-CHA · ST-HC-REC · ST-HU-CON | F8: CONTROL | G8: beneficial ownership, decisive ancestry, debt, tooling and key custody | H8: Control registrar | I8: SOURCE EMPTY | J8: =Controls!B25 -> 0 | K8: =IF(J8=1,"ACCEPTED","OPEN") -> OPEN
A9: ="PKT-"&B9&"-METROLOGY" -> PKT-SUB-01-METROLOGY | B9: ='Lot Register'!A7 -> SUB-01 | C9: ='Lot Register'!B7 -> Civil substrate | D9: ='Lot Register'!D7 -> MULTI | E9: ='Lot Register'!G7 -> ST-ET-CHA · ST-HC-REC · ST-HU-CON | F9: METROLOGY | G9: native commissioning, calibration chain and measurement uncertainty | H9: Commissioning authority | I9: SOURCE EMPTY | J9: =Controls!B25 -> 0 | K9: =IF(J9=1,"ACCEPTED","OPEN") -> OPEN
A10: ="PKT-"&B10&"-SAFETY" -> PKT-SUB-01-SAFETY | B10: ='Lot Register'!A7 -> SUB-01 | C10: ='Lot Register'!B7 -> Civil substrate | D10: ='Lot Register'!D7 -> MULTI | E10: ='Lot Register'!G7 -> ST-ET-CHA · ST-HC-REC · ST-HU-CON | F10: SAFETY | G10: worker, civil-rights, environmental, residual and safe-stop record | H10: Safety and rights authority | I10: SOURCE EMPTY | J10: =Controls!B25 -> 0 | K10: =IF(J10=1,"ACCEPTED","OPEN") -> OPEN
A11: ="PKT-"&B11&"-RECONSTRUCTION" -> PKT-SUB-01-RECONSTRUCTION | B11: ='Lot Register'!A7 -> SUB-01 | C11: ='Lot Register'!B7 -> Civil substrate | D11: ='Lot Register'!D7 -> MULTI | E11: ='Lot Register'!G7 -> ST-ET-CHA · ST-HC-REC · ST-HU-CON | F11: RECONSTRUCTION | G11: sealed custody, cold build description and outside-team replay | H11: Evidence Court | I11: SOURCE EMPTY | J11: =Controls!B25 -> 0 | K11: =IF(J11=1,"ACCEPTED","OPEN") -> OPEN
A12: ="PKT-"&B12&"-CONFIGURATION" -> PKT-SUB-02-CONFIGURATION | B12: ='Lot Register'!A8 -> SUB-02 | C12: ='Lot Register'!B8 -> Civil substrate | D12: ='Lot Register'!D8 -> MULTI | E12: ='Lot Register'!G8 -> ST-CT-CHA · ST-LF-REC · ST-RT-CON | F12: CONFIGURATION | G12: frozen requirement, materials, interfaces and as-built record | H12: Requirement issuer | I12: SOURCE EMPTY | J12: =Controls!B25 -> 0 | K12: =IF(J12=1,"ACCEPTED","OPEN") -> OPEN
A13: ="PKT-"&B13&"-CONTROL" -> PKT-SUB-02-CONTROL | B13: ='Lot Register'!A8 -> SUB-02 | C13: ='Lot Register'!B8 -> Civil substrate | D13: ='Lot Register'!D8 -> MULTI | E13: ='Lot Register'!G8 -> ST-CT-CHA · ST-LF-REC · ST-RT-CON | F13: CONTROL | G13: beneficial ownership, decisive ancestry, debt, tooling and key custody | H13: Control registrar | I13: SOURCE EMPTY | J13: =Controls!B25 -> 0 | K13: =IF(J13=1,"ACCEPTED","OPEN") -> OPEN
A14: ="PKT-"&B14&"-METROLOGY" -> PKT-SUB-02-METROLOGY | B14: ='Lot Register'!A8 -> SUB-02 | C14: ='Lot Register'!B8 -> Civil substrate | D14: ='Lot Register'!D8 -> MULTI | E14: ='Lot Register'!G8 -> ST-CT-CHA · ST-LF-REC · ST-RT-CON | F14: METROLOGY | G14: native commissioning, calibration chain and measurement uncertainty | H14: Commissioning authority | I14: SOURCE EMPTY | J14: =Controls!B25 -> 0 | K14: =IF(J14=1,"ACCEPTED","OPEN") -> OPEN
A15: ="PKT-"&B15&"-SAFETY" -> PKT-SUB-02-SAFETY | B15: ='Lot Register'!A8 -> SUB-02 | C15: ='Lot Register'!B8 -> Civil substrate | D15: ='Lot Register'!D8 -> MULTI | E15: ='Lot Register'!G8 -> ST-CT-CHA · ST-LF-REC · ST-RT-CON | F15: SAFETY | G15: worker, civil-rights, environmental, residual and safe-stop record | H15: Safety and rights authority | I15: SOURCE EMPTY | J15: =Controls!B25 -> 0 | K15: =IF(J15=1,"ACCEPTED","OPEN") -> OPEN
A16: ="PKT-"&B16&"-RECONSTRUCTION" -> PKT-SUB-02-RECONSTRUCTION | B16: ='Lot Register'!A8 -> SUB-02 | C16: ='Lot Register'!B8 -> Civil substrate | D16: ='Lot Register'!D8 -> MULTI | E16: ='Lot Register'!G8 -> ST-CT-CHA · ST-LF-REC · ST-RT-CON | F16: RECONSTRUCTION | G16: sealed custody, cold build description and outside-team replay | H16: Evidence Court | I16: SOURCE EMPTY | J16: =Controls!B25 -> 0 | K16: =IF(J16=1,"ACCEPTED","OPEN") -> OPEN
A17: ="PKT-"&B17&"-CONFIGURATION" -> PKT-SUB-03-CONFIGURATION | B17: ='Lot Register'!A9 -> SUB-03 | C17: ='Lot Register'!B9 -> Civil substrate | D17: ='Lot Register'!D9 -> MULTI | E17: ='Lot Register'!G9 -> ST-ET-CON · ST-HC-CHA · ST-HU-REC | F17: CONFIGURATION | G17: frozen requirement, materials, interfaces and as-built record | H17: Requirement issuer | I17: SOURCE EMPTY | J17: =Controls!B25 -> 0 | K17: =IF(J17=1,"ACCEPTED","OPEN") -> OPEN
A18: ="PKT-"&B18&"-CONTROL" -> PKT-SUB-03-CONTROL | B18: ='Lot Register'!A9 -> SUB-03 | C18: ='Lot Register'!B9 -> Civil substrate | D18: ='Lot Register'!D9 -> MULTI | E18: ='Lot Register'!G9 -> ST-ET-CON · ST-HC-CHA · ST-HU-REC | F18: CONTROL | G18: beneficial ownership, decisive ancestry, debt, tooling and key custody | H18: Control registrar | I18: SOURCE EMPTY | J18: =Controls!B25 -> 0 | K18: =IF(J18=1,"ACCEPTED","OPEN") -> OPEN
A19: ="PKT-"&B19&"-METROLOGY" -> PKT-SUB-03-METROLOGY | B19: ='Lot Register'!A9 -> SUB-03 | C19: ='Lot Register'!B9 -> Civil substrate | D19: ='Lot Register'!D9 -> MULTI | E19: ='Lot Register'!G9 -> ST-ET-CON · ST-HC-CHA · ST-HU-REC | F19: METROLOGY | G19: native commissioning, calibration chain and measurement uncertainty | H19: Commissioning authority | I19: SOURCE EMPTY | J19: =Controls!B25 -> 0 | K19: =IF(J19=1,"ACCEPTED","OPEN") -> OPEN
A20: ="PKT-"&B20&"-SAFETY" -> PKT-SUB-03-SAFETY | B20: ='Lot Register'!A9 -> SUB-03 | C20: ='Lot Register'!B9 -> Civil substrate | D20: ='Lot Register'!D9 -> MULTI | E20: ='Lot Register'!G9 -> ST-ET-CON · ST-HC-CHA · ST-HU-REC | F20: SAFETY | G20: worker, civil-rights, environmental, residual and safe-stop record | H20: Safety and rights authority | I20: SOURCE EMPTY | J20: =Controls!B25 -> 0 | K20: =IF(J20=1,"ACCEPTED","OPEN") -> OPEN
A21: ="PKT-"&B21&"-RECONSTRUCTION" -> PKT-SUB-03-RECONSTRUCTION | B21: ='Lot Register'!A9 -> SUB-03 | C21: ='Lot Register'!B9 -> Civil substrate | D21: ='Lot Register'!D9 -> MULTI | E21: ='Lot Register'!G9 -> ST-ET-CON · ST-HC-CHA · ST-HU-REC | F21: RECONSTRUCTION | G21: sealed custody, cold build description and outside-team replay | H21: Evidence Court | I21: SOURCE EMPTY | J21: =Controls!B25 -> 0 | K21: =IF(J21=1,"ACCEPTED","OPEN") -> OPEN
A22: ="PKT-"&B22&"-CONFIGURATION" -> PKT-SUB-04-CONFIGURATION | B22: ='Lot Register'!A10 -> SUB-04 | C22: ='Lot Register'!B10 -> Civil substrate | D22: ='Lot Register'!D10 -> MULTI | E22: ='Lot Register'!G10 -> ST-CT-CON · ST-LF-CHA · ST-RT-REC | F22: CONFIGURATION | G22: frozen requirement, materials, interfaces and as-built record | H22: Requirement issuer | I22: SOURCE EMPTY | J22: =Controls!B25 -> 0 | K22: =IF(J22=1,"ACCEPTED","OPEN") -> OPEN
A23: ="PKT-"&B23&"-CONTROL" -> PKT-SUB-04-CONTROL | B23: ='Lot Register'!A10 -> SUB-04 | C23: ='Lot Register'!B10 -> Civil substrate | D23: ='Lot Register'!D10 -> MULTI | E23: ='Lot Register'!G10 -> ST-CT-CON · ST-LF-CHA · ST-RT-REC | F23: CONTROL | G23: beneficial ownership, decisive ancestry, debt, tooling and key custody | H23: Control registrar | I23: SOURCE EMPTY | J23: =Controls!B25 -> 0 | K23: =IF(J23=1,"ACCEPTED","OPEN") -> OPEN
A24: ="PKT-"&B24&"-METROLOGY" -> PKT-SUB-04-METROLOGY | B24: ='Lot Register'!A10 -> SUB-04 | C24: ='Lot Register'!B10 -> Civil substrate | D24: ='Lot Register'!D10 -> MULTI | E24: ='Lot Register'!G10 -> ST-CT-CON · ST-LF-CHA · ST-RT-REC | F24: METROLOGY | G24: native commissioning, calibration chain and measurement uncertainty | H24: Commissioning authority | I24: SOURCE EMPTY | J24: =Controls!B25 -> 0 | K24: =IF(J24=1,"ACCEPTED","OPEN") -> OPEN
A25: ="PKT-"&B25&"-SAFETY" -> PKT-SUB-04-SAFETY | B25: ='Lot Register'!A10 -> SUB-04 | C25: ='Lot Register'!B10 -> Civil substrate | D25: ='Lot Register'!D10 -> MULTI | E25: ='Lot Register'!G10 -> ST-CT-CON · ST-LF-CHA · ST-RT-REC | F25: SAFETY | G25: worker, civil-rights, environmental, residual and safe-stop record | H25: Safety and rights authority | I25: SOURCE EMPTY | J25: =Controls!B25 -> 0 | K25: =IF(J25=1,"ACCEPTED","OPEN") -> OPEN
A26: ="PKT-"&B26&"-RECONSTRUCTION" -> PKT-SUB-04-RECONSTRUCTION | B26: ='Lot Register'!A10 -> SUB-04 | C26: ='Lot Register'!B10 -> Civil substrate | D26: ='Lot Register'!D10 -> MULTI | E26: ='Lot Register'!G10 -> ST-CT-CON · ST-LF-CHA · ST-RT-REC | F26: RECONSTRUCTION | G26: sealed custody, cold build description and outside-team replay | H26: Evidence Court | I26: SOURCE EMPTY | J26: =Controls!B25 -> 0 | K26: =IF(J26=1,"ACCEPTED","OPEN") -> OPEN
A27: ="PKT-"&B27&"-CONFIGURATION" -> PKT-SUB-05-CONFIGURATION | B27: ='Lot Register'!A11 -> SUB-05 | C27: ='Lot Register'!B11 -> Civil substrate | D27: ='Lot Register'!D11 -> MULTI | E27: ='Lot Register'!G11 -> ST-ET-REC · ST-HC-CON · ST-HU-CHA | F27: CONFIGURATION | G27: frozen requirement, materials, interfaces and as-built record | H27: Requirement issuer | I27: SOURCE EMPTY | J27: =Controls!B25 -> 0 | K27: =IF(J27=1,"ACCEPTED","OPEN") -> OPEN
A28: ="PKT-"&B28&"-CONTROL" -> PKT-SUB-05-CONTROL | B28: ='Lot Register'!A11 -> SUB-05 | C28: ='Lot Register'!B11 -> Civil substrate | D28: ='Lot Register'!D11 -> MULTI | E28: ='Lot Register'!G11 -> ST-ET-REC · ST-HC-CON · ST-HU-CHA | F28: CONTROL | G28: beneficial ownership, decisive ancestry, debt, tooling and key custody | H28: Control registrar | I28: SOURCE EMPTY | J28: =Controls!B25 -> 0 | K28: =IF(J28=1,"ACCEPTED","OPEN") -> OPEN
A29: ="PKT-"&B29&"-METROLOGY" -> PKT-SUB-05-METROLOGY | B29: ='Lot Register'!A11 -> SUB-05 | C29: ='Lot Register'!B11 -> Civil substrate | D29: ='Lot Register'!D11 -> MULTI | E29: ='Lot Register'!G11 -> ST-ET-REC · ST-HC-CON · ST-HU-CHA | F29: METROLOGY | G29: native commissioning, calibration chain and measurement uncertainty | H29: Commissioning authority | I29: SOURCE EMPTY | J29: =Controls!B25 -> 0 | K29: =IF(J29=1,"ACCEPTED","OPEN") -> OPEN
A30: ="PKT-"&B30&"-SAFETY" -> PKT-SUB-05-SAFETY | B30: ='Lot Register'!A11 -> SUB-05 | C30: ='Lot Register'!B11 -> Civil substrate | D30: ='Lot Register'!D11 -> MULTI | E30: ='Lot Register'!G11 -> ST-ET-REC · ST-HC-CON · ST-HU-CHA | F30: SAFETY | G30: worker, civil-rights, environmental, residual and safe-stop record | H30: Safety and rights authority | I30: SOURCE EMPTY | J30: =Controls!B25 -> 0 | K30: =IF(J30=1,"ACCEPTED","OPEN") -> OPEN
A31: ="PKT-"&B31&"-RECONSTRUCTION" -> PKT-SUB-05-RECONSTRUCTION | B31: ='Lot Register'!A11 -> SUB-05 | C31: ='Lot Register'!B11 -> Civil substrate | D31: ='Lot Register'!D11 -> MULTI | E31: ='Lot Register'!G11 -> ST-ET-REC · ST-HC-CON · ST-HU-CHA | F31: RECONSTRUCTION | G31: sealed custody, cold build description and outside-team replay | H31: Evidence Court | I31: SOURCE EMPTY | J31: =Controls!B25 -> 0 | K31: =IF(J31=1,"ACCEPTED","OPEN") -> OPEN
A32: ="PKT-"&B32&"-CONFIGURATION" -> PKT-SUB-06-CONFIGURATION | B32: ='Lot Register'!A12 -> SUB-06 | C32: ='Lot Register'!B12 -> Civil substrate | D32: ='Lot Register'!D12 -> MULTI | E32: ='Lot Register'!G12 -> ST-CT-REC · ST-LF-CON · ST-RT-CHA | F32: CONFIGURATION | G32: frozen requirement, materials, interfaces and as-built record | H32: Requirement issuer | I32: SOURCE EMPTY | J32: =Controls!B25 -> 0 | K32: =IF(J32=1,"ACCEPTED","OPEN") -> OPEN
A33: ="PKT-"&B33&"-CONTROL" -> PKT-SUB-06-CONTROL | B33: ='Lot Register'!A12 -> SUB-06 | C33: ='Lot Register'!B12 -> Civil substrate | D33: ='Lot Register'!D12 -> MULTI | E33: ='Lot Register'!G12 -> ST-CT-REC · ST-LF-CON · ST-RT-CHA | F33: CONTROL | G33: beneficial ownership, decisive ancestry, debt, tooling and key custody | H33: Control registrar | I33: SOURCE EMPTY | J33: =Controls!B25 -> 0 | K33: =IF(J33=1,"ACCEPTED","OPEN") -> OPEN
A34: ="PKT-"&B34&"-METROLOGY" -> PKT-SUB-06-METROLOGY | B34: ='Lot Register'!A12 -> SUB-06 | C34: ='Lot Register'!B12 -> Civil substrate | D34: ='Lot Register'!D12 -> MULTI | E34: ='Lot Register'!G12 -> ST-CT-REC · ST-LF-CON · ST-RT-CHA | F34: METROLOGY | G34: native commissioning, calibration chain and measurement uncertainty | H34: Commissioning authority | I34: SOURCE EMPTY | J34: =Controls!B25 -> 0 | K34: =IF(J34=1,"ACCEPTED","OPEN") -> OPEN
A35: ="PKT-"&B35&"-SAFETY" -> PKT-SUB-06-SAFETY | B35: ='Lot Register'!A12 -> SUB-06 | C35: ='Lot Register'!B12 -> Civil substrate | D35: ='Lot Register'!D12 -> MULTI | E35: ='Lot Register'!G12 -> ST-CT-REC · ST-LF-CON · ST-RT-CHA | F35: SAFETY | G35: worker, civil-rights, environmental, residual and safe-stop record | H35: Safety and rights authority | I35: SOURCE EMPTY | J35: =Controls!B25 -> 0 | K35: =IF(J35=1,"ACCEPTED","OPEN") -> OPEN
A36: ="PKT-"&B36&"-RECONSTRUCTION" -> PKT-SUB-06-RECONSTRUCTION | B36: ='Lot Register'!A12 -> SUB-06 | C36: ='Lot Register'!B12 -> Civil substrate | D36: ='Lot Register'!D12 -> MULTI | E36: ='Lot Register'!G12 -> ST-CT-REC · ST-LF-CON · ST-RT-CHA | F36: RECONSTRUCTION | G36: sealed custody, cold build description and outside-team replay | H36: Evidence Court | I36: SOURCE EMPTY | J36: =Controls!B25 -> 0 | K36: =IF(J36=1,"ACCEPTED","OPEN") -> OPEN
A37: ="PKT-"&B37&"-CONFIGURATION" -> PKT-RIG-ET-CHA-CONFIGURATION | B37: ='Lot Register'!A13 -> RIG-ET-CHA | C37: ='Lot Register'!B13 -> Root-native rig | D37: ='Lot Register'!D13 -> MS-ET | E37: ='Lot Register'!G13 -> ST-ET-CHA | F37: CONFIGURATION | G37: frozen requirement, materials, interfaces and as-built record | H37: Requirement issuer | I37: SOURCE EMPTY | J37: =Controls!B25 -> 0 | K37: =IF(J37=1,"ACCEPTED","OPEN") -> OPEN
A38: ="PKT-"&B38&"-CONTROL" -> PKT-RIG-ET-CHA-CONTROL | B38: ='Lot Register'!A13 -> RIG-ET-CHA | C38: ='Lot Register'!B13 -> Root-native rig | D38: ='Lot Register'!D13 -> MS-ET | E38: ='Lot Register'!G13 -> ST-ET-CHA | F38: CONTROL | G38: beneficial ownership, decisive ancestry, debt, tooling and key custody | H38: Control registrar | I38: SOURCE EMPTY | J38: =Controls!B25 -> 0 | K38: =IF(J38=1,"ACCEPTED","OPEN") -> OPEN
A39: ="PKT-"&B39&"-METROLOGY" -> PKT-RIG-ET-CHA-METROLOGY | B39: ='Lot Register'!A13 -> RIG-ET-CHA | C39: ='Lot Register'!B13 -> Root-native rig | D39: ='Lot Register'!D13 -> MS-ET | E39: ='Lot Register'!G13 -> ST-ET-CHA | F39: METROLOGY | G39: native commissioning, calibration chain and measurement uncertainty | H39: Commissioning authority | I39: SOURCE EMPTY | J39: =Controls!B25 -> 0 | K39: =IF(J39=1,"ACCEPTED","OPEN") -> OPEN
A40: ="PKT-"&B40&"-SAFETY" -> PKT-RIG-ET-CHA-SAFETY | B40: ='Lot Register'!A13 -> RIG-ET-CHA | C40: ='Lot Register'!B13 -> Root-native rig | D40: ='Lot Register'!D13 -> MS-ET | E40: ='Lot Register'!G13 -> ST-ET-CHA | F40: SAFETY | G40: worker, civil-rights, environmental, residual and safe-stop record | H40: Safety and rights authority | I40: SOURCE EMPTY | J40: =Controls!B25 -> 0 | K40: =IF(J40=1,"ACCEPTED","OPEN") -> OPEN
A41: ="PKT-"&B41&"-RECONSTRUCTION" -> PKT-RIG-ET-CHA-RECONSTRUCTION | B41: ='Lot Register'!A13 -> RIG-ET-CHA | C41: ='Lot Register'!B13 -> Root-native rig | D41: ='Lot Register'!D13 -> MS-ET | E41: ='Lot Register'!G13 -> ST-ET-CHA | F41: RECONSTRUCTION | G41: sealed custody, cold build description and outside-team replay | H41: Evidence Court | I41: SOURCE EMPTY | J41: =Controls!B25 -> 0 | K41: =IF(J41=1,"ACCEPTED","OPEN") -> OPEN
A42: ="PKT-"&B42&"-CONFIGURATION" -> PKT-MTH-ET-CHA-L1-CONFIGURATION | B42: ='Lot Register'!A14 -> MTH-ET-CHA-L1 | C42: ='Lot Register'!B14 -> Method lineage | D42: ='Lot Register'!D14 -> MS-ET | E42: ='Lot Register'!G14 -> ST-ET-CHA | F42: CONFIGURATION | G42: frozen requirement, materials, interfaces and as-built record | H42: Requirement issuer | I42: SOURCE EMPTY | J42: =Controls!B25 -> 0 | K42: =IF(J42=1,"ACCEPTED","OPEN") -> OPEN
A43: ="PKT-"&B43&"-CONTROL" -> PKT-MTH-ET-CHA-L1-CONTROL | B43: ='Lot Register'!A14 -> MTH-ET-CHA-L1 | C43: ='Lot Register'!B14 -> Method lineage | D43: ='Lot Register'!D14 -> MS-ET | E43: ='Lot Register'!G14 -> ST-ET-CHA | F43: CONTROL | G43: beneficial ownership, decisive ancestry, debt, tooling and key custody | H43: Control registrar | I43: SOURCE EMPTY | J43: =Controls!B25 -> 0 | K43: =IF(J43=1,"ACCEPTED","OPEN") -> OPEN
A44: ="PKT-"&B44&"-METROLOGY" -> PKT-MTH-ET-CHA-L1-METROLOGY | B44: ='Lot Register'!A14 -> MTH-ET-CHA-L1 | C44: ='Lot Register'!B14 -> Method lineage | D44: ='Lot Register'!D14 -> MS-ET | E44: ='Lot Register'!G14 -> ST-ET-CHA | F44: METROLOGY | G44: native commissioning, calibration chain and measurement uncertainty | H44: Commissioning authority | I44: SOURCE EMPTY | J44: =Controls!B25 -> 0 | K44: =IF(J44=1,"ACCEPTED","OPEN") -> OPEN
A45: ="PKT-"&B45&"-SAFETY" -> PKT-MTH-ET-CHA-L1-SAFETY | B45: ='Lot Register'!A14 -> MTH-ET-CHA-L1 | C45: ='Lot Register'!B14 -> Method lineage | D45: ='Lot Register'!D14 -> MS-ET | E45: ='Lot Register'!G14 -> ST-ET-CHA | F45: SAFETY | G45: worker, civil-rights, environmental, residual and safe-stop record | H45: Safety and rights authority | I45: SOURCE EMPTY | J45: =Controls!B25 -> 0 | K45: =IF(J45=1,"ACCEPTED","OPEN") -> OPEN
A46: ="PKT-"&B46&"-RECONSTRUCTION" -> PKT-MTH-ET-CHA-L1-RECONSTRUCTION | B46: ='Lot Register'!A14 -> MTH-ET-CHA-L1 | C46: ='Lot Register'!B14 -> Method lineage | D46: ='Lot Register'!D14 -> MS-ET | E46: ='Lot Register'!G14 -> ST-ET-CHA | F46: RECONSTRUCTION | G46: sealed custody, cold build description and outside-team replay | H46: Evidence Court | I46: SOURCE EMPTY | J46: =Controls!B25 -> 0 | K46: =IF(J46=1,"ACCEPTED","OPEN") -> OPEN
A47: ="PKT-"&B47&"-CONFIGURATION" -> PKT-MTH-ET-CHA-L2-CONFIGURATION | B47: ='Lot Register'!A15 -> MTH-ET-CHA-L2 | C47: ='Lot Register'!B15 -> Method lineage | D47: ='Lot Register'!D15 -> MS-ET | E47: ='Lot Register'!G15 -> ST-ET-CHA | F47: CONFIGURATION | G47: frozen requirement, materials, interfaces and as-built record | H47: Requirement issuer | I47: SOURCE EMPTY | J47: =Controls!B25 -> 0 | K47: =IF(J47=1,"ACCEPTED","OPEN") -> OPEN
A48: ="PKT-"&B48&"-CONTROL" -> PKT-MTH-ET-CHA-L2-CONTROL | B48: ='Lot Register'!A15 -> MTH-ET-CHA-L2 | C48: ='Lot Register'!B15 -> Method lineage | D48: ='Lot Register'!D15 -> MS-ET | E48: ='Lot Register'!G15 -> ST-ET-CHA | F48: CONTROL | G48: beneficial ownership, decisive ancestry, debt, tooling and key custody | H48: Control registrar | I48: SOURCE EMPTY | J48: =Controls!B25 -> 0 | K48: =IF(J48=1,"ACCEPTED","OPEN") -> OPEN
A49: ="PKT-"&B49&"-METROLOGY" -> PKT-MTH-ET-CHA-L2-METROLOGY | B49: ='Lot Register'!A15 -> MTH-ET-CHA-L2 | C49: ='Lot Register'!B15 -> Method lineage | D49: ='Lot Register'!D15 -> MS-ET | E49: ='Lot Register'!G15 -> ST-ET-CHA | F49: METROLOGY | G49: native commissioning, calibration chain and measurement uncertainty | H49: Commissioning authority | I49: SOURCE EMPTY | J49: =Controls!B25 -> 0 | K49: =IF(J49=1,"ACCEPTED","OPEN") -> OPEN
A50: ="PKT-"&B50&"-SAFETY" -> PKT-MTH-ET-CHA-L2-SAFETY | B50: ='Lot Register'!A15 -> MTH-ET-CHA-L2 | C50: ='Lot Register'!B15 -> Method lineage | D50: ='Lot Register'!D15 -> MS-ET | E50: ='Lot Register'!G15 -> ST-ET-CHA | F50: SAFETY | G50: worker, civil-rights, environmental, residual and safe-stop record | H50: Safety and rights authority | I50: SOURCE EMPTY | J50: =Controls!B25 -> 0 | K50: =IF(J50=1,"ACCEPTED","OPEN") -> OPEN
A51: ="PKT-"&B51&"-RECONSTRUCTION" -> PKT-MTH-ET-CHA-L2-RECONSTRUCTION | B51: ='Lot Register'!A15 -> MTH-ET-CHA-L2 | C51: ='Lot Register'!B15 -> Method lineage | D51: ='Lot Register'!D15 -> MS-ET | E51: ='Lot Register'!G15 -> ST-ET-CHA | F51: RECONSTRUCTION | G51: sealed custody, cold build description and outside-team replay | H51: Evidence Court | I51: SOURCE EMPTY | J51: =Controls!B25 -> 0 | K51: =IF(J51=1,"ACCEPTED","OPEN") -> OPEN
A52: ="PKT-"&B52&"-CONFIGURATION" -> PKT-REG-ET-CHA-CONFIGURATION | B52: ='Lot Register'!A16 -> REG-ET-CHA | C52: ='Lot Register'!B16 -> Regeneration tool | D52: ='Lot Register'!D16 -> MS-ET | E52: ='Lot Register'!G16 -> ST-ET-CHA | F52: CONFIGURATION | G52: frozen requirement, materials, interfaces and as-built record | H52: Requirement issuer | I52: SOURCE EMPTY | J52: =Controls!B25 -> 0 | K52: =IF(J52=1,"ACCEPTED","OPEN") -> OPEN
A53: ="PKT-"&B53&"-CONTROL" -> PKT-REG-ET-CHA-CONTROL | B53: ='Lot Register'!A16 -> REG-ET-CHA | C53: ='Lot Register'!B16 -> Regeneration tool | D53: ='Lot Register'!D16 -> MS-ET | E53: ='Lot Register'!G16 -> ST-ET-CHA | F53: CONTROL | G53: beneficial ownership, decisive ancestry, debt, tooling and key custody | H53: Control registrar | I53: SOURCE EMPTY | J53: =Controls!B25 -> 0 | K53: =IF(J53=1,"ACCEPTED","OPEN") -> OPEN
A54: ="PKT-"&B54&"-METROLOGY" -> PKT-REG-ET-CHA-METROLOGY | B54: ='Lot Register'!A16 -> REG-ET-CHA | C54: ='Lot Register'!B16 -> Regeneration tool | D54: ='Lot Register'!D16 -> MS-ET | E54: ='Lot Register'!G16 -> ST-ET-CHA | F54: METROLOGY | G54: native commissioning, calibration chain and measurement uncertainty | H54: Commissioning authority | I54: SOURCE EMPTY | J54: =Controls!B25 -> 0 | K54: =IF(J54=1,"ACCEPTED","OPEN") -> OPEN
A55: ="PKT-"&B55&"-SAFETY" -> PKT-REG-ET-CHA-SAFETY | B55: ='Lot Register'!A16 -> REG-ET-CHA | C55: ='Lot Register'!B16 -> Regeneration tool | D55: ='Lot Register'!D16 -> MS-ET | E55: ='Lot Register'!G16 -> ST-ET-CHA | F55: SAFETY | G55: worker, civil-rights, environmental, residual and safe-stop record | H55: Safety and rights authority | I55: SOURCE EMPTY | J55: =Controls!B25 -> 0 | K55: =IF(J55=1,"ACCEPTED","OPEN") -> OPEN
A56: ="PKT-"&B56&"-RECONSTRUCTION" -> PKT-REG-ET-CHA-RECONSTRUCTION | B56: ='Lot Register'!A16 -> REG-ET-CHA | C56: ='Lot Register'!B16 -> Regeneration tool | D56: ='Lot Register'!D16 -> MS-ET | E56: ='Lot Register'!G16 -> ST-ET-CHA | F56: RECONSTRUCTION | G56: sealed custody, cold build description and outside-team replay | H56: Evidence Court | I56: SOURCE EMPTY | J56: =Controls!B25 -> 0 | K56: =IF(J56=1,"ACCEPTED","OPEN") -> OPEN
A57: ="PKT-"&B57&"-CONFIGURATION" -> PKT-INT-ET-CHA-CONFIGURATION | B57: ='Lot Register'!A17 -> INT-ET-CHA | C57: ='Lot Register'!B17 -> Station integration | D57: ='Lot Register'!D17 -> MS-ET | E57: ='Lot Register'!G17 -> ST-ET-CHA | F57: CONFIGURATION | G57: frozen requirement, materials, interfaces and as-built record | H57: Requirement issuer | I57: SOURCE EMPTY | J57: =Controls!B25 -> 0 | K57: =IF(J57=1,"ACCEPTED","OPEN") -> OPEN
A58: ="PKT-"&B58&"-CONTROL" -> PKT-INT-ET-CHA-CONTROL | B58: ='Lot Register'!A17 -> INT-ET-CHA | C58: ='Lot Register'!B17 -> Station integration | D58: ='Lot Register'!D17 -> MS-ET | E58: ='Lot Register'!G17 -> ST-ET-CHA | F58: CONTROL | G58: beneficial ownership, decisive ancestry, debt, tooling and key custody | H58: Control registrar | I58: SOURCE EMPTY | J58: =Controls!B25 -> 0 | K58: =IF(J58=1,"ACCEPTED","OPEN") -> OPEN
A59: ="PKT-"&B59&"-METROLOGY" -> PKT-INT-ET-CHA-METROLOGY | B59: ='Lot Register'!A17 -> INT-ET-CHA | C59: ='Lot Register'!B17 -> Station integration | D59: ='Lot Register'!D17 -> MS-ET | E59: ='Lot Register'!G17 -> ST-ET-CHA | F59: METROLOGY | G59: native commissioning, calibration chain and measurement uncertainty | H59: Commissioning authority | I59: SOURCE EMPTY | J59: =Controls!B25 -> 0 | K59: =IF(J59=1,"ACCEPTED","OPEN") -> OPEN
A60: ="PKT-"&B60&"-SAFETY" -> PKT-INT-ET-CHA-SAFETY | B60: ='Lot Register'!A17 -> INT-ET-CHA | C60: ='Lot Register'!B17 -> Station integration | D60: ='Lot Register'!D17 -> MS-ET | E60: ='Lot Register'!G17 -> ST-ET-CHA | F60: SAFETY | G60: worker, civil-rights, environmental, residual and safe-stop record | H60: Safety and rights authority | I60: SOURCE EMPTY | J60: =Controls!B25 -> 0 | K60: =IF(J60=1,"ACCEPTED","OPEN") -> OPEN
A61: ="PKT-"&B61&"-RECONSTRUCTION" -> PKT-INT-ET-CHA-RECONSTRUCTION | B61: ='Lot Register'!A17 -> INT-ET-CHA | C61: ='Lot Register'!B17 -> Station integration | D61: ='Lot Register'!D17 -> MS-ET | E61: ='Lot Register'!G17 -> ST-ET-CHA | F61: RECONSTRUCTION | G61: sealed custody, cold build description and outside-team replay | H61: Evidence Court | I61: SOURCE EMPTY | J61: =Controls!B25 -> 0 | K61: =IF(J61=1,"ACCEPTED","OPEN") -> OPEN
A62: ="PKT-"&B62&"-CONFIGURATION" -> PKT-RIG-ET-CON-CONFIGURATION | B62: ='Lot Register'!A18 -> RIG-ET-CON | C62: ='Lot Register'!B18 -> Root-native rig | D62: ='Lot Register'!D18 -> MS-ET | E62: ='Lot Register'!G18 -> ST-ET-CON | F62: CONFIGURATION | G62: frozen requirement, materials, interfaces and as-built record | H62: Requirement issuer | I62: SOURCE EMPTY | J62: =Controls!B25 -> 0 | K62: =IF(J62=1,"ACCEPTED","OPEN") -> OPEN
A63: ="PKT-"&B63&"-CONTROL" -> PKT-RIG-ET-CON-CONTROL | B63: ='Lot Register'!A18 -> RIG-ET-CON | C63: ='Lot Register'!B18 -> Root-native rig | D63: ='Lot Register'!D18 -> MS-ET | E63: ='Lot Register'!G18 -> ST-ET-CON | F63: CONTROL | G63: beneficial ownership, decisive ancestry, debt, tooling and key custody | H63: Control registrar | I63: SOURCE EMPTY | J63: =Controls!B25 -> 0 | K63: =IF(J63=1,"ACCEPTED","OPEN") -> OPEN
A64: ="PKT-"&B64&"-METROLOGY" -> PKT-RIG-ET-CON-METROLOGY | B64: ='Lot Register'!A18 -> RIG-ET-CON | C64: ='Lot Register'!B18 -> Root-native rig | D64: ='Lot Register'!D18 -> MS-ET | E64: ='Lot Register'!G18 -> ST-ET-CON | F64: METROLOGY | G64: native commissioning, calibration chain and measurement uncertainty | H64: Commissioning authority | I64: SOURCE EMPTY | J64: =Controls!B25 -> 0 | K64: =IF(J64=1,"ACCEPTED","OPEN") -> OPEN
A65: ="PKT-"&B65&"-SAFETY" -> PKT-RIG-ET-CON-SAFETY | B65: ='Lot Register'!A18 -> RIG-ET-CON | C65: ='Lot Register'!B18 -> Root-native rig | D65: ='Lot Register'!D18 -> MS-ET | E65: ='Lot Register'!G18 -> ST-ET-CON | F65: SAFETY | G65: worker, civil-rights, environmental, residual and safe-stop record | H65: Safety and rights authority | I65: SOURCE EMPTY | J65: =Controls!B25 -> 0 | K65: =IF(J65=1,"ACCEPTED","OPEN") -> OPEN
A66: ="PKT-"&B66&"-RECONSTRUCTION" -> PKT-RIG-ET-CON-RECONSTRUCTION | B66: ='Lot Register'!A18 -> RIG-ET-CON | C66: ='Lot Register'!B18 -> Root-native rig | D66: ='Lot Register'!D18 -> MS-ET | E66: ='Lot Register'!G18 -> ST-ET-CON | F66: RECONSTRUCTION | G66: sealed custody, cold build description and outside-team replay | H66: Evidence Court | I66: SOURCE EMPTY | J66: =Controls!B25 -> 0 | K66: =IF(J66=1,"ACCEPTED","OPEN") -> OPEN
A67: ="PKT-"&B67&"-CONFIGURATION" -> PKT-MTH-ET-CON-L1-CONFIGURATION | B67: ='Lot Register'!A19 -> MTH-ET-CON-L1 | C67: ='Lot Register'!B19 -> Method lineage | D67: ='Lot Register'!D19 -> MS-ET | E67: ='Lot Register'!G19 -> ST-ET-CON | F67: CONFIGURATION | G67: frozen requirement, materials, interfaces and as-built record | H67: Requirement issuer | I67: SOURCE EMPTY | J67: =Controls!B25 -> 0 | K67: =IF(J67=1,"ACCEPTED","OPEN") -> OPEN
A68: ="PKT-"&B68&"-CONTROL" -> PKT-MTH-ET-CON-L1-CONTROL | B68: ='Lot Register'!A19 -> MTH-ET-CON-L1 | C68: ='Lot Register'!B19 -> Method lineage | D68: ='Lot Register'!D19 -> MS-ET | E68: ='Lot Register'!G19 -> ST-ET-CON | F68: CONTROL | G68: beneficial ownership, decisive ancestry, debt, tooling and key custody | H68: Control registrar | I68: SOURCE EMPTY | J68: =Controls!B25 -> 0 | K68: =IF(J68=1,"ACCEPTED","OPEN") -> OPEN
A69: ="PKT-"&B69&"-METROLOGY" -> PKT-MTH-ET-CON-L1-METROLOGY | B69: ='Lot Register'!A19 -> MTH-ET-CON-L1 | C69: ='Lot Register'!B19 -> Method lineage | D69: ='Lot Register'!D19 -> MS-ET | E69: ='Lot Register'!G19 -> ST-ET-CON | F69: METROLOGY | G69: native commissioning, calibration chain and measurement uncertainty | H69: Commissioning authority | I69: SOURCE EMPTY | J69: =Controls!B25 -> 0 | K69: =IF(J69=1,"ACCEPTED","OPEN") -> OPEN
A70: ="PKT-"&B70&"-SAFETY" -> PKT-MTH-ET-CON-L1-SAFETY | B70: ='Lot Register'!A19 -> MTH-ET-CON-L1 | C70: ='Lot Register'!B19 -> Method lineage | D70: ='Lot Register'!D19 -> MS-ET | E70: ='Lot Register'!G19 -> ST-ET-CON | F70: SAFETY | G70: worker, civil-rights, environmental, residual and safe-stop record | H70: Safety and rights authority | I70: SOURCE EMPTY | J70: =Controls!B25 -> 0 | K70: =IF(J70=1,"ACCEPTED","OPEN") -> OPEN
A71: ="PKT-"&B71&"-RECONSTRUCTION" -> PKT-MTH-ET-CON-L1-RECONSTRUCTION | B71: ='Lot Register'!A19 -> MTH-ET-CON-L1 | C71: ='Lot Register'!B19 -> Method lineage | D71: ='Lot Register'!D19 -> MS-ET | E71: ='Lot Register'!G19 -> ST-ET-CON | F71: RECONSTRUCTION | G71: sealed custody, cold build description and outside-team replay | H71: Evidence Court | I71: SOURCE EMPTY | J71: =Controls!B25 -> 0 | K71: =IF(J71=1,"ACCEPTED","OPEN") -> OPEN
A72: ="PKT-"&B72&"-CONFIGURATION" -> PKT-MTH-ET-CON-L2-CONFIGURATION | B72: ='Lot Register'!A20 -> MTH-ET-CON-L2 | C72: ='Lot Register'!B20 -> Method lineage | D72: ='Lot Register'!D20 -> MS-ET | E72: ='Lot Register'!G20 -> ST-ET-CON | F72: CONFIGURATION | G72: frozen requirement, materials, interfaces and as-built record | H72: Requirement issuer | I72: SOURCE EMPTY | J72: =Controls!B25 -> 0 | K72: =IF(J72=1,"ACCEPTED","OPEN") -> OPEN
A73: ="PKT-"&B73&"-CONTROL" -> PKT-MTH-ET-CON-L2-CONTROL | B73: ='Lot Register'!A20 -> MTH-ET-CON-L2 | C73: ='Lot Register'!B20 -> Method lineage | D73: ='Lot Register'!D20 -> MS-ET | E73: ='Lot Register'!G20 -> ST-ET-CON | F73: CONTROL | G73: beneficial ownership, decisive ancestry, debt, tooling and key custody | H73: Control registrar | I73: SOURCE EMPTY | J73: =Controls!B25 -> 0 | K73: =IF(J73=1,"ACCEPTED","OPEN") -> OPEN
A74: ="PKT-"&B74&"-METROLOGY" -> PKT-MTH-ET-CON-L2-METROLOGY | B74: ='Lot Register'!A20 -> MTH-ET-CON-L2 | C74: ='Lot Register'!B20 -> Method lineage | D74: ='Lot Register'!D20 -> MS-ET | E74: ='Lot Register'!G20 -> ST-ET-CON | F74: METROLOGY | G74: native commissioning, calibration chain and measurement uncertainty | H74: Commissioning authority | I74: SOURCE EMPTY | J74: =Controls!B25 -> 0 | K74: =IF(J74=1,"ACCEPTED","OPEN") -> OPEN
A75: ="PKT-"&B75&"-SAFETY" -> PKT-MTH-ET-CON-L2-SAFETY | B75: ='Lot Register'!A20 -> MTH-ET-CON-L2 | C75: ='Lot Register'!B20 -> Method lineage | D75: ='Lot Register'!D20 -> MS-ET | E75: ='Lot Register'!G20 -> ST-ET-CON | F75: SAFETY | G75: worker, civil-rights, environmental, residual and safe-stop record | H75: Safety and rights authority | I75: SOURCE EMPTY | J75: =Controls!B25 -> 0 | K75: =IF(J75=1,"ACCEPTED","OPEN") -> OPEN
A76: ="PKT-"&B76&"-RECONSTRUCTION" -> PKT-MTH-ET-CON-L2-RECONSTRUCTION | B76: ='Lot Register'!A20 -> MTH-ET-CON-L2 | C76: ='Lot Register'!B20 -> Method lineage | D76: ='Lot Register'!D20 -> MS-ET | E76: ='Lot Register'!G20 -> ST-ET-CON | F76: RECONSTRUCTION | G76: sealed custody, cold build description and outside-team replay | H76: Evidence Court | I76: SOURCE EMPTY | J76: =Controls!B25 -> 0 | K76: =IF(J76=1,"ACCEPTED","OPEN") -> OPEN
A77: ="PKT-"&B77&"-CONFIGURATION" -> PKT-REG-ET-CON-CONFIGURATION | B77: ='Lot Register'!A21 -> REG-ET-CON | C77: ='Lot Register'!B21 -> Regeneration tool | D77: ='Lot Register'!D21 -> MS-ET | E77: ='Lot Register'!G21 -> ST-ET-CON | F77: CONFIGURATION | G77: frozen requirement, materials, interfaces and as-built record | H77: Requirement issuer | I77: SOURCE EMPTY | J77: =Controls!B25 -> 0 | K77: =IF(J77=1,"ACCEPTED","OPEN") -> OPEN
A78: ="PKT-"&B78&"-CONTROL" -> PKT-REG-ET-CON-CONTROL | B78: ='Lot Register'!A21 -> REG-ET-CON | C78: ='Lot Register'!B21 -> Regeneration tool | D78: ='Lot Register'!D21 -> MS-ET | E78: ='Lot Register'!G21 -> ST-ET-CON | F78: CONTROL | G78: beneficial ownership, decisive ancestry, debt, tooling and key custody | H78: Control registrar | I78: SOURCE EMPTY | J78: =Controls!B25 -> 0 | K78: =IF(J78=1,"ACCEPTED","OPEN") -> OPEN
A79: ="PKT-"&B79&"-METROLOGY" -> PKT-REG-ET-CON-METROLOGY | B79: ='Lot Register'!A21 -> REG-ET-CON | C79: ='Lot Register'!B21 -> Regeneration tool | D79: ='Lot Register'!D21 -> MS-ET | E79: ='Lot Register'!G21 -> ST-ET-CON | F79: METROLOGY | G79: native commissioning, calibration chain and measurement uncertainty | H79: Commissioning authority | I79: SOURCE EMPTY | J79: =Controls!B25 -> 0 | K79: =IF(J79=1,"ACCEPTED","OPEN") -> OPEN
A80: ="PKT-"&B80&"-SAFETY" -> PKT-REG-ET-CON-SAFETY | B80: ='Lot Register'!A21 -> REG-ET-CON | C80: ='Lot Register'!B21 -> Regeneration tool | D80: ='Lot Register'!D21 -> MS-ET | E80: ='Lot Register'!G21 -> ST-ET-CON | F80: SAFETY | G80: worker, civil-rights, environmental, residual and safe-stop record | H80: Safety and rights authority | I80: SOURCE EMPTY | J80: =Controls!B25 -> 0 | K80: =IF(J80=1,"ACCEPTED","OPEN") -> OPEN
A81: ="PKT-"&B81&"-RECONSTRUCTION" -> PKT-REG-ET-CON-RECONSTRUCTION | B81: ='Lot Register'!A21 -> REG-ET-CON | C81: ='Lot Register'!B21 -> Regeneration tool | D81: ='Lot Register'!D21 -> MS-ET | E81: ='Lot Register'!G21 -> ST-ET-CON | F81: RECONSTRUCTION | G81: sealed custody, cold build description and outside-team replay | H81: Evidence Court | I81: SOURCE EMPTY | J81: =Controls!B25 -> 0 | K81: =IF(J81=1,"ACCEPTED","OPEN") -> OPEN
A82: ="PKT-"&B82&"-CONFIGURATION" -> PKT-INT-ET-CON-CONFIGURATION | B82: ='Lot Register'!A22 -> INT-ET-CON | C82: ='Lot Register'!B22 -> Station integration | D82: ='Lot Register'!D22 -> MS-ET | E82: ='Lot Register'!G22 -> ST-ET-CON | F82: CONFIGURATION | G82: frozen requirement, materials, interfaces and as-built record | H82: Requirement issuer | I82: SOURCE EMPTY | J82: =Controls!B25 -> 0 | K82: =IF(J82=1,"ACCEPTED","OPEN") -> OPEN
A83: ="PKT-"&B83&"-CONTROL" -> PKT-INT-ET-CON-CONTROL | B83: ='Lot Register'!A22 -> INT-ET-CON | C83: ='Lot Register'!B22 -> Station integration | D83: ='Lot Register'!D22 -> MS-ET | E83: ='Lot Register'!G22 -> ST-ET-CON | F83: CONTROL | G83: beneficial ownership, decisive ancestry, debt, tooling and key custody | H83: Control registrar | I83: SOURCE EMPTY | J83: =Controls!B25 -> 0 | K83: =IF(J83=1,"ACCEPTED","OPEN") -> OPEN
A84: ="PKT-"&B84&"-METROLOGY" -> PKT-INT-ET-CON-METROLOGY | B84: ='Lot Register'!A22 -> INT-ET-CON | C84: ='Lot Register'!B22 -> Station integration | D84: ='Lot Register'!D22 -> MS-ET | E84: ='Lot Register'!G22 -> ST-ET-CON | F84: METROLOGY | G84: native commissioning, calibration chain and measurement uncertainty | H84: Commissioning authority | I84: SOURCE EMPTY | J84: =Controls!B25 -> 0 | K84: =IF(J84=1,"ACCEPTED","OPEN") -> OPEN
A85: ="PKT-"&B85&"-SAFETY" -> PKT-INT-ET-CON-SAFETY | B85: ='Lot Register'!A22 -> INT-ET-CON | C85: ='Lot Register'!B22 -> Station integration | D85: ='Lot Register'!D22 -> MS-ET | E85: ='Lot Register'!G22 -> ST-ET-CON | F85: SAFETY | G85: worker, civil-rights, environmental, residual and safe-stop record | H85: Safety and rights authority | I85: SOURCE EMPTY | J85: =Controls!B25 -> 0 | K85: =IF(J85=1,"ACCEPTED","OPEN") -> OPEN
A86: ="PKT-"&B86&"-RECONSTRUCTION" -> PKT-INT-ET-CON-RECONSTRUCTION | B86: ='Lot Register'!A22 -> INT-ET-CON | C86: ='Lot Register'!B22 -> Station integration | D86: ='Lot Register'!D22 -> MS-ET | E86: ='Lot Register'!G22 -> ST-ET-CON | F86: RECONSTRUCTION | G86: sealed custody, cold build description and outside-team replay | H86: Evidence Court | I86: SOURCE EMPTY | J86: =Controls!B25 -> 0 | K86: =IF(J86=1,"ACCEPTED","OPEN") -> OPEN
A87: ="PKT-"&B87&"-CONFIGURATION" -> PKT-RIG-ET-REC-CONFIGURATION | B87: ='Lot Register'!A23 -> RIG-ET-REC | C87: ='Lot Register'!B23 -> Root-native rig | D87: ='Lot Register'!D23 -> MS-ET | E87: ='Lot Register'!G23 -> ST-ET-REC | F87: CONFIGURATION | G87: frozen requirement, materials, interfaces and as-built record | H87: Requirement issuer | I87: SOURCE EMPTY | J87: =Controls!B25 -> 0 | K87: =IF(J87=1,"ACCEPTED","OPEN") -> OPEN
A88: ="PKT-"&B88&"-CONTROL" -> PKT-RIG-ET-REC-CONTROL | B88: ='Lot Register'!A23 -> RIG-ET-REC | C88: ='Lot Register'!B23 -> Root-native rig | D88: ='Lot Register'!D23 -> MS-ET | E88: ='Lot Register'!G23 -> ST-ET-REC | F88: CONTROL | G88: beneficial ownership, decisive ancestry, debt, tooling and key custody | H88: Control registrar | I88: SOURCE EMPTY | J88: =Controls!B25 -> 0 | K88: =IF(J88=1,"ACCEPTED","OPEN") -> OPEN
A89: ="PKT-"&B89&"-METROLOGY" -> PKT-RIG-ET-REC-METROLOGY | B89: ='Lot Register'!A23 -> RIG-ET-REC | C89: ='Lot Register'!B23 -> Root-native rig | D89: ='Lot Register'!D23 -> MS-ET | E89: ='Lot Register'!G23 -> ST-ET-REC | F89: METROLOGY | G89: native commissioning, calibration chain and measurement uncertainty | H89: Commissioning authority | I89: SOURCE EMPTY | J89: =Controls!B25 -> 0 | K89: =IF(J89=1,"ACCEPTED","OPEN") -> OPEN
A90: ="PKT-"&B90&"-SAFETY" -> PKT-RIG-ET-REC-SAFETY | B90: ='Lot Register'!A23 -> RIG-ET-REC | C90: ='Lot Register'!B23 -> Root-native rig | D90: ='Lot Register'!D23 -> MS-ET | E90: ='Lot Register'!G23 -> ST-ET-REC | F90: SAFETY | G90: worker, civil-rights, environmental, residual and safe-stop record | H90: Safety and rights authority | I90: SOURCE EMPTY | J90: =Controls!B25 -> 0 | K90: =IF(J90=1,"ACCEPTED","OPEN") -> OPEN
A91: ="PKT-"&B91&"-RECONSTRUCTION" -> PKT-RIG-ET-REC-RECONSTRUCTION | B91: ='Lot Register'!A23 -> RIG-ET-REC | C91: ='Lot Register'!B23 -> Root-native rig | D91: ='Lot Register'!D23 -> MS-ET | E91: ='Lot Register'!G23 -> ST-ET-REC | F91: RECONSTRUCTION | G91: sealed custody, cold build description and outside-team replay | H91: Evidence Court | I91: SOURCE EMPTY | J91: =Controls!B25 -> 0 | K91: =IF(J91=1,"ACCEPTED","OPEN") -> OPEN
A92: ="PKT-"&B92&"-CONFIGURATION" -> PKT-MTH-ET-REC-L1-CONFIGURATION | B92: ='Lot Register'!A24 -> MTH-ET-REC-L1 | C92: ='Lot Register'!B24 -> Method lineage | D92: ='Lot Register'!D24 -> MS-ET | E92: ='Lot Register'!G24 -> ST-ET-REC | F92: CONFIGURATION | G92: frozen requirement, materials, interfaces and as-built record | H92: Requirement issuer | I92: SOURCE EMPTY | J92: =Controls!B25 -> 0 | K92: =IF(J92=1,"ACCEPTED","OPEN") -> OPEN
A93: ="PKT-"&B93&"-CONTROL" -> PKT-MTH-ET-REC-L1-CONTROL | B93: ='Lot Register'!A24 -> MTH-ET-REC-L1 | C93: ='Lot Register'!B24 -> Method lineage | D93: ='Lot Register'!D24 -> MS-ET | E93: ='Lot Register'!G24 -> ST-ET-REC | F93: CONTROL | G93: beneficial ownership, decisive ancestry, debt, tooling and key custody | H93: Control registrar | I93: SOURCE EMPTY | J93: =Controls!B25 -> 0 | K93: =IF(J93=1,"ACCEPTED","OPEN") -> OPEN
A94: ="PKT-"&B94&"-METROLOGY" -> PKT-MTH-ET-REC-L1-METROLOGY | B94: ='Lot Register'!A24 -> MTH-ET-REC-L1 | C94: ='Lot Register'!B24 -> Method lineage | D94: ='Lot Register'!D24 -> MS-ET | E94: ='Lot Register'!G24 -> ST-ET-REC | F94: METROLOGY | G94: native commissioning, calibration chain and measurement uncertainty | H94: Commissioning authority | I94: SOURCE EMPTY | J94: =Controls!B25 -> 0 | K94: =IF(J94=1,"ACCEPTED","OPEN") -> OPEN
A95: ="PKT-"&B95&"-SAFETY" -> PKT-MTH-ET-REC-L1-SAFETY | B95: ='Lot Register'!A24 -> MTH-ET-REC-L1 | C95: ='Lot Register'!B24 -> Method lineage | D95: ='Lot Register'!D24 -> MS-ET | E95: ='Lot Register'!G24 -> ST-ET-REC | F95: SAFETY | G95: worker, civil-rights, environmental, residual and safe-stop record | H95: Safety and rights authority | I95: SOURCE EMPTY | J95: =Controls!B25 -> 0 | K95: =IF(J95=1,"ACCEPTED","OPEN") -> OPEN
A96: ="PKT-"&B96&"-RECONSTRUCTION" -> PKT-MTH-ET-REC-L1-RECONSTRUCTION | B96: ='Lot Register'!A24 -> MTH-ET-REC-L1 | C96: ='Lot Register'!B24 -> Method lineage | D96: ='Lot Register'!D24 -> MS-ET | E96: ='Lot Register'!G24 -> ST-ET-REC | F96: RECONSTRUCTION | G96: sealed custody, cold build description and outside-team replay | H96: Evidence Court | I96: SOURCE EMPTY | J96: =Controls!B25 -> 0 | K96: =IF(J96=1,"ACCEPTED","OPEN") -> OPEN
A97: ="PKT-"&B97&"-CONFIGURATION" -> PKT-MTH-ET-REC-L2-CONFIGURATION | B97: ='Lot Register'!A25 -> MTH-ET-REC-L2 | C97: ='Lot Register'!B25 -> Method lineage | D97: ='Lot Register'!D25 -> MS-ET | E97: ='Lot Register'!G25 -> ST-ET-REC | F97: CONFIGURATION | G97: frozen requirement, materials, interfaces and as-built record | H97: Requirement issuer | I97: SOURCE EMPTY | J97: =Controls!B25 -> 0 | K97: =IF(J97=1,"ACCEPTED","OPEN") -> OPEN
A98: ="PKT-"&B98&"-CONTROL" -> PKT-MTH-ET-REC-L2-CONTROL | B98: ='Lot Register'!A25 -> MTH-ET-REC-L2 | C98: ='Lot Register'!B25 -> Method lineage | D98: ='Lot Register'!D25 -> MS-ET | E98: ='Lot Register'!G25 -> ST-ET-REC | F98: CONTROL | G98: beneficial ownership, decisive ancestry, debt, tooling and key custody | H98: Control registrar | I98: SOURCE EMPTY | J98: =Controls!B25 -> 0 | K98: =IF(J98=1,"ACCEPTED","OPEN") -> OPEN
A99: ="PKT-"&B99&"-METROLOGY" -> PKT-MTH-ET-REC-L2-METROLOGY | B99: ='Lot Register'!A25 -> MTH-ET-REC-L2 | C99: ='Lot Register'!B25 -> Method lineage | D99: ='Lot Register'!D25 -> MS-ET | E99: ='Lot Register'!G25 -> ST-ET-REC | F99: METROLOGY | G99: native commissioning, calibration chain and measurement uncertainty | H99: Commissioning authority | I99: SOURCE EMPTY | J99: =Controls!B25 -> 0 | K99: =IF(J99=1,"ACCEPTED","OPEN") -> OPEN
A100: ="PKT-"&B100&"-SAFETY" -> PKT-MTH-ET-REC-L2-SAFETY | B100: ='Lot Register'!A25 -> MTH-ET-REC-L2 | C100: ='Lot Register'!B25 -> Method lineage | D100: ='Lot Register'!D25 -> MS-ET | E100: ='Lot Register'!G25 -> ST-ET-REC | F100: SAFETY | G100: worker, civil-rights, environmental, residual and safe-stop record | H100: Safety and rights authority | I100: SOURCE EMPTY | J100: =Controls!B25 -> 0 | K100: =IF(J100=1,"ACCEPTED","OPEN") -> OPEN
A101: ="PKT-"&B101&"-RECONSTRUCTION" -> PKT-MTH-ET-REC-L2-RECONSTRUCTION | B101: ='Lot Register'!A25 -> MTH-ET-REC-L2 | C101: ='Lot Register'!B25 -> Method lineage | D101: ='Lot Register'!D25 -> MS-ET | E101: ='Lot Register'!G25 -> ST-ET-REC | F101: RECONSTRUCTION | G101: sealed custody, cold build description and outside-team replay | H101: Evidence Court | I101: SOURCE EMPTY | J101: =Controls!B25 -> 0 | K101: =IF(J101=1,"ACCEPTED","OPEN") -> OPEN
A102: ="PKT-"&B102&"-CONFIGURATION" -> PKT-REG-ET-REC-CONFIGURATION | B102: ='Lot Register'!A26 -> REG-ET-REC | C102: ='Lot Register'!B26 -> Regeneration tool | D102: ='Lot Register'!D26 -> MS-ET | E102: ='Lot Register'!G26 -> ST-ET-REC | F102: CONFIGURATION | G102: frozen requirement, materials, interfaces and as-built record | H102: Requirement issuer | I102: SOURCE EMPTY | J102: =Controls!B25 -> 0 | K102: =IF(J102=1,"ACCEPTED","OPEN") -> OPEN
A103: ="PKT-"&B103&"-CONTROL" -> PKT-REG-ET-REC-CONTROL | B103: ='Lot Register'!A26 -> REG-ET-REC | C103: ='Lot Register'!B26 -> Regeneration tool | D103: ='Lot Register'!D26 -> MS-ET | E103: ='Lot Register'!G26 -> ST-ET-REC | F103: CONTROL | G103: beneficial ownership, decisive ancestry, debt, tooling and key custody | H103: Control registrar | I103: SOURCE EMPTY | J103: =Controls!B25 -> 0 | K103: =IF(J103=1,"ACCEPTED","OPEN") -> OPEN
...

Sheet Acceptance Gates
A2: Seven hundred fourteen noncompensatory construction decisions
A4: One failed gate holds the lot. A valid adverse candidate result may be payable, but it cannot convert a failed construction gate into completion.
A6: Decision ID | B6: Lot ID | C6: Lot class | D6: System | E6: Station/package | F6: Gate | G6: Name | H6: Criterion | I6: Accepting authority | J6: Evidence identity | K6: Accepted | L6: State
A7: ="DEC-"&B7&"-G1" -> DEC-SUB-01-G1 | B7: ='Lot Register'!A7 -> SUB-01 | C7: ='Lot Register'!B7 -> Civil substrate | D7: ='Lot Register'!D7 -> MULTI | E7: ='Lot Register'!G7 -> ST-ET-CHA · ST-HC-REC · ST-HU-CON | F7: G1 | G7: IDENTITY | H7: identity and beneficial control admissible | I7: Control registrar | J7: SOURCE EMPTY | K7: =Controls!B26 -> 0 | L7: =IF(K7=1,"PASS","OPEN") -> OPEN
A8: ="DEC-"&B8&"-G2" -> DEC-SUB-01-G2 | B8: ='Lot Register'!A7 -> SUB-01 | C8: ='Lot Register'!B7 -> Civil substrate | D8: ='Lot Register'!D7 -> MULTI | E8: ='Lot Register'!G7 -> ST-ET-CHA · ST-HC-REC · ST-HU-CON | F8: G2 | G8: BASELINE | H8: issue baseline frozen without builder conversion | I8: Requirement issuer | J8: SOURCE EMPTY | K8: =Controls!B26 -> 0 | L8: =IF(K8=1,"PASS","OPEN") -> OPEN
A9: ="DEC-"&B9&"-G3" -> DEC-SUB-01-G3 | B9: ='Lot Register'!A7 -> SUB-01 | C9: ='Lot Register'!B7 -> Civil substrate | D9: ='Lot Register'!D7 -> MULTI | E9: ='Lot Register'!G7 -> ST-ET-CHA · ST-HC-REC · ST-HU-CON | F9: G3 | G9: AS-BUILT | H9: materials, interfaces and as-built state reconcile | I9: Commissioning authority | J9: SOURCE EMPTY | K9: =Controls!B26 -> 0 | L9: =IF(K9=1,"PASS","OPEN") -> OPEN
A10: ="DEC-"&B10&"-G4" -> DEC-SUB-01-G4 | B10: ='Lot Register'!A7 -> SUB-01 | C10: ='Lot Register'!B7 -> Civil substrate | D10: ='Lot Register'!D7 -> MULTI | E10: ='Lot Register'!G7 -> ST-ET-CHA · ST-HC-REC · ST-HU-CON | F10: G4 | G10: ISOLATION | H10: no forbidden common decisive path | I10: Control registrar | J10: SOURCE EMPTY | K10: =Controls!B26 -> 0 | L10: =IF(K10=1,"PASS","OPEN") -> OPEN
A11: ="DEC-"&B11&"-G5" -> DEC-SUB-01-G5 | B11: ='Lot Register'!A7 -> SUB-01 | C11: ='Lot Register'!B7 -> Civil substrate | D11: ='Lot Register'!D7 -> MULTI | E11: ='Lot Register'!G7 -> ST-ET-CHA · ST-HC-REC · ST-HU-CON | F11: G5 | G11: COMMISSION | H11: root-native commissioning closes | I11: Commissioning authority | J11: SOURCE EMPTY | K11: =Controls!B26 -> 0 | L11: =IF(K11=1,"PASS","OPEN") -> OPEN
A12: ="DEC-"&B12&"-G6" -> DEC-SUB-01-G6 | B12: ='Lot Register'!A7 -> SUB-01 | C12: ='Lot Register'!B7 -> Civil substrate | D12: ='Lot Register'!D7 -> MULTI | E12: ='Lot Register'!G7 -> ST-ET-CHA · ST-HC-REC · ST-HU-CON | F12: G6 | G12: DENIAL | H12: controlled denial or destructive witness is valid | I12: Evidence Court | J12: SOURCE EMPTY | K12: =Controls!B26 -> 0 | L12: =IF(K12=1,"PASS","OPEN") -> OPEN
A13: ="DEC-"&B13&"-G7" -> DEC-SUB-01-G7 | B13: ='Lot Register'!A7 -> SUB-01 | C13: ='Lot Register'!B7 -> Civil substrate | D13: ='Lot Register'!D7 -> MULTI | E13: ='Lot Register'!G7 -> ST-ET-CHA · ST-HC-REC · ST-HU-CON | F13: G7 | G13: COLD RETURN | H13: outside team reconstructs accepted state | I13: Evidence Court | J13: SOURCE EMPTY | K13: =Controls!B26 -> 0 | L13: =IF(K13=1,"PASS","OPEN") -> OPEN
A14: ="DEC-"&B14&"-G1" -> DEC-SUB-02-G1 | B14: ='Lot Register'!A8 -> SUB-02 | C14: ='Lot Register'!B8 -> Civil substrate | D14: ='Lot Register'!D8 -> MULTI | E14: ='Lot Register'!G8 -> ST-CT-CHA · ST-LF-REC · ST-RT-CON | F14: G1 | G14: IDENTITY | H14: identity and beneficial control admissible | I14: Control registrar | J14: SOURCE EMPTY | K14: =Controls!B26 -> 0 | L14: =IF(K14=1,"PASS","OPEN") -> OPEN
A15: ="DEC-"&B15&"-G2" -> DEC-SUB-02-G2 | B15: ='Lot Register'!A8 -> SUB-02 | C15: ='Lot Register'!B8 -> Civil substrate | D15: ='Lot Register'!D8 -> MULTI | E15: ='Lot Register'!G8 -> ST-CT-CHA · ST-LF-REC · ST-RT-CON | F15: G2 | G15: BASELINE | H15: issue baseline frozen without builder conversion | I15: Requirement issuer | J15: SOURCE EMPTY | K15: =Controls!B26 -> 0 | L15: =IF(K15=1,"PASS","OPEN") -> OPEN
A16: ="DEC-"&B16&"-G3" -> DEC-SUB-02-G3 | B16: ='Lot Register'!A8 -> SUB-02 | C16: ='Lot Register'!B8 -> Civil substrate | D16: ='Lot Register'!D8 -> MULTI | E16: ='Lot Register'!G8 -> ST-CT-CHA · ST-LF-REC · ST-RT-CON | F16: G3 | G16: AS-BUILT | H16: materials, interfaces and as-built state reconcile | I16: Commissioning authority | J16: SOURCE EMPTY | K16: =Controls!B26 -> 0 | L16: =IF(K16=1,"PASS","OPEN") -> OPEN
A17: ="DEC-"&B17&"-G4" -> DEC-SUB-02-G4 | B17: ='Lot Register'!A8 -> SUB-02 | C17: ='Lot Register'!B8 -> Civil substrate | D17: ='Lot Register'!D8 -> MULTI | E17: ='Lot Register'!G8 -> ST-CT-CHA · ST-LF-REC · ST-RT-CON | F17: G4 | G17: ISOLATION | H17: no forbidden common decisive path | I17: Control registrar | J17: SOURCE EMPTY | K17: =Controls!B26 -> 0 | L17: =IF(K17=1,"PASS","OPEN") -> OPEN
A18: ="DEC-"&B18&"-G5" -> DEC-SUB-02-G5 | B18: ='Lot Register'!A8 -> SUB-02 | C18: ='Lot Register'!B8 -> Civil substrate | D18: ='Lot Register'!D8 -> MULTI | E18: ='Lot Register'!G8 -> ST-CT-CHA · ST-LF-REC · ST-RT-CON | F18: G5 | G18: COMMISSION | H18: root-native commissioning closes | I18: Commissioning authority | J18: SOURCE EMPTY | K18: =Controls!B26 -> 0 | L18: =IF(K18=1,"PASS","OPEN") -> OPEN
A19: ="DEC-"&B19&"-G6" -> DEC-SUB-02-G6 | B19: ='Lot Register'!A8 -> SUB-02 | C19: ='Lot Register'!B8 -> Civil substrate | D19: ='Lot Register'!D8 -> MULTI | E19: ='Lot Register'!G8 -> ST-CT-CHA · ST-LF-REC · ST-RT-CON | F19: G6 | G19: DENIAL | H19: controlled denial or destructive witness is valid | I19: Evidence Court | J19: SOURCE EMPTY | K19: =Controls!B26 -> 0 | L19: =IF(K19=1,"PASS","OPEN") -> OPEN
A20: ="DEC-"&B20&"-G7" -> DEC-SUB-02-G7 | B20: ='Lot Register'!A8 -> SUB-02 | C20: ='Lot Register'!B8 -> Civil substrate | D20: ='Lot Register'!D8 -> MULTI | E20: ='Lot Register'!G8 -> ST-CT-CHA · ST-LF-REC · ST-RT-CON | F20: G7 | G20: COLD RETURN | H20: outside team reconstructs accepted state | I20: Evidence Court | J20: SOURCE EMPTY | K20: =Controls!B26 -> 0 | L20: =IF(K20=1,"PASS","OPEN") -> OPEN
A21: ="DEC-"&B21&"-G1" -> DEC-SUB-03-G1 | B21: ='Lot Register'!A9 -> SUB-03 | C21: ='Lot Register'!B9 -> Civil substrate | D21: ='Lot Register'!D9 -> MULTI | E21: ='Lot Register'!G9 -> ST-ET-CON · ST-HC-CHA · ST-HU-REC | F21: G1 | G21: IDENTITY | H21: identity and beneficial control admissible | I21: Control registrar | J21: SOURCE EMPTY | K21: =Controls!B26 -> 0 | L21: =IF(K21=1,"PASS","OPEN") -> OPEN
A22: ="DEC-"&B22&"-G2" -> DEC-SUB-03-G2 | B22: ='Lot Register'!A9 -> SUB-03 | C22: ='Lot Register'!B9 -> Civil substrate | D22: ='Lot Register'!D9 -> MULTI | E22: ='Lot Register'!G9 -> ST-ET-CON · ST-HC-CHA · ST-HU-REC | F22: G2 | G22: BASELINE | H22: issue baseline frozen without builder conversion | I22: Requirement issuer | J22: SOURCE EMPTY | K22: =Controls!B26 -> 0 | L22: =IF(K22=1,"PASS","OPEN") -> OPEN
A23: ="DEC-"&B23&"-G3" -> DEC-SUB-03-G3 | B23: ='Lot Register'!A9 -> SUB-03 | C23: ='Lot Register'!B9 -> Civil substrate | D23: ='Lot Register'!D9 -> MULTI | E23: ='Lot Register'!G9 -> ST-ET-CON · ST-HC-CHA · ST-HU-REC | F23: G3 | G23: AS-BUILT | H23: materials, interfaces and as-built state reconcile | I23: Commissioning authority | J23: SOURCE EMPTY | K23: =Controls!B26 -> 0 | L23: =IF(K23=1,"PASS","OPEN") -> OPEN
A24: ="DEC-"&B24&"-G4" -> DEC-SUB-03-G4 | B24: ='Lot Register'!A9 -> SUB-03 | C24: ='Lot Register'!B9 -> Civil substrate | D24: ='Lot Register'!D9 -> MULTI | E24: ='Lot Register'!G9 -> ST-ET-CON · ST-HC-CHA · ST-HU-REC | F24: G4 | G24: ISOLATION | H24: no forbidden common decisive path | I24: Control registrar | J24: SOURCE EMPTY | K24: =Controls!B26 -> 0 | L24: =IF(K24=1,"PASS","OPEN") -> OPEN
A25: ="DEC-"&B25&"-G5" -> DEC-SUB-03-G5 | B25: ='Lot Register'!A9 -> SUB-03 | C25: ='Lot Register'!B9 -> Civil substrate | D25: ='Lot Register'!D9 -> MULTI | E25: ='Lot Register'!G9 -> ST-ET-CON · ST-HC-CHA · ST-HU-REC | F25: G5 | G25: COMMISSION | H25: root-native commissioning closes | I25: Commissioning authority | J25: SOURCE EMPTY | K25: =Controls!B26 -> 0 | L25: =IF(K25=1,"PASS","OPEN") -> OPEN
A26: ="DEC-"&B26&"-G6" -> DEC-SUB-03-G6 | B26: ='Lot Register'!A9 -> SUB-03 | C26: ='Lot Register'!B9 -> Civil substrate | D26: ='Lot Register'!D9 -> MULTI | E26: ='Lot Register'!G9 -> ST-ET-CON · ST-HC-CHA · ST-HU-REC | F26: G6 | G26: DENIAL | H26: controlled denial or destructive witness is valid | I26: Evidence Court | J26: SOURCE EMPTY | K26: =Controls!B26 -> 0 | L26: =IF(K26=1,"PASS","OPEN") -> OPEN
A27: ="DEC-"&B27&"-G7" -> DEC-SUB-03-G7 | B27: ='Lot Register'!A9 -> SUB-03 | C27: ='Lot Register'!B9 -> Civil substrate | D27: ='Lot Register'!D9 -> MULTI | E27: ='Lot Register'!G9 -> ST-ET-CON · ST-HC-CHA · ST-HU-REC | F27: G7 | G27: COLD RETURN | H27: outside team reconstructs accepted state | I27: Evidence Court | J27: SOURCE EMPTY | K27: =Controls!B26 -> 0 | L27: =IF(K27=1,"PASS","OPEN") -> OPEN
A28: ="DEC-"&B28&"-G1" -> DEC-SUB-04-G1 | B28: ='Lot Register'!A10 -> SUB-04 | C28: ='Lot Register'!B10 -> Civil substrate | D28: ='Lot Register'!D10 -> MULTI | E28: ='Lot Register'!G10 -> ST-CT-CON · ST-LF-CHA · ST-RT-REC | F28: G1 | G28: IDENTITY | H28: identity and beneficial control admissible | I28: Control registrar | J28: SOURCE EMPTY | K28: =Controls!B26 -> 0 | L28: =IF(K28=1,"PASS","OPEN") -> OPEN
A29: ="DEC-"&B29&"-G2" -> DEC-SUB-04-G2 | B29: ='Lot Register'!A10 -> SUB-04 | C29: ='Lot Register'!B10 -> Civil substrate | D29: ='Lot Register'!D10 -> MULTI | E29: ='Lot Register'!G10 -> ST-CT-CON · ST-LF-CHA · ST-RT-REC | F29: G2 | G29: BASELINE | H29: issue baseline frozen without builder conversion | I29: Requirement issuer | J29: SOURCE EMPTY | K29: =Controls!B26 -> 0 | L29: =IF(K29=1,"PASS","OPEN") -> OPEN
A30: ="DEC-"&B30&"-G3" -> DEC-SUB-04-G3 | B30: ='Lot Register'!A10 -> SUB-04 | C30: ='Lot Register'!B10 -> Civil substrate | D30: ='Lot Register'!D10 -> MULTI | E30: ='Lot Register'!G10 -> ST-CT-CON · ST-LF-CHA · ST-RT-REC | F30: G3 | G30: AS-BUILT | H30: materials, interfaces and as-built state reconcile | I30: Commissioning authority | J30: SOURCE EMPTY | K30: =Controls!B26 -> 0 | L30: =IF(K30=1,"PASS","OPEN") -> OPEN
A31: ="DEC-"&B31&"-G4" -> DEC-SUB-04-G4 | B31: ='Lot Register'!A10 -> SUB-04 | C31: ='Lot Register'!B10 -> Civil substrate | D31: ='Lot Register'!D10 -> MULTI | E31: ='Lot Register'!G10 -> ST-CT-CON · ST-LF-CHA · ST-RT-REC | F31: G4 | G31: ISOLATION | H31: no forbidden common decisive path | I31: Control registrar | J31: SOURCE EMPTY | K31: =Controls!B26 -> 0 | L31: =IF(K31=1,"PASS","OPEN") -> OPEN
A32: ="DEC-"&B32&"-G5" -> DEC-SUB-04-G5 | B32: ='Lot Register'!A10 -> SUB-04 | C32: ='Lot Register'!B10 -> Civil substrate | D32: ='Lot Register'!D10 -> MULTI | E32: ='Lot Register'!G10 -> ST-CT-CON · ST-LF-CHA · ST-RT-REC | F32: G5 | G32: COMMISSION | H32: root-native commissioning closes | I32: Commissioning authority | J32: SOURCE EMPTY | K32: =Controls!B26 -> 0 | L32: =IF(K32=1,"PASS","OPEN") -> OPEN
A33: ="DEC-"&B33&"-G6" -> DEC-SUB-04-G6 | B33: ='Lot Register'!A10 -> SUB-04 | C33: ='Lot Register'!B10 -> Civil substrate | D33: ='Lot Register'!D10 -> MULTI | E33: ='Lot Register'!G10 -> ST-CT-CON · ST-LF-CHA · ST-RT-REC | F33: G6 | G33: DENIAL | H33: controlled denial or destructive witness is valid | I33: Evidence Court | J33: SOURCE EMPTY | K33: =Controls!B26 -> 0 | L33: =IF(K33=1,"PASS","OPEN") -> OPEN
A34: ="DEC-"&B34&"-G7" -> DEC-SUB-04-G7 | B34: ='Lot Register'!A10 -> SUB-04 | C34: ='Lot Register'!B10 -> Civil substrate | D34: ='Lot Register'!D10 -> MULTI | E34: ='Lot Register'!G10 -> ST-CT-CON · ST-LF-CHA · ST-RT-REC | F34: G7 | G34: COLD RETURN | H34: outside team reconstructs accepted state | I34: Evidence Court | J34: SOURCE EMPTY | K34: =Controls!B26 -> 0 | L34: =IF(K34=1,"PASS","OPEN") -> OPEN
A35: ="DEC-"&B35&"-G1" -> DEC-SUB-05-G1 | B35: ='Lot Register'!A11 -> SUB-05 | C35: ='Lot Register'!B11 -> Civil substrate | D35: ='Lot Register'!D11 -> MULTI | E35: ='Lot Register'!G11 -> ST-ET-REC · ST-HC-CON · ST-HU-CHA | F35: G1 | G35: IDENTITY | H35: identity and beneficial control admissible | I35: Control registrar | J35: SOURCE EMPTY | K35: =Controls!B26 -> 0 | L35: =IF(K35=1,"PASS","OPEN") -> OPEN
A36: ="DEC-"&B36&"-G2" -> DEC-SUB-05-G2 | B36: ='Lot Register'!A11 -> SUB-05 | C36: ='Lot Register'!B11 -> Civil substrate | D36: ='Lot Register'!D11 -> MULTI | E36: ='Lot Register'!G11 -> ST-ET-REC · ST-HC-CON · ST-HU-CHA | F36: G2 | G36: BASELINE | H36: issue baseline frozen without builder conversion | I36: Requirement issuer | J36: SOURCE EMPTY | K36: =Controls!B26 -> 0 | L36: =IF(K36=1,"PASS","OPEN") -> OPEN
A37: ="DEC-"&B37&"-G3" -> DEC-SUB-05-G3 | B37: ='Lot Register'!A11 -> SUB-05 | C37: ='Lot Register'!B11 -> Civil substrate | D37: ='Lot Register'!D11 -> MULTI | E37: ='Lot Register'!G11 -> ST-ET-REC · ST-HC-CON · ST-HU-CHA | F37: G3 | G37: AS-BUILT | H37: materials, interfaces and as-built state reconcile | I37: Commissioning authority | J37: SOURCE EMPTY | K37: =Controls!B26 -> 0 | L37: =IF(K37=1,"PASS","OPEN") -> OPEN
A38: ="DEC-"&B38&"-G4" -> DEC-SUB-05-G4 | B38: ='Lot Register'!A11 -> SUB-05 | C38: ='Lot Register'!B11 -> Civil substrate | D38: ='Lot Register'!D11 -> MULTI | E38: ='Lot Register'!G11 -> ST-ET-REC · ST-HC-CON · ST-HU-CHA | F38: G4 | G38: ISOLATION | H38: no forbidden common decisive path | I38: Control registrar | J38: SOURCE EMPTY | K38: =Controls!B26 -> 0 | L38: =IF(K38=1,"PASS","OPEN") -> OPEN
A39: ="DEC-"&B39&"-G5" -> DEC-SUB-05-G5 | B39: ='Lot Register'!A11 -> SUB-05 | C39: ='Lot Register'!B11 -> Civil substrate | D39: ='Lot Register'!D11 -> MULTI | E39: ='Lot Register'!G11 -> ST-ET-REC · ST-HC-CON · ST-HU-CHA | F39: G5 | G39: COMMISSION | H39: root-native commissioning closes | I39: Commissioning authority | J39: SOURCE EMPTY | K39: =Controls!B26 -> 0 | L39: =IF(K39=1,"PASS","OPEN") -> OPEN
A40: ="DEC-"&B40&"-G6" -> DEC-SUB-05-G6 | B40: ='Lot Register'!A11 -> SUB-05 | C40: ='Lot Register'!B11 -> Civil substrate | D40: ='Lot Register'!D11 -> MULTI | E40: ='Lot Register'!G11 -> ST-ET-REC · ST-HC-CON · ST-HU-CHA | F40: G6 | G40: DENIAL | H40: controlled denial or destructive witness is valid | I40: Evidence Court | J40: SOURCE EMPTY | K40: =Controls!B26 -> 0 | L40: =IF(K40=1,"PASS","OPEN") -> OPEN
A41: ="DEC-"&B41&"-G7" -> DEC-SUB-05-G7 | B41: ='Lot Register'!A11 -> SUB-05 | C41: ='Lot Register'!B11 -> Civil substrate | D41: ='Lot Register'!D11 -> MULTI | E41: ='Lot Register'!G11 -> ST-ET-REC · ST-HC-CON · ST-HU-CHA | F41: G7 | G41: COLD RETURN | H41: outside team reconstructs accepted state | I41: Evidence Court | J41: SOURCE EMPTY | K41: =Controls!B26 -> 0 | L41: =IF(K41=1,"PASS","OPEN") -> OPEN
A42: ="DEC-"&B42&"-G1" -> DEC-SUB-06-G1 | B42: ='Lot Register'!A12 -> SUB-06 | C42: ='Lot Register'!B12 -> Civil substrate | D42: ='Lot Register'!D12 -> MULTI | E42: ='Lot Register'!G12 -> ST-CT-REC · ST-LF-CON · ST-RT-CHA | F42: G1 | G42: IDENTITY | H42: identity and beneficial control admissible | I42: Control registrar | J42: SOURCE EMPTY | K42: =Controls!B26 -> 0 | L42: =IF(K42=1,"PASS","OPEN") -> OPEN
A43: ="DEC-"&B43&"-G2" -> DEC-SUB-06-G2 | B43: ='Lot Register'!A12 -> SUB-06 | C43: ='Lot Register'!B12 -> Civil substrate | D43: ='Lot Register'!D12 -> MULTI | E43: ='Lot Register'!G12 -> ST-CT-REC · ST-LF-CON · ST-RT-CHA | F43: G2 | G43: BASELINE | H43: issue baseline frozen without builder conversion | I43: Requirement issuer | J43: SOURCE EMPTY | K43: =Controls!B26 -> 0 | L43: =IF(K43=1,"PASS","OPEN") -> OPEN
A44: ="DEC-"&B44&"-G3" -> DEC-SUB-06-G3 | B44: ='Lot Register'!A12 -> SUB-06 | C44: ='Lot Register'!B12 -> Civil substrate | D44: ='Lot Register'!D12 -> MULTI | E44: ='Lot Register'!G12 -> ST-CT-REC · ST-LF-CON · ST-RT-CHA | F44: G3 | G44: AS-BUILT | H44: materials, interfaces and as-built state reconcile | I44: Commissioning authority | J44: SOURCE EMPTY | K44: =Controls!B26 -> 0 | L44: =IF(K44=1,"PASS","OPEN") -> OPEN
A45: ="DEC-"&B45&"-G4" -> DEC-SUB-06-G4 | B45: ='Lot Register'!A12 -> SUB-06 | C45: ='Lot Register'!B12 -> Civil substrate | D45: ='Lot Register'!D12 -> MULTI | E45: ='Lot Register'!G12 -> ST-CT-REC · ST-LF-CON · ST-RT-CHA | F45: G4 | G45: ISOLATION | H45: no forbidden common decisive path | I45: Control registrar | J45: SOURCE EMPTY | K45: =Controls!B26 -> 0 | L45: =IF(K45=1,"PASS","OPEN") -> OPEN
A46: ="DEC-"&B46&"-G5" -> DEC-SUB-06-G5 | B46: ='Lot Register'!A12 -> SUB-06 | C46: ='Lot Register'!B12 -> Civil substrate | D46: ='Lot Register'!D12 -> MULTI | E46: ='Lot Register'!G12 -> ST-CT-REC · ST-LF-CON · ST-RT-CHA | F46: G5 | G46: COMMISSION | H46: root-native commissioning closes | I46: Commissioning authority | J46: SOURCE EMPTY | K46: =Controls!B26 -> 0 | L46: =IF(K46=1,"PASS","OPEN") -> OPEN
A47: ="DEC-"&B47&"-G6" -> DEC-SUB-06-G6 | B47: ='Lot Register'!A12 -> SUB-06 | C47: ='Lot Register'!B12 -> Civil substrate | D47: ='Lot Register'!D12 -> MULTI | E47: ='Lot Register'!G12 -> ST-CT-REC · ST-LF-CON · ST-RT-CHA | F47: G6 | G47: DENIAL | H47: controlled denial or destructive witness is valid | I47: Evidence Court | J47: SOURCE EMPTY | K47: =Controls!B26 -> 0 | L47: =IF(K47=1,"PASS","OPEN") -> OPEN
A48: ="DEC-"&B48&"-G7" -> DEC-SUB-06-G7 | B48: ='Lot Register'!A12 -> SUB-06 | C48: ='Lot Register'!B12 -> Civil substrate | D48: ='Lot Register'!D12 -> MULTI | E48: ='Lot Register'!G12 -> ST-CT-REC · ST-LF-CON · ST-RT-CHA | F48: G7 | G48: COLD RETURN | H48: outside team reconstructs accepted state | I48: Evidence Court | J48: SOURCE EMPTY | K48: =Controls!B26 -> 0 | L48: =IF(K48=1,"PASS","OPEN") -> OPEN
A49: ="DEC-"&B49&"-G1" -> DEC-RIG-ET-CHA-G1 | B49: ='Lot Register'!A13 -> RIG-ET-CHA | C49: ='Lot Register'!B13 -> Root-native rig | D49: ='Lot Register'!D13 -> MS-ET | E49: ='Lot Register'!G13 -> ST-ET-CHA | F49: G1 | G49: IDENTITY | H49: identity and beneficial control admissible | I49: Control registrar | J49: SOURCE EMPTY | K49: =Controls!B26 -> 0 | L49: =IF(K49=1,"PASS","OPEN") -> OPEN
A50: ="DEC-"&B50&"-G2" -> DEC-RIG-ET-CHA-G2 | B50: ='Lot Register'!A13 -> RIG-ET-CHA | C50: ='Lot Register'!B13 -> Root-native rig | D50: ='Lot Register'!D13 -> MS-ET | E50: ='Lot Register'!G13 -> ST-ET-CHA | F50: G2 | G50: BASELINE | H50: issue baseline frozen without builder conversion | I50: Requirement issuer | J50: SOURCE EMPTY | K50: =Controls!B26 -> 0 | L50: =IF(K50=1,"PASS","OPEN") -> OPEN
A51: ="DEC-"&B51&"-G3" -> DEC-RIG-ET-CHA-G3 | B51: ='Lot Register'!A13 -> RIG-ET-CHA | C51: ='Lot Register'!B13 -> Root-native rig | D51: ='Lot Register'!D13 -> MS-ET | E51: ='Lot Register'!G13 -> ST-ET-CHA | F51: G3 | G51: AS-BUILT | H51: materials, interfaces and as-built state reconcile | I51: Commissioning authority | J51: SOURCE EMPTY | K51: =Controls!B26 -> 0 | L51: =IF(K51=1,"PASS","OPEN") -> OPEN
A52: ="DEC-"&B52&"-G4" -> DEC-RIG-ET-CHA-G4 | B52: ='Lot Register'!A13 -> RIG-ET-CHA | C52: ='Lot Register'!B13 -> Root-native rig | D52: ='Lot Register'!D13 -> MS-ET | E52: ='Lot Register'!G13 -> ST-ET-CHA | F52: G4 | G52: ISOLATION | H52: no forbidden common decisive path | I52: Control registrar | J52: SOURCE EMPTY | K52: =Controls!B26 -> 0 | L52: =IF(K52=1,"PASS","OPEN") -> OPEN
A53: ="DEC-"&B53&"-G5" -> DEC-RIG-ET-CHA-G5 | B53: ='Lot Register'!A13 -> RIG-ET-CHA | C53: ='Lot Register'!B13 -> Root-native rig | D53: ='Lot Register'!D13 -> MS-ET | E53: ='Lot Register'!G13 -> ST-ET-CHA | F53: G5 | G53: COMMISSION | H53: root-native commissioning closes | I53: Commissioning authority | J53: SOURCE EMPTY | K53: =Controls!B26 -> 0 | L53: =IF(K53=1,"PASS","OPEN") -> OPEN
A54: ="DEC-"&B54&"-G6" -> DEC-RIG-ET-CHA-G6 | B54: ='Lot Register'!A13 -> RIG-ET-CHA | C54: ='Lot Register'!B13 -> Root-native rig | D54: ='Lot Register'!D13 -> MS-ET | E54: ='Lot Register'!G13 -> ST-ET-CHA | F54: G6 | G54: DENIAL | H54: controlled denial or destructive witness is valid | I54: Evidence Court | J54: SOURCE EMPTY | K54: =Controls!B26 -> 0 | L54: =IF(K54=1,"PASS","OPEN") -> OPEN
A55: ="DEC-"&B55&"-G7" -> DEC-RIG-ET-CHA-G7 | B55: ='Lot Register'!A13 -> RIG-ET-CHA | C55: ='Lot Register'!B13 -> Root-native rig | D55: ='Lot Register'!D13 -> MS-ET | E55: ='Lot Register'!G13 -> ST-ET-CHA | F55: G7 | G55: COLD RETURN | H55: outside team reconstructs accepted state | I55: Evidence Court | J55: SOURCE EMPTY | K55: =Controls!B26 -> 0 | L55: =IF(K55=1,"PASS","OPEN") -> OPEN
A56: ="DEC-"&B56&"-G1" -> DEC-MTH-ET-CHA-L1-G1 | B56: ='Lot Register'!A14 -> MTH-ET-CHA-L1 | C56: ='Lot Register'!B14 -> Method lineage | D56: ='Lot Register'!D14 -> MS-ET | E56: ='Lot Register'!G14 -> ST-ET-CHA | F56: G1 | G56: IDENTITY | H56: identity and beneficial control admissible | I56: Control registrar | J56: SOURCE EMPTY | K56: =Controls!B26 -> 0 | L56: =IF(K56=1,"PASS","OPEN") -> OPEN
A57: ="DEC-"&B57&"-G2" -> DEC-MTH-ET-CHA-L1-G2 | B57: ='Lot Register'!A14 -> MTH-ET-CHA-L1 | C57: ='Lot Register'!B14 -> Method lineage | D57: ='Lot Register'!D14 -> MS-ET | E57: ='Lot Register'!G14 -> ST-ET-CHA | F57: G2 | G57: BASELINE | H57: issue baseline frozen without builder conversion | I57: Requirement issuer | J57: SOURCE EMPTY | K57: =Controls!B26 -> 0 | L57: =IF(K57=1,"PASS","OPEN") -> OPEN
A58: ="DEC-"&B58&"-G3" -> DEC-MTH-ET-CHA-L1-G3 | B58: ='Lot Register'!A14 -> MTH-ET-CHA-L1 | C58: ='Lot Register'!B14 -> Method lineage | D58: ='Lot Register'!D14 -> MS-ET | E58: ='Lot Register'!G14 -> ST-ET-CHA | F58: G3 | G58: AS-BUILT | H58: materials, interfaces and as-built state reconcile | I58: Commissioning authority | J58: SOURCE EMPTY | K58: =Controls!B26 -> 0 | L58: =IF(K58=1,"PASS","OPEN") -> OPEN
A59: ="DEC-"&B59&"-G4" -> DEC-MTH-ET-CHA-L1-G4 | B59: ='Lot Register'!A14 -> MTH-ET-CHA-L1 | C59: ='Lot Register'!B14 -> Method lineage | D59: ='Lot Register'!D14 -> MS-ET | E59: ='Lot Register'!G14 -> ST-ET-CHA | F59: G4 | G59: ISOLATION | H59: no forbidden common decisive path | I59: Control registrar | J59: SOURCE EMPTY | K59: =Controls!B26 -> 0 | L59: =IF(K59=1,"PASS","OPEN") -> OPEN
A60: ="DEC-"&B60&"-G5" -> DEC-MTH-ET-CHA-L1-G5 | B60: ='Lot Register'!A14 -> MTH-ET-CHA-L1 | C60: ='Lot Register'!B14 -> Method lineage | D60: ='Lot Register'!D14 -> MS-ET | E60: ='Lot Register'!G14 -> ST-ET-CHA | F60: G5 | G60: COMMISSION | H60: root-native commissioning closes | I60: Commissioning authority | J60: SOURCE EMPTY | K60: =Controls!B26 -> 0 | L60: =IF(K60=1,"PASS","OPEN") -> OPEN
A61: ="DEC-"&B61&"-G6" -> DEC-MTH-ET-CHA-L1-G6 | B61: ='Lot Register'!A14 -> MTH-ET-CHA-L1 | C61: ='Lot Register'!B14 -> Method lineage | D61: ='Lot Register'!D14 -> MS-ET | E61: ='Lot Register'!G14 -> ST-ET-CHA | F61: G6 | G61: DENIAL | H61: controlled denial or destructive witness is valid | I61: Evidence Court | J61: SOURCE EMPTY | K61: =Controls!B26 -> 0 | L61: =IF(K61=1,"PASS","OPEN") -> OPEN
A62: ="DEC-"&B62&"-G7" -> DEC-MTH-ET-CHA-L1-G7 | B62: ='Lot Register'!A14 -> MTH-ET-CHA-L1 | C62: ='Lot Register'!B14 -> Method lineage | D62: ='Lot Register'!D14 -> MS-ET | E62: ='Lot Register'!G14 -> ST-ET-CHA | F62: G7 | G62: COLD RETURN | H62: outside team reconstructs accepted state | I62: Evidence Court | J62: SOURCE EMPTY | K62: =Controls!B26 -> 0 | L62: =IF(K62=1,"PASS","OPEN") -> OPEN
A63: ="DEC-"&B63&"-G1" -> DEC-MTH-ET-CHA-L2-G1 | B63: ='Lot Register'!A15 -> MTH-ET-CHA-L2 | C63: ='Lot Register'!B15 -> Method lineage | D63: ='Lot Register'!D15 -> MS-ET | E63: ='Lot Register'!G15 -> ST-ET-CHA | F63: G1 | G63: IDENTITY | H63: identity and beneficial control admissible | I63: Control registrar | J63: SOURCE EMPTY | K63: =Controls!B26 -> 0 | L63: =IF(K63=1,"PASS","OPEN") -> OPEN
A64: ="DEC-"&B64&"-G2" -> DEC-MTH-ET-CHA-L2-G2 | B64: ='Lot Register'!A15 -> MTH-ET-CHA-L2 | C64: ='Lot Register'!B15 -> Method lineage | D64: ='Lot Register'!D15 -> MS-ET | E64: ='Lot Register'!G15 -> ST-ET-CHA | F64: G2 | G64: BASELINE | H64: issue baseline frozen without builder conversion | I64: Requirement issuer | J64: SOURCE EMPTY | K64: =Controls!B26 -> 0 | L64: =IF(K64=1,"PASS","OPEN") -> OPEN
A65: ="DEC-"&B65&"-G3" -> DEC-MTH-ET-CHA-L2-G3 | B65: ='Lot Register'!A15 -> MTH-ET-CHA-L2 | C65: ='Lot Register'!B15 -> Method lineage | D65: ='Lot Register'!D15 -> MS-ET | E65: ='Lot Register'!G15 -> ST-ET-CHA | F65: G3 | G65: AS-BUILT | H65: materials, interfaces and as-built state reconcile | I65: Commissioning authority | J65: SOURCE EMPTY | K65: =Controls!B26 -> 0 | L65: =IF(K65=1,"PASS","OPEN") -> OPEN
A66: ="DEC-"&B66&"-G4" -> DEC-MTH-ET-CHA-L2-G4 | B66: ='Lot Register'!A15 -> MTH-ET-CHA-L2 | C66: ='Lot Register'!B15 -> Method lineage | D66: ='Lot Register'!D15 -> MS-ET | E66: ='Lot Register'!G15 -> ST-ET-CHA | F66: G4 | G66: ISOLATION | H66: no forbidden common decisive path | I66: Control registrar | J66: SOURCE EMPTY | K66: =Controls!B26 -> 0 | L66: =IF(K66=1,"PASS","OPEN") -> OPEN
A67: ="DEC-"&B67&"-G5" -> DEC-MTH-ET-CHA-L2-G5 | B67: ='Lot Register'!A15 -> MTH-ET-CHA-L2 | C67: ='Lot Register'!B15 -> Method lineage | D67: ='Lot Register'!D15 -> MS-ET | E67: ='Lot Register'!G15 -> ST-ET-CHA | F67: G5 | G67: COMMISSION | H67: root-native commissioning closes | I67: Commissioning authority | J67: SOURCE EMPTY | K67: =Controls!B26 -> 0 | L67: =IF(K67=1,"PASS","OPEN") -> OPEN
A68: ="DEC-"&B68&"-G6" -> DEC-MTH-ET-CHA-L2-G6 | B68: ='Lot Register'!A15 -> MTH-ET-CHA-L2 | C68: ='Lot Register'!B15 -> Method lineage | D68: ='Lot Register'!D15 -> MS-ET | E68: ='Lot Register'!G15 -> ST-ET-CHA | F68: G6 | G68: DENIAL | H68: controlled denial or destructive witness is valid | I68: Evidence Court | J68: SOURCE EMPTY | K68: =Controls!B26 -> 0 | L68: =IF(K68=1,"PASS","OPEN") -> OPEN
A69: ="DEC-"&B69&"-G7" -> DEC-MTH-ET-CHA-L2-G7 | B69: ='Lot Register'!A15 -> MTH-ET-CHA-L2 | C69: ='Lot Register'!B15 -> Method lineage | D69: ='Lot Register'!D15 -> MS-ET | E69: ='Lot Register'!G15 -> ST-ET-CHA | F69: G7 | G69: COLD RETURN | H69: outside team reconstructs accepted state | I69: Evidence Court | J69: SOURCE EMPTY | K69: =Controls!B26 -> 0 | L69: =IF(K69=1,"PASS","OPEN") -> OPEN
A70: ="DEC-"&B70&"-G1" -> DEC-REG-ET-CHA-G1 | B70: ='Lot Register'!A16 -> REG-ET-CHA | C70: ='Lot Register'!B16 -> Regeneration tool | D70: ='Lot Register'!D16 -> MS-ET | E70: ='Lot Register'!G16 -> ST-ET-CHA | F70: G1 | G70: IDENTITY | H70: identity and beneficial control admissible | I70: Control registrar | J70: SOURCE EMPTY | K70: =Controls!B26 -> 0 | L70: =IF(K70=1,"PASS","OPEN") -> OPEN
A71: ="DEC-"&B71&"-G2" -> DEC-REG-ET-CHA-G2 | B71: ='Lot Register'!A16 -> REG-ET-CHA | C71: ='Lot Register'!B16 -> Regeneration tool | D71: ='Lot Register'!D16 -> MS-ET | E71: ='Lot Register'!G16 -> ST-ET-CHA | F71: G2 | G71: BASELINE | H71: issue baseline frozen without builder conversion | I71: Requirement issuer | J71: SOURCE EMPTY | K71: =Controls!B26 -> 0 | L71: =IF(K71=1,"PASS","OPEN") -> OPEN
A72: ="DEC-"&B72&"-G3" -> DEC-REG-ET-CHA-G3 | B72: ='Lot Register'!A16 -> REG-ET-CHA | C72: ='Lot Register'!B16 -> Regeneration tool | D72: ='Lot Register'!D16 -> MS-ET | E72: ='Lot Register'!G16 -> ST-ET-CHA | F72: G3 | G72: AS-BUILT | H72: materials, interfaces and as-built state reconcile | I72: Commissioning authority | J72: SOURCE EMPTY | K72: =Controls!B26 -> 0 | L72: =IF(K72=1,"PASS","OPEN") -> OPEN
A73: ="DEC-"&B73&"-G4" -> DEC-REG-ET-CHA-G4 | B73: ='Lot Register'!A16 -> REG-ET-CHA | C73: ='Lot Register'!B16 -> Regeneration tool | D73: ='Lot Register'!D16 -> MS-ET | E73: ='Lot Register'!G16 -> ST-ET-CHA | F73: G4 | G73: ISOLATION | H73: no forbidden common decisive path | I73: Control registrar | J73: SOURCE EMPTY | K73: =Controls!B26 -> 0 | L73: =IF(K73=1,"PASS","OPEN") -> OPEN
A74: ="DEC-"&B74&"-G5" -> DEC-REG-ET-CHA-G5 | B74: ='Lot Register'!A16 -> REG-ET-CHA | C74: ='Lot Register'!B16 -> Regeneration tool | D74: ='Lot Register'!D16 -> MS-ET | E74: ='Lot Register'!G16 -> ST-ET-CHA | F74: G5 | G74: COMMISSION | H74: root-native commissioning closes | I74: Commissioning authority | J74: SOURCE EMPTY | K74: =Controls!B26 -> 0 | L74: =IF(K74=1,"PASS","OPEN") -> OPEN
A75: ="DEC-"&B75&"-G6" -> DEC-REG-ET-CHA-G6 | B75: ='Lot Register'!A16 -> REG-ET-CHA | C75: ='Lot Register'!B16 -> Regeneration tool | D75: ='Lot Register'!D16 -> MS-ET | E75: ='Lot Register'!G16 -> ST-ET-CHA | F75: G6 | G75: DENIAL | H75: controlled denial or destructive witness is valid | I75: Evidence Court | J75: SOURCE EMPTY | K75: =Controls!B26 -> 0 | L75: =IF(K75=1,"PASS","OPEN") -> OPEN
A76: ="DEC-"&B76&"-G7" -> DEC-REG-ET-CHA-G7 | B76: ='Lot Register'!A16 -> REG-ET-CHA | C76: ='Lot Register'!B16 -> Regeneration tool | D76: ='Lot Register'!D16 -> MS-ET | E76: ='Lot Register'!G16 -> ST-ET-CHA | F76: G7 | G76: COLD RETURN | H76: outside team reconstructs accepted state | I76: Evidence Court | J76: SOURCE EMPTY | K76: =Controls!B26 -> 0 | L76: =IF(K76=1,"PASS","OPEN") -> OPEN
A77: ="DEC-"&B77&"-G1" -> DEC-INT-ET-CHA-G1 | B77: ='Lot Register'!A17 -> INT-ET-CHA | C77: ='Lot Register'!B17 -> Station integration | D77: ='Lot Register'!D17 -> MS-ET | E77: ='Lot Register'!G17 -> ST-ET-CHA | F77: G1 | G77: IDENTITY | H77: identity and beneficial control admissible | I77: Control registrar | J77: SOURCE EMPTY | K77: =Controls!B26 -> 0 | L77: =IF(K77=1,"PASS","OPEN") -> OPEN
A78: ="DEC-"&B78&"-G2" -> DEC-INT-ET-CHA-G2 | B78: ='Lot Register'!A17 -> INT-ET-CHA | C78: ='Lot Register'!B17 -> Station integration | D78: ='Lot Register'!D17 -> MS-ET | E78: ='Lot Register'!G17 -> ST-ET-CHA | F78: G2 | G78: BASELINE | H78: issue baseline frozen without builder conversion | I78: Requirement issuer | J78: SOURCE EMPTY | K78: =Controls!B26 -> 0 | L78: =IF(K78=1,"PASS","OPEN") -> OPEN
A79: ="DEC-"&B79&"-G3" -> DEC-INT-ET-CHA-G3 | B79: ='Lot Register'!A17 -> INT-ET-CHA | C79: ='Lot Register'!B17 -> Station integration | D79: ='Lot Register'!D17 -> MS-ET | E79: ='Lot Register'!G17 -> ST-ET-CHA | F79: G3 | G79: AS-BUILT | H79: materials, interfaces and as-built state reconcile | I79: Commissioning authority | J79: SOURCE EMPTY | K79: =Controls!B26 -> 0 | L79: =IF(K79=1,"PASS","OPEN") -> OPEN
A80: ="DEC-"&B80&"-G4" -> DEC-INT-ET-CHA-G4 | B80: ='Lot Register'!A17 -> INT-ET-CHA | C80: ='Lot Register'!B17 -> Station integration | D80: ='Lot Register'!D17 -> MS-ET | E80: ='Lot Register'!G17 -> ST-ET-CHA | F80: G4 | G80: ISOLATION | H80: no forbidden common decisive path | I80: Control registrar | J80: SOURCE EMPTY | K80: =Controls!B26 -> 0 | L80: =IF(K80=1,"PASS","OPEN") -> OPEN
A81: ="DEC-"&B81&"-G5" -> DEC-INT-ET-CHA-G5 | B81: ='Lot Register'!A17 -> INT-ET-CHA | C81: ='Lot Register'!B17 -> Station integration | D81: ='Lot Register'!D17 -> MS-ET | E81: ='Lot Register'!G17 -> ST-ET-CHA | F81: G5 | G81: COMMISSION | H81: root-native commissioning closes | I81: Commissioning authority | J81: SOURCE EMPTY | K81: =Controls!B26 -> 0 | L81: =IF(K81=1,"PASS","OPEN") -> OPEN
A82: ="DEC-"&B82&"-G6" -> DEC-INT-ET-CHA-G6 | B82: ='Lot Register'!A17 -> INT-ET-CHA | C82: ='Lot Register'!B17 -> Station integration | D82: ='Lot Register'!D17 -> MS-ET | E82: ='Lot Register'!G17 -> ST-ET-CHA | F82: G6 | G82: DENIAL | H82: controlled denial or destructive witness is valid | I82: Evidence Court | J82: SOURCE EMPTY | K82: =Controls!B26 -> 0 | L82: =IF(K82=1,"PASS","OPEN") -> OPEN
A83: ="DEC-"&B83&"-G7" -> DEC-INT-ET-CHA-G7 | B83: ='Lot Register'!A17 -> INT-ET-CHA | C83: ='Lot Register'!B17 -> Station integration | D83: ='Lot Register'!D17 -> MS-ET | E83: ='Lot Register'!G17 -> ST-ET-CHA | F83: G7 | G83: COLD RETURN | H83: outside team reconstructs accepted state | I83: Evidence Court | J83: SOURCE EMPTY | K83: =Controls!B26 -> 0 | L83: =IF(K83=1,"PASS","OPEN") -> OPEN
A84: ="DEC-"&B84&"-G1" -> DEC-RIG-ET-CON-G1 | B84: ='Lot Register'!A18 -> RIG-ET-CON | C84: ='Lot Register'!B18 -> Root-native rig | D84: ='Lot Register'!D18 -> MS-ET | E84: ='Lot Register'!G18 -> ST-ET-CON | F84: G1 | G84: IDENTITY | H84: identity and beneficial control admissible | I84: Control registrar | J84: SOURCE EMPTY | K84: =Controls!B26 -> 0 | L84: =IF(K84=1,"PASS","OPEN") -> OPEN
A85: ="DEC-"&B85&"-G2" -> DEC-RIG-ET-CON-G2 | B85: ='Lot Register'!A18 -> RIG-ET-CON | C85: ='Lot Register'!B18 -> Root-native rig | D85: ='Lot Register'!D18 -> MS-ET | E85: ='Lot Register'!G18 -> ST-ET-CON | F85: G2 | G85: BASELINE | H85: issue baseline frozen without builder conversion | I85: Requirement issuer | J85: SOURCE EMPTY | K85: =Controls!B26 -> 0 | L85: =IF(K85=1,"PASS","OPEN") -> OPEN
A86: ="DEC-"&B86&"-G3" -> DEC-RIG-ET-CON-G3 | B86: ='Lot Register'!A18 -> RIG-ET-CON | C86: ='Lot Register'!B18 -> Root-native rig | D86: ='Lot Register'!D18 -> MS-ET | E86: ='Lot Register'!G18 -> ST-ET-CON | F86: G3 | G86: AS-BUILT | H86: materials, interfaces and as-built state reconcile | I86: Commissioning authority | J86: SOURCE EMPTY | K86: =Controls!B26 -> 0 | L86: =IF(K86=1,"PASS","OPEN") -> OPEN
A87: ="DEC-"&B87&"-G4" -> DEC-RIG-ET-CON-G4 | B87: ='Lot Register'!A18 -> RIG-ET-CON | C87: ='Lot Register'!B18 -> Root-native rig | D87: ='Lot Register'!D18 -> MS-ET | E87: ='Lot Register'!G18 -> ST-ET-CON | F87: G4 | G87: ISOLATION | H87: no forbidden common decisive path | I87: Control registrar | J87: SOURCE EMPTY | K87: =Controls!B26 -> 0 | L87: =IF(K87=1,"PASS","OPEN") -> OPEN
A88: ="DEC-"&B88&"-G5" -> DEC-RIG-ET-CON-G5 | B88: ='Lot Register'!A18 -> RIG-ET-CON | C88: ='Lot Register'!B18 -> Root-native rig | D88: ='Lot Register'!D18 -> MS-ET | E88: ='Lot Register'!G18 -> ST-ET-CON | F88: G5 | G88: COMMISSION | H88: root-native commissioning closes | I88: Commissioning authority | J88: SOURCE EMPTY | K88: =Controls!B26 -> 0 | L88: =IF(K88=1,"PASS","OPEN") -> OPEN
A89: ="DEC-"&B89&"-G6" -> DEC-RIG-ET-CON-G6 | B89: ='Lot Register'!A18 -> RIG-ET-CON | C89: ='Lot Register'!B18 -> Root-native rig | D89: ='Lot Register'!D18 -> MS-ET | E89: ='Lot Register'!G18 -> ST-ET-CON | F89: G6 | G89: DENIAL | H89: controlled denial or destructive witness is valid | I89: Evidence Court | J89: SOURCE EMPTY | K89: =Controls!B26 -> 0 | L89: =IF(K89=1,"PASS","OPEN") -> OPEN
A90: ="DEC-"&B90&"-G7" -> DEC-RIG-ET-CON-G7 | B90: ='Lot Register'!A18 -> RIG-ET-CON | C90: ='Lot Register'!B18 -> Root-native rig | D90: ='Lot Register'!D18 -> MS-ET | E90: ='Lot Register'!G18 -> ST-ET-CON | F90: G7 | G90: COLD RETURN | H90: outside team reconstructs accepted state | I90: Evidence Court | J90: SOURCE EMPTY | K90: =Controls!B26 -> 0 | L90: =IF(K90=1,"PASS","OPEN") -> OPEN
A91: ="DEC-"&B91&"-G1" -> DEC-MTH-ET-CON-L1-G1 | B91: ='Lot Register'!A19 -> MTH-ET-CON-L1 | C91: ='Lot Register'!B19 -> Method lineage | D91: ='Lot Register'!D19 -> MS-ET | E91: ='Lot Register'!G19 -> ST-ET-CON | F91: G1 | G91: IDENTITY | H91: identity and beneficial control admissible | I91: Control registrar | J91: SOURCE EMPTY | K91: =Controls!B26 -> 0 | L91: =IF(K91=1,"PASS","OPEN") -> OPEN
A92: ="DEC-"&B92&"-G2" -> DEC-MTH-ET-CON-L1-G2 | B92: ='Lot Register'!A19 -> MTH-ET-CON-L1 | C92: ='Lot Register'!B19 -> Method lineage | D92: ='Lot Register'!D19 -> MS-ET | E92: ='Lot Register'!G19 -> ST-ET-CON | F92: G2 | G92: BASELINE | H92: issue baseline frozen without builder conversion | I92: Requirement issuer | J92: SOURCE EMPTY | K92: =Controls!B26 -> 0 | L92: =IF(K92=1,"PASS","OPEN") -> OPEN
A93: ="DEC-"&B93&"-G3" -> DEC-MTH-ET-CON-L1-G3 | B93: ='Lot Register'!A19 -> MTH-ET-CON-L1 | C93: ='Lot Register'!B19 -> Method lineage | D93: ='Lot Register'!D19 -> MS-ET | E93: ='Lot Register'!G19 -> ST-ET-CON | F93: G3 | G93: AS-BUILT | H93: materials, interfaces and as-built state reconcile | I93: Commissioning authority | J93: SOURCE EMPTY | K93: =Controls!B26 -> 0 | L93: =IF(K93=1,"PASS","OPEN") -> OPEN
A94: ="DEC-"&B94&"-G4" -> DEC-MTH-ET-CON-L1-G4 | B94: ='Lot Register'!A19 -> MTH-ET-CON-L1 | C94: ='Lot Register'!B19 -> Method lineage | D94: ='Lot Register'!D19 -> MS-ET | E94: ='Lot Register'!G19 -> ST-ET-CON | F94: G4 | G94: ISOLATION | H94: no forbidden common decisive path | I94: Control registrar | J94: SOURCE EMPTY | K94: =Controls!B26 -> 0 | L94: =IF(K94=1,"PASS","OPEN") -> OPEN
A95: ="DEC-"&B95&"-G5" -> DEC-MTH-ET-CON-L1-G5 | B95: ='Lot Register'!A19 -> MTH-ET-CON-L1 | C95: ='Lot Register'!B19 -> Method lineage | D95: ='Lot Register'!D19 -> MS-ET | E95: ='Lot Register'!G19 -> ST-ET-CON | F95: G5 | G95: COMMISSION | H95: root-native commissioning closes | I95: Commissioning authority | J95: SOURCE EMPTY | K95: =Controls!B26 -> 0 | L95: =IF(K95=1,"PASS","OPEN") -> OPEN
A96: ="DEC-"&B96&"-G6" -> DEC-MTH-ET-CON-L1-G6 | B96: ='Lot Register'!A19 -> MTH-ET-CON-L1 | C96: ='Lot Register'!B19 -> Method lineage | D96: ='Lot Register'!D19 -> MS-ET | E96: ='Lot Register'!G19 -> ST-ET-CON | F96: G6 | G96: DENIAL | H96: controlled denial or destructive witness is valid | I96: Evidence Court | J96: SOURCE EMPTY | K96: =Controls!B26 -> 0 | L96: =IF(K96=1,"PASS","OPEN") -> OPEN
A97: ="DEC-"&B97&"-G7" -> DEC-MTH-ET-CON-L1-G7 | B97: ='Lot Register'!A19 -> MTH-ET-CON-L1 | C97: ='Lot Register'!B19 -> Method lineage | D97: ='Lot Register'!D19 -> MS-ET | E97: ='Lot Register'!G19 -> ST-ET-CON | F97: G7 | G97: COLD RETURN | H97: outside team reconstructs accepted state | I97: Evidence Court | J97: SOURCE EMPTY | K97: =Controls!B26 -> 0 | L97: =IF(K97=1,"PASS","OPEN") -> OPEN
A98: ="DEC-"&B98&"-G1" -> DEC-MTH-ET-CON-L2-G1 | B98: ='Lot Register'!A20 -> MTH-ET-CON-L2 | C98: ='Lot Register'!B20 -> Method lineage | D98: ='Lot Register'!D20 -> MS-ET | E98: ='Lot Register'!G20 -> ST-ET-CON | F98: G1 | G98: IDENTITY | H98: identity and beneficial control admissible | I98: Control registrar | J98: SOURCE EMPTY | K98: =Controls!B26 -> 0 | L98: =IF(K98=1,"PASS","OPEN") -> OPEN
A99: ="DEC-"&B99&"-G2" -> DEC-MTH-ET-CON-L2-G2 | B99: ='Lot Register'!A20 -> MTH-ET-CON-L2 | C99: ='Lot Register'!B20 -> Method lineage | D99: ='Lot Register'!D20 -> MS-ET | E99: ='Lot Register'!G20 -> ST-ET-CON | F99: G2 | G99: BASELINE | H99: issue baseline frozen without builder conversion | I99: Requirement issuer | J99: SOURCE EMPTY | K99: =Controls!B26 -> 0 | L99: =IF(K99=1,"PASS","OPEN") -> OPEN
A100: ="DEC-"&B100&"-G3" -> DEC-MTH-ET-CON-L2-G3 | B100: ='Lot Register'!A20 -> MTH-ET-CON-L2 | C100: ='Lot Register'!B20 -> Method lineage | D100: ='Lot Register'!D20 -> MS-ET | E100: ='Lot Register'!G20 -> ST-ET-CON | F100: G3 | G100: AS-BUILT | H100: materials, interfaces and as-built state reconcile | I100: Commissioning authority | J100: SOURCE EMPTY | K100: =Controls!B26 -> 0 | L100: =IF(K100=1,"PASS","OPEN") -> OPEN
A101: ="DEC-"&B101&"-G4" -> DEC-MTH-ET-CON-L2-G4 | B101: ='Lot Register'!A20 -> MTH-ET-CON-L2 | C101: ='Lot Register'!B20 -> Method lineage | D101: ='Lot Register'!D20 -> MS-ET | E101: ='Lot Register'!G20 -> ST-ET-CON | F101: G4 | G101: ISOLATION | H101: no forbidden common decisive path | I101: Control registrar | J101: SOURCE EMPTY | K101: =Controls!B26 -> 0 | L101: =IF(K101=1,"PASS","OPEN") -> OPEN
A102: ="DEC-"&B102&"-G5" -> DEC-MTH-ET-CON-L2-G5 | B102: ='Lot Register'!A20 -> MTH-ET-CON-L2 | C102: ='Lot Register'!B20 -> Method lineage | D102: ='Lot Register'!D20 -> MS-ET | E102: ='Lot Register'!G20 -> ST-ET-CON | F102: G5 | G102: COMMISSION | H102: root-native commissioning closes | I102: Commissioning authority | J102: SOURCE EMPTY | K102: =Controls!B26 -> 0 | L102: =IF(K102=1,"PASS","OPEN") -> OPEN
A103: ="DEC-"&B103&"-G6" -> DEC-MTH-ET-CON-L2-G6 | B103: ='Lot Register'!A20 -> MTH-ET-CON-L2 | C103: ='Lot Register'!B20 -> Method lineage | D103: ='Lot Register'!D20 -> MS-ET | E103: ='Lot Register'!G20 -> ST-ET-CON | F103: G6 | G103: DENIAL | H103: controlled denial or destructive witness is valid | I103: Evidence Court | J103: SOURCE EMPTY | K103: =Controls!B26 -> 0 | L103: =IF(K103=1,"PASS","OPEN") -> OPEN
...

Sheet Release Sequence
A2: Seven-step construction release sequence
A4: R3 is a compound cohort: no system, station role or method lineage may receive an isolated advantage from early release.
A6: Step | B6: Name | C6: Object released | D6: Entry condition | E6: Exit product | F6: Forbidden conversion | G6: Payment boundary | H6: Current state
A7: R0 | B7: CONSTITUTE | C7: 102 empty lot records | D7: A2C-3 closes | E7: complete lot grammar | F7: lot record to award | G7: none | H7: CLOSED
A8: R1 | B8: CONTROL FREEZE | C8: national control and dependency map | D8: all identities supplied later | E8: collision-free national slate | F8: partial slate to independence | G8: none | H8: HELD
A9: R2 | B9: BOUNDARY BUILD | C9: six substrate packages | D9: R1 closed | E9: accepted nondecisive boundaries | F9: civil works to technical root | G9: public FRAME/MAKE | H9: HELD
A10: R3 | B10: DECISIVE BUILD | C10: 72 decisive public + 6 private candidate lots | D10: all six system cohorts issue together | E10: native as-built objects | F10: one system or role advances alone | G10: public/candidate FRAME/MAKE | H10: HELD
A11: R4 | B11: INTEGRATE | C11: eighteen station integration lots | D11: incoming as-built states accepted | E11: verified public interfaces | F11: integration changes native object | G11: public FRAME/MAKE | H11: HELD
A12: R5 | B12: BREAK | C12: station and system interlocks | D12: all construction gates through commission | E12: valid denial evidence | F12: favorable result to acceptance | G12: candidate BREAK only | H12: HELD
A13: R6 | B13: COLD RETURN | C13: outside reconstruction and regeneration | D13: valid event and sealed custody | E13: transferable accepted state | F13: builder replay to outside reproduction | G13: TRANSFER | H13: HELD

Sheet Payment Schedule
A2: Payment law and maximum-loss exposure
A4: Public BREAK is evidentiary and pays zero incremental construction money. Private valid adverse evidence remains payable and binding.
A6: Class | B6: Funding | C6: Authority USD B | D6: FRAME % | E6: MAKE % | F6: BREAK % | G6: TRANSFER % | H6: Through MAKE USD B | I6: Through BREAK USD B | J6: Full USD B | K6: Current obligation | L6: Current payment
A7: Civil substrate | B7: Public | C7: 0.72 | D7: 0.25 | E7: 0.5 | F7: 0 | G7: 0.25 | H7: =C7*(D7+E7) -> 0.54 | I7: =C7*(D7+E7+F7) -> 0.54 | J7: =C7 -> 0.72 | K7: =Controls!B23 -> 0 | L7: =Controls!B24 -> 0
A8: Root-native rig | B8: Public | C8: 5.7 | D8: 0.25 | E8: 0.5 | F8: 0 | G8: 0.25 | H8: =C8*(D8+E8) -> 4.275 | I8: =C8*(D8+E8+F8) -> 4.275 | J8: =C8 -> 5.7 | K8: =Controls!B23 -> 0 | L8: =Controls!B24 -> 0
A9: Method lineage | B9: Public | C9: 3.24 | D9: 0.25 | E9: 0.5 | F9: 0 | G9: 0.25 | H9: =C9*(D9+E9) -> 2.43 | I9: =C9*(D9+E9+F9) -> 2.43 | J9: =C9 -> 3.24 | K9: =Controls!B23 -> 0 | L9: =Controls!B24 -> 0
A10: Regeneration tool | B10: Public | C10: 1.2 | D10: 0.25 | E10: 0.5 | F10: 0 | G10: 0.25 | H10: =C10*(D10+E10) -> 0.9 | I10: =C10*(D10+E10+F10) -> 0.9 | J10: =C10 -> 1.2 | K10: =Controls!B23 -> 0 | L10: =Controls!B24 -> 0
A11: Station integration | B11: Public | C11: 1.14 | D11: 0.25 | E11: 0.5 | F11: 0 | G11: 0.25 | H11: =C11*(D11+E11) -> 0.855 | I11: =C11*(D11+E11+F11) -> 0.855 | J11: =C11 -> 1.14 | K11: =Controls!B23 -> 0 | L11: =Controls!B24 -> 0
A12: Candidate mechanism | B12: Private option | C12: 3.5869128 | D12: 0.15 | E12: 0.35 | F12: 0.35 | G12: 0.15 | H12: =C12*(D12+E12) -> 1.7934564 | I12: =C12*(D12+E12+F12) -> 3.0488759 | J12: =C12 -> 3.5869128 | K12: =Controls!B23 -> 0 | L12: =Controls!B24 -> 0
A13: TOTAL | B13: mixed | C13: =SUM(C7:C12) -> 15.586913 | H13: =SUM(H7:H12) -> 10.793456 | I13: =SUM(I7:I12) -> 12.048876 | J13: =SUM(J7:J12) -> 15.586913 | K13: =SUM(K7:K12) -> 0 | L13: =SUM(L7:L12) -> 0
A17: Outcome | B17: Paid USD B | C17: Unreleased USD B | D17: Meaning
A18: through MAKE | B18: =H13 -> 10.793456 | C18: =J13-B18 -> 4.7934564 | D18: maximum exposure before destructive evidence
A19: all-six valid kill at BREAK | B19: =SUM(H7:H11)+I12 -> 12.048876 | C19: =J13-B19 -> 3.5380369 | D19: public construction through MAKE plus candidate through BREAK
A20: all transfer | B20: =J13 -> 15.586913 | C20: =J13-B20 -> 0 | D20: complete accepted transfer
A21: current | B21: =L13 -> 0 | C21: =J13-B21 -> 15.586913 | D21: no artifact accepted

Sheet Authority Separation
A2: Six acceptance authorities with nonconvertible signatures
A4: No builder, station integrator or authority may sign the state it creates. Disagreement holds the lot; it does not escalate to a universal technical superior.
A6: Authority | B6: Owns | C6: Must receive | D6: May sign | E6: Cannot sign or create | F6: Builder overlap | G6: State
A7: Requirement issuer | B7: public requirement and issue baseline | C7: enacted service vector | D7: configuration packet and G2 | E7: physical truth, ownership admissibility or payment | F7: NO | G7: CONSTITUTED
A8: Control registrar | B8: beneficial-control and dependency graph | C8: complete ownership, debt, tool and key declarations | D8: control packet, G1 and G4 | E8: technical performance or favorable disposition | F8: NO | G8: CONSTITUTED
A9: Commissioning authority | B9: native metrology and as-built comparison | C9: sealed calibration and material records | D9: metrology packet, G3 and G5 | E9: requirement change or evidentiary result | F9: NO | G9: CONSTITUTED
A10: Safety and rights authority | B10: people, environment, residual and safe stop | C10: worker, receiver and property protections | D10: safety packet and work suspension | E10: candidate completion or effect | F10: NO | G10: CONSTITUTED
A11: Evidence Court | B11: event validity, custody and cold reconstruction | C11: sealed observations and outside-team record | D11: reconstruction packet, G6 and G7 | E11: award, obligation or favorable reinterpretation | F11: NO | G11: CONSTITUTED
A12: Comptroller | B12: obligation and payment against accepted artifacts | C12: valid signatures and payment schedule | D12: fund release only | E12: technical acceptance, evidence or capability | F12: NO | G12: CONSTITUTED

Sheet Industrial Base
A2: First-wave sovereign construction industries
A4: The analogue of a defense prime is a deep capability house inside one causal domain, not a universal resilience integrator.
A6: Field | B6: What must become industrially repeatable | C6: Why ordinary procurement is insufficient | D6: Permitted scale | E6: Forbidden convergence | F6: First physical customer
A7: dynamic marine exchange | B7: moving-load, compliant-interface and dry-custody truth bodies | C7: a static quay cannot reproduce coupled motion and transfer | D7: national specialist | E7: candidate plus truth train | F7: ET stations
A8: occupied-building insertion | B8: sacrificial building sectors, live utility trunks and reversible anchors | C8: laboratory benches omit occupancy, propagation and egress | D8: national specialist | E8: common autonomy stack | F8: CT stations
A9: atmospheric source fields | B9: kilometre-scale heat, plume, ember and deposition corridors | C9: airframe certification does not prove landscape effect | D9: national specialist | E9: common sensing-control root | F9: HC stations
A10: heat-water truth bodies | B10: live subsurface, firm bus, treatment and residual chain | C10: component tests erase geology and coupled products | D10: national specialist | E10: shared source model | F10: LF stations
A11: clinical-load synthesis | B11: complete acuity, utility, staffing, supply and discharge worlds | C11: bed counts omit metabolism and downstream care | D11: national specialist | E11: hospital-brand acceptance | F11: HU stations
A12: disconnected metrology | B12: coupon-to-qualified-part production and portable certification | C12: factory output does not prove field recertification | D12: national specialist | E12: networked trust service | F12: RT stations
A13: destructive reconstruction | B13: teardown, forensic state, rebuild and cold replay | C13: maintenance contracts optimize return rather than falsification | D13: cross-system within caps | E13: candidate-controlled repair | F13: all stations
A14: public-boundary integration | B14: reversible civil interfaces without technical influence | C14: ordinary EPC practice seeks whole-system optimization | D14: national boundary house | E14: decisive control | F14: all stations

Sheet Stress Tests
A2: Acquisition and control stress cases
A4: The slate is valid only if it remains separable after corporate change, failure, schedule pressure and destructive physical evidence.
A6: ID | B6: Disturbance | C6: Required response | D6: Forbidden conversion | E6: Disposition | F6: State
A7: S01 | B7: one parent acquires two Root Houses | C7: reopen national slate and divest one | D7: brands to independence | E7: REJECT | F7: PASS
A8: S02 | B8: decisive controller wins third lot | C8: award to collision-free alternate | D8: price to waiver | E8: REJECT | F8: PASS
A9: S03 | B9: L1 and L2 share calibration compiler | C9: classify compiler as decisive and split | D9: software license to plurality | E9: REBUILD | F9: PASS
A10: S04 | B10: rig and regeneration share debt covenant | C10: treat as common control | D10: separate subsidiaries to independence | E10: REJECT | F10: PASS
A11: S05 | B11: substrate utility conditions candidate input | C11: reclassify and split utility | D11: public boundary to technical root | E11: REBUILD | F11: PASS
A12: S06 | B12: integrator changes safeing threshold | C12: restore native baseline and invalidate work | D12: interface assembly to design authority | E12: INVALID | F12: PASS
A13: S07 | B13: one system is ready early | C13: hold compound R3 release | D13: schedule to isolated advantage | E13: HOLD | F13: PASS
A14: S08 | B14: valid candidate failure at BREAK | C14: pay evidence and bind kill | D14: failure to nonperformance | E14: KILL ROOT | F14: PASS
A15: S09 | B15: construction packet is incomplete but test succeeds | C15: hold lot and event | D15: outcome to as-built acceptance | E15: HOLD | F15: PASS
A16: S10 | B16: common accepting office signs three states | C16: separate signatures and repeat decisions | D16: administrative efficiency to truth | E16: INVALID | F16: PASS
A17: S11 | B17: site identity enters solicitation | C17: return to source-independent site class | D17: envelope to location | E17: SOURCE EMPTY | F17: PASS
... A22: S16 | B22: exterior rendering requested | C22: retain functional envelopes only | D22: lot constitution to platform form | E22: HELD | F22: PASS

Sheet Mutations
A2: Live mutation and restoration log
A4: Each mutation changes one authoritative control, forces at least one terminal audit to fail, then restores the passing baseline before export.
A6: ID | B6: Control cell | C6: Baseline | D6: Mutated | E6: Audit failures | F6: Mutation detected | G6: Baseline restored
A7: M01 | B7: Controls!B7 | C7: 12 | D7: 13 | E7: 2 | F7: YES | G7: YES
A8: M02 | B8: Controls!B8 | C8: 3.5869128 | D8: 4 | E8: 2 | F8: YES | G8: YES
A9: M03 | B9: Controls!B9 | C9: 6 | D9: 5 | E9: 2 | F9: YES | G9: YES
A10: M04 | B10: Controls!B10 | C10: 3 | D10: 2 | E10: 2 | F10: YES | G10: YES
A11: M05 | B11: Controls!B11 | C11: 6 | D11: 5 | E11: 1 | F11: YES | G11: YES
A12: M06 | B12: Controls!B12 | C12: 18 | D12: 17 | E12: 1 | F12: YES | G12: YES
A13: M07 | B13: Controls!B13 | C13: 36 | D13: 35 | E13: 1 | F13: YES | G13: YES
A14: M08 | B14: Controls!B14 | C14: 18 | D14: 17 | E14: 1 | F14: YES | G14: YES
A15: M09 | B15: Controls!B15 | C15: 18 | D15: 17 | E15: 1 | F15: YES | G15: YES
A16: M10 | B16: Controls!B16 | C16: 6 | D16: 5 | E16: 1 | F16: YES | G16: YES
A17: M11 | B17: Controls!B17 | C17: 48 | D17: 47 | E17: 1 | F17: YES | G17: YES
A18: M12 | B18: Controls!B18 | C18: 5 | D18: 4 | E18: 2 | F18: YES | G18: YES
... A24: M18 | B24: Controls!B28 | C24: 0 | D24: 1 | E24: 1 | F24: YES | G24: YES

Sheet Audit
A2: Terminal structural and numerical audit
A4: The audit tests the constituted model. It does not create sites, firms, awards, physical evidence, payment, capability or rendering authority.
A6: Audit | B6: Observed | C6: Expected | D6: Difference | E6: State
A7: public reserve | B7: =Controls!B7 -> 12 | C7: 12 | D7: =B7-C7 -> 0 | E7: =IF(ABS(D7)<0.000001,"PASS","FAIL") -> PASS
A8: private options | B8: =Controls!B8 -> 3.5869128 | C8: 3.5869128 | D8: =B8-C8 -> 0 | E8: =IF(ABS(D8)<0.000001,"PASS","FAIL") -> PASS
A9: combined ceiling | B9: =Controls!B7+Controls!B8 -> 15.586913 | C9: 15.586913 | D9: =B9-C9 -> 0 | E9: =IF(ABS(D9)<0.000001,"PASS","FAIL") -> PASS
A10: systems | B10: =Controls!B9 -> 6 | C10: 6 | D10: =B10-C10 -> 0 | E10: =IF(ABS(D10)<0.000001,"PASS","FAIL") -> PASS
A11: roles per system | B11: =Controls!B10 -> 3 | C11: 3 | D11: =B11-C11 -> 0 | E11: =IF(ABS(D11)<0.000001,"PASS","FAIL") -> PASS
A12: stations arithmetic | B12: =Controls!B9*Controls!B10 -> 18 | C12: 18 | D12: =B12-C12 -> 0 | E12: =IF(ABS(D12)<0.000001,"PASS","FAIL") -> PASS
A13: substrate lots | B13: =Controls!B11 -> 6 | C13: 6 | D13: =B13-C13 -> 0 | E13: =IF(ABS(D13)<0.000001,"PASS","FAIL") -> PASS
A14: rig lots | B14: =Controls!B12 -> 18 | C14: 18 | D14: =B14-C14 -> 0 | E14: =IF(ABS(D14)<0.000001,"PASS","FAIL") -> PASS
A15: method lots | B15: =Controls!B13 -> 36 | C15: 36 | D15: =B15-C15 -> 0 | E15: =IF(ABS(D15)<0.000001,"PASS","FAIL") -> PASS
A16: regeneration lots | B16: =Controls!B14 -> 18 | C16: 18 | D16: =B16-C16 -> 0 | E16: =IF(ABS(D16)<0.000001,"PASS","FAIL") -> PASS
A17: integration lots | B17: =Controls!B15 -> 18 | C17: 18 | D17: =B17-C17 -> 0 | E17: =IF(ABS(D17)<0.000001,"PASS","FAIL") -> PASS
A18: candidate lots | B18: =Controls!B16 -> 6 | C18: 6 | D18: =B18-C18 -> 0 | E18: =IF(ABS(D18)<0.000001,"PASS","FAIL") -> PASS
A19: class lots total | B19: ='Lot Classes'!D13 -> 102 | C19: 102 | D19: =B19-C19 -> 0 | E19: =IF(ABS(D19)<0.000001,"PASS","FAIL") -> PASS
A20: lot register rows | B20: =COUNTA('Lot Register'!A7:A108) -> 102 | C20: 102 | D20: =B20-C20 -> 0 | E20: =IF(ABS(D20)<0.000001,"PASS","FAIL") -> PASS
A21: public lot rows | B21: =COUNTIF('Lot Register'!C7:C108,"Public") -> 96 | C21: 96 | D21: =B21-C21 -> 0 | E21: =IF(ABS(D21)<0.000001,"PASS","FAIL") -> PASS
A22: private lot rows | B22: =COUNTIF('Lot Register'!C7:C108,"Private option") -> 6 | C22: 6 | D22: =B22-C22 -> 0 | E22: =IF(ABS(D22)<0.000001,"PASS","FAIL") -> PASS
A23: public authority | B23: =SUM('Lot Classes'!E7:E11) -> 12 | C23: 12 | D23: =B23-C23 -> 0 | E23: =IF(ABS(D23)<0.000001,"PASS","FAIL") -> PASS
A24: private authority | B24: ='Lot Classes'!E12 -> 3.5869128 | C24: 3.5869128 | D24: =B24-C24 -> 0 | E24: =IF(ABS(D24)<0.000001,"PASS","FAIL") -> PASS
A25: class authority total | B25: ='Lot Classes'!E13 -> 15.586913 | C25: 15.586913 | D25: =B25-C25 -> 0 | E25: =IF(ABS(D25)<0.000001,"PASS","FAIL") -> PASS
A26: lot authority total | B26: =SUM('Lot Register'!K7:K108) -> 15.586913 | C26: 15.586913 | D26: =B26-C26 -> -1.2434498e-14 | E26: =IF(ABS(D26)<0.000001,"PASS","FAIL") -> PASS
A27: selected architectures | B27: =COUNTIF(Alternatives!P7:P11,"SELECT") -> 1 | C27: 1 | D27: =B27-C27 -> 0 | E27: =IF(ABS(D27)<0.000001,"PASS","FAIL") -> PASS
A28: selected gates | B28: =Alternatives!N7 -> 12 | C28: 12 | D28: =B28-C28 -> 0 | E28: =IF(ABS(D28)<0.000001,"PASS","FAIL") -> PASS
A29: rejected architectures | B29: =COUNTIF(Alternatives!P7:P11,"REJECT") -> 4 | C29: 4 | D29: =B29-C29 -> 0 | E29: =IF(ABS(D29)<0.000001,"PASS","FAIL") -> PASS
A30: substrate rotation rows | B30: =COUNTA('Substrate Rotation'!A7:A12) -> 6 | C30: 6 | D30: =B30-C30 -> 0 | E30: =IF(ABS(D30)<0.000001,"PASS","FAIL") -> PASS
A31: substrate station assignments | B31: =SUM('Substrate Rotation'!F7:F12) -> 18 | C31: 18 | D31: =B31-C31 -> 0 | E31: =IF(ABS(D31)<0.000001,"PASS","FAIL") -> PASS
A32: substrate distinct-system sum | B32: =SUM('Substrate Rotation'!G7:G12) -> 18 | C32: 18 | D32: =B32-C32 -> 0 | E32: =IF(ABS(D32)<0.000001,"PASS","FAIL") -> PASS
A33: substrate distinct-role sum | B33: =SUM('Substrate Rotation'!H7:H12) -> 18 | C33: 18 | D33: =B33-C33 -> 0 | E33: =IF(ABS(D33)<0.000001,"PASS","FAIL") -> PASS
A34: station crosswalk rows | B34: =COUNTA('Station Crosswalk'!A7:A24) -> 18 | C34: 18 | D34: =B34-C34 -> 0 | E34: =IF(ABS(D34)<0.000001,"PASS","FAIL") -> PASS
A35: method register rows | B35: =COUNTA('Method Lots'!A7:A42) -> 36 | C35: 36 | D35: =B35-C35 -> 0 | E35: =IF(ABS(D35)<0.000001,"PASS","FAIL") -> PASS
A36: method receiver bays | B36: =SUM('Method Lots'!G7:G42) -> 144 | C36: 144 | D36: =B36-C36 -> 0 | E36: =IF(ABS(D36)<0.000001,"PASS","FAIL") -> PASS
A37: control-group floor | B37: =Controls!B17 -> 48 | C37: 48 | D37: =B37-C37 -> 0 | E37: =IF(ABS(D37)<0.000001,"PASS","FAIL") -> PASS
A38: control-group rows | B38: =COUNTA('Control Groups'!A7:A54) -> 48 | C38: 48 | D38: =B38-C38 -> 0 | E38: =IF(ABS(D38)<0.000001,"PASS","FAIL") -> PASS
A39: candidate groups | B39: =COUNTIF('Control Groups'!B7:B54,"Candidate") -> 6 | C39: 6 | D39: =B39-C39 -> 0 | E39: =IF(ABS(D39)<0.000001,"PASS","FAIL") -> PASS
A40: decisive groups | B40: =COUNTIF('Control Groups'!B7:B54,"Public decisive") -> 36 | C40: 36 | D40: =B40-C40 -> 0 | E40: =IF(ABS(D40)<0.000001,"PASS","FAIL") -> PASS
A41: boundary groups | B41: =COUNTIF('Control Groups'!B7:B54,"Public boundary") -> 6 | C41: 6 | D41: =B41-C41 -> 0 | E41: =IF(ABS(D41)<0.000001,"PASS","FAIL") -> PASS
A42: group assigned lots | B42: =SUM('Control Groups'!E7:E54) -> 102 | C42: 102 | D42: =B42-C42 -> 0 | E42: =IF(ABS(D42)<0.000001,"PASS","FAIL") -> PASS
A43: group cap failures | B43: =COUNTIF('Control Groups'!G7:G54,"FAIL") -> 0 | C43: 0 | D43: =B43-C43 -> 0 | E43: =IF(ABS(D43)<0.000001,"PASS","FAIL") -> PASS
A44: collision rules | B44: =COUNTA('Collision Rules'!A7:A18) -> 12 | C44: 12 | D44: =B44-C44 -> 0 | E44: =IF(ABS(D44)<0.000001,"PASS","FAIL") -> PASS
A45: frozen collision rules | B45: =COUNTIF('Collision Rules'!G7:G18,"FROZEN") -> 12 | C45: 12 | D45: =B45-C45 -> 0 | E45: =IF(ABS(D45)<0.000001,"PASS","FAIL") -> PASS
A46: packet families per lot | B46: =Controls!B18 -> 5 | C46: 5 | D46: =B46-C46 -> 0 | E46: =IF(ABS(D46)<0.000001,"PASS","FAIL") -> PASS
A47: packet arithmetic | B47: =COUNTA('Lot Register'!A7:A108)*Controls!B18 -> 510 | C47: 510 | D47: =B47-C47 -> 0 | E47: =IF(ABS(D47)<0.000001,"PASS","FAIL") -> PASS
A48: packet rows | B48: =COUNTA('Acceptance Packets'!A7:A516) -> 510 | C48: 510 | D48: =B48-C48 -> 0 | E48: =IF(ABS(D48)<0.000001,"PASS","FAIL") -> PASS
A49: packet source empty | B49: =COUNTIF('Acceptance Packets'!I7:I516,"SOURCE EMPTY") -> 510 | C49: 510 | D49: =B49-C49 -> 0 | E49: =IF(ABS(D49)<0.000001,"PASS","FAIL") -> PASS
A50: packet accepted zero | B50: =SUM('Acceptance Packets'!J7:J516) -> 0 | C50: 0 | D50: =B50-C50 -> 0 | E50: =IF(ABS(D50)<0.000001,"PASS","FAIL") -> PASS
A51: packet open | B51: =COUNTIF('Acceptance Packets'!K7:K516,"OPEN") -> 510 | C51: 510 | D51: =B51-C51 -> 0 | E51: =IF(ABS(D51)<0.000001,"PASS","FAIL") -> PASS
A52: gates per lot | B52: =Controls!B19 -> 7 | C52: 7 | D52: =B52-C52 -> 0 | E52: =IF(ABS(D52)<0.000001,"PASS","FAIL") -> PASS
A53: gate arithmetic | B53: =COUNTA('Lot Register'!A7:A108)*Controls!B19 -> 714 | C53: 714 | D53: =B53-C53 -> 0 | E53: =IF(ABS(D53)<0.000001,"PASS","FAIL") -> PASS
A54: gate rows | B54: =COUNTA('Acceptance Gates'!A7:A720) -> 714 | C54: 714 | D54: =B54-C54 -> 0 | E54: =IF(ABS(D54)<0.000001,"PASS","FAIL") -> PASS
A55: gate evidence empty | B55: =COUNTIF('Acceptance Gates'!J7:J720,"SOURCE EMPTY") -> 714 | C55: 714 | D55: =B55-C55 -> 0 | E55: =IF(ABS(D55)<0.000001,"PASS","FAIL") -> PASS
A56: gate accepted zero | B56: =SUM('Acceptance Gates'!K7:K720) -> 0 | C56: 0 | D56: =B56-C56 -> 0 | E56: =IF(ABS(D56)<0.000001,"PASS","FAIL") -> PASS
A57: gate open | B57: =COUNTIF('Acceptance Gates'!L7:L720,"OPEN") -> 714 | C57: 714 | D57: =B57-C57 -> 0 | E57: =IF(ABS(D57)<0.000001,"PASS","FAIL") -> PASS
A58: release steps | B58: =COUNTA('Release Sequence'!A7:A13) -> 7 | C58: 7 | D58: =B58-C58 -> 0 | E58: =IF(ABS(D58)<0.000001,"PASS","FAIL") -> PASS
A59: held future release steps | B59: =COUNTIF('Release Sequence'!H7:H13,"HELD") -> 6 | C59: 6 | D59: =B59-C59 -> 0 | E59: =IF(ABS(D59)<0.000001,"PASS","FAIL") -> PASS
A60: public through MAKE | B60: =SUM('Payment Schedule'!H7:H11) -> 9 | C60: 9 | D60: =B60-C60 -> 1.7763568e-15 | E60: =IF(ABS(D60)<0.000001,"PASS","FAIL") -> PASS
A61: candidate through MAKE | B61: ='Payment Schedule'!H12 -> 1.7934564 | C61: 1.7934564 | D61: =B61-C61 -> 0 | E61: =IF(ABS(D61)<0.000001,"PASS","FAIL") -> PASS
A62: combined through MAKE | B62: ='Payment Schedule'!B18 -> 10.793456 | C62: 10.793456 | D62: =B62-C62 -> 1.7763568e-15 | E62: =IF(ABS(D62)<0.000001,"PASS","FAIL") -> PASS
A63: all-six kill paid | B63: ='Payment Schedule'!B19 -> 12.048876 | C63: 12.048876 | D63: =B63-C63 -> 1.7763568e-15 | E63: =IF(ABS(D63)<0.000001,"PASS","FAIL") -> PASS
A64: all-six kill unreleased | B64: ='Payment Schedule'!C19 -> 3.5380369 | C64: 3.5380369 | D64: =B64-C64 -> -1.7763568e-15 | E64: =IF(ABS(D64)<0.000001,"PASS","FAIL") -> PASS
A65: acceptance authorities | B65: =COUNTA('Authority Separation'!A7:A12) -> 6 | C65: 6 | D65: =B65-C65 -> 0 | E65: =IF(ABS(D65)<0.000001,"PASS","FAIL") -> PASS
A66: builder overlaps | B66: =COUNTIF('Authority Separation'!F7:F12,"NO") -> 6 | C66: 6 | D66: =B66-C66 -> 0 | E66: =IF(ABS(D66)<0.000001,"PASS","FAIL") -> PASS
A67: industrial fields | B67: =COUNTA('Industrial Base'!A7:A14) -> 8 | C67: 8 | D67: =B67-C67 -> 0 | E67: =IF(ABS(D67)<0.000001,"PASS","FAIL") -> PASS
A68: stress tests | B68: =COUNTA('Stress Tests'!A7:A22) -> 16 | C68: 16 | D68: =B68-C68 -> 0 | E68: =IF(ABS(D68)<0.000001,"PASS","FAIL") -> PASS
A69: stress passes | B69: =COUNTIF('Stress Tests'!F7:F22,"PASS") -> 16 | C69: 16 | D69: =B69-C69 -> 0 | E69: =IF(ABS(D69)<0.000001,"PASS","FAIL") -> PASS
A70: controller identities empty | B70: =COUNTIF('Lot Register'!L7:L108,"SOURCE EMPTY") -> 102 | C70: 102 | D70: =B70-C70 -> 0 | E70: =IF(ABS(D70)<0.000001,"PASS","FAIL") -> PASS
A71: supplier identities empty | B71: =COUNTIF('Lot Register'!M7:M108,"SOURCE EMPTY") -> 102 | C71: 102 | D71: =B71-C71 -> 0 | E71: =IF(ABS(D71)<0.000001,"PASS","FAIL") -> PASS
A72: awards zero | B72: =SUM('Lot Register'!N7:N108) -> 0 | C72: 0 | D72: =B72-C72 -> 0 | E72: =IF(ABS(D72)<0.000001,"PASS","FAIL") -> PASS
A73: obligations zero | B73: =SUM('Lot Register'!O7:O108) -> 0 | C73: 0 | D73: =B73-C73 -> 0 | E73: =IF(ABS(D73)<0.000001,"PASS","FAIL") -> PASS
A74: payments zero | B74: =SUM('Lot Register'!P7:P108) -> 0 | C74: 0 | D74: =B74-C74 -> 0 | E74: =IF(ABS(D74)<0.000001,"PASS","FAIL") -> PASS
A75: packets passed zero | B75: =SUM('Lot Register'!Q7:Q108) -> 0 | C75: 0 | D75: =B75-C75 -> 0 | E75: =IF(ABS(D75)<0.000001,"PASS","FAIL") -> PASS
A76: gates passed zero | B76: =SUM('Lot Register'!R7:R108) -> 0 | C76: 0 | D76: =B76-C76 -> 0 | E76: =IF(ABS(D76)<0.000001,"PASS","FAIL") -> PASS
A77: lot capability zero | B77: =SUM('Lot Register'!S7:S108) -> 0 | C77: 0 | D77: =B77-C77 -> 0 | E77: =IF(ABS(D77)<0.000001,"PASS","FAIL") -> PASS
A78: sites zero | B78: =Controls!B20 -> 0 | C78: 0 | D78: =B78-C78 -> 0 | E78: =IF(ABS(D78)<0.000001,"PASS","FAIL") -> PASS
A79: firms zero | B79: =Controls!B21 -> 0 | C79: 0 | D79: =B79-C79 -> 0 | E79: =IF(ABS(D79)<0.000001,"PASS","FAIL") -> PASS
A80: current awards zero | B80: =Controls!B22 -> 0 | C80: 0 | D80: =B80-C80 -> 0 | E80: =IF(ABS(D80)<0.000001,"PASS","FAIL") -> PASS
A81: current obligations zero | B81: =Controls!B23 -> 0 | C81: 0 | D81: =B81-C81 -> 0 | E81: =IF(ABS(D81)<0.000001,"PASS","FAIL") -> PASS
A82: current payments zero | B82: =Controls!B24 -> 0 | C82: 0 | D82: =B82-C82 -> 0 | E82: =IF(ABS(D82)<0.000001,"PASS","FAIL") -> PASS
A83: accepted packets control zero | B83: =Controls!B25 -> 0 | C83: 0 | D83: =B83-C83 -> 0 | E83: =IF(ABS(D83)<0.000001,"PASS","FAIL") -> PASS
A84: accepted gates control zero | B84: =Controls!B26 -> 0 | C84: 0 | D84: =B84-C84 -> 0 | E84: =IF(ABS(D84)<0.000001,"PASS","FAIL") -> PASS
A85: capability control zero | B85: =Controls!B27 -> 0 | C85: 0 | D85: =B85-C85 -> 0 | E85: =IF(ABS(D85)<0.000001,"PASS","FAIL") -> PASS
A86: rendering authority zero | B86: =Controls!B28 -> 0 | C86: 0 | D86: =B86-C86 -> 0 | E86: =IF(ABS(D86)<0.000001,"PASS","FAIL") -> PASS

Sheet Sources & Limits
A2: Internal authorities and model limits
A4: This model composes authoritative internal design decisions. It does not claim empirical performance for unbuilt systems.
A6: Source | B6: Repository artifact | C6: Role | D6: Access | E6: Limitation
A7: A2C-2 | B7: federated physical-truth station and rig constitution | C7: eighteen nuclei, six truth trains, thin substrate and USD 12.0B reserve | D7: internal repository | E7: no site, firm or physical observation
A8: A2C-1 | B8: six-root sentinel wave and cancellation constitution | C8: selected candidates and exact private-option ceilings | D8: internal repository | E8: no award or article
A9: PFP-4 | B9: federated public-method grid | C9: two unlike lineages and seventy-two method cards | D9: internal repository | E9: no accepted realization
A10: PFP-2 | B10: separated option-and-proof market | C10: Root House and beneficial-control doctrine | D10: internal repository | E10: no implementation identity
A11: Model boundary | B11: this workbook | C11: formula, mutation, rendering and reconciliation checks | D11: internal repository | E11: no external sites used
A12: Evidence boundary | B12: all physical and contractual records | C12: deliberate source-empty and zero states | D12: not available | E12: design does not imply execution
A13: Precision boundary | B13: all reported quantities | C13: exact arithmetic retained in workbook | D13: derived | E13: prose limited to three significant figures
A14: Rendering boundary | B14: exterior form | C14: held until requirements and platform architectures stabilize | D14: not applicable | E14: no exterior rendering in this pass
