Workbook

Sheet Summary
A2: Six-root internal-section architecture
A4: Decision | B4: Value | C4: Unit | D4: State | F4: Interpretation
A5: root-native sections | B5: =COUNTA('Root Architecture'!B7:B12) -> 6 | C5: count | D5: FROZEN FOR FALSIFICATION | F5: Decision Freeze six different internal falsification sections. Sixty nominal and largest-cell-loss cells close under the selected screen. Eighty-four cells now have executable, root-native protocols but no observations. The sections may be built for hostile proof; they may not be treated as validated platforms, production designs or exterior-rendering authority.
A6: cell decisions | B6: =COUNTA('Cell Register'!A7:A150) -> 144 | C6: count | D6: COMPLETE
A7: design-close cells | B7: =COUNTIFS('Cell Register'!S7:S150,"DESIGN CLOSE") -> 60 | C7: count | D7: CONTROLLED HYPOTHESIS
A8: measurement-ready cells | B8: =COUNTIFS('Cell Register'!S7:S150,"MEASUREMENT READY") -> 84 | C8: count | D8: EVIDENCE EMPTY
A9: unscoped cells | B9: =COUNTIFS('Cell Register'!S7:S150,"UNSCOPED") -> 0 | C9: count | D9: ZERO
A10: legacy gaps with successor | B10: =SUM('Gap Migration'!J7:J91) -> 85 | C10: count | D10: COMPLETE
A11: physical observations | B11: =Controls!B19 -> 0 | C11: count | D11: ZERO
A12: G06 credits | B12: =SUM('Root Architecture'!J7:J12) -> 0 | C12: count | D12: ZERO
A14: System | B14: Root | C14: Article | D14: Design close | E14: Measurement ready | F14: Unscoped | G14: Minimum W03 margin | H14: G06 | I14: Disposition | J14: Governing architecture
A15: MS-ET | B15: ET-A | C15: Pelagic exchange cell | D15: ='Root Architecture'!D7 -> 10 | E15: ='Root Architecture'!E7 -> 14 | F15: ='Root Architecture'!G7 -> 0 | G15: ='Root Architecture'!I7 -> 0.001669627 | H15: ='Root Architecture'!J7 -> 0 | I15: ='Root Architecture'!K7 -> SECTION FROZEN / EVIDENCE HOLD | J15: two complete exchange paths and motion-decoupled custody
A16: MS-CT | B16: CT-C | C16: Occupied-building utility-spine sector | D16: ='Root Architecture'!D8 -> 10 | E16: ='Root Architecture'!E8 -> 14 | F16: ='Root Architecture'!G8 -> 0 | G16: ='Root Architecture'!I8 -> 0.0028571429 | H16: ='Root Architecture'!J8 -> 0 | I16: ='Root Architecture'!K8 -> SECTION FROZEN / EVIDENCE HOLD | J16: seven isolated energy cells and five fault-contained service trunks
A17: MS-HC | B17: HC-A | C17: Atmospheric intervention cell | D17: ='Root Architecture'!D9 -> 10 | E17: ='Root Architecture'!E9 -> 14 | F17: ='Root Architecture'!G9 -> 0 | G17: ='Root Architecture'!I9 -> 0.0033980583 | H17: ='Root Architecture'!J9 -> 0 | I17: ='Root Architecture'!K9 -> SECTION FROZEN / EVIDENCE HOLD | J17: five attributable held-line sectors and eight energy cells
A18: MS-LF | B18: LF-B | C18: Geothermal source position | D18: ='Root Architecture'!D10 -> 10 | E18: ='Root Architecture'!E10 -> 14 | F18: ='Root Architecture'!G10 -> 0 | G18: ='Root Architecture'!I10 -> 0.0015124698 | H18: ='Root Architecture'!J10 -> 0 | I18: ='Root Architecture'!K10 -> SECTION FROZEN / EVIDENCE HOLD | J18: loss-separable access, conversion, route, buffer and residual sections
A19: MS-HU | B19: HU-A | C19: Complete clinical island | D19: ='Root Architecture'!D11 -> 10 | E19: ='Root Architecture'!E11 -> 14 | F19: ='Root Architecture'!G11 -> 0 | G19: ='Root Architecture'!I11 -> 0.003275 | H19: ='Root Architecture'!J11 -> 0 | I19: ='Root Architecture'!K11 -> SECTION FROZEN / EVIDENCE HOLD | J19: eight access cells without deleting ten indivisible care lines
A20: MS-RT | B20: RT-B | C20: Disconnected microfactory mesh | D20: ='Root Architecture'!D12 -> 10 | E20: ='Root Architecture'!E12 -> 14 | F20: ='Root Architecture'!G12 -> 0 | G20: ='Root Architecture'!I12 -> 0.00016129032 | H20: ='Root Architecture'!J12 -> 0 | I20: ='Root Architecture'!K12 -> SECTION FROZEN / EVIDENCE HOLD | J20: seven process-energy cells and five complete process meshes

Sheet Controls
A2: Internal-section architecture controls
A4: Blue cells are controlled design inputs. Physical observations remain empty and every release state remains held.
A6: Control | B6: Value | C6: Unit | D6: Authority
A7: adverse coefficient screen | B7: 0.025 | C7: share | D7: Pass 218 selected screen
A8: closure threshold | B8: 1 | C8: ratio | D8: Pass 216 endpoint rule
A9: roots | B9: 6 | C9: count | D9: Pass 211 / 216
A10: accounts | B10: 6 | C10: count | D10: Pass 217
A11: worlds | B11: 4 | C11: count | D11: Pass 217
A12: closure cells | B12: 144 | C12: count | D12: direct arithmetic
A13: legacy gaps | B13: 85 | C13: count | D13: Pass 218
A14: option ceiling | B14: 3.5869128 | C14: USD B | D14: Pass 215
A15: FRAME share | B15: 0.15 | C15: share | D15: Pass 215
A16: FRAME ceiling | B16: 0.53803692 | C16: USD B | D16: direct arithmetic
A17: accepted authority | B17: 0 | C17: USD B | D17: held
A18: paid authority | B18: 0 | C18: USD B | D18: held
... A22: rendering authority | B22: 0 | C22: count | D22: held

Sheet Root Architecture
A2: Six internal sections frozen for falsification
A4: A frozen falsification section says what must be built and measured. It does not claim evidence, platform form or production readiness.
A6: System | B6: Root | C6: Article | D6: Design-close cells | E6: Measurement-ready cells | F6: Negative cells | G6: Unscoped cells | H6: All 24 specified | I6: Minimum W03 margin | J6: G06 credit | K6: Disposition | L6: Governing architecture
A7: MS-ET | B7: ET-A | C7: Pelagic exchange cell | D7: =COUNTIFS('Cell Register'!$C$7:$C$150,B7,'Cell Register'!$S$7:$S$150,"DESIGN CLOSE") -> 10 | E7: =COUNTIFS('Cell Register'!$C$7:$C$150,B7,'Cell Register'!$S$7:$S$150,"MEASUREMENT READY") -> 14 | F7: =COUNTIFS('Cell Register'!$C$7:$C$150,B7,'Cell Register'!$S$7:$S$150,"NEGATIVE") -> 0 | G7: =COUNTIFS('Cell Register'!$C$7:$C$150,B7,'Cell Register'!$S$7:$S$150,"UNSCOPED") -> 0 | H7: =IF(D7+E7=24,1,0) -> 1 | I7: =MIN('Cell Register'!N7:N30)-Controls!$B$8 -> 0.001669627 | J7: =SUM('Cell Register'!R7:R30) -> 0 | K7: =IF(AND(D7=10,E7=14,F7=0,G7=0,H7=1,J7=0),"SECTION FROZEN / EVIDENCE HOLD","RETURN") -> SECTION FROZEN / EVIDENCE HOLD | L7: two complete exchange paths and motion-decoupled custody
A8: MS-CT | B8: CT-C | C8: Occupied-building utility-spine sector | D8: =COUNTIFS('Cell Register'!$C$7:$C$150,B8,'Cell Register'!$S$7:$S$150,"DESIGN CLOSE") -> 10 | E8: =COUNTIFS('Cell Register'!$C$7:$C$150,B8,'Cell Register'!$S$7:$S$150,"MEASUREMENT READY") -> 14 | F8: =COUNTIFS('Cell Register'!$C$7:$C$150,B8,'Cell Register'!$S$7:$S$150,"NEGATIVE") -> 0 | G8: =COUNTIFS('Cell Register'!$C$7:$C$150,B8,'Cell Register'!$S$7:$S$150,"UNSCOPED") -> 0 | H8: =IF(D8+E8=24,1,0) -> 1 | I8: =MIN('Cell Register'!N31:N54)-Controls!$B$8 -> 0.0028571429 | J8: =SUM('Cell Register'!R31:R54) -> 0 | K8: =IF(AND(D8=10,E8=14,F8=0,G8=0,H8=1,J8=0),"SECTION FROZEN / EVIDENCE HOLD","RETURN") -> SECTION FROZEN / EVIDENCE HOLD | L8: seven isolated energy cells and five fault-contained service trunks
A9: MS-HC | B9: HC-A | C9: Atmospheric intervention cell | D9: =COUNTIFS('Cell Register'!$C$7:$C$150,B9,'Cell Register'!$S$7:$S$150,"DESIGN CLOSE") -> 10 | E9: =COUNTIFS('Cell Register'!$C$7:$C$150,B9,'Cell Register'!$S$7:$S$150,"MEASUREMENT READY") -> 14 | F9: =COUNTIFS('Cell Register'!$C$7:$C$150,B9,'Cell Register'!$S$7:$S$150,"NEGATIVE") -> 0 | G9: =COUNTIFS('Cell Register'!$C$7:$C$150,B9,'Cell Register'!$S$7:$S$150,"UNSCOPED") -> 0 | H9: =IF(D9+E9=24,1,0) -> 1 | I9: =MIN('Cell Register'!N55:N78)-Controls!$B$8 -> 0.0033980583 | J9: =SUM('Cell Register'!R55:R78) -> 0 | K9: =IF(AND(D9=10,E9=14,F9=0,G9=0,H9=1,J9=0),"SECTION FROZEN / EVIDENCE HOLD","RETURN") -> SECTION FROZEN / EVIDENCE HOLD | L9: five attributable held-line sectors and eight energy cells
A10: MS-LF | B10: LF-B | C10: Geothermal source position | D10: =COUNTIFS('Cell Register'!$C$7:$C$150,B10,'Cell Register'!$S$7:$S$150,"DESIGN CLOSE") -> 10 | E10: =COUNTIFS('Cell Register'!$C$7:$C$150,B10,'Cell Register'!$S$7:$S$150,"MEASUREMENT READY") -> 14 | F10: =COUNTIFS('Cell Register'!$C$7:$C$150,B10,'Cell Register'!$S$7:$S$150,"NEGATIVE") -> 0 | G10: =COUNTIFS('Cell Register'!$C$7:$C$150,B10,'Cell Register'!$S$7:$S$150,"UNSCOPED") -> 0 | H10: =IF(D10+E10=24,1,0) -> 1 | I10: =MIN('Cell Register'!N79:N102)-Controls!$B$8 -> 0.0015124698 | J10: =SUM('Cell Register'!R79:R102) -> 0 | K10: =IF(AND(D10=10,E10=14,F10=0,G10=0,H10=1,J10=0),"SECTION FROZEN / EVIDENCE HOLD","RETURN") -> SECTION FROZEN / EVIDENCE HOLD | L10: loss-separable access, conversion, route, buffer and residual sections
A11: MS-HU | B11: HU-A | C11: Complete clinical island | D11: =COUNTIFS('Cell Register'!$C$7:$C$150,B11,'Cell Register'!$S$7:$S$150,"DESIGN CLOSE") -> 10 | E11: =COUNTIFS('Cell Register'!$C$7:$C$150,B11,'Cell Register'!$S$7:$S$150,"MEASUREMENT READY") -> 14 | F11: =COUNTIFS('Cell Register'!$C$7:$C$150,B11,'Cell Register'!$S$7:$S$150,"NEGATIVE") -> 0 | G11: =COUNTIFS('Cell Register'!$C$7:$C$150,B11,'Cell Register'!$S$7:$S$150,"UNSCOPED") -> 0 | H11: =IF(D11+E11=24,1,0) -> 1 | I11: =MIN('Cell Register'!N103:N126)-Controls!$B$8 -> 0.003275 | J11: =SUM('Cell Register'!R103:R126) -> 0 | K11: =IF(AND(D11=10,E11=14,F11=0,G11=0,H11=1,J11=0),"SECTION FROZEN / EVIDENCE HOLD","RETURN") -> SECTION FROZEN / EVIDENCE HOLD | L11: eight access cells without deleting ten indivisible care lines
A12: MS-RT | B12: RT-B | C12: Disconnected microfactory mesh | D12: =COUNTIFS('Cell Register'!$C$7:$C$150,B12,'Cell Register'!$S$7:$S$150,"DESIGN CLOSE") -> 10 | E12: =COUNTIFS('Cell Register'!$C$7:$C$150,B12,'Cell Register'!$S$7:$S$150,"MEASUREMENT READY") -> 14 | F12: =COUNTIFS('Cell Register'!$C$7:$C$150,B12,'Cell Register'!$S$7:$S$150,"NEGATIVE") -> 0 | G12: =COUNTIFS('Cell Register'!$C$7:$C$150,B12,'Cell Register'!$S$7:$S$150,"UNSCOPED") -> 0 | H12: =IF(D12+E12=24,1,0) -> 1 | I12: =MIN('Cell Register'!N127:N150)-Controls!$B$8 -> 0.00016129032 | J12: =SUM('Cell Register'!R127:R150) -> 0 | K12: =IF(AND(D12=10,E12=14,F12=0,G12=0,H12=1,J12=0),"SECTION FROZEN / EVIDENCE HOLD","RETURN") -> SECTION FROZEN / EVIDENCE HOLD | L12: seven process-energy cells and five complete process meshes

Sheet Section Bills
A2: Six root-native internal section bills
A4: These are minimum falsification configurations. They select internal partitions and test boundaries, not exterior geometry or a production design.
A6: System | B6: Root | C6: Account | D6: Closure account | E6: Internal section | F6: Unit | G6: Installed cells | H6: Cells after loss | I6: Cell rating | J6: W01 owned capacity | K6: W01 requirement | L6: W03 survivor capacity | M6: W03 requirement | N6: Causal isolation | O6: Cold-rebuild object | P6: Basis | Q6: Adverse screen | R6: W01 lower ratio | S6: W03 lower ratio | T6: Minimum margin | U6: Section state
A7: MS-ET | B7: ET-A | C7: A01 | D7: Mass and material custody | E7: 8 independent access cells | F7: t | G7: 8 | H7: 7 | I7: 16000 | J7: 128000 | K7: 102000 | L7: 112000 | M7: 102000 | N7: separate lift, handling and custody path per cell | O7: rebuild access cell and serial custody from frozen bill | P7: Pass 182 plus Pass 218 screen | Q7: =Controls!$B$7 -> 0.025 | R7: =IF(AND(ISNUMBER(J7),ISNUMBER(K7),K7>0),J7/K7*(1-Q7),"") -> 1.2235294 | S7: =IF(AND(ISNUMBER(L7),ISNUMBER(M7),M7>0),L7/M7*(1-Q7),"") -> 1.0705882 | T7: =IF(AND(ISNUMBER(R7),ISNUMBER(S7)),MIN(R7,S7)-Controls!$B$8,"") -> 0.070588235 | U7: FROZEN FOR FALSIFICATION
A8: MS-ET | B8: ET-A | C8: A02 | D8: Energy and heat | E8: 6 black-start generation cells | F8: MW | G8: 6 | H8: 5 | I8: 20 | J8: 120 | K8: 96 | L8: 100 | M8: 96 | N8: cell-local breaker, start source and heat rejection | O8: rebuild generator, switchgear and heat path | P8: Pass 182 retained | Q8: =Controls!$B$7 -> 0.025 | R8: =IF(AND(ISNUMBER(J8),ISNUMBER(K8),K8>0),J8/K8*(1-Q8),"") -> 1.21875 | S8: =IF(AND(ISNUMBER(L8),ISNUMBER(M8),M8>0),L8/M8*(1-Q8),"") -> 1.015625 | T8: =IF(AND(ISNUMBER(R8),ISNUMBER(S8)),MIN(R8,S8)-Controls!$B$8,"") -> 0.015625 | U8: FROZEN FOR FALSIFICATION
A9: MS-ET | B9: ET-A | C9: A03 | D9: Geometry and load path | E9: 2 complete motion-decoupled exchange paths | F9: t/h | G9: 2 | H9: 1 | I9: 241 | J9: 482 | K9: 234.58333 | L9: 241 | M9: 234.58333 | N9: either path crosses moving source, transition, custody and handoff | O9: rebuild connector, transition and metering chain | P9: RZ-01 | Q9: =Controls!$B$7 -> 0.025 | R9: =IF(AND(ISNUMBER(J9),ISNUMBER(K9),K9>0),J9/K9*(1-Q9),"") -> 2.0033393 | S9: =IF(AND(ISNUMBER(L9),ISNUMBER(M9),M9>0),L9/M9*(1-Q9),"") -> 1.0016696 | T9: =IF(AND(ISNUMBER(R9),ISNUMBER(S9)),MIN(R9,S9)-Controls!$B$8,"") -> 0.001669627 | U9: FROZEN FOR FALSIFICATION
A10: MS-ET | B10: ET-A | C10: A04 | D10: Safe state and human boundary | E10: 6 independent refuge and receiver zones | F10: ratio | G10: 6 | H10: 5 | I10: 0.21 | J10: 1.26 | K10: 1 | L10: 1.05 | M10: 1 | N10: each zone has detection, refuge, egress and manual safeing | O10: rebuild safe-state chain and prove lawful egress | P10: Pass 182 retained | Q10: =Controls!$B$7 -> 0.025 | R10: =IF(AND(ISNUMBER(J10),ISNUMBER(K10),K10>0),J10/K10*(1-Q10),"") -> 1.2285 | S10: =IF(AND(ISNUMBER(L10),ISNUMBER(M10),M10>0),L10/M10*(1-Q10),"") -> 1.02375 | T10: =IF(AND(ISNUMBER(R10),ISNUMBER(S10)),MIN(R10,S10)-Controls!$B$8,"") -> 0.02375 | U10: FROZEN FOR FALSIFICATION
A11: MS-ET | B11: ET-A | C11: A05 | D11: Residual and environmental custody | E11: 6 contained residual cells | F11: t/day | G11: 6 | H11: 5 | I11: 252 | J11: 1512 | K11: 1200 | L11: 1260 | M11: 1200 | N11: each cell owns treatment, buffer and discharge custody | O11: rebuild residual cell and reconcile inventory | P11: Pass 182 retained | Q11: =Controls!$B$7 -> 0.025 | R11: =IF(AND(ISNUMBER(J11),ISNUMBER(K11),K11>0),J11/K11*(1-Q11),"") -> 1.2285 | S11: =IF(AND(ISNUMBER(L11),ISNUMBER(M11),M11>0),L11/M11*(1-Q11),"") -> 1.02375 | T11: =IF(AND(ISNUMBER(R11),ISNUMBER(S11)),MIN(R11,S11)-Controls!$B$8,"") -> 0.02375 | U11: FROZEN FOR FALSIFICATION
A12: MS-ET | B12: ET-A | C12: A06 | D12: Removal and cold reconstruction | E12: sealed exchange-section reconstruction chain | F12: h | G12: 1 | H12: 1 | N12: records, tools, calibration and clean team remain outside candidate runtime | O12: outside team rebuilds complete causal section within 168 h | P12: Pass 219 protocol | Q12: =Controls!$B$7 -> 0.025 | R12: =IF(AND(ISNUMBER(J12),ISNUMBER(K12),K12>0),J12/K12*(1-Q12),"") | S12: =IF(AND(ISNUMBER(L12),ISNUMBER(M12),M12>0),L12/M12*(1-Q12),"") | T12: =IF(AND(ISNUMBER(R12),ISNUMBER(S12)),MIN(R12,S12)-Controls!$B$8,"") | U12: FROZEN FOR FALSIFICATION
A13: MS-CT | B13: CT-C | C13: A01 | D13: Mass and material custody | E13: 10 independently admitted insertion cells | F13: t | G13: 10 | H13: 9 | I13: 3600 | J13: 36000 | K13: 31000 | L13: 32400 | M13: 31000 | N13: each cell owns lifting, reversible attachment and removal custody | O13: rebuild one insertion cell at occupied receiver | P13: Pass 182 retained | Q13: =Controls!$B$7 -> 0.025 | R13: =IF(AND(ISNUMBER(J13),ISNUMBER(K13),K13>0),J13/K13*(1-Q13),"") -> 1.1322581 | S13: =IF(AND(ISNUMBER(L13),ISNUMBER(M13),M13>0),L13/M13*(1-Q13),"") -> 1.0190323 | T13: =IF(AND(ISNUMBER(R13),ISNUMBER(S13)),MIN(R13,S13)-Controls!$B$8,"") -> 0.019032258 | U13: FROZEN FOR FALSIFICATION
A14: MS-CT | B14: CT-C | C14: A02 | D14: Energy and heat | E14: 7 isolated generation cells | F14: MW | G14: 7 | H14: 6 | I14: 7.2 | J14: 50.4 | K14: 42 | L14: 43.2 | M14: 42 | N14: cell-local breaker, black start and thermal containment | O14: rebuild one 7.2 MW cell and isolation boundary | P14: RZ-02 | Q14: =Controls!$B$7 -> 0.025 | R14: =IF(AND(ISNUMBER(J14),ISNUMBER(K14),K14>0),J14/K14*(1-Q14),"") -> 1.17 | S14: =IF(AND(ISNUMBER(L14),ISNUMBER(M14),M14>0),L14/M14*(1-Q14),"") -> 1.0028571 | T14: =IF(AND(ISNUMBER(R14),ISNUMBER(S14)),MIN(R14,S14)-Controls!$B$8,"") -> 0.0028571429 | U14: FROZEN FOR FALSIFICATION
A15: MS-CT | B15: CT-C | C15: A03 | D15: Geometry and load path | E15: 5 complete multi-utility trunk corridors | F15: ratio | G15: 5 | H15: 4 | I15: 0.264 | J15: 1.32 | K15: 1 | L15: 1.056 | M15: 1 | N15: each corridor carries isolated power, water, communications, smoke and dirty return | O15: rebuild reversible attachment and five service boundaries | P15: Pass 182 retained | Q15: =Controls!$B$7 -> 0.025 | R15: =IF(AND(ISNUMBER(J15),ISNUMBER(K15),K15>0),J15/K15*(1-Q15),"") -> 1.287 | S15: =IF(AND(ISNUMBER(L15),ISNUMBER(M15),M15>0),L15/M15*(1-Q15),"") -> 1.0296 | T15: =IF(AND(ISNUMBER(R15),ISNUMBER(S15)),MIN(R15,S15)-Controls!$B$8,"") -> 0.0296 | U15: FROZEN FOR FALSIFICATION
A16: MS-CT | B16: CT-C | C16: A04 | D16: Safe state and human boundary | E16: 8 separately safe occupied zones | F16: ratio | G16: 8 | H16: 7 | I16: 0.15 | J16: 1.2 | K16: 1 | L16: 1.05 | M16: 1 | N16: smoke, contamination, egress and manual control do not cross zones | O16: rebuild one safe zone without displacing the receiver | P16: Pass 182 retained | Q16: =Controls!$B$7 -> 0.025 | R16: =IF(AND(ISNUMBER(J16),ISNUMBER(K16),K16>0),J16/K16*(1-Q16),"") -> 1.17 | S16: =IF(AND(ISNUMBER(L16),ISNUMBER(M16),M16>0),L16/M16*(1-Q16),"") -> 1.02375 | T16: =IF(AND(ISNUMBER(R16),ISNUMBER(S16)),MIN(R16,S16)-Controls!$B$8,"") -> 0.02375 | U16: FROZEN FOR FALSIFICATION
A17: MS-CT | B17: CT-C | C17: A05 | D17: Residual and environmental custody | E17: 6 dirty-return treatment cells | F17: t/day | G17: 6 | H17: 5 | I17: 46.2 | J17: 277.2 | K17: 220 | L17: 231 | M17: 220 | N17: valved return, contained buffer and sampled discharge per cell | O17: rebuild dirty-return cell and reconcile building inventory | P17: Pass 182 retained | Q17: =Controls!$B$7 -> 0.025 | R17: =IF(AND(ISNUMBER(J17),ISNUMBER(K17),K17>0),J17/K17*(1-Q17),"") -> 1.2285 | S17: =IF(AND(ISNUMBER(L17),ISNUMBER(M17),M17>0),L17/M17*(1-Q17),"") -> 1.02375 | T17: =IF(AND(ISNUMBER(R17),ISNUMBER(S17)),MIN(R17,S17)-Controls!$B$8,"") -> 0.02375 | U17: FROZEN FOR FALSIFICATION
A18: MS-CT | B18: CT-C | C18: A06 | D18: Removal and cold reconstruction | E18: sealed occupied-spine reconstruction chain | F18: h | G18: 1 | H18: 1 | N18: public attachment datum and clean tools survive loss of candidate runtime | O18: outside team removes and rebuilds section within 168 h | P18: Pass 219 protocol | Q18: =Controls!$B$7 -> 0.025 | R18: =IF(AND(ISNUMBER(J18),ISNUMBER(K18),K18>0),J18/K18*(1-Q18),"") | S18: =IF(AND(ISNUMBER(L18),ISNUMBER(M18),M18>0),L18/M18*(1-Q18),"") | T18: =IF(AND(ISNUMBER(R18),ISNUMBER(S18)),MIN(R18,S18)-Controls!$B$8,"") | U18: FROZEN FOR FALSIFICATION
A19: MS-HC | B19: HC-A | C19: A01 | D19: Mass and material custody | E19: 10 independently admitted intervention cells | F19: t | G19: 10 | H19: 9 | I19: 6300 | J19: 63000 | K19: 54000 | L19: 56700 | M19: 54000 | N19: carrier, refill and working-fluid custody remain serially separate | O19: rebuild intervention cell and custody record | P19: Pass 182 retained | Q19: =Controls!$B$7 -> 0.025 | R19: =IF(AND(ISNUMBER(J19),ISNUMBER(K19),K19>0),J19/K19*(1-Q19),"") -> 1.1375 | S19: =IF(AND(ISNUMBER(L19),ISNUMBER(M19),M19>0),L19/M19*(1-Q19),"") -> 1.02375 | T19: =IF(AND(ISNUMBER(R19),ISNUMBER(S19)),MIN(R19,S19)-Controls!$B$8,"") -> 0.02375 | U19: FROZEN FOR FALSIFICATION
A20: MS-HC | B20: HC-A | C20: A02 | D20: Energy and heat | E20: 8 isolated intervention-energy cells | F20: MW | G20: 8 | H20: 7 | I20: 20.6 | J20: 164.8 | K20: 140 | L20: 144.2 | M20: 140 | N20: cell-local conversion, start source and heat rejection | O20: rebuild one 20.6 MW energy cell | P20: RZ-04 | Q20: =Controls!$B$7 -> 0.025 | R20: =IF(AND(ISNUMBER(J20),ISNUMBER(K20),K20>0),J20/K20*(1-Q20),"") -> 1.1477143 | S20: =IF(AND(ISNUMBER(L20),ISNUMBER(M20),M20>0),L20/M20*(1-Q20),"") -> 1.00425 | T20: =IF(AND(ISNUMBER(R20),ISNUMBER(S20)),MIN(R20,S20)-Controls!$B$8,"") -> 0.00425 | U20: FROZEN FOR FALSIFICATION
A21: MS-HC | B21: HC-A | C21: A03 | D21: Geometry and load path | E21: 5 independently attributable held-line sectors | F21: km/day | G21: 5 | H21: 4 | I21: 26.5 | J21: 132.5 | K21: 103 | L21: 106 | M21: 103 | N21: each sector joins plume observation, delivery and protected edge | O21: rebuild one kilometre-scale causal sector | P21: RZ-03 | Q21: =Controls!$B$7 -> 0.025 | R21: =IF(AND(ISNUMBER(J21),ISNUMBER(K21),K21>0),J21/K21*(1-Q21),"") -> 1.2542476 | S21: =IF(AND(ISNUMBER(L21),ISNUMBER(M21),M21>0),L21/M21*(1-Q21),"") -> 1.0033981 | T21: =IF(AND(ISNUMBER(R21),ISNUMBER(S21)),MIN(R21,S21)-Controls!$B$8,"") -> 0.0033980583 | U21: FROZEN FOR FALSIFICATION
A22: MS-HC | B22: HC-A | C22: A04 | D22: Safe state and human boundary | E22: 8 protected response and avoidance zones | F22: ratio | G22: 8 | H22: 7 | I22: 0.15 | J22: 1.2 | K22: 1 | L22: 1.05 | M22: 1 | N22: independent avoidance, responder refuge and manual termination | O22: rebuild one protected zone and its public release | P22: Pass 182 retained | Q22: =Controls!$B$7 -> 0.025 | R22: =IF(AND(ISNUMBER(J22),ISNUMBER(K22),K22>0),J22/K22*(1-Q22),"") -> 1.17 | S22: =IF(AND(ISNUMBER(L22),ISNUMBER(M22),M22>0),L22/M22*(1-Q22),"") -> 1.02375 | T22: =IF(AND(ISNUMBER(R22),ISNUMBER(S22)),MIN(R22,S22)-Controls!$B$8,"") -> 0.02375 | U22: FROZEN FOR FALSIFICATION
A23: MS-HC | B23: HC-A | C23: A05 | D23: Residual and environmental custody | E23: 6 runoff and working-fluid custody cells | F23: t/day | G23: 6 | H23: 5 | I23: 189 | J23: 1134 | K23: 900 | L23: 945 | M23: 900 | N23: source, deposition, runoff and recovered material reconcile per cell | O23: rebuild fluid and runoff custody chain | P23: Pass 182 retained | Q23: =Controls!$B$7 -> 0.025 | R23: =IF(AND(ISNUMBER(J23),ISNUMBER(K23),K23>0),J23/K23*(1-Q23),"") -> 1.2285 | S23: =IF(AND(ISNUMBER(L23),ISNUMBER(M23),M23>0),L23/M23*(1-Q23),"") -> 1.02375 | T23: =IF(AND(ISNUMBER(R23),ISNUMBER(S23)),MIN(R23,S23)-Controls!$B$8,"") -> 0.02375 | U23: FROZEN FOR FALSIFICATION
A24: MS-HC | B24: HC-A | C24: A06 | D24: Removal and cold reconstruction | E24: sealed atmospheric-section reconstruction chain | F24: h | G24: 1 | H24: 1 | N24: public plume record and calibration survive deletion of mission runtime | O24: outside team recreates sensing-to-runoff section within 168 h | P24: Pass 219 protocol | Q24: =Controls!$B$7 -> 0.025 | R24: =IF(AND(ISNUMBER(J24),ISNUMBER(K24),K24>0),J24/K24*(1-Q24),"") | S24: =IF(AND(ISNUMBER(L24),ISNUMBER(M24),M24>0),L24/M24*(1-Q24),"") | T24: =IF(AND(ISNUMBER(R24),ISNUMBER(S24)),MIN(R24,S24)-Controls!$B$8,"") | U24: FROZEN FOR FALSIFICATION
A25: MS-LF | B25: LF-B | C25: A01 | D25: Mass and material custody | E25: 9 independent 3.99 kt access slots; 8 required | F25: kt | G25: 9 | H25: 8 | I25: 3.99 | J25: 35.91 | K25: 31.075 | L25: 31.92 | M25: 31.075 | N25: one access slot may disappear without deleting credited source hardware | O25: rebuild access schedule and custody for all required source sections | P25: RZ-05 decomposition | Q25: =Controls!$B$7 -> 0.025 | R25: =IF(AND(ISNUMBER(J25),ISNUMBER(K25),K25>0),J25/K25*(1-Q25),"") -> 1.1267015 | S25: =IF(AND(ISNUMBER(L25),ISNUMBER(M25),M25>0),L25/M25*(1-Q25),"") -> 1.0015125 | T25: =IF(AND(ISNUMBER(R25),ISNUMBER(S25)),MIN(R25,S25)-Controls!$B$8,"") -> 0.0015124698 | U25: FROZEN FOR FALSIFICATION
A26: MS-LF | B26: LF-B | C26: A02 | D26: Energy and heat | E26: 4 isolated conversion cells | F26: MW | G26: 4 | H26: 3 | I26: 13 | J26: 52 | K26: 37.351042 | L26: 39 | M26: 37.351042 | N26: separate conversion, breaker, black start and heat rejection per cell | O26: rebuild one 13 MW conversion cell | P26: RZ-06 | Q26: =Controls!$B$7 -> 0.025 | R26: =IF(AND(ISNUMBER(J26),ISNUMBER(K26),K26>0),J26/K26*(1-Q26),"") -> 1.3573919 | S26: =IF(AND(ISNUMBER(L26),ISNUMBER(M26),M26>0),L26/M26*(1-Q26),"") -> 1.0180439 | T26: =IF(AND(ISNUMBER(R26),ISNUMBER(S26)),MIN(R26,S26)-Controls!$B$8,"") -> 0.018043897 | U26: FROZEN FOR FALSIFICATION
A27: MS-LF | B27: LF-B | C27: A03 | D27: Geometry and load path | E27: 2 independently usable 15.5 km water paths | F27: pipe-km | G27: 2 | H27: 1 | I27: 15.5 | J27: 31 | K27: 30 | L27: 15.5 | M27: 15 | N27: either surveyed path reaches the lawful receiver without a shared active junction | O27: rebuild one buried route and verify alignment | P27: RZ-07 | Q27: =Controls!$B$7 -> 0.025 | R27: =IF(AND(ISNUMBER(J27),ISNUMBER(K27),K27>0),J27/K27*(1-Q27),"") -> 1.0075 | S27: =IF(AND(ISNUMBER(L27),ISNUMBER(M27),M27>0),L27/M27*(1-Q27),"") -> 1.0075 | T27: =IF(AND(ISNUMBER(R27),ISNUMBER(S27)),MIN(R27,S27)-Controls!$B$8,"") -> 0.0075 | U27: FROZEN FOR FALSIFICATION
A28: MS-LF | B28: LF-B | C28: A04 | D28: Safe state and human boundary | E28: 3 isolated 13,000 m3 product-water cells | F28: thousand m3 | G28: 3 | H28: 2 | I28: 13 | J28: 39 | K28: 25 | L28: 26 | M28: 25 | N28: buffer cells have separate valves, sensing and safe discharge | O28: rebuild one buffer cell and black-start boundary | P28: RZ-08 | Q28: =Controls!$B$7 -> 0.025 | R28: =IF(AND(ISNUMBER(J28),ISNUMBER(K28),K28>0),J28/K28*(1-Q28),"") -> 1.521 | S28: =IF(AND(ISNUMBER(L28),ISNUMBER(M28),M28>0),L28/M28*(1-Q28),"") -> 1.014 | T28: =IF(AND(ISNUMBER(R28),ISNUMBER(S28)),MIN(R28,S28)-Controls!$B$8,"") -> 0.014 | U28: FROZEN FOR FALSIFICATION
A29: MS-LF | B29: LF-B | C29: A05 | D29: Residual and environmental custody | E29: 3 isolated 10,300 m3/day injection paths | F29: thousand m3/day | G29: 3 | H29: 2 | I29: 10.3 | J29: 30.9 | K29: 20 | L29: 20.6 | M29: 20 | N29: production, brine treatment, injection and hazard sensing separate by path | O29: rebuild injection path and subsurface custody | P29: RZ-09 | Q29: =Controls!$B$7 -> 0.025 | R29: =IF(AND(ISNUMBER(J29),ISNUMBER(K29),K29>0),J29/K29*(1-Q29),"") -> 1.506375 | S29: =IF(AND(ISNUMBER(L29),ISNUMBER(M29),M29>0),L29/M29*(1-Q29),"") -> 1.00425 | T29: =IF(AND(ISNUMBER(R29),ISNUMBER(S29)),MIN(R29,S29)-Controls!$B$8,"") -> 0.00425 | U29: FROZEN FOR FALSIFICATION
A30: MS-LF | B30: LF-B | C30: A06 | D30: Removal and cold reconstruction | E30: sealed geothermal-position reconstruction chain | F30: h | G30: 1 | H30: 1 | N30: public subsurface truth and bore registry survive loss of source-house runtime | O30: outside team recreates bores-to-injection section within 168 h | P30: Pass 219 protocol | Q30: =Controls!$B$7 -> 0.025 | R30: =IF(AND(ISNUMBER(J30),ISNUMBER(K30),K30>0),J30/K30*(1-Q30),"") | S30: =IF(AND(ISNUMBER(L30),ISNUMBER(M30),M30>0),L30/M30*(1-Q30),"") | T30: =IF(AND(ISNUMBER(R30),ISNUMBER(S30)),MIN(R30,S30)-Controls!$B$8,"") | U30: FROZEN FOR FALSIFICATION
A31: MS-HU | B31: HU-A | C31: A01 | D31: Mass and material custody | E31: 8 independent 7.35 kt access cells | F31: kt | G31: 8 | H31: 7 | I31: 7.35 | J31: 58.8 | K31: 50 | L31: 51.45 | M31: 50 | N31: access loss cannot remove a care line or relationship record | O31: rebuild access cell while preserving clinical custody | P31: RZ-10 | Q31: =Controls!$B$7 -> 0.025 | R31: =IF(AND(ISNUMBER(J31),ISNUMBER(K31),K31>0),J31/K31*(1-Q31),"") -> 1.1466 | S31: =IF(AND(ISNUMBER(L31),ISNUMBER(M31),M31>0),L31/M31*(1-Q31),"") -> 1.003275 | T31: =IF(AND(ISNUMBER(R31),ISNUMBER(S31)),MIN(R31,S31)-Controls!$B$8,"") -> 0.003275 | U31: FROZEN FOR FALSIFICATION
A32: MS-HU | B32: HU-A | C32: A02 | D32: Energy and heat | E32: 6 isolated clinical-utility cells | F32: MW | G32: 6 | H32: 5 | I32: 11 | J32: 66 | K32: 52 | L32: 55 | M32: 52 | N32: each cell owns black start, sterile heat and cold-chain rejection | O32: rebuild one 11 MW utility cell | P32: Pass 182 retained | Q32: =Controls!$B$7 -> 0.025 | R32: =IF(AND(ISNUMBER(J32),ISNUMBER(K32),K32>0),J32/K32*(1-Q32),"") -> 1.2375 | S32: =IF(AND(ISNUMBER(L32),ISNUMBER(M32),M32>0),L32/M32*(1-Q32),"") -> 1.03125 | T32: =IF(AND(ISNUMBER(R32),ISNUMBER(S32)),MIN(R32,S32)-Controls!$B$8,"") -> 0.03125 | U32: FROZEN FOR FALSIFICATION
A33: MS-HU | B33: HU-A | C33: A03 | D33: Geometry and load path | E33: 10 indivisible care lines over separated transfer routes | F33: ratio | G33: 10 | H33: 10 | J33: 1.28 | K33: 1 | L33: 1.032 | M33: 1 | N33: care-line completeness survives access loss; transfer routes fail independently | O33: rebuild one care-route interface without deleting episode scope | P33: Pass 182 retained | Q33: =Controls!$B$7 -> 0.025 | R33: =IF(AND(ISNUMBER(J33),ISNUMBER(K33),K33>0),J33/K33*(1-Q33),"") -> 1.248 | S33: =IF(AND(ISNUMBER(L33),ISNUMBER(M33),M33>0),L33/M33*(1-Q33),"") -> 1.0062 | T33: =IF(AND(ISNUMBER(R33),ISNUMBER(S33)),MIN(R33,S33)-Controls!$B$8,"") -> 0.0062 | U33: FROZEN FOR FALSIFICATION
A34: MS-HU | B34: HU-A | C34: A04 | D34: Safe state and human boundary | E34: 8 separately safe clinical and refuge zones | F34: ratio | G34: 8 | H34: 7 | I34: 0.15 | J34: 1.2 | K34: 1 | L34: 1.05 | M34: 1 | N34: sterile isolation, refuge, egress and patient rights remain zone-local | O34: rebuild one safe clinical zone | P34: Pass 182 retained | Q34: =Controls!$B$7 -> 0.025 | R34: =IF(AND(ISNUMBER(J34),ISNUMBER(K34),K34>0),J34/K34*(1-Q34),"") -> 1.17 | S34: =IF(AND(ISNUMBER(L34),ISNUMBER(M34),M34>0),L34/M34*(1-Q34),"") -> 1.02375 | T34: =IF(AND(ISNUMBER(R34),ISNUMBER(S34)),MIN(R34,S34)-Controls!$B$8,"") -> 0.02375 | U34: FROZEN FOR FALSIFICATION
A35: MS-HU | B35: HU-A | C35: A05 | D35: Residual and environmental custody | E35: 6 clinical residual cells | F35: t/day | G35: 6 | H35: 5 | I35: 73.5 | J35: 441 | K35: 350 | L35: 367.5 | M35: 350 | N35: sterile and dirty counterflow, quarantine and disposal remain separate | O35: rebuild residual cell and signed disposition | P35: Pass 182 retained | Q35: =Controls!$B$7 -> 0.025 | R35: =IF(AND(ISNUMBER(J35),ISNUMBER(K35),K35>0),J35/K35*(1-Q35),"") -> 1.2285 | S35: =IF(AND(ISNUMBER(L35),ISNUMBER(M35),M35>0),L35/M35*(1-Q35),"") -> 1.02375 | T35: =IF(AND(ISNUMBER(R35),ISNUMBER(S35)),MIN(R35,S35)-Controls!$B$8,"") -> 0.02375 | U35: FROZEN FOR FALSIFICATION
A36: MS-HU | B36: HU-A | C36: A06 | D36: Removal and cold reconstruction | E36: sealed clinical-island reconstruction chain | F36: h | G36: 1 | H36: 1 | N36: lawful person and relationship records remain public while candidate runtime is absent | O36: outside team recreates all ten care-line interfaces within 168 h | P36: Pass 219 protocol | Q36: =Controls!$B$7 -> 0.025 | R36: =IF(AND(ISNUMBER(J36),ISNUMBER(K36),K36>0),J36/K36*(1-Q36),"") | S36: =IF(AND(ISNUMBER(L36),ISNUMBER(M36),M36>0),L36/M36*(1-Q36),"") | T36: =IF(AND(ISNUMBER(R36),ISNUMBER(S36)),MIN(R36,S36)-Controls!$B$8,"") | U36: FROZEN FOR FALSIFICATION
A37: MS-RT | B37: RT-B | C37: A01 | D37: Mass and material custody | E37: 10 independent 8.40 kt process-access cells | F37: t | G37: 10 | H37: 9 | I37: 8400 | J37: 84000 | K37: 72000 | L37: 75600 | M37: 72000 | N37: feedstock, tooling, product and rejected material remain serially attributable | O37: rebuild one process-access cell | P37: Pass 182 retained | Q37: =Controls!$B$7 -> 0.025 | R37: =IF(AND(ISNUMBER(J37),ISNUMBER(K37),K37>0),J37/K37*(1-Q37),"") -> 1.1375 | S37: =IF(AND(ISNUMBER(L37),ISNUMBER(M37),M37>0),L37/M37*(1-Q37),"") -> 1.02375 | T37: =IF(AND(ISNUMBER(R37),ISNUMBER(S37)),MIN(R37,S37)-Controls!$B$8,"") -> 0.02375 | U37: FROZEN FOR FALSIFICATION
A38: MS-RT | B38: RT-B | C38: A02 | D38: Energy and heat | E38: 7 isolated process-energy cells | F38: MW | G38: 7 | H38: 6 | I38: 26.5 | J38: 185.5 | K38: 155 | L38: 159 | M38: 155 | N38: cell-local conversion, black start and process heat rejection | O38: rebuild one 26.5 MW process-energy cell | P38: RZ-11 | Q38: =Controls!$B$7 -> 0.025 | R38: =IF(AND(ISNUMBER(J38),ISNUMBER(K38),K38>0),J38/K38*(1-Q38),"") -> 1.1668548 | S38: =IF(AND(ISNUMBER(L38),ISNUMBER(M38),M38>0),L38/M38*(1-Q38),"") -> 1.0001613 | T38: =IF(AND(ISNUMBER(R38),ISNUMBER(S38)),MIN(R38,S38)-Controls!$B$8,"") -> 0.00016129032 | U38: FROZEN FOR FALSIFICATION
A39: MS-RT | B39: RT-B | C39: A03 | D39: Geometry and load path | E39: 5 complete disconnected process meshes | F39: ratio | G39: 5 | H39: 4 | I39: 0.26 | J39: 1.3 | K39: 1 | L39: 1.04 | M39: 1 | N39: each mesh spans dirty return, diagnosis, manufacture, inspection and release | O39: rebuild one complete mesh from public interfaces | P39: Pass 182 retained | Q39: =Controls!$B$7 -> 0.025 | R39: =IF(AND(ISNUMBER(J39),ISNUMBER(K39),K39>0),J39/K39*(1-Q39),"") -> 1.2675 | S39: =IF(AND(ISNUMBER(L39),ISNUMBER(M39),M39>0),L39/M39*(1-Q39),"") -> 1.014 | T39: =IF(AND(ISNUMBER(R39),ISNUMBER(S39)),MIN(R39,S39)-Controls!$B$8,"") -> 0.014 | U39: FROZEN FOR FALSIFICATION
A40: MS-RT | B40: RT-B | C40: A04 | D40: Safe state and human boundary | E40: 9 independent release and receiver envelopes | F40: ratio | G40: 9 | H40: 8 | I40: 0.13125 | J40: 1.18125 | K40: 1 | L40: 1.05 | M40: 1 | N40: quarantine, manual stop and signed release remain locally enforceable | O40: rebuild one receiver/release envelope | P40: Pass 182 retained | Q40: =Controls!$B$7 -> 0.025 | R40: =IF(AND(ISNUMBER(J40),ISNUMBER(K40),K40>0),J40/K40*(1-Q40),"") -> 1.1517187 | S40: =IF(AND(ISNUMBER(L40),ISNUMBER(M40),M40>0),L40/M40*(1-Q40),"") -> 1.02375 | T40: =IF(AND(ISNUMBER(R40),ISNUMBER(S40)),MIN(R40,S40)-Controls!$B$8,"") -> 0.02375 | U40: FROZEN FOR FALSIFICATION
A41: MS-RT | B41: RT-B | C41: A05 | D41: Residual and environmental custody | E41: 6 rejected-material treatment cells | F41: t/day | G41: 6 | H41: 5 | I41: 252 | J41: 1512 | K41: 1200 | L41: 1260 | M41: 1200 | N41: dirty input, reject, recovery and disposal balance per cell | O41: rebuild residual treatment and reconcile material ancestry | P41: Pass 182 retained | Q41: =Controls!$B$7 -> 0.025 | R41: =IF(AND(ISNUMBER(J41),ISNUMBER(K41),K41>0),J41/K41*(1-Q41),"") -> 1.2285 | S41: =IF(AND(ISNUMBER(L41),ISNUMBER(M41),M41>0),L41/M41*(1-Q41),"") -> 1.02375 | T41: =IF(AND(ISNUMBER(R41),ISNUMBER(S41)),MIN(R41,S41)-Controls!$B$8,"") -> 0.02375 | U41: FROZEN FOR FALSIFICATION
A42: MS-RT | B42: RT-B | C42: A06 | D42: Removal and cold reconstruction | E42: sealed microfactory reconstruction chain | F42: h | G42: 1 | H42: 1 | N42: public material and calibration standards survive loss of process planner | O42: outside team recreates dirty-return-to-release mesh within 168 h | P42: Pass 219 protocol | Q42: =Controls!$B$7 -> 0.025 | R42: =IF(AND(ISNUMBER(J42),ISNUMBER(K42),K42>0),J42/K42*(1-Q42),"") | S42: =IF(AND(ISNUMBER(L42),ISNUMBER(M42),M42>0),L42/M42*(1-Q42),"") | T42: =IF(AND(ISNUMBER(R42),ISNUMBER(S42)),MIN(R42,S42)-Controls!$B$8,"") | U42: FROZEN FOR FALSIFICATION

Sheet Cell Register
A2: One hundred forty-four section-account-world decisions
A4: Sixty cells close by design arithmetic. Eighty-four have executable protocols but require observations. No specification is evidence and no root earns G06.
A6: Cell | B6: System | C6: Root | D6: Account | E6: Closure account | F6: World | G6: World state | H6: Section row | I6: Internal section | J6: Unit | K6: Capacity / limit | L6: Requirement / burden | M6: Adverse screen | N6: Lower-bound ratio | O6: Successor specification | P6: Specification executable | Q6: Evidence accepted | R6: G06 credit | S6: Disposition | T6: Basis | U6: Host contribution
A7: ET-A-A01-W01 | B7: MS-ET | C7: ET-A | D7: A01 | E7: Mass and material custody | F7: W01 | G7: Nominal mission | H7: 7 | I7: 8 independent access cells | J7: t | K7: =IF(ISNUMBER('Section Bills'!J7),'Section Bills'!J7,"") -> 128000 | L7: =IF(ISNUMBER('Section Bills'!K7),'Section Bills'!K7,"") -> 102000 | M7: =Controls!$B$7 -> 0.025 | N7: =IF(AND(ISNUMBER(K7),ISNUMBER(L7),L7>0),K7/L7*(1-M7),"") -> 1.2235294 | P7: =IF(O7="",0,COUNTIFS('Gap Migration'!$G$7:$G$91,O7,'Gap Migration'!$J$7:$J$91,1)) -> 0 | Q7: 0 | R7: 0 | S7: =IF(ISNUMBER(N7),IF(N7>=Controls!$B$8,"DESIGN CLOSE","NEGATIVE"),IF(P7=1,"MEASUREMENT READY","UNSCOPED")) -> DESIGN CLOSE | T7: =IF(S7="DESIGN CLOSE","root-native section bill",IF(S7="MEASUREMENT READY","executable protocol; observation empty","return to architecture")) -> root-native section bill | U7: 0
A8: ET-A-A01-W02 | B8: MS-ET | C8: ET-A | D8: A01 | E8: Mass and material custody | F8: W02 | G8: Fatal-keystone challenge | H8: 7 | I8: 8 independent access cells | J8: t | M8: =Controls!$B$7 -> 0.025 | N8: =IF(AND(ISNUMBER(K8),ISNUMBER(L8),L8>0),K8/L8*(1-M8),"") | O8: KX-ET-A-A01 | P8: =IF(O8="",0,COUNTIFS('Gap Migration'!$G$7:$G$91,O8,'Gap Migration'!$J$7:$J$91,1)) -> 1 | Q8: 0 | R8: 0 | S8: =IF(ISNUMBER(N8),IF(N8>=Controls!$B$8,"DESIGN CLOSE","NEGATIVE"),IF(P8=1,"MEASUREMENT READY","UNSCOPED")) -> MEASUREMENT READY | T8: =IF(S8="DESIGN CLOSE","root-native section bill",IF(S8="MEASUREMENT READY","executable protocol; observation empty","return to architecture")) -> executable protocol; observation empty | U8: 0
A9: ET-A-A01-W03 | B9: MS-ET | C9: ET-A | D9: A01 | E9: Mass and material custody | F9: W03 | G9: Largest-independent-cell loss | H9: 7 | I9: 8 independent access cells | J9: t | K9: =IF(ISNUMBER('Section Bills'!L7),'Section Bills'!L7,"") -> 112000 | L9: =IF(ISNUMBER('Section Bills'!M7),'Section Bills'!M7,"") -> 102000 | M9: =Controls!$B$7 -> 0.025 | N9: =IF(AND(ISNUMBER(K9),ISNUMBER(L9),L9>0),K9/L9*(1-M9),"") -> 1.0705882 | P9: =IF(O9="",0,COUNTIFS('Gap Migration'!$G$7:$G$91,O9,'Gap Migration'!$J$7:$J$91,1)) -> 0 | Q9: 0 | R9: 0 | S9: =IF(ISNUMBER(N9),IF(N9>=Controls!$B$8,"DESIGN CLOSE","NEGATIVE"),IF(P9=1,"MEASUREMENT READY","UNSCOPED")) -> DESIGN CLOSE | T9: =IF(S9="DESIGN CLOSE","root-native section bill",IF(S9="MEASUREMENT READY","executable protocol; observation empty","return to architecture")) -> root-native section bill | U9: 0
A10: ET-A-A01-W04 | B10: MS-ET | C10: ET-A | D10: A01 | E10: Mass and material custody | F10: W04 | G10: Cold reconstruction | H10: 7 | I10: 8 independent access cells | J10: t | M10: =Controls!$B$7 -> 0.025 | N10: =IF(AND(ISNUMBER(K10),ISNUMBER(L10),L10>0),K10/L10*(1-M10),"") | O10: RC-ET-A-A01 | P10: =IF(O10="",0,COUNTIFS('Gap Migration'!$G$7:$G$91,O10,'Gap Migration'!$J$7:$J$91,1)) -> 1 | Q10: 0 | R10: 0 | S10: =IF(ISNUMBER(N10),IF(N10>=Controls!$B$8,"DESIGN CLOSE","NEGATIVE"),IF(P10=1,"MEASUREMENT READY","UNSCOPED")) -> MEASUREMENT READY | T10: =IF(S10="DESIGN CLOSE","root-native section bill",IF(S10="MEASUREMENT READY","executable protocol; observation empty","return to architecture")) -> executable protocol; observation empty | U10: 0
A11: ET-A-A02-W01 | B11: MS-ET | C11: ET-A | D11: A02 | E11: Energy and heat | F11: W01 | G11: Nominal mission | H11: 8 | I11: 6 black-start generation cells | J11: MW | K11: =IF(ISNUMBER('Section Bills'!J8),'Section Bills'!J8,"") -> 120 | L11: =IF(ISNUMBER('Section Bills'!K8),'Section Bills'!K8,"") -> 96 | M11: =Controls!$B$7 -> 0.025 | N11: =IF(AND(ISNUMBER(K11),ISNUMBER(L11),L11>0),K11/L11*(1-M11),"") -> 1.21875 | P11: =IF(O11="",0,COUNTIFS('Gap Migration'!$G$7:$G$91,O11,'Gap Migration'!$J$7:$J$91,1)) -> 0 | Q11: 0 | R11: 0 | S11: =IF(ISNUMBER(N11),IF(N11>=Controls!$B$8,"DESIGN CLOSE","NEGATIVE"),IF(P11=1,"MEASUREMENT READY","UNSCOPED")) -> DESIGN CLOSE | T11: =IF(S11="DESIGN CLOSE","root-native section bill",IF(S11="MEASUREMENT READY","executable protocol; observation empty","return to architecture")) -> root-native section bill | U11: 0
A12: ET-A-A02-W02 | B12: MS-ET | C12: ET-A | D12: A02 | E12: Energy and heat | F12: W02 | G12: Fatal-keystone challenge | H12: 8 | I12: 6 black-start generation cells | J12: MW | M12: =Controls!$B$7 -> 0.025 | N12: =IF(AND(ISNUMBER(K12),ISNUMBER(L12),L12>0),K12/L12*(1-M12),"") | O12: KX-ET-A-A02 | P12: =IF(O12="",0,COUNTIFS('Gap Migration'!$G$7:$G$91,O12,'Gap Migration'!$J$7:$J$91,1)) -> 1 | Q12: 0 | R12: 0 | S12: =IF(ISNUMBER(N12),IF(N12>=Controls!$B$8,"DESIGN CLOSE","NEGATIVE"),IF(P12=1,"MEASUREMENT READY","UNSCOPED")) -> MEASUREMENT READY | T12: =IF(S12="DESIGN CLOSE","root-native section bill",IF(S12="MEASUREMENT READY","executable protocol; observation empty","return to architecture")) -> executable protocol; observation empty | U12: 0
A13: ET-A-A02-W03 | B13: MS-ET | C13: ET-A | D13: A02 | E13: Energy and heat | F13: W03 | G13: Largest-independent-cell loss | H13: 8 | I13: 6 black-start generation cells | J13: MW | K13: =IF(ISNUMBER('Section Bills'!L8),'Section Bills'!L8,"") -> 100 | L13: =IF(ISNUMBER('Section Bills'!M8),'Section Bills'!M8,"") -> 96 | M13: =Controls!$B$7 -> 0.025 | N13: =IF(AND(ISNUMBER(K13),ISNUMBER(L13),L13>0),K13/L13*(1-M13),"") -> 1.015625 | P13: =IF(O13="",0,COUNTIFS('Gap Migration'!$G$7:$G$91,O13,'Gap Migration'!$J$7:$J$91,1)) -> 0 | Q13: 0 | R13: 0 | S13: =IF(ISNUMBER(N13),IF(N13>=Controls!$B$8,"DESIGN CLOSE","NEGATIVE"),IF(P13=1,"MEASUREMENT READY","UNSCOPED")) -> DESIGN CLOSE | T13: =IF(S13="DESIGN CLOSE","root-native section bill",IF(S13="MEASUREMENT READY","executable protocol; observation empty","return to architecture")) -> root-native section bill | U13: 0
A14: ET-A-A02-W04 | B14: MS-ET | C14: ET-A | D14: A02 | E14: Energy and heat | F14: W04 | G14: Cold reconstruction | H14: 8 | I14: 6 black-start generation cells | J14: MW | M14: =Controls!$B$7 -> 0.025 | N14: =IF(AND(ISNUMBER(K14),ISNUMBER(L14),L14>0),K14/L14*(1-M14),"") | O14: RC-ET-A-A02 | P14: =IF(O14="",0,COUNTIFS('Gap Migration'!$G$7:$G$91,O14,'Gap Migration'!$J$7:$J$91,1)) -> 1 | Q14: 0 | R14: 0 | S14: =IF(ISNUMBER(N14),IF(N14>=Controls!$B$8,"DESIGN CLOSE","NEGATIVE"),IF(P14=1,"MEASUREMENT READY","UNSCOPED")) -> MEASUREMENT READY | T14: =IF(S14="DESIGN CLOSE","root-native section bill",IF(S14="MEASUREMENT READY","executable protocol; observation empty","return to architecture")) -> executable protocol; observation empty | U14: 0
A15: ET-A-A03-W01 | B15: MS-ET | C15: ET-A | D15: A03 | E15: Geometry and load path | F15: W01 | G15: Nominal mission | H15: 9 | I15: 2 complete motion-decoupled exchange paths | J15: t/h | K15: =IF(ISNUMBER('Section Bills'!J9),'Section Bills'!J9,"") -> 482 | L15: =IF(ISNUMBER('Section Bills'!K9),'Section Bills'!K9,"") -> 234.58333 | M15: =Controls!$B$7 -> 0.025 | N15: =IF(AND(ISNUMBER(K15),ISNUMBER(L15),L15>0),K15/L15*(1-M15),"") -> 2.0033393 | P15: =IF(O15="",0,COUNTIFS('Gap Migration'!$G$7:$G$91,O15,'Gap Migration'!$J$7:$J$91,1)) -> 0 | Q15: 0 | R15: 0 | S15: =IF(ISNUMBER(N15),IF(N15>=Controls!$B$8,"DESIGN CLOSE","NEGATIVE"),IF(P15=1,"MEASUREMENT READY","UNSCOPED")) -> DESIGN CLOSE | T15: =IF(S15="DESIGN CLOSE","root-native section bill",IF(S15="MEASUREMENT READY","executable protocol; observation empty","return to architecture")) -> root-native section bill | U15: 0
A16: ET-A-A03-W02 | B16: MS-ET | C16: ET-A | D16: A03 | E16: Geometry and load path | F16: W02 | G16: Fatal-keystone challenge | H16: 9 | I16: 2 complete motion-decoupled exchange paths | J16: t/h | M16: =Controls!$B$7 -> 0.025 | N16: =IF(AND(ISNUMBER(K16),ISNUMBER(L16),L16>0),K16/L16*(1-M16),"") | O16: KX-ET-A-A03 | P16: =IF(O16="",0,COUNTIFS('Gap Migration'!$G$7:$G$91,O16,'Gap Migration'!$J$7:$J$91,1)) -> 1 | Q16: 0 | R16: 0 | S16: =IF(ISNUMBER(N16),IF(N16>=Controls!$B$8,"DESIGN CLOSE","NEGATIVE"),IF(P16=1,"MEASUREMENT READY","UNSCOPED")) -> MEASUREMENT READY | T16: =IF(S16="DESIGN CLOSE","root-native section bill",IF(S16="MEASUREMENT READY","executable protocol; observation empty","return to architecture")) -> executable protocol; observation empty | U16: 0
A17: ET-A-A03-W03 | B17: MS-ET | C17: ET-A | D17: A03 | E17: Geometry and load path | F17: W03 | G17: Largest-independent-cell loss | H17: 9 | I17: 2 complete motion-decoupled exchange paths | J17: t/h | K17: =IF(ISNUMBER('Section Bills'!L9),'Section Bills'!L9,"") -> 241 | L17: =IF(ISNUMBER('Section Bills'!M9),'Section Bills'!M9,"") -> 234.58333 | M17: =Controls!$B$7 -> 0.025 | N17: =IF(AND(ISNUMBER(K17),ISNUMBER(L17),L17>0),K17/L17*(1-M17),"") -> 1.0016696 | P17: =IF(O17="",0,COUNTIFS('Gap Migration'!$G$7:$G$91,O17,'Gap Migration'!$J$7:$J$91,1)) -> 0 | Q17: 0 | R17: 0 | S17: =IF(ISNUMBER(N17),IF(N17>=Controls!$B$8,"DESIGN CLOSE","NEGATIVE"),IF(P17=1,"MEASUREMENT READY","UNSCOPED")) -> DESIGN CLOSE | T17: =IF(S17="DESIGN CLOSE","root-native section bill",IF(S17="MEASUREMENT READY","executable protocol; observation empty","return to architecture")) -> root-native section bill | U17: 0
A18: ET-A-A03-W04 | B18: MS-ET | C18: ET-A | D18: A03 | E18: Geometry and load path | F18: W04 | G18: Cold reconstruction | H18: 9 | I18: 2 complete motion-decoupled exchange paths | J18: t/h | M18: =Controls!$B$7 -> 0.025 | N18: =IF(AND(ISNUMBER(K18),ISNUMBER(L18),L18>0),K18/L18*(1-M18),"") | O18: RC-ET-A-A03 | P18: =IF(O18="",0,COUNTIFS('Gap Migration'!$G$7:$G$91,O18,'Gap Migration'!$J$7:$J$91,1)) -> 1 | Q18: 0 | R18: 0 | S18: =IF(ISNUMBER(N18),IF(N18>=Controls!$B$8,"DESIGN CLOSE","NEGATIVE"),IF(P18=1,"MEASUREMENT READY","UNSCOPED")) -> MEASUREMENT READY | T18: =IF(S18="DESIGN CLOSE","root-native section bill",IF(S18="MEASUREMENT READY","executable protocol; observation empty","return to architecture")) -> executable protocol; observation empty | U18: 0
A19: ET-A-A04-W01 | B19: MS-ET | C19: ET-A | D19: A04 | E19: Safe state and human boundary | F19: W01 | G19: Nominal mission | H19: 10 | I19: 6 independent refuge and receiver zones | J19: ratio | K19: =IF(ISNUMBER('Section Bills'!J10),'Section Bills'!J10,"") -> 1.26 | L19: =IF(ISNUMBER('Section Bills'!K10),'Section Bills'!K10,"") -> 1 | M19: =Controls!$B$7 -> 0.025 | N19: =IF(AND(ISNUMBER(K19),ISNUMBER(L19),L19>0),K19/L19*(1-M19),"") -> 1.2285 | P19: =IF(O19="",0,COUNTIFS('Gap Migration'!$G$7:$G$91,O19,'Gap Migration'!$J$7:$J$91,1)) -> 0 | Q19: 0 | R19: 0 | S19: =IF(ISNUMBER(N19),IF(N19>=Controls!$B$8,"DESIGN CLOSE","NEGATIVE"),IF(P19=1,"MEASUREMENT READY","UNSCOPED")) -> DESIGN CLOSE | T19: =IF(S19="DESIGN CLOSE","root-native section bill",IF(S19="MEASUREMENT READY","executable protocol; observation empty","return to architecture")) -> root-native section bill | U19: 0
A20: ET-A-A04-W02 | B20: MS-ET | C20: ET-A | D20: A04 | E20: Safe state and human boundary | F20: W02 | G20: Fatal-keystone challenge | H20: 10 | I20: 6 independent refuge and receiver zones | J20: ratio | M20: =Controls!$B$7 -> 0.025 | N20: =IF(AND(ISNUMBER(K20),ISNUMBER(L20),L20>0),K20/L20*(1-M20),"") | O20: KX-ET-A-A04 | P20: =IF(O20="",0,COUNTIFS('Gap Migration'!$G$7:$G$91,O20,'Gap Migration'!$J$7:$J$91,1)) -> 1 | Q20: 0 | R20: 0 | S20: =IF(ISNUMBER(N20),IF(N20>=Controls!$B$8,"DESIGN CLOSE","NEGATIVE"),IF(P20=1,"MEASUREMENT READY","UNSCOPED")) -> MEASUREMENT READY | T20: =IF(S20="DESIGN CLOSE","root-native section bill",IF(S20="MEASUREMENT READY","executable protocol; observation empty","return to architecture")) -> executable protocol; observation empty | U20: 0
A21: ET-A-A04-W03 | B21: MS-ET | C21: ET-A | D21: A04 | E21: Safe state and human boundary | F21: W03 | G21: Largest-independent-cell loss | H21: 10 | I21: 6 independent refuge and receiver zones | J21: ratio | K21: =IF(ISNUMBER('Section Bills'!L10),'Section Bills'!L10,"") -> 1.05 | L21: =IF(ISNUMBER('Section Bills'!M10),'Section Bills'!M10,"") -> 1 | M21: =Controls!$B$7 -> 0.025 | N21: =IF(AND(ISNUMBER(K21),ISNUMBER(L21),L21>0),K21/L21*(1-M21),"") -> 1.02375 | P21: =IF(O21="",0,COUNTIFS('Gap Migration'!$G$7:$G$91,O21,'Gap Migration'!$J$7:$J$91,1)) -> 0 | Q21: 0 | R21: 0 | S21: =IF(ISNUMBER(N21),IF(N21>=Controls!$B$8,"DESIGN CLOSE","NEGATIVE"),IF(P21=1,"MEASUREMENT READY","UNSCOPED")) -> DESIGN CLOSE | T21: =IF(S21="DESIGN CLOSE","root-native section bill",IF(S21="MEASUREMENT READY","executable protocol; observation empty","return to architecture")) -> root-native section bill | U21: 0
A22: ET-A-A04-W04 | B22: MS-ET | C22: ET-A | D22: A04 | E22: Safe state and human boundary | F22: W04 | G22: Cold reconstruction | H22: 10 | I22: 6 independent refuge and receiver zones | J22: ratio | M22: =Controls!$B$7 -> 0.025 | N22: =IF(AND(ISNUMBER(K22),ISNUMBER(L22),L22>0),K22/L22*(1-M22),"") | O22: RC-ET-A-A04 | P22: =IF(O22="",0,COUNTIFS('Gap Migration'!$G$7:$G$91,O22,'Gap Migration'!$J$7:$J$91,1)) -> 1 | Q22: 0 | R22: 0 | S22: =IF(ISNUMBER(N22),IF(N22>=Controls!$B$8,"DESIGN CLOSE","NEGATIVE"),IF(P22=1,"MEASUREMENT READY","UNSCOPED")) -> MEASUREMENT READY | T22: =IF(S22="DESIGN CLOSE","root-native section bill",IF(S22="MEASUREMENT READY","executable protocol; observation empty","return to architecture")) -> executable protocol; observation empty | U22: 0
A23: ET-A-A05-W01 | B23: MS-ET | C23: ET-A | D23: A05 | E23: Residual and environmental custody | F23: W01 | G23: Nominal mission | H23: 11 | I23: 6 contained residual cells | J23: t/day | K23: =IF(ISNUMBER('Section Bills'!J11),'Section Bills'!J11,"") -> 1512 | L23: =IF(ISNUMBER('Section Bills'!K11),'Section Bills'!K11,"") -> 1200 | M23: =Controls!$B$7 -> 0.025 | N23: =IF(AND(ISNUMBER(K23),ISNUMBER(L23),L23>0),K23/L23*(1-M23),"") -> 1.2285 | P23: =IF(O23="",0,COUNTIFS('Gap Migration'!$G$7:$G$91,O23,'Gap Migration'!$J$7:$J$91,1)) -> 0 | Q23: 0 | R23: 0 | S23: =IF(ISNUMBER(N23),IF(N23>=Controls!$B$8,"DESIGN CLOSE","NEGATIVE"),IF(P23=1,"MEASUREMENT READY","UNSCOPED")) -> DESIGN CLOSE | T23: =IF(S23="DESIGN CLOSE","root-native section bill",IF(S23="MEASUREMENT READY","executable protocol; observation empty","return to architecture")) -> root-native section bill | U23: 0
A24: ET-A-A05-W02 | B24: MS-ET | C24: ET-A | D24: A05 | E24: Residual and environmental custody | F24: W02 | G24: Fatal-keystone challenge | H24: 11 | I24: 6 contained residual cells | J24: t/day | M24: =Controls!$B$7 -> 0.025 | N24: =IF(AND(ISNUMBER(K24),ISNUMBER(L24),L24>0),K24/L24*(1-M24),"") | O24: KX-ET-A-A05 | P24: =IF(O24="",0,COUNTIFS('Gap Migration'!$G$7:$G$91,O24,'Gap Migration'!$J$7:$J$91,1)) -> 1 | Q24: 0 | R24: 0 | S24: =IF(ISNUMBER(N24),IF(N24>=Controls!$B$8,"DESIGN CLOSE","NEGATIVE"),IF(P24=1,"MEASUREMENT READY","UNSCOPED")) -> MEASUREMENT READY | T24: =IF(S24="DESIGN CLOSE","root-native section bill",IF(S24="MEASUREMENT READY","executable protocol; observation empty","return to architecture")) -> executable protocol; observation empty | U24: 0
A25: ET-A-A05-W03 | B25: MS-ET | C25: ET-A | D25: A05 | E25: Residual and environmental custody | F25: W03 | G25: Largest-independent-cell loss | H25: 11 | I25: 6 contained residual cells | J25: t/day | K25: =IF(ISNUMBER('Section Bills'!L11),'Section Bills'!L11,"") -> 1260 | L25: =IF(ISNUMBER('Section Bills'!M11),'Section Bills'!M11,"") -> 1200 | M25: =Controls!$B$7 -> 0.025 | N25: =IF(AND(ISNUMBER(K25),ISNUMBER(L25),L25>0),K25/L25*(1-M25),"") -> 1.02375 | P25: =IF(O25="",0,COUNTIFS('Gap Migration'!$G$7:$G$91,O25,'Gap Migration'!$J$7:$J$91,1)) -> 0 | Q25: 0 | R25: 0 | S25: =IF(ISNUMBER(N25),IF(N25>=Controls!$B$8,"DESIGN CLOSE","NEGATIVE"),IF(P25=1,"MEASUREMENT READY","UNSCOPED")) -> DESIGN CLOSE | T25: =IF(S25="DESIGN CLOSE","root-native section bill",IF(S25="MEASUREMENT READY","executable protocol; observation empty","return to architecture")) -> root-native section bill | U25: 0
A26: ET-A-A05-W04 | B26: MS-ET | C26: ET-A | D26: A05 | E26: Residual and environmental custody | F26: W04 | G26: Cold reconstruction | H26: 11 | I26: 6 contained residual cells | J26: t/day | M26: =Controls!$B$7 -> 0.025 | N26: =IF(AND(ISNUMBER(K26),ISNUMBER(L26),L26>0),K26/L26*(1-M26),"") | O26: RC-ET-A-A05 | P26: =IF(O26="",0,COUNTIFS('Gap Migration'!$G$7:$G$91,O26,'Gap Migration'!$J$7:$J$91,1)) -> 1 | Q26: 0 | R26: 0 | S26: =IF(ISNUMBER(N26),IF(N26>=Controls!$B$8,"DESIGN CLOSE","NEGATIVE"),IF(P26=1,"MEASUREMENT READY","UNSCOPED")) -> MEASUREMENT READY | T26: =IF(S26="DESIGN CLOSE","root-native section bill",IF(S26="MEASUREMENT READY","executable protocol; observation empty","return to architecture")) -> executable protocol; observation empty | U26: 0
A27: ET-A-A06-W01 | B27: MS-ET | C27: ET-A | D27: A06 | E27: Removal and cold reconstruction | F27: W01 | G27: Nominal mission | H27: 12 | I27: sealed exchange-section reconstruction chain | J27: h | M27: =Controls!$B$7 -> 0.025 | N27: =IF(AND(ISNUMBER(K27),ISNUMBER(L27),L27>0),K27/L27*(1-M27),"") | O27: RB-ET-A-W01 | P27: =IF(O27="",0,COUNTIFS('Gap Migration'!$G$7:$G$91,O27,'Gap Migration'!$J$7:$J$91,1)) -> 1 | Q27: 0 | R27: 0 | S27: =IF(ISNUMBER(N27),IF(N27>=Controls!$B$8,"DESIGN CLOSE","NEGATIVE"),IF(P27=1,"MEASUREMENT READY","UNSCOPED")) -> MEASUREMENT READY | T27: =IF(S27="DESIGN CLOSE","root-native section bill",IF(S27="MEASUREMENT READY","executable protocol; observation empty","return to architecture")) -> executable protocol; observation empty | U27: 0
A28: ET-A-A06-W02 | B28: MS-ET | C28: ET-A | D28: A06 | E28: Removal and cold reconstruction | F28: W02 | G28: Fatal-keystone challenge | H28: 12 | I28: sealed exchange-section reconstruction chain | J28: h | M28: =Controls!$B$7 -> 0.025 | N28: =IF(AND(ISNUMBER(K28),ISNUMBER(L28),L28>0),K28/L28*(1-M28),"") | O28: KX-ET-A-A06 | P28: =IF(O28="",0,COUNTIFS('Gap Migration'!$G$7:$G$91,O28,'Gap Migration'!$J$7:$J$91,1)) -> 1 | Q28: 0 | R28: 0 | S28: =IF(ISNUMBER(N28),IF(N28>=Controls!$B$8,"DESIGN CLOSE","NEGATIVE"),IF(P28=1,"MEASUREMENT READY","UNSCOPED")) -> MEASUREMENT READY | T28: =IF(S28="DESIGN CLOSE","root-native section bill",IF(S28="MEASUREMENT READY","executable protocol; observation empty","return to architecture")) -> executable protocol; observation empty | U28: 0
A29: ET-A-A06-W03 | B29: MS-ET | C29: ET-A | D29: A06 | E29: Removal and cold reconstruction | F29: W03 | G29: Largest-independent-cell loss | H29: 12 | I29: sealed exchange-section reconstruction chain | J29: h | M29: =Controls!$B$7 -> 0.025 | N29: =IF(AND(ISNUMBER(K29),ISNUMBER(L29),L29>0),K29/L29*(1-M29),"") | O29: RB-ET-A-W03 | P29: =IF(O29="",0,COUNTIFS('Gap Migration'!$G$7:$G$91,O29,'Gap Migration'!$J$7:$J$91,1)) -> 1 | Q29: 0 | R29: 0 | S29: =IF(ISNUMBER(N29),IF(N29>=Controls!$B$8,"DESIGN CLOSE","NEGATIVE"),IF(P29=1,"MEASUREMENT READY","UNSCOPED")) -> MEASUREMENT READY | T29: =IF(S29="DESIGN CLOSE","root-native section bill",IF(S29="MEASUREMENT READY","executable protocol; observation empty","return to architecture")) -> executable protocol; observation empty | U29: 0
A30: ET-A-A06-W04 | B30: MS-ET | C30: ET-A | D30: A06 | E30: Removal and cold reconstruction | F30: W04 | G30: Cold reconstruction | H30: 12 | I30: sealed exchange-section reconstruction chain | J30: h | M30: =Controls!$B$7 -> 0.025 | N30: =IF(AND(ISNUMBER(K30),ISNUMBER(L30),L30>0),K30/L30*(1-M30),"") | O30: RC-ET-A-A06 | P30: =IF(O30="",0,COUNTIFS('Gap Migration'!$G$7:$G$91,O30,'Gap Migration'!$J$7:$J$91,1)) -> 1 | Q30: 0 | R30: 0 | S30: =IF(ISNUMBER(N30),IF(N30>=Controls!$B$8,"DESIGN CLOSE","NEGATIVE"),IF(P30=1,"MEASUREMENT READY","UNSCOPED")) -> MEASUREMENT READY | T30: =IF(S30="DESIGN CLOSE","root-native section bill",IF(S30="MEASUREMENT READY","executable protocol; observation empty","return to architecture")) -> executable protocol; observation empty | U30: 0
A31: CT-C-A01-W01 | B31: MS-CT | C31: CT-C | D31: A01 | E31: Mass and material custody | F31: W01 | G31: Nominal mission | H31: 13 | I31: 10 independently admitted insertion cells | J31: t | K31: =IF(ISNUMBER('Section Bills'!J13),'Section Bills'!J13,"") -> 36000 | L31: =IF(ISNUMBER('Section Bills'!K13),'Section Bills'!K13,"") -> 31000 | M31: =Controls!$B$7 -> 0.025 | N31: =IF(AND(ISNUMBER(K31),ISNUMBER(L31),L31>0),K31/L31*(1-M31),"") -> 1.1322581 | P31: =IF(O31="",0,COUNTIFS('Gap Migration'!$G$7:$G$91,O31,'Gap Migration'!$J$7:$J$91,1)) -> 0 | Q31: 0 | R31: 0 | S31: =IF(ISNUMBER(N31),IF(N31>=Controls!$B$8,"DESIGN CLOSE","NEGATIVE"),IF(P31=1,"MEASUREMENT READY","UNSCOPED")) -> DESIGN CLOSE | T31: =IF(S31="DESIGN CLOSE","root-native section bill",IF(S31="MEASUREMENT READY","executable protocol; observation empty","return to architecture")) -> root-native section bill | U31: 0
A32: CT-C-A01-W02 | B32: MS-CT | C32: CT-C | D32: A01 | E32: Mass and material custody | F32: W02 | G32: Fatal-keystone challenge | H32: 13 | I32: 10 independently admitted insertion cells | J32: t | M32: =Controls!$B$7 -> 0.025 | N32: =IF(AND(ISNUMBER(K32),ISNUMBER(L32),L32>0),K32/L32*(1-M32),"") | O32: KX-CT-C-A01 | P32: =IF(O32="",0,COUNTIFS('Gap Migration'!$G$7:$G$91,O32,'Gap Migration'!$J$7:$J$91,1)) -> 1 | Q32: 0 | R32: 0 | S32: =IF(ISNUMBER(N32),IF(N32>=Controls!$B$8,"DESIGN CLOSE","NEGATIVE"),IF(P32=1,"MEASUREMENT READY","UNSCOPED")) -> MEASUREMENT READY | T32: =IF(S32="DESIGN CLOSE","root-native section bill",IF(S32="MEASUREMENT READY","executable protocol; observation empty","return to architecture")) -> executable protocol; observation empty | U32: 0
A33: CT-C-A01-W03 | B33: MS-CT | C33: CT-C | D33: A01 | E33: Mass and material custody | F33: W03 | G33: Largest-independent-cell loss | H33: 13 | I33: 10 independently admitted insertion cells | J33: t | K33: =IF(ISNUMBER('Section Bills'!L13),'Section Bills'!L13,"") -> 32400 | L33: =IF(ISNUMBER('Section Bills'!M13),'Section Bills'!M13,"") -> 31000 | M33: =Controls!$B$7 -> 0.025 | N33: =IF(AND(ISNUMBER(K33),ISNUMBER(L33),L33>0),K33/L33*(1-M33),"") -> 1.0190323 | P33: =IF(O33="",0,COUNTIFS('Gap Migration'!$G$7:$G$91,O33,'Gap Migration'!$J$7:$J$91,1)) -> 0 | Q33: 0 | R33: 0 | S33: =IF(ISNUMBER(N33),IF(N33>=Controls!$B$8,"DESIGN CLOSE","NEGATIVE"),IF(P33=1,"MEASUREMENT READY","UNSCOPED")) -> DESIGN CLOSE | T33: =IF(S33="DESIGN CLOSE","root-native section bill",IF(S33="MEASUREMENT READY","executable protocol; observation empty","return to architecture")) -> root-native section bill | U33: 0
A34: CT-C-A01-W04 | B34: MS-CT | C34: CT-C | D34: A01 | E34: Mass and material custody | F34: W04 | G34: Cold reconstruction | H34: 13 | I34: 10 independently admitted insertion cells | J34: t | M34: =Controls!$B$7 -> 0.025 | N34: =IF(AND(ISNUMBER(K34),ISNUMBER(L34),L34>0),K34/L34*(1-M34),"") | O34: RC-CT-C-A01 | P34: =IF(O34="",0,COUNTIFS('Gap Migration'!$G$7:$G$91,O34,'Gap Migration'!$J$7:$J$91,1)) -> 1 | Q34: 0 | R34: 0 | S34: =IF(ISNUMBER(N34),IF(N34>=Controls!$B$8,"DESIGN CLOSE","NEGATIVE"),IF(P34=1,"MEASUREMENT READY","UNSCOPED")) -> MEASUREMENT READY | T34: =IF(S34="DESIGN CLOSE","root-native section bill",IF(S34="MEASUREMENT READY","executable protocol; observation empty","return to architecture")) -> executable protocol; observation empty | U34: 0
A35: CT-C-A02-W01 | B35: MS-CT | C35: CT-C | D35: A02 | E35: Energy and heat | F35: W01 | G35: Nominal mission | H35: 14 | I35: 7 isolated generation cells | J35: MW | K35: =IF(ISNUMBER('Section Bills'!J14),'Section Bills'!J14,"") -> 50.4 | L35: =IF(ISNUMBER('Section Bills'!K14),'Section Bills'!K14,"") -> 42 | M35: =Controls!$B$7 -> 0.025 | N35: =IF(AND(ISNUMBER(K35),ISNUMBER(L35),L35>0),K35/L35*(1-M35),"") -> 1.17 | P35: =IF(O35="",0,COUNTIFS('Gap Migration'!$G$7:$G$91,O35,'Gap Migration'!$J$7:$J$91,1)) -> 0 | Q35: 0 | R35: 0 | S35: =IF(ISNUMBER(N35),IF(N35>=Controls!$B$8,"DESIGN CLOSE","NEGATIVE"),IF(P35=1,"MEASUREMENT READY","UNSCOPED")) -> DESIGN CLOSE | T35: =IF(S35="DESIGN CLOSE","root-native section bill",IF(S35="MEASUREMENT READY","executable protocol; observation empty","return to architecture")) -> root-native section bill | U35: 0
A36: CT-C-A02-W02 | B36: MS-CT | C36: CT-C | D36: A02 | E36: Energy and heat | F36: W02 | G36: Fatal-keystone challenge | H36: 14 | I36: 7 isolated generation cells | J36: MW | M36: =Controls!$B$7 -> 0.025 | N36: =IF(AND(ISNUMBER(K36),ISNUMBER(L36),L36>0),K36/L36*(1-M36),"") | O36: KX-CT-C-A02 | P36: =IF(O36="",0,COUNTIFS('Gap Migration'!$G$7:$G$91,O36,'Gap Migration'!$J$7:$J$91,1)) -> 1 | Q36: 0 | R36: 0 | S36: =IF(ISNUMBER(N36),IF(N36>=Controls!$B$8,"DESIGN CLOSE","NEGATIVE"),IF(P36=1,"MEASUREMENT READY","UNSCOPED")) -> MEASUREMENT READY | T36: =IF(S36="DESIGN CLOSE","root-native section bill",IF(S36="MEASUREMENT READY","executable protocol; observation empty","return to architecture")) -> executable protocol; observation empty | U36: 0
A37: CT-C-A02-W03 | B37: MS-CT | C37: CT-C | D37: A02 | E37: Energy and heat | F37: W03 | G37: Largest-independent-cell loss | H37: 14 | I37: 7 isolated generation cells | J37: MW | K37: =IF(ISNUMBER('Section Bills'!L14),'Section Bills'!L14,"") -> 43.2 | L37: =IF(ISNUMBER('Section Bills'!M14),'Section Bills'!M14,"") -> 42 | M37: =Controls!$B$7 -> 0.025 | N37: =IF(AND(ISNUMBER(K37),ISNUMBER(L37),L37>0),K37/L37*(1-M37),"") -> 1.0028571 | P37: =IF(O37="",0,COUNTIFS('Gap Migration'!$G$7:$G$91,O37,'Gap Migration'!$J$7:$J$91,1)) -> 0 | Q37: 0 | R37: 0 | S37: =IF(ISNUMBER(N37),IF(N37>=Controls!$B$8,"DESIGN CLOSE","NEGATIVE"),IF(P37=1,"MEASUREMENT READY","UNSCOPED")) -> DESIGN CLOSE | T37: =IF(S37="DESIGN CLOSE","root-native section bill",IF(S37="MEASUREMENT READY","executable protocol; observation empty","return to architecture")) -> root-native section bill | U37: 0
A38: CT-C-A02-W04 | B38: MS-CT | C38: CT-C | D38: A02 | E38: Energy and heat | F38: W04 | G38: Cold reconstruction | H38: 14 | I38: 7 isolated generation cells | J38: MW | M38: =Controls!$B$7 -> 0.025 | N38: =IF(AND(ISNUMBER(K38),ISNUMBER(L38),L38>0),K38/L38*(1-M38),"") | O38: RC-CT-C-A02 | P38: =IF(O38="",0,COUNTIFS('Gap Migration'!$G$7:$G$91,O38,'Gap Migration'!$J$7:$J$91,1)) -> 1 | Q38: 0 | R38: 0 | S38: =IF(ISNUMBER(N38),IF(N38>=Controls!$B$8,"DESIGN CLOSE","NEGATIVE"),IF(P38=1,"MEASUREMENT READY","UNSCOPED")) -> MEASUREMENT READY | T38: =IF(S38="DESIGN CLOSE","root-native section bill",IF(S38="MEASUREMENT READY","executable protocol; observation empty","return to architecture")) -> executable protocol; observation empty | U38: 0
A39: CT-C-A03-W01 | B39: MS-CT | C39: CT-C | D39: A03 | E39: Geometry and load path | F39: W01 | G39: Nominal mission | H39: 15 | I39: 5 complete multi-utility trunk corridors | J39: ratio | K39: =IF(ISNUMBER('Section Bills'!J15),'Section Bills'!J15,"") -> 1.32 | L39: =IF(ISNUMBER('Section Bills'!K15),'Section Bills'!K15,"") -> 1 | M39: =Controls!$B$7 -> 0.025 | N39: =IF(AND(ISNUMBER(K39),ISNUMBER(L39),L39>0),K39/L39*(1-M39),"") -> 1.287 | P39: =IF(O39="",0,COUNTIFS('Gap Migration'!$G$7:$G$91,O39,'Gap Migration'!$J$7:$J$91,1)) -> 0 | Q39: 0 | R39: 0 | S39: =IF(ISNUMBER(N39),IF(N39>=Controls!$B$8,"DESIGN CLOSE","NEGATIVE"),IF(P39=1,"MEASUREMENT READY","UNSCOPED")) -> DESIGN CLOSE | T39: =IF(S39="DESIGN CLOSE","root-native section bill",IF(S39="MEASUREMENT READY","executable protocol; observation empty","return to architecture")) -> root-native section bill | U39: 0
A40: CT-C-A03-W02 | B40: MS-CT | C40: CT-C | D40: A03 | E40: Geometry and load path | F40: W02 | G40: Fatal-keystone challenge | H40: 15 | I40: 5 complete multi-utility trunk corridors | J40: ratio | M40: =Controls!$B$7 -> 0.025 | N40: =IF(AND(ISNUMBER(K40),ISNUMBER(L40),L40>0),K40/L40*(1-M40),"") | O40: KX-CT-C-A03 | P40: =IF(O40="",0,COUNTIFS('Gap Migration'!$G$7:$G$91,O40,'Gap Migration'!$J$7:$J$91,1)) -> 1 | Q40: 0 | R40: 0 | S40: =IF(ISNUMBER(N40),IF(N40>=Controls!$B$8,"DESIGN CLOSE","NEGATIVE"),IF(P40=1,"MEASUREMENT READY","UNSCOPED")) -> MEASUREMENT READY | T40: =IF(S40="DESIGN CLOSE","root-native section bill",IF(S40="MEASUREMENT READY","executable protocol; observation empty","return to architecture")) -> executable protocol; observation empty | U40: 0
A41: CT-C-A03-W03 | B41: MS-CT | C41: CT-C | D41: A03 | E41: Geometry and load path | F41: W03 | G41: Largest-independent-cell loss | H41: 15 | I41: 5 complete multi-utility trunk corridors | J41: ratio | K41: =IF(ISNUMBER('Section Bills'!L15),'Section Bills'!L15,"") -> 1.056 | L41: =IF(ISNUMBER('Section Bills'!M15),'Section Bills'!M15,"") -> 1 | M41: =Controls!$B$7 -> 0.025 | N41: =IF(AND(ISNUMBER(K41),ISNUMBER(L41),L41>0),K41/L41*(1-M41),"") -> 1.0296 | P41: =IF(O41="",0,COUNTIFS('Gap Migration'!$G$7:$G$91,O41,'Gap Migration'!$J$7:$J$91,1)) -> 0 | Q41: 0 | R41: 0 | S41: =IF(ISNUMBER(N41),IF(N41>=Controls!$B$8,"DESIGN CLOSE","NEGATIVE"),IF(P41=1,"MEASUREMENT READY","UNSCOPED")) -> DESIGN CLOSE | T41: =IF(S41="DESIGN CLOSE","root-native section bill",IF(S41="MEASUREMENT READY","executable protocol; observation empty","return to architecture")) -> root-native section bill | U41: 0
A42: CT-C-A03-W04 | B42: MS-CT | C42: CT-C | D42: A03 | E42: Geometry and load path | F42: W04 | G42: Cold reconstruction | H42: 15 | I42: 5 complete multi-utility trunk corridors | J42: ratio | M42: =Controls!$B$7 -> 0.025 | N42: =IF(AND(ISNUMBER(K42),ISNUMBER(L42),L42>0),K42/L42*(1-M42),"") | O42: RC-CT-C-A03 | P42: =IF(O42="",0,COUNTIFS('Gap Migration'!$G$7:$G$91,O42,'Gap Migration'!$J$7:$J$91,1)) -> 1 | Q42: 0 | R42: 0 | S42: =IF(ISNUMBER(N42),IF(N42>=Controls!$B$8,"DESIGN CLOSE","NEGATIVE"),IF(P42=1,"MEASUREMENT READY","UNSCOPED")) -> MEASUREMENT READY | T42: =IF(S42="DESIGN CLOSE","root-native section bill",IF(S42="MEASUREMENT READY","executable protocol; observation empty","return to architecture")) -> executable protocol; observation empty | U42: 0
A43: CT-C-A04-W01 | B43: MS-CT | C43: CT-C | D43: A04 | E43: Safe state and human boundary | F43: W01 | G43: Nominal mission | H43: 16 | I43: 8 separately safe occupied zones | J43: ratio | K43: =IF(ISNUMBER('Section Bills'!J16),'Section Bills'!J16,"") -> 1.2 | L43: =IF(ISNUMBER('Section Bills'!K16),'Section Bills'!K16,"") -> 1 | M43: =Controls!$B$7 -> 0.025 | N43: =IF(AND(ISNUMBER(K43),ISNUMBER(L43),L43>0),K43/L43*(1-M43),"") -> 1.17 | P43: =IF(O43="",0,COUNTIFS('Gap Migration'!$G$7:$G$91,O43,'Gap Migration'!$J$7:$J$91,1)) -> 0 | Q43: 0 | R43: 0 | S43: =IF(ISNUMBER(N43),IF(N43>=Controls!$B$8,"DESIGN CLOSE","NEGATIVE"),IF(P43=1,"MEASUREMENT READY","UNSCOPED")) -> DESIGN CLOSE | T43: =IF(S43="DESIGN CLOSE","root-native section bill",IF(S43="MEASUREMENT READY","executable protocol; observation empty","return to architecture")) -> root-native section bill | U43: 0
A44: CT-C-A04-W02 | B44: MS-CT | C44: CT-C | D44: A04 | E44: Safe state and human boundary | F44: W02 | G44: Fatal-keystone challenge | H44: 16 | I44: 8 separately safe occupied zones | J44: ratio | M44: =Controls!$B$7 -> 0.025 | N44: =IF(AND(ISNUMBER(K44),ISNUMBER(L44),L44>0),K44/L44*(1-M44),"") | O44: KX-CT-C-A04 | P44: =IF(O44="",0,COUNTIFS('Gap Migration'!$G$7:$G$91,O44,'Gap Migration'!$J$7:$J$91,1)) -> 1 | Q44: 0 | R44: 0 | S44: =IF(ISNUMBER(N44),IF(N44>=Controls!$B$8,"DESIGN CLOSE","NEGATIVE"),IF(P44=1,"MEASUREMENT READY","UNSCOPED")) -> MEASUREMENT READY | T44: =IF(S44="DESIGN CLOSE","root-native section bill",IF(S44="MEASUREMENT READY","executable protocol; observation empty","return to architecture")) -> executable protocol; observation empty | U44: 0
A45: CT-C-A04-W03 | B45: MS-CT | C45: CT-C | D45: A04 | E45: Safe state and human boundary | F45: W03 | G45: Largest-independent-cell loss | H45: 16 | I45: 8 separately safe occupied zones | J45: ratio | K45: =IF(ISNUMBER('Section Bills'!L16),'Section Bills'!L16,"") -> 1.05 | L45: =IF(ISNUMBER('Section Bills'!M16),'Section Bills'!M16,"") -> 1 | M45: =Controls!$B$7 -> 0.025 | N45: =IF(AND(ISNUMBER(K45),ISNUMBER(L45),L45>0),K45/L45*(1-M45),"") -> 1.02375 | P45: =IF(O45="",0,COUNTIFS('Gap Migration'!$G$7:$G$91,O45,'Gap Migration'!$J$7:$J$91,1)) -> 0 | Q45: 0 | R45: 0 | S45: =IF(ISNUMBER(N45),IF(N45>=Controls!$B$8,"DESIGN CLOSE","NEGATIVE"),IF(P45=1,"MEASUREMENT READY","UNSCOPED")) -> DESIGN CLOSE | T45: =IF(S45="DESIGN CLOSE","root-native section bill",IF(S45="MEASUREMENT READY","executable protocol; observation empty","return to architecture")) -> root-native section bill | U45: 0
A46: CT-C-A04-W04 | B46: MS-CT | C46: CT-C | D46: A04 | E46: Safe state and human boundary | F46: W04 | G46: Cold reconstruction | H46: 16 | I46: 8 separately safe occupied zones | J46: ratio | M46: =Controls!$B$7 -> 0.025 | N46: =IF(AND(ISNUMBER(K46),ISNUMBER(L46),L46>0),K46/L46*(1-M46),"") | O46: RC-CT-C-A04 | P46: =IF(O46="",0,COUNTIFS('Gap Migration'!$G$7:$G$91,O46,'Gap Migration'!$J$7:$J$91,1)) -> 1 | Q46: 0 | R46: 0 | S46: =IF(ISNUMBER(N46),IF(N46>=Controls!$B$8,"DESIGN CLOSE","NEGATIVE"),IF(P46=1,"MEASUREMENT READY","UNSCOPED")) -> MEASUREMENT READY | T46: =IF(S46="DESIGN CLOSE","root-native section bill",IF(S46="MEASUREMENT READY","executable protocol; observation empty","return to architecture")) -> executable protocol; observation empty | U46: 0
A47: CT-C-A05-W01 | B47: MS-CT | C47: CT-C | D47: A05 | E47: Residual and environmental custody | F47: W01 | G47: Nominal mission | H47: 17 | I47: 6 dirty-return treatment cells | J47: t/day | K47: =IF(ISNUMBER('Section Bills'!J17),'Section Bills'!J17,"") -> 277.2 | L47: =IF(ISNUMBER('Section Bills'!K17),'Section Bills'!K17,"") -> 220 | M47: =Controls!$B$7 -> 0.025 | N47: =IF(AND(ISNUMBER(K47),ISNUMBER(L47),L47>0),K47/L47*(1-M47),"") -> 1.2285 | P47: =IF(O47="",0,COUNTIFS('Gap Migration'!$G$7:$G$91,O47,'Gap Migration'!$J$7:$J$91,1)) -> 0 | Q47: 0 | R47: 0 | S47: =IF(ISNUMBER(N47),IF(N47>=Controls!$B$8,"DESIGN CLOSE","NEGATIVE"),IF(P47=1,"MEASUREMENT READY","UNSCOPED")) -> DESIGN CLOSE | T47: =IF(S47="DESIGN CLOSE","root-native section bill",IF(S47="MEASUREMENT READY","executable protocol; observation empty","return to architecture")) -> root-native section bill | U47: 0
A48: CT-C-A05-W02 | B48: MS-CT | C48: CT-C | D48: A05 | E48: Residual and environmental custody | F48: W02 | G48: Fatal-keystone challenge | H48: 17 | I48: 6 dirty-return treatment cells | J48: t/day | M48: =Controls!$B$7 -> 0.025 | N48: =IF(AND(ISNUMBER(K48),ISNUMBER(L48),L48>0),K48/L48*(1-M48),"") | O48: KX-CT-C-A05 | P48: =IF(O48="",0,COUNTIFS('Gap Migration'!$G$7:$G$91,O48,'Gap Migration'!$J$7:$J$91,1)) -> 1 | Q48: 0 | R48: 0 | S48: =IF(ISNUMBER(N48),IF(N48>=Controls!$B$8,"DESIGN CLOSE","NEGATIVE"),IF(P48=1,"MEASUREMENT READY","UNSCOPED")) -> MEASUREMENT READY | T48: =IF(S48="DESIGN CLOSE","root-native section bill",IF(S48="MEASUREMENT READY","executable protocol; observation empty","return to architecture")) -> executable protocol; observation empty | U48: 0
A49: CT-C-A05-W03 | B49: MS-CT | C49: CT-C | D49: A05 | E49: Residual and environmental custody | F49: W03 | G49: Largest-independent-cell loss | H49: 17 | I49: 6 dirty-return treatment cells | J49: t/day | K49: =IF(ISNUMBER('Section Bills'!L17),'Section Bills'!L17,"") -> 231 | L49: =IF(ISNUMBER('Section Bills'!M17),'Section Bills'!M17,"") -> 220 | M49: =Controls!$B$7 -> 0.025 | N49: =IF(AND(ISNUMBER(K49),ISNUMBER(L49),L49>0),K49/L49*(1-M49),"") -> 1.02375 | P49: =IF(O49="",0,COUNTIFS('Gap Migration'!$G$7:$G$91,O49,'Gap Migration'!$J$7:$J$91,1)) -> 0 | Q49: 0 | R49: 0 | S49: =IF(ISNUMBER(N49),IF(N49>=Controls!$B$8,"DESIGN CLOSE","NEGATIVE"),IF(P49=1,"MEASUREMENT READY","UNSCOPED")) -> DESIGN CLOSE | T49: =IF(S49="DESIGN CLOSE","root-native section bill",IF(S49="MEASUREMENT READY","executable protocol; observation empty","return to architecture")) -> root-native section bill | U49: 0
A50: CT-C-A05-W04 | B50: MS-CT | C50: CT-C | D50: A05 | E50: Residual and environmental custody | F50: W04 | G50: Cold reconstruction | H50: 17 | I50: 6 dirty-return treatment cells | J50: t/day | M50: =Controls!$B$7 -> 0.025 | N50: =IF(AND(ISNUMBER(K50),ISNUMBER(L50),L50>0),K50/L50*(1-M50),"") | O50: RC-CT-C-A05 | P50: =IF(O50="",0,COUNTIFS('Gap Migration'!$G$7:$G$91,O50,'Gap Migration'!$J$7:$J$91,1)) -> 1 | Q50: 0 | R50: 0 | S50: =IF(ISNUMBER(N50),IF(N50>=Controls!$B$8,"DESIGN CLOSE","NEGATIVE"),IF(P50=1,"MEASUREMENT READY","UNSCOPED")) -> MEASUREMENT READY | T50: =IF(S50="DESIGN CLOSE","root-native section bill",IF(S50="MEASUREMENT READY","executable protocol; observation empty","return to architecture")) -> executable protocol; observation empty | U50: 0
A51: CT-C-A06-W01 | B51: MS-CT | C51: CT-C | D51: A06 | E51: Removal and cold reconstruction | F51: W01 | G51: Nominal mission | H51: 18 | I51: sealed occupied-spine reconstruction chain | J51: h | M51: =Controls!$B$7 -> 0.025 | N51: =IF(AND(ISNUMBER(K51),ISNUMBER(L51),L51>0),K51/L51*(1-M51),"") | O51: RB-CT-C-W01 | P51: =IF(O51="",0,COUNTIFS('Gap Migration'!$G$7:$G$91,O51,'Gap Migration'!$J$7:$J$91,1)) -> 1 | Q51: 0 | R51: 0 | S51: =IF(ISNUMBER(N51),IF(N51>=Controls!$B$8,"DESIGN CLOSE","NEGATIVE"),IF(P51=1,"MEASUREMENT READY","UNSCOPED")) -> MEASUREMENT READY | T51: =IF(S51="DESIGN CLOSE","root-native section bill",IF(S51="MEASUREMENT READY","executable protocol; observation empty","return to architecture")) -> executable protocol; observation empty | U51: 0
A52: CT-C-A06-W02 | B52: MS-CT | C52: CT-C | D52: A06 | E52: Removal and cold reconstruction | F52: W02 | G52: Fatal-keystone challenge | H52: 18 | I52: sealed occupied-spine reconstruction chain | J52: h | M52: =Controls!$B$7 -> 0.025 | N52: =IF(AND(ISNUMBER(K52),ISNUMBER(L52),L52>0),K52/L52*(1-M52),"") | O52: KX-CT-C-A06 | P52: =IF(O52="",0,COUNTIFS('Gap Migration'!$G$7:$G$91,O52,'Gap Migration'!$J$7:$J$91,1)) -> 1 | Q52: 0 | R52: 0 | S52: =IF(ISNUMBER(N52),IF(N52>=Controls!$B$8,"DESIGN CLOSE","NEGATIVE"),IF(P52=1,"MEASUREMENT READY","UNSCOPED")) -> MEASUREMENT READY | T52: =IF(S52="DESIGN CLOSE","root-native section bill",IF(S52="MEASUREMENT READY","executable protocol; observation empty","return to architecture")) -> executable protocol; observation empty | U52: 0
A53: CT-C-A06-W03 | B53: MS-CT | C53: CT-C | D53: A06 | E53: Removal and cold reconstruction | F53: W03 | G53: Largest-independent-cell loss | H53: 18 | I53: sealed occupied-spine reconstruction chain | J53: h | M53: =Controls!$B$7 -> 0.025 | N53: =IF(AND(ISNUMBER(K53),ISNUMBER(L53),L53>0),K53/L53*(1-M53),"") | O53: RB-CT-C-W03 | P53: =IF(O53="",0,COUNTIFS('Gap Migration'!$G$7:$G$91,O53,'Gap Migration'!$J$7:$J$91,1)) -> 1 | Q53: 0 | R53: 0 | S53: =IF(ISNUMBER(N53),IF(N53>=Controls!$B$8,"DESIGN CLOSE","NEGATIVE"),IF(P53=1,"MEASUREMENT READY","UNSCOPED")) -> MEASUREMENT READY | T53: =IF(S53="DESIGN CLOSE","root-native section bill",IF(S53="MEASUREMENT READY","executable protocol; observation empty","return to architecture")) -> executable protocol; observation empty | U53: 0
A54: CT-C-A06-W04 | B54: MS-CT | C54: CT-C | D54: A06 | E54: Removal and cold reconstruction | F54: W04 | G54: Cold reconstruction | H54: 18 | I54: sealed occupied-spine reconstruction chain | J54: h | M54: =Controls!$B$7 -> 0.025 | N54: =IF(AND(ISNUMBER(K54),ISNUMBER(L54),L54>0),K54/L54*(1-M54),"") | O54: RC-CT-C-A06 | P54: =IF(O54="",0,COUNTIFS('Gap Migration'!$G$7:$G$91,O54,'Gap Migration'!$J$7:$J$91,1)) -> 1 | Q54: 0 | R54: 0 | S54: =IF(ISNUMBER(N54),IF(N54>=Controls!$B$8,"DESIGN CLOSE","NEGATIVE"),IF(P54=1,"MEASUREMENT READY","UNSCOPED")) -> MEASUREMENT READY | T54: =IF(S54="DESIGN CLOSE","root-native section bill",IF(S54="MEASUREMENT READY","executable protocol; observation empty","return to architecture")) -> executable protocol; observation empty | U54: 0
A55: HC-A-A01-W01 | B55: MS-HC | C55: HC-A | D55: A01 | E55: Mass and material custody | F55: W01 | G55: Nominal mission | H55: 19 | I55: 10 independently admitted intervention cells | J55: t | K55: =IF(ISNUMBER('Section Bills'!J19),'Section Bills'!J19,"") -> 63000 | L55: =IF(ISNUMBER('Section Bills'!K19),'Section Bills'!K19,"") -> 54000 | M55: =Controls!$B$7 -> 0.025 | N55: =IF(AND(ISNUMBER(K55),ISNUMBER(L55),L55>0),K55/L55*(1-M55),"") -> 1.1375 | P55: =IF(O55="",0,COUNTIFS('Gap Migration'!$G$7:$G$91,O55,'Gap Migration'!$J$7:$J$91,1)) -> 0 | Q55: 0 | R55: 0 | S55: =IF(ISNUMBER(N55),IF(N55>=Controls!$B$8,"DESIGN CLOSE","NEGATIVE"),IF(P55=1,"MEASUREMENT READY","UNSCOPED")) -> DESIGN CLOSE | T55: =IF(S55="DESIGN CLOSE","root-native section bill",IF(S55="MEASUREMENT READY","executable protocol; observation empty","return to architecture")) -> root-native section bill | U55: 0
A56: HC-A-A01-W02 | B56: MS-HC | C56: HC-A | D56: A01 | E56: Mass and material custody | F56: W02 | G56: Fatal-keystone challenge | H56: 19 | I56: 10 independently admitted intervention cells | J56: t | M56: =Controls!$B$7 -> 0.025 | N56: =IF(AND(ISNUMBER(K56),ISNUMBER(L56),L56>0),K56/L56*(1-M56),"") | O56: KX-HC-A-A01 | P56: =IF(O56="",0,COUNTIFS('Gap Migration'!$G$7:$G$91,O56,'Gap Migration'!$J$7:$J$91,1)) -> 1 | Q56: 0 | R56: 0 | S56: =IF(ISNUMBER(N56),IF(N56>=Controls!$B$8,"DESIGN CLOSE","NEGATIVE"),IF(P56=1,"MEASUREMENT READY","UNSCOPED")) -> MEASUREMENT READY | T56: =IF(S56="DESIGN CLOSE","root-native section bill",IF(S56="MEASUREMENT READY","executable protocol; observation empty","return to architecture")) -> executable protocol; observation empty | U56: 0
A57: HC-A-A01-W03 | B57: MS-HC | C57: HC-A | D57: A01 | E57: Mass and material custody | F57: W03 | G57: Largest-independent-cell loss | H57: 19 | I57: 10 independently admitted intervention cells | J57: t | K57: =IF(ISNUMBER('Section Bills'!L19),'Section Bills'!L19,"") -> 56700 | L57: =IF(ISNUMBER('Section Bills'!M19),'Section Bills'!M19,"") -> 54000 | M57: =Controls!$B$7 -> 0.025 | N57: =IF(AND(ISNUMBER(K57),ISNUMBER(L57),L57>0),K57/L57*(1-M57),"") -> 1.02375 | P57: =IF(O57="",0,COUNTIFS('Gap Migration'!$G$7:$G$91,O57,'Gap Migration'!$J$7:$J$91,1)) -> 0 | Q57: 0 | R57: 0 | S57: =IF(ISNUMBER(N57),IF(N57>=Controls!$B$8,"DESIGN CLOSE","NEGATIVE"),IF(P57=1,"MEASUREMENT READY","UNSCOPED")) -> DESIGN CLOSE | T57: =IF(S57="DESIGN CLOSE","root-native section bill",IF(S57="MEASUREMENT READY","executable protocol; observation empty","return to architecture")) -> root-native section bill | U57: 0
A58: HC-A-A01-W04 | B58: MS-HC | C58: HC-A | D58: A01 | E58: Mass and material custody | F58: W04 | G58: Cold reconstruction | H58: 19 | I58: 10 independently admitted intervention cells | J58: t | M58: =Controls!$B$7 -> 0.025 | N58: =IF(AND(ISNUMBER(K58),ISNUMBER(L58),L58>0),K58/L58*(1-M58),"") | O58: RC-HC-A-A01 | P58: =IF(O58="",0,COUNTIFS('Gap Migration'!$G$7:$G$91,O58,'Gap Migration'!$J$7:$J$91,1)) -> 1 | Q58: 0 | R58: 0 | S58: =IF(ISNUMBER(N58),IF(N58>=Controls!$B$8,"DESIGN CLOSE","NEGATIVE"),IF(P58=1,"MEASUREMENT READY","UNSCOPED")) -> MEASUREMENT READY | T58: =IF(S58="DESIGN CLOSE","root-native section bill",IF(S58="MEASUREMENT READY","executable protocol; observation empty","return to architecture")) -> executable protocol; observation empty | U58: 0
A59: HC-A-A02-W01 | B59: MS-HC | C59: HC-A | D59: A02 | E59: Energy and heat | F59: W01 | G59: Nominal mission | H59: 20 | I59: 8 isolated intervention-energy cells | J59: MW | K59: =IF(ISNUMBER('Section Bills'!J20),'Section Bills'!J20,"") -> 164.8 | L59: =IF(ISNUMBER('Section Bills'!K20),'Section Bills'!K20,"") -> 140 | M59: =Controls!$B$7 -> 0.025 | N59: =IF(AND(ISNUMBER(K59),ISNUMBER(L59),L59>0),K59/L59*(1-M59),"") -> 1.1477143 | P59: =IF(O59="",0,COUNTIFS('Gap Migration'!$G$7:$G$91,O59,'Gap Migration'!$J$7:$J$91,1)) -> 0 | Q59: 0 | R59: 0 | S59: =IF(ISNUMBER(N59),IF(N59>=Controls!$B$8,"DESIGN CLOSE","NEGATIVE"),IF(P59=1,"MEASUREMENT READY","UNSCOPED")) -> DESIGN CLOSE | T59: =IF(S59="DESIGN CLOSE","root-native section bill",IF(S59="MEASUREMENT READY","executable protocol; observation empty","return to architecture")) -> root-native section bill | U59: 0
A60: HC-A-A02-W02 | B60: MS-HC | C60: HC-A | D60: A02 | E60: Energy and heat | F60: W02 | G60: Fatal-keystone challenge | H60: 20 | I60: 8 isolated intervention-energy cells | J60: MW | M60: =Controls!$B$7 -> 0.025 | N60: =IF(AND(ISNUMBER(K60),ISNUMBER(L60),L60>0),K60/L60*(1-M60),"") | O60: KX-HC-A-A02 | P60: =IF(O60="",0,COUNTIFS('Gap Migration'!$G$7:$G$91,O60,'Gap Migration'!$J$7:$J$91,1)) -> 1 | Q60: 0 | R60: 0 | S60: =IF(ISNUMBER(N60),IF(N60>=Controls!$B$8,"DESIGN CLOSE","NEGATIVE"),IF(P60=1,"MEASUREMENT READY","UNSCOPED")) -> MEASUREMENT READY | T60: =IF(S60="DESIGN CLOSE","root-native section bill",IF(S60="MEASUREMENT READY","executable protocol; observation empty","return to architecture")) -> executable protocol; observation empty | U60: 0
A61: HC-A-A02-W03 | B61: MS-HC | C61: HC-A | D61: A02 | E61: Energy and heat | F61: W03 | G61: Largest-independent-cell loss | H61: 20 | I61: 8 isolated intervention-energy cells | J61: MW | K61: =IF(ISNUMBER('Section Bills'!L20),'Section Bills'!L20,"") -> 144.2 | L61: =IF(ISNUMBER('Section Bills'!M20),'Section Bills'!M20,"") -> 140 | M61: =Controls!$B$7 -> 0.025 | N61: =IF(AND(ISNUMBER(K61),ISNUMBER(L61),L61>0),K61/L61*(1-M61),"") -> 1.00425 | P61: =IF(O61="",0,COUNTIFS('Gap Migration'!$G$7:$G$91,O61,'Gap Migration'!$J$7:$J$91,1)) -> 0 | Q61: 0 | R61: 0 | S61: =IF(ISNUMBER(N61),IF(N61>=Controls!$B$8,"DESIGN CLOSE","NEGATIVE"),IF(P61=1,"MEASUREMENT READY","UNSCOPED")) -> DESIGN CLOSE | T61: =IF(S61="DESIGN CLOSE","root-native section bill",IF(S61="MEASUREMENT READY","executable protocol; observation empty","return to architecture")) -> root-native section bill | U61: 0
A62: HC-A-A02-W04 | B62: MS-HC | C62: HC-A | D62: A02 | E62: Energy and heat | F62: W04 | G62: Cold reconstruction | H62: 20 | I62: 8 isolated intervention-energy cells | J62: MW | M62: =Controls!$B$7 -> 0.025 | N62: =IF(AND(ISNUMBER(K62),ISNUMBER(L62),L62>0),K62/L62*(1-M62),"") | O62: RC-HC-A-A02 | P62: =IF(O62="",0,COUNTIFS('Gap Migration'!$G$7:$G$91,O62,'Gap Migration'!$J$7:$J$91,1)) -> 1 | Q62: 0 | R62: 0 | S62: =IF(ISNUMBER(N62),IF(N62>=Controls!$B$8,"DESIGN CLOSE","NEGATIVE"),IF(P62=1,"MEASUREMENT READY","UNSCOPED")) -> MEASUREMENT READY | T62: =IF(S62="DESIGN CLOSE","root-native section bill",IF(S62="MEASUREMENT READY","executable protocol; observation empty","return to architecture")) -> executable protocol; observation empty | U62: 0
A63: HC-A-A03-W01 | B63: MS-HC | C63: HC-A | D63: A03 | E63: Geometry and load path | F63: W01 | G63: Nominal mission | H63: 21 | I63: 5 independently attributable held-line sectors | J63: km/day | K63: =IF(ISNUMBER('Section Bills'!J21),'Section Bills'!J21,"") -> 132.5 | L63: =IF(ISNUMBER('Section Bills'!K21),'Section Bills'!K21,"") -> 103 | M63: =Controls!$B$7 -> 0.025 | N63: =IF(AND(ISNUMBER(K63),ISNUMBER(L63),L63>0),K63/L63*(1-M63),"") -> 1.2542476 | P63: =IF(O63="",0,COUNTIFS('Gap Migration'!$G$7:$G$91,O63,'Gap Migration'!$J$7:$J$91,1)) -> 0 | Q63: 0 | R63: 0 | S63: =IF(ISNUMBER(N63),IF(N63>=Controls!$B$8,"DESIGN CLOSE","NEGATIVE"),IF(P63=1,"MEASUREMENT READY","UNSCOPED")) -> DESIGN CLOSE | T63: =IF(S63="DESIGN CLOSE","root-native section bill",IF(S63="MEASUREMENT READY","executable protocol; observation empty","return to architecture")) -> root-native section bill | U63: 0
A64: HC-A-A03-W02 | B64: MS-HC | C64: HC-A | D64: A03 | E64: Geometry and load path | F64: W02 | G64: Fatal-keystone challenge | H64: 21 | I64: 5 independently attributable held-line sectors | J64: km/day | M64: =Controls!$B$7 -> 0.025 | N64: =IF(AND(ISNUMBER(K64),ISNUMBER(L64),L64>0),K64/L64*(1-M64),"") | O64: KX-HC-A-A03 | P64: =IF(O64="",0,COUNTIFS('Gap Migration'!$G$7:$G$91,O64,'Gap Migration'!$J$7:$J$91,1)) -> 1 | Q64: 0 | R64: 0 | S64: =IF(ISNUMBER(N64),IF(N64>=Controls!$B$8,"DESIGN CLOSE","NEGATIVE"),IF(P64=1,"MEASUREMENT READY","UNSCOPED")) -> MEASUREMENT READY | T64: =IF(S64="DESIGN CLOSE","root-native section bill",IF(S64="MEASUREMENT READY","executable protocol; observation empty","return to architecture")) -> executable protocol; observation empty | U64: 0
A65: HC-A-A03-W03 | B65: MS-HC | C65: HC-A | D65: A03 | E65: Geometry and load path | F65: W03 | G65: Largest-independent-cell loss | H65: 21 | I65: 5 independently attributable held-line sectors | J65: km/day | K65: =IF(ISNUMBER('Section Bills'!L21),'Section Bills'!L21,"") -> 106 | L65: =IF(ISNUMBER('Section Bills'!M21),'Section Bills'!M21,"") -> 103 | M65: =Controls!$B$7 -> 0.025 | N65: =IF(AND(ISNUMBER(K65),ISNUMBER(L65),L65>0),K65/L65*(1-M65),"") -> 1.0033981 | P65: =IF(O65="",0,COUNTIFS('Gap Migration'!$G$7:$G$91,O65,'Gap Migration'!$J$7:$J$91,1)) -> 0 | Q65: 0 | R65: 0 | S65: =IF(ISNUMBER(N65),IF(N65>=Controls!$B$8,"DESIGN CLOSE","NEGATIVE"),IF(P65=1,"MEASUREMENT READY","UNSCOPED")) -> DESIGN CLOSE | T65: =IF(S65="DESIGN CLOSE","root-native section bill",IF(S65="MEASUREMENT READY","executable protocol; observation empty","return to architecture")) -> root-native section bill | U65: 0
A66: HC-A-A03-W04 | B66: MS-HC | C66: HC-A | D66: A03 | E66: Geometry and load path | F66: W04 | G66: Cold reconstruction | H66: 21 | I66: 5 independently attributable held-line sectors | J66: km/day | M66: =Controls!$B$7 -> 0.025 | N66: =IF(AND(ISNUMBER(K66),ISNUMBER(L66),L66>0),K66/L66*(1-M66),"") | O66: RC-HC-A-A03 | P66: =IF(O66="",0,COUNTIFS('Gap Migration'!$G$7:$G$91,O66,'Gap Migration'!$J$7:$J$91,1)) -> 1 | Q66: 0 | R66: 0 | S66: =IF(ISNUMBER(N66),IF(N66>=Controls!$B$8,"DESIGN CLOSE","NEGATIVE"),IF(P66=1,"MEASUREMENT READY","UNSCOPED")) -> MEASUREMENT READY | T66: =IF(S66="DESIGN CLOSE","root-native section bill",IF(S66="MEASUREMENT READY","executable protocol; observation empty","return to architecture")) -> executable protocol; observation empty | U66: 0
A67: HC-A-A04-W01 | B67: MS-HC | C67: HC-A | D67: A04 | E67: Safe state and human boundary | F67: W01 | G67: Nominal mission | H67: 22 | I67: 8 protected response and avoidance zones | J67: ratio | K67: =IF(ISNUMBER('Section Bills'!J22),'Section Bills'!J22,"") -> 1.2 | L67: =IF(ISNUMBER('Section Bills'!K22),'Section Bills'!K22,"") -> 1 | M67: =Controls!$B$7 -> 0.025 | N67: =IF(AND(ISNUMBER(K67),ISNUMBER(L67),L67>0),K67/L67*(1-M67),"") -> 1.17 | P67: =IF(O67="",0,COUNTIFS('Gap Migration'!$G$7:$G$91,O67,'Gap Migration'!$J$7:$J$91,1)) -> 0 | Q67: 0 | R67: 0 | S67: =IF(ISNUMBER(N67),IF(N67>=Controls!$B$8,"DESIGN CLOSE","NEGATIVE"),IF(P67=1,"MEASUREMENT READY","UNSCOPED")) -> DESIGN CLOSE | T67: =IF(S67="DESIGN CLOSE","root-native section bill",IF(S67="MEASUREMENT READY","executable protocol; observation empty","return to architecture")) -> root-native section bill | U67: 0
A68: HC-A-A04-W02 | B68: MS-HC | C68: HC-A | D68: A04 | E68: Safe state and human boundary | F68: W02 | G68: Fatal-keystone challenge | H68: 22 | I68: 8 protected response and avoidance zones | J68: ratio | M68: =Controls!$B$7 -> 0.025 | N68: =IF(AND(ISNUMBER(K68),ISNUMBER(L68),L68>0),K68/L68*(1-M68),"") | O68: KX-HC-A-A04 | P68: =IF(O68="",0,COUNTIFS('Gap Migration'!$G$7:$G$91,O68,'Gap Migration'!$J$7:$J$91,1)) -> 1 | Q68: 0 | R68: 0 | S68: =IF(ISNUMBER(N68),IF(N68>=Controls!$B$8,"DESIGN CLOSE","NEGATIVE"),IF(P68=1,"MEASUREMENT READY","UNSCOPED")) -> MEASUREMENT READY | T68: =IF(S68="DESIGN CLOSE","root-native section bill",IF(S68="MEASUREMENT READY","executable protocol; observation empty","return to architecture")) -> executable protocol; observation empty | U68: 0
A69: HC-A-A04-W03 | B69: MS-HC | C69: HC-A | D69: A04 | E69: Safe state and human boundary | F69: W03 | G69: Largest-independent-cell loss | H69: 22 | I69: 8 protected response and avoidance zones | J69: ratio | K69: =IF(ISNUMBER('Section Bills'!L22),'Section Bills'!L22,"") -> 1.05 | L69: =IF(ISNUMBER('Section Bills'!M22),'Section Bills'!M22,"") -> 1 | M69: =Controls!$B$7 -> 0.025 | N69: =IF(AND(ISNUMBER(K69),ISNUMBER(L69),L69>0),K69/L69*(1-M69),"") -> 1.02375 | P69: =IF(O69="",0,COUNTIFS('Gap Migration'!$G$7:$G$91,O69,'Gap Migration'!$J$7:$J$91,1)) -> 0 | Q69: 0 | R69: 0 | S69: =IF(ISNUMBER(N69),IF(N69>=Controls!$B$8,"DESIGN CLOSE","NEGATIVE"),IF(P69=1,"MEASUREMENT READY","UNSCOPED")) -> DESIGN CLOSE | T69: =IF(S69="DESIGN CLOSE","root-native section bill",IF(S69="MEASUREMENT READY","executable protocol; observation empty","return to architecture")) -> root-native section bill | U69: 0
A70: HC-A-A04-W04 | B70: MS-HC | C70: HC-A | D70: A04 | E70: Safe state and human boundary | F70: W04 | G70: Cold reconstruction | H70: 22 | I70: 8 protected response and avoidance zones | J70: ratio | M70: =Controls!$B$7 -> 0.025 | N70: =IF(AND(ISNUMBER(K70),ISNUMBER(L70),L70>0),K70/L70*(1-M70),"") | O70: RC-HC-A-A04 | P70: =IF(O70="",0,COUNTIFS('Gap Migration'!$G$7:$G$91,O70,'Gap Migration'!$J$7:$J$91,1)) -> 1 | Q70: 0 | R70: 0 | S70: =IF(ISNUMBER(N70),IF(N70>=Controls!$B$8,"DESIGN CLOSE","NEGATIVE"),IF(P70=1,"MEASUREMENT READY","UNSCOPED")) -> MEASUREMENT READY | T70: =IF(S70="DESIGN CLOSE","root-native section bill",IF(S70="MEASUREMENT READY","executable protocol; observation empty","return to architecture")) -> executable protocol; observation empty | U70: 0
A71: HC-A-A05-W01 | B71: MS-HC | C71: HC-A | D71: A05 | E71: Residual and environmental custody | F71: W01 | G71: Nominal mission | H71: 23 | I71: 6 runoff and working-fluid custody cells | J71: t/day | K71: =IF(ISNUMBER('Section Bills'!J23),'Section Bills'!J23,"") -> 1134 | L71: =IF(ISNUMBER('Section Bills'!K23),'Section Bills'!K23,"") -> 900 | M71: =Controls!$B$7 -> 0.025 | N71: =IF(AND(ISNUMBER(K71),ISNUMBER(L71),L71>0),K71/L71*(1-M71),"") -> 1.2285 | P71: =IF(O71="",0,COUNTIFS('Gap Migration'!$G$7:$G$91,O71,'Gap Migration'!$J$7:$J$91,1)) -> 0 | Q71: 0 | R71: 0 | S71: =IF(ISNUMBER(N71),IF(N71>=Controls!$B$8,"DESIGN CLOSE","NEGATIVE"),IF(P71=1,"MEASUREMENT READY","UNSCOPED")) -> DESIGN CLOSE | T71: =IF(S71="DESIGN CLOSE","root-native section bill",IF(S71="MEASUREMENT READY","executable protocol; observation empty","return to architecture")) -> root-native section bill | U71: 0
A72: HC-A-A05-W02 | B72: MS-HC | C72: HC-A | D72: A05 | E72: Residual and environmental custody | F72: W02 | G72: Fatal-keystone challenge | H72: 23 | I72: 6 runoff and working-fluid custody cells | J72: t/day | M72: =Controls!$B$7 -> 0.025 | N72: =IF(AND(ISNUMBER(K72),ISNUMBER(L72),L72>0),K72/L72*(1-M72),"") | O72: KX-HC-A-A05 | P72: =IF(O72="",0,COUNTIFS('Gap Migration'!$G$7:$G$91,O72,'Gap Migration'!$J$7:$J$91,1)) -> 1 | Q72: 0 | R72: 0 | S72: =IF(ISNUMBER(N72),IF(N72>=Controls!$B$8,"DESIGN CLOSE","NEGATIVE"),IF(P72=1,"MEASUREMENT READY","UNSCOPED")) -> MEASUREMENT READY | T72: =IF(S72="DESIGN CLOSE","root-native section bill",IF(S72="MEASUREMENT READY","executable protocol; observation empty","return to architecture")) -> executable protocol; observation empty | U72: 0
A73: HC-A-A05-W03 | B73: MS-HC | C73: HC-A | D73: A05 | E73: Residual and environmental custody | F73: W03 | G73: Largest-independent-cell loss | H73: 23 | I73: 6 runoff and working-fluid custody cells | J73: t/day | K73: =IF(ISNUMBER('Section Bills'!L23),'Section Bills'!L23,"") -> 945 | L73: =IF(ISNUMBER('Section Bills'!M23),'Section Bills'!M23,"") -> 900 | M73: =Controls!$B$7 -> 0.025 | N73: =IF(AND(ISNUMBER(K73),ISNUMBER(L73),L73>0),K73/L73*(1-M73),"") -> 1.02375 | P73: =IF(O73="",0,COUNTIFS('Gap Migration'!$G$7:$G$91,O73,'Gap Migration'!$J$7:$J$91,1)) -> 0 | Q73: 0 | R73: 0 | S73: =IF(ISNUMBER(N73),IF(N73>=Controls!$B$8,"DESIGN CLOSE","NEGATIVE"),IF(P73=1,"MEASUREMENT READY","UNSCOPED")) -> DESIGN CLOSE | T73: =IF(S73="DESIGN CLOSE","root-native section bill",IF(S73="MEASUREMENT READY","executable protocol; observation empty","return to architecture")) -> root-native section bill | U73: 0
A74: HC-A-A05-W04 | B74: MS-HC | C74: HC-A | D74: A05 | E74: Residual and environmental custody | F74: W04 | G74: Cold reconstruction | H74: 23 | I74: 6 runoff and working-fluid custody cells | J74: t/day | M74: =Controls!$B$7 -> 0.025 | N74: =IF(AND(ISNUMBER(K74),ISNUMBER(L74),L74>0),K74/L74*(1-M74),"") | O74: RC-HC-A-A05 | P74: =IF(O74="",0,COUNTIFS('Gap Migration'!$G$7:$G$91,O74,'Gap Migration'!$J$7:$J$91,1)) -> 1 | Q74: 0 | R74: 0 | S74: =IF(ISNUMBER(N74),IF(N74>=Controls!$B$8,"DESIGN CLOSE","NEGATIVE"),IF(P74=1,"MEASUREMENT READY","UNSCOPED")) -> MEASUREMENT READY | T74: =IF(S74="DESIGN CLOSE","root-native section bill",IF(S74="MEASUREMENT READY","executable protocol; observation empty","return to architecture")) -> executable protocol; observation empty | U74: 0
A75: HC-A-A06-W01 | B75: MS-HC | C75: HC-A | D75: A06 | E75: Removal and cold reconstruction | F75: W01 | G75: Nominal mission | H75: 24 | I75: sealed atmospheric-section reconstruction chain | J75: h | M75: =Controls!$B$7 -> 0.025 | N75: =IF(AND(ISNUMBER(K75),ISNUMBER(L75),L75>0),K75/L75*(1-M75),"") | O75: RB-HC-A-W01 | P75: =IF(O75="",0,COUNTIFS('Gap Migration'!$G$7:$G$91,O75,'Gap Migration'!$J$7:$J$91,1)) -> 1 | Q75: 0 | R75: 0 | S75: =IF(ISNUMBER(N75),IF(N75>=Controls!$B$8,"DESIGN CLOSE","NEGATIVE"),IF(P75=1,"MEASUREMENT READY","UNSCOPED")) -> MEASUREMENT READY | T75: =IF(S75="DESIGN CLOSE","root-native section bill",IF(S75="MEASUREMENT READY","executable protocol; observation empty","return to architecture")) -> executable protocol; observation empty | U75: 0
A76: HC-A-A06-W02 | B76: MS-HC | C76: HC-A | D76: A06 | E76: Removal and cold reconstruction | F76: W02 | G76: Fatal-keystone challenge | H76: 24 | I76: sealed atmospheric-section reconstruction chain | J76: h | M76: =Controls!$B$7 -> 0.025 | N76: =IF(AND(ISNUMBER(K76),ISNUMBER(L76),L76>0),K76/L76*(1-M76),"") | O76: KX-HC-A-A06 | P76: =IF(O76="",0,COUNTIFS('Gap Migration'!$G$7:$G$91,O76,'Gap Migration'!$J$7:$J$91,1)) -> 1 | Q76: 0 | R76: 0 | S76: =IF(ISNUMBER(N76),IF(N76>=Controls!$B$8,"DESIGN CLOSE","NEGATIVE"),IF(P76=1,"MEASUREMENT READY","UNSCOPED")) -> MEASUREMENT READY | T76: =IF(S76="DESIGN CLOSE","root-native section bill",IF(S76="MEASUREMENT READY","executable protocol; observation empty","return to architecture")) -> executable protocol; observation empty | U76: 0
A77: HC-A-A06-W03 | B77: MS-HC | C77: HC-A | D77: A06 | E77: Removal and cold reconstruction | F77: W03 | G77: Largest-independent-cell loss | H77: 24 | I77: sealed atmospheric-section reconstruction chain | J77: h | M77: =Controls!$B$7 -> 0.025 | N77: =IF(AND(ISNUMBER(K77),ISNUMBER(L77),L77>0),K77/L77*(1-M77),"") | O77: RB-HC-A-W03 | P77: =IF(O77="",0,COUNTIFS('Gap Migration'!$G$7:$G$91,O77,'Gap Migration'!$J$7:$J$91,1)) -> 1 | Q77: 0 | R77: 0 | S77: =IF(ISNUMBER(N77),IF(N77>=Controls!$B$8,"DESIGN CLOSE","NEGATIVE"),IF(P77=1,"MEASUREMENT READY","UNSCOPED")) -> MEASUREMENT READY | T77: =IF(S77="DESIGN CLOSE","root-native section bill",IF(S77="MEASUREMENT READY","executable protocol; observation empty","return to architecture")) -> executable protocol; observation empty | U77: 0
A78: HC-A-A06-W04 | B78: MS-HC | C78: HC-A | D78: A06 | E78: Removal and cold reconstruction | F78: W04 | G78: Cold reconstruction | H78: 24 | I78: sealed atmospheric-section reconstruction chain | J78: h | M78: =Controls!$B$7 -> 0.025 | N78: =IF(AND(ISNUMBER(K78),ISNUMBER(L78),L78>0),K78/L78*(1-M78),"") | O78: RC-HC-A-A06 | P78: =IF(O78="",0,COUNTIFS('Gap Migration'!$G$7:$G$91,O78,'Gap Migration'!$J$7:$J$91,1)) -> 1 | Q78: 0 | R78: 0 | S78: =IF(ISNUMBER(N78),IF(N78>=Controls!$B$8,"DESIGN CLOSE","NEGATIVE"),IF(P78=1,"MEASUREMENT READY","UNSCOPED")) -> MEASUREMENT READY | T78: =IF(S78="DESIGN CLOSE","root-native section bill",IF(S78="MEASUREMENT READY","executable protocol; observation empty","return to architecture")) -> executable protocol; observation empty | U78: 0
A79: LF-B-A01-W01 | B79: MS-LF | C79: LF-B | D79: A01 | E79: Mass and material custody | F79: W01 | G79: Nominal mission | H79: 25 | I79: 9 independent 3.99 kt access slots; 8 required | J79: kt | K79: =IF(ISNUMBER('Section Bills'!J25),'Section Bills'!J25,"") -> 35.91 | L79: =IF(ISNUMBER('Section Bills'!K25),'Section Bills'!K25,"") -> 31.075 | M79: =Controls!$B$7 -> 0.025 | N79: =IF(AND(ISNUMBER(K79),ISNUMBER(L79),L79>0),K79/L79*(1-M79),"") -> 1.1267015 | P79: =IF(O79="",0,COUNTIFS('Gap Migration'!$G$7:$G$91,O79,'Gap Migration'!$J$7:$J$91,1)) -> 0 | Q79: 0 | R79: 0 | S79: =IF(ISNUMBER(N79),IF(N79>=Controls!$B$8,"DESIGN CLOSE","NEGATIVE"),IF(P79=1,"MEASUREMENT READY","UNSCOPED")) -> DESIGN CLOSE | T79: =IF(S79="DESIGN CLOSE","root-native section bill",IF(S79="MEASUREMENT READY","executable protocol; observation empty","return to architecture")) -> root-native section bill | U79: 0
A80: LF-B-A01-W02 | B80: MS-LF | C80: LF-B | D80: A01 | E80: Mass and material custody | F80: W02 | G80: Fatal-keystone challenge | H80: 25 | I80: 9 independent 3.99 kt access slots; 8 required | J80: kt | M80: =Controls!$B$7 -> 0.025 | N80: =IF(AND(ISNUMBER(K80),ISNUMBER(L80),L80>0),K80/L80*(1-M80),"") | O80: KX-LF-B-A01 | P80: =IF(O80="",0,COUNTIFS('Gap Migration'!$G$7:$G$91,O80,'Gap Migration'!$J$7:$J$91,1)) -> 1 | Q80: 0 | R80: 0 | S80: =IF(ISNUMBER(N80),IF(N80>=Controls!$B$8,"DESIGN CLOSE","NEGATIVE"),IF(P80=1,"MEASUREMENT READY","UNSCOPED")) -> MEASUREMENT READY | T80: =IF(S80="DESIGN CLOSE","root-native section bill",IF(S80="MEASUREMENT READY","executable protocol; observation empty","return to architecture")) -> executable protocol; observation empty | U80: 0
A81: LF-B-A01-W03 | B81: MS-LF | C81: LF-B | D81: A01 | E81: Mass and material custody | F81: W03 | G81: Largest-independent-cell loss | H81: 25 | I81: 9 independent 3.99 kt access slots; 8 required | J81: kt | K81: =IF(ISNUMBER('Section Bills'!L25),'Section Bills'!L25,"") -> 31.92 | L81: =IF(ISNUMBER('Section Bills'!M25),'Section Bills'!M25,"") -> 31.075 | M81: =Controls!$B$7 -> 0.025 | N81: =IF(AND(ISNUMBER(K81),ISNUMBER(L81),L81>0),K81/L81*(1-M81),"") -> 1.0015125 | O81: MA-LF-B-A01-W03 | P81: =IF(O81="",0,COUNTIFS('Gap Migration'!$G$7:$G$91,O81,'Gap Migration'!$J$7:$J$91,1)) -> 1 | Q81: 0 | R81: 0 | S81: =IF(ISNUMBER(N81),IF(N81>=Controls!$B$8,"DESIGN CLOSE","NEGATIVE"),IF(P81=1,"MEASUREMENT READY","UNSCOPED")) -> DESIGN CLOSE | T81: =IF(S81="DESIGN CLOSE","root-native section bill",IF(S81="MEASUREMENT READY","executable protocol; observation empty","return to architecture")) -> root-native section bill | U81: 0
A82: LF-B-A01-W04 | B82: MS-LF | C82: LF-B | D82: A01 | E82: Mass and material custody | F82: W04 | G82: Cold reconstruction | H82: 25 | I82: 9 independent 3.99 kt access slots; 8 required | J82: kt | M82: =Controls!$B$7 -> 0.025 | N82: =IF(AND(ISNUMBER(K82),ISNUMBER(L82),L82>0),K82/L82*(1-M82),"") | O82: RC-LF-B-A01 | P82: =IF(O82="",0,COUNTIFS('Gap Migration'!$G$7:$G$91,O82,'Gap Migration'!$J$7:$J$91,1)) -> 1 | Q82: 0 | R82: 0 | S82: =IF(ISNUMBER(N82),IF(N82>=Controls!$B$8,"DESIGN CLOSE","NEGATIVE"),IF(P82=1,"MEASUREMENT READY","UNSCOPED")) -> MEASUREMENT READY | T82: =IF(S82="DESIGN CLOSE","root-native section bill",IF(S82="MEASUREMENT READY","executable protocol; observation empty","return to architecture")) -> executable protocol; observation empty | U82: 0
A83: LF-B-A02-W01 | B83: MS-LF | C83: LF-B | D83: A02 | E83: Energy and heat | F83: W01 | G83: Nominal mission | H83: 26 | I83: 4 isolated conversion cells | J83: MW | K83: =IF(ISNUMBER('Section Bills'!J26),'Section Bills'!J26,"") -> 52 | L83: =IF(ISNUMBER('Section Bills'!K26),'Section Bills'!K26,"") -> 37.351042 | M83: =Controls!$B$7 -> 0.025 | N83: =IF(AND(ISNUMBER(K83),ISNUMBER(L83),L83>0),K83/L83*(1-M83),"") -> 1.3573919 | P83: =IF(O83="",0,COUNTIFS('Gap Migration'!$G$7:$G$91,O83,'Gap Migration'!$J$7:$J$91,1)) -> 0 | Q83: 0 | R83: 0 | S83: =IF(ISNUMBER(N83),IF(N83>=Controls!$B$8,"DESIGN CLOSE","NEGATIVE"),IF(P83=1,"MEASUREMENT READY","UNSCOPED")) -> DESIGN CLOSE | T83: =IF(S83="DESIGN CLOSE","root-native section bill",IF(S83="MEASUREMENT READY","executable protocol; observation empty","return to architecture")) -> root-native section bill | U83: 0
A84: LF-B-A02-W02 | B84: MS-LF | C84: LF-B | D84: A02 | E84: Energy and heat | F84: W02 | G84: Fatal-keystone challenge | H84: 26 | I84: 4 isolated conversion cells | J84: MW | M84: =Controls!$B$7 -> 0.025 | N84: =IF(AND(ISNUMBER(K84),ISNUMBER(L84),L84>0),K84/L84*(1-M84),"") | O84: KX-LF-B-A02 | P84: =IF(O84="",0,COUNTIFS('Gap Migration'!$G$7:$G$91,O84,'Gap Migration'!$J$7:$J$91,1)) -> 1 | Q84: 0 | R84: 0 | S84: =IF(ISNUMBER(N84),IF(N84>=Controls!$B$8,"DESIGN CLOSE","NEGATIVE"),IF(P84=1,"MEASUREMENT READY","UNSCOPED")) -> MEASUREMENT READY | T84: =IF(S84="DESIGN CLOSE","root-native section bill",IF(S84="MEASUREMENT READY","executable protocol; observation empty","return to architecture")) -> executable protocol; observation empty | U84: 0
A85: LF-B-A02-W03 | B85: MS-LF | C85: LF-B | D85: A02 | E85: Energy and heat | F85: W03 | G85: Largest-independent-cell loss | H85: 26 | I85: 4 isolated conversion cells | J85: MW | K85: =IF(ISNUMBER('Section Bills'!L26),'Section Bills'!L26,"") -> 39 | L85: =IF(ISNUMBER('Section Bills'!M26),'Section Bills'!M26,"") -> 37.351042 | M85: =Controls!$B$7 -> 0.025 | N85: =IF(AND(ISNUMBER(K85),ISNUMBER(L85),L85>0),K85/L85*(1-M85),"") -> 1.0180439 | P85: =IF(O85="",0,COUNTIFS('Gap Migration'!$G$7:$G$91,O85,'Gap Migration'!$J$7:$J$91,1)) -> 0 | Q85: 0 | R85: 0 | S85: =IF(ISNUMBER(N85),IF(N85>=Controls!$B$8,"DESIGN CLOSE","NEGATIVE"),IF(P85=1,"MEASUREMENT READY","UNSCOPED")) -> DESIGN CLOSE | T85: =IF(S85="DESIGN CLOSE","root-native section bill",IF(S85="MEASUREMENT READY","executable protocol; observation empty","return to architecture")) -> root-native section bill | U85: 0
A86: LF-B-A02-W04 | B86: MS-LF | C86: LF-B | D86: A02 | E86: Energy and heat | F86: W04 | G86: Cold reconstruction | H86: 26 | I86: 4 isolated conversion cells | J86: MW | M86: =Controls!$B$7 -> 0.025 | N86: =IF(AND(ISNUMBER(K86),ISNUMBER(L86),L86>0),K86/L86*(1-M86),"") | O86: RC-LF-B-A02 | P86: =IF(O86="",0,COUNTIFS('Gap Migration'!$G$7:$G$91,O86,'Gap Migration'!$J$7:$J$91,1)) -> 1 | Q86: 0 | R86: 0 | S86: =IF(ISNUMBER(N86),IF(N86>=Controls!$B$8,"DESIGN CLOSE","NEGATIVE"),IF(P86=1,"MEASUREMENT READY","UNSCOPED")) -> MEASUREMENT READY | T86: =IF(S86="DESIGN CLOSE","root-native section bill",IF(S86="MEASUREMENT READY","executable protocol; observation empty","return to architecture")) -> executable protocol; observation empty | U86: 0
A87: LF-B-A03-W01 | B87: MS-LF | C87: LF-B | D87: A03 | E87: Geometry and load path | F87: W01 | G87: Nominal mission | H87: 27 | I87: 2 independently usable 15.5 km water paths | J87: pipe-km | K87: =IF(ISNUMBER('Section Bills'!J27),'Section Bills'!J27,"") -> 31 | L87: =IF(ISNUMBER('Section Bills'!K27),'Section Bills'!K27,"") -> 30 | M87: =Controls!$B$7 -> 0.025 | N87: =IF(AND(ISNUMBER(K87),ISNUMBER(L87),L87>0),K87/L87*(1-M87),"") -> 1.0075 | P87: =IF(O87="",0,COUNTIFS('Gap Migration'!$G$7:$G$91,O87,'Gap Migration'!$J$7:$J$91,1)) -> 0 | Q87: 0 | R87: 0 | S87: =IF(ISNUMBER(N87),IF(N87>=Controls!$B$8,"DESIGN CLOSE","NEGATIVE"),IF(P87=1,"MEASUREMENT READY","UNSCOPED")) -> DESIGN CLOSE | T87: =IF(S87="DESIGN CLOSE","root-native section bill",IF(S87="MEASUREMENT READY","executable protocol; observation empty","return to architecture")) -> root-native section bill | U87: 0
A88: LF-B-A03-W02 | B88: MS-LF | C88: LF-B | D88: A03 | E88: Geometry and load path | F88: W02 | G88: Fatal-keystone challenge | H88: 27 | I88: 2 independently usable 15.5 km water paths | J88: pipe-km | M88: =Controls!$B$7 -> 0.025 | N88: =IF(AND(ISNUMBER(K88),ISNUMBER(L88),L88>0),K88/L88*(1-M88),"") | O88: KX-LF-B-A03 | P88: =IF(O88="",0,COUNTIFS('Gap Migration'!$G$7:$G$91,O88,'Gap Migration'!$J$7:$J$91,1)) -> 1 | Q88: 0 | R88: 0 | S88: =IF(ISNUMBER(N88),IF(N88>=Controls!$B$8,"DESIGN CLOSE","NEGATIVE"),IF(P88=1,"MEASUREMENT READY","UNSCOPED")) -> MEASUREMENT READY | T88: =IF(S88="DESIGN CLOSE","root-native section bill",IF(S88="MEASUREMENT READY","executable protocol; observation empty","return to architecture")) -> executable protocol; observation empty | U88: 0
A89: LF-B-A03-W03 | B89: MS-LF | C89: LF-B | D89: A03 | E89: Geometry and load path | F89: W03 | G89: Largest-independent-cell loss | H89: 27 | I89: 2 independently usable 15.5 km water paths | J89: pipe-km | K89: =IF(ISNUMBER('Section Bills'!L27),'Section Bills'!L27,"") -> 15.5 | L89: =IF(ISNUMBER('Section Bills'!M27),'Section Bills'!M27,"") -> 15 | M89: =Controls!$B$7 -> 0.025 | N89: =IF(AND(ISNUMBER(K89),ISNUMBER(L89),L89>0),K89/L89*(1-M89),"") -> 1.0075 | P89: =IF(O89="",0,COUNTIFS('Gap Migration'!$G$7:$G$91,O89,'Gap Migration'!$J$7:$J$91,1)) -> 0 | Q89: 0 | R89: 0 | S89: =IF(ISNUMBER(N89),IF(N89>=Controls!$B$8,"DESIGN CLOSE","NEGATIVE"),IF(P89=1,"MEASUREMENT READY","UNSCOPED")) -> DESIGN CLOSE | T89: =IF(S89="DESIGN CLOSE","root-native section bill",IF(S89="MEASUREMENT READY","executable protocol; observation empty","return to architecture")) -> root-native section bill | U89: 0
A90: LF-B-A03-W04 | B90: MS-LF | C90: LF-B | D90: A03 | E90: Geometry and load path | F90: W04 | G90: Cold reconstruction | H90: 27 | I90: 2 independently usable 15.5 km water paths | J90: pipe-km | M90: =Controls!$B$7 -> 0.025 | N90: =IF(AND(ISNUMBER(K90),ISNUMBER(L90),L90>0),K90/L90*(1-M90),"") | O90: RC-LF-B-A03 | P90: =IF(O90="",0,COUNTIFS('Gap Migration'!$G$7:$G$91,O90,'Gap Migration'!$J$7:$J$91,1)) -> 1 | Q90: 0 | R90: 0 | S90: =IF(ISNUMBER(N90),IF(N90>=Controls!$B$8,"DESIGN CLOSE","NEGATIVE"),IF(P90=1,"MEASUREMENT READY","UNSCOPED")) -> MEASUREMENT READY | T90: =IF(S90="DESIGN CLOSE","root-native section bill",IF(S90="MEASUREMENT READY","executable protocol; observation empty","return to architecture")) -> executable protocol; observation empty | U90: 0
A91: LF-B-A04-W01 | B91: MS-LF | C91: LF-B | D91: A04 | E91: Safe state and human boundary | F91: W01 | G91: Nominal mission | H91: 28 | I91: 3 isolated 13,000 m3 product-water cells | J91: thousand m3 | K91: =IF(ISNUMBER('Section Bills'!J28),'Section Bills'!J28,"") -> 39 | L91: =IF(ISNUMBER('Section Bills'!K28),'Section Bills'!K28,"") -> 25 | M91: =Controls!$B$7 -> 0.025 | N91: =IF(AND(ISNUMBER(K91),ISNUMBER(L91),L91>0),K91/L91*(1-M91),"") -> 1.521 | P91: =IF(O91="",0,COUNTIFS('Gap Migration'!$G$7:$G$91,O91,'Gap Migration'!$J$7:$J$91,1)) -> 0 | Q91: 0 | R91: 0 | S91: =IF(ISNUMBER(N91),IF(N91>=Controls!$B$8,"DESIGN CLOSE","NEGATIVE"),IF(P91=1,"MEASUREMENT READY","UNSCOPED")) -> DESIGN CLOSE | T91: =IF(S91="DESIGN CLOSE","root-native section bill",IF(S91="MEASUREMENT READY","executable protocol; observation empty","return to architecture")) -> root-native section bill | U91: 0
A92: LF-B-A04-W02 | B92: MS-LF | C92: LF-B | D92: A04 | E92: Safe state and human boundary | F92: W02 | G92: Fatal-keystone challenge | H92: 28 | I92: 3 isolated 13,000 m3 product-water cells | J92: thousand m3 | M92: =Controls!$B$7 -> 0.025 | N92: =IF(AND(ISNUMBER(K92),ISNUMBER(L92),L92>0),K92/L92*(1-M92),"") | O92: KX-LF-B-A04 | P92: =IF(O92="",0,COUNTIFS('Gap Migration'!$G$7:$G$91,O92,'Gap Migration'!$J$7:$J$91,1)) -> 1 | Q92: 0 | R92: 0 | S92: =IF(ISNUMBER(N92),IF(N92>=Controls!$B$8,"DESIGN CLOSE","NEGATIVE"),IF(P92=1,"MEASUREMENT READY","UNSCOPED")) -> MEASUREMENT READY | T92: =IF(S92="DESIGN CLOSE","root-native section bill",IF(S92="MEASUREMENT READY","executable protocol; observation empty","return to architecture")) -> executable protocol; observation empty | U92: 0
A93: LF-B-A04-W03 | B93: MS-LF | C93: LF-B | D93: A04 | E93: Safe state and human boundary | F93: W03 | G93: Largest-independent-cell loss | H93: 28 | I93: 3 isolated 13,000 m3 product-water cells | J93: thousand m3 | K93: =IF(ISNUMBER('Section Bills'!L28),'Section Bills'!L28,"") -> 26 | L93: =IF(ISNUMBER('Section Bills'!M28),'Section Bills'!M28,"") -> 25 | M93: =Controls!$B$7 -> 0.025 | N93: =IF(AND(ISNUMBER(K93),ISNUMBER(L93),L93>0),K93/L93*(1-M93),"") -> 1.014 | P93: =IF(O93="",0,COUNTIFS('Gap Migration'!$G$7:$G$91,O93,'Gap Migration'!$J$7:$J$91,1)) -> 0 | Q93: 0 | R93: 0 | S93: =IF(ISNUMBER(N93),IF(N93>=Controls!$B$8,"DESIGN CLOSE","NEGATIVE"),IF(P93=1,"MEASUREMENT READY","UNSCOPED")) -> DESIGN CLOSE | T93: =IF(S93="DESIGN CLOSE","root-native section bill",IF(S93="MEASUREMENT READY","executable protocol; observation empty","return to architecture")) -> root-native section bill | U93: 0
A94: LF-B-A04-W04 | B94: MS-LF | C94: LF-B | D94: A04 | E94: Safe state and human boundary | F94: W04 | G94: Cold reconstruction | H94: 28 | I94: 3 isolated 13,000 m3 product-water cells | J94: thousand m3 | M94: =Controls!$B$7 -> 0.025 | N94: =IF(AND(ISNUMBER(K94),ISNUMBER(L94),L94>0),K94/L94*(1-M94),"") | O94: RC-LF-B-A04 | P94: =IF(O94="",0,COUNTIFS('Gap Migration'!$G$7:$G$91,O94,'Gap Migration'!$J$7:$J$91,1)) -> 1 | Q94: 0 | R94: 0 | S94: =IF(ISNUMBER(N94),IF(N94>=Controls!$B$8,"DESIGN CLOSE","NEGATIVE"),IF(P94=1,"MEASUREMENT READY","UNSCOPED")) -> MEASUREMENT READY | T94: =IF(S94="DESIGN CLOSE","root-native section bill",IF(S94="MEASUREMENT READY","executable protocol; observation empty","return to architecture")) -> executable protocol; observation empty | U94: 0
A95: LF-B-A05-W01 | B95: MS-LF | C95: LF-B | D95: A05 | E95: Residual and environmental custody | F95: W01 | G95: Nominal mission | H95: 29 | I95: 3 isolated 10,300 m3/day injection paths | J95: thousand m3/day | K95: =IF(ISNUMBER('Section Bills'!J29),'Section Bills'!J29,"") -> 30.9 | L95: =IF(ISNUMBER('Section Bills'!K29),'Section Bills'!K29,"") -> 20 | M95: =Controls!$B$7 -> 0.025 | N95: =IF(AND(ISNUMBER(K95),ISNUMBER(L95),L95>0),K95/L95*(1-M95),"") -> 1.506375 | P95: =IF(O95="",0,COUNTIFS('Gap Migration'!$G$7:$G$91,O95,'Gap Migration'!$J$7:$J$91,1)) -> 0 | Q95: 0 | R95: 0 | S95: =IF(ISNUMBER(N95),IF(N95>=Controls!$B$8,"DESIGN CLOSE","NEGATIVE"),IF(P95=1,"MEASUREMENT READY","UNSCOPED")) -> DESIGN CLOSE | T95: =IF(S95="DESIGN CLOSE","root-native section bill",IF(S95="MEASUREMENT READY","executable protocol; observation empty","return to architecture")) -> root-native section bill | U95: 0
A96: LF-B-A05-W02 | B96: MS-LF | C96: LF-B | D96: A05 | E96: Residual and environmental custody | F96: W02 | G96: Fatal-keystone challenge | H96: 29 | I96: 3 isolated 10,300 m3/day injection paths | J96: thousand m3/day | M96: =Controls!$B$7 -> 0.025 | N96: =IF(AND(ISNUMBER(K96),ISNUMBER(L96),L96>0),K96/L96*(1-M96),"") | O96: KX-LF-B-A05 | P96: =IF(O96="",0,COUNTIFS('Gap Migration'!$G$7:$G$91,O96,'Gap Migration'!$J$7:$J$91,1)) -> 1 | Q96: 0 | R96: 0 | S96: =IF(ISNUMBER(N96),IF(N96>=Controls!$B$8,"DESIGN CLOSE","NEGATIVE"),IF(P96=1,"MEASUREMENT READY","UNSCOPED")) -> MEASUREMENT READY | T96: =IF(S96="DESIGN CLOSE","root-native section bill",IF(S96="MEASUREMENT READY","executable protocol; observation empty","return to architecture")) -> executable protocol; observation empty | U96: 0
A97: LF-B-A05-W03 | B97: MS-LF | C97: LF-B | D97: A05 | E97: Residual and environmental custody | F97: W03 | G97: Largest-independent-cell loss | H97: 29 | I97: 3 isolated 10,300 m3/day injection paths | J97: thousand m3/day | K97: =IF(ISNUMBER('Section Bills'!L29),'Section Bills'!L29,"") -> 20.6 | L97: =IF(ISNUMBER('Section Bills'!M29),'Section Bills'!M29,"") -> 20 | M97: =Controls!$B$7 -> 0.025 | N97: =IF(AND(ISNUMBER(K97),ISNUMBER(L97),L97>0),K97/L97*(1-M97),"") -> 1.00425 | P97: =IF(O97="",0,COUNTIFS('Gap Migration'!$G$7:$G$91,O97,'Gap Migration'!$J$7:$J$91,1)) -> 0 | Q97: 0 | R97: 0 | S97: =IF(ISNUMBER(N97),IF(N97>=Controls!$B$8,"DESIGN CLOSE","NEGATIVE"),IF(P97=1,"MEASUREMENT READY","UNSCOPED")) -> DESIGN CLOSE | T97: =IF(S97="DESIGN CLOSE","root-native section bill",IF(S97="MEASUREMENT READY","executable protocol; observation empty","return to architecture")) -> root-native section bill | U97: 0
A98: LF-B-A05-W04 | B98: MS-LF | C98: LF-B | D98: A05 | E98: Residual and environmental custody | F98: W04 | G98: Cold reconstruction | H98: 29 | I98: 3 isolated 10,300 m3/day injection paths | J98: thousand m3/day | M98: =Controls!$B$7 -> 0.025 | N98: =IF(AND(ISNUMBER(K98),ISNUMBER(L98),L98>0),K98/L98*(1-M98),"") | O98: RC-LF-B-A05 | P98: =IF(O98="",0,COUNTIFS('Gap Migration'!$G$7:$G$91,O98,'Gap Migration'!$J$7:$J$91,1)) -> 1 | Q98: 0 | R98: 0 | S98: =IF(ISNUMBER(N98),IF(N98>=Controls!$B$8,"DESIGN CLOSE","NEGATIVE"),IF(P98=1,"MEASUREMENT READY","UNSCOPED")) -> MEASUREMENT READY | T98: =IF(S98="DESIGN CLOSE","root-native section bill",IF(S98="MEASUREMENT READY","executable protocol; observation empty","return to architecture")) -> executable protocol; observation empty | U98: 0
A99: LF-B-A06-W01 | B99: MS-LF | C99: LF-B | D99: A06 | E99: Removal and cold reconstruction | F99: W01 | G99: Nominal mission | H99: 30 | I99: sealed geothermal-position reconstruction chain | J99: h | M99: =Controls!$B$7 -> 0.025 | N99: =IF(AND(ISNUMBER(K99),ISNUMBER(L99),L99>0),K99/L99*(1-M99),"") | O99: RB-LF-B-W01 | P99: =IF(O99="",0,COUNTIFS('Gap Migration'!$G$7:$G$91,O99,'Gap Migration'!$J$7:$J$91,1)) -> 1 | Q99: 0 | R99: 0 | S99: =IF(ISNUMBER(N99),IF(N99>=Controls!$B$8,"DESIGN CLOSE","NEGATIVE"),IF(P99=1,"MEASUREMENT READY","UNSCOPED")) -> MEASUREMENT READY | T99: =IF(S99="DESIGN CLOSE","root-native section bill",IF(S99="MEASUREMENT READY","executable protocol; observation empty","return to architecture")) -> executable protocol; observation empty | U99: 0
A100: LF-B-A06-W02 | B100: MS-LF | C100: LF-B | D100: A06 | E100: Removal and cold reconstruction | F100: W02 | G100: Fatal-keystone challenge | H100: 30 | I100: sealed geothermal-position reconstruction chain | J100: h | M100: =Controls!$B$7 -> 0.025 | N100: =IF(AND(ISNUMBER(K100),ISNUMBER(L100),L100>0),K100/L100*(1-M100),"") | O100: KX-LF-B-A06 | P100: =IF(O100="",0,COUNTIFS('Gap Migration'!$G$7:$G$91,O100,'Gap Migration'!$J$7:$J$91,1)) -> 1 | Q100: 0 | R100: 0 | S100: =IF(ISNUMBER(N100),IF(N100>=Controls!$B$8,"DESIGN CLOSE","NEGATIVE"),IF(P100=1,"MEASUREMENT READY","UNSCOPED")) -> MEASUREMENT READY | T100: =IF(S100="DESIGN CLOSE","root-native section bill",IF(S100="MEASUREMENT READY","executable protocol; observation empty","return to architecture")) -> executable protocol; observation empty | U100: 0
A101: LF-B-A06-W03 | B101: MS-LF | C101: LF-B | D101: A06 | E101: Removal and cold reconstruction | F101: W03 | G101: Largest-independent-cell loss | H101: 30 | I101: sealed geothermal-position reconstruction chain | J101: h | M101: =Controls!$B$7 -> 0.025 | N101: =IF(AND(ISNUMBER(K101),ISNUMBER(L101),L101>0),K101/L101*(1-M101),"") | O101: RB-LF-B-W03 | P101: =IF(O101="",0,COUNTIFS('Gap Migration'!$G$7:$G$91,O101,'Gap Migration'!$J$7:$J$91,1)) -> 1 | Q101: 0 | R101: 0 | S101: =IF(ISNUMBER(N101),IF(N101>=Controls!$B$8,"DESIGN CLOSE","NEGATIVE"),IF(P101=1,"MEASUREMENT READY","UNSCOPED")) -> MEASUREMENT READY | T101: =IF(S101="DESIGN CLOSE","root-native section bill",IF(S101="MEASUREMENT READY","executable protocol; observation empty","return to architecture")) -> executable protocol; observation empty | U101: 0
A102: LF-B-A06-W04 | B102: MS-LF | C102: LF-B | D102: A06 | E102: Removal and cold reconstruction | F102: W04 | G102: Cold reconstruction | H102: 30 | I102: sealed geothermal-position reconstruction chain | J102: h | M102: =Controls!$B$7 -> 0.025 | N102: =IF(AND(ISNUMBER(K102),ISNUMBER(L102),L102>0),K102/L102*(1-M102),"") | O102: RC-LF-B-A06 | P102: =IF(O102="",0,COUNTIFS('Gap Migration'!$G$7:$G$91,O102,'Gap Migration'!$J$7:$J$91,1)) -> 1 | Q102: 0 | R102: 0 | S102: =IF(ISNUMBER(N102),IF(N102>=Controls!$B$8,"DESIGN CLOSE","NEGATIVE"),IF(P102=1,"MEASUREMENT READY","UNSCOPED")) -> MEASUREMENT READY | T102: =IF(S102="DESIGN CLOSE","root-native section bill",IF(S102="MEASUREMENT READY","executable protocol; observation empty","return to architecture")) -> executable protocol; observation empty | U102: 0
A103: HU-A-A01-W01 | B103: MS-HU | C103: HU-A | D103: A01 | E103: Mass and material custody | F103: W01 | G103: Nominal mission | H103: 31 | I103: 8 independent 7.35 kt access cells | J103: kt | K103: =IF(ISNUMBER('Section Bills'!J31),'Section Bills'!J31,"") -> 58.8 | L103: =IF(ISNUMBER('Section Bills'!K31),'Section Bills'!K31,"") -> 50 | M103: =Controls!$B$7 -> 0.025 | N103: =IF(AND(ISNUMBER(K103),ISNUMBER(L103),L103>0),K103/L103*(1-M103),"") -> 1.1466 | P103: =IF(O103="",0,COUNTIFS('Gap Migration'!$G$7:$G$91,O103,'Gap Migration'!$J$7:$J$91,1)) -> 0 | Q103: 0 | R103: 0 | S103: =IF(ISNUMBER(N103),IF(N103>=Controls!$B$8,"DESIGN CLOSE","NEGATIVE"),IF(P103=1,"MEASUREMENT READY","UNSCOPED")) -> DESIGN CLOSE | T103: =IF(S103="DESIGN CLOSE","root-native section bill",IF(S103="MEASUREMENT READY","executable protocol; observation empty","return to architecture")) -> root-native section bill | U103: 0
...

Sheet Gap Migration
A2: Eighty-five inherited gaps now have executable successors
A4: One LF-B access gap is now defined by architecture and still awaits test. The other eighty-four are measurement-ready and evidence-empty.
A6: Legacy gap | B6: System | C6: Root | D6: Account | E6: World | F6: Original absence | G6: Successor specification | H6: Protocol owner | I6: Acceptance criterion | J6: Executable | K6: Resolved by design | L6: Observations | M6: Evidence accepted | N6: Successor state
A7: KX-ET-A-A01 | B7: MS-ET | C7: ET-A | D7: A01 | E7: W02 | F7: fatal-keystone coefficient and valid event absent | G7: KX-ET-A-A01 | H7: Keystone Protocols | I7: lower admitted capacity / upper burden ≥ 1.00 after the 2.5% screen | J7: 1 | K7: 0 | L7: 0 | M7: 0 | N7: =IF(K7=1,"DESIGN DEFINED / TEST PENDING",IF(AND(J7=1,L7=0,M7=0),"MEASUREMENT READY / EVIDENCE EMPTY","RETURN")) -> MEASUREMENT READY / EVIDENCE EMPTY
A8: RC-ET-A-A01 | B8: MS-ET | C8: ET-A | D8: A01 | E8: W04 | F8: outside-team cold-reconstruction result absent | G8: RC-ET-A-A01 | H8: Rebuild Protocols | I8: outside team requalifies the account with signed ancestry within 168 h | J8: 1 | K8: 0 | L8: 0 | M8: 0 | N8: =IF(K8=1,"DESIGN DEFINED / TEST PENDING",IF(AND(J8=1,L8=0,M8=0),"MEASUREMENT READY / EVIDENCE EMPTY","RETURN")) -> MEASUREMENT READY / EVIDENCE EMPTY
A9: KX-ET-A-A02 | B9: MS-ET | C9: ET-A | D9: A02 | E9: W02 | F9: fatal-keystone coefficient and valid event absent | G9: KX-ET-A-A02 | H9: Keystone Protocols | I9: lower firm output / upper demand ≥ 1.00 after the 2.5% screen | J9: 1 | K9: 0 | L9: 0 | M9: 0 | N9: =IF(K9=1,"DESIGN DEFINED / TEST PENDING",IF(AND(J9=1,L9=0,M9=0),"MEASUREMENT READY / EVIDENCE EMPTY","RETURN")) -> MEASUREMENT READY / EVIDENCE EMPTY
A10: RC-ET-A-A02 | B10: MS-ET | C10: ET-A | D10: A02 | E10: W04 | F10: outside-team cold-reconstruction result absent | G10: RC-ET-A-A02 | H10: Rebuild Protocols | I10: outside team requalifies the account with signed ancestry within 168 h | J10: 1 | K10: 0 | L10: 0 | M10: 0 | N10: =IF(K10=1,"DESIGN DEFINED / TEST PENDING",IF(AND(J10=1,L10=0,M10=0),"MEASUREMENT READY / EVIDENCE EMPTY","RETURN")) -> MEASUREMENT READY / EVIDENCE EMPTY
A11: KX-ET-A-A03 | B11: MS-ET | C11: ET-A | D11: A03 | E11: W02 | F11: fatal-keystone coefficient and valid event absent | G11: KX-ET-A-A03 | H11: Keystone Protocols | I11: lower usable geometry / upper requirement ≥ 1.00 after the 2.5% screen | J11: 1 | K11: 0 | L11: 0 | M11: 0 | N11: =IF(K11=1,"DESIGN DEFINED / TEST PENDING",IF(AND(J11=1,L11=0,M11=0),"MEASUREMENT READY / EVIDENCE EMPTY","RETURN")) -> MEASUREMENT READY / EVIDENCE EMPTY
A12: RC-ET-A-A03 | B12: MS-ET | C12: ET-A | D12: A03 | E12: W04 | F12: outside-team cold-reconstruction result absent | G12: RC-ET-A-A03 | H12: Rebuild Protocols | I12: outside team requalifies the account with signed ancestry within 168 h | J12: 1 | K12: 0 | L12: 0 | M12: 0 | N12: =IF(K12=1,"DESIGN DEFINED / TEST PENDING",IF(AND(J12=1,L12=0,M12=0),"MEASUREMENT READY / EVIDENCE EMPTY","RETURN")) -> MEASUREMENT READY / EVIDENCE EMPTY
A13: KX-ET-A-A04 | B13: MS-ET | C13: ET-A | D13: A04 | E13: W02 | F13: fatal-keystone coefficient and valid event absent | G13: KX-ET-A-A04 | H13: Keystone Protocols | I13: every safe-state and civil-rights predicate remains true; no averaging | J13: 1 | K13: 0 | L13: 0 | M13: 0 | N13: =IF(K13=1,"DESIGN DEFINED / TEST PENDING",IF(AND(J13=1,L13=0,M13=0),"MEASUREMENT READY / EVIDENCE EMPTY","RETURN")) -> MEASUREMENT READY / EVIDENCE EMPTY
A14: RC-ET-A-A04 | B14: MS-ET | C14: ET-A | D14: A04 | E14: W04 | F14: outside-team cold-reconstruction result absent | G14: RC-ET-A-A04 | H14: Rebuild Protocols | I14: outside team requalifies the account with signed ancestry within 168 h | J14: 1 | K14: 0 | L14: 0 | M14: 0 | N14: =IF(K14=1,"DESIGN DEFINED / TEST PENDING",IF(AND(J14=1,L14=0,M14=0),"MEASUREMENT READY / EVIDENCE EMPTY","RETURN")) -> MEASUREMENT READY / EVIDENCE EMPTY
A15: KX-ET-A-A05 | B15: MS-ET | C15: ET-A | D15: A05 | E15: W02 | F15: fatal-keystone coefficient and valid event absent | G15: KX-ET-A-A05 | H15: Keystone Protocols | I15: lower owned treatment / upper generated residual ≥ 1.00 after the 2.5% screen | J15: 1 | K15: 0 | L15: 0 | M15: 0 | N15: =IF(K15=1,"DESIGN DEFINED / TEST PENDING",IF(AND(J15=1,L15=0,M15=0),"MEASUREMENT READY / EVIDENCE EMPTY","RETURN")) -> MEASUREMENT READY / EVIDENCE EMPTY
A16: RC-ET-A-A05 | B16: MS-ET | C16: ET-A | D16: A05 | E16: W04 | F16: outside-team cold-reconstruction result absent | G16: RC-ET-A-A05 | H16: Rebuild Protocols | I16: outside team requalifies the account with signed ancestry within 168 h | J16: 1 | K16: 0 | L16: 0 | M16: 0 | N16: =IF(K16=1,"DESIGN DEFINED / TEST PENDING",IF(AND(J16=1,L16=0,M16=0),"MEASUREMENT READY / EVIDENCE EMPTY","RETURN")) -> MEASUREMENT READY / EVIDENCE EMPTY
A17: KX-ET-A-A06 | B17: MS-ET | C17: ET-A | D17: A06 | E17: W02 | F17: fatal-keystone coefficient and valid event absent | G17: KX-ET-A-A06 | H17: Keystone Protocols | I17: same account requalified with signed ancestry within 168 h | J17: 1 | K17: 0 | L17: 0 | M17: 0 | N17: =IF(K17=1,"DESIGN DEFINED / TEST PENDING",IF(AND(J17=1,L17=0,M17=0),"MEASUREMENT READY / EVIDENCE EMPTY","RETURN")) -> MEASUREMENT READY / EVIDENCE EMPTY
A18: RC-ET-A-A06 | B18: MS-ET | C18: ET-A | D18: A06 | E18: W04 | F18: outside-team cold-reconstruction result absent | G18: RC-ET-A-A06 | H18: Rebuild Protocols | I18: outside team requalifies the account with signed ancestry within 168 h | J18: 1 | K18: 0 | L18: 0 | M18: 0 | N18: =IF(K18=1,"DESIGN DEFINED / TEST PENDING",IF(AND(J18=1,L18=0,M18=0),"MEASUREMENT READY / EVIDENCE EMPTY","RETURN")) -> MEASUREMENT READY / EVIDENCE EMPTY
... A91: MA-LF-B-A01-W03 | B91: MS-LF | C91: LF-B | D91: A01 | E91: W03 | F91: independent loss-world access envelope absent | G91: MA-LF-B-A01-W03 | H91: Section Bills | I91: nine slots installed; eight survivors close the 2.5% screen | J91: 1 | K91: 1 | L91: 0 | M91: 0 | N91: =IF(K91=1,"DESIGN DEFINED / TEST PENDING",IF(AND(J91=1,L91=0,M91=0),"MEASUREMENT READY / EVIDENCE EMPTY","RETURN")) -> DESIGN DEFINED / TEST PENDING

Sheet Keystone Protocols
A2: Thirty-six root-native fatal-keystone protocols
A4: Every challenge is full causal-interface scale. A valid terminal failure kills the lineage; a favorable protocol cannot substitute for the missing observation.
A6: Specification | B6: System | C6: Root | D6: Account | E6: Closure account | F6: Scale | G6: Precondition | H6: Intervention | I6: Primary observation | J6: Sampling and custody | K6: Sustain window | L6: Pass threshold | M6: Immediate kill condition | N6: Observation | O6: Accepted | P6: State
A7: KX-ET-A-A01 | B7: MS-ET | C7: ET-A | D7: A01 | E7: Mass and material custody | F7: full causal-interface article | G7: 24 h rated exchange with moving source and no pier support | H7: remove largest access cell at transfer peak | I7: admitted mass or access capacity and signed custody after largest-cell loss | J7: serial event log plus one-minute mass and custody reconciliation | K7: 72 h | L7: lower admitted capacity / upper burden ≥ 1.00 after the 2.5% screen | M7: motion compensation, wet-to-dry transition or custody breaks complete flow | N7: SOURCE EMPTY | O7: 0 | P7: MEASUREMENT READY
A8: KX-ET-A-A02 | B8: MS-ET | C8: ET-A | D8: A02 | E8: Energy and heat | F8: full causal-interface article | G8: 24 h rated exchange with moving source and no pier support | H8: trip largest energy cell during black start | I8: firm output, black-start recovery, conversion loss and heat rejection after trip | J8: 100 Hz transient capture plus one-minute firm-output and thermal balance | K8: 72 h | L8: lower firm output / upper demand ≥ 1.00 after the 2.5% screen | M8: motion compensation, wet-to-dry transition or custody breaks complete flow | N8: SOURCE EMPTY | O8: 0 | P8: MEASUREMENT READY
A9: KX-ET-A-A03 | B9: MS-ET | C9: ET-A | D9: A03 | E9: Geometry and load path | F9: full causal-interface article | G9: 24 h rated exchange with moving source and no pier support | H9: sever one complete connector at maximum relative motion | I9: complete usable geometry or service flow after path severance | J9: 10 Hz load/path capture plus one-minute flow and clearance record | K9: 72 h | L9: lower usable geometry / upper requirement ≥ 1.00 after the 2.5% screen | M9: motion compensation, wet-to-dry transition or custody breaks complete flow | N9: SOURCE EMPTY | O9: 0 | P9: MEASUREMENT READY
A10: KX-ET-A-A04 | B10: MS-ET | C10: ET-A | D10: A04 | E10: Safe state and human boundary | F10: full causal-interface article | G10: 24 h rated exchange with moving source and no pier support | H10: isolate one refuge/receiver zone | I10: detection, isolation, refuge, egress, manual control and lawful disposition | J10: one-minute environment state plus continuous person/authority event log | K10: 72 h | L10: every safe-state and civil-rights predicate remains true; no averaging | M10: motion compensation, wet-to-dry transition or custody breaks complete flow | N10: SOURCE EMPTY | O10: 0 | P10: MEASUREMENT READY
A11: KX-ET-A-A05 | B11: MS-ET | C11: ET-A | D11: A05 | E11: Residual and environmental custody | F11: full causal-interface article | G11: 24 h rated exchange with moving source and no pier support | H11: close largest residual cell | I11: generated residual, retained inventory, treatment capacity and accepted discharge | J11: one-minute mass balance plus inlet/outlet samples at intervals no longer than 6 h | K11: 72 h | L11: lower owned treatment / upper generated residual ≥ 1.00 after the 2.5% screen | M11: motion compensation, wet-to-dry transition or custody breaks complete flow | N11: SOURCE EMPTY | O11: 0 | P11: MEASUREMENT READY
A12: KX-ET-A-A06 | B12: MS-ET | C12: ET-A | D12: A06 | E12: Removal and cold reconstruction | F12: full causal-interface article | G12: 24 h rated exchange with moving source and no pier support | H12: delete originating runtime, calibration index and builder contact | I12: elapsed outside-team rebuild, recovered ancestry and same-world requalification | J12: signed build-event log with elapsed time recorded to one minute | K12: 72 h | L12: same account requalified with signed ancestry within 168 h | M12: motion compensation, wet-to-dry transition or custody breaks complete flow | N12: SOURCE EMPTY | O12: 0 | P12: MEASUREMENT READY
A13: KX-CT-C-A01 | B13: MS-CT | C13: CT-C | D13: A01 | E13: Mass and material custody | F13: full causal-interface article | G13: 24 h occupied service at declared household and route load | H13: remove largest insertion cell after reversible attachment | I13: admitted mass or access capacity and signed custody after largest-cell loss | J13: serial event log plus one-minute mass and custody reconciliation | K13: 72 h | L13: lower admitted capacity / upper burden ≥ 1.00 after the 2.5% screen | M13: attachment or utility isolation propagates structural, smoke or contamination damage | N13: SOURCE EMPTY | O13: 0 | P13: MEASUREMENT READY
A14: KX-CT-C-A02 | B14: MS-CT | C14: CT-C | D14: A02 | E14: Energy and heat | F14: full causal-interface article | G14: 24 h occupied service at declared household and route load | H14: trip one 7.2 MW cell while islanded | I14: firm output, black-start recovery, conversion loss and heat rejection after trip | J14: 100 Hz transient capture plus one-minute firm-output and thermal balance | K14: 72 h | L14: lower firm output / upper demand ≥ 1.00 after the 2.5% screen | M14: attachment or utility isolation propagates structural, smoke or contamination damage | N14: SOURCE EMPTY | O14: 0 | P14: MEASUREMENT READY
A15: KX-CT-C-A03 | B15: MS-CT | C15: CT-C | D15: A03 | E15: Geometry and load path | F15: full causal-interface article | G15: 24 h occupied service at declared household and route load | H15: hard-isolate the highest-load multi-utility trunk | I15: complete usable geometry or service flow after path severance | J15: 10 Hz load/path capture plus one-minute flow and clearance record | K15: 72 h | L15: lower usable geometry / upper requirement ≥ 1.00 after the 2.5% screen | M15: attachment or utility isolation propagates structural, smoke or contamination damage | N15: SOURCE EMPTY | O15: 0 | P15: MEASUREMENT READY
A16: KX-CT-C-A04 | B16: MS-CT | C16: CT-C | D16: A04 | E16: Safe state and human boundary | F16: full causal-interface article | G16: 24 h occupied service at declared household and route load | H16: introduce smoke and contamination at one zone boundary | I16: detection, isolation, refuge, egress, manual control and lawful disposition | J16: one-minute environment state plus continuous person/authority event log | K16: 72 h | L16: every safe-state and civil-rights predicate remains true; no averaging | M16: attachment or utility isolation propagates structural, smoke or contamination damage | N16: SOURCE EMPTY | O16: 0 | P16: MEASUREMENT READY
A17: KX-CT-C-A05 | B17: MS-CT | C17: CT-C | D17: A05 | E17: Residual and environmental custody | F17: full causal-interface article | G17: 24 h occupied service at declared household and route load | H17: block one dirty-return cell | I17: generated residual, retained inventory, treatment capacity and accepted discharge | J17: one-minute mass balance plus inlet/outlet samples at intervals no longer than 6 h | K17: 72 h | L17: lower owned treatment / upper generated residual ≥ 1.00 after the 2.5% screen | M17: attachment or utility isolation propagates structural, smoke or contamination damage | N17: SOURCE EMPTY | O17: 0 | P17: MEASUREMENT READY
A18: KX-CT-C-A06 | B18: MS-CT | C18: CT-C | D18: A06 | E18: Removal and cold reconstruction | F18: full causal-interface article | G18: 24 h occupied service at declared household and route load | H18: withhold origin geometry, attachment toolchain and runtime | I18: elapsed outside-team rebuild, recovered ancestry and same-world requalification | J18: signed build-event log with elapsed time recorded to one minute | K18: 72 h | L18: same account requalified with signed ancestry within 168 h | M18: attachment or utility isolation propagates structural, smoke or contamination damage | N18: SOURCE EMPTY | O18: 0 | P18: MEASUREMENT READY
... A42: KX-RT-B-A06 | B42: MS-RT | C42: RT-B | D42: A06 | E42: Removal and cold reconstruction | F42: full causal-interface article | G42: 24 h complete 99-position process stack under disconnected control | H42: remove origin planner, calibration stack and proprietary tool index | I42: elapsed outside-team rebuild, recovered ancestry and same-world requalification | J42: signed build-event log with elapsed time recorded to one minute | K42: 168 h | L42: same account requalified with signed ancestry within 168 h | M42: material state, calibration, ancestry or independent release is not reproducible | N42: SOURCE EMPTY | O42: 0 | P42: MEASUREMENT READY

Sheet Rebuild Protocols
A2: Thirty-six account-specific outside-team rebuild protocols
A4: Cold reconstruction means a clean team, frozen public records, no originating runtime and same-world requalification.
A6: Specification | B6: System | C6: Root | D6: Account | E6: Closure account | F6: Starting denial | G6: Builder | H6: Frozen package | I6: Prohibited aid | J6: Start event | K6: End event | L6: Deadline | M6: Unit | N6: Observation | O6: Accepted | P6: State
A7: RC-ET-A-A01 | B7: MS-ET | C7: ET-A | D7: A01 | E7: Mass and material custody | F7: 8 independent access cells disassembled to its public boundary after candidate code and private tools are removed | G7: outside team with no candidate-house personnel | H7: rebuild access cell and serial custody from frozen bill | I7: no origin runtime, undocumented tool, private key, live coaching or hidden host service | J7: sealed record, physical inventory and clean team released at the same instant | K7: account passes W01 and W03 with accepted serial ancestry and safe state | L7: 168 | M7: h | N7: SOURCE EMPTY | O7: 0 | P7: MEASUREMENT READY
A8: RC-ET-A-A02 | B8: MS-ET | C8: ET-A | D8: A02 | E8: Energy and heat | F8: 6 black-start generation cells disassembled to its public boundary after candidate code and private tools are removed | G8: outside team with no candidate-house personnel | H8: rebuild generator, switchgear and heat path | I8: no origin runtime, undocumented tool, private key, live coaching or hidden host service | J8: sealed record, physical inventory and clean team released at the same instant | K8: account passes W01 and W03 with accepted serial ancestry and safe state | L8: 168 | M8: h | N8: SOURCE EMPTY | O8: 0 | P8: MEASUREMENT READY
A9: RC-ET-A-A03 | B9: MS-ET | C9: ET-A | D9: A03 | E9: Geometry and load path | F9: 2 complete motion-decoupled exchange paths disassembled to its public boundary after candidate code and private tools are removed | G9: outside team with no candidate-house personnel | H9: rebuild connector, transition and metering chain | I9: no origin runtime, undocumented tool, private key, live coaching or hidden host service | J9: sealed record, physical inventory and clean team released at the same instant | K9: account passes W01 and W03 with accepted serial ancestry and safe state | L9: 168 | M9: h | N9: SOURCE EMPTY | O9: 0 | P9: MEASUREMENT READY
A10: RC-ET-A-A04 | B10: MS-ET | C10: ET-A | D10: A04 | E10: Safe state and human boundary | F10: 6 independent refuge and receiver zones disassembled to its public boundary after candidate code and private tools are removed | G10: outside team with no candidate-house personnel | H10: rebuild safe-state chain and prove lawful egress | I10: no origin runtime, undocumented tool, private key, live coaching or hidden host service | J10: sealed record, physical inventory and clean team released at the same instant | K10: account passes W01 and W03 with accepted serial ancestry and safe state | L10: 168 | M10: h | N10: SOURCE EMPTY | O10: 0 | P10: MEASUREMENT READY
A11: RC-ET-A-A05 | B11: MS-ET | C11: ET-A | D11: A05 | E11: Residual and environmental custody | F11: 6 contained residual cells disassembled to its public boundary after candidate code and private tools are removed | G11: outside team with no candidate-house personnel | H11: rebuild residual cell and reconcile inventory | I11: no origin runtime, undocumented tool, private key, live coaching or hidden host service | J11: sealed record, physical inventory and clean team released at the same instant | K11: account passes W01 and W03 with accepted serial ancestry and safe state | L11: 168 | M11: h | N11: SOURCE EMPTY | O11: 0 | P11: MEASUREMENT READY
A12: RC-ET-A-A06 | B12: MS-ET | C12: ET-A | D12: A06 | E12: Removal and cold reconstruction | F12: sealed exchange-section reconstruction chain disassembled to its public boundary after candidate code and private tools are removed | G12: outside team with no candidate-house personnel | H12: outside team rebuilds complete causal section within 168 h | I12: no origin runtime, undocumented tool, private key, live coaching or hidden host service | J12: sealed record, physical inventory and clean team released at the same instant | K12: account passes W01 and W03 with accepted serial ancestry and safe state | L12: 168 | M12: h | N12: SOURCE EMPTY | O12: 0 | P12: MEASUREMENT READY
A13: RC-CT-C-A01 | B13: MS-CT | C13: CT-C | D13: A01 | E13: Mass and material custody | F13: 10 independently admitted insertion cells disassembled to its public boundary after candidate code and private tools are removed | G13: outside team with no candidate-house personnel | H13: rebuild one insertion cell at occupied receiver | I13: no origin runtime, undocumented tool, private key, live coaching or hidden host service | J13: sealed record, physical inventory and clean team released at the same instant | K13: account passes W01 and W03 with accepted serial ancestry and safe state | L13: 168 | M13: h | N13: SOURCE EMPTY | O13: 0 | P13: MEASUREMENT READY
A14: RC-CT-C-A02 | B14: MS-CT | C14: CT-C | D14: A02 | E14: Energy and heat | F14: 7 isolated generation cells disassembled to its public boundary after candidate code and private tools are removed | G14: outside team with no candidate-house personnel | H14: rebuild one 7.2 MW cell and isolation boundary | I14: no origin runtime, undocumented tool, private key, live coaching or hidden host service | J14: sealed record, physical inventory and clean team released at the same instant | K14: account passes W01 and W03 with accepted serial ancestry and safe state | L14: 168 | M14: h | N14: SOURCE EMPTY | O14: 0 | P14: MEASUREMENT READY
A15: RC-CT-C-A03 | B15: MS-CT | C15: CT-C | D15: A03 | E15: Geometry and load path | F15: 5 complete multi-utility trunk corridors disassembled to its public boundary after candidate code and private tools are removed | G15: outside team with no candidate-house personnel | H15: rebuild reversible attachment and five service boundaries | I15: no origin runtime, undocumented tool, private key, live coaching or hidden host service | J15: sealed record, physical inventory and clean team released at the same instant | K15: account passes W01 and W03 with accepted serial ancestry and safe state | L15: 168 | M15: h | N15: SOURCE EMPTY | O15: 0 | P15: MEASUREMENT READY
A16: RC-CT-C-A04 | B16: MS-CT | C16: CT-C | D16: A04 | E16: Safe state and human boundary | F16: 8 separately safe occupied zones disassembled to its public boundary after candidate code and private tools are removed | G16: outside team with no candidate-house personnel | H16: rebuild one safe zone without displacing the receiver | I16: no origin runtime, undocumented tool, private key, live coaching or hidden host service | J16: sealed record, physical inventory and clean team released at the same instant | K16: account passes W01 and W03 with accepted serial ancestry and safe state | L16: 168 | M16: h | N16: SOURCE EMPTY | O16: 0 | P16: MEASUREMENT READY
A17: RC-CT-C-A05 | B17: MS-CT | C17: CT-C | D17: A05 | E17: Residual and environmental custody | F17: 6 dirty-return treatment cells disassembled to its public boundary after candidate code and private tools are removed | G17: outside team with no candidate-house personnel | H17: rebuild dirty-return cell and reconcile building inventory | I17: no origin runtime, undocumented tool, private key, live coaching or hidden host service | J17: sealed record, physical inventory and clean team released at the same instant | K17: account passes W01 and W03 with accepted serial ancestry and safe state | L17: 168 | M17: h | N17: SOURCE EMPTY | O17: 0 | P17: MEASUREMENT READY
A18: RC-CT-C-A06 | B18: MS-CT | C18: CT-C | D18: A06 | E18: Removal and cold reconstruction | F18: sealed occupied-spine reconstruction chain disassembled to its public boundary after candidate code and private tools are removed | G18: outside team with no candidate-house personnel | H18: outside team removes and rebuilds section within 168 h | I18: no origin runtime, undocumented tool, private key, live coaching or hidden host service | J18: sealed record, physical inventory and clean team released at the same instant | K18: account passes W01 and W03 with accepted serial ancestry and safe state | L18: 168 | M18: h | N18: SOURCE EMPTY | O18: 0 | P18: MEASUREMENT READY
... A42: RC-RT-B-A06 | B42: MS-RT | C42: RT-B | D42: A06 | E42: Removal and cold reconstruction | F42: sealed microfactory reconstruction chain disassembled to its public boundary after candidate code and private tools are removed | G42: outside team with no candidate-house personnel | H42: outside team recreates dirty-return-to-release mesh within 168 h | I42: no origin runtime, undocumented tool, private key, live coaching or hidden host service | J42: sealed record, physical inventory and clean team released at the same instant | K42: account passes W01 and W03 with accepted serial ancestry and safe state | L42: 168 | M42: h | N42: SOURCE EMPTY | O42: 0 | P42: MEASUREMENT READY

Sheet Rebuild Clocks
A2: Twelve nominal and loss-world reconstruction clocks
A4: These clocks replace the twelve missing A06 W01/W03 objects with executable tests. The 168-hour ceiling is inherited, not observed.
A6: Specification | B6: System | C6: Root | D6: World | E6: Starting state | F6: Required end state | G6: Clock start | H6: Clock stop | I6: Maximum | J6: Unit | K6: Observation | L6: Accepted | M6: State
A7: RB-ET-A-W01 | B7: MS-ET | C7: ET-A | D7: W01 | E7: complete causal section packed and unassembled at public boundary | F7: complete section passes nominal account set | G7: clock starts when sealed package, inventory and clean team are simultaneously released | H7: clock stops only after independent requalification and signed ancestry | I7: 168 | J7: h | K7: SOURCE EMPTY | L7: 0 | M7: MEASUREMENT READY
A8: RB-ET-A-W03 | B8: MS-ET | C8: ET-A | D8: W03 | E8: section operating on survivors with largest independent cell removed | F8: lost cell restored and section passes largest-cell-loss account set | G8: clock starts when sealed package, inventory and clean team are simultaneously released | H8: clock stops only after independent requalification and signed ancestry | I8: 168 | J8: h | K8: SOURCE EMPTY | L8: 0 | M8: MEASUREMENT READY
A9: RB-CT-C-W01 | B9: MS-CT | C9: CT-C | D9: W01 | E9: complete causal section packed and unassembled at public boundary | F9: complete section passes nominal account set | G9: clock starts when sealed package, inventory and clean team are simultaneously released | H9: clock stops only after independent requalification and signed ancestry | I9: 168 | J9: h | K9: SOURCE EMPTY | L9: 0 | M9: MEASUREMENT READY
A10: RB-CT-C-W03 | B10: MS-CT | C10: CT-C | D10: W03 | E10: section operating on survivors with largest independent cell removed | F10: lost cell restored and section passes largest-cell-loss account set | G10: clock starts when sealed package, inventory and clean team are simultaneously released | H10: clock stops only after independent requalification and signed ancestry | I10: 168 | J10: h | K10: SOURCE EMPTY | L10: 0 | M10: MEASUREMENT READY
A11: RB-HC-A-W01 | B11: MS-HC | C11: HC-A | D11: W01 | E11: complete causal section packed and unassembled at public boundary | F11: complete section passes nominal account set | G11: clock starts when sealed package, inventory and clean team are simultaneously released | H11: clock stops only after independent requalification and signed ancestry | I11: 168 | J11: h | K11: SOURCE EMPTY | L11: 0 | M11: MEASUREMENT READY
A12: RB-HC-A-W03 | B12: MS-HC | C12: HC-A | D12: W03 | E12: section operating on survivors with largest independent cell removed | F12: lost cell restored and section passes largest-cell-loss account set | G12: clock starts when sealed package, inventory and clean team are simultaneously released | H12: clock stops only after independent requalification and signed ancestry | I12: 168 | J12: h | K12: SOURCE EMPTY | L12: 0 | M12: MEASUREMENT READY
A13: RB-LF-B-W01 | B13: MS-LF | C13: LF-B | D13: W01 | E13: complete causal section packed and unassembled at public boundary | F13: complete section passes nominal account set | G13: clock starts when sealed package, inventory and clean team are simultaneously released | H13: clock stops only after independent requalification and signed ancestry | I13: 168 | J13: h | K13: SOURCE EMPTY | L13: 0 | M13: MEASUREMENT READY
A14: RB-LF-B-W03 | B14: MS-LF | C14: LF-B | D14: W03 | E14: section operating on survivors with largest independent cell removed | F14: lost cell restored and section passes largest-cell-loss account set | G14: clock starts when sealed package, inventory and clean team are simultaneously released | H14: clock stops only after independent requalification and signed ancestry | I14: 168 | J14: h | K14: SOURCE EMPTY | L14: 0 | M14: MEASUREMENT READY
A15: RB-HU-A-W01 | B15: MS-HU | C15: HU-A | D15: W01 | E15: complete causal section packed and unassembled at public boundary | F15: complete section passes nominal account set | G15: clock starts when sealed package, inventory and clean team are simultaneously released | H15: clock stops only after independent requalification and signed ancestry | I15: 168 | J15: h | K15: SOURCE EMPTY | L15: 0 | M15: MEASUREMENT READY
A16: RB-HU-A-W03 | B16: MS-HU | C16: HU-A | D16: W03 | E16: section operating on survivors with largest independent cell removed | F16: lost cell restored and section passes largest-cell-loss account set | G16: clock starts when sealed package, inventory and clean team are simultaneously released | H16: clock stops only after independent requalification and signed ancestry | I16: 168 | J16: h | K16: SOURCE EMPTY | L16: 0 | M16: MEASUREMENT READY
A17: RB-RT-B-W01 | B17: MS-RT | C17: RT-B | D17: W01 | E17: complete causal section packed and unassembled at public boundary | F17: complete section passes nominal account set | G17: clock starts when sealed package, inventory and clean team are simultaneously released | H17: clock stops only after independent requalification and signed ancestry | I17: 168 | J17: h | K17: SOURCE EMPTY | L17: 0 | M17: MEASUREMENT READY
A18: RB-RT-B-W03 | B18: MS-RT | C18: RT-B | D18: W03 | E18: section operating on survivors with largest independent cell removed | F18: lost cell restored and section passes largest-cell-loss account set | G18: clock starts when sealed package, inventory and clean team are simultaneously released | H18: clock stops only after independent requalification and signed ancestry | I18: 168 | J18: h | K18: SOURCE EMPTY | L18: 0 | M18: MEASUREMENT READY

Sheet Isolation Map
A2: Thirty-six decisive independence boundaries
A4: A shared semantic interface is permitted. A shared mechanism, runtime, utility, safeing path or reconstruction memory is not.
A6: Boundary | B6: System | C6: Root | D6: Account | E6: Decisive section | F6: Physical isolation barrier | G6: Forbidden dependency | H6: Independent witness | I6: State
A7: ET-A-A01 | B7: MS-ET | C7: ET-A | D7: A01 | E7: 8 independent access cells | F7: independent handling path, serial custody and removable cell boundary | G7: shared candidate runtime, hidden host utility, common safeing path or origin-team craft memory | H7: root-native challenge cell and independent evidence custodian | I7: FROZEN
A8: ET-A-A02 | B8: MS-ET | C8: ET-A | D8: A02 | E8: 6 black-start generation cells | F8: cell-local breaker, black start, conversion and heat-rejection boundary | G8: shared candidate runtime, hidden host utility, common safeing path or origin-team craft memory | H8: root-native challenge cell and independent evidence custodian | I8: FROZEN
A9: ET-A-A03 | B9: MS-ET | C9: ET-A | D9: A03 | E9: 2 complete motion-decoupled exchange paths | F9: mechanical, pressure, flow and control hard disconnect at each complete path | G9: shared candidate runtime, hidden host utility, common safeing path or origin-team craft memory | H9: root-native challenge cell and independent evidence custodian | I9: FROZEN
A10: ET-A-A04 | B10: MS-ET | C10: ET-A | D10: A04 | E10: 6 independent refuge and receiver zones | F10: separate detection, isolation, refuge, egress and manual termination | G10: shared candidate runtime, hidden host utility, common safeing path or origin-team craft memory | H10: root-native challenge cell and independent evidence custodian | I10: FROZEN
A11: ET-A-A05 | B11: MS-ET | C11: ET-A | D11: A05 | E11: 6 contained residual cells | F11: valved containment, measured inventory and independent accepted discharge | G11: shared candidate runtime, hidden host utility, common safeing path or origin-team craft memory | H11: root-native challenge cell and independent evidence custodian | I11: FROZEN
A12: ET-A-A06 | B12: MS-ET | C12: ET-A | D12: A06 | E12: sealed exchange-section reconstruction chain | F12: sealed public records, clean tools, independent keys and outside builder | G12: shared candidate runtime, hidden host utility, common safeing path or origin-team craft memory | H12: root-native challenge cell and independent evidence custodian | I12: FROZEN
A13: CT-C-A01 | B13: MS-CT | C13: CT-C | D13: A01 | E13: 10 independently admitted insertion cells | F13: independent handling path, serial custody and removable cell boundary | G13: shared candidate runtime, hidden host utility, common safeing path or origin-team craft memory | H13: root-native challenge cell and independent evidence custodian | I13: FROZEN
A14: CT-C-A02 | B14: MS-CT | C14: CT-C | D14: A02 | E14: 7 isolated generation cells | F14: cell-local breaker, black start, conversion and heat-rejection boundary | G14: shared candidate runtime, hidden host utility, common safeing path or origin-team craft memory | H14: root-native challenge cell and independent evidence custodian | I14: FROZEN
A15: CT-C-A03 | B15: MS-CT | C15: CT-C | D15: A03 | E15: 5 complete multi-utility trunk corridors | F15: mechanical, pressure, flow and control hard disconnect at each complete path | G15: shared candidate runtime, hidden host utility, common safeing path or origin-team craft memory | H15: root-native challenge cell and independent evidence custodian | I15: FROZEN
A16: CT-C-A04 | B16: MS-CT | C16: CT-C | D16: A04 | E16: 8 separately safe occupied zones | F16: separate detection, isolation, refuge, egress and manual termination | G16: shared candidate runtime, hidden host utility, common safeing path or origin-team craft memory | H16: root-native challenge cell and independent evidence custodian | I16: FROZEN
A17: CT-C-A05 | B17: MS-CT | C17: CT-C | D17: A05 | E17: 6 dirty-return treatment cells | F17: valved containment, measured inventory and independent accepted discharge | G17: shared candidate runtime, hidden host utility, common safeing path or origin-team craft memory | H17: root-native challenge cell and independent evidence custodian | I17: FROZEN
... A42: RT-B-A06 | B42: MS-RT | C42: RT-B | D42: A06 | E42: sealed microfactory reconstruction chain | F42: sealed public records, clean tools, independent keys and outside builder | G42: shared candidate runtime, hidden host utility, common safeing path or origin-team craft memory | H42: root-native challenge cell and independent evidence custodian | I42: FROZEN

Sheet Technology Thrusts
A2: Twenty-four root-native invention campaigns
A4: These campaigns pursue the architecture's broken causal sections. They do not converge on a common machine, controller or production design.
A6: Thrust | B6: System | C6: Root | D6: Technology target | E6: Assumption retired | F6: Prototype artifact | G6: Fatal experiment | H6: Article stage | I6: State
A7: ET-A-T1 | B7: MS-ET | C7: ET-A | D7: moving-base load transfer | E7: fixed-base connector assumptions | F7: full-scale active connector under six-axis relative motion | G7: loss of one connector at maximum transfer load | H7: A2 falsification article | I7: HELD FOR TEST
A8: ET-A-T2 | B8: MS-ET | C8: ET-A | D8: self-forming shore transition | E8: prepared pier and crane dependence | F8: autonomous wet-to-dry transition with recoverable anchors | G8: unprepared-shore transition cannot preserve flow | H8: A2 falsification article | I8: HELD FOR TEST
A9: ET-A-T3 | B9: MS-ET | C9: ET-A | D9: custody metrology | E9: mass throughput inferred from machine state | F9: independent metered custody chain across media | G9: custody discontinuity under connector failure | H9: A2 falsification article | I9: HELD FOR TEST
A10: ET-A-T4 | B10: MS-ET | C10: ET-A | D10: reconstructable connectors | E10: vendor service as repairability | F10: cold-built connector from public interface records | G10: outside team misses 168 h requalification | H10: A2 falsification article | I10: HELD FOR TEST
A11: CT-C-T1 | B11: MS-CT | C11: CT-C | D11: reversible occupied-structure attachment | E11: permanent retrofit as insertion prerequisite | F11: load-spreading removable attachment cell | G11: attachment propagates structural damage | H11: A2 falsification article | I11: HELD FOR TEST
A12: CT-C-T2 | B12: MS-CT | C12: CT-C | D12: fault-contained utility trunks | E12: one common riser for all services | F12: five independently isolatable multi-utility corridors | G12: one trunk fault crosses another service | H12: A2 falsification article | I12: HELD FOR TEST
A13: CT-C-T3 | B13: MS-CT | C13: CT-C | D13: contamination-aware installation robotics | E13: evacuated clean workspace assumption | F13: robotic workcell operating through dirty/occupied boundary | G13: installation contaminates occupied zone | H13: A2 falsification article | I13: HELD FOR TEST
A14: CT-C-T4 | B14: MS-CT | C14: CT-C | D14: offline human release | E14: cloud workflow as lawful disposition | F14: local signed household and egress ledger | G14: network loss deletes a lawful disposition | H14: A2 falsification article | I14: HELD FOR TEST
A15: HC-A-T1 | B15: MS-HC | C15: HC-A | D15: plume tomography | E15: single forecast model as causal truth | F15: multi-angle independent plume observation lattice | G15: delivered fluid is not attributable to held edge | H15: A2 falsification article | I15: HELD FOR TEST
A16: HC-A-T2 | B16: MS-HC | C16: HC-A | D16: high-duty thermal flight | E16: short sortie duty cycle | F16: 72 h intervention-energy and refill cell | G16: thermal state forces service interruption | H16: A2 falsification article | I16: HELD FOR TEST
A17: HC-A-T3 | B17: MS-HC | C17: HC-A | D17: causal deposition control | E17: coverage area as effect proxy | F17: one-kilometre controlled deposition section | G17: working fluid crosses protected boundary | H17: A2 falsification article | I17: HELD FOR TEST
... A30: RT-B-T4 | B30: MS-RT | C30: RT-B | D30: robotic disassembly and reconstruction | E30: maintainer craft memory | F30: machine-readable teardown and cold-build chain | G30: outside team misses 168 h requalification | H30: A2 falsification article | I30: HELD FOR TEST

Sheet Sensitivity
A2: Minimum loss-world ratio by adverse screen
A4: The selected architecture closes at 2.5%, but its minimum margins are test targets rather than production growth allowance.
A6: Scenario | B6: Adverse movement | C6: Root | D6: Minimum pre-screen W03 ratio | E6: Lower-bound ratio | F6: Margin | G6: Decision
A7: No screen | B7: 0 | C7: ET-A | D7: 1.0273535 | E7: =D7*(1-B7) -> 1.0273535 | F7: =E7-Controls!$B$8 -> 0.027353464 | G7: =IF(F7>=0,"DESIGN CLOSE","NEGATIVE") -> DESIGN CLOSE
A8: No screen | B8: 0 | C8: CT-C | D8: 1.0285714 | E8: =D8*(1-B8) -> 1.0285714 | F8: =E8-Controls!$B$8 -> 0.028571429 | G8: =IF(F8>=0,"DESIGN CLOSE","NEGATIVE") -> DESIGN CLOSE
A9: No screen | B9: 0 | C9: HC-A | D9: 1.0291262 | E9: =D9*(1-B9) -> 1.0291262 | F9: =E9-Controls!$B$8 -> 0.029126214 | G9: =IF(F9>=0,"DESIGN CLOSE","NEGATIVE") -> DESIGN CLOSE
A10: No screen | B10: 0 | C10: LF-B | D10: 1.0271923 | E10: =D10*(1-B10) -> 1.0271923 | F10: =E10-Controls!$B$8 -> 0.027192277 | G10: =IF(F10>=0,"DESIGN CLOSE","NEGATIVE") -> DESIGN CLOSE
A11: No screen | B11: 0 | C11: HU-A | D11: 1.029 | E11: =D11*(1-B11) -> 1.029 | F11: =E11-Controls!$B$8 -> 0.029 | G11: =IF(F11>=0,"DESIGN CLOSE","NEGATIVE") -> DESIGN CLOSE
A12: No screen | B12: 0 | C12: RT-B | D12: 1.0258065 | E12: =D12*(1-B12) -> 1.0258065 | F12: =E12-Controls!$B$8 -> 0.025806452 | G12: =IF(F12>=0,"DESIGN CLOSE","NEGATIVE") -> DESIGN CLOSE
A13: 1% adverse | B13: 0.01 | C13: ET-A | D13: 1.0273535 | E13: =D13*(1-B13) -> 1.0170799 | F13: =E13-Controls!$B$8 -> 0.017079929 | G13: =IF(F13>=0,"DESIGN CLOSE","NEGATIVE") -> DESIGN CLOSE
A14: 1% adverse | B14: 0.01 | C14: CT-C | D14: 1.0285714 | E14: =D14*(1-B14) -> 1.0182857 | F14: =E14-Controls!$B$8 -> 0.018285714 | G14: =IF(F14>=0,"DESIGN CLOSE","NEGATIVE") -> DESIGN CLOSE
A15: 1% adverse | B15: 0.01 | C15: HC-A | D15: 1.0291262 | E15: =D15*(1-B15) -> 1.018835 | F15: =E15-Controls!$B$8 -> 0.018834951 | G15: =IF(F15>=0,"DESIGN CLOSE","NEGATIVE") -> DESIGN CLOSE
A16: 1% adverse | B16: 0.01 | C16: LF-B | D16: 1.0271923 | E16: =D16*(1-B16) -> 1.0169204 | F16: =E16-Controls!$B$8 -> 0.016920354 | G16: =IF(F16>=0,"DESIGN CLOSE","NEGATIVE") -> DESIGN CLOSE
A17: 1% adverse | B17: 0.01 | C17: HU-A | D17: 1.029 | E17: =D17*(1-B17) -> 1.01871 | F17: =E17-Controls!$B$8 -> 0.01871 | G17: =IF(F17>=0,"DESIGN CLOSE","NEGATIVE") -> DESIGN CLOSE
A18: 1% adverse | B18: 0.01 | C18: RT-B | D18: 1.0258065 | E18: =D18*(1-B18) -> 1.0155484 | F18: =E18-Controls!$B$8 -> 0.015548387 | G18: =IF(F18>=0,"DESIGN CLOSE","NEGATIVE") -> DESIGN CLOSE
... A36: 10% adverse | B36: 0.1 | C36: RT-B | D36: 1.0258065 | E36: =D36*(1-B36) -> 0.92322581 | F36: =E36-Controls!$B$8 -> -0.076774194 | G36: =IF(F36>=0,"DESIGN CLOSE","NEGATIVE") -> NEGATIVE

Sheet Finance
A2: Architecture specification releases no money
A4: The USD 0.538B maximum FRAME envelope is unchanged. A design specification is not an accepted artifact, award, obligation or payment.
A6: System | B6: Root | C6: Article | D6: Option ceiling USD B | E6: FRAME share | F6: Maximum FRAME USD B | G6: Accepted USD B | H6: Paid USD B | I6: State
A7: MS-ET | B7: ET-A | C7: Pelagic exchange cell | D7: 0.50047462 | E7: =Controls!$B$15 -> 0.15 | F7: =D7*E7 -> 0.075071193 | G7: 0 | H7: 0 | I7: HELD
A8: MS-CT | B8: CT-C | C8: Occupied-building utility-spine sector | D8: 0.51649348 | E8: =Controls!$B$15 -> 0.15 | F8: =D8*E8 -> 0.077474022 | G8: 0 | H8: 0 | I8: HELD
A9: MS-HC | B9: HC-A | C9: Atmospheric intervention cell | D9: 0.30722165 | E9: =Controls!$B$15 -> 0.15 | F9: =D9*E9 -> 0.046083248 | G9: 0 | H9: 0 | I9: HELD
A10: MS-LF | B10: LF-B | C10: Geothermal source position | D10: 0.89941282 | E10: =Controls!$B$15 -> 0.15 | F10: =D10*E10 -> 0.13491192 | G10: 0 | H10: 0 | I10: HELD
A11: MS-HU | B11: HU-A | C11: Complete clinical island | D11: 0.86071245 | E11: =Controls!$B$15 -> 0.15 | F11: =D11*E11 -> 0.12910687 | G11: 0 | H11: 0 | I11: HELD
A12: MS-RT | B12: RT-B | C12: Disconnected microfactory mesh | D12: 0.50259779 | E12: =Controls!$B$15 -> 0.15 | F12: =D12*E12 -> 0.075389669 | G12: 0 | H12: 0 | I12: HELD
A13: TOTAL | B13: six roots | C13: internal-section architecture | D13: =SUM(D7:D12) -> 3.5869128 | F13: =SUM(F7:F12) -> 0.53803692 | G13: =SUM(G7:G12) -> 0 | H13: =SUM(H7:H12) -> 0 | I13: HELD

Sheet Release Gates
A2: Seventy-two requirement-to-architecture gates
A4: G06 is specified but not closed. Measurement readiness cannot become evidence, architecture warrant or exterior authority.
A6: Gate | B6: System | C6: Root | D6: Order | E6: Gate claim | F6: State | G6: Authority basis | H6: Requirement constituted | I6: Evidence accepted | J6: Gate closed | K6: Pass 219 effect | L6: Exterior authority
A7: ET-A-G01 | B7: MS-ET | C7: ET-A | D7: 1 | E7: denominator | F7: CONSTITUTED | G7: Pass 216 requirement record | H7: 1 | I7: 0 | J7: 0 | K7: NO CHANGE | L7: n.a.
A8: ET-A-G02 | B8: MS-ET | C8: ET-A | D8: 2 | E8: article boundary | F8: CONSTITUTED | G8: Pass 216 requirement record | H8: 1 | I8: 0 | J8: 0 | K8: NO CHANGE | L8: n.a.
A9: ET-A-G03 | B9: MS-ET | C9: ET-A | D9: 3 | E9: form loads | F9: CONSTITUTED | G9: Pass 216 requirement record | H9: 1 | I9: 0 | J9: 0 | K9: NO CHANGE | L9: n.a.
A10: ET-A-G04 | B10: MS-ET | C10: ET-A | D10: 4 | E10: interfaces | F10: CONSTITUTED | G10: Pass 216 requirement record | H10: 1 | I10: 0 | J10: 0 | K10: NO CHANGE | L10: n.a.
A11: ET-A-G05 | B11: MS-ET | C11: ET-A | D11: 5 | E11: denial set | F11: CONSTITUTED | G11: Pass 216 requirement record | H11: 1 | I11: 0 | J11: 0 | K11: NO CHANGE | L11: n.a.
A12: ET-A-G06 | B12: MS-ET | C12: ET-A | D12: 6 | E12: paper closure | F12: SPECIFIED / NOT CLOSED | G12: 60 design cells close; 84 cells await observations | H12: 0 | I12: 0 | J12: 0 | K12: SECTION FROZEN FOR TEST | L12: n.a.
A13: ET-A-G07 | B13: MS-ET | C13: ET-A | D13: 7 | E13: safety and rights | F13: OPEN | G13: future accepted record | H13: 0 | I13: 0 | J13: 0 | K13: NO CHANGE | L13: n.a.
A14: ET-A-G08 | B14: MS-ET | C14: ET-A | D14: 8 | E14: ancestry | F14: OPEN | G14: future accepted record | H14: 0 | I14: 0 | J14: 0 | K14: NO CHANGE | L14: n.a.
A15: ET-A-G09 | B15: MS-ET | C15: ET-A | D15: 9 | E15: executable build record | F15: OPEN | G15: future accepted record | H15: 0 | I15: 0 | J15: 0 | K15: NO CHANGE | L15: n.a.
A16: ET-A-G10 | B16: MS-ET | C16: ET-A | D16: 10 | E16: representative event | F16: OPEN | G16: future accepted record | H16: 0 | I16: 0 | J16: 0 | K16: NO CHANGE | L16: n.a.
A17: ET-A-G11 | B17: MS-ET | C17: ET-A | D17: 11 | E17: cold reconstruction | F17: OPEN | G17: future accepted record | H17: 0 | I17: 0 | J17: 0 | K17: NO CHANGE | L17: n.a.
A18: ET-A-G12 | B18: MS-ET | C18: ET-A | D18: 12 | E18: architecture warrant | F18: OPEN | G18: future accepted record | H18: 0 | I18: 0 | J18: 0 | K18: NO CHANGE | L18: HELD
... A78: RT-B-G12 | B78: MS-RT | C78: RT-B | D78: 12 | E78: architecture warrant | F78: OPEN | G78: future accepted record | H78: 0 | I78: 0 | J78: 0 | K78: NO CHANGE | L78: HELD

Sheet Mutations
A2: Restored control-mutation register
A4: The verifier applies every edit to a disposable in-memory workbook, recalculates, observes the named boundary and restores the baseline.
A6: Mutation | B6: Counterfactual edit | C6: Expected propagation | D6: Observed boundary | E6: Result
A7: M01 | B7: adverse screen raised to 5% | C7: design-close count falls | D7: Audit | E7: DETECTED
A8: M02 | B8: ET-A flow cell reduced | C8: negative count rises | D8: Audit | E8: DETECTED
A9: M03 | B9: CT-C energy cell reduced | C9: negative count rises | D9: Audit | E9: DETECTED
A10: M04 | B10: HC-A held-line cell reduced | C10: negative count rises | D10: Audit | E10: DETECTED
A11: M05 | B11: LF-B access survivor reduced | C11: negative count rises | D11: Audit | E11: DETECTED
A12: M06 | B12: LF-B energy cell reduced | C12: negative count rises | D12: Audit | E12: DETECTED
A13: M07 | B13: HU-A access cell reduced | C13: negative count rises | D13: Audit | E13: DETECTED
A14: M08 | B14: RT-B energy cell reduced | C14: negative count rises | D14: Audit | E14: DETECTED
A15: M09 | B15: one executable specification removed | C15: specification coverage falls | D15: Audit | E15: DETECTED
A16: M10 | B16: one gap mapping deleted | C16: legacy-gap count falls | D16: Audit | E16: DETECTED
A17: M11 | B17: one host contribution entered | C17: host-zero audit fails | D17: Audit | E17: DETECTED
... A24: M18 | B24: one technology thrust removed | C24: technology count falls | D24: Audit | E24: DETECTED

Sheet Audit
A2: Terminal internal-architecture audits
A4: Audits read the model and do not feed any architecture, finance or release decision.
A6: Audit | B6: Check | C6: Actual | D6: Expected | E6: State
A7: A01 | B7: root count | C7: =COUNTA('Root Architecture'!B7:B12) -> 6 | D7: 6 | E7: =IF(ABS(C7-D7)<0.000001,"PASS","FAIL") -> PASS
A8: A02 | B8: section-account rows | C8: =COUNTA('Section Bills'!C7:C42) -> 36 | D8: 36 | E8: =IF(ABS(C8-D8)<0.000001,"PASS","FAIL") -> PASS
A9: A03 | B9: cell register | C9: =COUNTA('Cell Register'!A7:A150) -> 144 | D9: 144 | E9: =IF(ABS(C9-D9)<0.000001,"PASS","FAIL") -> PASS
A10: A04 | B10: design-close cells | C10: =COUNTIFS('Cell Register'!S7:S150,"DESIGN CLOSE") -> 60 | D10: 60 | E10: =IF(ABS(C10-D10)<0.000001,"PASS","FAIL") -> PASS
A11: A05 | B11: measurement-ready cells | C11: =COUNTIFS('Cell Register'!S7:S150,"MEASUREMENT READY") -> 84 | D11: 84 | E11: =IF(ABS(C11-D11)<0.000001,"PASS","FAIL") -> PASS
A12: A06 | B12: negative cells | C12: =COUNTIFS('Cell Register'!S7:S150,"NEGATIVE") -> 0 | D12: 0 | E12: =IF(ABS(C12-D12)<0.000001,"PASS","FAIL") -> PASS
A13: A07 | B13: unscoped cells | C13: =COUNTIFS('Cell Register'!S7:S150,"UNSCOPED") -> 0 | D13: 0 | E13: =IF(ABS(C13-D13)<0.000001,"PASS","FAIL") -> PASS
A14: A08 | B14: legacy-gap mappings | C14: =COUNTA('Gap Migration'!A7:A91) -> 85 | D14: 85 | E14: =IF(ABS(C14-D14)<0.000001,"PASS","FAIL") -> PASS
A15: A09 | B15: keystone specifications | C15: =COUNTIFS('Gap Migration'!E7:E91,"W02") -> 36 | D15: 36 | E15: =IF(ABS(C15-D15)<0.000001,"PASS","FAIL") -> PASS
A16: A10 | B16: cold-reconstruction specifications | C16: =COUNTIFS('Gap Migration'!E7:E91,"W04") -> 36 | D16: 36 | E16: =IF(ABS(C16-D16)<0.000001,"PASS","FAIL") -> PASS
A17: A11 | B17: rebuild-clock specifications | C17: =COUNTIFS('Gap Migration'!H7:H91,"Rebuild Clocks") -> 12 | D17: 12 | E17: =IF(ABS(C17-D17)<0.000001,"PASS","FAIL") -> PASS
A18: A12 | B18: LF-B access definition | C18: =COUNTIFS('Gap Migration'!A7:A91,"MA-LF-B-A01-W03",'Gap Migration'!K7:K91,1) -> 1 | D18: 1 | E18: =IF(ABS(C18-D18)<0.000001,"PASS","FAIL") -> PASS
A19: A13 | B19: executable specification coverage | C19: =SUM('Gap Migration'!J7:J91) -> 85 | D19: 85 | E19: =IF(ABS(C19-D19)<0.000001,"PASS","FAIL") -> PASS
A20: A14 | B20: design-resolved gaps | C20: =SUM('Gap Migration'!K7:K91) -> 1 | D20: 1 | E20: =IF(ABS(C20-D20)<0.000001,"PASS","FAIL") -> PASS
A21: A15 | B21: gap observations | C21: =SUM('Gap Migration'!L7:L91) -> 0 | D21: 0 | E21: =IF(ABS(C21-D21)<0.000001,"PASS","FAIL") -> PASS
A22: A16 | B22: gap evidence accepted | C22: =SUM('Gap Migration'!M7:M91) -> 0 | D22: 0 | E22: =IF(ABS(C22-D22)<0.000001,"PASS","FAIL") -> PASS
A23: A17 | B23: keystone protocol rows | C23: =COUNTA('Keystone Protocols'!A7:A42) -> 36 | D23: 36 | E23: =IF(ABS(C23-D23)<0.000001,"PASS","FAIL") -> PASS
A24: A18 | B24: rebuild protocol rows | C24: =COUNTA('Rebuild Protocols'!A7:A42) -> 36 | D24: 36 | E24: =IF(ABS(C24-D24)<0.000001,"PASS","FAIL") -> PASS
A25: A19 | B25: rebuild clock rows | C25: =COUNTA('Rebuild Clocks'!A7:A18) -> 12 | D25: 12 | E25: =IF(ABS(C25-D25)<0.000001,"PASS","FAIL") -> PASS
A26: A20 | B26: isolation boundaries | C26: =COUNTA('Isolation Map'!A7:A42) -> 36 | D26: 36 | E26: =IF(ABS(C26-D26)<0.000001,"PASS","FAIL") -> PASS
A27: A21 | B27: frozen isolation boundaries | C27: =COUNTIFS('Isolation Map'!I7:I42,"FROZEN") -> 36 | D27: 36 | E27: =IF(ABS(C27-D27)<0.000001,"PASS","FAIL") -> PASS
A28: A22 | B28: technology thrusts | C28: =COUNTA('Technology Thrusts'!A7:A30) -> 24 | D28: 24 | E28: =IF(ABS(C28-D28)<0.000001,"PASS","FAIL") -> PASS
A29: A23 | B29: release gates | C29: =COUNTA('Release Gates'!A7:A78) -> 72 | D29: 72 | E29: =IF(ABS(C29-D29)<0.000001,"PASS","FAIL") -> PASS
A30: A24 | B30: G06 closures | C30: =SUM('Root Architecture'!J7:J12) -> 0 | D30: 0 | E30: =IF(ABS(C30-D30)<0.000001,"PASS","FAIL") -> PASS
A31: A25 | B31: roots fully specified | C31: =SUM('Root Architecture'!H7:H12) -> 6 | D31: 6 | E31: =IF(ABS(C31-D31)<0.000001,"PASS","FAIL") -> PASS
A32: A26 | B32: roots frozen for test | C32: =COUNTIFS('Root Architecture'!K7:K12,"SECTION FROZEN / EVIDENCE HOLD") -> 6 | D32: 6 | E32: =IF(ABS(C32-D32)<0.000001,"PASS","FAIL") -> PASS
A33: A27 | B33: selected margins nonnegative | C33: =COUNTIFS('Root Architecture'!I7:I12,">=0") -> 6 | D33: 6 | E33: =IF(ABS(C33-D33)<0.000001,"PASS","FAIL") -> PASS
A34: A28 | B34: cell-state reconciliation | C34: =COUNTIFS('Cell Register'!S7:S150,"DESIGN CLOSE")+COUNTIFS('Cell Register'!S7:S150,"MEASUREMENT READY")+COUNTIFS('Cell Register'!S7:S150,"NEGATIVE")+COUNTIFS('Cell Register'!S7:S150,"UNSCOPED") -> 144 | D34: 144 | E34: =IF(ABS(C34-D34)<0.000001,"PASS","FAIL") -> PASS
A35: A29 | B35: numeric W01 cells | C35: =COUNTIFS('Cell Register'!F7:F150,"W01",'Cell Register'!S7:S150,"DESIGN CLOSE") -> 30 | D35: 30 | E35: =IF(ABS(C35-D35)<0.000001,"PASS","FAIL") -> PASS
A36: A30 | B36: numeric W03 cells | C36: =COUNTIFS('Cell Register'!F7:F150,"W03",'Cell Register'!S7:S150,"DESIGN CLOSE") -> 30 | D36: 30 | E36: =IF(ABS(C36-D36)<0.000001,"PASS","FAIL") -> PASS
A37: A31 | B37: measurement W02 cells | C37: =COUNTIFS('Cell Register'!F7:F150,"W02",'Cell Register'!S7:S150,"MEASUREMENT READY") -> 36 | D37: 36 | E37: =IF(ABS(C37-D37)<0.000001,"PASS","FAIL") -> PASS
A38: A32 | B38: measurement W04 cells | C38: =COUNTIFS('Cell Register'!F7:F150,"W04",'Cell Register'!S7:S150,"MEASUREMENT READY") -> 36 | D38: 36 | E38: =IF(ABS(C38-D38)<0.000001,"PASS","FAIL") -> PASS
A39: A33 | B39: A06 W01 and W03 measurements | C39: =COUNTIFS('Cell Register'!D7:D150,"A06",'Cell Register'!F7:F150,"W01",'Cell Register'!S7:S150,"MEASUREMENT READY")+COUNTIFS('Cell Register'!D7:D150,"A06",'Cell Register'!F7:F150,"W03",'Cell Register'!S7:S150,"MEASUREMENT READY") -> 12 | D39: 12 | E39: =IF(ABS(C39-D39)<0.000001,"PASS","FAIL") -> PASS
A40: A34 | B40: host contribution zero | C40: =SUM('Cell Register'!U7:U150) -> 0 | D40: 0 | E40: =IF(ABS(C40-D40)<0.000001,"PASS","FAIL") -> PASS
A41: A35 | B41: cell evidence accepted zero | C41: =SUM('Cell Register'!Q7:Q150) -> 0 | D41: 0 | E41: =IF(ABS(C41-D41)<0.000001,"PASS","FAIL") -> PASS
A42: A36 | B42: option ceiling conserved | C42: =Finance!D13 -> 3.5869128 | D42: 3.5869128 | E42: =IF(ABS(C42-D42)<0.000001,"PASS","FAIL") -> PASS
A43: A37 | B43: FRAME ceiling conserved | C43: =Finance!F13 -> 0.53803692 | D43: 0.53803692 | E43: =IF(ABS(C43-D43)<0.000001,"PASS","FAIL") -> PASS
A44: A38 | B44: accepted authority zero | C44: =Finance!G13 -> 0 | D44: 0 | E44: =IF(ABS(C44-D44)<0.000001,"PASS","FAIL") -> PASS
A45: A39 | B45: paid authority zero | C45: =Finance!H13 -> 0 | D45: 0 | E45: =IF(ABS(C45-D45)<0.000001,"PASS","FAIL") -> PASS
A46: A40 | B46: capability credit zero | C46: =Controls!B20 -> 0 | D46: 0 | E46: =IF(ABS(C46-D46)<0.000001,"PASS","FAIL") -> PASS
A47: A41 | B47: production credit zero | C47: =Controls!B21 -> 0 | D47: 0 | E47: =IF(ABS(C47-D47)<0.000001,"PASS","FAIL") -> PASS
A48: A42 | B48: rendering authority zero | C48: =Controls!B22 -> 0 | D48: 0 | E48: =IF(ABS(C48-D48)<0.000001,"PASS","FAIL") -> PASS
A49: A43 | B49: mutation records | C49: =COUNTA(Mutations!A7:A24) -> 18 | D49: 18 | E49: =IF(ABS(C49-D49)<0.000001,"PASS","FAIL") -> PASS

Sheet Sources & Limits
A2: Internal sources and decision limits
A4: Every quantitative claim is inherited from repository authority or identified as a new controlled design hypothesis.
A6: ID | B6: Source or limit | C6: Repository path or statement | D6: Use
A7: S01 | B7: Pass 218 quantitative triage | C7: research/force/generation/department-of-resilience-six-root-quantitative-causal-section-triage-and-resize-constitution.md | D7: eleven resize orders, 85 gaps and hold dispositions
A8: S02 | B8: Pass 217 causal-section closure | C8: research/force/generation/department-of-resilience-concurrent-six-root-causal-section-closure-constitution.md | D8: six accounts, four worlds, 144-cell grammar and no-host rule
A9: S03 | B9: Pass 216 candidate-article requirements | C9: research/force/generation/department-of-resilience-six-root-form-giving-candidate-article-requirement-constitution.md | D9: article boundaries, fatal results and technology campaigns
A10: S04 | B10: Pass 182 non-lifeline physical balances | C10: models/force/generation/department-of-resilience-twenty-non-lifeline-root-first-principles-physical-balance-constitution.xlsx | D10: five non-lifeline root capacities and 2.5% screen
A11: S05 | B11: Pass 183 lifeline configurations | C11: models/force/generation/department-of-resilience-lifeline-four-root-physical-configuration-and-g3-entry-constitution.xlsx | D11: LF-B source position, service requirements and article bill
A12: S06 | B12: Pass 215 construction compact | C12: research/force/generation/department-of-resilience-national-first-sentinel-construction-compact-and-return.md | D12: option and FRAME ceilings and release nonconversions
A15: ID | B15: Limit | C15: Meaning | D15: Effect
A16: L01 | B16: No external sites | C16: Repository-only analytical pass by instruction | D16: No claim depends on current external evidence
A17: L02 | B17: No observed performance | C17: All capacities remain controlled hypotheses or direct arithmetic | D17: Every measurement field remains empty
A18: L03 | B18: Specification is not evidence | C18: Eighty-four measurement-ready cells remain source empty | D18: G06 remains zero
A19: L04 | B19: No shared technical core | C19: Only semantic seams may be common across roots | D19: Each root retains its own implementation
... A21: L06 | B21: No release | C21: Awards, obligations, payments, capability, production and rendering remain zero | D21: The option and FRAME values remain ceilings
