Workbook

Sheet Summary
A2: Cohort-one numerical interval solvency
A4: Pass 237 closes the numerical question negatively: all six forms require redesign and bounded physical coefficients.
A6: Decision | B6: Decision | C6: Decision | D6: Decision | E6: Decision | F6: Decision | M6: Form | N6: Current maximum interval | O6: Required interval
M7: ET-A-A | N7: ='Form Results'!E7 -> 0.013492203 | O7: =Inputs!$B$7 -> 0.025
A8: Method | B8: NIS-1 | C8: Lower capacity must meet upper requirement under source-specific intervals | M8: CT-C-B | N8: ='Form Results'!E8 -> 0.014084507 | O8: =Inputs!$B$7 -> 0.025
A9: Selected two-sided screen | B9: =Inputs!B7 -> 0.025 | C9: 2.5% capacity downside and 2.5% requirement upside | M9: HC-A-C | N9: ='Form Results'!E9 -> 0.014354067 | O9: =Inputs!$B$7 -> 0.025
A10: Required raw capacity ratio | B10: =Inputs!B10 -> 1.0512821 | C10: direct arithmetic | M10: LF-B-A | N10: ='Form Results'!E10 -> 0.013413763 | O10: =Inputs!$B$7 -> 0.025
A11: Forms closing all worlds | B11: =COUNTIF('Form Results'!$K$7:$K$12,"CLOSE") -> 0 | C11: none | M11: HU-A-B | N11: ='Form Results'!E11 -> 0.014292755 | O11: =Inputs!$B$7 -> 0.025
A12: Largest-loss accounts | B12: =COUNTIFS('Closure Cells'!$D$7:$D$126,"LARGEST_CELL_LOSS",'Closure Cells'!$O$7:$O$126,"CLOSE")&" close / "&COUNTIFS('Closure Cells'!$D$7:$D$126,"LARGEST_CELL_LOSS",'Closure Cells'!$O$7:$O$126,"FAIL")&" fail" -> 3 close / 21 fail | C12: twenty-one rating orders | M12: RT-B-C | N12: ='Form Results'!E12 -> 0.012738854 | O12: =Inputs!$B$7 -> 0.025
A13: Unbounded cells | B13: 72 | C13: fatal-keystone, cold-start and thermal states
A16: Portfolio consequence | B16: Portfolio consequence | C16: Portfolio consequence | D16: Portfolio consequence | E16: Portfolio consequence | F16: Portfolio consequence
A18: ET-A-A | B18: Service | C18: 247 t/h exchange path | D18: thermal duty and keystone retention still open
A19: CT-C-B | B19: Energy | C19: 7.36 MW isolated cell | D19: occupied-zone heat and anchor propagation still open
A20: HC-A-C | B20: Service | C20: 27.1 km/day held-line sector | D20: hot-zone duty and local-control loss still open
A21: LF-B-A | B21: Mass | C21: 4.08 kt access slot | D21: reservoir enthalpy and brine closure still open
A22: HU-A-B | B22: Mass | C22: 7.51 kt access cell | D22: clinical thermal continuity and bypass loss still open
A23: RT-B-C | B23: Energy | C23: 27.2 MW process cell | D23: process heat and trainlet isolation still open
A26: Authority boundary | B26: Authority boundary | C26: Authority boundary | D26: Authority boundary | E26: Authority boundary | F26: Authority boundary
A28: Measured coefficients | B28: 0 | C28: all thirty-six remain open
A29: Accepted baselines | B29: 0 | C29: design arithmetic is not evidence
A30: New obligation | B30: 0 | C30: USD179M obligation and USD359M reserve remain conserved
A31: Rendering authority | B31: 0 | C31: geometry, structure and safe-state closure remain next

Sheet Decision Tests
A2: Numerical closure method
A4: The selected method must expose both sides of the interval and preserve source-specific unknowns.
A6: Candidate | B6: Method | C6: Two-sided interval | D6: Root-specific | E6: No midpoint | F6: Missing holds | G6: Four worlds | H6: Five accounts | I6: Sensitivity | J6: No authority conversion | K6: Passed | L6: Disposition
A7: C1 | B7: Inherited one-sided 2.5% capacity screen | C7: 0 | D7: 1 | E7: 1 | F7: 1 | G7: 0 | H7: 0 | I7: 1 | J7: 1 | K7: =SUM(C7:J7) -> 5 | L7: =IF(K7=8,"SELECT","REJECT") -> REJECT
A8: C2 | B8: Common 5% gross reserve | C8: 1 | D8: 0 | E8: 1 | F8: 1 | G8: 0 | H8: 1 | I8: 1 | J8: 1 | K8: =SUM(C8:J8) -> 6 | L8: =IF(K8=8,"SELECT","REJECT") -> REJECT
A9: C3 | B9: Midpoint model with assigned priors | C9: 1 | D9: 1 | E9: 0 | F9: 0 | G9: 1 | H9: 1 | I9: 1 | J9: 1 | K9: =SUM(C9:J9) -> 6 | L9: =IF(K9=8,"SELECT","REJECT") -> REJECT
A10: C4 | B10: Unbounded worst case as automatic rejection | C10: 1 | D10: 1 | E10: 1 | F10: 0 | G10: 1 | H10: 1 | I10: 0 | J10: 1 | K10: =SUM(C10:J10) -> 6 | L10: =IF(K10=8,"SELECT","REJECT") -> REJECT
A11: C5 | B11: Source-specific interval budgets plus 2.5/2.5 design rule | C11: 1 | D11: 1 | E11: 1 | F11: 1 | G11: 1 | H11: 1 | I11: 1 | J11: 1 | K11: =SUM(C11:J11) -> 8 | L11: =IF(K11=8,"SELECT","REJECT") -> SELECT
A14: Authoritative decision | B14: Authoritative decision | C14: Authoritative decision | D14: Authoritative decision | E14: Authoritative decision | F14: Authoritative decision | G14: Authoritative decision | H14: Authoritative decision | I14: Authoritative decision | J14: Authoritative decision | K14: Authoritative decision | L14: Authoritative decision
A16: Decision | B16: NIS-1 | C16: Adopt two-sided interval solvency and issue twenty-one account uprates across all six forms
A17: Negative result | B17: 0 of 6 | C17: No form closes all five accounts in all four worlds
A18: Superseded claim | B18: Pass 219 | C18: One-sided 2.5% design close is no longer sufficient numerical closure
A19: Present authority | B19: DESIGN REDESIGN / TEST | C19: No evidence, selection, MAKE, REP-4, production or rendering authority

Sheet Form Results
A2: Cohort-one numerical disposition
A4: No form closes. All six need rating changes and bounded fatal, cold-start and thermal coefficients.
A6: Form | B6: Root | C6: Governing account | D6: Minimum loss ratio | E6: Maximum symmetric half-width | F6: Nominal accounts closed | G6: Loss accounts closed | H6: Loss accounts failed | I6: Unbounded cells | J6: Open coefficients | K6: Baseline disposition | L6: Governing redesign
A7: ET-A-A | B7: ET-A | C7: Service | D7: =MIN('Loss Rating Orders'!$G$7:$G$10) -> 1.0273535 | E7: =MIN('Loss Rating Orders'!$H$7:$H$10) -> 0.013492203 | F7: =COUNTIFS('Closure Cells'!$B$7:$B$126,A7,'Closure Cells'!$D$7:$D$126,"NOMINAL",'Closure Cells'!$O$7:$O$126,"CLOSE") -> 4 | G7: =COUNTIFS('Closure Cells'!$B$7:$B$126,A7,'Closure Cells'!$D$7:$D$126,"LARGEST_CELL_LOSS",'Closure Cells'!$O$7:$O$126,"CLOSE") -> 1 | H7: =COUNTIFS('Closure Cells'!$B$7:$B$126,A7,'Closure Cells'!$D$7:$D$126,"LARGEST_CELL_LOSS",'Closure Cells'!$O$7:$O$126,"FAIL") -> 3 | I7: =COUNTIFS('Closure Cells'!$B$7:$B$126,A7,'Closure Cells'!$O$7:$O$126,"HOLD") -> 12 | J7: =COUNTIFS('Coefficient Register'!$B$7:$B$42,A7,'Coefficient Register'!$K$7:$K$42,"OPEN") -> 6 | K7: =IF(AND(F7=4,G7=4,H7=0,I7=0,J7=0),"CLOSE","REDESIGN / HOLD") -> REDESIGN / HOLD | L7: Raise each complete exchange path from 241 to at least 247 t/h before thermal and keystone closure.
A8: CT-C-B | B8: CT-C | C8: Energy | D8: =MIN('Loss Rating Orders'!$G$11:$G$14) -> 1.0285714 | E8: =MIN('Loss Rating Orders'!$H$11:$H$14) -> 0.014084507 | F8: =COUNTIFS('Closure Cells'!$B$7:$B$126,A8,'Closure Cells'!$D$7:$D$126,"NOMINAL",'Closure Cells'!$O$7:$O$126,"CLOSE") -> 4 | G8: =COUNTIFS('Closure Cells'!$B$7:$B$126,A8,'Closure Cells'!$D$7:$D$126,"LARGEST_CELL_LOSS",'Closure Cells'!$O$7:$O$126,"CLOSE") -> 1 | H8: =COUNTIFS('Closure Cells'!$B$7:$B$126,A8,'Closure Cells'!$D$7:$D$126,"LARGEST_CELL_LOSS",'Closure Cells'!$O$7:$O$126,"FAIL") -> 3 | I8: =COUNTIFS('Closure Cells'!$B$7:$B$126,A8,'Closure Cells'!$O$7:$O$126,"HOLD") -> 12 | J8: =COUNTIFS('Coefficient Register'!$B$7:$B$42,A8,'Coefficient Register'!$K$7:$K$42,"OPEN") -> 6 | K8: =IF(AND(F8=4,G8=4,H8=0,I8=0,J8=0),"CLOSE","REDESIGN / HOLD") -> REDESIGN / HOLD | L8: Raise each isolated generation cell from 7.20 to at least 7.36 MW before thermal and attachment closure.
A9: HC-A-C | B9: HC-A | C9: Service | D9: =MIN('Loss Rating Orders'!$G$15:$G$18) -> 1.0291262 | E9: =MIN('Loss Rating Orders'!$H$15:$H$18) -> 0.014354067 | F9: =COUNTIFS('Closure Cells'!$B$7:$B$126,A9,'Closure Cells'!$D$7:$D$126,"NOMINAL",'Closure Cells'!$O$7:$O$126,"CLOSE") -> 4 | G9: =COUNTIFS('Closure Cells'!$B$7:$B$126,A9,'Closure Cells'!$D$7:$D$126,"LARGEST_CELL_LOSS",'Closure Cells'!$O$7:$O$126,"CLOSE") -> 0 | H9: =COUNTIFS('Closure Cells'!$B$7:$B$126,A9,'Closure Cells'!$D$7:$D$126,"LARGEST_CELL_LOSS",'Closure Cells'!$O$7:$O$126,"FAIL") -> 4 | I9: =COUNTIFS('Closure Cells'!$B$7:$B$126,A9,'Closure Cells'!$O$7:$O$126,"HOLD") -> 12 | J9: =COUNTIFS('Coefficient Register'!$B$7:$B$42,A9,'Coefficient Register'!$K$7:$K$42,"OPEN") -> 6 | K9: =IF(AND(F9=4,G9=4,H9=0,I9=0,J9=0),"CLOSE","REDESIGN / HOLD") -> REDESIGN / HOLD | L9: Raise each surviving held-line sector from 26.5 to at least 27.1 km/day before hot-zone closure.
A10: LF-B-A | B10: LF-B | C10: Mass | D10: =MIN('Loss Rating Orders'!$G$19:$G$22) -> 1.0271923 | E10: =MIN('Loss Rating Orders'!$H$19:$H$22) -> 0.013413763 | F10: =COUNTIFS('Closure Cells'!$B$7:$B$126,A10,'Closure Cells'!$D$7:$D$126,"NOMINAL",'Closure Cells'!$O$7:$O$126,"CLOSE") -> 4 | G10: =COUNTIFS('Closure Cells'!$B$7:$B$126,A10,'Closure Cells'!$D$7:$D$126,"LARGEST_CELL_LOSS",'Closure Cells'!$O$7:$O$126,"CLOSE") -> 0 | H10: =COUNTIFS('Closure Cells'!$B$7:$B$126,A10,'Closure Cells'!$D$7:$D$126,"LARGEST_CELL_LOSS",'Closure Cells'!$O$7:$O$126,"FAIL") -> 4 | I10: =COUNTIFS('Closure Cells'!$B$7:$B$126,A10,'Closure Cells'!$O$7:$O$126,"HOLD") -> 12 | J10: =COUNTIFS('Coefficient Register'!$B$7:$B$42,A10,'Coefficient Register'!$K$7:$K$42,"OPEN") -> 6 | K10: =IF(AND(F10=4,G10=4,H10=0,I10=0,J10=0),"CLOSE","REDESIGN / HOLD") -> REDESIGN / HOLD | L10: Raise each access-slot allowance from 3.99 to at least 4.08 kt before reservoir and brine closure.
A11: HU-A-B | B11: HU-A | C11: Mass | D11: =MIN('Loss Rating Orders'!$G$23:$G$26) -> 1.029 | E11: =MIN('Loss Rating Orders'!$H$23:$H$26) -> 0.014292755 | F11: =COUNTIFS('Closure Cells'!$B$7:$B$126,A11,'Closure Cells'!$D$7:$D$126,"NOMINAL",'Closure Cells'!$O$7:$O$126,"CLOSE") -> 4 | G11: =COUNTIFS('Closure Cells'!$B$7:$B$126,A11,'Closure Cells'!$D$7:$D$126,"LARGEST_CELL_LOSS",'Closure Cells'!$O$7:$O$126,"CLOSE") -> 1 | H11: =COUNTIFS('Closure Cells'!$B$7:$B$126,A11,'Closure Cells'!$D$7:$D$126,"LARGEST_CELL_LOSS",'Closure Cells'!$O$7:$O$126,"FAIL") -> 3 | I11: =COUNTIFS('Closure Cells'!$B$7:$B$126,A11,'Closure Cells'!$O$7:$O$126,"HOLD") -> 12 | J11: =COUNTIFS('Coefficient Register'!$B$7:$B$42,A11,'Coefficient Register'!$K$7:$K$42,"OPEN") -> 6 | K11: =IF(AND(F11=4,G11=4,H11=0,I11=0,J11=0),"CLOSE","REDESIGN / HOLD") -> REDESIGN / HOLD | L11: Raise each access-cell allowance from 7.35 to at least 7.51 kt without deleting a care line.
A12: RT-B-C | B12: RT-B | C12: Energy | D12: =MIN('Loss Rating Orders'!$G$27:$G$30) -> 1.0258065 | E12: =MIN('Loss Rating Orders'!$H$27:$H$30) -> 0.012738854 | F12: =COUNTIFS('Closure Cells'!$B$7:$B$126,A12,'Closure Cells'!$D$7:$D$126,"NOMINAL",'Closure Cells'!$O$7:$O$126,"CLOSE") -> 4 | G12: =COUNTIFS('Closure Cells'!$B$7:$B$126,A12,'Closure Cells'!$D$7:$D$126,"LARGEST_CELL_LOSS",'Closure Cells'!$O$7:$O$126,"CLOSE") -> 0 | H12: =COUNTIFS('Closure Cells'!$B$7:$B$126,A12,'Closure Cells'!$D$7:$D$126,"LARGEST_CELL_LOSS",'Closure Cells'!$O$7:$O$126,"FAIL") -> 4 | I12: =COUNTIFS('Closure Cells'!$B$7:$B$126,A12,'Closure Cells'!$O$7:$O$126,"HOLD") -> 12 | J12: =COUNTIFS('Coefficient Register'!$B$7:$B$42,A12,'Coefficient Register'!$K$7:$K$42,"OPEN") -> 6 | K12: =IF(AND(F12=4,G12=4,H12=0,I12=0,J12=0),"CLOSE","REDESIGN / HOLD") -> REDESIGN / HOLD | L12: Raise each isolated process-energy cell from 26.5 to at least 27.2 MW before process-heat closure.

Sheet Closure Cells
A2: Physical account interval closure
A4: A cell closes only when lower capacity meets upper requirement. Missing bounds order HOLD, never zero or midpoint substitution.
A6: Cell | B6: Form | C6: Account | D6: World | E6: Unit | F6: Raw capacity | G6: Capacity downside | H6: Raw requirement | I6: Requirement upside | J6: Lower capacity | K6: Upper requirement | L6: Interval ratio | M6: Maximum symmetric half-width | N6: Data state | O6: Disposition
A7: ET-A-A-SERVICE-NOMINAL | B7: ET-A-A | C7: Service | D7: NOMINAL | E7: t/h | F7: ='Source Inputs'!H7 -> 482 | G7: =Inputs!$B$7 -> 0.025 | H7: ='Source Inputs'!I7 -> 234.58333 | I7: =Inputs!$B$8 -> 0.025 | J7: =IF(ISNUMBER(F7),F7*(1-G7),"") -> 469.95 | K7: =IF(ISNUMBER(H7),H7*(1+I7),"") -> 240.44792 | L7: =IF(AND(ISNUMBER(J7),ISNUMBER(K7),K7>0),J7/K7,"") -> 1.9544773 | M7: =IF(AND(ISNUMBER(F7),ISNUMBER(H7),H7>0),(F7/H7-1)/(F7/H7+1),"") -> 0.34527271 | N7: =IF(AND(ISNUMBER(F7),ISNUMBER(H7)) ,"BOUNDED","UNBOUNDED") -> BOUNDED | O7: =IF(N7="UNBOUNDED","HOLD",IF(L7>=Inputs!$B$9,"CLOSE","FAIL")) -> CLOSE
A8: ET-A-A-SERVICE-LARGEST_CELL_LOSS | B8: ET-A-A | C8: Service | D8: LARGEST_CELL_LOSS | E8: t/h | F8: ='Source Inputs'!J7 -> 241 | G8: =Inputs!$B$7 -> 0.025 | H8: ='Source Inputs'!K7 -> 234.58333 | I8: =Inputs!$B$8 -> 0.025 | J8: =IF(ISNUMBER(F8),F8*(1-G8),"") -> 234.975 | K8: =IF(ISNUMBER(H8),H8*(1+I8),"") -> 240.44792 | L8: =IF(AND(ISNUMBER(J8),ISNUMBER(K8),K8>0),J8/K8,"") -> 0.97723866 | M8: =IF(AND(ISNUMBER(F8),ISNUMBER(H8),H8>0),(F8/H8-1)/(F8/H8+1),"") -> 0.013492203 | N8: =IF(AND(ISNUMBER(F8),ISNUMBER(H8)) ,"BOUNDED","UNBOUNDED") -> BOUNDED | O8: =IF(N8="UNBOUNDED","HOLD",IF(L8>=Inputs!$B$9,"CLOSE","FAIL")) -> FAIL
A9: ET-A-A-SERVICE-FATAL_KEYSTONE | B9: ET-A-A | C9: Service | D9: FATAL_KEYSTONE | E9: t/h | G9: =Inputs!$B$7 -> 0.025 | H9: ='Source Inputs'!I7 -> 234.58333 | I9: =Inputs!$B$8 -> 0.025 | J9: =IF(ISNUMBER(F9),F9*(1-G9),"") | K9: =IF(ISNUMBER(H9),H9*(1+I9),"") -> 240.44792 | L9: =IF(AND(ISNUMBER(J9),ISNUMBER(K9),K9>0),J9/K9,"") | M9: =IF(AND(ISNUMBER(F9),ISNUMBER(H9),H9>0),(F9/H9-1)/(F9/H9+1),"") | N9: =IF(AND(ISNUMBER(F9),ISNUMBER(H9)) ,"BOUNDED","UNBOUNDED") -> UNBOUNDED | O9: =IF(N9="UNBOUNDED","HOLD",IF(L9>=Inputs!$B$9,"CLOSE","FAIL")) -> HOLD
A10: ET-A-A-SERVICE-COLD_START | B10: ET-A-A | C10: Service | D10: COLD_START | E10: t/h | G10: =Inputs!$B$7 -> 0.025 | H10: ='Source Inputs'!I7 -> 234.58333 | I10: =Inputs!$B$8 -> 0.025 | J10: =IF(ISNUMBER(F10),F10*(1-G10),"") | K10: =IF(ISNUMBER(H10),H10*(1+I10),"") -> 240.44792 | L10: =IF(AND(ISNUMBER(J10),ISNUMBER(K10),K10>0),J10/K10,"") | M10: =IF(AND(ISNUMBER(F10),ISNUMBER(H10),H10>0),(F10/H10-1)/(F10/H10+1),"") | N10: =IF(AND(ISNUMBER(F10),ISNUMBER(H10)) ,"BOUNDED","UNBOUNDED") -> UNBOUNDED | O10: =IF(N10="UNBOUNDED","HOLD",IF(L10>=Inputs!$B$9,"CLOSE","FAIL")) -> HOLD
A11: ET-A-A-MASS-NOMINAL | B11: ET-A-A | C11: Mass | D11: NOMINAL | E11: t | F11: ='Source Inputs'!H8 -> 128000 | G11: =Inputs!$B$7 -> 0.025 | H11: ='Source Inputs'!I8 -> 102000 | I11: =Inputs!$B$8 -> 0.025 | J11: =IF(ISNUMBER(F11),F11*(1-G11),"") -> 124800 | K11: =IF(ISNUMBER(H11),H11*(1+I11),"") -> 104550 | L11: =IF(AND(ISNUMBER(J11),ISNUMBER(K11),K11>0),J11/K11,"") -> 1.1936872 | M11: =IF(AND(ISNUMBER(F11),ISNUMBER(H11),H11>0),(F11/H11-1)/(F11/H11+1),"") -> 0.11304348 | N11: =IF(AND(ISNUMBER(F11),ISNUMBER(H11)) ,"BOUNDED","UNBOUNDED") -> BOUNDED | O11: =IF(N11="UNBOUNDED","HOLD",IF(L11>=Inputs!$B$9,"CLOSE","FAIL")) -> CLOSE
A12: ET-A-A-MASS-LARGEST_CELL_LOSS | B12: ET-A-A | C12: Mass | D12: LARGEST_CELL_LOSS | E12: t | F12: ='Source Inputs'!J8 -> 112000 | G12: =Inputs!$B$7 -> 0.025 | H12: ='Source Inputs'!K8 -> 102000 | I12: =Inputs!$B$8 -> 0.025 | J12: =IF(ISNUMBER(F12),F12*(1-G12),"") -> 109200 | K12: =IF(ISNUMBER(H12),H12*(1+I12),"") -> 104550 | L12: =IF(AND(ISNUMBER(J12),ISNUMBER(K12),K12>0),J12/K12,"") -> 1.0444763 | M12: =IF(AND(ISNUMBER(F12),ISNUMBER(H12),H12>0),(F12/H12-1)/(F12/H12+1),"") -> 0.046728972 | N12: =IF(AND(ISNUMBER(F12),ISNUMBER(H12)) ,"BOUNDED","UNBOUNDED") -> BOUNDED | O12: =IF(N12="UNBOUNDED","HOLD",IF(L12>=Inputs!$B$9,"CLOSE","FAIL")) -> CLOSE
A13: ET-A-A-MASS-FATAL_KEYSTONE | B13: ET-A-A | C13: Mass | D13: FATAL_KEYSTONE | E13: t | G13: =Inputs!$B$7 -> 0.025 | H13: ='Source Inputs'!I8 -> 102000 | I13: =Inputs!$B$8 -> 0.025 | J13: =IF(ISNUMBER(F13),F13*(1-G13),"") | K13: =IF(ISNUMBER(H13),H13*(1+I13),"") -> 104550 | L13: =IF(AND(ISNUMBER(J13),ISNUMBER(K13),K13>0),J13/K13,"") | M13: =IF(AND(ISNUMBER(F13),ISNUMBER(H13),H13>0),(F13/H13-1)/(F13/H13+1),"") | N13: =IF(AND(ISNUMBER(F13),ISNUMBER(H13)) ,"BOUNDED","UNBOUNDED") -> UNBOUNDED | O13: =IF(N13="UNBOUNDED","HOLD",IF(L13>=Inputs!$B$9,"CLOSE","FAIL")) -> HOLD
A14: ET-A-A-MASS-COLD_START | B14: ET-A-A | C14: Mass | D14: COLD_START | E14: t | G14: =Inputs!$B$7 -> 0.025 | H14: ='Source Inputs'!I8 -> 102000 | I14: =Inputs!$B$8 -> 0.025 | J14: =IF(ISNUMBER(F14),F14*(1-G14),"") | K14: =IF(ISNUMBER(H14),H14*(1+I14),"") -> 104550 | L14: =IF(AND(ISNUMBER(J14),ISNUMBER(K14),K14>0),J14/K14,"") | M14: =IF(AND(ISNUMBER(F14),ISNUMBER(H14),H14>0),(F14/H14-1)/(F14/H14+1),"") | N14: =IF(AND(ISNUMBER(F14),ISNUMBER(H14)) ,"BOUNDED","UNBOUNDED") -> UNBOUNDED | O14: =IF(N14="UNBOUNDED","HOLD",IF(L14>=Inputs!$B$9,"CLOSE","FAIL")) -> HOLD
A15: ET-A-A-ENERGY-NOMINAL | B15: ET-A-A | C15: Energy | D15: NOMINAL | E15: MW | F15: ='Source Inputs'!H9 -> 120 | G15: =Inputs!$B$7 -> 0.025 | H15: ='Source Inputs'!I9 -> 96 | I15: =Inputs!$B$8 -> 0.025 | J15: =IF(ISNUMBER(F15),F15*(1-G15),"") -> 117 | K15: =IF(ISNUMBER(H15),H15*(1+I15),"") -> 98.4 | L15: =IF(AND(ISNUMBER(J15),ISNUMBER(K15),K15>0),J15/K15,"") -> 1.1890244 | M15: =IF(AND(ISNUMBER(F15),ISNUMBER(H15),H15>0),(F15/H15-1)/(F15/H15+1),"") -> 0.11111111 | N15: =IF(AND(ISNUMBER(F15),ISNUMBER(H15)) ,"BOUNDED","UNBOUNDED") -> BOUNDED | O15: =IF(N15="UNBOUNDED","HOLD",IF(L15>=Inputs!$B$9,"CLOSE","FAIL")) -> CLOSE
A16: ET-A-A-ENERGY-LARGEST_CELL_LOSS | B16: ET-A-A | C16: Energy | D16: LARGEST_CELL_LOSS | E16: MW | F16: ='Source Inputs'!J9 -> 100 | G16: =Inputs!$B$7 -> 0.025 | H16: ='Source Inputs'!K9 -> 96 | I16: =Inputs!$B$8 -> 0.025 | J16: =IF(ISNUMBER(F16),F16*(1-G16),"") -> 97.5 | K16: =IF(ISNUMBER(H16),H16*(1+I16),"") -> 98.4 | L16: =IF(AND(ISNUMBER(J16),ISNUMBER(K16),K16>0),J16/K16,"") -> 0.99085366 | M16: =IF(AND(ISNUMBER(F16),ISNUMBER(H16),H16>0),(F16/H16-1)/(F16/H16+1),"") -> 0.020408163 | N16: =IF(AND(ISNUMBER(F16),ISNUMBER(H16)) ,"BOUNDED","UNBOUNDED") -> BOUNDED | O16: =IF(N16="UNBOUNDED","HOLD",IF(L16>=Inputs!$B$9,"CLOSE","FAIL")) -> FAIL
A17: ET-A-A-ENERGY-FATAL_KEYSTONE | B17: ET-A-A | C17: Energy | D17: FATAL_KEYSTONE | E17: MW | G17: =Inputs!$B$7 -> 0.025 | H17: ='Source Inputs'!I9 -> 96 | I17: =Inputs!$B$8 -> 0.025 | J17: =IF(ISNUMBER(F17),F17*(1-G17),"") | K17: =IF(ISNUMBER(H17),H17*(1+I17),"") -> 98.4 | L17: =IF(AND(ISNUMBER(J17),ISNUMBER(K17),K17>0),J17/K17,"") | M17: =IF(AND(ISNUMBER(F17),ISNUMBER(H17),H17>0),(F17/H17-1)/(F17/H17+1),"") | N17: =IF(AND(ISNUMBER(F17),ISNUMBER(H17)) ,"BOUNDED","UNBOUNDED") -> UNBOUNDED | O17: =IF(N17="UNBOUNDED","HOLD",IF(L17>=Inputs!$B$9,"CLOSE","FAIL")) -> HOLD
A18: ET-A-A-ENERGY-COLD_START | B18: ET-A-A | C18: Energy | D18: COLD_START | E18: MW | G18: =Inputs!$B$7 -> 0.025 | H18: ='Source Inputs'!I9 -> 96 | I18: =Inputs!$B$8 -> 0.025 | J18: =IF(ISNUMBER(F18),F18*(1-G18),"") | K18: =IF(ISNUMBER(H18),H18*(1+I18),"") -> 98.4 | L18: =IF(AND(ISNUMBER(J18),ISNUMBER(K18),K18>0),J18/K18,"") | M18: =IF(AND(ISNUMBER(F18),ISNUMBER(H18),H18>0),(F18/H18-1)/(F18/H18+1),"") | N18: =IF(AND(ISNUMBER(F18),ISNUMBER(H18)) ,"BOUNDED","UNBOUNDED") -> UNBOUNDED | O18: =IF(N18="UNBOUNDED","HOLD",IF(L18>=Inputs!$B$9,"CLOSE","FAIL")) -> HOLD
A19: ET-A-A-FLOW-NOMINAL | B19: ET-A-A | C19: Flow | D19: NOMINAL | E19: t/day | F19: ='Source Inputs'!H10 -> 1512 | G19: =Inputs!$B$7 -> 0.025 | H19: ='Source Inputs'!I10 -> 1200 | I19: =Inputs!$B$8 -> 0.025 | J19: =IF(ISNUMBER(F19),F19*(1-G19),"") -> 1474.2 | K19: =IF(ISNUMBER(H19),H19*(1+I19),"") -> 1230 | L19: =IF(AND(ISNUMBER(J19),ISNUMBER(K19),K19>0),J19/K19,"") -> 1.1985366 | M19: =IF(AND(ISNUMBER(F19),ISNUMBER(H19),H19>0),(F19/H19-1)/(F19/H19+1),"") -> 0.11504425 | N19: =IF(AND(ISNUMBER(F19),ISNUMBER(H19)) ,"BOUNDED","UNBOUNDED") -> BOUNDED | O19: =IF(N19="UNBOUNDED","HOLD",IF(L19>=Inputs!$B$9,"CLOSE","FAIL")) -> CLOSE
A20: ET-A-A-FLOW-LARGEST_CELL_LOSS | B20: ET-A-A | C20: Flow | D20: LARGEST_CELL_LOSS | E20: t/day | F20: ='Source Inputs'!J10 -> 1260 | G20: =Inputs!$B$7 -> 0.025 | H20: ='Source Inputs'!K10 -> 1200 | I20: =Inputs!$B$8 -> 0.025 | J20: =IF(ISNUMBER(F20),F20*(1-G20),"") -> 1228.5 | K20: =IF(ISNUMBER(H20),H20*(1+I20),"") -> 1230 | L20: =IF(AND(ISNUMBER(J20),ISNUMBER(K20),K20>0),J20/K20,"") -> 0.99878049 | M20: =IF(AND(ISNUMBER(F20),ISNUMBER(H20),H20>0),(F20/H20-1)/(F20/H20+1),"") -> 0.024390244 | N20: =IF(AND(ISNUMBER(F20),ISNUMBER(H20)) ,"BOUNDED","UNBOUNDED") -> BOUNDED | O20: =IF(N20="UNBOUNDED","HOLD",IF(L20>=Inputs!$B$9,"CLOSE","FAIL")) -> FAIL
A21: ET-A-A-FLOW-FATAL_KEYSTONE | B21: ET-A-A | C21: Flow | D21: FATAL_KEYSTONE | E21: t/day | G21: =Inputs!$B$7 -> 0.025 | H21: ='Source Inputs'!I10 -> 1200 | I21: =Inputs!$B$8 -> 0.025 | J21: =IF(ISNUMBER(F21),F21*(1-G21),"") | K21: =IF(ISNUMBER(H21),H21*(1+I21),"") -> 1230 | L21: =IF(AND(ISNUMBER(J21),ISNUMBER(K21),K21>0),J21/K21,"") | M21: =IF(AND(ISNUMBER(F21),ISNUMBER(H21),H21>0),(F21/H21-1)/(F21/H21+1),"") | N21: =IF(AND(ISNUMBER(F21),ISNUMBER(H21)) ,"BOUNDED","UNBOUNDED") -> UNBOUNDED | O21: =IF(N21="UNBOUNDED","HOLD",IF(L21>=Inputs!$B$9,"CLOSE","FAIL")) -> HOLD
A22: ET-A-A-FLOW-COLD_START | B22: ET-A-A | C22: Flow | D22: COLD_START | E22: t/day | G22: =Inputs!$B$7 -> 0.025 | H22: ='Source Inputs'!I10 -> 1200 | I22: =Inputs!$B$8 -> 0.025 | J22: =IF(ISNUMBER(F22),F22*(1-G22),"") | K22: =IF(ISNUMBER(H22),H22*(1+I22),"") -> 1230 | L22: =IF(AND(ISNUMBER(J22),ISNUMBER(K22),K22>0),J22/K22,"") | M22: =IF(AND(ISNUMBER(F22),ISNUMBER(H22),H22>0),(F22/H22-1)/(F22/H22+1),"") | N22: =IF(AND(ISNUMBER(F22),ISNUMBER(H22)) ,"BOUNDED","UNBOUNDED") -> UNBOUNDED | O22: =IF(N22="UNBOUNDED","HOLD",IF(L22>=Inputs!$B$9,"CLOSE","FAIL")) -> HOLD
A23: ET-A-A-THERMAL-NOMINAL | B23: ET-A-A | C23: Thermal | D23: NOMINAL | E23: form-native | G23: =Inputs!$B$7 -> 0.025 | I23: =Inputs!$B$8 -> 0.025 | J23: =IF(ISNUMBER(F23),F23*(1-G23),"") | K23: =IF(ISNUMBER(H23),H23*(1+I23),"") | L23: =IF(AND(ISNUMBER(J23),ISNUMBER(K23),K23>0),J23/K23,"") | M23: =IF(AND(ISNUMBER(F23),ISNUMBER(H23),H23>0),(F23/H23-1)/(F23/H23+1),"") | N23: =IF(AND(ISNUMBER(F23),ISNUMBER(H23)) ,"BOUNDED","UNBOUNDED") -> UNBOUNDED | O23: =IF(N23="UNBOUNDED","HOLD",IF(L23>=Inputs!$B$9,"CLOSE","FAIL")) -> HOLD
A24: ET-A-A-THERMAL-LARGEST_CELL_LOSS | B24: ET-A-A | C24: Thermal | D24: LARGEST_CELL_LOSS | E24: form-native | G24: =Inputs!$B$7 -> 0.025 | I24: =Inputs!$B$8 -> 0.025 | J24: =IF(ISNUMBER(F24),F24*(1-G24),"") | K24: =IF(ISNUMBER(H24),H24*(1+I24),"") | L24: =IF(AND(ISNUMBER(J24),ISNUMBER(K24),K24>0),J24/K24,"") | M24: =IF(AND(ISNUMBER(F24),ISNUMBER(H24),H24>0),(F24/H24-1)/(F24/H24+1),"") | N24: =IF(AND(ISNUMBER(F24),ISNUMBER(H24)) ,"BOUNDED","UNBOUNDED") -> UNBOUNDED | O24: =IF(N24="UNBOUNDED","HOLD",IF(L24>=Inputs!$B$9,"CLOSE","FAIL")) -> HOLD
A25: ET-A-A-THERMAL-FATAL_KEYSTONE | B25: ET-A-A | C25: Thermal | D25: FATAL_KEYSTONE | E25: form-native | G25: =Inputs!$B$7 -> 0.025 | I25: =Inputs!$B$8 -> 0.025 | J25: =IF(ISNUMBER(F25),F25*(1-G25),"") | K25: =IF(ISNUMBER(H25),H25*(1+I25),"") | L25: =IF(AND(ISNUMBER(J25),ISNUMBER(K25),K25>0),J25/K25,"") | M25: =IF(AND(ISNUMBER(F25),ISNUMBER(H25),H25>0),(F25/H25-1)/(F25/H25+1),"") | N25: =IF(AND(ISNUMBER(F25),ISNUMBER(H25)) ,"BOUNDED","UNBOUNDED") -> UNBOUNDED | O25: =IF(N25="UNBOUNDED","HOLD",IF(L25>=Inputs!$B$9,"CLOSE","FAIL")) -> HOLD
A26: ET-A-A-THERMAL-COLD_START | B26: ET-A-A | C26: Thermal | D26: COLD_START | E26: form-native | G26: =Inputs!$B$7 -> 0.025 | I26: =Inputs!$B$8 -> 0.025 | J26: =IF(ISNUMBER(F26),F26*(1-G26),"") | K26: =IF(ISNUMBER(H26),H26*(1+I26),"") | L26: =IF(AND(ISNUMBER(J26),ISNUMBER(K26),K26>0),J26/K26,"") | M26: =IF(AND(ISNUMBER(F26),ISNUMBER(H26),H26>0),(F26/H26-1)/(F26/H26+1),"") | N26: =IF(AND(ISNUMBER(F26),ISNUMBER(H26)) ,"BOUNDED","UNBOUNDED") -> UNBOUNDED | O26: =IF(N26="UNBOUNDED","HOLD",IF(L26>=Inputs!$B$9,"CLOSE","FAIL")) -> HOLD
A27: CT-C-B-SERVICE-NOMINAL | B27: CT-C-B | C27: Service | D27: NOMINAL | E27: ratio | F27: ='Source Inputs'!H11 -> 1.32 | G27: =Inputs!$B$7 -> 0.025 | H27: ='Source Inputs'!I11 -> 1 | I27: =Inputs!$B$8 -> 0.025 | J27: =IF(ISNUMBER(F27),F27*(1-G27),"") -> 1.287 | K27: =IF(ISNUMBER(H27),H27*(1+I27),"") -> 1.025 | L27: =IF(AND(ISNUMBER(J27),ISNUMBER(K27),K27>0),J27/K27,"") -> 1.2556098 | M27: =IF(AND(ISNUMBER(F27),ISNUMBER(H27),H27>0),(F27/H27-1)/(F27/H27+1),"") -> 0.13793103 | N27: =IF(AND(ISNUMBER(F27),ISNUMBER(H27)) ,"BOUNDED","UNBOUNDED") -> BOUNDED | O27: =IF(N27="UNBOUNDED","HOLD",IF(L27>=Inputs!$B$9,"CLOSE","FAIL")) -> CLOSE
A28: CT-C-B-SERVICE-LARGEST_CELL_LOSS | B28: CT-C-B | C28: Service | D28: LARGEST_CELL_LOSS | E28: ratio | F28: ='Source Inputs'!J11 -> 1.056 | G28: =Inputs!$B$7 -> 0.025 | H28: ='Source Inputs'!K11 -> 1 | I28: =Inputs!$B$8 -> 0.025 | J28: =IF(ISNUMBER(F28),F28*(1-G28),"") -> 1.0296 | K28: =IF(ISNUMBER(H28),H28*(1+I28),"") -> 1.025 | L28: =IF(AND(ISNUMBER(J28),ISNUMBER(K28),K28>0),J28/K28,"") -> 1.0044878 | M28: =IF(AND(ISNUMBER(F28),ISNUMBER(H28),H28>0),(F28/H28-1)/(F28/H28+1),"") -> 0.027237354 | N28: =IF(AND(ISNUMBER(F28),ISNUMBER(H28)) ,"BOUNDED","UNBOUNDED") -> BOUNDED | O28: =IF(N28="UNBOUNDED","HOLD",IF(L28>=Inputs!$B$9,"CLOSE","FAIL")) -> CLOSE
A29: CT-C-B-SERVICE-FATAL_KEYSTONE | B29: CT-C-B | C29: Service | D29: FATAL_KEYSTONE | E29: ratio | G29: =Inputs!$B$7 -> 0.025 | H29: ='Source Inputs'!I11 -> 1 | I29: =Inputs!$B$8 -> 0.025 | J29: =IF(ISNUMBER(F29),F29*(1-G29),"") | K29: =IF(ISNUMBER(H29),H29*(1+I29),"") -> 1.025 | L29: =IF(AND(ISNUMBER(J29),ISNUMBER(K29),K29>0),J29/K29,"") | M29: =IF(AND(ISNUMBER(F29),ISNUMBER(H29),H29>0),(F29/H29-1)/(F29/H29+1),"") | N29: =IF(AND(ISNUMBER(F29),ISNUMBER(H29)) ,"BOUNDED","UNBOUNDED") -> UNBOUNDED | O29: =IF(N29="UNBOUNDED","HOLD",IF(L29>=Inputs!$B$9,"CLOSE","FAIL")) -> HOLD
A30: CT-C-B-SERVICE-COLD_START | B30: CT-C-B | C30: Service | D30: COLD_START | E30: ratio | G30: =Inputs!$B$7 -> 0.025 | H30: ='Source Inputs'!I11 -> 1 | I30: =Inputs!$B$8 -> 0.025 | J30: =IF(ISNUMBER(F30),F30*(1-G30),"") | K30: =IF(ISNUMBER(H30),H30*(1+I30),"") -> 1.025 | L30: =IF(AND(ISNUMBER(J30),ISNUMBER(K30),K30>0),J30/K30,"") | M30: =IF(AND(ISNUMBER(F30),ISNUMBER(H30),H30>0),(F30/H30-1)/(F30/H30+1),"") | N30: =IF(AND(ISNUMBER(F30),ISNUMBER(H30)) ,"BOUNDED","UNBOUNDED") -> UNBOUNDED | O30: =IF(N30="UNBOUNDED","HOLD",IF(L30>=Inputs!$B$9,"CLOSE","FAIL")) -> HOLD
A31: CT-C-B-MASS-NOMINAL | B31: CT-C-B | C31: Mass | D31: NOMINAL | E31: t | F31: ='Source Inputs'!H12 -> 36000 | G31: =Inputs!$B$7 -> 0.025 | H31: ='Source Inputs'!I12 -> 31000 | I31: =Inputs!$B$8 -> 0.025 | J31: =IF(ISNUMBER(F31),F31*(1-G31),"") -> 35100 | K31: =IF(ISNUMBER(H31),H31*(1+I31),"") -> 31775 | L31: =IF(AND(ISNUMBER(J31),ISNUMBER(K31),K31>0),J31/K31,"") -> 1.104642 | M31: =IF(AND(ISNUMBER(F31),ISNUMBER(H31),H31>0),(F31/H31-1)/(F31/H31+1),"") -> 0.074626866 | N31: =IF(AND(ISNUMBER(F31),ISNUMBER(H31)) ,"BOUNDED","UNBOUNDED") -> BOUNDED | O31: =IF(N31="UNBOUNDED","HOLD",IF(L31>=Inputs!$B$9,"CLOSE","FAIL")) -> CLOSE
A32: CT-C-B-MASS-LARGEST_CELL_LOSS | B32: CT-C-B | C32: Mass | D32: LARGEST_CELL_LOSS | E32: t | F32: ='Source Inputs'!J12 -> 32400 | G32: =Inputs!$B$7 -> 0.025 | H32: ='Source Inputs'!K12 -> 31000 | I32: =Inputs!$B$8 -> 0.025 | J32: =IF(ISNUMBER(F32),F32*(1-G32),"") -> 31590 | K32: =IF(ISNUMBER(H32),H32*(1+I32),"") -> 31775 | L32: =IF(AND(ISNUMBER(J32),ISNUMBER(K32),K32>0),J32/K32,"") -> 0.99417781 | M32: =IF(AND(ISNUMBER(F32),ISNUMBER(H32),H32>0),(F32/H32-1)/(F32/H32+1),"") -> 0.022082019 | N32: =IF(AND(ISNUMBER(F32),ISNUMBER(H32)) ,"BOUNDED","UNBOUNDED") -> BOUNDED | O32: =IF(N32="UNBOUNDED","HOLD",IF(L32>=Inputs!$B$9,"CLOSE","FAIL")) -> FAIL
A33: CT-C-B-MASS-FATAL_KEYSTONE | B33: CT-C-B | C33: Mass | D33: FATAL_KEYSTONE | E33: t | G33: =Inputs!$B$7 -> 0.025 | H33: ='Source Inputs'!I12 -> 31000 | I33: =Inputs!$B$8 -> 0.025 | J33: =IF(ISNUMBER(F33),F33*(1-G33),"") | K33: =IF(ISNUMBER(H33),H33*(1+I33),"") -> 31775 | L33: =IF(AND(ISNUMBER(J33),ISNUMBER(K33),K33>0),J33/K33,"") | M33: =IF(AND(ISNUMBER(F33),ISNUMBER(H33),H33>0),(F33/H33-1)/(F33/H33+1),"") | N33: =IF(AND(ISNUMBER(F33),ISNUMBER(H33)) ,"BOUNDED","UNBOUNDED") -> UNBOUNDED | O33: =IF(N33="UNBOUNDED","HOLD",IF(L33>=Inputs!$B$9,"CLOSE","FAIL")) -> HOLD
A34: CT-C-B-MASS-COLD_START | B34: CT-C-B | C34: Mass | D34: COLD_START | E34: t | G34: =Inputs!$B$7 -> 0.025 | H34: ='Source Inputs'!I12 -> 31000 | I34: =Inputs!$B$8 -> 0.025 | J34: =IF(ISNUMBER(F34),F34*(1-G34),"") | K34: =IF(ISNUMBER(H34),H34*(1+I34),"") -> 31775 | L34: =IF(AND(ISNUMBER(J34),ISNUMBER(K34),K34>0),J34/K34,"") | M34: =IF(AND(ISNUMBER(F34),ISNUMBER(H34),H34>0),(F34/H34-1)/(F34/H34+1),"") | N34: =IF(AND(ISNUMBER(F34),ISNUMBER(H34)) ,"BOUNDED","UNBOUNDED") -> UNBOUNDED | O34: =IF(N34="UNBOUNDED","HOLD",IF(L34>=Inputs!$B$9,"CLOSE","FAIL")) -> HOLD
A35: CT-C-B-ENERGY-NOMINAL | B35: CT-C-B | C35: Energy | D35: NOMINAL | E35: MW | F35: ='Source Inputs'!H13 -> 50.4 | G35: =Inputs!$B$7 -> 0.025 | H35: ='Source Inputs'!I13 -> 42 | I35: =Inputs!$B$8 -> 0.025 | J35: =IF(ISNUMBER(F35),F35*(1-G35),"") -> 49.14 | K35: =IF(ISNUMBER(H35),H35*(1+I35),"") -> 43.05 | L35: =IF(AND(ISNUMBER(J35),ISNUMBER(K35),K35>0),J35/K35,"") -> 1.1414634 | M35: =IF(AND(ISNUMBER(F35),ISNUMBER(H35),H35>0),(F35/H35-1)/(F35/H35+1),"") -> 0.090909091 | N35: =IF(AND(ISNUMBER(F35),ISNUMBER(H35)) ,"BOUNDED","UNBOUNDED") -> BOUNDED | O35: =IF(N35="UNBOUNDED","HOLD",IF(L35>=Inputs!$B$9,"CLOSE","FAIL")) -> CLOSE
A36: CT-C-B-ENERGY-LARGEST_CELL_LOSS | B36: CT-C-B | C36: Energy | D36: LARGEST_CELL_LOSS | E36: MW | F36: ='Source Inputs'!J13 -> 43.2 | G36: =Inputs!$B$7 -> 0.025 | H36: ='Source Inputs'!K13 -> 42 | I36: =Inputs!$B$8 -> 0.025 | J36: =IF(ISNUMBER(F36),F36*(1-G36),"") -> 42.12 | K36: =IF(ISNUMBER(H36),H36*(1+I36),"") -> 43.05 | L36: =IF(AND(ISNUMBER(J36),ISNUMBER(K36),K36>0),J36/K36,"") -> 0.97839721 | M36: =IF(AND(ISNUMBER(F36),ISNUMBER(H36),H36>0),(F36/H36-1)/(F36/H36+1),"") -> 0.014084507 | N36: =IF(AND(ISNUMBER(F36),ISNUMBER(H36)) ,"BOUNDED","UNBOUNDED") -> BOUNDED | O36: =IF(N36="UNBOUNDED","HOLD",IF(L36>=Inputs!$B$9,"CLOSE","FAIL")) -> FAIL
A37: CT-C-B-ENERGY-FATAL_KEYSTONE | B37: CT-C-B | C37: Energy | D37: FATAL_KEYSTONE | E37: MW | G37: =Inputs!$B$7 -> 0.025 | H37: ='Source Inputs'!I13 -> 42 | I37: =Inputs!$B$8 -> 0.025 | J37: =IF(ISNUMBER(F37),F37*(1-G37),"") | K37: =IF(ISNUMBER(H37),H37*(1+I37),"") -> 43.05 | L37: =IF(AND(ISNUMBER(J37),ISNUMBER(K37),K37>0),J37/K37,"") | M37: =IF(AND(ISNUMBER(F37),ISNUMBER(H37),H37>0),(F37/H37-1)/(F37/H37+1),"") | N37: =IF(AND(ISNUMBER(F37),ISNUMBER(H37)) ,"BOUNDED","UNBOUNDED") -> UNBOUNDED | O37: =IF(N37="UNBOUNDED","HOLD",IF(L37>=Inputs!$B$9,"CLOSE","FAIL")) -> HOLD
A38: CT-C-B-ENERGY-COLD_START | B38: CT-C-B | C38: Energy | D38: COLD_START | E38: MW | G38: =Inputs!$B$7 -> 0.025 | H38: ='Source Inputs'!I13 -> 42 | I38: =Inputs!$B$8 -> 0.025 | J38: =IF(ISNUMBER(F38),F38*(1-G38),"") | K38: =IF(ISNUMBER(H38),H38*(1+I38),"") -> 43.05 | L38: =IF(AND(ISNUMBER(J38),ISNUMBER(K38),K38>0),J38/K38,"") | M38: =IF(AND(ISNUMBER(F38),ISNUMBER(H38),H38>0),(F38/H38-1)/(F38/H38+1),"") | N38: =IF(AND(ISNUMBER(F38),ISNUMBER(H38)) ,"BOUNDED","UNBOUNDED") -> UNBOUNDED | O38: =IF(N38="UNBOUNDED","HOLD",IF(L38>=Inputs!$B$9,"CLOSE","FAIL")) -> HOLD
A39: CT-C-B-FLOW-NOMINAL | B39: CT-C-B | C39: Flow | D39: NOMINAL | E39: t/day | F39: ='Source Inputs'!H14 -> 277.2 | G39: =Inputs!$B$7 -> 0.025 | H39: ='Source Inputs'!I14 -> 220 | I39: =Inputs!$B$8 -> 0.025 | J39: =IF(ISNUMBER(F39),F39*(1-G39),"") -> 270.27 | K39: =IF(ISNUMBER(H39),H39*(1+I39),"") -> 225.5 | L39: =IF(AND(ISNUMBER(J39),ISNUMBER(K39),K39>0),J39/K39,"") -> 1.1985366 | M39: =IF(AND(ISNUMBER(F39),ISNUMBER(H39),H39>0),(F39/H39-1)/(F39/H39+1),"") -> 0.11504425 | N39: =IF(AND(ISNUMBER(F39),ISNUMBER(H39)) ,"BOUNDED","UNBOUNDED") -> BOUNDED | O39: =IF(N39="UNBOUNDED","HOLD",IF(L39>=Inputs!$B$9,"CLOSE","FAIL")) -> CLOSE
A40: CT-C-B-FLOW-LARGEST_CELL_LOSS | B40: CT-C-B | C40: Flow | D40: LARGEST_CELL_LOSS | E40: t/day | F40: ='Source Inputs'!J14 -> 231 | G40: =Inputs!$B$7 -> 0.025 | H40: ='Source Inputs'!K14 -> 220 | I40: =Inputs!$B$8 -> 0.025 | J40: =IF(ISNUMBER(F40),F40*(1-G40),"") -> 225.225 | K40: =IF(ISNUMBER(H40),H40*(1+I40),"") -> 225.5 | L40: =IF(AND(ISNUMBER(J40),ISNUMBER(K40),K40>0),J40/K40,"") -> 0.99878049 | M40: =IF(AND(ISNUMBER(F40),ISNUMBER(H40),H40>0),(F40/H40-1)/(F40/H40+1),"") -> 0.024390244 | N40: =IF(AND(ISNUMBER(F40),ISNUMBER(H40)) ,"BOUNDED","UNBOUNDED") -> BOUNDED | O40: =IF(N40="UNBOUNDED","HOLD",IF(L40>=Inputs!$B$9,"CLOSE","FAIL")) -> FAIL
A41: CT-C-B-FLOW-FATAL_KEYSTONE | B41: CT-C-B | C41: Flow | D41: FATAL_KEYSTONE | E41: t/day | G41: =Inputs!$B$7 -> 0.025 | H41: ='Source Inputs'!I14 -> 220 | I41: =Inputs!$B$8 -> 0.025 | J41: =IF(ISNUMBER(F41),F41*(1-G41),"") | K41: =IF(ISNUMBER(H41),H41*(1+I41),"") -> 225.5 | L41: =IF(AND(ISNUMBER(J41),ISNUMBER(K41),K41>0),J41/K41,"") | M41: =IF(AND(ISNUMBER(F41),ISNUMBER(H41),H41>0),(F41/H41-1)/(F41/H41+1),"") | N41: =IF(AND(ISNUMBER(F41),ISNUMBER(H41)) ,"BOUNDED","UNBOUNDED") -> UNBOUNDED | O41: =IF(N41="UNBOUNDED","HOLD",IF(L41>=Inputs!$B$9,"CLOSE","FAIL")) -> HOLD
A42: CT-C-B-FLOW-COLD_START | B42: CT-C-B | C42: Flow | D42: COLD_START | E42: t/day | G42: =Inputs!$B$7 -> 0.025 | H42: ='Source Inputs'!I14 -> 220 | I42: =Inputs!$B$8 -> 0.025 | J42: =IF(ISNUMBER(F42),F42*(1-G42),"") | K42: =IF(ISNUMBER(H42),H42*(1+I42),"") -> 225.5 | L42: =IF(AND(ISNUMBER(J42),ISNUMBER(K42),K42>0),J42/K42,"") | M42: =IF(AND(ISNUMBER(F42),ISNUMBER(H42),H42>0),(F42/H42-1)/(F42/H42+1),"") | N42: =IF(AND(ISNUMBER(F42),ISNUMBER(H42)) ,"BOUNDED","UNBOUNDED") -> UNBOUNDED | O42: =IF(N42="UNBOUNDED","HOLD",IF(L42>=Inputs!$B$9,"CLOSE","FAIL")) -> HOLD
A43: CT-C-B-THERMAL-NOMINAL | B43: CT-C-B | C43: Thermal | D43: NOMINAL | E43: form-native | G43: =Inputs!$B$7 -> 0.025 | I43: =Inputs!$B$8 -> 0.025 | J43: =IF(ISNUMBER(F43),F43*(1-G43),"") | K43: =IF(ISNUMBER(H43),H43*(1+I43),"") | L43: =IF(AND(ISNUMBER(J43),ISNUMBER(K43),K43>0),J43/K43,"") | M43: =IF(AND(ISNUMBER(F43),ISNUMBER(H43),H43>0),(F43/H43-1)/(F43/H43+1),"") | N43: =IF(AND(ISNUMBER(F43),ISNUMBER(H43)) ,"BOUNDED","UNBOUNDED") -> UNBOUNDED | O43: =IF(N43="UNBOUNDED","HOLD",IF(L43>=Inputs!$B$9,"CLOSE","FAIL")) -> HOLD
A44: CT-C-B-THERMAL-LARGEST_CELL_LOSS | B44: CT-C-B | C44: Thermal | D44: LARGEST_CELL_LOSS | E44: form-native | G44: =Inputs!$B$7 -> 0.025 | I44: =Inputs!$B$8 -> 0.025 | J44: =IF(ISNUMBER(F44),F44*(1-G44),"") | K44: =IF(ISNUMBER(H44),H44*(1+I44),"") | L44: =IF(AND(ISNUMBER(J44),ISNUMBER(K44),K44>0),J44/K44,"") | M44: =IF(AND(ISNUMBER(F44),ISNUMBER(H44),H44>0),(F44/H44-1)/(F44/H44+1),"") | N44: =IF(AND(ISNUMBER(F44),ISNUMBER(H44)) ,"BOUNDED","UNBOUNDED") -> UNBOUNDED | O44: =IF(N44="UNBOUNDED","HOLD",IF(L44>=Inputs!$B$9,"CLOSE","FAIL")) -> HOLD
A45: CT-C-B-THERMAL-FATAL_KEYSTONE | B45: CT-C-B | C45: Thermal | D45: FATAL_KEYSTONE | E45: form-native | G45: =Inputs!$B$7 -> 0.025 | I45: =Inputs!$B$8 -> 0.025 | J45: =IF(ISNUMBER(F45),F45*(1-G45),"") | K45: =IF(ISNUMBER(H45),H45*(1+I45),"") | L45: =IF(AND(ISNUMBER(J45),ISNUMBER(K45),K45>0),J45/K45,"") | M45: =IF(AND(ISNUMBER(F45),ISNUMBER(H45),H45>0),(F45/H45-1)/(F45/H45+1),"") | N45: =IF(AND(ISNUMBER(F45),ISNUMBER(H45)) ,"BOUNDED","UNBOUNDED") -> UNBOUNDED | O45: =IF(N45="UNBOUNDED","HOLD",IF(L45>=Inputs!$B$9,"CLOSE","FAIL")) -> HOLD
A46: CT-C-B-THERMAL-COLD_START | B46: CT-C-B | C46: Thermal | D46: COLD_START | E46: form-native | G46: =Inputs!$B$7 -> 0.025 | I46: =Inputs!$B$8 -> 0.025 | J46: =IF(ISNUMBER(F46),F46*(1-G46),"") | K46: =IF(ISNUMBER(H46),H46*(1+I46),"") | L46: =IF(AND(ISNUMBER(J46),ISNUMBER(K46),K46>0),J46/K46,"") | M46: =IF(AND(ISNUMBER(F46),ISNUMBER(H46),H46>0),(F46/H46-1)/(F46/H46+1),"") | N46: =IF(AND(ISNUMBER(F46),ISNUMBER(H46)) ,"BOUNDED","UNBOUNDED") -> UNBOUNDED | O46: =IF(N46="UNBOUNDED","HOLD",IF(L46>=Inputs!$B$9,"CLOSE","FAIL")) -> HOLD
A47: HC-A-C-SERVICE-NOMINAL | B47: HC-A-C | C47: Service | D47: NOMINAL | E47: km/day | F47: ='Source Inputs'!H15 -> 132.5 | G47: =Inputs!$B$7 -> 0.025 | H47: ='Source Inputs'!I15 -> 103 | I47: =Inputs!$B$8 -> 0.025 | J47: =IF(ISNUMBER(F47),F47*(1-G47),"") -> 129.1875 | K47: =IF(ISNUMBER(H47),H47*(1+I47),"") -> 105.575 | L47: =IF(AND(ISNUMBER(J47),ISNUMBER(K47),K47>0),J47/K47,"") -> 1.2236562 | M47: =IF(AND(ISNUMBER(F47),ISNUMBER(H47),H47>0),(F47/H47-1)/(F47/H47+1),"") -> 0.12526539 | N47: =IF(AND(ISNUMBER(F47),ISNUMBER(H47)) ,"BOUNDED","UNBOUNDED") -> BOUNDED | O47: =IF(N47="UNBOUNDED","HOLD",IF(L47>=Inputs!$B$9,"CLOSE","FAIL")) -> CLOSE
A48: HC-A-C-SERVICE-LARGEST_CELL_LOSS | B48: HC-A-C | C48: Service | D48: LARGEST_CELL_LOSS | E48: km/day | F48: ='Source Inputs'!J15 -> 106 | G48: =Inputs!$B$7 -> 0.025 | H48: ='Source Inputs'!K15 -> 103 | I48: =Inputs!$B$8 -> 0.025 | J48: =IF(ISNUMBER(F48),F48*(1-G48),"") -> 103.35 | K48: =IF(ISNUMBER(H48),H48*(1+I48),"") -> 105.575 | L48: =IF(AND(ISNUMBER(J48),ISNUMBER(K48),K48>0),J48/K48,"") -> 0.97892493 | M48: =IF(AND(ISNUMBER(F48),ISNUMBER(H48),H48>0),(F48/H48-1)/(F48/H48+1),"") -> 0.014354067 | N48: =IF(AND(ISNUMBER(F48),ISNUMBER(H48)) ,"BOUNDED","UNBOUNDED") -> BOUNDED | O48: =IF(N48="UNBOUNDED","HOLD",IF(L48>=Inputs!$B$9,"CLOSE","FAIL")) -> FAIL
A49: HC-A-C-SERVICE-FATAL_KEYSTONE | B49: HC-A-C | C49: Service | D49: FATAL_KEYSTONE | E49: km/day | G49: =Inputs!$B$7 -> 0.025 | H49: ='Source Inputs'!I15 -> 103 | I49: =Inputs!$B$8 -> 0.025 | J49: =IF(ISNUMBER(F49),F49*(1-G49),"") | K49: =IF(ISNUMBER(H49),H49*(1+I49),"") -> 105.575 | L49: =IF(AND(ISNUMBER(J49),ISNUMBER(K49),K49>0),J49/K49,"") | M49: =IF(AND(ISNUMBER(F49),ISNUMBER(H49),H49>0),(F49/H49-1)/(F49/H49+1),"") | N49: =IF(AND(ISNUMBER(F49),ISNUMBER(H49)) ,"BOUNDED","UNBOUNDED") -> UNBOUNDED | O49: =IF(N49="UNBOUNDED","HOLD",IF(L49>=Inputs!$B$9,"CLOSE","FAIL")) -> HOLD
A50: HC-A-C-SERVICE-COLD_START | B50: HC-A-C | C50: Service | D50: COLD_START | E50: km/day | G50: =Inputs!$B$7 -> 0.025 | H50: ='Source Inputs'!I15 -> 103 | I50: =Inputs!$B$8 -> 0.025 | J50: =IF(ISNUMBER(F50),F50*(1-G50),"") | K50: =IF(ISNUMBER(H50),H50*(1+I50),"") -> 105.575 | L50: =IF(AND(ISNUMBER(J50),ISNUMBER(K50),K50>0),J50/K50,"") | M50: =IF(AND(ISNUMBER(F50),ISNUMBER(H50),H50>0),(F50/H50-1)/(F50/H50+1),"") | N50: =IF(AND(ISNUMBER(F50),ISNUMBER(H50)) ,"BOUNDED","UNBOUNDED") -> UNBOUNDED | O50: =IF(N50="UNBOUNDED","HOLD",IF(L50>=Inputs!$B$9,"CLOSE","FAIL")) -> HOLD
A51: HC-A-C-MASS-NOMINAL | B51: HC-A-C | C51: Mass | D51: NOMINAL | E51: t | F51: ='Source Inputs'!H16 -> 63000 | G51: =Inputs!$B$7 -> 0.025 | H51: ='Source Inputs'!I16 -> 54000 | I51: =Inputs!$B$8 -> 0.025 | J51: =IF(ISNUMBER(F51),F51*(1-G51),"") -> 61425 | K51: =IF(ISNUMBER(H51),H51*(1+I51),"") -> 55350 | L51: =IF(AND(ISNUMBER(J51),ISNUMBER(K51),K51>0),J51/K51,"") -> 1.1097561 | M51: =IF(AND(ISNUMBER(F51),ISNUMBER(H51),H51>0),(F51/H51-1)/(F51/H51+1),"") -> 0.076923077 | N51: =IF(AND(ISNUMBER(F51),ISNUMBER(H51)) ,"BOUNDED","UNBOUNDED") -> BOUNDED | O51: =IF(N51="UNBOUNDED","HOLD",IF(L51>=Inputs!$B$9,"CLOSE","FAIL")) -> CLOSE
A52: HC-A-C-MASS-LARGEST_CELL_LOSS | B52: HC-A-C | C52: Mass | D52: LARGEST_CELL_LOSS | E52: t | F52: ='Source Inputs'!J16 -> 56700 | G52: =Inputs!$B$7 -> 0.025 | H52: ='Source Inputs'!K16 -> 54000 | I52: =Inputs!$B$8 -> 0.025 | J52: =IF(ISNUMBER(F52),F52*(1-G52),"") -> 55282.5 | K52: =IF(ISNUMBER(H52),H52*(1+I52),"") -> 55350 | L52: =IF(AND(ISNUMBER(J52),ISNUMBER(K52),K52>0),J52/K52,"") -> 0.99878049 | M52: =IF(AND(ISNUMBER(F52),ISNUMBER(H52),H52>0),(F52/H52-1)/(F52/H52+1),"") -> 0.024390244 | N52: =IF(AND(ISNUMBER(F52),ISNUMBER(H52)) ,"BOUNDED","UNBOUNDED") -> BOUNDED | O52: =IF(N52="UNBOUNDED","HOLD",IF(L52>=Inputs!$B$9,"CLOSE","FAIL")) -> FAIL
A53: HC-A-C-MASS-FATAL_KEYSTONE | B53: HC-A-C | C53: Mass | D53: FATAL_KEYSTONE | E53: t | G53: =Inputs!$B$7 -> 0.025 | H53: ='Source Inputs'!I16 -> 54000 | I53: =Inputs!$B$8 -> 0.025 | J53: =IF(ISNUMBER(F53),F53*(1-G53),"") | K53: =IF(ISNUMBER(H53),H53*(1+I53),"") -> 55350 | L53: =IF(AND(ISNUMBER(J53),ISNUMBER(K53),K53>0),J53/K53,"") | M53: =IF(AND(ISNUMBER(F53),ISNUMBER(H53),H53>0),(F53/H53-1)/(F53/H53+1),"") | N53: =IF(AND(ISNUMBER(F53),ISNUMBER(H53)) ,"BOUNDED","UNBOUNDED") -> UNBOUNDED | O53: =IF(N53="UNBOUNDED","HOLD",IF(L53>=Inputs!$B$9,"CLOSE","FAIL")) -> HOLD
A54: HC-A-C-MASS-COLD_START | B54: HC-A-C | C54: Mass | D54: COLD_START | E54: t | G54: =Inputs!$B$7 -> 0.025 | H54: ='Source Inputs'!I16 -> 54000 | I54: =Inputs!$B$8 -> 0.025 | J54: =IF(ISNUMBER(F54),F54*(1-G54),"") | K54: =IF(ISNUMBER(H54),H54*(1+I54),"") -> 55350 | L54: =IF(AND(ISNUMBER(J54),ISNUMBER(K54),K54>0),J54/K54,"") | M54: =IF(AND(ISNUMBER(F54),ISNUMBER(H54),H54>0),(F54/H54-1)/(F54/H54+1),"") | N54: =IF(AND(ISNUMBER(F54),ISNUMBER(H54)) ,"BOUNDED","UNBOUNDED") -> UNBOUNDED | O54: =IF(N54="UNBOUNDED","HOLD",IF(L54>=Inputs!$B$9,"CLOSE","FAIL")) -> HOLD
A55: HC-A-C-ENERGY-NOMINAL | B55: HC-A-C | C55: Energy | D55: NOMINAL | E55: MW | F55: ='Source Inputs'!H17 -> 164.8 | G55: =Inputs!$B$7 -> 0.025 | H55: ='Source Inputs'!I17 -> 140 | I55: =Inputs!$B$8 -> 0.025 | J55: =IF(ISNUMBER(F55),F55*(1-G55),"") -> 160.68 | K55: =IF(ISNUMBER(H55),H55*(1+I55),"") -> 143.5 | L55: =IF(AND(ISNUMBER(J55),ISNUMBER(K55),K55>0),J55/K55,"") -> 1.1197213 | M55: =IF(AND(ISNUMBER(F55),ISNUMBER(H55),H55>0),(F55/H55-1)/(F55/H55+1),"") -> 0.081364829 | N55: =IF(AND(ISNUMBER(F55),ISNUMBER(H55)) ,"BOUNDED","UNBOUNDED") -> BOUNDED | O55: =IF(N55="UNBOUNDED","HOLD",IF(L55>=Inputs!$B$9,"CLOSE","FAIL")) -> CLOSE
A56: HC-A-C-ENERGY-LARGEST_CELL_LOSS | B56: HC-A-C | C56: Energy | D56: LARGEST_CELL_LOSS | E56: MW | F56: ='Source Inputs'!J17 -> 144.2 | G56: =Inputs!$B$7 -> 0.025 | H56: ='Source Inputs'!K17 -> 140 | I56: =Inputs!$B$8 -> 0.025 | J56: =IF(ISNUMBER(F56),F56*(1-G56),"") -> 140.595 | K56: =IF(ISNUMBER(H56),H56*(1+I56),"") -> 143.5 | L56: =IF(AND(ISNUMBER(J56),ISNUMBER(K56),K56>0),J56/K56,"") -> 0.9797561 | M56: =IF(AND(ISNUMBER(F56),ISNUMBER(H56),H56>0),(F56/H56-1)/(F56/H56+1),"") -> 0.014778325 | N56: =IF(AND(ISNUMBER(F56),ISNUMBER(H56)) ,"BOUNDED","UNBOUNDED") -> BOUNDED | O56: =IF(N56="UNBOUNDED","HOLD",IF(L56>=Inputs!$B$9,"CLOSE","FAIL")) -> FAIL
A57: HC-A-C-ENERGY-FATAL_KEYSTONE | B57: HC-A-C | C57: Energy | D57: FATAL_KEYSTONE | E57: MW | G57: =Inputs!$B$7 -> 0.025 | H57: ='Source Inputs'!I17 -> 140 | I57: =Inputs!$B$8 -> 0.025 | J57: =IF(ISNUMBER(F57),F57*(1-G57),"") | K57: =IF(ISNUMBER(H57),H57*(1+I57),"") -> 143.5 | L57: =IF(AND(ISNUMBER(J57),ISNUMBER(K57),K57>0),J57/K57,"") | M57: =IF(AND(ISNUMBER(F57),ISNUMBER(H57),H57>0),(F57/H57-1)/(F57/H57+1),"") | N57: =IF(AND(ISNUMBER(F57),ISNUMBER(H57)) ,"BOUNDED","UNBOUNDED") -> UNBOUNDED | O57: =IF(N57="UNBOUNDED","HOLD",IF(L57>=Inputs!$B$9,"CLOSE","FAIL")) -> HOLD
A58: HC-A-C-ENERGY-COLD_START | B58: HC-A-C | C58: Energy | D58: COLD_START | E58: MW | G58: =Inputs!$B$7 -> 0.025 | H58: ='Source Inputs'!I17 -> 140 | I58: =Inputs!$B$8 -> 0.025 | J58: =IF(ISNUMBER(F58),F58*(1-G58),"") | K58: =IF(ISNUMBER(H58),H58*(1+I58),"") -> 143.5 | L58: =IF(AND(ISNUMBER(J58),ISNUMBER(K58),K58>0),J58/K58,"") | M58: =IF(AND(ISNUMBER(F58),ISNUMBER(H58),H58>0),(F58/H58-1)/(F58/H58+1),"") | N58: =IF(AND(ISNUMBER(F58),ISNUMBER(H58)) ,"BOUNDED","UNBOUNDED") -> UNBOUNDED | O58: =IF(N58="UNBOUNDED","HOLD",IF(L58>=Inputs!$B$9,"CLOSE","FAIL")) -> HOLD
A59: HC-A-C-FLOW-NOMINAL | B59: HC-A-C | C59: Flow | D59: NOMINAL | E59: t/day | F59: ='Source Inputs'!H18 -> 1134 | G59: =Inputs!$B$7 -> 0.025 | H59: ='Source Inputs'!I18 -> 900 | I59: =Inputs!$B$8 -> 0.025 | J59: =IF(ISNUMBER(F59),F59*(1-G59),"") -> 1105.65 | K59: =IF(ISNUMBER(H59),H59*(1+I59),"") -> 922.5 | L59: =IF(AND(ISNUMBER(J59),ISNUMBER(K59),K59>0),J59/K59,"") -> 1.1985366 | M59: =IF(AND(ISNUMBER(F59),ISNUMBER(H59),H59>0),(F59/H59-1)/(F59/H59+1),"") -> 0.11504425 | N59: =IF(AND(ISNUMBER(F59),ISNUMBER(H59)) ,"BOUNDED","UNBOUNDED") -> BOUNDED | O59: =IF(N59="UNBOUNDED","HOLD",IF(L59>=Inputs!$B$9,"CLOSE","FAIL")) -> CLOSE
A60: HC-A-C-FLOW-LARGEST_CELL_LOSS | B60: HC-A-C | C60: Flow | D60: LARGEST_CELL_LOSS | E60: t/day | F60: ='Source Inputs'!J18 -> 945 | G60: =Inputs!$B$7 -> 0.025 | H60: ='Source Inputs'!K18 -> 900 | I60: =Inputs!$B$8 -> 0.025 | J60: =IF(ISNUMBER(F60),F60*(1-G60),"") -> 921.375 | K60: =IF(ISNUMBER(H60),H60*(1+I60),"") -> 922.5 | L60: =IF(AND(ISNUMBER(J60),ISNUMBER(K60),K60>0),J60/K60,"") -> 0.99878049 | M60: =IF(AND(ISNUMBER(F60),ISNUMBER(H60),H60>0),(F60/H60-1)/(F60/H60+1),"") -> 0.024390244 | N60: =IF(AND(ISNUMBER(F60),ISNUMBER(H60)) ,"BOUNDED","UNBOUNDED") -> BOUNDED | O60: =IF(N60="UNBOUNDED","HOLD",IF(L60>=Inputs!$B$9,"CLOSE","FAIL")) -> FAIL
A61: HC-A-C-FLOW-FATAL_KEYSTONE | B61: HC-A-C | C61: Flow | D61: FATAL_KEYSTONE | E61: t/day | G61: =Inputs!$B$7 -> 0.025 | H61: ='Source Inputs'!I18 -> 900 | I61: =Inputs!$B$8 -> 0.025 | J61: =IF(ISNUMBER(F61),F61*(1-G61),"") | K61: =IF(ISNUMBER(H61),H61*(1+I61),"") -> 922.5 | L61: =IF(AND(ISNUMBER(J61),ISNUMBER(K61),K61>0),J61/K61,"") | M61: =IF(AND(ISNUMBER(F61),ISNUMBER(H61),H61>0),(F61/H61-1)/(F61/H61+1),"") | N61: =IF(AND(ISNUMBER(F61),ISNUMBER(H61)) ,"BOUNDED","UNBOUNDED") -> UNBOUNDED | O61: =IF(N61="UNBOUNDED","HOLD",IF(L61>=Inputs!$B$9,"CLOSE","FAIL")) -> HOLD
A62: HC-A-C-FLOW-COLD_START | B62: HC-A-C | C62: Flow | D62: COLD_START | E62: t/day | G62: =Inputs!$B$7 -> 0.025 | H62: ='Source Inputs'!I18 -> 900 | I62: =Inputs!$B$8 -> 0.025 | J62: =IF(ISNUMBER(F62),F62*(1-G62),"") | K62: =IF(ISNUMBER(H62),H62*(1+I62),"") -> 922.5 | L62: =IF(AND(ISNUMBER(J62),ISNUMBER(K62),K62>0),J62/K62,"") | M62: =IF(AND(ISNUMBER(F62),ISNUMBER(H62),H62>0),(F62/H62-1)/(F62/H62+1),"") | N62: =IF(AND(ISNUMBER(F62),ISNUMBER(H62)) ,"BOUNDED","UNBOUNDED") -> UNBOUNDED | O62: =IF(N62="UNBOUNDED","HOLD",IF(L62>=Inputs!$B$9,"CLOSE","FAIL")) -> HOLD
A63: HC-A-C-THERMAL-NOMINAL | B63: HC-A-C | C63: Thermal | D63: NOMINAL | E63: form-native | G63: =Inputs!$B$7 -> 0.025 | I63: =Inputs!$B$8 -> 0.025 | J63: =IF(ISNUMBER(F63),F63*(1-G63),"") | K63: =IF(ISNUMBER(H63),H63*(1+I63),"") | L63: =IF(AND(ISNUMBER(J63),ISNUMBER(K63),K63>0),J63/K63,"") | M63: =IF(AND(ISNUMBER(F63),ISNUMBER(H63),H63>0),(F63/H63-1)/(F63/H63+1),"") | N63: =IF(AND(ISNUMBER(F63),ISNUMBER(H63)) ,"BOUNDED","UNBOUNDED") -> UNBOUNDED | O63: =IF(N63="UNBOUNDED","HOLD",IF(L63>=Inputs!$B$9,"CLOSE","FAIL")) -> HOLD
A64: HC-A-C-THERMAL-LARGEST_CELL_LOSS | B64: HC-A-C | C64: Thermal | D64: LARGEST_CELL_LOSS | E64: form-native | G64: =Inputs!$B$7 -> 0.025 | I64: =Inputs!$B$8 -> 0.025 | J64: =IF(ISNUMBER(F64),F64*(1-G64),"") | K64: =IF(ISNUMBER(H64),H64*(1+I64),"") | L64: =IF(AND(ISNUMBER(J64),ISNUMBER(K64),K64>0),J64/K64,"") | M64: =IF(AND(ISNUMBER(F64),ISNUMBER(H64),H64>0),(F64/H64-1)/(F64/H64+1),"") | N64: =IF(AND(ISNUMBER(F64),ISNUMBER(H64)) ,"BOUNDED","UNBOUNDED") -> UNBOUNDED | O64: =IF(N64="UNBOUNDED","HOLD",IF(L64>=Inputs!$B$9,"CLOSE","FAIL")) -> HOLD
A65: HC-A-C-THERMAL-FATAL_KEYSTONE | B65: HC-A-C | C65: Thermal | D65: FATAL_KEYSTONE | E65: form-native | G65: =Inputs!$B$7 -> 0.025 | I65: =Inputs!$B$8 -> 0.025 | J65: =IF(ISNUMBER(F65),F65*(1-G65),"") | K65: =IF(ISNUMBER(H65),H65*(1+I65),"") | L65: =IF(AND(ISNUMBER(J65),ISNUMBER(K65),K65>0),J65/K65,"") | M65: =IF(AND(ISNUMBER(F65),ISNUMBER(H65),H65>0),(F65/H65-1)/(F65/H65+1),"") | N65: =IF(AND(ISNUMBER(F65),ISNUMBER(H65)) ,"BOUNDED","UNBOUNDED") -> UNBOUNDED | O65: =IF(N65="UNBOUNDED","HOLD",IF(L65>=Inputs!$B$9,"CLOSE","FAIL")) -> HOLD
A66: HC-A-C-THERMAL-COLD_START | B66: HC-A-C | C66: Thermal | D66: COLD_START | E66: form-native | G66: =Inputs!$B$7 -> 0.025 | I66: =Inputs!$B$8 -> 0.025 | J66: =IF(ISNUMBER(F66),F66*(1-G66),"") | K66: =IF(ISNUMBER(H66),H66*(1+I66),"") | L66: =IF(AND(ISNUMBER(J66),ISNUMBER(K66),K66>0),J66/K66,"") | M66: =IF(AND(ISNUMBER(F66),ISNUMBER(H66),H66>0),(F66/H66-1)/(F66/H66+1),"") | N66: =IF(AND(ISNUMBER(F66),ISNUMBER(H66)) ,"BOUNDED","UNBOUNDED") -> UNBOUNDED | O66: =IF(N66="UNBOUNDED","HOLD",IF(L66>=Inputs!$B$9,"CLOSE","FAIL")) -> HOLD
A67: LF-B-A-SERVICE-NOMINAL | B67: LF-B-A | C67: Service | D67: NOMINAL | E67: thousand m3/day | F67: ='Source Inputs'!H19 -> 39 | G67: =Inputs!$B$7 -> 0.025 | H67: ='Source Inputs'!I19 -> 25 | I67: =Inputs!$B$8 -> 0.025 | J67: =IF(ISNUMBER(F67),F67*(1-G67),"") -> 38.025 | K67: =IF(ISNUMBER(H67),H67*(1+I67),"") -> 25.625 | L67: =IF(AND(ISNUMBER(J67),ISNUMBER(K67),K67>0),J67/K67,"") -> 1.4839024 | M67: =IF(AND(ISNUMBER(F67),ISNUMBER(H67),H67>0),(F67/H67-1)/(F67/H67+1),"") -> 0.21875 | N67: =IF(AND(ISNUMBER(F67),ISNUMBER(H67)) ,"BOUNDED","UNBOUNDED") -> BOUNDED | O67: =IF(N67="UNBOUNDED","HOLD",IF(L67>=Inputs!$B$9,"CLOSE","FAIL")) -> CLOSE
A68: LF-B-A-SERVICE-LARGEST_CELL_LOSS | B68: LF-B-A | C68: Service | D68: LARGEST_CELL_LOSS | E68: thousand m3/day | F68: ='Source Inputs'!J19 -> 26 | G68: =Inputs!$B$7 -> 0.025 | H68: ='Source Inputs'!K19 -> 25 | I68: =Inputs!$B$8 -> 0.025 | J68: =IF(ISNUMBER(F68),F68*(1-G68),"") -> 25.35 | K68: =IF(ISNUMBER(H68),H68*(1+I68),"") -> 25.625 | L68: =IF(AND(ISNUMBER(J68),ISNUMBER(K68),K68>0),J68/K68,"") -> 0.98926829 | M68: =IF(AND(ISNUMBER(F68),ISNUMBER(H68),H68>0),(F68/H68-1)/(F68/H68+1),"") -> 0.019607843 | N68: =IF(AND(ISNUMBER(F68),ISNUMBER(H68)) ,"BOUNDED","UNBOUNDED") -> BOUNDED | O68: =IF(N68="UNBOUNDED","HOLD",IF(L68>=Inputs!$B$9,"CLOSE","FAIL")) -> FAIL
A69: LF-B-A-SERVICE-FATAL_KEYSTONE | B69: LF-B-A | C69: Service | D69: FATAL_KEYSTONE | E69: thousand m3/day | G69: =Inputs!$B$7 -> 0.025 | H69: ='Source Inputs'!I19 -> 25 | I69: =Inputs!$B$8 -> 0.025 | J69: =IF(ISNUMBER(F69),F69*(1-G69),"") | K69: =IF(ISNUMBER(H69),H69*(1+I69),"") -> 25.625 | L69: =IF(AND(ISNUMBER(J69),ISNUMBER(K69),K69>0),J69/K69,"") | M69: =IF(AND(ISNUMBER(F69),ISNUMBER(H69),H69>0),(F69/H69-1)/(F69/H69+1),"") | N69: =IF(AND(ISNUMBER(F69),ISNUMBER(H69)) ,"BOUNDED","UNBOUNDED") -> UNBOUNDED | O69: =IF(N69="UNBOUNDED","HOLD",IF(L69>=Inputs!$B$9,"CLOSE","FAIL")) -> HOLD
A70: LF-B-A-SERVICE-COLD_START | B70: LF-B-A | C70: Service | D70: COLD_START | E70: thousand m3/day | G70: =Inputs!$B$7 -> 0.025 | H70: ='Source Inputs'!I19 -> 25 | I70: =Inputs!$B$8 -> 0.025 | J70: =IF(ISNUMBER(F70),F70*(1-G70),"") | K70: =IF(ISNUMBER(H70),H70*(1+I70),"") -> 25.625 | L70: =IF(AND(ISNUMBER(J70),ISNUMBER(K70),K70>0),J70/K70,"") | M70: =IF(AND(ISNUMBER(F70),ISNUMBER(H70),H70>0),(F70/H70-1)/(F70/H70+1),"") | N70: =IF(AND(ISNUMBER(F70),ISNUMBER(H70)) ,"BOUNDED","UNBOUNDED") -> UNBOUNDED | O70: =IF(N70="UNBOUNDED","HOLD",IF(L70>=Inputs!$B$9,"CLOSE","FAIL")) -> HOLD
A71: LF-B-A-MASS-NOMINAL | B71: LF-B-A | C71: Mass | D71: NOMINAL | E71: kt | F71: ='Source Inputs'!H20 -> 35.91 | G71: =Inputs!$B$7 -> 0.025 | H71: ='Source Inputs'!I20 -> 31.075 | I71: =Inputs!$B$8 -> 0.025 | J71: =IF(ISNUMBER(F71),F71*(1-G71),"") -> 35.01225 | K71: =IF(ISNUMBER(H71),H71*(1+I71),"") -> 31.851875 | L71: =IF(AND(ISNUMBER(J71),ISNUMBER(K71),K71>0),J71/K71,"") -> 1.099221 | M71: =IF(AND(ISNUMBER(F71),ISNUMBER(H71),H71>0),(F71/H71-1)/(F71/H71+1),"") -> 0.072180339 | N71: =IF(AND(ISNUMBER(F71),ISNUMBER(H71)) ,"BOUNDED","UNBOUNDED") -> BOUNDED | O71: =IF(N71="UNBOUNDED","HOLD",IF(L71>=Inputs!$B$9,"CLOSE","FAIL")) -> CLOSE
A72: LF-B-A-MASS-LARGEST_CELL_LOSS | B72: LF-B-A | C72: Mass | D72: LARGEST_CELL_LOSS | E72: kt | F72: ='Source Inputs'!J20 -> 31.92 | G72: =Inputs!$B$7 -> 0.025 | H72: ='Source Inputs'!K20 -> 31.075 | I72: =Inputs!$B$8 -> 0.025 | J72: =IF(ISNUMBER(F72),F72*(1-G72),"") -> 31.122 | K72: =IF(ISNUMBER(H72),H72*(1+I72),"") -> 31.851875 | L72: =IF(AND(ISNUMBER(J72),ISNUMBER(K72),K72>0),J72/K72,"") -> 0.97708534 | M72: =IF(AND(ISNUMBER(F72),ISNUMBER(H72),H72>0),(F72/H72-1)/(F72/H72+1),"") -> 0.013413763 | N72: =IF(AND(ISNUMBER(F72),ISNUMBER(H72)) ,"BOUNDED","UNBOUNDED") -> BOUNDED | O72: =IF(N72="UNBOUNDED","HOLD",IF(L72>=Inputs!$B$9,"CLOSE","FAIL")) -> FAIL
A73: LF-B-A-MASS-FATAL_KEYSTONE | B73: LF-B-A | C73: Mass | D73: FATAL_KEYSTONE | E73: kt | G73: =Inputs!$B$7 -> 0.025 | H73: ='Source Inputs'!I20 -> 31.075 | I73: =Inputs!$B$8 -> 0.025 | J73: =IF(ISNUMBER(F73),F73*(1-G73),"") | K73: =IF(ISNUMBER(H73),H73*(1+I73),"") -> 31.851875 | L73: =IF(AND(ISNUMBER(J73),ISNUMBER(K73),K73>0),J73/K73,"") | M73: =IF(AND(ISNUMBER(F73),ISNUMBER(H73),H73>0),(F73/H73-1)/(F73/H73+1),"") | N73: =IF(AND(ISNUMBER(F73),ISNUMBER(H73)) ,"BOUNDED","UNBOUNDED") -> UNBOUNDED | O73: =IF(N73="UNBOUNDED","HOLD",IF(L73>=Inputs!$B$9,"CLOSE","FAIL")) -> HOLD
A74: LF-B-A-MASS-COLD_START | B74: LF-B-A | C74: Mass | D74: COLD_START | E74: kt | G74: =Inputs!$B$7 -> 0.025 | H74: ='Source Inputs'!I20 -> 31.075 | I74: =Inputs!$B$8 -> 0.025 | J74: =IF(ISNUMBER(F74),F74*(1-G74),"") | K74: =IF(ISNUMBER(H74),H74*(1+I74),"") -> 31.851875 | L74: =IF(AND(ISNUMBER(J74),ISNUMBER(K74),K74>0),J74/K74,"") | M74: =IF(AND(ISNUMBER(F74),ISNUMBER(H74),H74>0),(F74/H74-1)/(F74/H74+1),"") | N74: =IF(AND(ISNUMBER(F74),ISNUMBER(H74)) ,"BOUNDED","UNBOUNDED") -> UNBOUNDED | O74: =IF(N74="UNBOUNDED","HOLD",IF(L74>=Inputs!$B$9,"CLOSE","FAIL")) -> HOLD
A75: LF-B-A-ENERGY-NOMINAL | B75: LF-B-A | C75: Energy | D75: NOMINAL | E75: MW | F75: ='Source Inputs'!H21 -> 52 | G75: =Inputs!$B$7 -> 0.025 | H75: ='Source Inputs'!I21 -> 37.351042 | I75: =Inputs!$B$8 -> 0.025 | J75: =IF(ISNUMBER(F75),F75*(1-G75),"") -> 50.7 | K75: =IF(ISNUMBER(H75),H75*(1+I75),"") -> 38.284818 | L75: =IF(AND(ISNUMBER(J75),ISNUMBER(K75),K75>0),J75/K75,"") -> 1.3242847 | M75: =IF(AND(ISNUMBER(F75),ISNUMBER(H75),H75>0),(F75/H75-1)/(F75/H75+1),"") -> 0.16394838 | N75: =IF(AND(ISNUMBER(F75),ISNUMBER(H75)) ,"BOUNDED","UNBOUNDED") -> BOUNDED | O75: =IF(N75="UNBOUNDED","HOLD",IF(L75>=Inputs!$B$9,"CLOSE","FAIL")) -> CLOSE
A76: LF-B-A-ENERGY-LARGEST_CELL_LOSS | B76: LF-B-A | C76: Energy | D76: LARGEST_CELL_LOSS | E76: MW | F76: ='Source Inputs'!J21 -> 39 | G76: =Inputs!$B$7 -> 0.025 | H76: ='Source Inputs'!K21 -> 37.351042 | I76: =Inputs!$B$8 -> 0.025 | J76: =IF(ISNUMBER(F76),F76*(1-G76),"") -> 38.025 | K76: =IF(ISNUMBER(H76),H76*(1+I76),"") -> 38.284818 | L76: =IF(AND(ISNUMBER(J76),ISNUMBER(K76),K76>0),J76/K76,"") -> 0.99321356 | M76: =IF(AND(ISNUMBER(F76),ISNUMBER(H76),H76>0),(F76/H76-1)/(F76/H76+1),"") -> 0.021597064 | N76: =IF(AND(ISNUMBER(F76),ISNUMBER(H76)) ,"BOUNDED","UNBOUNDED") -> BOUNDED | O76: =IF(N76="UNBOUNDED","HOLD",IF(L76>=Inputs!$B$9,"CLOSE","FAIL")) -> FAIL
A77: LF-B-A-ENERGY-FATAL_KEYSTONE | B77: LF-B-A | C77: Energy | D77: FATAL_KEYSTONE | E77: MW | G77: =Inputs!$B$7 -> 0.025 | H77: ='Source Inputs'!I21 -> 37.351042 | I77: =Inputs!$B$8 -> 0.025 | J77: =IF(ISNUMBER(F77),F77*(1-G77),"") | K77: =IF(ISNUMBER(H77),H77*(1+I77),"") -> 38.284818 | L77: =IF(AND(ISNUMBER(J77),ISNUMBER(K77),K77>0),J77/K77,"") | M77: =IF(AND(ISNUMBER(F77),ISNUMBER(H77),H77>0),(F77/H77-1)/(F77/H77+1),"") | N77: =IF(AND(ISNUMBER(F77),ISNUMBER(H77)) ,"BOUNDED","UNBOUNDED") -> UNBOUNDED | O77: =IF(N77="UNBOUNDED","HOLD",IF(L77>=Inputs!$B$9,"CLOSE","FAIL")) -> HOLD
A78: LF-B-A-ENERGY-COLD_START | B78: LF-B-A | C78: Energy | D78: COLD_START | E78: MW | G78: =Inputs!$B$7 -> 0.025 | H78: ='Source Inputs'!I21 -> 37.351042 | I78: =Inputs!$B$8 -> 0.025 | J78: =IF(ISNUMBER(F78),F78*(1-G78),"") | K78: =IF(ISNUMBER(H78),H78*(1+I78),"") -> 38.284818 | L78: =IF(AND(ISNUMBER(J78),ISNUMBER(K78),K78>0),J78/K78,"") | M78: =IF(AND(ISNUMBER(F78),ISNUMBER(H78),H78>0),(F78/H78-1)/(F78/H78+1),"") | N78: =IF(AND(ISNUMBER(F78),ISNUMBER(H78)) ,"BOUNDED","UNBOUNDED") -> UNBOUNDED | O78: =IF(N78="UNBOUNDED","HOLD",IF(L78>=Inputs!$B$9,"CLOSE","FAIL")) -> HOLD
A79: LF-B-A-FLOW-NOMINAL | B79: LF-B-A | C79: Flow | D79: NOMINAL | E79: thousand m3/day | F79: ='Source Inputs'!H22 -> 30.9 | G79: =Inputs!$B$7 -> 0.025 | H79: ='Source Inputs'!I22 -> 20 | I79: =Inputs!$B$8 -> 0.025 | J79: =IF(ISNUMBER(F79),F79*(1-G79),"") -> 30.1275 | K79: =IF(ISNUMBER(H79),H79*(1+I79),"") -> 20.5 | L79: =IF(AND(ISNUMBER(J79),ISNUMBER(K79),K79>0),J79/K79,"") -> 1.4696341 | M79: =IF(AND(ISNUMBER(F79),ISNUMBER(H79),H79>0),(F79/H79-1)/(F79/H79+1),"") -> 0.21414538 | N79: =IF(AND(ISNUMBER(F79),ISNUMBER(H79)) ,"BOUNDED","UNBOUNDED") -> BOUNDED | O79: =IF(N79="UNBOUNDED","HOLD",IF(L79>=Inputs!$B$9,"CLOSE","FAIL")) -> CLOSE
A80: LF-B-A-FLOW-LARGEST_CELL_LOSS | B80: LF-B-A | C80: Flow | D80: LARGEST_CELL_LOSS | E80: thousand m3/day | F80: ='Source Inputs'!J22 -> 20.6 | G80: =Inputs!$B$7 -> 0.025 | H80: ='Source Inputs'!K22 -> 20 | I80: =Inputs!$B$8 -> 0.025 | J80: =IF(ISNUMBER(F80),F80*(1-G80),"") -> 20.085 | K80: =IF(ISNUMBER(H80),H80*(1+I80),"") -> 20.5 | L80: =IF(AND(ISNUMBER(J80),ISNUMBER(K80),K80>0),J80/K80,"") -> 0.9797561 | M80: =IF(AND(ISNUMBER(F80),ISNUMBER(H80),H80>0),(F80/H80-1)/(F80/H80+1),"") -> 0.014778325 | N80: =IF(AND(ISNUMBER(F80),ISNUMBER(H80)) ,"BOUNDED","UNBOUNDED") -> BOUNDED | O80: =IF(N80="UNBOUNDED","HOLD",IF(L80>=Inputs!$B$9,"CLOSE","FAIL")) -> FAIL
A81: LF-B-A-FLOW-FATAL_KEYSTONE | B81: LF-B-A | C81: Flow | D81: FATAL_KEYSTONE | E81: thousand m3/day | G81: =Inputs!$B$7 -> 0.025 | H81: ='Source Inputs'!I22 -> 20 | I81: =Inputs!$B$8 -> 0.025 | J81: =IF(ISNUMBER(F81),F81*(1-G81),"") | K81: =IF(ISNUMBER(H81),H81*(1+I81),"") -> 20.5 | L81: =IF(AND(ISNUMBER(J81),ISNUMBER(K81),K81>0),J81/K81,"") | M81: =IF(AND(ISNUMBER(F81),ISNUMBER(H81),H81>0),(F81/H81-1)/(F81/H81+1),"") | N81: =IF(AND(ISNUMBER(F81),ISNUMBER(H81)) ,"BOUNDED","UNBOUNDED") -> UNBOUNDED | O81: =IF(N81="UNBOUNDED","HOLD",IF(L81>=Inputs!$B$9,"CLOSE","FAIL")) -> HOLD
A82: LF-B-A-FLOW-COLD_START | B82: LF-B-A | C82: Flow | D82: COLD_START | E82: thousand m3/day | G82: =Inputs!$B$7 -> 0.025 | H82: ='Source Inputs'!I22 -> 20 | I82: =Inputs!$B$8 -> 0.025 | J82: =IF(ISNUMBER(F82),F82*(1-G82),"") | K82: =IF(ISNUMBER(H82),H82*(1+I82),"") -> 20.5 | L82: =IF(AND(ISNUMBER(J82),ISNUMBER(K82),K82>0),J82/K82,"") | M82: =IF(AND(ISNUMBER(F82),ISNUMBER(H82),H82>0),(F82/H82-1)/(F82/H82+1),"") | N82: =IF(AND(ISNUMBER(F82),ISNUMBER(H82)) ,"BOUNDED","UNBOUNDED") -> UNBOUNDED | O82: =IF(N82="UNBOUNDED","HOLD",IF(L82>=Inputs!$B$9,"CLOSE","FAIL")) -> HOLD
A83: LF-B-A-THERMAL-NOMINAL | B83: LF-B-A | C83: Thermal | D83: NOMINAL | E83: form-native | G83: =Inputs!$B$7 -> 0.025 | I83: =Inputs!$B$8 -> 0.025 | J83: =IF(ISNUMBER(F83),F83*(1-G83),"") | K83: =IF(ISNUMBER(H83),H83*(1+I83),"") | L83: =IF(AND(ISNUMBER(J83),ISNUMBER(K83),K83>0),J83/K83,"") | M83: =IF(AND(ISNUMBER(F83),ISNUMBER(H83),H83>0),(F83/H83-1)/(F83/H83+1),"") | N83: =IF(AND(ISNUMBER(F83),ISNUMBER(H83)) ,"BOUNDED","UNBOUNDED") -> UNBOUNDED | O83: =IF(N83="UNBOUNDED","HOLD",IF(L83>=Inputs!$B$9,"CLOSE","FAIL")) -> HOLD
A84: LF-B-A-THERMAL-LARGEST_CELL_LOSS | B84: LF-B-A | C84: Thermal | D84: LARGEST_CELL_LOSS | E84: form-native | G84: =Inputs!$B$7 -> 0.025 | I84: =Inputs!$B$8 -> 0.025 | J84: =IF(ISNUMBER(F84),F84*(1-G84),"") | K84: =IF(ISNUMBER(H84),H84*(1+I84),"") | L84: =IF(AND(ISNUMBER(J84),ISNUMBER(K84),K84>0),J84/K84,"") | M84: =IF(AND(ISNUMBER(F84),ISNUMBER(H84),H84>0),(F84/H84-1)/(F84/H84+1),"") | N84: =IF(AND(ISNUMBER(F84),ISNUMBER(H84)) ,"BOUNDED","UNBOUNDED") -> UNBOUNDED | O84: =IF(N84="UNBOUNDED","HOLD",IF(L84>=Inputs!$B$9,"CLOSE","FAIL")) -> HOLD
A85: LF-B-A-THERMAL-FATAL_KEYSTONE | B85: LF-B-A | C85: Thermal | D85: FATAL_KEYSTONE | E85: form-native | G85: =Inputs!$B$7 -> 0.025 | I85: =Inputs!$B$8 -> 0.025 | J85: =IF(ISNUMBER(F85),F85*(1-G85),"") | K85: =IF(ISNUMBER(H85),H85*(1+I85),"") | L85: =IF(AND(ISNUMBER(J85),ISNUMBER(K85),K85>0),J85/K85,"") | M85: =IF(AND(ISNUMBER(F85),ISNUMBER(H85),H85>0),(F85/H85-1)/(F85/H85+1),"") | N85: =IF(AND(ISNUMBER(F85),ISNUMBER(H85)) ,"BOUNDED","UNBOUNDED") -> UNBOUNDED | O85: =IF(N85="UNBOUNDED","HOLD",IF(L85>=Inputs!$B$9,"CLOSE","FAIL")) -> HOLD
A86: LF-B-A-THERMAL-COLD_START | B86: LF-B-A | C86: Thermal | D86: COLD_START | E86: form-native | G86: =Inputs!$B$7 -> 0.025 | I86: =Inputs!$B$8 -> 0.025 | J86: =IF(ISNUMBER(F86),F86*(1-G86),"") | K86: =IF(ISNUMBER(H86),H86*(1+I86),"") | L86: =IF(AND(ISNUMBER(J86),ISNUMBER(K86),K86>0),J86/K86,"") | M86: =IF(AND(ISNUMBER(F86),ISNUMBER(H86),H86>0),(F86/H86-1)/(F86/H86+1),"") | N86: =IF(AND(ISNUMBER(F86),ISNUMBER(H86)) ,"BOUNDED","UNBOUNDED") -> UNBOUNDED | O86: =IF(N86="UNBOUNDED","HOLD",IF(L86>=Inputs!$B$9,"CLOSE","FAIL")) -> HOLD
A87: HU-A-B-SERVICE-NOMINAL | B87: HU-A-B | C87: Service | D87: NOMINAL | E87: ratio | F87: ='Source Inputs'!H23 -> 1.28 | G87: =Inputs!$B$7 -> 0.025 | H87: ='Source Inputs'!I23 -> 1 | I87: =Inputs!$B$8 -> 0.025 | J87: =IF(ISNUMBER(F87),F87*(1-G87),"") -> 1.248 | K87: =IF(ISNUMBER(H87),H87*(1+I87),"") -> 1.025 | L87: =IF(AND(ISNUMBER(J87),ISNUMBER(K87),K87>0),J87/K87,"") -> 1.217561 | M87: =IF(AND(ISNUMBER(F87),ISNUMBER(H87),H87>0),(F87/H87-1)/(F87/H87+1),"") -> 0.12280702 | N87: =IF(AND(ISNUMBER(F87),ISNUMBER(H87)) ,"BOUNDED","UNBOUNDED") -> BOUNDED | O87: =IF(N87="UNBOUNDED","HOLD",IF(L87>=Inputs!$B$9,"CLOSE","FAIL")) -> CLOSE
A88: HU-A-B-SERVICE-LARGEST_CELL_LOSS | B88: HU-A-B | C88: Service | D88: LARGEST_CELL_LOSS | E88: ratio | F88: ='Source Inputs'!J23 -> 1.032 | G88: =Inputs!$B$7 -> 0.025 | H88: ='Source Inputs'!K23 -> 1 | I88: =Inputs!$B$8 -> 0.025 | J88: =IF(ISNUMBER(F88),F88*(1-G88),"") -> 1.0062 | K88: =IF(ISNUMBER(H88),H88*(1+I88),"") -> 1.025 | L88: =IF(AND(ISNUMBER(J88),ISNUMBER(K88),K88>0),J88/K88,"") -> 0.98165854 | M88: =IF(AND(ISNUMBER(F88),ISNUMBER(H88),H88>0),(F88/H88-1)/(F88/H88+1),"") -> 0.015748031 | N88: =IF(AND(ISNUMBER(F88),ISNUMBER(H88)) ,"BOUNDED","UNBOUNDED") -> BOUNDED | O88: =IF(N88="UNBOUNDED","HOLD",IF(L88>=Inputs!$B$9,"CLOSE","FAIL")) -> FAIL
A89: HU-A-B-SERVICE-FATAL_KEYSTONE | B89: HU-A-B | C89: Service | D89: FATAL_KEYSTONE | E89: ratio | G89: =Inputs!$B$7 -> 0.025 | H89: ='Source Inputs'!I23 -> 1 | I89: =Inputs!$B$8 -> 0.025 | J89: =IF(ISNUMBER(F89),F89*(1-G89),"") | K89: =IF(ISNUMBER(H89),H89*(1+I89),"") -> 1.025 | L89: =IF(AND(ISNUMBER(J89),ISNUMBER(K89),K89>0),J89/K89,"") | M89: =IF(AND(ISNUMBER(F89),ISNUMBER(H89),H89>0),(F89/H89-1)/(F89/H89+1),"") | N89: =IF(AND(ISNUMBER(F89),ISNUMBER(H89)) ,"BOUNDED","UNBOUNDED") -> UNBOUNDED | O89: =IF(N89="UNBOUNDED","HOLD",IF(L89>=Inputs!$B$9,"CLOSE","FAIL")) -> HOLD
A90: HU-A-B-SERVICE-COLD_START | B90: HU-A-B | C90: Service | D90: COLD_START | E90: ratio | G90: =Inputs!$B$7 -> 0.025 | H90: ='Source Inputs'!I23 -> 1 | I90: =Inputs!$B$8 -> 0.025 | J90: =IF(ISNUMBER(F90),F90*(1-G90),"") | K90: =IF(ISNUMBER(H90),H90*(1+I90),"") -> 1.025 | L90: =IF(AND(ISNUMBER(J90),ISNUMBER(K90),K90>0),J90/K90,"") | M90: =IF(AND(ISNUMBER(F90),ISNUMBER(H90),H90>0),(F90/H90-1)/(F90/H90+1),"") | N90: =IF(AND(ISNUMBER(F90),ISNUMBER(H90)) ,"BOUNDED","UNBOUNDED") -> UNBOUNDED | O90: =IF(N90="UNBOUNDED","HOLD",IF(L90>=Inputs!$B$9,"CLOSE","FAIL")) -> HOLD
A91: HU-A-B-MASS-NOMINAL | B91: HU-A-B | C91: Mass | D91: NOMINAL | E91: kt | F91: ='Source Inputs'!H24 -> 58.8 | G91: =Inputs!$B$7 -> 0.025 | H91: ='Source Inputs'!I24 -> 50 | I91: =Inputs!$B$8 -> 0.025 | J91: =IF(ISNUMBER(F91),F91*(1-G91),"") -> 57.33 | K91: =IF(ISNUMBER(H91),H91*(1+I91),"") -> 51.25 | L91: =IF(AND(ISNUMBER(J91),ISNUMBER(K91),K91>0),J91/K91,"") -> 1.1186341 | M91: =IF(AND(ISNUMBER(F91),ISNUMBER(H91),H91>0),(F91/H91-1)/(F91/H91+1),"") -> 0.080882353 | N91: =IF(AND(ISNUMBER(F91),ISNUMBER(H91)) ,"BOUNDED","UNBOUNDED") -> BOUNDED | O91: =IF(N91="UNBOUNDED","HOLD",IF(L91>=Inputs!$B$9,"CLOSE","FAIL")) -> CLOSE
A92: HU-A-B-MASS-LARGEST_CELL_LOSS | B92: HU-A-B | C92: Mass | D92: LARGEST_CELL_LOSS | E92: kt | F92: ='Source Inputs'!J24 -> 51.45 | G92: =Inputs!$B$7 -> 0.025 | H92: ='Source Inputs'!K24 -> 50 | I92: =Inputs!$B$8 -> 0.025 | J92: =IF(ISNUMBER(F92),F92*(1-G92),"") -> 50.16375 | K92: =IF(ISNUMBER(H92),H92*(1+I92),"") -> 51.25 | L92: =IF(AND(ISNUMBER(J92),ISNUMBER(K92),K92>0),J92/K92,"") -> 0.97880488 | M92: =IF(AND(ISNUMBER(F92),ISNUMBER(H92),H92>0),(F92/H92-1)/(F92/H92+1),"") -> 0.014292755 | N92: =IF(AND(ISNUMBER(F92),ISNUMBER(H92)) ,"BOUNDED","UNBOUNDED") -> BOUNDED | O92: =IF(N92="UNBOUNDED","HOLD",IF(L92>=Inputs!$B$9,"CLOSE","FAIL")) -> FAIL
A93: HU-A-B-MASS-FATAL_KEYSTONE | B93: HU-A-B | C93: Mass | D93: FATAL_KEYSTONE | E93: kt | G93: =Inputs!$B$7 -> 0.025 | H93: ='Source Inputs'!I24 -> 50 | I93: =Inputs!$B$8 -> 0.025 | J93: =IF(ISNUMBER(F93),F93*(1-G93),"") | K93: =IF(ISNUMBER(H93),H93*(1+I93),"") -> 51.25 | L93: =IF(AND(ISNUMBER(J93),ISNUMBER(K93),K93>0),J93/K93,"") | M93: =IF(AND(ISNUMBER(F93),ISNUMBER(H93),H93>0),(F93/H93-1)/(F93/H93+1),"") | N93: =IF(AND(ISNUMBER(F93),ISNUMBER(H93)) ,"BOUNDED","UNBOUNDED") -> UNBOUNDED | O93: =IF(N93="UNBOUNDED","HOLD",IF(L93>=Inputs!$B$9,"CLOSE","FAIL")) -> HOLD
A94: HU-A-B-MASS-COLD_START | B94: HU-A-B | C94: Mass | D94: COLD_START | E94: kt | G94: =Inputs!$B$7 -> 0.025 | H94: ='Source Inputs'!I24 -> 50 | I94: =Inputs!$B$8 -> 0.025 | J94: =IF(ISNUMBER(F94),F94*(1-G94),"") | K94: =IF(ISNUMBER(H94),H94*(1+I94),"") -> 51.25 | L94: =IF(AND(ISNUMBER(J94),ISNUMBER(K94),K94>0),J94/K94,"") | M94: =IF(AND(ISNUMBER(F94),ISNUMBER(H94),H94>0),(F94/H94-1)/(F94/H94+1),"") | N94: =IF(AND(ISNUMBER(F94),ISNUMBER(H94)) ,"BOUNDED","UNBOUNDED") -> UNBOUNDED | O94: =IF(N94="UNBOUNDED","HOLD",IF(L94>=Inputs!$B$9,"CLOSE","FAIL")) -> HOLD
A95: HU-A-B-ENERGY-NOMINAL | B95: HU-A-B | C95: Energy | D95: NOMINAL | E95: MW | F95: ='Source Inputs'!H25 -> 66 | G95: =Inputs!$B$7 -> 0.025 | H95: ='Source Inputs'!I25 -> 52 | I95: =Inputs!$B$8 -> 0.025 | J95: =IF(ISNUMBER(F95),F95*(1-G95),"") -> 64.35 | K95: =IF(ISNUMBER(H95),H95*(1+I95),"") -> 53.3 | L95: =IF(AND(ISNUMBER(J95),ISNUMBER(K95),K95>0),J95/K95,"") -> 1.2073171 | M95: =IF(AND(ISNUMBER(F95),ISNUMBER(H95),H95>0),(F95/H95-1)/(F95/H95+1),"") -> 0.11864407 | N95: =IF(AND(ISNUMBER(F95),ISNUMBER(H95)) ,"BOUNDED","UNBOUNDED") -> BOUNDED | O95: =IF(N95="UNBOUNDED","HOLD",IF(L95>=Inputs!$B$9,"CLOSE","FAIL")) -> CLOSE
A96: HU-A-B-ENERGY-LARGEST_CELL_LOSS | B96: HU-A-B | C96: Energy | D96: LARGEST_CELL_LOSS | E96: MW | F96: ='Source Inputs'!J25 -> 55 | G96: =Inputs!$B$7 -> 0.025 | H96: ='Source Inputs'!K25 -> 52 | I96: =Inputs!$B$8 -> 0.025 | J96: =IF(ISNUMBER(F96),F96*(1-G96),"") -> 53.625 | K96: =IF(ISNUMBER(H96),H96*(1+I96),"") -> 53.3 | L96: =IF(AND(ISNUMBER(J96),ISNUMBER(K96),K96>0),J96/K96,"") -> 1.0060976 | M96: =IF(AND(ISNUMBER(F96),ISNUMBER(H96),H96>0),(F96/H96-1)/(F96/H96+1),"") -> 0.028037383 | N96: =IF(AND(ISNUMBER(F96),ISNUMBER(H96)) ,"BOUNDED","UNBOUNDED") -> BOUNDED | O96: =IF(N96="UNBOUNDED","HOLD",IF(L96>=Inputs!$B$9,"CLOSE","FAIL")) -> CLOSE
A97: HU-A-B-ENERGY-FATAL_KEYSTONE | B97: HU-A-B | C97: Energy | D97: FATAL_KEYSTONE | E97: MW | G97: =Inputs!$B$7 -> 0.025 | H97: ='Source Inputs'!I25 -> 52 | I97: =Inputs!$B$8 -> 0.025 | J97: =IF(ISNUMBER(F97),F97*(1-G97),"") | K97: =IF(ISNUMBER(H97),H97*(1+I97),"") -> 53.3 | L97: =IF(AND(ISNUMBER(J97),ISNUMBER(K97),K97>0),J97/K97,"") | M97: =IF(AND(ISNUMBER(F97),ISNUMBER(H97),H97>0),(F97/H97-1)/(F97/H97+1),"") | N97: =IF(AND(ISNUMBER(F97),ISNUMBER(H97)) ,"BOUNDED","UNBOUNDED") -> UNBOUNDED | O97: =IF(N97="UNBOUNDED","HOLD",IF(L97>=Inputs!$B$9,"CLOSE","FAIL")) -> HOLD
A98: HU-A-B-ENERGY-COLD_START | B98: HU-A-B | C98: Energy | D98: COLD_START | E98: MW | G98: =Inputs!$B$7 -> 0.025 | H98: ='Source Inputs'!I25 -> 52 | I98: =Inputs!$B$8 -> 0.025 | J98: =IF(ISNUMBER(F98),F98*(1-G98),"") | K98: =IF(ISNUMBER(H98),H98*(1+I98),"") -> 53.3 | L98: =IF(AND(ISNUMBER(J98),ISNUMBER(K98),K98>0),J98/K98,"") | M98: =IF(AND(ISNUMBER(F98),ISNUMBER(H98),H98>0),(F98/H98-1)/(F98/H98+1),"") | N98: =IF(AND(ISNUMBER(F98),ISNUMBER(H98)) ,"BOUNDED","UNBOUNDED") -> UNBOUNDED | O98: =IF(N98="UNBOUNDED","HOLD",IF(L98>=Inputs!$B$9,"CLOSE","FAIL")) -> HOLD
A99: HU-A-B-FLOW-NOMINAL | B99: HU-A-B | C99: Flow | D99: NOMINAL | E99: t/day | F99: ='Source Inputs'!H26 -> 441 | G99: =Inputs!$B$7 -> 0.025 | H99: ='Source Inputs'!I26 -> 350 | I99: =Inputs!$B$8 -> 0.025 | J99: =IF(ISNUMBER(F99),F99*(1-G99),"") -> 429.975 | K99: =IF(ISNUMBER(H99),H99*(1+I99),"") -> 358.75 | L99: =IF(AND(ISNUMBER(J99),ISNUMBER(K99),K99>0),J99/K99,"") -> 1.1985366 | M99: =IF(AND(ISNUMBER(F99),ISNUMBER(H99),H99>0),(F99/H99-1)/(F99/H99+1),"") -> 0.11504425 | N99: =IF(AND(ISNUMBER(F99),ISNUMBER(H99)) ,"BOUNDED","UNBOUNDED") -> BOUNDED | O99: =IF(N99="UNBOUNDED","HOLD",IF(L99>=Inputs!$B$9,"CLOSE","FAIL")) -> CLOSE
A100: HU-A-B-FLOW-LARGEST_CELL_LOSS | B100: HU-A-B | C100: Flow | D100: LARGEST_CELL_LOSS | E100: t/day | F100: ='Source Inputs'!J26 -> 367.5 | G100: =Inputs!$B$7 -> 0.025 | H100: ='Source Inputs'!K26 -> 350 | I100: =Inputs!$B$8 -> 0.025 | J100: =IF(ISNUMBER(F100),F100*(1-G100),"") -> 358.3125 | K100: =IF(ISNUMBER(H100),H100*(1+I100),"") -> 358.75 | L100: =IF(AND(ISNUMBER(J100),ISNUMBER(K100),K100>0),J100/K100,"") -> 0.99878049 | M100: =IF(AND(ISNUMBER(F100),ISNUMBER(H100),H100>0),(F100/H100-1)/(F100/H100+1),"") -> 0.024390244 | N100: =IF(AND(ISNUMBER(F100),ISNUMBER(H100)) ,"BOUNDED","UNBOUNDED") -> BOUNDED | O100: =IF(N100="UNBOUNDED","HOLD",IF(L100>=Inputs!$B$9,"CLOSE","FAIL")) -> FAIL
A101: HU-A-B-FLOW-FATAL_KEYSTONE | B101: HU-A-B | C101: Flow | D101: FATAL_KEYSTONE | E101: t/day | G101: =Inputs!$B$7 -> 0.025 | H101: ='Source Inputs'!I26 -> 350 | I101: =Inputs!$B$8 -> 0.025 | J101: =IF(ISNUMBER(F101),F101*(1-G101),"") | K101: =IF(ISNUMBER(H101),H101*(1+I101),"") -> 358.75 | L101: =IF(AND(ISNUMBER(J101),ISNUMBER(K101),K101>0),J101/K101,"") | M101: =IF(AND(ISNUMBER(F101),ISNUMBER(H101),H101>0),(F101/H101-1)/(F101/H101+1),"") | N101: =IF(AND(ISNUMBER(F101),ISNUMBER(H101)) ,"BOUNDED","UNBOUNDED") -> UNBOUNDED | O101: =IF(N101="UNBOUNDED","HOLD",IF(L101>=Inputs!$B$9,"CLOSE","FAIL")) -> HOLD
A102: HU-A-B-FLOW-COLD_START | B102: HU-A-B | C102: Flow | D102: COLD_START | E102: t/day | G102: =Inputs!$B$7 -> 0.025 | H102: ='Source Inputs'!I26 -> 350 | I102: =Inputs!$B$8 -> 0.025 | J102: =IF(ISNUMBER(F102),F102*(1-G102),"") | K102: =IF(ISNUMBER(H102),H102*(1+I102),"") -> 358.75 | L102: =IF(AND(ISNUMBER(J102),ISNUMBER(K102),K102>0),J102/K102,"") | M102: =IF(AND(ISNUMBER(F102),ISNUMBER(H102),H102>0),(F102/H102-1)/(F102/H102+1),"") | N102: =IF(AND(ISNUMBER(F102),ISNUMBER(H102)) ,"BOUNDED","UNBOUNDED") -> UNBOUNDED | O102: =IF(N102="UNBOUNDED","HOLD",IF(L102>=Inputs!$B$9,"CLOSE","FAIL")) -> HOLD
A103: HU-A-B-THERMAL-NOMINAL | B103: HU-A-B | C103: Thermal | D103: NOMINAL | E103: form-native | G103: =Inputs!$B$7 -> 0.025 | I103: =Inputs!$B$8 -> 0.025 | J103: =IF(ISNUMBER(F103),F103*(1-G103),"") | K103: =IF(ISNUMBER(H103),H103*(1+I103),"") | L103: =IF(AND(ISNUMBER(J103),ISNUMBER(K103),K103>0),J103/K103,"") | M103: =IF(AND(ISNUMBER(F103),ISNUMBER(H103),H103>0),(F103/H103-1)/(F103/H103+1),"") | N103: =IF(AND(ISNUMBER(F103),ISNUMBER(H103)) ,"BOUNDED","UNBOUNDED") -> UNBOUNDED | O103: =IF(N103="UNBOUNDED","HOLD",IF(L103>=Inputs!$B$9,"CLOSE","FAIL")) -> HOLD
...

Sheet Loss Rating Orders
A2: Largest-cell-loss rating orders
A4: The target is the minimum raw surviving capacity required for independent 2.5% downside and 2.5% requirement upside.
A6: Order | B6: Form | C6: Account | D6: Unit | E6: Current survivor capacity | F6: Loss requirement | G6: Current raw ratio | H6: Maximum symmetric half-width | I6: Required raw ratio | J6: Required survivor capacity | K6: Capacity gap | L6: Required uplift | M6: State | N6: Engineering instruction
A7: ET-A-A-SERVICE-RATING | B7: ET-A-A | C7: Service | D7: t/h | E7: ='Source Inputs'!J7 -> 241 | F7: ='Source Inputs'!K7 -> 234.58333 | G7: =E7/F7 -> 1.0273535 | H7: =(G7-1)/(G7+1) -> 0.013492203 | I7: =Inputs!$B$10 -> 1.0512821 | J7: =F7*I7 -> 246.61325 | K7: =MAX(0,J7-E7) -> 5.6132479 | L7: =MAX(0,J7/E7-1) -> 0.023291485 | M7: =IF(E7>=J7,"RETAIN","UPRATE") -> UPRATE | N7: Raise each complete exchange path from 241 to at least 247 t/h before thermal and keystone closure.
A8: ET-A-A-MASS-RATING | B8: ET-A-A | C8: Mass | D8: t | E8: ='Source Inputs'!J8 -> 112000 | F8: ='Source Inputs'!K8 -> 102000 | G8: =E8/F8 -> 1.0980392 | H8: =(G8-1)/(G8+1) -> 0.046728972 | I8: =Inputs!$B$10 -> 1.0512821 | J8: =F8*I8 -> 107230.77 | K8: =MAX(0,J8-E8) -> 0 | L8: =MAX(0,J8/E8-1) -> 0 | M8: =IF(E8>=J8,"RETAIN","UPRATE") -> RETAIN | N8: Meet the form-native mass target without borrowing a sibling coefficient or deleting a cell boundary.
A9: ET-A-A-ENERGY-RATING | B9: ET-A-A | C9: Energy | D9: MW | E9: ='Source Inputs'!J9 -> 100 | F9: ='Source Inputs'!K9 -> 96 | G9: =E9/F9 -> 1.0416667 | H9: =(G9-1)/(G9+1) -> 0.020408163 | I9: =Inputs!$B$10 -> 1.0512821 | J9: =F9*I9 -> 100.92308 | K9: =MAX(0,J9-E9) -> 0.92307692 | L9: =MAX(0,J9/E9-1) -> 0.0092307692 | M9: =IF(E9>=J9,"RETAIN","UPRATE") -> UPRATE | N9: Meet the form-native energy target without borrowing a sibling coefficient or deleting a cell boundary.
A10: ET-A-A-FLOW-RATING | B10: ET-A-A | C10: Flow | D10: t/day | E10: ='Source Inputs'!J10 -> 1260 | F10: ='Source Inputs'!K10 -> 1200 | G10: =E10/F10 -> 1.05 | H10: =(G10-1)/(G10+1) -> 0.024390244 | I10: =Inputs!$B$10 -> 1.0512821 | J10: =F10*I10 -> 1261.5385 | K10: =MAX(0,J10-E10) -> 1.5384615 | L10: =MAX(0,J10/E10-1) -> 0.0012210012 | M10: =IF(E10>=J10,"RETAIN","UPRATE") -> UPRATE | N10: Meet the form-native flow target without borrowing a sibling coefficient or deleting a cell boundary.
A11: CT-C-B-SERVICE-RATING | B11: CT-C-B | C11: Service | D11: ratio | E11: ='Source Inputs'!J11 -> 1.056 | F11: ='Source Inputs'!K11 -> 1 | G11: =E11/F11 -> 1.056 | H11: =(G11-1)/(G11+1) -> 0.027237354 | I11: =Inputs!$B$10 -> 1.0512821 | J11: =F11*I11 -> 1.0512821 | K11: =MAX(0,J11-E11) -> 0 | L11: =MAX(0,J11/E11-1) -> 0 | M11: =IF(E11>=J11,"RETAIN","UPRATE") -> RETAIN | N11: Meet the form-native service target without borrowing a sibling coefficient or deleting a cell boundary.
A12: CT-C-B-MASS-RATING | B12: CT-C-B | C12: Mass | D12: t | E12: ='Source Inputs'!J12 -> 32400 | F12: ='Source Inputs'!K12 -> 31000 | G12: =E12/F12 -> 1.0451613 | H12: =(G12-1)/(G12+1) -> 0.022082019 | I12: =Inputs!$B$10 -> 1.0512821 | J12: =F12*I12 -> 32589.744 | K12: =MAX(0,J12-E12) -> 189.74359 | L12: =MAX(0,J12/E12-1) -> 0.0058562836 | M12: =IF(E12>=J12,"RETAIN","UPRATE") -> UPRATE | N12: Meet the form-native mass target without borrowing a sibling coefficient or deleting a cell boundary.
A13: CT-C-B-ENERGY-RATING | B13: CT-C-B | C13: Energy | D13: MW | E13: ='Source Inputs'!J13 -> 43.2 | F13: ='Source Inputs'!K13 -> 42 | G13: =E13/F13 -> 1.0285714 | H13: =(G13-1)/(G13+1) -> 0.014084507 | I13: =Inputs!$B$10 -> 1.0512821 | J13: =F13*I13 -> 44.153846 | K13: =MAX(0,J13-E13) -> 0.95384615 | L13: =MAX(0,J13/E13-1) -> 0.022079772 | M13: =IF(E13>=J13,"RETAIN","UPRATE") -> UPRATE | N13: Raise each isolated generation cell from 7.20 to at least 7.36 MW before thermal and attachment closure.
A14: CT-C-B-FLOW-RATING | B14: CT-C-B | C14: Flow | D14: t/day | E14: ='Source Inputs'!J14 -> 231 | F14: ='Source Inputs'!K14 -> 220 | G14: =E14/F14 -> 1.05 | H14: =(G14-1)/(G14+1) -> 0.024390244 | I14: =Inputs!$B$10 -> 1.0512821 | J14: =F14*I14 -> 231.28205 | K14: =MAX(0,J14-E14) -> 0.28205128 | L14: =MAX(0,J14/E14-1) -> 0.0012210012 | M14: =IF(E14>=J14,"RETAIN","UPRATE") -> UPRATE | N14: Meet the form-native flow target without borrowing a sibling coefficient or deleting a cell boundary.
A15: HC-A-C-SERVICE-RATING | B15: HC-A-C | C15: Service | D15: km/day | E15: ='Source Inputs'!J15 -> 106 | F15: ='Source Inputs'!K15 -> 103 | G15: =E15/F15 -> 1.0291262 | H15: =(G15-1)/(G15+1) -> 0.014354067 | I15: =Inputs!$B$10 -> 1.0512821 | J15: =F15*I15 -> 108.28205 | K15: =MAX(0,J15-E15) -> 2.2820513 | L15: =MAX(0,J15/E15-1) -> 0.021528786 | M15: =IF(E15>=J15,"RETAIN","UPRATE") -> UPRATE | N15: Raise each surviving held-line sector from 26.5 to at least 27.1 km/day before hot-zone closure.
A16: HC-A-C-MASS-RATING | B16: HC-A-C | C16: Mass | D16: t | E16: ='Source Inputs'!J16 -> 56700 | F16: ='Source Inputs'!K16 -> 54000 | G16: =E16/F16 -> 1.05 | H16: =(G16-1)/(G16+1) -> 0.024390244 | I16: =Inputs!$B$10 -> 1.0512821 | J16: =F16*I16 -> 56769.231 | K16: =MAX(0,J16-E16) -> 69.230769 | L16: =MAX(0,J16/E16-1) -> 0.0012210012 | M16: =IF(E16>=J16,"RETAIN","UPRATE") -> UPRATE | N16: Meet the form-native mass target without borrowing a sibling coefficient or deleting a cell boundary.
A17: HC-A-C-ENERGY-RATING | B17: HC-A-C | C17: Energy | D17: MW | E17: ='Source Inputs'!J17 -> 144.2 | F17: ='Source Inputs'!K17 -> 140 | G17: =E17/F17 -> 1.03 | H17: =(G17-1)/(G17+1) -> 0.014778325 | I17: =Inputs!$B$10 -> 1.0512821 | J17: =F17*I17 -> 147.17949 | K17: =MAX(0,J17-E17) -> 2.9794872 | L17: =MAX(0,J17/E17-1) -> 0.020662186 | M17: =IF(E17>=J17,"RETAIN","UPRATE") -> UPRATE | N17: Meet the form-native energy target without borrowing a sibling coefficient or deleting a cell boundary.
A18: HC-A-C-FLOW-RATING | B18: HC-A-C | C18: Flow | D18: t/day | E18: ='Source Inputs'!J18 -> 945 | F18: ='Source Inputs'!K18 -> 900 | G18: =E18/F18 -> 1.05 | H18: =(G18-1)/(G18+1) -> 0.024390244 | I18: =Inputs!$B$10 -> 1.0512821 | J18: =F18*I18 -> 946.15385 | K18: =MAX(0,J18-E18) -> 1.1538462 | L18: =MAX(0,J18/E18-1) -> 0.0012210012 | M18: =IF(E18>=J18,"RETAIN","UPRATE") -> UPRATE | N18: Meet the form-native flow target without borrowing a sibling coefficient or deleting a cell boundary.
... A30: RT-B-C-FLOW-RATING | B30: RT-B-C | C30: Flow | D30: t/day | E30: ='Source Inputs'!J30 -> 1260 | F30: ='Source Inputs'!K30 -> 1200 | G30: =E30/F30 -> 1.05 | H30: =(G30-1)/(G30+1) -> 0.024390244 | I30: =Inputs!$B$10 -> 1.0512821 | J30: =F30*I30 -> 1261.5385 | K30: =MAX(0,J30-E30) -> 1.5384615 | L30: =MAX(0,J30/E30-1) -> 0.0012210012 | M30: =IF(E30>=J30,"RETAIN","UPRATE") -> UPRATE | N30: Meet the form-native flow target without borrowing a sibling coefficient or deleting a cell boundary.

Sheet Sensitivity
A2: Loss-world interval sensitivity
A4: This view varies the public symmetric screen. It does not invent probability distributions or close missing worlds.
A6: Scenario | B6: Symmetric half-width | C6: Form | D6: Governing raw ratio | E6: Lower interval ratio | F6: Loss-world result | G6: Full-baseline result
A7: No interval | B7: 0 | C7: ET-A-A | D7: =MIN('Loss Rating Orders'!$G$7:$G$10) -> 1.0273535 | E7: =D7*(1-B7)/(1+B7) -> 1.0273535 | F7: =IF(E7>=1,"CLOSE","FAIL") -> CLOSE | G7: ="HOLD: unbounded fatal, cold and thermal cells" -> HOLD: unbounded fatal, cold and thermal cells
A8: No interval | B8: 0 | C8: CT-C-B | D8: =MIN('Loss Rating Orders'!$G$11:$G$14) -> 1.0285714 | E8: =D8*(1-B8)/(1+B8) -> 1.0285714 | F8: =IF(E8>=1,"CLOSE","FAIL") -> CLOSE | G8: ="HOLD: unbounded fatal, cold and thermal cells" -> HOLD: unbounded fatal, cold and thermal cells
A9: No interval | B9: 0 | C9: HC-A-C | D9: =MIN('Loss Rating Orders'!$G$15:$G$18) -> 1.0291262 | E9: =D9*(1-B9)/(1+B9) -> 1.0291262 | F9: =IF(E9>=1,"CLOSE","FAIL") -> CLOSE | G9: ="HOLD: unbounded fatal, cold and thermal cells" -> HOLD: unbounded fatal, cold and thermal cells
A10: No interval | B10: 0 | C10: LF-B-A | D10: =MIN('Loss Rating Orders'!$G$19:$G$22) -> 1.0271923 | E10: =D10*(1-B10)/(1+B10) -> 1.0271923 | F10: =IF(E10>=1,"CLOSE","FAIL") -> CLOSE | G10: ="HOLD: unbounded fatal, cold and thermal cells" -> HOLD: unbounded fatal, cold and thermal cells
A11: No interval | B11: 0 | C11: HU-A-B | D11: =MIN('Loss Rating Orders'!$G$23:$G$26) -> 1.029 | E11: =D11*(1-B11)/(1+B11) -> 1.029 | F11: =IF(E11>=1,"CLOSE","FAIL") -> CLOSE | G11: ="HOLD: unbounded fatal, cold and thermal cells" -> HOLD: unbounded fatal, cold and thermal cells
A12: No interval | B12: 0 | C12: RT-B-C | D12: =MIN('Loss Rating Orders'!$G$27:$G$30) -> 1.0258065 | E12: =D12*(1-B12)/(1+B12) -> 1.0258065 | F12: =IF(E12>=1,"CLOSE","FAIL") -> CLOSE | G12: ="HOLD: unbounded fatal, cold and thermal cells" -> HOLD: unbounded fatal, cold and thermal cells
A13: 1.00% | B13: 0.01 | C13: ET-A-A | D13: =MIN('Loss Rating Orders'!$G$7:$G$10) -> 1.0273535 | E13: =D13*(1-B13)/(1+B13) -> 1.0070098 | F13: =IF(E13>=1,"CLOSE","FAIL") -> CLOSE | G13: ="HOLD: unbounded fatal, cold and thermal cells" -> HOLD: unbounded fatal, cold and thermal cells
A14: 1.00% | B14: 0.01 | C14: CT-C-B | D14: =MIN('Loss Rating Orders'!$G$11:$G$14) -> 1.0285714 | E14: =D14*(1-B14)/(1+B14) -> 1.0082037 | F14: =IF(E14>=1,"CLOSE","FAIL") -> CLOSE | G14: ="HOLD: unbounded fatal, cold and thermal cells" -> HOLD: unbounded fatal, cold and thermal cells
A15: 1.00% | B15: 0.01 | C15: HC-A-C | D15: =MIN('Loss Rating Orders'!$G$15:$G$18) -> 1.0291262 | E15: =D15*(1-B15)/(1+B15) -> 1.0087475 | F15: =IF(E15>=1,"CLOSE","FAIL") -> CLOSE | G15: ="HOLD: unbounded fatal, cold and thermal cells" -> HOLD: unbounded fatal, cold and thermal cells
A16: 1.00% | B16: 0.01 | C16: LF-B-A | D16: =MIN('Loss Rating Orders'!$G$19:$G$22) -> 1.0271923 | E16: =D16*(1-B16)/(1+B16) -> 1.0068518 | F16: =IF(E16>=1,"CLOSE","FAIL") -> CLOSE | G16: ="HOLD: unbounded fatal, cold and thermal cells" -> HOLD: unbounded fatal, cold and thermal cells
A17: 1.00% | B17: 0.01 | C17: HU-A-B | D17: =MIN('Loss Rating Orders'!$G$23:$G$26) -> 1.029 | E17: =D17*(1-B17)/(1+B17) -> 1.0086238 | F17: =IF(E17>=1,"CLOSE","FAIL") -> CLOSE | G17: ="HOLD: unbounded fatal, cold and thermal cells" -> HOLD: unbounded fatal, cold and thermal cells
A18: 1.00% | B18: 0.01 | C18: RT-B-C | D18: =MIN('Loss Rating Orders'!$G$27:$G$30) -> 1.0258065 | E18: =D18*(1-B18)/(1+B18) -> 1.0054935 | F18: =IF(E18>=1,"CLOSE","FAIL") -> CLOSE | G18: ="HOLD: unbounded fatal, cold and thermal cells" -> HOLD: unbounded fatal, cold and thermal cells
A19: 1.25% | B19: 0.0125 | C19: ET-A-A | D19: =MIN('Loss Rating Orders'!$G$7:$G$10) -> 1.0273535 | E19: =D19*(1-B19)/(1+B19) -> 1.0019867 | F19: =IF(E19>=1,"CLOSE","FAIL") -> CLOSE | G19: ="HOLD: unbounded fatal, cold and thermal cells" -> HOLD: unbounded fatal, cold and thermal cells
A20: 1.25% | B20: 0.0125 | C20: CT-C-B | D20: =MIN('Loss Rating Orders'!$G$11:$G$14) -> 1.0285714 | E20: =D20*(1-B20)/(1+B20) -> 1.0031746 | F20: =IF(E20>=1,"CLOSE","FAIL") -> CLOSE | G20: ="HOLD: unbounded fatal, cold and thermal cells" -> HOLD: unbounded fatal, cold and thermal cells
A21: 1.25% | B21: 0.0125 | C21: HC-A-C | D21: =MIN('Loss Rating Orders'!$G$15:$G$18) -> 1.0291262 | E21: =D21*(1-B21)/(1+B21) -> 1.0037157 | F21: =IF(E21>=1,"CLOSE","FAIL") -> CLOSE | G21: ="HOLD: unbounded fatal, cold and thermal cells" -> HOLD: unbounded fatal, cold and thermal cells
A22: 1.25% | B22: 0.0125 | C22: LF-B-A | D22: =MIN('Loss Rating Orders'!$G$19:$G$22) -> 1.0271923 | E22: =D22*(1-B22)/(1+B22) -> 1.0018295 | F22: =IF(E22>=1,"CLOSE","FAIL") -> CLOSE | G22: ="HOLD: unbounded fatal, cold and thermal cells" -> HOLD: unbounded fatal, cold and thermal cells
A23: 1.25% | B23: 0.0125 | C23: HU-A-B | D23: =MIN('Loss Rating Orders'!$G$23:$G$26) -> 1.029 | E23: =D23*(1-B23)/(1+B23) -> 1.0035926 | F23: =IF(E23>=1,"CLOSE","FAIL") -> CLOSE | G23: ="HOLD: unbounded fatal, cold and thermal cells" -> HOLD: unbounded fatal, cold and thermal cells
A24: 1.25% | B24: 0.0125 | C24: RT-B-C | D24: =MIN('Loss Rating Orders'!$G$27:$G$30) -> 1.0258065 | E24: =D24*(1-B24)/(1+B24) -> 1.0004779 | F24: =IF(E24>=1,"CLOSE","FAIL") -> CLOSE | G24: ="HOLD: unbounded fatal, cold and thermal cells" -> HOLD: unbounded fatal, cold and thermal cells
A25: 1.50% | B25: 0.015 | C25: ET-A-A | D25: =MIN('Loss Rating Orders'!$G$7:$G$10) -> 1.0273535 | E25: =D25*(1-B25)/(1+B25) -> 0.99698834 | F25: =IF(E25>=1,"CLOSE","FAIL") -> FAIL | G25: ="HOLD: unbounded fatal, cold and thermal cells" -> HOLD: unbounded fatal, cold and thermal cells
A26: 1.50% | B26: 0.015 | C26: CT-C-B | D26: =MIN('Loss Rating Orders'!$G$11:$G$14) -> 1.0285714 | E26: =D26*(1-B26)/(1+B26) -> 0.9981703 | F26: =IF(E26>=1,"CLOSE","FAIL") -> FAIL | G26: ="HOLD: unbounded fatal, cold and thermal cells" -> HOLD: unbounded fatal, cold and thermal cells
A27: 1.50% | B27: 0.015 | C27: HC-A-C | D27: =MIN('Loss Rating Orders'!$G$15:$G$18) -> 1.0291262 | E27: =D27*(1-B27)/(1+B27) -> 0.99870869 | F27: =IF(E27>=1,"CLOSE","FAIL") -> FAIL | G27: ="HOLD: unbounded fatal, cold and thermal cells" -> HOLD: unbounded fatal, cold and thermal cells
A28: 1.50% | B28: 0.015 | C28: LF-B-A | D28: =MIN('Loss Rating Orders'!$G$19:$G$22) -> 1.0271923 | E28: =D28*(1-B28)/(1+B28) -> 0.99683191 | F28: =IF(E28>=1,"CLOSE","FAIL") -> FAIL | G28: ="HOLD: unbounded fatal, cold and thermal cells" -> HOLD: unbounded fatal, cold and thermal cells
A29: 1.50% | B29: 0.015 | C29: HU-A-B | D29: =MIN('Loss Rating Orders'!$G$23:$G$26) -> 1.029 | E29: =D29*(1-B29)/(1+B29) -> 0.99858621 | F29: =IF(E29>=1,"CLOSE","FAIL") -> FAIL | G29: ="HOLD: unbounded fatal, cold and thermal cells" -> HOLD: unbounded fatal, cold and thermal cells
A30: 1.50% | B30: 0.015 | C30: RT-B-C | D30: =MIN('Loss Rating Orders'!$G$27:$G$30) -> 1.0258065 | E30: =D30*(1-B30)/(1+B30) -> 0.99548705 | F30: =IF(E30>=1,"CLOSE","FAIL") -> FAIL | G30: ="HOLD: unbounded fatal, cold and thermal cells" -> HOLD: unbounded fatal, cold and thermal cells
A31: Selected 2.50% | B31: 0.025 | C31: ET-A-A | D31: =MIN('Loss Rating Orders'!$G$7:$G$10) -> 1.0273535 | E31: =D31*(1-B31)/(1+B31) -> 0.97723866 | F31: =IF(E31>=1,"CLOSE","FAIL") -> FAIL | G31: ="HOLD: unbounded fatal, cold and thermal cells" -> HOLD: unbounded fatal, cold and thermal cells
A32: Selected 2.50% | B32: 0.025 | C32: CT-C-B | D32: =MIN('Loss Rating Orders'!$G$11:$G$14) -> 1.0285714 | E32: =D32*(1-B32)/(1+B32) -> 0.97839721 | F32: =IF(E32>=1,"CLOSE","FAIL") -> FAIL | G32: ="HOLD: unbounded fatal, cold and thermal cells" -> HOLD: unbounded fatal, cold and thermal cells
A33: Selected 2.50% | B33: 0.025 | C33: HC-A-C | D33: =MIN('Loss Rating Orders'!$G$15:$G$18) -> 1.0291262 | E33: =D33*(1-B33)/(1+B33) -> 0.97892493 | F33: =IF(E33>=1,"CLOSE","FAIL") -> FAIL | G33: ="HOLD: unbounded fatal, cold and thermal cells" -> HOLD: unbounded fatal, cold and thermal cells
A34: Selected 2.50% | B34: 0.025 | C34: LF-B-A | D34: =MIN('Loss Rating Orders'!$G$19:$G$22) -> 1.0271923 | E34: =D34*(1-B34)/(1+B34) -> 0.97708534 | F34: =IF(E34>=1,"CLOSE","FAIL") -> FAIL | G34: ="HOLD: unbounded fatal, cold and thermal cells" -> HOLD: unbounded fatal, cold and thermal cells
A35: Selected 2.50% | B35: 0.025 | C35: HU-A-B | D35: =MIN('Loss Rating Orders'!$G$23:$G$26) -> 1.029 | E35: =D35*(1-B35)/(1+B35) -> 0.97880488 | F35: =IF(E35>=1,"CLOSE","FAIL") -> FAIL | G35: ="HOLD: unbounded fatal, cold and thermal cells" -> HOLD: unbounded fatal, cold and thermal cells
A36: Selected 2.50% | B36: 0.025 | C36: RT-B-C | D36: =MIN('Loss Rating Orders'!$G$27:$G$30) -> 1.0258065 | E36: =D36*(1-B36)/(1+B36) -> 0.97576711 | F36: =IF(E36>=1,"CLOSE","FAIL") -> FAIL | G36: ="HOLD: unbounded fatal, cold and thermal cells" -> HOLD: unbounded fatal, cold and thermal cells
A37: 5.00% | B37: 0.05 | C37: ET-A-A | D37: =MIN('Loss Rating Orders'!$G$7:$G$10) -> 1.0273535 | E37: =D37*(1-B37)/(1+B37) -> 0.92951028 | F37: =IF(E37>=1,"CLOSE","FAIL") -> FAIL | G37: ="HOLD: unbounded fatal, cold and thermal cells" -> HOLD: unbounded fatal, cold and thermal cells
A38: 5.00% | B38: 0.05 | C38: CT-C-B | D38: =MIN('Loss Rating Orders'!$G$11:$G$14) -> 1.0285714 | E38: =D38*(1-B38)/(1+B38) -> 0.93061224 | F38: =IF(E38>=1,"CLOSE","FAIL") -> FAIL | G38: ="HOLD: unbounded fatal, cold and thermal cells" -> HOLD: unbounded fatal, cold and thermal cells
A39: 5.00% | B39: 0.05 | C39: HC-A-C | D39: =MIN('Loss Rating Orders'!$G$15:$G$18) -> 1.0291262 | E39: =D39*(1-B39)/(1+B39) -> 0.93111419 | F39: =IF(E39>=1,"CLOSE","FAIL") -> FAIL | G39: ="HOLD: unbounded fatal, cold and thermal cells" -> HOLD: unbounded fatal, cold and thermal cells
A40: 5.00% | B40: 0.05 | C40: LF-B-A | D40: =MIN('Loss Rating Orders'!$G$19:$G$22) -> 1.0271923 | E40: =D40*(1-B40)/(1+B40) -> 0.92936444 | F40: =IF(E40>=1,"CLOSE","FAIL") -> FAIL | G40: ="HOLD: unbounded fatal, cold and thermal cells" -> HOLD: unbounded fatal, cold and thermal cells
A41: 5.00% | B41: 0.05 | C41: HU-A-B | D41: =MIN('Loss Rating Orders'!$G$23:$G$26) -> 1.029 | E41: =D41*(1-B41)/(1+B41) -> 0.931 | F41: =IF(E41>=1,"CLOSE","FAIL") -> FAIL | G41: ="HOLD: unbounded fatal, cold and thermal cells" -> HOLD: unbounded fatal, cold and thermal cells
A42: 5.00% | B42: 0.05 | C42: RT-B-C | D42: =MIN('Loss Rating Orders'!$G$27:$G$30) -> 1.0258065 | E42: =D42*(1-B42)/(1+B42) -> 0.9281106 | F42: =IF(E42>=1,"CLOSE","FAIL") -> FAIL | G42: ="HOLD: unbounded fatal, cold and thermal cells" -> HOLD: unbounded fatal, cold and thermal cells
A43: 10.0% | B43: 0.1 | C43: ET-A-A | D43: =MIN('Loss Rating Orders'!$G$7:$G$10) -> 1.0273535 | E43: =D43*(1-B43)/(1+B43) -> 0.84056192 | F43: =IF(E43>=1,"CLOSE","FAIL") -> FAIL | G43: ="HOLD: unbounded fatal, cold and thermal cells" -> HOLD: unbounded fatal, cold and thermal cells
A44: 10.0% | B44: 0.1 | C44: CT-C-B | D44: =MIN('Loss Rating Orders'!$G$11:$G$14) -> 1.0285714 | E44: =D44*(1-B44)/(1+B44) -> 0.84155844 | F44: =IF(E44>=1,"CLOSE","FAIL") -> FAIL | G44: ="HOLD: unbounded fatal, cold and thermal cells" -> HOLD: unbounded fatal, cold and thermal cells
A45: 10.0% | B45: 0.1 | C45: HC-A-C | D45: =MIN('Loss Rating Orders'!$G$15:$G$18) -> 1.0291262 | E45: =D45*(1-B45)/(1+B45) -> 0.84201236 | F45: =IF(E45>=1,"CLOSE","FAIL") -> FAIL | G45: ="HOLD: unbounded fatal, cold and thermal cells" -> HOLD: unbounded fatal, cold and thermal cells
A46: 10.0% | B46: 0.1 | C46: LF-B-A | D46: =MIN('Loss Rating Orders'!$G$19:$G$22) -> 1.0271923 | E46: =D46*(1-B46)/(1+B46) -> 0.84043004 | F46: =IF(E46>=1,"CLOSE","FAIL") -> FAIL | G46: ="HOLD: unbounded fatal, cold and thermal cells" -> HOLD: unbounded fatal, cold and thermal cells
A47: 10.0% | B47: 0.1 | C47: HU-A-B | D47: =MIN('Loss Rating Orders'!$G$23:$G$26) -> 1.029 | E47: =D47*(1-B47)/(1+B47) -> 0.84190909 | F47: =IF(E47>=1,"CLOSE","FAIL") -> FAIL | G47: ="HOLD: unbounded fatal, cold and thermal cells" -> HOLD: unbounded fatal, cold and thermal cells
A48: 10.0% | B48: 0.1 | C48: RT-B-C | D48: =MIN('Loss Rating Orders'!$G$27:$G$30) -> 1.0258065 | E48: =D48*(1-B48)/(1+B48) -> 0.83929619 | F48: =IF(E48>=1,"CLOSE","FAIL") -> FAIL | G48: ="HOLD: unbounded fatal, cold and thermal cells" -> HOLD: unbounded fatal, cold and thermal cells

Sheet Coefficient Register
A2: Source-specific coefficient register
A4: Every form must bound its own six coefficients. No sibling value, midpoint or favorable zero may be imported.
A6: Coefficient | B6: Form | C6: Symbol | D6: Quantity | E6: Unit | F6: Lower bound | G6: Upper bound | H6: Measured | I6: Required experiment | J6: Prohibited substitution | K6: State | L6: Closure use
A7: ET-A-A-CAP | B7: ET-A-A | C7: βC | D7: capacity calibration factor | E7: ratio | H7: 0 | I7: full-range metered capacity sweep | J7: nominal rating or sibling derate | K7: =IF(AND(ISNUMBER(F7),ISNUMBER(G7),H7=1),"BOUNDED","OPEN") -> OPEN | L7: capacity lower bound
A8: ET-A-A-REQ | B8: ET-A-A | C8: βR | D8: service requirement scale factor | E8: ratio | H8: 0 | I8: receiver-denominator replay | J8: interval midpoint or average receiver | K8: =IF(AND(ISNUMBER(F8),ISNUMBER(G8),H8=1),"BOUNDED","OPEN") -> OPEN | L8: requirement upper bound
A9: ET-A-A-LOSS | B9: ET-A-A | C9: λ | D9: largest-cell propagation fraction | E9: share | H9: 0 | I9: instrumented cell-loss trial | J9: independence declaration | K9: =IF(AND(ISNUMBER(F9),ISNUMBER(G9),H9=1),"BOUNDED","OPEN") -> OPEN | L9: loss-world capacity
A10: ET-A-A-KEY | B10: ET-A-A | C10: κ | D10: fatal-keystone retained fraction | E10: share | H10: 0 | I10: frozen keystone intervention | J10: modeled safeing or operator judgment | K10: =IF(AND(ISNUMBER(F10),ISNUMBER(G10),H10=1),"BOUNDED","OPEN") -> OPEN | L10: fatal-world capacity
A11: ET-A-A-COLD | B11: ET-A-A | C11: χ | D11: cold-start retained fraction | E11: share | H11: 0 | I11: clean-team reconstruction and black start | J11: builder demonstration or vendor runtime | K11: =IF(AND(ISNUMBER(F11),ISNUMBER(G11),H11=1),"BOUNDED","OPEN") -> OPEN | L11: cold-start capacity
A12: ET-A-A-THERM | B12: ET-A-A | C12: θ | D12: peak thermal duty coefficient | E12: form-native | H12: 0 | I12: worst-ambient calorimetry and heat rejection | J12: electrical surplus or sibling coefficient | K12: =IF(AND(ISNUMBER(F12),ISNUMBER(G12),H12=1),"BOUNDED","OPEN") -> OPEN | L12: thermal capacity and requirement
A13: CT-C-B-CAP | B13: CT-C-B | C13: βC | D13: capacity calibration factor | E13: ratio | H13: 0 | I13: full-range metered capacity sweep | J13: nominal rating or sibling derate | K13: =IF(AND(ISNUMBER(F13),ISNUMBER(G13),H13=1),"BOUNDED","OPEN") -> OPEN | L13: capacity lower bound
A14: CT-C-B-REQ | B14: CT-C-B | C14: βR | D14: service requirement scale factor | E14: ratio | H14: 0 | I14: receiver-denominator replay | J14: interval midpoint or average receiver | K14: =IF(AND(ISNUMBER(F14),ISNUMBER(G14),H14=1),"BOUNDED","OPEN") -> OPEN | L14: requirement upper bound
A15: CT-C-B-LOSS | B15: CT-C-B | C15: λ | D15: largest-cell propagation fraction | E15: share | H15: 0 | I15: instrumented cell-loss trial | J15: independence declaration | K15: =IF(AND(ISNUMBER(F15),ISNUMBER(G15),H15=1),"BOUNDED","OPEN") -> OPEN | L15: loss-world capacity
A16: CT-C-B-KEY | B16: CT-C-B | C16: κ | D16: fatal-keystone retained fraction | E16: share | H16: 0 | I16: frozen keystone intervention | J16: modeled safeing or operator judgment | K16: =IF(AND(ISNUMBER(F16),ISNUMBER(G16),H16=1),"BOUNDED","OPEN") -> OPEN | L16: fatal-world capacity
A17: CT-C-B-COLD | B17: CT-C-B | C17: χ | D17: cold-start retained fraction | E17: share | H17: 0 | I17: clean-team reconstruction and black start | J17: builder demonstration or vendor runtime | K17: =IF(AND(ISNUMBER(F17),ISNUMBER(G17),H17=1),"BOUNDED","OPEN") -> OPEN | L17: cold-start capacity
A18: CT-C-B-THERM | B18: CT-C-B | C18: θ | D18: peak thermal duty coefficient | E18: form-native | H18: 0 | I18: worst-ambient calorimetry and heat rejection | J18: electrical surplus or sibling coefficient | K18: =IF(AND(ISNUMBER(F18),ISNUMBER(G18),H18=1),"BOUNDED","OPEN") -> OPEN | L18: thermal capacity and requirement
... A42: RT-B-C-THERM | B42: RT-B-C | C42: θ | D42: peak thermal duty coefficient | E42: form-native | H42: 0 | I42: worst-ambient calorimetry and heat rejection | J42: electrical surplus or sibling coefficient | K42: =IF(AND(ISNUMBER(F42),ISNUMBER(G42),H42=1),"BOUNDED","OPEN") -> OPEN | L42: thermal capacity and requirement

Sheet Thermal Experiments
A2: Thermal closure experiments
A4: Electrical reserve cannot establish heat rejection, occupied-zone temperature, reservoir balance or process thermal safety.
A6: Form | B6: Thermal coefficient | C6: Control envelope | D6: Measured boundary | E6: Instrumentation | F6: Required intervention | G6: Closure condition | H6: Current bound | I6: State | J6: Technology consequence
A7: ET-A-A | B7: MWth per dry-custody t/h | C7: peak relative motion; warm seawater; saturated air | D7: connector drive, drying, refrigeration and refuge rejection | E7: shaft torque, calorimetry, wet/dry enthalpy and zone temperature | F7: disable one body and one rejection loop | G7: upper duty remains below surviving exchanger capacity with no wet-dry propagation | I7: OPEN | J7: two-body heat rejection must remain independent across the transfer saddle
A8: CT-C-B | B8: MWth per delivered utility MW | C8: occupied envelope; smoke-control limit; severed mixed trunk | D8: conversion loss, cable heat, smoke transport and indoor rejection | E8: distributed temperature, smoke, current, flow and pressure tomography | F8: fault and guillotine one mixed-utility segment | G8: occupied-zone limits hold after isolation without exporting heat or smoke | I8: OPEN | J8: utility guillotines need thermal as well as hydraulic and electrical selectivity
A9: HC-A-C | B9: MJth per held-line km | C9: hot-day plume; hover; 72 h duty; denied coordination | D9: rotor drive, battery or fluid exchange, payload and refuge thermal state | E9: cell calorimetry, winding and pack temperature, plume and refill enthalpy | F9: safe one cell inside plume and continue locally | G9: four cells hold the line without thermal runaway or shared cooling | I9: OPEN | J9: hot-zone exchange must be cell-local and operable without the mesh
A10: LF-B-A | B10: MWth per thousand m3/day | C10: reservoir decline; full salinity; ambient maximum | D10: wellhead enthalpy, conversion rejection, product cooling and reinjection | E10: mass-flow and enthalpy metering from bore through injection | F10: isolate one header, conversion cell and bore at full state | G10: three conversion cells and two injection paths close enthalpy and chemistry | I10: OPEN | J10: brine-to-mineral metabolism becomes part of heat rejection, not a byproduct
A11: HU-A-B | B11: MWth per complete care line | C11: full census; hot-humid ambient; sterile and cold-chain duty | D11: clinical sensible and latent load, sterilization, refrigeration and refuge | E11: zone calorimetry, humidity, cold-chain and utility metering | F11: block one spine section and one cooling path | G11: all ten care lines remain within clinical temperature and humidity limits | I11: OPEN | J11: bypass architecture must carry thermal continuity with clinical continuity
A12: RT-B-C | B12: MJth per released product-equivalent | C12: worst product mix; pulsed loads; islanded trainlets | D12: process heat, machine losses, quarantine and rejected-material cooling | E12: machine-level energy, calorimetry and material-ancestry ledger | F12: isolate one trainlet and its largest energy cell | G12: four trainlets preserve qualified release without shared heat sink | I12: OPEN | J12: self-describing process chains must include heat and cooling ancestry

Sheet World Rules
A2: World-specific numerical law
A4: The same content-addressed baseline enters every world. Reconfiguration, receiver substitution and cross-form borrowing are prohibited.
A6: World | B6: Capacity basis | C6: Requirement basis | D6: Uncertainty treatment | E6: Missing-value treatment | F6: Allowed closure | G6: Current bounded cells | H6: Current disposition | I6: Reason
A7: NOMINAL | B7: nominal | C7: nominal | D7: capacity lower bound versus requirement upper bound | E7: HOLD; never zero or midpoint | F7: all five accounts conjunctive | G7: =COUNTIFS('Closure Cells'!$D$7:$D$126,A7,'Closure Cells'!$N$7:$N$126,"BOUNDED") -> 24 | H7: =IF(COUNTIFS('Closure Cells'!$D$7:$D$126,A7,'Closure Cells'!$O$7:$O$126,"HOLD")>0,"HOLD",IF(COUNTIFS('Closure Cells'!$D$7:$D$126,A7,'Closure Cells'!$O$7:$O$126,"FAIL")>0,"FAIL","CLOSE")) -> HOLD | I7: No denial; configured service denominator applies.
A8: LARGEST_CELL_LOSS | B8: loss | C8: loss | D8: capacity lower bound versus requirement upper bound | E8: HOLD; never zero or midpoint | F8: all five accounts conjunctive | G8: =COUNTIFS('Closure Cells'!$D$7:$D$126,A8,'Closure Cells'!$N$7:$N$126,"BOUNDED") -> 24 | H8: =IF(COUNTIFS('Closure Cells'!$D$7:$D$126,A8,'Closure Cells'!$O$7:$O$126,"HOLD")>0,"HOLD",IF(COUNTIFS('Closure Cells'!$D$7:$D$126,A8,'Closure Cells'!$O$7:$O$126,"FAIL")>0,"FAIL","CLOSE")) -> HOLD | I8: Remove the largest independent cell without changing receiver or configuration.
A9: FATAL_KEYSTONE | B9: unknown | C9: nominal | D9: capacity lower bound versus requirement upper bound | E9: HOLD; never zero or midpoint | F9: all five accounts conjunctive | G9: =COUNTIFS('Closure Cells'!$D$7:$D$126,A9,'Closure Cells'!$N$7:$N$126,"BOUNDED") -> 0 | H9: =IF(COUNTIFS('Closure Cells'!$D$7:$D$126,A9,'Closure Cells'!$O$7:$O$126,"HOLD")>0,"HOLD",IF(COUNTIFS('Closure Cells'!$D$7:$D$126,A9,'Closure Cells'!$O$7:$O$126,"FAIL")>0,"FAIL","CLOSE")) -> HOLD | I9: Apply the frozen form-specific keystone intervention at full causal load.
A10: COLD_START | B10: unknown | C10: nominal | D10: capacity lower bound versus requirement upper bound | E10: HOLD; never zero or midpoint | F10: all five accounts conjunctive | G10: =COUNTIFS('Closure Cells'!$D$7:$D$126,A10,'Closure Cells'!$N$7:$N$126,"BOUNDED") -> 0 | H10: =IF(COUNTIFS('Closure Cells'!$D$7:$D$126,A10,'Closure Cells'!$O$7:$O$126,"HOLD")>0,"HOLD",IF(COUNTIFS('Closure Cells'!$D$7:$D$126,A10,'Closure Cells'!$O$7:$O$126,"FAIL")>0,"FAIL","CLOSE")) -> HOLD | I10: Deny builder team, private runtime, vendor key and tacit setup; restore from the public package.

Sheet Finance
A2: Conserved cohort-one obligation
A4: Numerical redesign changes technical content, not the USD179M obligation. Rating uplift is not treated as cost uplift.
A6: Form | B6: Ceiling (USD M) | C6: Event method 20% | D6: Instrumentation 25% | E6: Civil closure 15% | F6: Article engineering 25% | G6: Cold reconstruction 15% | H6: Reconciled ceiling
A7: ET-A-A | B7: 25.023731 | C7: =B7*20% -> 5.0047462 | D7: =B7*25% -> 6.2559327 | E7: =B7*15% -> 3.7535596 | F7: =B7*25% -> 6.2559327 | G7: =B7*15% -> 3.7535596 | H7: =SUM(C7:G7) -> 25.023731
A8: CT-C-B | B8: 25.824674 | C8: =B8*20% -> 5.1649348 | D8: =B8*25% -> 6.4561685 | E8: =B8*15% -> 3.8737011 | F8: =B8*25% -> 6.4561685 | G8: =B8*15% -> 3.8737011 | H8: =SUM(C8:G8) -> 25.824674
A9: HC-A-C | B9: 15.361083 | C9: =B9*20% -> 3.0722165 | D9: =B9*25% -> 3.8402707 | E9: =B9*15% -> 2.3041624 | F9: =B9*25% -> 3.8402707 | G9: =B9*15% -> 2.3041624 | H9: =SUM(C9:G9) -> 15.361083
A10: LF-B-A | B10: 44.970641 | C10: =B10*20% -> 8.9941282 | D10: =B10*25% -> 11.24266 | E10: =B10*15% -> 6.7455961 | F10: =B10*25% -> 11.24266 | G10: =B10*15% -> 6.7455961 | H10: =SUM(C10:G10) -> 44.970641
A11: HU-A-B | B11: 43.035623 | C11: =B11*20% -> 8.6071245 | D11: =B11*25% -> 10.758906 | E11: =B11*15% -> 6.4553434 | F11: =B11*25% -> 10.758906 | G11: =B11*15% -> 6.4553434 | H11: =SUM(C11:G11) -> 43.035623
A12: RT-B-C | B12: 25.12989 | C12: =B12*20% -> 5.0259779 | D12: =B12*25% -> 6.2824724 | E12: =B12*15% -> 3.7694834 | F12: =B12*25% -> 6.2824724 | G12: =B12*15% -> 3.7694834 | H12: =SUM(C12:G12) -> 25.12989
A13: Total | B13: =SUM(B7:B12) -> 179.34564 | C13: =SUM(C7:C12) -> 35.869128 | D13: =SUM(D7:D12) -> 44.83641 | E13: =SUM(E7:E12) -> 26.901846 | F13: =SUM(F7:F12) -> 44.83641 | G13: =SUM(G7:G12) -> 26.901846 | H13: =SUM(H7:H12) -> 179.34564
A16: Boundary | B16: Boundary | C16: Boundary | D16: Boundary | E16: Boundary | F16: Boundary | G16: Boundary | H16: Boundary
A18: Protected sibling reserve | B18: 358.69128 | C18: USD M | D18: unchanged
A19: FRAME ceiling | B19: 538.03692 | C19: USD M | D19: unchanged
A20: Rating-uplift price | C20: USD M | D20: OPEN: a 2.5% capacity change is not a 2.5% cost change
A21: New obligation authorized | B21: 0 | C21: USD M | D21: none

Sheet Inputs
A2: Numerical interval-solvency controls
A4: Blue cells are design rules or zero authority states. They are not measured coefficients or evidence.
A6: Interval-solvency rule | B6: Interval-solvency rule | C6: Interval-solvency rule | D6: Interval-solvency rule
A7: Capacity downside half-width | B7: 0.025 | C7: share | D7: public design test; not a distribution
A8: Requirement upside half-width | B8: 0.025 | C8: share | D8: public design test; not a distribution
A9: Closure ratio | B9: 1 | C9: ratio | D9: lower capacity / upper requirement
A10: Required raw ratio | B10: =(1+B8)/(1-B7) -> 1.0512821 | C10: ratio | D10: (1 + requirement upside) / (1 - capacity downside)
A11: Cold reconstruction maximum | B11: 168 | C11: h | D11: Pass 219
A12: Numerical tolerance | B12: 1e-06 | C12: ratio | D12: model control
A15: Current evidence and authority | B15: Current evidence and authority | C15: Current evidence and authority | D15: Current evidence and authority
A16: Measured coefficients | B16: 0 | C16: count | D16: source empty
A17: Accepted baselines | B17: 0 | C17: count | D17: held
A18: Payments | B18: 0 | C18: count | D18: held
A19: Accepted observations | B19: 0 | C19: count | D19: held
A20: Selected forms | B20: 0 | C20: count | D20: held
A21: MAKE warrants | B21: 0 | C21: count | D21: held
A22: REP-4 records | B22: 0 | C22: count | D22: held
A23: Capability credit | B23: 0 | C23: count | D23: held
A24: Production credit | B24: 0 | C24: count | D24: held
A25: Renderings authorized | B25: 0 | C25: count | D25: held
A28: Conserved finance | B28: Conserved finance | C28: Conserved finance | D28: Conserved finance
A29: Cohort-one obligation | B29: 179.34564 | C29: USD M | D29: Pass 229
A30: Protected sibling reserve | B30: 358.69128 | C30: USD M | D30: Pass 229
A31: FRAME ceiling | B31: 538.03692 | C31: USD M | D31: Pass 226

Sheet Source Inputs
A2: Inherited quantitative inputs
A4: Twenty-four planning rows are copied without measurement uplift. Thermal, fatal-keystone and cold-start quantities remain absent.
A6: Source ID | B6: Form | C6: Account | D6: Unit | E6: Installed cells | F6: Cells after loss | G6: Cell rating | H6: Nominal capacity | I6: Nominal requirement | J6: Loss capacity | K6: Loss requirement | L6: Repository origin | M6: Value class | N6: Measured | O6: Physical meaning
A7: ET-A-A-SERVICE | B7: ET-A-A | C7: Service | D7: t/h | E7: 2 | F7: 1 | G7: 241 | H7: 482 | I7: 234.58333 | J7: 241 | K7: 234.58333 | L7: Pass 219 A03 | M7: INHERITED HYPOTHESIS | N7: 0 | O7: Complete moving-source-to-dry-custody path
A8: ET-A-A-MASS | B8: ET-A-A | C8: Mass | D8: t | E8: 8 | F8: 7 | G8: 16000 | H8: 128000 | I8: 102000 | J8: 112000 | K8: 102000 | L8: Pass 219 A01 | M8: INHERITED HYPOTHESIS | N8: 0 | O8: Independent access and custody cells
A9: ET-A-A-ENERGY | B9: ET-A-A | C9: Energy | D9: MW | E9: 6 | F9: 5 | G9: 20 | H9: 120 | I9: 96 | J9: 100 | K9: 96 | L9: Pass 219 A02 | M9: INHERITED HYPOTHESIS | N9: 0 | O9: Black-start generation cells
A10: ET-A-A-FLOW | B10: ET-A-A | C10: Flow | D10: t/day | E10: 6 | F10: 5 | G10: 252 | H10: 1512 | I10: 1200 | J10: 1260 | K10: 1200 | L10: Pass 219 A05 | M10: INHERITED HYPOTHESIS | N10: 0 | O10: Contained residual treatment
A11: CT-C-B-SERVICE | B11: CT-C-B | C11: Service | D11: ratio | E11: 5 | F11: 4 | G11: 0.264 | H11: 1.32 | I11: 1 | J11: 1.056 | K11: 1 | L11: Pass 219 A03 | M11: INHERITED HYPOTHESIS | N11: 0 | O11: Complete fault-contained utility trunk
A12: CT-C-B-MASS | B12: CT-C-B | C12: Mass | D12: t | E12: 10 | F12: 9 | G12: 3600 | H12: 36000 | I12: 31000 | J12: 32400 | K12: 31000 | L12: Pass 219 A01 | M12: INHERITED HYPOTHESIS | N12: 0 | O12: Independent insertion cells
A13: CT-C-B-ENERGY | B13: CT-C-B | C13: Energy | D13: MW | E13: 7 | F13: 6 | G13: 7.2 | H13: 50.4 | I13: 42 | J13: 43.2 | K13: 42 | L13: Pass 219 A02 | M13: INHERITED HYPOTHESIS | N13: 0 | O13: Isolated generation cells
A14: CT-C-B-FLOW | B14: CT-C-B | C14: Flow | D14: t/day | E14: 6 | F14: 5 | G14: 46.2 | H14: 277.2 | I14: 220 | J14: 231 | K14: 220 | L14: Pass 219 A05 | M14: INHERITED HYPOTHESIS | N14: 0 | O14: Dirty-return treatment
A15: HC-A-C-SERVICE | B15: HC-A-C | C15: Service | D15: km/day | E15: 5 | F15: 4 | G15: 26.5 | H15: 132.5 | I15: 103 | J15: 106 | K15: 103 | L15: Pass 219 A03 | M15: INHERITED HYPOTHESIS | N15: 0 | O15: Attributable held-line sectors
A16: HC-A-C-MASS | B16: HC-A-C | C16: Mass | D16: t | E16: 10 | F16: 9 | G16: 6300 | H16: 63000 | I16: 54000 | J16: 56700 | K16: 54000 | L16: Pass 219 A01 | M16: INHERITED HYPOTHESIS | N16: 0 | O16: Independent intervention cells
A17: HC-A-C-ENERGY | B17: HC-A-C | C17: Energy | D17: MW | E17: 8 | F17: 7 | G17: 20.6 | H17: 164.8 | I17: 140 | J17: 144.2 | K17: 140 | L17: Pass 219 A02 | M17: INHERITED HYPOTHESIS | N17: 0 | O17: Isolated intervention-energy cells
A18: HC-A-C-FLOW | B18: HC-A-C | C18: Flow | D18: t/day | E18: 6 | F18: 5 | G18: 189 | H18: 1134 | I18: 900 | J18: 945 | K18: 900 | L18: Pass 219 A05 | M18: INHERITED HYPOTHESIS | N18: 0 | O18: Runoff and working-fluid custody
... A22: LF-B-A-FLOW | B22: LF-B-A | C22: Flow | D22: thousand m3/day | E22: 3 | F22: 2 | G22: 10.3 | H22: 30.9 | I22: 20 | J22: 20.6 | K22: 20 | L22: Pass 219 A05 | M22: INHERITED HYPOTHESIS | N22: 0 | O22: Brine treatment and injection paths
A23: HU-A-B-SERVICE | B23: HU-A-B | C23: Service | D23: ratio | E23: 10 | F23: 10 | H23: 1.28 | I23: 1 | J23: 1.032 | K23: 1 | L23: Pass 219 A03 | M23: INHERITED HYPOTHESIS | N23: 0 | O23: Ten complete care lines over separated routes
A24: HU-A-B-MASS | B24: HU-A-B | C24: Mass | D24: kt | E24: 8 | F24: 7 | G24: 7.35 | H24: 58.8 | I24: 50 | J24: 51.45 | K24: 50 | L24: Pass 219 A01 | M24: INHERITED HYPOTHESIS | N24: 0 | O24: Independent access cells
A25: HU-A-B-ENERGY | B25: HU-A-B | C25: Energy | D25: MW | E25: 6 | F25: 5 | G25: 11 | H25: 66 | I25: 52 | J25: 55 | K25: 52 | L25: Pass 219 A02 | M25: INHERITED HYPOTHESIS | N25: 0 | O25: Isolated clinical-utility cells
A26: HU-A-B-FLOW | B26: HU-A-B | C26: Flow | D26: t/day | E26: 6 | F26: 5 | G26: 73.5 | H26: 441 | I26: 350 | J26: 367.5 | K26: 350 | L26: Pass 219 A05 | M26: INHERITED HYPOTHESIS | N26: 0 | O26: Clinical residual custody
A27: RT-B-C-SERVICE | B27: RT-B-C | C27: Service | D27: ratio | E27: 5 | F27: 4 | G27: 0.26 | H27: 1.3 | I27: 1 | J27: 1.04 | K27: 1 | L27: Pass 219 A03 | M27: INHERITED HYPOTHESIS | N27: 0 | O27: Complete disconnected process meshes
A28: RT-B-C-MASS | B28: RT-B-C | C28: Mass | D28: t | E28: 10 | F28: 9 | G28: 8400 | H28: 84000 | I28: 72000 | J28: 75600 | K28: 72000 | L28: Pass 219 A01 | M28: INHERITED HYPOTHESIS | N28: 0 | O28: Independent process-access cells
A29: RT-B-C-ENERGY | B29: RT-B-C | C29: Energy | D29: MW | E29: 7 | F29: 6 | G29: 26.5 | H29: 185.5 | I29: 155 | J29: 159 | K29: 155 | L29: Pass 219 A02 | M29: INHERITED HYPOTHESIS | N29: 0 | O29: Isolated process-energy cells
A30: RT-B-C-FLOW | B30: RT-B-C | C30: Flow | D30: t/day | E30: 6 | F30: 5 | G30: 252 | H30: 1512 | I30: 1200 | J30: 1260 | K30: 1200 | L30: Pass 219 A05 | M30: INHERITED HYPOTHESIS | N30: 0 | O30: Rejected-material treatment

Sheet Mutations
A2: Adversarial mutation record
A4: Each corruption was applied to a disposable copy, detected by the audit layer and restored before release.
A6: Mutation | B6: Target | C6: Corruption | D6: Expected detection | E6: Applied | F6: Detected | G6: Restored
A7: M01 | B7: Inputs!B7 | C7: capacity downside set to 0 | D7: selected screen control mismatch | E7: 1 | F7: 1 | G7: 1
A8: M02 | B8: Inputs!B8 | C8: requirement upside set to 0 | D8: selected screen control mismatch | E8: 1 | F8: 1 | G8: 1
A9: M03 | B9: Inputs!B9 | C9: closure ratio set to 0 | D9: closure rule mismatch | E9: 1 | F9: 1 | G9: 1
A10: M04 | B10: Inputs!B10 | C10: required ratio overwritten with 1 | D10: interval identity mismatch | E10: 1 | F10: 1 | G10: 1
A11: M05 | B11: Inputs!B16 | C11: measured coefficient count set to 1 | D11: zero-authority check | E11: 1 | F11: 1 | G11: 1
A12: M06 | B12: Inputs!B17 | C12: accepted baseline count set to 1 | D12: zero-authority check | E12: 1 | F12: 1 | G12: 1
A13: M07 | B13: Inputs!B18 | C13: payment count set to 1 | D13: zero-authority check | E13: 1 | F13: 1 | G13: 1
A14: M08 | B14: Inputs!B19 | C14: accepted observation count set to 1 | D14: zero-authority check | E14: 1 | F14: 1 | G14: 1
A15: M09 | B15: Inputs!B20 | C15: selected form count set to 1 | D15: zero-authority check | E15: 1 | F15: 1 | G15: 1
A16: M10 | B16: Inputs!B21 | C16: MAKE count set to 1 | D16: zero-authority check | E16: 1 | F16: 1 | G16: 1
A17: M11 | B17: Inputs!B22 | C17: REP-4 count set to 1 | D17: zero-authority check | E17: 1 | F17: 1 | G17: 1
A18: M12 | B18: Inputs!B23 | C18: capability credit set to 1 | D18: zero-authority check | E18: 1 | F18: 1 | G18: 1
... A28: M22 | B28: Sensitivity!F31 | C28: selected-screen FAIL replaced by CLOSE | D28: sensitivity count | E28: 1 | F28: 1 | G28: 1

Sheet Audit
A2: Terminal audit
A4: Checks observe the model and do not feed any output, assumption or decision cell.
A6: Audit | B6: Test | C6: Actual | D6: Expected | E6: Tolerance | F6: Status
A7: A01 | B7: closure cell count | C7: =COUNTA('Closure Cells'!$A$7:$A$126) -> 120 | D7: 120 | E7: 0 | F7: =IF(ABS(C7-D7)<=E7,"PASS","FAIL") -> PASS
A8: A02 | B8: bounded cell count | C8: =COUNTIF('Closure Cells'!$N$7:$N$126,"BOUNDED") -> 48 | D8: 48 | E8: 0 | F8: =IF(ABS(C8-D8)<=E8,"PASS","FAIL") -> PASS
A9: A03 | B9: unbounded cell count | C9: =COUNTIF('Closure Cells'!$N$7:$N$126,"UNBOUNDED") -> 72 | D9: 72 | E9: 0 | F9: =IF(ABS(C9-D9)<=E9,"PASS","FAIL") -> PASS
A10: A04 | B10: closed interval cells | C10: =COUNTIF('Closure Cells'!$O$7:$O$126,"CLOSE") -> 27 | D10: 27 | E10: 0 | F10: =IF(ABS(C10-D10)<=E10,"PASS","FAIL") -> PASS
A11: A05 | B11: failed interval cells | C11: =COUNTIF('Closure Cells'!$O$7:$O$126,"FAIL") -> 21 | D11: 21 | E11: 0 | F11: =IF(ABS(C11-D11)<=E11,"PASS","FAIL") -> PASS
A12: A06 | B12: held interval cells | C12: =COUNTIF('Closure Cells'!$O$7:$O$126,"HOLD") -> 72 | D12: 72 | E12: 0 | F12: =IF(ABS(C12-D12)<=E12,"PASS","FAIL") -> PASS
A13: A07 | B13: nominal closed accounts | C13: =COUNTIFS('Closure Cells'!$D$7:$D$126,"NOMINAL",'Closure Cells'!$O$7:$O$126,"CLOSE") -> 24 | D13: 24 | E13: 0 | F13: =IF(ABS(C13-D13)<=E13,"PASS","FAIL") -> PASS
A14: A08 | B14: nominal failed accounts | C14: =COUNTIFS('Closure Cells'!$D$7:$D$126,"NOMINAL",'Closure Cells'!$O$7:$O$126,"FAIL") -> 0 | D14: 0 | E14: 0 | F14: =IF(ABS(C14-D14)<=E14,"PASS","FAIL") -> PASS
A15: A09 | B15: nominal held thermal cells | C15: =COUNTIFS('Closure Cells'!$D$7:$D$126,"NOMINAL",'Closure Cells'!$O$7:$O$126,"HOLD") -> 6 | D15: 6 | E15: 0 | F15: =IF(ABS(C15-D15)<=E15,"PASS","FAIL") -> PASS
A16: A10 | B16: loss closed accounts | C16: =COUNTIFS('Closure Cells'!$D$7:$D$126,"LARGEST_CELL_LOSS",'Closure Cells'!$O$7:$O$126,"CLOSE") -> 3 | D16: 3 | E16: 0 | F16: =IF(ABS(C16-D16)<=E16,"PASS","FAIL") -> PASS
A17: A11 | B17: loss failed accounts | C17: =COUNTIFS('Closure Cells'!$D$7:$D$126,"LARGEST_CELL_LOSS",'Closure Cells'!$O$7:$O$126,"FAIL") -> 21 | D17: 21 | E17: 0 | F17: =IF(ABS(C17-D17)<=E17,"PASS","FAIL") -> PASS
A18: A12 | B18: loss held thermal cells | C18: =COUNTIFS('Closure Cells'!$D$7:$D$126,"LARGEST_CELL_LOSS",'Closure Cells'!$O$7:$O$126,"HOLD") -> 6 | D18: 6 | E18: 0 | F18: =IF(ABS(C18-D18)<=E18,"PASS","FAIL") -> PASS
A19: A13 | B19: fatal world held cells | C19: =COUNTIFS('Closure Cells'!$D$7:$D$126,"FATAL_KEYSTONE",'Closure Cells'!$O$7:$O$126,"HOLD") -> 30 | D19: 30 | E19: 0 | F19: =IF(ABS(C19-D19)<=E19,"PASS","FAIL") -> PASS
A20: A14 | B20: cold world held cells | C20: =COUNTIFS('Closure Cells'!$D$7:$D$126,"COLD_START",'Closure Cells'!$O$7:$O$126,"HOLD") -> 30 | D20: 30 | E20: 0 | F20: =IF(ABS(C20-D20)<=E20,"PASS","FAIL") -> PASS
A21: A15 | B21: thermal held cells | C21: =COUNTIFS('Closure Cells'!$C$7:$C$126,"Thermal",'Closure Cells'!$O$7:$O$126,"HOLD") -> 24 | D21: 24 | E21: 0 | F21: =IF(ABS(C21-D21)<=E21,"PASS","FAIL") -> PASS
A22: A16 | B22: source input rows | C22: =COUNTA('Source Inputs'!$A$7:$A$30) -> 24 | D22: 24 | E22: 0 | F22: =IF(ABS(C22-D22)<=E22,"PASS","FAIL") -> PASS
A23: A17 | B23: source measured flags | C23: =SUM('Source Inputs'!$N$7:$N$30) -> 0 | D23: 0 | E23: 0 | F23: =IF(ABS(C23-D23)<=E23,"PASS","FAIL") -> PASS
A24: A18 | B24: coefficient rows | C24: =COUNTA('Coefficient Register'!$A$7:$A$42) -> 36 | D24: 36 | E24: 0 | F24: =IF(ABS(C24-D24)<=E24,"PASS","FAIL") -> PASS
A25: A19 | B25: open coefficients | C25: =COUNTIF('Coefficient Register'!$K$7:$K$42,"OPEN") -> 36 | D25: 36 | E25: 0 | F25: =IF(ABS(C25-D25)<=E25,"PASS","FAIL") -> PASS
A26: A20 | B26: measured coefficients | C26: =SUM('Coefficient Register'!$H$7:$H$42) -> 0 | D26: 0 | E26: 0 | F26: =IF(ABS(C26-D26)<=E26,"PASS","FAIL") -> PASS
A27: A21 | B27: rating orders | C27: =COUNTA('Loss Rating Orders'!$A$7:$A$30) -> 24 | D27: 24 | E27: 0 | F27: =IF(ABS(C27-D27)<=E27,"PASS","FAIL") -> PASS
A28: A22 | B28: uprate orders | C28: =COUNTIF('Loss Rating Orders'!$M$7:$M$30,"UPRATE") -> 21 | D28: 21 | E28: 0 | F28: =IF(ABS(C28-D28)<=E28,"PASS","FAIL") -> PASS
A29: A23 | B29: retained ratings | C29: =COUNTIF('Loss Rating Orders'!$M$7:$M$30,"RETAIN") -> 3 | D29: 3 | E29: 0 | F29: =IF(ABS(C29-D29)<=E29,"PASS","FAIL") -> PASS
A30: A24 | B30: required raw ratio | C30: =Inputs!$B$10 -> 1.0512821 | D30: 1.0512821 | E30: 1e-07 | F30: =IF(ABS(C30-D30)<=E30,"PASS","FAIL") -> PASS
A31: A25 | B31: form rows | C31: =COUNTA('Form Results'!$A$7:$A$12) -> 6 | D31: 6 | E31: 0 | F31: =IF(ABS(C31-D31)<=E31,"PASS","FAIL") -> PASS
A32: A26 | B32: closed forms | C32: =COUNTIF('Form Results'!$K$7:$K$12,"CLOSE") -> 0 | D32: 0 | E32: 0 | F32: =IF(ABS(C32-D32)<=E32,"PASS","FAIL") -> PASS
A33: A27 | B33: redesign-held forms | C33: =COUNTIF('Form Results'!$K$7:$K$12,"REDESIGN / HOLD") -> 6 | D33: 6 | E33: 0 | F33: =IF(ABS(C33-D33)<=E33,"PASS","FAIL") -> PASS
A34: A28 | B34: sensitivity rows | C34: =COUNTA(Sensitivity!$A$7:$A$48) -> 42 | D34: 42 | E34: 0 | F34: =IF(ABS(C34-D34)<=E34,"PASS","FAIL") -> PASS
A35: A29 | B35: forms closing 1.25% loss screen | C35: =COUNTIFS(Sensitivity!$A$7:$A$48,"1.25%",Sensitivity!$F$7:$F$48,"CLOSE") -> 6 | D35: 6 | E35: 0 | F35: =IF(ABS(C35-D35)<=E35,"PASS","FAIL") -> PASS
A36: A30 | B36: forms closing 1.50% loss screen | C36: =COUNTIFS(Sensitivity!$A$7:$A$48,"1.50%",Sensitivity!$F$7:$F$48,"CLOSE") -> 0 | D36: 0 | E36: 0 | F36: =IF(ABS(C36-D36)<=E36,"PASS","FAIL") -> PASS
A37: A31 | B37: forms closing selected loss screen | C37: =COUNTIFS(Sensitivity!$A$7:$A$48,"Selected 2.50%",Sensitivity!$F$7:$F$48,"CLOSE") -> 0 | D37: 0 | E37: 0 | F37: =IF(ABS(C37-D37)<=E37,"PASS","FAIL") -> PASS
A38: A32 | B38: thermal experiments | C38: =COUNTA('Thermal Experiments'!$A$7:$A$12) -> 6 | D38: 6 | E38: 0 | F38: =IF(ABS(C38-D38)<=E38,"PASS","FAIL") -> PASS
A39: A33 | B39: finance obligation reconciliation | C39: =Finance!$H$13 -> 179.34564 | D39: 179.34564 | E39: 1e-06 | F39: =IF(ABS(C39-D39)<=E39,"PASS","FAIL") -> PASS
A40: A34 | B40: finance form ceiling sum | C40: =Finance!$B$13 -> 179.34564 | D40: 179.34564 | E40: 1e-06 | F40: =IF(ABS(C40-D40)<=E40,"PASS","FAIL") -> PASS
A41: A35 | B41: obligation plus reserve | C41: =Inputs!$B$29+Inputs!$B$30 -> 538.03692 | D41: 538.03692 | E41: 1e-06 | F41: =IF(ABS(C41-D41)<=E41,"PASS","FAIL") -> PASS
A42: A36 | B42: zero evidence and authority | C42: =SUM(Inputs!$B$16:$B$25) -> 0 | D42: 0 | E42: 0 | F42: =IF(ABS(C42-D42)<=E42,"PASS","FAIL") -> PASS
A43: A37 | B43: rendering authority | C43: =Inputs!$B$25 -> 0 | D43: 0 | E43: 0 | F43: =IF(ABS(C43-D43)<=E43,"PASS","FAIL") -> PASS
A44: A38 | B44: mutation rows | C44: =COUNTA(Mutations!$A$7:$A$28) -> 22 | D44: 22 | E44: 0 | F44: =IF(ABS(C44-D44)<=E44,"PASS","FAIL") -> PASS
A45: A39 | B45: mutations applied | C45: =SUM(Mutations!$E$7:$E$28) -> 22 | D45: 22 | E45: 0 | F45: =IF(ABS(C45-D45)<=E45,"PASS","FAIL") -> PASS
A46: A40 | B46: mutations detected | C46: =SUM(Mutations!$F$7:$F$28) -> 22 | D46: 22 | E46: 0 | F46: =IF(ABS(C46-D46)<=E46,"PASS","FAIL") -> PASS
A47: A41 | B47: mutations restored | C47: =SUM(Mutations!$G$7:$G$28) -> 22 | D47: 22 | E47: 0 | F47: =IF(ABS(C47-D47)<=E47,"PASS","FAIL") -> PASS
A48: A42 | B48: capacity downside control | C48: =Inputs!$B$7 -> 0.025 | D48: 0.025 | E48: 1e-07 | F48: =IF(ABS(C48-D48)<=E48,"PASS","FAIL") -> PASS
A49: A43 | B49: requirement upside control | C49: =Inputs!$B$8 -> 0.025 | D49: 0.025 | E49: 1e-07 | F49: =IF(ABS(C49-D49)<=E49,"PASS","FAIL") -> PASS
A50: A44 | B50: closure ratio control | C50: =Inputs!$B$9 -> 1 | D50: 1 | E50: 1e-07 | F50: =IF(ABS(C50-D50)<=E50,"PASS","FAIL") -> PASS
A51: A45 | B51: numeric coefficient bounds | C51: =COUNT('Coefficient Register'!$F$7:$G$42) -> 0 | D51: 0 | E51: 0 | F51: =IF(ABS(C51-D51)<=E51,"PASS","FAIL") -> PASS
A52: A46 | B52: ET-A-A closure rows | C52: =COUNTIF('Closure Cells'!$B$7:$B$126,"ET-A-A") -> 20 | D52: 20 | E52: 0 | F52: =IF(ABS(C52-D52)<=E52,"PASS","FAIL") -> PASS
A53: A47 | B53: ET-A-A bounded rows | C53: =COUNTIFS('Closure Cells'!$B$7:$B$126,"ET-A-A",'Closure Cells'!$N$7:$N$126,"BOUNDED") -> 8 | D53: 8 | E53: 0 | F53: =IF(ABS(C53-D53)<=E53,"PASS","FAIL") -> PASS
A54: A48 | B54: ET-A-A held rows | C54: =COUNTIFS('Closure Cells'!$B$7:$B$126,"ET-A-A",'Closure Cells'!$O$7:$O$126,"HOLD") -> 12 | D54: 12 | E54: 0 | F54: =IF(ABS(C54-D54)<=E54,"PASS","FAIL") -> PASS
A55: A49 | B55: ET-A-A loss closes | C55: ='Form Results'!G7 -> 1 | D55: 1 | E55: 0 | F55: =IF(ABS(C55-D55)<=E55,"PASS","FAIL") -> PASS
A56: A50 | B56: ET-A-A loss failures | C56: ='Form Results'!H7 -> 3 | D56: 3 | E56: 0 | F56: =IF(ABS(C56-D56)<=E56,"PASS","FAIL") -> PASS
A57: A51 | B57: ET-A-A open coefficients | C57: ='Form Results'!J7 -> 6 | D57: 6 | E57: 0 | F57: =IF(ABS(C57-D57)<=E57,"PASS","FAIL") -> PASS
A58: A52 | B58: ET-A-A below selected symmetric screen | C58: =IF('Form Results'!E7<Inputs!$B$7,1,0) -> 1 | D58: 1 | E58: 0 | F58: =IF(ABS(C58-D58)<=E58,"PASS","FAIL") -> PASS
A59: A53 | B59: CT-C-B closure rows | C59: =COUNTIF('Closure Cells'!$B$7:$B$126,"CT-C-B") -> 20 | D59: 20 | E59: 0 | F59: =IF(ABS(C59-D59)<=E59,"PASS","FAIL") -> PASS
A60: A54 | B60: CT-C-B bounded rows | C60: =COUNTIFS('Closure Cells'!$B$7:$B$126,"CT-C-B",'Closure Cells'!$N$7:$N$126,"BOUNDED") -> 8 | D60: 8 | E60: 0 | F60: =IF(ABS(C60-D60)<=E60,"PASS","FAIL") -> PASS
A61: A55 | B61: CT-C-B held rows | C61: =COUNTIFS('Closure Cells'!$B$7:$B$126,"CT-C-B",'Closure Cells'!$O$7:$O$126,"HOLD") -> 12 | D61: 12 | E61: 0 | F61: =IF(ABS(C61-D61)<=E61,"PASS","FAIL") -> PASS
A62: A56 | B62: CT-C-B loss closes | C62: ='Form Results'!G8 -> 1 | D62: 1 | E62: 0 | F62: =IF(ABS(C62-D62)<=E62,"PASS","FAIL") -> PASS
A63: A57 | B63: CT-C-B loss failures | C63: ='Form Results'!H8 -> 3 | D63: 3 | E63: 0 | F63: =IF(ABS(C63-D63)<=E63,"PASS","FAIL") -> PASS
A64: A58 | B64: CT-C-B open coefficients | C64: ='Form Results'!J8 -> 6 | D64: 6 | E64: 0 | F64: =IF(ABS(C64-D64)<=E64,"PASS","FAIL") -> PASS
A65: A59 | B65: CT-C-B below selected symmetric screen | C65: =IF('Form Results'!E8<Inputs!$B$7,1,0) -> 1 | D65: 1 | E65: 0 | F65: =IF(ABS(C65-D65)<=E65,"PASS","FAIL") -> PASS
A66: A60 | B66: HC-A-C closure rows | C66: =COUNTIF('Closure Cells'!$B$7:$B$126,"HC-A-C") -> 20 | D66: 20 | E66: 0 | F66: =IF(ABS(C66-D66)<=E66,"PASS","FAIL") -> PASS
A67: A61 | B67: HC-A-C bounded rows | C67: =COUNTIFS('Closure Cells'!$B$7:$B$126,"HC-A-C",'Closure Cells'!$N$7:$N$126,"BOUNDED") -> 8 | D67: 8 | E67: 0 | F67: =IF(ABS(C67-D67)<=E67,"PASS","FAIL") -> PASS
A68: A62 | B68: HC-A-C held rows | C68: =COUNTIFS('Closure Cells'!$B$7:$B$126,"HC-A-C",'Closure Cells'!$O$7:$O$126,"HOLD") -> 12 | D68: 12 | E68: 0 | F68: =IF(ABS(C68-D68)<=E68,"PASS","FAIL") -> PASS
A69: A63 | B69: HC-A-C loss closes | C69: ='Form Results'!G9 -> 0 | D69: 0 | E69: 0 | F69: =IF(ABS(C69-D69)<=E69,"PASS","FAIL") -> PASS
A70: A64 | B70: HC-A-C loss failures | C70: ='Form Results'!H9 -> 4 | D70: 4 | E70: 0 | F70: =IF(ABS(C70-D70)<=E70,"PASS","FAIL") -> PASS
A71: A65 | B71: HC-A-C open coefficients | C71: ='Form Results'!J9 -> 6 | D71: 6 | E71: 0 | F71: =IF(ABS(C71-D71)<=E71,"PASS","FAIL") -> PASS
A72: A66 | B72: HC-A-C below selected symmetric screen | C72: =IF('Form Results'!E9<Inputs!$B$7,1,0) -> 1 | D72: 1 | E72: 0 | F72: =IF(ABS(C72-D72)<=E72,"PASS","FAIL") -> PASS
A73: A67 | B73: LF-B-A closure rows | C73: =COUNTIF('Closure Cells'!$B$7:$B$126,"LF-B-A") -> 20 | D73: 20 | E73: 0 | F73: =IF(ABS(C73-D73)<=E73,"PASS","FAIL") -> PASS
A74: A68 | B74: LF-B-A bounded rows | C74: =COUNTIFS('Closure Cells'!$B$7:$B$126,"LF-B-A",'Closure Cells'!$N$7:$N$126,"BOUNDED") -> 8 | D74: 8 | E74: 0 | F74: =IF(ABS(C74-D74)<=E74,"PASS","FAIL") -> PASS
A75: A69 | B75: LF-B-A held rows | C75: =COUNTIFS('Closure Cells'!$B$7:$B$126,"LF-B-A",'Closure Cells'!$O$7:$O$126,"HOLD") -> 12 | D75: 12 | E75: 0 | F75: =IF(ABS(C75-D75)<=E75,"PASS","FAIL") -> PASS
A76: A70 | B76: LF-B-A loss closes | C76: ='Form Results'!G10 -> 0 | D76: 0 | E76: 0 | F76: =IF(ABS(C76-D76)<=E76,"PASS","FAIL") -> PASS
A77: A71 | B77: LF-B-A loss failures | C77: ='Form Results'!H10 -> 4 | D77: 4 | E77: 0 | F77: =IF(ABS(C77-D77)<=E77,"PASS","FAIL") -> PASS
A78: A72 | B78: LF-B-A open coefficients | C78: ='Form Results'!J10 -> 6 | D78: 6 | E78: 0 | F78: =IF(ABS(C78-D78)<=E78,"PASS","FAIL") -> PASS
A79: A73 | B79: LF-B-A below selected symmetric screen | C79: =IF('Form Results'!E10<Inputs!$B$7,1,0) -> 1 | D79: 1 | E79: 0 | F79: =IF(ABS(C79-D79)<=E79,"PASS","FAIL") -> PASS
A80: A74 | B80: HU-A-B closure rows | C80: =COUNTIF('Closure Cells'!$B$7:$B$126,"HU-A-B") -> 20 | D80: 20 | E80: 0 | F80: =IF(ABS(C80-D80)<=E80,"PASS","FAIL") -> PASS
A81: A75 | B81: HU-A-B bounded rows | C81: =COUNTIFS('Closure Cells'!$B$7:$B$126,"HU-A-B",'Closure Cells'!$N$7:$N$126,"BOUNDED") -> 8 | D81: 8 | E81: 0 | F81: =IF(ABS(C81-D81)<=E81,"PASS","FAIL") -> PASS
A82: A76 | B82: HU-A-B held rows | C82: =COUNTIFS('Closure Cells'!$B$7:$B$126,"HU-A-B",'Closure Cells'!$O$7:$O$126,"HOLD") -> 12 | D82: 12 | E82: 0 | F82: =IF(ABS(C82-D82)<=E82,"PASS","FAIL") -> PASS
A83: A77 | B83: HU-A-B loss closes | C83: ='Form Results'!G11 -> 1 | D83: 1 | E83: 0 | F83: =IF(ABS(C83-D83)<=E83,"PASS","FAIL") -> PASS
A84: A78 | B84: HU-A-B loss failures | C84: ='Form Results'!H11 -> 3 | D84: 3 | E84: 0 | F84: =IF(ABS(C84-D84)<=E84,"PASS","FAIL") -> PASS
A85: A79 | B85: HU-A-B open coefficients | C85: ='Form Results'!J11 -> 6 | D85: 6 | E85: 0 | F85: =IF(ABS(C85-D85)<=E85,"PASS","FAIL") -> PASS
A86: A80 | B86: HU-A-B below selected symmetric screen | C86: =IF('Form Results'!E11<Inputs!$B$7,1,0) -> 1 | D86: 1 | E86: 0 | F86: =IF(ABS(C86-D86)<=E86,"PASS","FAIL") -> PASS
A87: A81 | B87: RT-B-C closure rows | C87: =COUNTIF('Closure Cells'!$B$7:$B$126,"RT-B-C") -> 20 | D87: 20 | E87: 0 | F87: =IF(ABS(C87-D87)<=E87,"PASS","FAIL") -> PASS
A88: A82 | B88: RT-B-C bounded rows | C88: =COUNTIFS('Closure Cells'!$B$7:$B$126,"RT-B-C",'Closure Cells'!$N$7:$N$126,"BOUNDED") -> 8 | D88: 8 | E88: 0 | F88: =IF(ABS(C88-D88)<=E88,"PASS","FAIL") -> PASS
A89: A83 | B89: RT-B-C held rows | C89: =COUNTIFS('Closure Cells'!$B$7:$B$126,"RT-B-C",'Closure Cells'!$O$7:$O$126,"HOLD") -> 12 | D89: 12 | E89: 0 | F89: =IF(ABS(C89-D89)<=E89,"PASS","FAIL") -> PASS
A90: A84 | B90: RT-B-C loss closes | C90: ='Form Results'!G12 -> 0 | D90: 0 | E90: 0 | F90: =IF(ABS(C90-D90)<=E90,"PASS","FAIL") -> PASS
A91: A85 | B91: RT-B-C loss failures | C91: ='Form Results'!H12 -> 4 | D91: 4 | E91: 0 | F91: =IF(ABS(C91-D91)<=E91,"PASS","FAIL") -> PASS
A92: A86 | B92: RT-B-C open coefficients | C92: ='Form Results'!J12 -> 6 | D92: 6 | E92: 0 | F92: =IF(ABS(C92-D92)<=E92,"PASS","FAIL") -> PASS
A93: A87 | B93: RT-B-C below selected symmetric screen | C93: =IF('Form Results'!E12<Inputs!$B$7,1,0) -> 1 | D93: 1 | E93: 0 | F93: =IF(ABS(C93-D93)<=E93,"PASS","FAIL") -> PASS

Sheet ReadMe
A2: Method and use
A4: This workbook is a design-solvency instrument. It contains no measured result, probability distribution or acquisition authority.
A6: Interpretation | B6: Interpretation | C6: Interpretation | D6: Interpretation | E6: Interpretation | F6: Interpretation | G6: Interpretation | H6: Interpretation
A8: Question | B8: Can all six baselines close service, mass, energy, flow and thermal accounts in four worlds under honest intervals?
A9: Answer | B9: No. The inherited configurations close nominal nonthermal arithmetic, but only 3 of 24 loss-world accounts survive the selected two-sided screen.
A10: Interval law | B10: Capacity is evaluated at its lower bound and requirement at its upper bound. The midpoint is never used.
A11: Unknown law | B11: A missing capacity, requirement or coefficient produces HOLD. Zero is a physical value and cannot stand for missing.
A12: Sensitivity | B12: The common screens are public design tests only. They are not evidence that every form shares the same uncertainty.
A13: Thermal law | B13: Each form must establish its own peak-duty coefficient and surviving heat-rejection boundary.
A14: Authority | B14: No output creates measurement, evidence, selection, MAKE, REP-4, capability, production or rendering authority.
A17: Trace and refresh | B17: Trace and refresh | C17: Trace and refresh | D17: Trace and refresh | E17: Trace and refresh | F17: Trace and refresh | G17: Trace and refresh | H17: Trace and refresh
A19: Source lineage | B19: Pass 219 Section Bills supply the twenty-four nonthermal planning rows. Pass 236 supplies the four-world and five-account grammar.
A20: Update rule | B20: Append form-native measured bounds in the source and coefficient registers. Do not overwrite inherited hypotheses.
A21: Configuration rule | B21: A changed denominator, article boundary or cell partition creates a new content-addressed baseline.
A22: Rating order | B22: Required survivor capacity equals loss requirement × (1 + requirement upside) / (1 - capacity downside).
A23: Financial rule | B23: The work remains inside the existing USD179M obligation. Rating percentage is not a cost percentage.
A24: Verification | B24: Recalculate in the target office engine, scan formula errors, test corruptions and render every sheet before release.
A25: Next decision | B25: Close geometry, load path, control, civil rights, residual custody and safe state around the revised ratings.
