Workbook

Sheet Decision
A2: First physical build portfolio
A3: Pass 206 | PFP-1 | build-to-learn authority for all six complete service systems | Verdict: CLOSE
A6: Selected portfolio
A7: Authorize a USD 200B National First Article Portfolio across all six mission systems. The first tranche builds public truth infrastructure, 96 unlike mechanism opportunities, root-native kill and resize experiments, route-complete service frames and cold-reconstruction capacity. It releases no production quantity. Production begins only after at least one root from every system survives a rotating all-six G4 mission.
A11: First-tranche control | B11: Value | C11: Unit | E11: Mature control | F11: Value | G11: Unit
A12: Total authority | B12: 200 | C12: USD billions | E12: Technology program | F12: 1000 | G12: USD billions
A13: Mission-system authority | B13: 110 | C13: USD billions | E13: First fifteen years before field acceptance | F13: 750 | G13: USD billions
A14: Systems funded | B14: 6 | C14: systems | E14: Mission-system technology | F14: 550 | G14: USD billions
A15: Problem fields | B15: 24 | C15: fields | E15: Capital estate | F15: 17400 | G15: USD billions
A16: Unlike mechanism opportunities | B16: 96 | C16: minimum | E16: Owned formations | F16: 5251 | G16: formations
A17: Complete roots retained for G3 | B17: 24 | C17: roots | E17: Ready formations | F17: 3667 | G17: formations
A18: All-six stacks required | B18: 4 | C18: stacks | E18: Committed formations | F18: 2420 | G18: formations
A19: Production authority | B19: 0 | C19: USD billions | E19: Implementation credit | F19: 0 | G19: formations
A21: Why this form
A22: Candidate | B22: All six survive | C22: Complete-service context | D22: Unlike roots | E22: Independent proof | F22: G4 barrier | G22: Failure reserve | H22: No platform credit | I22: Within USD 200B | J22: Executable now | K22: Result | L22: Governing reason
A23: ='Portfolio Test'!A7 -> Balanced first article portfolio | B23: ='Portfolio Test'!B7 -> 1 | C23: ='Portfolio Test'!C7 -> 1 | D23: ='Portfolio Test'!D7 -> 1 | E23: ='Portfolio Test'!E7 -> 1 | F23: ='Portfolio Test'!F7 -> 1 | G23: ='Portfolio Test'!G7 -> 1 | H23: ='Portfolio Test'!H7 -> 1 | ... J23: ='Portfolio Test'!J7 -> 1 | K23: ='Portfolio Test'!L7 -> SELECT | L23: ='Portfolio Test'!M7 -> All systems receive asymmetric learning authority; production remains gated.
A24: ='Portfolio Test'!A8 -> Human-continuity first | B24: ='Portfolio Test'!B8 -> 0 | C24: ='Portfolio Test'!C8 -> 1 | D24: ='Portfolio Test'!D8 -> 1 | E24: ='Portfolio Test'!E8 -> 1 | F24: ='Portfolio Test'!F8 -> 0 | G24: ='Portfolio Test'!G8 -> 1 | H24: ='Portfolio Test'!H8 -> 1 | ... J24: ='Portfolio Test'!J8 -> 1 | K24: ='Portfolio Test'!L8 -> REJECT | L24: ='Portfolio Test'!M8 -> Highest demand becomes a serial queue and starves enabling systems.
A25: ='Portfolio Test'!A9 -> Lifeline and hazard first | B25: ='Portfolio Test'!B9 -> 0 | C25: ='Portfolio Test'!C9 -> 1 | D25: ='Portfolio Test'!D9 -> 1 | E25: ='Portfolio Test'!E9 -> 1 | F25: ='Portfolio Test'!F9 -> 0 | G25: ='Portfolio Test'!G9 -> 1 | H25: ='Portfolio Test'!H9 -> 0 | ... J25: ='Portfolio Test'!J9 -> 1 | K25: ='Portfolio Test'!L9 -> REJECT | L25: ='Portfolio Test'!M9 -> Visible physics outruns civil reach, care, entry and regeneration.
A26: ='Portfolio Test'!A10 -> Mobility first | B26: ='Portfolio Test'!B10 -> 0 | C26: ='Portfolio Test'!C10 -> 0 | D26: ='Portfolio Test'!D10 -> 1 | E26: ='Portfolio Test'!E10 -> 1 | F26: ='Portfolio Test'!F10 -> 0 | G26: ='Portfolio Test'!G10 -> 1 | H26: ='Portfolio Test'!H10 -> 0 | ... J26: ='Portfolio Test'!J10 -> 1 | K26: ='Portfolio Test'!L10 -> REJECT | L26: ='Portfolio Test'!M10 -> Delivery hardware arrives before service production, reception and exit.
A27: ='Portfolio Test'!A11 -> Proving estate first | B27: ='Portfolio Test'!B11 -> 1 | C27: ='Portfolio Test'!C11 -> 0 | D27: ='Portfolio Test'!D11 -> 1 | E27: ='Portfolio Test'!E11 -> 1 | F27: ='Portfolio Test'!F11 -> 1 | G27: ='Portfolio Test'!G11 -> 1 | H27: ='Portfolio Test'!H11 -> 1 | ... J27: ='Portfolio Test'!J11 -> 0 | K27: ='Portfolio Test'!L11 -> REJECT | L27: ='Portfolio Test'!M11 -> Truth infrastructure without root-native service articles has nothing valid to test.

Sheet Portfolio Test
A2: Portfolio architecture test
A3: A candidate is selected only if every hard gate passes. A higher partial score cannot compensate for one failed constitutional condition.
A6: Candidate | B6: All six survive | C6: Complete service | D6: Unlike roots | E6: Independent proof | F6: G4 barrier | G6: Failure reserve | H6: No platform credit | I6: Within USD 200B | J6: Executable now | K6: Passed gates | L6: Result | M6: Governing reason
A7: Balanced first article portfolio | B7: 1 | C7: 1 | D7: 1 | E7: 1 | F7: 1 | G7: 1 | H7: 1 | I7: 1 | J7: 1 | K7: =SUM(B7:J7) -> 9 | L7: =IF(K7=9,"SELECT","REJECT") -> SELECT | M7: All systems receive asymmetric learning authority; production remains gated.
A8: Human-continuity first | B8: 0 | C8: 1 | D8: 1 | E8: 1 | F8: 0 | G8: 1 | H8: 1 | I8: 1 | J8: 1 | K8: =SUM(B8:J8) -> 7 | L8: =IF(K8=9,"SELECT","REJECT") -> REJECT | M8: Highest demand becomes a serial queue and starves enabling systems.
A9: Lifeline and hazard first | B9: 0 | C9: 1 | D9: 1 | E9: 1 | F9: 0 | G9: 1 | H9: 0 | I9: 1 | J9: 1 | K9: =SUM(B9:J9) -> 6 | L9: =IF(K9=9,"SELECT","REJECT") -> REJECT | M9: Visible physics outruns civil reach, care, entry and regeneration.
A10: Mobility first | B10: 0 | C10: 0 | D10: 1 | E10: 1 | F10: 0 | G10: 1 | H10: 0 | I10: 1 | J10: 1 | K10: =SUM(B10:J10) -> 5 | L10: =IF(K10=9,"SELECT","REJECT") -> REJECT | M10: Delivery hardware arrives before service production, reception and exit.
A11: Proving estate first | B11: 1 | C11: 0 | D11: 1 | E11: 1 | F11: 1 | G11: 1 | H11: 1 | I11: 1 | J11: 0 | K11: =SUM(B11:J11) -> 7 | L11: =IF(K11=9,"SELECT","REJECT") -> REJECT | M11: Truth infrastructure without root-native service articles has nothing valid to test.

Sheet Mission Systems
A2: Mission-system first-tranche allocation
A3: All six systems receive 20 percent of their USD 550B mission-system authority in the first wave. Unequal dollars reflect unequal obligations.
A6: ID | B6: Mission system | C6: Families | D6: Concurrent demand | E6: N−1 inventory | F6: Full allocation (USD B) | G6: First-wave share | H6: First tranche (USD B) | I6: Physical learning object | J6: Production credit | L6: System | M6: First tranche (USD B)
A7: MS-ET | B7: Enter a broken theater | C7: 9 | D7: 369 | E7: 827 | F7: 89.023396 | G7: 0.2 | H7: =F7*G7 -> 17.804679 | I7: Theater-entry corridor and four field competitions | J7: 0 | L7: =A7 -> MS-ET | M7: =H7 -> 17.804679
A8: MS-CT | B8: Reach occupied civil terrain | C8: 6 | D8: 343 | E8: 724 | F8: 91.872799 | G8: 0.2 | H8: =F8*G8 -> 18.37456 | I8: Occupied-terrain district and four field competitions | J8: 0 | L8: =A8 -> MS-CT | M8: =H8 -> 18.37456
A9: MS-HC | B9: Control an active hazard | C9: 4 | D9: 170 | E9: 370 | F9: 54.647956 | G9: 0.2 | H9: =F9*G9 -> 10.929591 | I9: Hazard-control cell and four field competitions | J9: 0 | L9: =A9 -> MS-HC | M9: =H9 -> 10.929591
A10: MS-LF | B10: Produce and distribute lifelines | C10: 5 | D10: 256 | E10: 554 | F10: 71.953026 | G10: 0.2 | H10: =F10*G10 -> 14.390605 | I10: Utility-sector proof campaign and four field competitions | J10: 0 | L10: =A10 -> MS-LF | M10: =H10 -> 14.390605
A11: MS-HU | B11: Preserve care and human continuity | C11: 15 | D11: 879 | E11: 1944 | F11: 153.10176 | G11: 0.2 | H11: =F11*G11 -> 30.620352 | I11: Relationship-bearing continuity district and four competitions | J11: 0 | L11: =A11 -> MS-HU | M11: =H11 -> 30.620352
A12: MS-RT | B12: Sustain, transfer and regenerate | C12: 9 | D12: 403 | E12: 832 | F12: 89.401062 | G12: 0.2 | H12: =F12*G12 -> 17.880212 | I12: Closed regeneration loop and four field competitions | J12: 0 | L12: =A12 -> MS-RT | M12: =H12 -> 17.880212
A13: Total | C13: =SUM(C7:C12) -> 48 | D13: =SUM(D7:D12) -> 2420 | E13: =SUM(E7:E12) -> 5251 | F13: =SUM(F7:F12) -> 550 | G13: =H13/F13 -> 0.2 | H13: =SUM(H7:H12) -> 110 | I13: All six remain live | J13: 0

Sheet Problem Fields
A2: Twenty-four problem-field competitions
A3: Each field keeps four unlike mechanism opportunities in the first wave. The field allocation is one quarter of its mission system and 20 percent enters the first tranche.
A6: Program | B6: System | C6: Problem field | D6: Binding coefficient | E6: Rival mechanisms | F6: Kill condition | G6: Full allocation (USD B) | H6: First-wave share | I6: First tranche (USD B) | J6: Minimum mechanisms | K6: Production credit
A7: ET-01 | B7: MS-ET | C7: No-pier heavy transfer | D7: Accepted tonnes/hour after port denial | E7: Ground-effect transfer; semisubmersible exchange; modular causeway; autonomous lighterage | F7: No rival closes sea state, receiver denial, safety and throughput. | G7: 22.255849 | H7: 0.2 | I7: =G7*H7 -> 4.4511698 | J7: 4 | K7: 0
A8: ET-02 | B8: MS-ET | C8: Austere strategic lift | D8: Complete-formation tonnes without prepared runway | E8: Ground-coupled buoyant lift; distributed electric heavy lift; short-field lifting body | F8: Payload arrives without service cell or cannot reset. | G8: 22.255849 | H8: 0.2 | I8: =G8*H8 -> 4.4511698 | J8: 4 | K8: 0
A9: ET-03 | B9: MS-ET | C9: Autonomous node opening | D9: Hours to certified 1,000-tonne/day reception | E9: Robotic survey; self-leveling surfaces; modular quay; autonomous cross-dock | F9: Opening depends on unavailable host plant, labor or utilities. | G9: 22.255849 | H9: 0.2 | I9: =G9*H9 -> 4.4511698 | J9: 4 | K9: 0
A10: ET-04 | B10: MS-ET | C10: Distributed operating bases | D10: Host-utility burden per formation-day | E10: Closed-loop mobile, offshore, rail and cellular terrain bases | F10: Base competes with population for water, power, access or waste. | G10: 22.255849 | H10: 0.2 | I10: =G10*H10 -> 4.4511698 | J10: 4 | K10: 0
A11: CT-01 | B11: MS-CT | C11: Disconnected civil state | D11: Households served without grid or cloud | E11: Local-first identity; delay-tolerant mesh; privacy-preserving edge records | F11: Coverage or rights fail for a protected cohort. | G11: 22.9682 | H11: 0.2 | I11: =G11*H11 -> 4.5936399 | J11: 4 | K11: 0
A12: CT-02 | B12: MS-CT | C12: Building and vertical access | D12: Occupied floors reached per team-hour | E12: Robotic entry; temporary vertical systems; exterior access; stair support | F12: Risk or labor is transferred to residents and caregivers. | G12: 22.9682 | H12: 0.2 | I12: =G12*H12 -> 4.5936399 | J12: 4 | K12: 0
A13: CT-03 | B13: MS-CT | C13: Accessible collection | D13: Complete person transfers per crew-hour | E13: Common-cabin mobility; autonomous carriers; modular care cabins | F13: Movement breaks caregiver, device, medicine, identity or destination. | G13: 22.9682 | H13: 0.2 | I13: =G13*H13 -> 4.5936399 | J13: 4 | K13: 0
A14: CT-04 | B14: MS-CT | C14: Degraded public communications | D14: Authenticated transactions per kilowatt-hour | E14: Air relay; terrestrial mesh; optical links; local compute and broadcast | F14: Common software, spectrum or power loss defeats access. | G14: 22.9682 | H14: 0.2 | I14: =G14*H14 -> 4.5936399 | J14: 4 | K14: 0
A15: HC-01 | B15: MS-HC | C15: Persistent fire control | D15: Contained edge per safe operating cycle | E15: Purpose-built endurance aircraft; uncrewed lattice; ground-fluid corridor | F15: Sortie output does not produce containment or safe exposure. | G15: 13.661989 | H15: 0.2 | I15: =G15*H15 -> 2.7323978 | J15: 4 | K15: 0
A16: HC-02 | B16: MS-HC | C16: Megaflow hydraulic control | D16: Controlled flow per deployed tonne and megawatt | E16: Cellular pumping; breach-arrest fabrics; mobile diversion; autonomous barriers | F16: Movement fails intake, discharge, erosion, contamination or recovery. | G16: 13.661989 | H16: 0.2 | I16: =G16*H16 -> 2.7323978 | J16: 4 | K16: 0
A17: HC-03 | B17: MS-HC | C17: Autonomous earth and debris work | D17: Hazardous volume per exposed worker-hour | E17: Teleoperation; cooperative autonomy; mobile sorting; adaptive heavy plant | F17: Productivity depends on unsafe exposure or unbounded residual. | G17: 13.661989 | H17: 0.2 | I17: =G17*H17 -> 2.7323978 | J17: 4 | K17: 0
A18: HC-04 | B18: MS-HC | C18: Environmental consequence control | D18: Time to lawful source and pathway decision | E18: Distributed sensing; aerial tomography; causal plume and watershed models | F18: Signal cannot support lawful intervention or release. | G18: 13.661989 | H18: 0.2 | I18: =G18*H18 -> 2.7323978 | J18: 4 | K18: 0
... A30: RT-04 | B30: MS-RT | C30: Workforce regeneration | D30: Certified shift-hours restored per worker-day | E30: Replacement cohorts; portable credentials; fatigue sensing; family support | F30: Readiness depends on exhausted staff or hollowed local systems. | G30: 22.350266 | H30: 0.2 | I30: =G30*H30 -> 4.4700531 | J30: 4 | K30: 0
A31: Total | B31: 6 systems | C31: 24 fields | G31: =SUM(G7:G30) -> 550 | H31: =I31/G31 -> 0.2 | I31: =SUM(I7:I30) -> 110 | J31: =SUM(J7:J30) -> 96 | K31: =SUM(K7:K30) -> 0

Sheet First Tranche
A2: USD 200B first-tranche constitution
A3: Appropriation authority is separated from obligation and production. Mission-system authority remains inside its six owning accounts.
A6: Account | B6: Authority (USD B) | C6: Share | D6: Immediate object | E6: Physical output boundary | F6: Release owner | G6: May obligate now | H6: Held for evidence | I6: Production credit
A7: Mission systems | B7: 110 | C7: =B7/$B$12 -> 0.55 | D7: Twenty-four problem fields and root-native service articles | E7: Mechanism and build-to-learn articles only | F7: Mission System Commands | G7: Yes, by field gate | H7: Unspent options stay in system | I7: 0
A8: Service technical bases | B8: 30 | C8: =B8/$B$12 -> 0.15 | D8: Professional methods, safety and configuration standards | E8: No formation or readiness inference | F8: Generating Services | G8: Yes, after denominator | H8: Unqualified methods | I8: 0
A9: Common capacity | B9: 30 | C9: =B9/$B$12 -> 0.15 | D9: Receiver emulators, public seams and shared metrology | E9: At least four unlike implementations before root credit | F9: Capital Board and public owners | G9: Yes, as noncredit infrastructure | H9: Unproved substitution | I9: 0
A10: Sovereign technical estate | B10: 20 | C10: =B10/$B$12 -> 0.1 | D10: Challenge, control, cold reconstruction and evidence custody | E10: Distributed proving functions; no mega-range | F10: Resilience Proving Service | G10: Yes, after independence review | H10: Missing authority or custody | I10: 0
A11: Failure reserve | B11: 10 | C11: =B11/$B$12 -> 0.05 | D11: Killed-root replacement and invalid-attempt capacity | E11: Cannot reward favorable outcome or move across systems | F11: Program Comptroller | G11: No | H11: Entire account | I11: 0
A12: Total | B12: =SUM(B7:B11) -> 200 | C12: =SUM(C7:C11) -> 1 | D12: One first article portfolio | H12: No production release | I12: =SUM(I7:I11) -> 0
A14: Mission-system disposition inside the USD 110B account
A15: Use | B15: Authority (USD B) | C15: Status | D15: What it buys | E15: What it cannot buy | F15: Next release
A16: Non-lifeline paired root triage | B16: 43 | C16: May stage | D16: Forty decisive endpoints, sixty rig roles and 240 valid events | E16: G3 or production | F16: BUILD PROOF disposition
A17: Lifeline first-wave authority | B17: 14.390605 | C17: May stage | D17: Method qualification and route-complete sector construction within its first-wave ceiling | E17: Full USD 36B campaign or G3 | F17: Accepted staged evidence
A18: Remaining mission-system options | B18: =$B$7-SUM(B16:B17) -> 52.609395 | C18: Held | D18: Mechanism articles, replacement roots and cost uncertainty across all six systems | E18: Transfer to apparent leader | F18: Owning-system release

Sheet Article Ladder
A2: Article Ladder
A3: Physical authority advances through objects that retain increasingly complete service context. A favorable lower-level result never releases a higher state.
A6: Level | B6: Physical object | C6: Required content | D6: Evidence question | E6: Permitted decision | F6: Forbidden conversion | G6: Owner | H6: Next object
A7: A0 | B7: Public method and interface article | C7: Denominator, measurement, custody, safety and receiver semantics | D7: Can the claim be measured and independently replayed? | E7: QUALIFY METHOD | F7: A method is not a mechanism | G7: Proving Service | H7: Mechanism article
A8: A1 | B8: Mechanism article | C8: Decisive physical principle and unlike ancestry | D8: Does the principle survive its keystone denial? | E8: SUPPORT or KILL | F8: Output is not a complete root | G8: Root House / Proving Service | H8: Root endpoint rig
A9: A2 | B9: Root endpoint rig | C9: Balance endpoint plus keystone endpoint | D9: Does the paper-balanced root survive scale and mechanism falsification? | E9: BUILD PROOF, RESIZE or KILL | F9: BUILD PROOF is not G3 | G9: Disposition Board | H9: Route-complete proof unit
A10: A3 | B10: Route-complete proof unit | C10: Every route, seven stages, receiver and residual custody | D10: Does one complete unit work under matched challenge and control? | E10: Continue root campaign | F10: One unit is not reproduction | G10: Mission System Command | H10: P1 / P2 / R1 root
A11: A4 | B11: Complete system root | C11: Paired units plus cold outside reconstruction | D11: Can an unlike root reproduce complete service and reset? | E11: G3 root release | F11: G3 is not production | G11: Proving Service and Effect Trustees | H11: All-six stack
A12: A5 | B12: Rotating all-six stack | C12: One root from every system, rotating ancestry and campaign worlds | D12: Does the Department deliver complete compound service? | E12: G4 mission disposition | F12: One stack is not fleet readiness | G12: Joint campaign authorities | H12: Production-representative increment
A13: A6 | B13: Production-representative increment | C13: Cold lot, public data, alternate route, crew, receiver and regeneration | D13: Can industry reproduce bounded units without root capture? | E13: G5 production readiness | F13: Production is not formation | G13: Industrial administration | H13: Field formation
A14: A7 | B14: Field formation and regenerated serial | C14: Articles, crew, stocks, mobility, receiver, evidence and reset | D14: Can the exact serial hold service and return? | E14: G6 field credit / G7 renewal | F14: History is not current authority | G14: JCA / Sustainment | H14: Renew, resize or retire

Sheet Root Triage
A2: Root Triage
A3: The first physical tranche separates a bad scale from a dead mechanism before the Department constructs the complete proof estate.
A6: Population | B6: Count | C6: Physical burden | D6: Valid events | E6: Evidence packages | F6: Authority (USD B) | G6: Decision law | H6: First-tranche treatment
A7: Non-lifeline complete roots | B7: 20 | C7: Forty decisive endpoints across sixty rig roles | D7: 240 | E7: 1200 | F7: 43 | G7: Balance failure → RESIZE; keystone failure → KILL | H7: Fully staged within owning system options
A8: Lifeline complete roots | B8: 4 | C8: Twelve complete quarter-service sectors in the full campaign | D8: 168 | E8: 636 | F8: 36 | G8: Six independent judgments; one successor ceiling | H8: USD 14.4B first-wave ceiling only; remainder gated
A9: All six systems | B9: 24 | C9: Twenty-four roots required for four rotating stacks | D9: 408 | E9: 1836 | F9: 79 | G9: No evidence transfer across roots or systems | H9: No G3, G4 or production credit

Sheet Evidence Gates
A2: Evidence Gates
A3: The inherited G0–G7 sequence defines exactly what each tranche may claim.
A6: Gate | B6: State created | C6: Minimum positive evidence | D6: Independent negative authority | E6: Fiscal release | F6: What remains prohibited | G6: Portfolio condition | H6: Current credit
A7: G0 | B7: Constituted service denominator | C7: Population, service, time, damage, receiver and residual contract | D7: Rights and Effect Trustees | E7: Method authority | F7: Mechanism or platform preference | G7: All six contracts retained | H7: 0
A8: G1 | B8: Qualified mechanism and method | C8: Unlike ancestry; accepted method; supported keystone endpoint | D8: Proving Service | E8: First build-to-learn block | F8: Complete-root or production claim | G8: Four opportunities per field | H8: 0
A9: G2 | B9: Integrated representative configuration | C9: Seven balances; every route; challenge and clean control | D9: Technical and safety authorities | E9: Proof construction block | F9: Root release | G9: Four configurations per system | H9: 0
A10: G3 | B10: Reproduced complete root | C10: P1/P2 and cold R1; accepted packages; reset | D10: Root Disposition Board | E10: Completed root option | F10: Joint or production claim | G10: Twenty-four root releases | H10: 0
A11: G4 | B11: Complete all-six mission | C11: Rotating stacks; ten campaign archetypes; effect acceptance | D11: Effect Trustees and sovereign receivers | E11: Joint campaign block | F11: G5 for any system if one system absent | G11: At least one root from every system | H11: 0
A12: G5 | B12: Production readiness | C12: Cold production lot; public technical data; alternate supply and recovery | D12: Industrial administration and Proving Service | E12: Production tranche | F12: Formation or readiness | G12: All-six G4 barrier already passed | H12: 0
A13: G6 | B13: Bounded field credit | C13: Exact formation warrant, readiness, receiver and campaign evidence | D13: JCA and Public Allocation Ledger | E13: Fielding increment | F13: Sibling or fleet-wide credit | G13: Serial-specific | H13: 0
A14: G7 | B14: Renewal, resize or retirement | C14: Current evidence, challenger, regeneration and effect disposition | D14: Effect Trustees and Sustainment | E14: Renewal only | F14: Prestige or history as authority | G14: Unlike challenger retained | H14: 0

Sheet Production Release
A2: Technology and production release sequence
A3: Production authority begins in years 16–20 only after the G4 all-six barrier. Earlier tranches buy learning, proof and joint evidence.
A6: Tranche | B6: Years | C6: Program authority (USD B) | D6: Cumulative (USD B) | E6: Entry gate | F6: Required exit | G6: Primary physical output | H6: Production quantity | I6: Failure disposition | J6: Portfolio rule
A7: T1 — first articles | B7: 1–5 | C7: 200 | D7: =C7 -> 200 | E7: G0 | F7: G1 | G7: Methods, mechanism articles, endpoint rigs and first service frames | H7: 0 | I7: Kill, resize or retain within system | J7: All six systems funded
A8: T2 — integrated roots | B8: 6–10 | C8: 300 | D8: =D7+C8 -> 500 | E8: G1 | F8: G2–G3 | G8: Complete route units, paired proof and cold reconstruction | H8: 0 | I8: Adverse evidence stays in denominator | J8: No system can absorb another's failure money
A9: T3 — complete missions | B9: 11–15 | C9: 250 | D9: =D8+C9 -> 750 | E9: G3 | F9: G4 | G9: Four rotating all-six stacks across representative campaigns | H9: 0 | I9: Failed dependency denies focal claim | J9: All-six mission is unit of truth
A10: T4 — production and field use | B10: 16–20 | C10: 150 | D10: =D9+C10 -> 900 | E10: G4 | F10: G5–G6 | G10: Cold lots and bounded production-representative formations | I10: Hold serial-specific release | J10: No system enters G5 before all-six G4
A11: T5 — challenge and renewal | B11: 21–25 | C11: 100 | D11: =D10+C11 -> 1000 | E11: G6 | F11: G7 | G11: Unlike challengers, regeneration and retirement replacements | I11: Renew, resize or retire | J11: History and prestige create no authority

Sheet Authority
A2: Authority
A3: Every physical release is a transaction among separate authorities. No program integrator may fund, build, prove and accept its own result.
A6: Authority | B6: Owns | C6: Physical artifact | D6: May release | E6: May stop | F6: Cannot infer | G6: Alternate | H6: Public record
A7: Capital Board | B7: Fiscal option | C7: Staged account authority | D7: Appropriation tranche | E7: Unearned option | F7: Spending → capability | G7: Independent fiscal panel | H7: Option and cancellation
A8: Mission System Commands | B8: Complete service requirement | C8: Denominator and route baseline | D8: Field competition | E8: Incomplete chain | F8: Mission ownership → release | G8: Alternate mission office | H8: Baseline and change
A9: Generating Services | B9: Professional and technical state | C9: Methods, articles, formation content | D9: Technical release | E9: Unsafe configuration | F9: Article → formation | G9: Unlike service authority | H9: Configuration release
A10: Root Houses | B10: Candidate design | C10: Mechanism and root articles | D10: Controlled root claim | E10: Own withdrawal | F10: Industry → proof | G10: Unlike root | H10: Ancestry and bill
A11: Resilience Proving Service | B11: Adverse evidence | C11: Challenge, control and cold reconstruction | D11: Evidence disposition | E11: Invalid method or unreproduced claim | F11: Trial result → authority | G11: Unlike proving root | H11: Evidence packet
A12: Root Disposition Board | B12: Root decision | C12: Complete root dossier | D12: BUILD PROOF, RESIZE or KILL | E12: Missing or conflicting evidence | F12: Favorable score → release | G12: Independent panel | H12: Reasoned disposition
A13: Effect Trustees | B13: Civil acceptance | C13: Observed service and effect records | D13: G4 effect disposition | E13: Incomplete or unknown effect | F13: Output → effect | G13: Unlike trustee panel | H13: Effect ledger
A14: Industrial administration | B14: Production reproducibility | C14: Cold lot and recovery path | D14: G5 availability | E14: Unqualified lot | F14: Factory → formation | G14: Public production cell | H14: Lot genealogy
A15: Joint Capacity Authority | B15: Readiness | C15: Exact formation serial | D15: G6 readiness state | E15: Missing family or decayed evidence | F15: Inventory → readiness | G15: Alternate joint board | H15: Family state
A16: Sovereign receivers | B16: Use and transfer | C16: Receiver interface and service packet | D16: Acceptance and transfer | E16: Rights, custody or host stop | F16: Access → command | G16: Named sovereign alternate | H16: Consent and exit

Sheet Industry
A2: Industry
A3: The first tranche creates a national experimental economy before it creates production winners.
A6: Industrial layer | B6: Scale | C6: First-tranche role | D6: Required diversity | E6: Public asset | F6: Private opportunity | G6: No-credit rule | H6: Later conversion
A7: Problem-field mechanism teams | B7: 96 | C7: Build unlike physical principles across twenty-four fields | D7: Four per field | E7: Public denominator and interfaces | F7: New primes and specialist firms | G7: Mechanism success is not a root | H7: Synthesize complete roots
A8: Complete Root Houses | B8: 24 | C8: Integrate four roots per mission system | D8: Four unlike roots per system | E8: Public technical seams | F8: Lockheed-scale complete-system integrators | G8: Paper balance is not evidence | H8: G3 root campaigns
A9: Proving Service stations | B9: 15 | C9: Non-lifeline challenge, control and reconstruction | D9: Three separated station classes | E9: Ranges, metrology and evidence custody | F9: Instrumentation and casualty-field supply | G9: Test capacity is not truth | H9: Distributed national proving estate
A10: Lifeline proof sectors | B10: 12 | C10: Paired and cold-rebuilt utility service sectors | D10: Four root-native lineages | E10: Receiver spines and quality custody | F10: Water, power, thermal and residual systems | G10: One sector is not reproduction | H10: Four G3 lifeline roots
A11: Public production cells | B11: 24 | C11: Design and readiness work only in T1 | D11: One per root with separated cold paths | E11: Fallback tooling and public data | F11: Commercial useful output and export | G11: Factory is not formation | H11: G5 cold-lot production
A12: Civil Service professions | B12: 13.0M | C12: Staff design, proving, operation and regeneration | D12: Career, reserve, covenant, productive and partner statuses | E12: Academies and portable credentials | F12: Qualified labor ecosystems | G12: Employment is not readiness | H12: Formation and renewal

Sheet 25-Year Path
A2: Twenty-five-year technology authority
A3: Five inherited waves conserve the USD 1.00T technology program. Annual timing is even within each five-year wave for transparency.
A6: Year | B6: Wave | C6: Mission systems | D6: Service technical bases | E6: Common capacity | F6: Sovereign technical estate | G6: Failure reserve | H6: Annual authority | I6: Cumulative authority | J6: Production permitted
A7: 1 | B7: 1 | C7: 22 | D7: 6 | E7: 6 | F7: 4 | G7: 2 | H7: =SUM(C7:G7) -> 40 | I7: =H7 -> 40 | J7: NO
A8: 2 | B8: 1 | C8: 22 | D8: 6 | E8: 6 | F8: 4 | G8: 2 | H8: =SUM(C8:G8) -> 40 | I8: =I7+H8 -> 80 | J8: NO
A9: 3 | B9: 1 | C9: 22 | D9: 6 | E9: 6 | F9: 4 | G9: 2 | H9: =SUM(C9:G9) -> 40 | I9: =I8+H9 -> 120 | J9: NO
A10: 4 | B10: 1 | C10: 22 | D10: 6 | E10: 6 | F10: 4 | G10: 2 | H10: =SUM(C10:G10) -> 40 | I10: =I9+H10 -> 160 | J10: NO
A11: 5 | B11: 1 | C11: 22 | D11: 6 | E11: 6 | F11: 4 | G11: 2 | H11: =SUM(C11:G11) -> 40 | I11: =I10+H11 -> 200 | J11: NO
A12: 6 | B12: 2 | C12: 33 | D12: 9 | E12: 9 | F12: 6 | G12: 3 | H12: =SUM(C12:G12) -> 60 | I12: =I11+H12 -> 260 | J12: NO
A13: 7 | B13: 2 | C13: 33 | D13: 9 | E13: 9 | F13: 6 | G13: 3 | H13: =SUM(C13:G13) -> 60 | I13: =I12+H13 -> 320 | J13: NO
A14: 8 | B14: 2 | C14: 33 | D14: 9 | E14: 9 | F14: 6 | G14: 3 | H14: =SUM(C14:G14) -> 60 | I14: =I13+H14 -> 380 | J14: NO
A15: 9 | B15: 2 | C15: 33 | D15: 9 | E15: 9 | F15: 6 | G15: 3 | H15: =SUM(C15:G15) -> 60 | I15: =I14+H15 -> 440 | J15: NO
A16: 10 | B16: 2 | C16: 33 | D16: 9 | E16: 9 | F16: 6 | G16: 3 | H16: =SUM(C16:G16) -> 60 | I16: =I15+H16 -> 500 | J16: NO
A17: 11 | B17: 3 | C17: 27.5 | D17: 7.5 | E17: 7.5 | F17: 5 | G17: 2.5 | H17: =SUM(C17:G17) -> 50 | I17: =I16+H17 -> 550 | J17: NO
A18: 12 | B18: 3 | C18: 27.5 | D18: 7.5 | E18: 7.5 | F18: 5 | G18: 2.5 | H18: =SUM(C18:G18) -> 50 | I18: =I17+H18 -> 600 | J18: NO
A19: 13 | B19: 3 | C19: 27.5 | D19: 7.5 | E19: 7.5 | F19: 5 | G19: 2.5 | H19: =SUM(C19:G19) -> 50 | I19: =I18+H19 -> 650 | J19: NO
... A31: 25 | B31: 5 | C31: 11 | D31: 3 | E31: 3 | F31: 2 | G31: 1 | H31: =SUM(C31:G31) -> 20 | I31: =I30+H31 -> 1000 | J31: YES
A32: Total | C32: =SUM(C7:C31) -> 550 | D32: =SUM(D7:D31) -> 150 | E32: =SUM(E7:E31) -> 150 | F32: =SUM(F7:F31) -> 100 | G32: =SUM(G7:G31) -> 50 | H32: =SUM(H7:H31) -> 1000 | I32: =I31 -> 1000 | J32: G4 required

Sheet Stress Tests
A2: Stress Tests
A3: Each world tests whether the portfolio can learn and continue without manufacturing production authority.
A6: # | B6: Stress world | C6: Required response | D6: Exact gate | E6: Held authority | F6: Forbidden shortcut | G6: Result | H6: Reason
A7: 1 | B7: Human continuity is ready first | C7: Retain other five systems and hold G5 | D7: G4 | E7: 150 | F7: Demand rank → production | G7: PASS | H7: All-six barrier survives
A8: 2 | B8: Lifeline root passes while civil terrain fails | C8: Keep lifeline G3; deny joint G4 | D8: G4 | E8: 250 | F8: One strong system → Department maturity | G8: PASS | H8: Dependency failure stays visible
A9: 3 | B9: Common interface has one implementation | C9: Fund three unlike alternatives | D9: G2 | F9: Standard title → independence | G9: PASS | H9: Four implementations required
A10: 4 | B10: Keystone trial fails | C10: Kill lineage and use owning-system option | D10: G1 | F10: Scale increase → mechanism repair | G10: PASS | H10: Failure meaning preserved
A11: 5 | B11: Balance endpoint fails | C11: Resize configuration and repeat full evidence | D11: G2 | F11: Mechanism death → budget transfer | G11: PASS | H11: Scale and mechanism differ
A12: 6 | B12: First-wave cost exceeds system option | C12: Reduce scope or return authority | D12: G1 | F12: Raid another system | G12: PASS | H12: All six remain funded
A13: 7 | B13: Mega-range becomes unavailable | C13: Use separated challenge, control and reconstruction stations | D13: G2 | F13: One site → national proof | G13: PASS | H13: No common truth bottleneck
A14: 8 | B14: Prototype is demanded during disaster | C14: Use ready force; keep experimental article outside readiness | D14: G6 | F14: Urgency → field credit | G14: PASS | H14: Experiment is not force
A15: 9 | B15: Cold lot succeeds without receiver path | C15: Hold G5 | D15: G5 | E15: 150 | F15: Factory output → capability | G15: PASS | H15: Complete chain required
A16: 10 | B16: Partner buys a mechanism | C16: Keep market and U.S. readiness ledgers separate | D16: G6 | F16: Export → readiness | G16: PASS | H16: Revenue creates no authority
A17: 11 | B17: One all-six stack passes | C17: Retain rotation and campaign coverage | D17: G4 | E17: 250 | F17: Single success → blanket production | G17: PASS | H17: Ancestry rotation remains
A18: 12 | B18: Outcome-aware repeat proposed | C18: Reject repeat and preserve adverse result | D18: G1–G4 | F18: Retry → favorable evidence | G18: PASS | H18: Valid adverse evidence is permanent

Sheet Mutations
A2: Mutations
A3: Deliberate invalid states must fail and restore with zero production credit.
A6: # | B6: Mutation | C6: Broken law | D6: Expected | E6: Observed | F6: Restoration | G6: Restored | H6: Production credit
A7: 1 | B7: Fund only the highest-demand system | C7: All six survive | D7: FAIL | E7: FAIL | F7: Restore six system accounts | G7: YES | H7: 0
A8: 2 | B8: Treat mechanism pass as root release | C8: Article ladder | D8: FAIL | E8: FAIL | F8: Return to endpoint rig | G8: YES | H8: 0
A9: 3 | B9: Transfer failure reserve to apparent leader | C9: Owning-account conservation | D9: FAIL | E9: FAIL | F9: Restore protected reserve | G9: YES | H9: 0
A10: 4 | B10: Let root house accept its own evidence | C10: Authority separation | D10: FAIL | E10: FAIL | F10: Restore independent proving | G10: YES | H10: 0
A11: 5 | B11: Enter G5 with one system absent from G4 | C11: All-six barrier | D11: FAIL | E11: FAIL | F11: Hold production tranche | G11: YES | H11: 0
A12: 6 | B12: Count cold lot as formation | C12: Production is not readiness | D12: FAIL | E12: FAIL | F12: Require formation warrant | G12: YES | H12: 0
A13: 7 | B13: Average a failed route into system score | C13: Complete service | D13: FAIL | E13: FAIL | F13: Restore conjunctive route gate | G13: YES | H13: 0
A14: 8 | B14: Repeat valid adverse trial | C14: Permanent adverse evidence | D14: FAIL | E14: FAIL | F14: Retain result and disposition | G14: YES | H14: 0

Sheet Audit
A2: Terminal audit
A3: Checks observe the portfolio and do not feed decisions, inputs or releases.
A6: # | B6: Audit | C6: Actual | D6: Required | E6: Status | F6: Interpretation
A7: 1 | B7: Selected candidate gates | C7: ='Portfolio Test'!K7 -> 9 | D7: 9 | E7: =IF(ABS(C7-D7)<0.01,"PASS","FAIL") -> PASS | F7: All hard gates
A8: 2 | B8: Selected candidate status | C8: =COUNTIFS('Portfolio Test'!L7:L11,"SELECT") -> 1 | D8: 1 | E8: =IF(ABS(C8-D8)<0.01,"PASS","FAIL") -> PASS | F8: Exactly one selected
A9: 3 | B9: Systems funded | C9: =COUNTA('Mission Systems'!A7:A12) -> 6 | D9: 6 | E9: =IF(ABS(C9-D9)<0.01,"PASS","FAIL") -> PASS | F9: All six survive
A10: 4 | B10: Family total | C10: ='Mission Systems'!C13 -> 48 | D10: 48 | E10: =IF(ABS(C10-D10)<0.01,"PASS","FAIL") -> PASS | F10: All families
A11: 5 | B11: Concurrent demand | C11: ='Mission Systems'!D13 -> 2420 | D11: 2420 | E11: =IF(ABS(C11-D11)<0.01,"PASS","FAIL") -> PASS | F11: Committed demand
A12: 6 | B12: Inventory | C12: ='Mission Systems'!E13 -> 5251 | D12: 5251 | E12: =IF(ABS(C12-D12)<0.01,"PASS","FAIL") -> PASS | F12: Owned force
A13: 7 | B13: Mission allocation | C13: ='Mission Systems'!F13 -> 550 | D13: 550 | E13: =IF(ABS(C13-D13)<0.01,"PASS","FAIL") -> PASS | F13: Full mission account
A14: 8 | B14: First-wave share | C14: ='Mission Systems'!G13 -> 0.2 | D14: 0.2 | E14: =IF(ABS(C14-D14)<0.01,"PASS","FAIL") -> PASS | F14: Common wave share
A15: 9 | B15: Mission first tranche | C15: ='Mission Systems'!H13 -> 110 | D15: 110 | E15: =IF(ABS(C15-D15)<0.01,"PASS","FAIL") -> PASS | F15: System authority
A16: 10 | B16: System production credit | C16: ='Mission Systems'!J13 -> 0 | D16: 0 | E16: =IF(ABS(C16-D16)<0.01,"PASS","FAIL") -> PASS | F16: No production
A17: 11 | B17: Problem fields | C17: =COUNTA('Problem Fields'!A7:A30) -> 24 | D17: 24 | E17: =IF(ABS(C17-D17)<0.01,"PASS","FAIL") -> PASS | F17: All fields
A18: 12 | B18: Mechanism opportunities | C18: ='Problem Fields'!J31 -> 96 | D18: 96 | E18: =IF(ABS(C18-D18)<0.01,"PASS","FAIL") -> PASS | F18: Four per field
A19: 13 | B19: Field production credit | C19: ='Problem Fields'!K31 -> 0 | D19: 0 | E19: =IF(ABS(C19-D19)<0.01,"PASS","FAIL") -> PASS | F19: No field release
A20: 14 | B20: First-tranche accounts | C20: =COUNTA('First Tranche'!A7:A11) -> 5 | D20: 5 | E20: =IF(ABS(C20-D20)<0.01,"PASS","FAIL") -> PASS | F20: Exclusive account classes
A21: 15 | B21: First-tranche total | C21: ='First Tranche'!B12 -> 200 | D21: 200 | E21: =IF(ABS(C21-D21)<0.01,"PASS","FAIL") -> PASS | F21: Wave-one ceiling
A22: 16 | B22: First-tranche share | C22: ='First Tranche'!C12 -> 1 | D22: 1 | E22: =IF(ABS(C22-D22)<0.01,"PASS","FAIL") -> PASS | F22: Account conservation
A23: 17 | B23: First-tranche production | C23: ='First Tranche'!I12 -> 0 | D23: 0 | E23: =IF(ABS(C23-D23)<0.01,"PASS","FAIL") -> PASS | F23: No production
A24: 18 | B24: Non-lifeline endpoint authority | C24: ='First Tranche'!B16 -> 43 | D24: 43 | E24: =IF(ABS(C24-D24)<0.01,"PASS","FAIL") -> PASS | F24: Inherited ceiling
A25: 19 | B25: Lifeline first-wave authority | C25: ='First Tranche'!B17 -> 14.390605 | D25: 14.390605 | E25: =IF(ABS(C25-D25)<0.01,"PASS","FAIL") -> PASS | F25: Twenty percent
A26: 20 | B26: Mission options retained | C26: ='First Tranche'!B18 -> 52.609395 | D26: 52.609395 | E26: =IF(ABS(C26-D26)<0.01,"PASS","FAIL") -> PASS | F26: Unassigned within systems
A27: 21 | B27: Root population | C27: ='Root Triage'!B9 -> 24 | D27: 24 | E27: =IF(ABS(C27-D27)<0.01,"PASS","FAIL") -> PASS | F27: Four per system
A28: 22 | B28: Valid events | C28: ='Root Triage'!D9 -> 408 | D28: 408 | E28: =IF(ABS(C28-D28)<0.01,"PASS","FAIL") -> PASS | F28: Inherited designs
A29: 23 | B29: Evidence packages | C29: ='Root Triage'!E9 -> 1836 | D29: 1836 | E29: =IF(ABS(C29-D29)<0.01,"PASS","FAIL") -> PASS | F29: Inherited designs
A30: 24 | B30: Gate count | C30: =COUNTA('Evidence Gates'!A7:A14) -> 8 | D30: 8 | E30: =IF(ABS(C30-D30)<0.01,"PASS","FAIL") -> PASS | F30: G0–G7
A31: 25 | B31: Production starts tranche | C31: =COUNTIFS('Production Release'!H7:H9,0) -> 3 | D31: 3 | E31: =IF(ABS(C31-D31)<0.01,"PASS","FAIL") -> PASS | F31: No early production
A32: 26 | B32: Technology total | C32: ='25-Year Path'!H32 -> 1000 | D32: 1000 | E32: =IF(ABS(C32-D32)<0.01,"PASS","FAIL") -> PASS | F32: Program control
A33: 27 | B33: Mission-system total | C33: ='25-Year Path'!C32 -> 550 | D33: 550 | E33: =IF(ABS(C33-D33)<0.01,"PASS","FAIL") -> PASS | F33: Mission control
A34: 28 | B34: Pre-field authority | C34: =SUM('Production Release'!C7:C9) -> 750 | D34: 750 | E34: =IF(ABS(C34-D34)<0.01,"PASS","FAIL") -> PASS | F34: First fifteen years
A35: 29 | B35: Stress tests | C35: =COUNTIFS('Stress Tests'!G7:G18,"PASS") -> 12 | D35: 12 | E35: =IF(ABS(C35-D35)<0.01,"PASS","FAIL") -> PASS | F35: All pass
A36: 30 | B36: Mutation failures | C36: =COUNTIFS(Mutations!E7:E14,"FAIL") -> 8 | D36: 8 | E36: =IF(ABS(C36-D36)<0.01,"PASS","FAIL") -> PASS | F36: All detected
A37: 31 | B37: Mutation restores | C37: =COUNTIFS(Mutations!G7:G14,"YES") -> 8 | D37: 8 | E37: =IF(ABS(C37-D37)<0.01,"PASS","FAIL") -> PASS | F37: All restored
A38: 32 | B38: Mutation production credit | C38: =SUM(Mutations!H7:H14) -> 0 | D38: 0 | E38: =IF(ABS(C38-D38)<0.01,"PASS","FAIL") -> PASS | F38: No synthetic release

Sheet Sources & Limits
A2: Sources & Limits
A3: Repository-internal sources only. The workbook defines a planning constitution, not a procurement decision or observed capability.
A6: Source or limit | B6: Title | C6: Claims used | D6: Status
A7: Pass 168 | B7: Six Mission-System Portfolio Topology | C7: Six systems, 24 fields, USD 550B allocation | D7: Authoritative
A8: Pass 171 | B8: Coupled Development Wavefront | C8: Five waves, all-six G4 barrier and USD 1.00T accounts | D8: Authoritative
A9: Pass 179 | B9: Lifeline G3 Return | C9: Ten-element proof kernel and USD 36.0B lifeline campaign | D9: Authoritative
A10: Pass 180 | B10: Six-System G3 Proof Unit | C10: 24 roots, 1,428 units, 1,008 events and 4,276 packages | D10: Authoritative
A11: Pass 183 | B11: Pre-Article Falsification | C11: 40 endpoints, 60 rig roles, 240 events and USD 43.0B ceiling | D11: Authoritative
A12: Pass 184 | B12: Resilience Proving Service Return | C12: Independent proof institution, 15 stations and 75 lanes | D12: Authoritative
A13: Pass 195 | B13: Force-Generation Compact | C13: Formation, readiness and allocation firebreaks | D13: Integrated
A14: Pass 205 | B14: Department Constitutional Compact | C14: Five houses, 17 warrants and USD 68.4T public economy | D14: Integrated
A15: Source status | B15: All physical identities and observations | C15: No article, root, station, supplier or site is commissioned | D15: Source-empty
A16: Fiscal status | B16: Technology authority only | C16: USD 1.00T is nested inside the USD 68.4T Department economy | D16: Do not add
A17: Production status | B17: No G4 evidence exists | C17: T4 production authority is conditional, not released | D17: Zero
... A19: Next decision | B19: First-tranche industrial execution | C19: How four roots per system are contracted without common control | D19: Frontier
