Workbook

Sheet Decision
A2: Department force-generation compact and return
A4: Pass 195 | DFG-5 | five circuits create mass without consolidating truth or authority
M5: Circuit | N5: Primary scale
A6: Decision metric | B6: Value | M6: Industry | N6: 24
A7: Verdict | B7: RETURN | M7: Formation | N7: 5251
A8: Deepest branch | B8: DFG-5, fifth of five | M8: Ready | N8: 3667
A9: Selected architecture | B9: Constitutional five-circuit compact | M9: Committed | N9: 2420
A10: Circuits | B10: 5 | M10: Reserve | N10: 502
A11: Institution classes | B11: 15
A12: State transitions | B12: 10
A13: Forbidden conversions | B13: 12
A14: Root Houses | B14: 24
A15: Owned formations | B15: 5251
A16: Ready floor | B16: 3667
A17: Committed force | B17: 2420
A18: Protected reserve | B18: 502
A19: Mature capital screen USD B | B19: 17400
A20: Mature annual operations USD B | B20: 2110
A21: Domestic market USD B/year | B21: 75
A22: Released authority | B22: 0
A23: Return state | B23: SOURCE EMPTY / HOLD

Sheet Controls
A2: Force-generation compact controls
A4: Three fiscal circuits remain separate; blue controls cannot manufacture authority.
A6: Control | B6: Value | C6: Unit
A7: Technology program | B7: 1000 | C7: USD B
A8: Formation capital | B8: 9410.56 | C8: USD B
A9: Common capital and reserve | B9: 7989.44 | C9: USD B
A10: Mature capital screen | B10: 17400 | C10: USD B
A11: Mature annual operations | B11: 2110 | C11: USD B/year
A12: Domestic market | B12: 75 | C12: USD B/year
A13: Reference partner market | B13: 12 | C13: USD B/year
A14: Build years | B14: 11 | C14: years
A15: Sustaining years | B15: 15 | C15: years
A16: Owned formations | B16: 5251 | C16: formations
A17: Ready floor | B17: 3667 | C17: formations
A18: Released authority | B18: 0 | C18: formations

Sheet Architecture
A2: Force-generation integration architecture
A4: Only the compact integrates the full cycle without giving one hierarchy all warrants.
A6: Architecture | B6: Civil sovereignty | C6: Root rivalry | D6: Service depth | E6: Independent proof | F6: Serial formation | G6: Family readiness | H6: Scarcity law | I6: Fiscal separation | J6: Regeneration | K6: Public rollback | L6: Decision
A7: One Force Generation Command | B7: PASS | C7: FAIL | D7: FAIL | E7: FAIL | F7: FAIL | G7: FAIL | H7: FAIL | I7: FAIL | J7: FAIL | K7: FAIL | L7: REJECT
A8: Seven sovereign services | B8: PASS | C8: PASS | D8: FAIL | E8: FAIL | F8: FAIL | G8: FAIL | H8: FAIL | I8: FAIL | J8: FAIL | K8: FAIL | L8: REJECT
A9: Industrial mobilization state | B9: PASS | C9: PASS | D9: PASS | E9: FAIL | F9: FAIL | G9: FAIL | H9: FAIL | I9: FAIL | J9: FAIL | K9: FAIL | L9: REJECT
A10: Operational-command economy | B10: PASS | C10: PASS | D10: PASS | E10: PASS | F10: PASS | G10: FAIL | H10: FAIL | I10: FAIL | J10: FAIL | K10: FAIL | L10: REJECT
A11: Constitutional five-circuit compact | B11: PASS | C11: PASS | D11: PASS | E11: PASS | F11: PASS | G11: PASS | H11: PASS | I11: PASS | J11: PASS | K11: PASS | L11: SELECT

Sheet Five-Circuit Compact
A2: Constitutional five-circuit compact
A4: The interfaces are permanent; authority does not flow upward into a force-generation super-command.
A6: Circuit | B6: Domain | C6: Principal institutions | D6: Positive power | E6: Prohibition
A7: C1 | B7: Public purpose and capital | C7: Civil Resilience Authority; Capital Board | D7: Public effects, program ceilings and cancellation | E7: Cannot select mechanism, evidence or serial
A8: C2 | B8: Technology and productive commonwealth | C8: Mission Systems; Root Houses; Industrial Mobilization Administration | D8: Compete roots, reproduce configurations, sustain labor and suppliers | E8: Factory and revenue create zero force credit
A9: C3 | B9: Formation generation | C9: Seven services; Strategic Sustainment; Resilience Proving Service | D9: Bind articles, crews, stocks, receivers and ten warrants | E9: Equipment or favorable output cannot self-certify
A10: C4 | B10: Readiness and allocation | C10: Joint Capacity Authority; NMAC; Rights and Scarcity Tribunal | D10: Maintain family floors and issue collision-free schedules | E10: Aggregate slack cannot cure scarce families
A11: C5 | B11: Employment, transfer and regeneration | C11: Operational commands; civil/host receivers; Productive Commonwealth | D11: Deliver accepted effects, transfer service, return and rebuild serials | E11: Employment cannot rewrite evidence or custody

Sheet Institution Map
A2: Fifteen institution classes
A4: Scale comes from specialized powers joined by public interfaces, not one consolidated chain.
A6: Institution | B6: Exclusive role
A7: Civil Resilience Authority | B7: Public priority, admission, acceptance, transfer
A8: Department Capital Board | B8: Portfolio option, stage and cancellation authority
A9: Six Mission System Commands | B9: Complete end-to-end service baselines
A10: Seven operating services | B10: Professions, article release and formation generation
A11: Twenty-four Root Houses | B11: Independent design, build and reproduction roots
A12: Industrial Mobilization Administration | B12: Public rights, alternate production and productive estate
A13: Resilience Proving Service | B13: Hostile worlds, evidence custody and adverse disposition
A14: Strategic Sustainment Command | B14: Stocks, replacement and regeneration
A15: Joint Capacity Authority | B15: Serial readiness, family floors and reservation
A16: National Mobilization and Allocation Command | B16: Collision-free executable schedules
A17: Seven District Commands | B17: Local access, stocks, crews and receivers
... A21: Public Allocation Ledger | B21: Reconstructable decisions, failures and rollback

Sheet Authority Boundaries
A2: Five exclusive warrant domains
A4: Each circuit receives inputs but cannot issue its own successor state.
A6: Domain | B6: Owner | C6: Input received | D6: Output issued | E6: Cannot issue
A7: Public value | B7: Civil Resilience Authority | C7: Population state and lawful objective | D7: Accepted effect and transfer | E7: Technical or readiness release
A8: Technical truth | B8: Services + Proving Service | C8: Controlled mechanism and trials | D8: Article/formation evidence | E8: Civil priority or allocation
A9: Industrial reproducibility | B9: Root Houses + IMA | C9: Public rights and accepted configuration | D9: Cold production availability | E9: Formation credit
A10: Readiness truth | B10: Joint Capacity Authority | C10: Ten-warrant serial and exclusive claims | D10: Family-ready state | E10: Campaign priority
A11: Executable allocation | B11: NMAC + rights/custody authorities | C11: Admitted claim and ready serials | D11: Twelve-seal schedule | E11: Evidence or civil acceptance

Sheet State Transitions
A2: Ten-state public-service lifecycle
A4: Every transition has one positive artifact and one prohibited inference.
A6: From | B6: To | C6: Issuing authority | D6: Positive artifact | E6: Prohibited inference
A7: Public effect | B7: Mission baseline | C7: Civil Resilience Authority | D7: Accepted need and measurable service | E7: No platform requirement
A8: Mission baseline | B8: Root competition | C8: Mission System Command | D8: Unlike mechanisms and kill criteria | E8: No favored exterior
A9: Root competition | B9: Production availability | C9: Root House + RPS + Industrial Mobilization | D9: Reproducible cold route | E9: No formation credit
A10: Production availability | B10: Accepted article | C10: Operating service | D10: Controlled equipment and technical release | E10: No crew/readiness credit
A11: Accepted article | B11: Service formation | C11: Operating service + RPS | D11: Ten warrants on one serial | E11: No averaging
A12: Service formation | B12: Ready family pool | C12: Joint Capacity Authority | D12: Family floor, district and reservation pass | E12: No aggregate percentage
A13: Ready family pool | B13: Allocation order | C13: NMAC + civil/rights authorities | D13: Twelve seals and zero collisions | E13: No executive waiver
A14: Allocation order | B14: Campaign credit | C14: Operational command + civil receiver | D14: Complete public service accepted | E14: No output-only success
A15: Campaign credit | B15: Transfer | C15: Civil/host receiver | D15: Local capacity and residual custody accepted | E15: No premature exit
A16: Transfer | B16: Regenerated serial | C16: Strategic Sustainment + productive commonwealth | D16: Cold rebuild and recertification | E16: No erased adverse history

Sheet Nonconversion Laws
A2: Twelve forbidden conversions
A4: These are constitutional firebreaks, not accounting preferences.
A6: Law | B6: Forbidden conversion | C6: Reason
A7: P01 | B7: Program spending → capability | C7: Money spent never issues a technical, evidentiary or readiness warrant
A8: P02 | B8: Market revenue → readiness | C8: Useful civil sales sustain industry but create zero formation credit
A9: P03 | B9: Factory → formation | C9: Tooling, workers and cold lots are regeneration sources only
A10: P04 | B10: Accepted article → formation | C10: Equipment lacks crew, stocks, receiver, command, trial and regeneration
A11: P05 | B11: Service formation → campaign | C11: Joint interface, concurrent trial and civil admission remain separate
A12: P06 | B12: Aggregate inventory → family coverage | C12: Every one of forty-eight families is non-substitutable
A13: P07 | B13: Aggregate reserve → new campaign | C13: A 502-formation reserve covers only 390 of a 406-formation event
A14: P08 | B14: Geographic buffer → general reserve | C14: Conversion consumes published N−1 assurance
A15: P09 | B15: Crew relief → free article | C15: An occupied article remains committed through recertification
A16: P10 | B16: International urgency → domestic recall | C16: Accepted serials require bilateral release
A17: P11 | B17: Positive evidence → erased failure | C17: Adverse history and rollback remain public
A18: P12 | B18: Common interface → quantity saving | C18: Only exclusive reservation plus substitution evidence reduces force

Sheet Industrial Base
A2: Productive Commonwealth input circuit
A4: Industry supplies regeneration and useful civil output; every identity remains source-empty.
A6: Metric | B6: Value | C6: Unit | D6: Force-credit rule
A7: Industrial Root Houses | B7: 24 | C7: firms | D7: ZERO UNTIL SERIAL CONVERSION
A8: Public production cells | B8: 24 | C8: cells | D8: ZERO UNTIL SERIAL CONVERSION
A9: Campus roles | B9: 96 | C9: campuses | D9: ZERO UNTIL SERIAL CONVERSION
A10: Qualified industrial positions | B10: 199584 | C10: positions | D10: ZERO UNTIL SERIAL CONVERSION
A11: Annual supplier cold lots | B11: 1152 | C11: lots | D11: ZERO UNTIL SERIAL CONVERSION
A12: Domestic useful-output market | B12: 75 | C12: USD B/year | D12: ZERO UNTIL SERIAL CONVERSION

Sheet Formation System
A2: Formation-generation output circuit
A4: People, articles, receivers and evidence bind to 5,251 serials.
A6: Metric | B6: Value | C6: Unit | D6: Authority
A7: Formation families | B7: 48 | C7: families | D7: SOURCE EMPTY / HOLD
A8: Owned formation serials | B8: 5251 | C8: formations | D8: SOURCE EMPTY / HOLD
A9: Direct affiliated billets | B9: 11465213 | C9: billets | D9: SOURCE EMPTY / HOLD
A10: Crew-set equivalents | B10: 15123.6 | C10: sets | D10: SOURCE EMPTY / HOLD

Sheet Readiness System
A2: Permanent readiness circuit
A4: Ready and regeneration accounts conserve the entire inventory.
A6: Account | B6: Formations | C6: Treatment
A7: Committed | B7: 2420 | C7: Ready and occupied
A8: Protected reserve | B8: 502 | C8: Ready; explicit activation
A9: Geographic buffer | B9: 745 | C9: Ready; N−1 assurance
A10: Requalification | B10: 514 | C10: Not ready
A11: Maintenance | B11: 527 | C11: Not ready
A12: Deep overhaul | B12: 543 | C12: Not ready
A13: Total | B13: 5251 | C13: Conserved

Sheet Allocation System
A2: Constitutional allocation circuit
A4: NMAC schedules only claims that preserve prior warrants and public rights.
A6: Metric | B6: Value | C6: Meaning
A7: Instantaneous ready floor | B7: 3667 | C7: formations
A8: Committed campaigns | B8: 2420 | C8: formations
A9: Protected reserve | B9: 502 | C9: formations
A10: Geographic buffer | B10: 745 | C10: formations
A11: Regeneration pool | B11: 1584 | C11: formations
A12: Family-campaign claims | B12: 480 | C12: claims
A13: Allocation seals | B13: 12 | C13: seals
A14: Released authority | B14: 0 | C14: formations

Sheet Fiscal Ledgers
A2: Three separate fiscal circuits
A4: The ledgers may be compared but not collapsed into one readiness total.
A6: Ledger | B6: 25-year / mature value | C6: Status | D6: What it cannot buy
A7: Technology and proving | B7: USD 1.00T finite | C7: Program authority | D7: Automatic procurement or readiness
A8: Mature force capital | B8: USD 17.4T screen | C8: Formation + common capital | D8: Evidence, acceptance or operations
A9: Mature annual operations | B9: USD 2.11T/year | C9: Steady-state screen | D9: New capital authority
A10: Domestic useful-output market | B10: USD 75.0B/year | C10: Separate market revenue | D10: Formation or reserve credit
A11: Reference partner market | B11: USD 12.0B/year | C11: Optional opportunity | D11: Domestic sovereignty or recall

Sheet 25-Year Resource Path
A2: Twenty-five-year resource-path model
A4: Operations ramp with built inventory; market revenue remains separate and partner sales optional.
A6: Year | B6: Built share | C6: Technology program USD B | D6: Formation capital USD B | E6: Common capital USD B | F6: Operations USD B | G6: Domestic market USD B | H6: Partner market USD B | I6: Mature capital USD B | J6: Operating economy USD B
A7: 1 | B7: 0.02 | C7: 88 | D7: 188.2112 | E7: 159.8 | F7: 42.2 | G7: 0 | H7: 0 | I7: 348.0112 | J7: 42.2
A8: 2 | B8: 0.05 | C8: 88 | D8: 282.3168 | E8: 239.7 | F8: 105.5 | G8: 0 | H8: 0 | I8: 522.0168 | J8: 105.5
A9: 3 | B9: 0.1 | C9: 88 | D9: 470.528 | E9: 399.5 | F9: 211 | G9: 0 | H9: 0 | I9: 870.028 | J9: 211
A10: 4 | B10: 0.18 | C10: 88 | D10: 752.8448 | E10: 639.2 | F10: 379.8 | G10: 0 | H10: 0 | I10: 1392.0448 | J10: 379.8
A11: 5 | B11: 0.28 | C11: 88 | D11: 941.056 | E11: 799 | F11: 590.8 | G11: 0 | H11: 0 | I11: 1740.056 | J11: 590.8
A12: 6 | B12: 0.4 | C12: 88 | D12: 1129.2672 | E12: 958.8 | F12: 844 | G12: 0 | H12: 0 | I12: 2088.0672 | J12: 844
A13: 7 | B13: 0.54 | C13: 88 | D13: 1317.4784 | E13: 1118.6 | F13: 1139.4 | G13: 0 | H13: 0 | I13: 2436.0784 | J13: 1139.4
A14: 8 | B14: 0.7 | C14: 88 | D14: 1505.6896 | E14: 1278.4 | F14: 1477 | G14: 0 | H14: 0 | I14: 2784.0896 | J14: 1477
A15: 9 | B15: 0.84 | C15: 88 | D15: 1317.4784 | E15: 1118.6 | F15: 1772.4 | G15: 0 | H15: 0 | I15: 2436.0784 | J15: 1772.4
A16: 10 | B16: 0.94 | C16: 88 | D16: 941.056 | E16: 799 | F16: 1983.4 | G16: 0 | H16: 0 | I16: 1740.056 | J16: 1983.4
A17: 11 | B17: 1 | C17: 8 | D17: 564.6336 | E17: 479.4 | F17: 2110 | G17: 75 | H17: 12 | I17: 1044.0336 | J17: 2197
A18: 12 | B18: 1 | C18: 8 | D18: 0 | E18: 0 | F18: 2110 | G18: 75 | H18: 12 | I18: 0 | J18: 2197
... A31: 25 | B31: 1 | C31: 8 | D31: 0 | E31: 0 | F31: 2110 | G31: 75 | H31: 12 | I31: 0 | J31: 2197

Sheet Operating Economy
A2: Mature force and productive economy
A4: Market activity sustains industry but remains outside the readiness ledger.
A6: Measure | B6: Annual USD B | C6: 15-year USD B | D6: 25-year equivalent USD B | E6: Treatment
A7: Mature operations | B7: 2110 | C7: — | D7: 52750 | E7: Force operating screen
A8: Domestic useful output | B8: 75 | C8: 1125 | D8: — | E8: Separate sales
A9: Reference partner output | B9: 12 | C9: 180 | D9: — | E9: Optional sales
A10: Availability program | B10: 8 | C10: 120 | D10: — | E10: Inside USD 1.00T program
A11: Command-and-truth reference | B11: 21.1 | C11: — | D11: 527.5 | E11: Inside operations

Sheet Failure and Rollback
A2: Cross-circuit failure law
A4: A failure returns only the affected object to its last valid state and preserves history.
A6: Failure | B6: Rollback | C6: Receiver | D6: Unchanged authority
A7: Root insolvency | B7: Production availability to alternate route | C7: Continuity receiver | D7: Adverse evidence
A8: Cold-lot failure | B8: Reproducibility to HOLD | C8: Industrial Mobilization Administration | D8: Public need
A9: Formation trial failure | B9: Serial to technical/formation release | C9: Operating service | D9: Unrelated serials
A10: Reservation collision | B10: Both claims to zero | C10: Joint Capacity Authority | D10: Civil priority
A11: Receiver withdrawal | B11: Allocation to claim recompilation | C11: NMAC | D11: Evidence history
A12: International release dispute | B12: Custody remains committed | C12: International Custody Chamber | D12: No domestic recall
A13: Regeneration failure | B13: Serial remains non-ready | C13: Strategic Sustainment Command | D13: Family floor shrinks publicly
A14: Rights violation | B14: Execution seal revoked | C14: Rights and Scarcity Tribunal | D14: No urgency waiver

Sheet Innovation
A2: Technology program for the compact
A4: The compact must be executable, adversarially testable and publicly reconstructable.
A6: Program | B6: Technology | C6: Capability
A7: I01 | B7: Executable constitutional twin | C7: Represent institutions, warrants, clocks, collisions and rollback as one inspectable state
A8: I02 | B8: Cross-circuit provenance fabric | C8: Trace public need through mechanism, article, formation, campaign and regeneration
A9: I03 | B9: Sovereign offline scheduler | C9: Operate allocation and custody after national communications partition
A10: I04 | B10: Public causal evidence bank | C10: Preserve positive, adverse and invalid evidence across firms and generations
A11: I05 | B11: Adaptive family-floor governor | C11: Recompute non-substitutable readiness after hazard, labor and district loss
A12: I06 | B12: Cold-regeneration orchestration | C12: Move exact configuration, tools, people and suppliers across public/private routes
A13: I07 | B13: Receiver federation | C13: Make civil endpoints active members of force generation rather than mission afterthoughts
A14: I08 | B14: Rights-preserving population state | C14: Measure service deficit without converting vulnerability into surveillance
A15: I09 | B15: Partner-sovereign replication kit | C15: Export complete capability without remote operational dependence
A16: I10 | B16: Industrial-demobilization compiler | C16: Move capacity into useful civil output without destroying mobilization paths
A17: I11 | B17: Adversarial institutional range | C17: Test authority capture, collision, insolvency and evidence suppression at full scale
A18: I12 | B18: Machine-readable public compact | C18: Let outsiders reproduce why money, readiness and service claims did or did not advance

Sheet Return Map
A2: Five-pass DFG return
A4: Each pass closes one Department-scale conversion and hands a bounded result upward.
A6: Pass | B6: Object | C6: Established | D6: Returned constraint
A7: 191 | B7: DFG-1 conversion | C7: Five states, ten formation warrants, 5,251 serials | D7: Industry is not force
A8: 192 | B8: DFG-2 build | C8: 336 seeds, 528 family-year cohorts, eleven-year build | D8: Balanced generation before scale
A9: 193 | B9: DFG-3 readiness | C9: Six accounts and 3,667 ready floor | D9: Rotation cannot consume promise
A10: 194 | B10: DFG-4 allocation | C10: Ten authorities, seven layers, twelve seals | D10: Aggregate reserve is not complete service
A11: 195 | B11: DFG-5 compact | C11: Five circuits, fifteen institutions, twelve firebreaks | D11: Return to mature-force architecture

Sheet Audit
A2: Terminal audit
A4: One-way checks never issue authority.
A6: Audit | B6: Expected | C6: Observed | D6: Result
A7: Circuits | B7: 5 | C7: =COUNTA('Five-Circuit Compact'!A7:A11) -> 5 | D7: =IF(ABS(B7-C7)<0.01,"PASS","FAIL") -> PASS
A8: Institutions | B8: 15 | C8: =COUNTA('Institution Map'!A7:A21) -> 15 | D8: =IF(ABS(B8-C8)<0.01,"PASS","FAIL") -> PASS
A9: Transitions | B9: 10 | C9: =COUNTA('State Transitions'!A7:A16) -> 10 | D9: =IF(ABS(B9-C9)<0.01,"PASS","FAIL") -> PASS
A10: Firebreaks | B10: 12 | C10: =COUNTA('Nonconversion Laws'!A7:A18) -> 12 | D10: =IF(ABS(B10-C10)<0.01,"PASS","FAIL") -> PASS
A11: Capital reconciliation | B11: 17400 | C11: =Controls!B10 -> 17400 | D11: =IF(ABS(B11-C11)<0.01,"PASS","FAIL") -> PASS
A12: Formation + common capital | B12: 17400 | C12: =Controls!B8+Controls!B9 -> 17400 | D12: =IF(ABS(B12-C12)<0.01,"PASS","FAIL") -> PASS
A13: Owned inventory | B13: 5251 | C13: ='Readiness System'!B13 -> 5251 | D13: =IF(ABS(B13-C13)<0.01,"PASS","FAIL") -> PASS
A14: Ready floor | B14: 3667 | C14: =SUM('Readiness System'!B7:B9) -> 3667 | D14: =IF(ABS(B14-C14)<0.01,"PASS","FAIL") -> PASS
A15: Regeneration | B15: 1584 | C15: =SUM('Readiness System'!B10:B12) -> 1584 | D15: =IF(ABS(B15-C15)<0.01,"PASS","FAIL") -> PASS
A16: Return passes | B16: 5 | C16: =COUNTA('Return Map'!A7:A11) -> 5 | D16: =IF(ABS(B16-C16)<0.01,"PASS","FAIL") -> PASS
A17: Program authority | B17: 1000 | C17: =SUM('25-Year Resource Path'!C7:C31) -> 1000 | D17: =IF(ABS(B17-C17)<0.01,"PASS","FAIL") -> PASS
A18: Released authority | B18: 0 | C18: =Controls!B18 -> 0 | D18: =IF(ABS(B18-C18)<0.01,"PASS","FAIL") -> PASS

Sheet Mutation Tests
A2: Restored mutation tests
A4: Four compact controls fail their terminal audit and restore.
A6: Test | B6: Control | C6: Baseline | D6: Mutation | E6: Mutated | F6: Restored
A7: M1 | B7: Technology program | C7: 1000 | D7: 1001 | E7: FAIL | F7: PASS
A8: M2 | B8: Formation capital | C8: 9410.56 | D8: 9411.56 | E8: FAIL | F8: PASS
A9: M3 | B9: Owned formations | C9: 5251 | D9: 5252 | E9: FAIL | F9: PASS
A10: M4 | B10: Released authority | C10: 0 | D10: 1 | E10: FAIL | F10: PASS

Sheet Sources
A2: Internal source lineage
A4: No external sites or datasets are introduced.
A6: Pass | B6: Artifact | C6: Claims integrated
A7: 190 | B7: department-of-resilience-productive-commonwealth-sustaining-economy-and-return.md | C7: Industrial availability, labor, suppliers and market
A8: 191 | B8: department-of-resilience-formation-and-joint-readiness-conversion-constitution.md | C8: Five states and ten formation warrants
A9: 192 | B9: department-of-resilience-synchronized-formation-generation-campaign.md | C9: National build and regeneration campaign
A10: 193 | B10: department-of-resilience-permanent-readiness-cycle-constitution.md | C10: Six readiness accounts and family floors
A11: 194 | B11: department-of-resilience-national-mobilization-and-allocation-command.md | C11: Constitutional allocation and scarcity law

Sheet Read Me
A2: Model use and limits
A4: This workbook integrates the force-generation constitution and returns the branch; it issues no real authority.
A6: Topic | B6: Guidance
A7: Purpose | B7: Join industrial availability, formation generation, readiness, allocation, employment and regeneration without one super-command.
A8: Architecture | B8: Five circuits and fifteen institution classes exchange bounded artifacts through ten state transitions.
A9: Firebreaks | B9: Twelve forbidden conversions prevent money, factories, equipment, aggregate slack or urgency from creating force.
A10: Fiscal | B10: Technology, mature capital, operations and market revenue remain separate ledgers.
A11: 25-year path | B11: Operations ramp linearly with built share; this is a transparent planning hypothesis, not a budget estimate.
A12: Authority | B12: All implementation identities and released authority remain zero.
A13: Return | B13: DFG ends at five passes and returns to mature Department architecture.
A14: Rendering | B14: No exterior form is authorized by this compact.
A15: Next | B15: Select the next Department-level architecture question now that force generation is coherent.
